Workbook

Sheet はじめに
B2: シン・コンセ発注ツール（刷新版・計算エンジン）
D5: このブックの位置づけ
D6: 現行版の業務ロジックを踏襲したまま、データの持ち方を作り直したものです。
D7: 受入条件である 理論残／購買率／使用見込／必要数／発注目安 の5項目を算出します。
D8: 分納スケジュール（冷凍・飲料）と3区分の出力シートは次の段階で載せます。
D10: 週次の流れ
C11: TOP | D11: 自劇場・発注日・参照購買率・調整値・実動員を入れる
C12: ①在庫CSV_発注日 | D12: 発注日時点の理論在庫CSVを貼る
C13: ②〜④実績CSV | D13: 期間A／B／Cの実績CSVを貼る（購買率の元）
C14: ⑤減算マスタCSV | D14: イールド（販売商品→在庫商品の減算定義）を貼る
C15: ⑥商品照会CSV | D15: 発注ロット・仕入単価・パック入り数を貼る
C16: ⑦動員計画 | D16: 発注日からの日別動員見込みを入れる
C17: 取込チェック | D17: 貼付の抜けや型ずれが無いか確認する ★まずここ
C18: ⑧発注計算 | D18: 発注目安を見て発注数を決める ★ここで発注
D20: 算出式（現行踏襲）
D21: 調整後動員 ＝ 期間合計動員 × 動員見込み調整値
D22: 購買率 ＝ M換算販売数 ÷ 実動員 （S=0.88 / M=1 / L=1.66）
D23: 算出購買率 ＝ その在庫商品を減らす販売商品の購買率の合計
D24: 販売数見込 ＝ 調整後動員 × 算出購買率
D25: 使用見込 ＝ ROUNDUP(販売数見込 ÷ イールド, 0)
D26: 実在庫換算 ＝ カウント数 × パック入り数
D27: 必要数 ＝ (ストック設定 ＋ 使用見込) − 理論在庫（設定が「実数」なら実在庫換算）
D28: 発注目安 ＝ ROUNDUP(必要数 ÷ 発注ロット, 0) ※0以下は空欄
D30: 現行版から変えたところ
D31: ・商品マスタの ##1〜##150（323列の横持ち）を、減算マスタの縦持ちに転換しました。
D32: 商品が増えても列を足す必要がなくなり、紐付けの追加はCSVの行追加だけで済みます。
... D42: ・分納の11日は可変にしてありますが、配送サイクル固定かどうかの確認が要ります。

Sheet TOP
B2: TOP（設定）
B3: 黄色のセルを入力・選択してください。
B5: 自劇場コード | C5: 0761 | D5: 劇場マスタから選びます。CSVの劇場コードと一致させてください。
B6: 劇場名 | C6: =IFERROR(INDEX(劇場マスタ!$C$6:$C$105,MATCH($C$5,劇場マスタ!$B$6:$B$105,0)),"") -> 新宿 | D6: 劇場マスタから自動取得します。
B7: 劇場タイプ | C7: =IFERROR(INDEX(劇場マスタ!$D$6:$D$105,MATCH($C$5,劇場マスタ!$B$6:$B$105,0)),"") -> 通常劇場 | D7: ポップコーン豆の商品コードを切り替えます（通常劇場／前田農産／ライスト）。
B8: 発注日 | D8: 発注する日です。動員計画の起点になります。
B9: 分納日数 | C9: 11 | D9: 冷凍品・飲料品の分納スケジュールの日数です（現行は11日固定）。
B10: 参照購買率 | C10: 【期間A】 | D10: 購買率をどの期間の実績から取るかを選びます。
B11: 動員見込み調整値 | C11: 1.2 | D11: 日別動員見込みに掛ける係数です（現行の既定は120%）。
B12: 【期間A】実動員 | D12: 予算実績管理表の 有料＋無料 の合計です。
B13: 【期間B】実動員 | D13: 同上。
B14: 【期間C】実動員 | D14: 同上。
B15: 期間合計動員 | C15: =SUM(⑦動員計画!$D$8:$D$28) -> 0 | D15: 動員計画の日別見込みの合計です（調整値を掛ける前）。
B16: 調整後動員 | C16: =ROUND($C$15*$C$11,0) -> 0 | D16: すべての発注計算の需要ドライバです（期間合計動員 × 調整値）。
B17: 発注担当者 | D17: 発注書に記載されます。
B19: ポップコーン豆の商品コード（劇場タイプ別）
B20: 通常劇場 | C20: 1812000007106
B21: 前田農産 | C21: 1812000011561
B22: ライスト | C22: 1812000011387
B24: 採用する豆の商品コード | C24: =IFERROR(INDEX($C$20:$C$22,MATCH($C$7,$B$20:$B$22,0)),"") -> 1812000007106

Sheet ①在庫CSV_発注日
A1: タイトル | B1: 劇場コード | C1: 劇場名 | D1: 対象期間開始 | E1: 対象期間終了 | F1: 大分類コード | G1: 小分類コード | H1: 分類名 | I1: 作品コード | J1: 作品名 | K1: 支払先コード | L1: 支払先名 | M1: 商品コード | N1: 商品名 | O1: 買取区分 | P1: 買取区分名 | Q1: 前日残数 | R1: 仕入数 | S1: 移動入庫数 | T1: 返品数 | U1: 廃棄数 | V1: 移動出庫数 | W1: 差異数 | X1: 資産廃棄数 | Y1: 減算数 | Z1: 残数（理論在庫） | AA1: 売上数（販売数） | AB1: 売上金額 | AC1: 売上原価 | AD1: 仕入先商品コード
B2: ①在庫CSV（発注日）
B3: 発注日時点の理論在庫です。Z列（残数）が理論在庫になります。 データ行を A2 セルから貼り付けてください（見出し行は不要です）。

Sheet ②実績CSV_期間A
A1: タイトル | B1: 劇場コード | C1: 劇場名 | D1: 対象期間開始 | E1: 対象期間終了 | F1: 大分類コード | G1: 小分類コード | H1: 分類名 | I1: 作品コード | J1: 作品名 | K1: 支払先コード | L1: 支払先名 | M1: 商品コード | N1: 商品名 | O1: 買取区分 | P1: 買取区分名 | Q1: 前日残数 | R1: 仕入数 | S1: 移動入庫数 | T1: 返品数 | U1: 廃棄数 | V1: 移動出庫数 | W1: 差異数 | X1: 資産廃棄数 | Y1: 減算数 | Z1: 残数（理論在庫） | AA1: 売上数（販売数） | AB1: 売上金額 | AC1: 売上原価 | AD1: 仕入先商品コード
B2: ②実績CSV（期間A）
B3: 購買率を出すための販売実績です。 データ行を A2 セルから貼り付けてください（見出し行は不要です）。

Sheet ③実績CSV_期間B
A1: タイトル | B1: 劇場コード | C1: 劇場名 | D1: 対象期間開始 | E1: 対象期間終了 | F1: 大分類コード | G1: 小分類コード | H1: 分類名 | I1: 作品コード | J1: 作品名 | K1: 支払先コード | L1: 支払先名 | M1: 商品コード | N1: 商品名 | O1: 買取区分 | P1: 買取区分名 | Q1: 前日残数 | R1: 仕入数 | S1: 移動入庫数 | T1: 返品数 | U1: 廃棄数 | V1: 移動出庫数 | W1: 差異数 | X1: 資産廃棄数 | Y1: 減算数 | Z1: 残数（理論在庫） | AA1: 売上数（販売数） | AB1: 売上金額 | AC1: 売上原価 | AD1: 仕入先商品コード
B2: ③実績CSV（期間B）
B3: 同上。 データ行を A2 セルから貼り付けてください（見出し行は不要です）。

Sheet ④実績CSV_期間C
A1: タイトル | B1: 劇場コード | C1: 劇場名 | D1: 対象期間開始 | E1: 対象期間終了 | F1: 大分類コード | G1: 小分類コード | H1: 分類名 | I1: 作品コード | J1: 作品名 | K1: 支払先コード | L1: 支払先名 | M1: 商品コード | N1: 商品名 | O1: 買取区分 | P1: 買取区分名 | Q1: 前日残数 | R1: 仕入数 | S1: 移動入庫数 | T1: 返品数 | U1: 廃棄数 | V1: 移動出庫数 | W1: 差異数 | X1: 資産廃棄数 | Y1: 減算数 | Z1: 残数（理論在庫） | AA1: 売上数（販売数） | AB1: 売上金額 | AC1: 売上原価 | AD1: 仕入先商品コード
B2: ④実績CSV（期間C）
B3: 同上。 データ行を A2 セルから貼り付けてください（見出し行は不要です）。

Sheet ⑤減算マスタCSV
A1: 販売商品コード | B1: 販売商品名 | C1: 適用開始日 | D1: 劇場コード | E1: 劇場名 | F1: 減算商品コード | G1: 減算商品名 | H1: 必要販売数量（イールド） | I1: 使用量 | K1: 適用 | L1: 販売商品の購買率
B2: ⑤減算マスタCSV（イールド） | K2: =IF($A2="",0,IF(OR(N($D2)=0,$D2&""=TOP!$C$5&""),1,0)) -> 0 | L2: =IF($K2=0,0,IFERROR(INDEX(購買率算出!$P$6:$P$3005,MATCH($A2&"",購買率算出!$C$6:$C$3005,0)),0)) -> 0
B3: HELLO『在庫減算マスタ一覧』のデータ行を A2 セルから貼り付けてください。販売商品1つが、どの在庫商品をいくつ減らすかの定義です。 | K3: =IF($A3="",0,IF(OR(N($D3)=0,$D3&""=TOP!$C$5&""),1,0)) -> 0 | L3: =IF($K3=0,0,IFERROR(INDEX(購買率算出!$P$6:$P$3005,MATCH($A3&"",購買率算出!$C$6:$C$3005,0)),0)) -> 0
K4: =IF($A4="",0,IF(OR(N($D4)=0,$D4&""=TOP!$C$5&""),1,0)) -> 0 | L4: =IF($K4=0,0,IFERROR(INDEX(購買率算出!$P$6:$P$3005,MATCH($A4&"",購買率算出!$C$6:$C$3005,0)),0)) -> 0
K5: =IF($A5="",0,IF(OR(N($D5)=0,$D5&""=TOP!$C$5&""),1,0)) -> 0 | L5: =IF($K5=0,0,IFERROR(INDEX(購買率算出!$P$6:$P$3005,MATCH($A5&"",購買率算出!$C$6:$C$3005,0)),0)) -> 0
K6: =IF($A6="",0,IF(OR(N($D6)=0,$D6&""=TOP!$C$5&""),1,0)) -> 0 | L6: =IF($K6=0,0,IFERROR(INDEX(購買率算出!$P$6:$P$3005,MATCH($A6&"",購買率算出!$C$6:$C$3005,0)),0)) -> 0
K7: =IF($A7="",0,IF(OR(N($D7)=0,$D7&""=TOP!$C$5&""),1,0)) -> 0 | L7: =IF($K7=0,0,IFERROR(INDEX(購買率算出!$P$6:$P$3005,MATCH($A7&"",購買率算出!$C$6:$C$3005,0)),0)) -> 0
K8: =IF($A8="",0,IF(OR(N($D8)=0,$D8&""=TOP!$C$5&""),1,0)) -> 0 | L8: =IF($K8=0,0,IFERROR(INDEX(購買率算出!$P$6:$P$3005,MATCH($A8&"",購買率算出!$C$6:$C$3005,0)),0)) -> 0
K9: =IF($A9="",0,IF(OR(N($D9)=0,$D9&""=TOP!$C$5&""),1,0)) -> 0 | L9: =IF($K9=0,0,IFERROR(INDEX(購買率算出!$P$6:$P$3005,MATCH($A9&"",購買率算出!$C$6:$C$3005,0)),0)) -> 0
K10: =IF($A10="",0,IF(OR(N($D10)=0,$D10&""=TOP!$C$5&""),1,0)) -> 0 | L10: =IF($K10=0,0,IFERROR(INDEX(購買率算出!$P$6:$P$3005,MATCH($A10&"",購買率算出!$C$6:$C$3005,0)),0)) -> 0
K11: =IF($A11="",0,IF(OR(N($D11)=0,$D11&""=TOP!$C$5&""),1,0)) -> 0 | L11: =IF($K11=0,0,IFERROR(INDEX(購買率算出!$P$6:$P$3005,MATCH($A11&"",購買率算出!$C$6:$C$3005,0)),0)) -> 0
K12: =IF($A12="",0,IF(OR(N($D12)=0,$D12&""=TOP!$C$5&""),1,0)) -> 0 | L12: =IF($K12=0,0,IFERROR(INDEX(購買率算出!$P$6:$P$3005,MATCH($A12&"",購買率算出!$C$6:$C$3005,0)),0)) -> 0
K13: =IF($A13="",0,IF(OR(N($D13)=0,$D13&""=TOP!$C$5&""),1,0)) -> 0 | L13: =IF($K13=0,0,IFERROR(INDEX(購買率算出!$P$6:$P$3005,MATCH($A13&"",購買率算出!$C$6:$C$3005,0)),0)) -> 0
K14: =IF($A14="",0,IF(OR(N($D14)=0,$D14&""=TOP!$C$5&""),1,0)) -> 0 | L14: =IF($K14=0,0,IFERROR(INDEX(購買率算出!$P$6:$P$3005,MATCH($A14&"",購買率算出!$C$6:$C$3005,0)),0)) -> 0
K15: =IF($A15="",0,IF(OR(N($D15)=0,$D15&""=TOP!$C$5&""),1,0)) -> 0 | L15: =IF($K15=0,0,IFERROR(INDEX(購買率算出!$P$6:$P$3005,MATCH($A15&"",購買率算出!$C$6:$C$3005,0)),0)) -> 0
... K8001: =IF($A8001="",0,IF(OR(N($D8001)=0,$D8001&""=TOP!$C$5&""),1,0)) -> 0 | L8001: =IF($K8001=0,0,IFERROR(INDEX(購買率算出!$P$6:$P$3005,MATCH($A8001&"",購買率算出!$C$6:$C$3005,0)),0)) -> 0

Sheet ⑥商品照会CSV
A1: SYOUHIN_CD | B1: （予備） | C1: SYOUHIN_NM | M1: IRISU（発注ロット） | Q1: SIIRE_TANKA | S1: TORIATUKAI_KBN | AK1: IRISU_PACK | AL1: TANAOROSI_CASE | AM1: TANAOROSI_PACK | AN1: TANAOROSI_BARA
B2: ⑥商品照会CSV
B3: HELLO『商品一覧照会』のデータ行を A2 セルから貼り付けてください。発注ロット・仕入単価・パック入り数の出どころです。

Sheet ⑦動員計画
B2: ⑦動員計画
B3: 発注日からの日別動員見込みです。ここが来場者予測の唯一の入力場所です。
B6: 自動 | C6: 自動 | D6: 入力 | E6: 入力 | F6: 自動
B7: 日付 | C7: 曜日 | D7: 日別動員見込み | E7: 主な作品・備考 | F7: 調整後動員
B8: =IF(TOP!$C$8="","",IF(0<TOP!$C$9,TOP!$C$8+0,"")) | C8: =IF($B8="","",CHOOSE(WEEKDAY($B8),"日","月","火","水","木","金","土")) | F8: =IF($B8="","",ROUND(N($D8)*N(TOP!$C$11),0))
B9: =IF(TOP!$C$8="","",IF(1<TOP!$C$9,TOP!$C$8+1,"")) | C9: =IF($B9="","",CHOOSE(WEEKDAY($B9),"日","月","火","水","木","金","土")) | F9: =IF($B9="","",ROUND(N($D9)*N(TOP!$C$11),0))
B10: =IF(TOP!$C$8="","",IF(2<TOP!$C$9,TOP!$C$8+2,"")) | C10: =IF($B10="","",CHOOSE(WEEKDAY($B10),"日","月","火","水","木","金","土")) | F10: =IF($B10="","",ROUND(N($D10)*N(TOP!$C$11),0))
B11: =IF(TOP!$C$8="","",IF(3<TOP!$C$9,TOP!$C$8+3,"")) | C11: =IF($B11="","",CHOOSE(WEEKDAY($B11),"日","月","火","水","木","金","土")) | F11: =IF($B11="","",ROUND(N($D11)*N(TOP!$C$11),0))
B12: =IF(TOP!$C$8="","",IF(4<TOP!$C$9,TOP!$C$8+4,"")) | C12: =IF($B12="","",CHOOSE(WEEKDAY($B12),"日","月","火","水","木","金","土")) | F12: =IF($B12="","",ROUND(N($D12)*N(TOP!$C$11),0))
B13: =IF(TOP!$C$8="","",IF(5<TOP!$C$9,TOP!$C$8+5,"")) | C13: =IF($B13="","",CHOOSE(WEEKDAY($B13),"日","月","火","水","木","金","土")) | F13: =IF($B13="","",ROUND(N($D13)*N(TOP!$C$11),0))
B14: =IF(TOP!$C$8="","",IF(6<TOP!$C$9,TOP!$C$8+6,"")) | C14: =IF($B14="","",CHOOSE(WEEKDAY($B14),"日","月","火","水","木","金","土")) | F14: =IF($B14="","",ROUND(N($D14)*N(TOP!$C$11),0))
B15: =IF(TOP!$C$8="","",IF(7<TOP!$C$9,TOP!$C$8+7,"")) | C15: =IF($B15="","",CHOOSE(WEEKDAY($B15),"日","月","火","水","木","金","土")) | F15: =IF($B15="","",ROUND(N($D15)*N(TOP!$C$11),0))
B16: =IF(TOP!$C$8="","",IF(8<TOP!$C$9,TOP!$C$8+8,"")) | C16: =IF($B16="","",CHOOSE(WEEKDAY($B16),"日","月","火","水","木","金","土")) | F16: =IF($B16="","",ROUND(N($D16)*N(TOP!$C$11),0))
B17: =IF(TOP!$C$8="","",IF(9<TOP!$C$9,TOP!$C$8+9,"")) | C17: =IF($B17="","",CHOOSE(WEEKDAY($B17),"日","月","火","水","木","金","土")) | F17: =IF($B17="","",ROUND(N($D17)*N(TOP!$C$11),0))
B18: =IF(TOP!$C$8="","",IF(10<TOP!$C$9,TOP!$C$8+10,"")) | C18: =IF($B18="","",CHOOSE(WEEKDAY($B18),"日","月","火","水","木","金","土")) | F18: =IF($B18="","",ROUND(N($D18)*N(TOP!$C$11),0))
B19: =IF(TOP!$C$8="","",IF(11<TOP!$C$9,TOP!$C$8+11,"")) | C19: =IF($B19="","",CHOOSE(WEEKDAY($B19),"日","月","火","水","木","金","土")) | F19: =IF($B19="","",ROUND(N($D19)*N(TOP!$C$11),0))
B20: =IF(TOP!$C$8="","",IF(12<TOP!$C$9,TOP!$C$8+12,"")) | C20: =IF($B20="","",CHOOSE(WEEKDAY($B20),"日","月","火","水","木","金","土")) | F20: =IF($B20="","",ROUND(N($D20)*N(TOP!$C$11),0))
B21: =IF(TOP!$C$8="","",IF(13<TOP!$C$9,TOP!$C$8+13,"")) | C21: =IF($B21="","",CHOOSE(WEEKDAY($B21),"日","月","火","水","木","金","土")) | F21: =IF($B21="","",ROUND(N($D21)*N(TOP!$C$11),0))
B22: =IF(TOP!$C$8="","",IF(14<TOP!$C$9,TOP!$C$8+14,"")) | C22: =IF($B22="","",CHOOSE(WEEKDAY($B22),"日","月","火","水","木","金","土")) | F22: =IF($B22="","",ROUND(N($D22)*N(TOP!$C$11),0))
B23: =IF(TOP!$C$8="","",IF(15<TOP!$C$9,TOP!$C$8+15,"")) | C23: =IF($B23="","",CHOOSE(WEEKDAY($B23),"日","月","火","水","木","金","土")) | F23: =IF($B23="","",ROUND(N($D23)*N(TOP!$C$11),0))
B24: =IF(TOP!$C$8="","",IF(16<TOP!$C$9,TOP!$C$8+16,"")) | C24: =IF($B24="","",CHOOSE(WEEKDAY($B24),"日","月","火","水","木","金","土")) | F24: =IF($B24="","",ROUND(N($D24)*N(TOP!$C$11),0))
B25: =IF(TOP!$C$8="","",IF(17<TOP!$C$9,TOP!$C$8+17,"")) | C25: =IF($B25="","",CHOOSE(WEEKDAY($B25),"日","月","火","水","木","金","土")) | F25: =IF($B25="","",ROUND(N($D25)*N(TOP!$C$11),0))
B26: =IF(TOP!$C$8="","",IF(18<TOP!$C$9,TOP!$C$8+18,"")) | C26: =IF($B26="","",CHOOSE(WEEKDAY($B26),"日","月","火","水","木","金","土")) | F26: =IF($B26="","",ROUND(N($D26)*N(TOP!$C$11),0))
B27: =IF(TOP!$C$8="","",IF(19<TOP!$C$9,TOP!$C$8+19,"")) | C27: =IF($B27="","",CHOOSE(WEEKDAY($B27),"日","月","火","水","木","金","土")) | F27: =IF($B27="","",ROUND(N($D27)*N(TOP!$C$11),0))
B28: =IF(TOP!$C$8="","",IF(20<TOP!$C$9,TOP!$C$8+20,"")) | C28: =IF($B28="","",CHOOSE(WEEKDAY($B28),"日","月","火","水","木","金","土")) | F28: =IF($B28="","",ROUND(N($D28)*N(TOP!$C$11),0))

Sheet 取込チェック
B2: 取込チェック
B3: CSVを貼り替えたら、まずここを見てください。想定と違う数字が出ていたら取込ミスです。
B4: 自動 | C4: 自動 | D4: 自動 | E4: 自動
B5: チェック項目 | C5: 結果 | D5: 判定 | E5: 意味
B6: ①在庫CSV 行数 | C6: =COUNTIF(①在庫CSV_発注日!$M$2:$M$5001,"?*") -> 0 | D6: =IF(N($C6)>0,"OK","要確認") -> 要確認 | E6: 0なら未貼付です。
B7: うち自劇場ぶん | C7: =COUNTIF(①在庫CSV_発注日!$B$2:$B$5001,TOP!$C$5) -> 0 | D7: =IF(N($C7)>0,"OK","要確認") -> 要確認 | E7: 0のままなら劇場コードの型がずれています（先頭ゼロの脱落）。
B8: ②実績CSV_期間A 行数 | C8: =COUNTIF(②実績CSV_期間A!$M$2:$M$5001,"?*") -> 0 | D8: =IF(N($C8)>0,"OK","要確認") -> 要確認 | E8: 購買率の元になります。
B9: ③実績CSV_期間B 行数 | C9: =COUNTIF(③実績CSV_期間B!$M$2:$M$5001,"?*") -> 0 | D9: =IF(N($C9)>0,"OK","要確認") -> 要確認 | E9: 期間B購買率を使う場合に必要です。
B10: ④実績CSV_期間C 行数 | C10: =COUNTIF(④実績CSV_期間C!$M$2:$M$5001,"?*") -> 0 | D10: =IF(N($C10)>0,"OK","要確認") -> 要確認 | E10: 期間C購買率を使う場合に必要です。
B11: ⑤減算マスタ 行数 | C11: =COUNTIF(⑤減算マスタCSV!$A$2:$A$8001,"?*") -> 0 | D11: =IF(N($C11)>0,"OK","要確認") -> 要確認 | E11: イールドの元です。0なら購買率が全て0になります。
B12: うち自劇場に適用 | C12: =SUM(⑤減算マスタCSV!$K$2:$K$8001) -> 0 | D12: =IF(N($C12)>0,"OK","要確認") -> 要確認 | E12: 劇場コード0（全劇場）と自劇場ぶんの合計です。
B13: ⑥商品照会CSV 行数 | C13: =COUNTIF(⑥商品照会CSV!$A$2:$A$3001,"?*") -> 0 | D13: =IF(N($C13)>0,"OK","要確認") -> 要確認 | E13: 発注ロット・単価・パック入り数の元です。
B14: 動員計画の入力日数 | C14: =COUNT(⑦動員計画!$D$8:$D$28) -> 0 | D14: =IF(N($C14)>0,"OK","要確認") -> 要確認 | E14: 分納日数ぶん入っているか確認してください。
B15: 調整後動員 | C15: =TOP!$C$16 -> 0 | D15: =IF(N($C15)>0,"OK","要確認") -> 要確認 | E15: すべての発注計算の需要ドライバです。
B16: 発注対象の商品数 | C16: =COUNTIF(⑧発注計算!$C$7:$C$3006,"?*") -> 0 | D16: =IF(N($C16)>0,"OK","要確認") -> 要確認 | E16: 発注計算シートの行数です。
B17: 購買率が0の商品 | C17: =COUNTIFS(⑧発注計算!$C$7:$C$3006,"?*",⑧発注計算!$K$7:$K$3006,0) -> 0 | D17: =IF(N($C17)=0,"OK","要確認") -> OK | E17: 減算マスタに紐付きが無い商品です。マスタ登録漏れの可能性があります。
B18: 発注ロットが1の商品 | C18: =COUNTIFS(⑧発注計算!$C$7:$C$3006,"?*",⑧発注計算!$Q$7:$Q$3006,1) -> 0 | D18: =IF(N($C18)=0,"OK","要確認") -> OK | E18: 商品照会CSVに無い商品です。既定値1で計算しています。
B19: 発注目安が出た商品 | C19: =COUNTIF(⑧発注計算!$R$7:$R$3006,">0") -> 0 | D19: =IF(N($C19)>0,"OK","要確認") -> 要確認 | E19: 今回の発注対象です。

Sheet ⑧発注計算
B2: ⑧発注計算
B3: 現行版の算出式をそのまま実装しています。黄色の「発注数」と「カウント数」だけが入力欄です。
B4: 販売数見込 ＝ 調整後動員 × 算出購買率 ／ 使用見込 ＝ ROUNDUP(販売数見込 ÷ イールド, 0) ／ 必要数 ＝ (ストック設定 ＋ 使用見込) − 在庫 ／ 発注目安 ＝ ROUNDUP(必要数 ÷ 発注ロット, 0)
B5: 自動 | C5: 自動 | D5: 自動 | E5: 自動 | F5: 自動 | G5: 自動 | H5: 入力 | I5: 自動 | J5: 自動 | K5: 自動 | L5: 自動 | M5: 自動 | N5: 自動 | O5: 自動 | P5: 自動 | Q5: 自動 | R5: 自動 | S5: 入力 | T5: 自動 | U5: 自動 | V5: 入力
B6: No | C6: 商品コード | D6: 商品名 | E6: 温度区分 | F6: 設定 | G6: 理論在庫 | H6: カウント数 | I6: 実在庫換算 | J6: 理論差 | K6: 算出購買率 | L6: イールド | M6: 販売数見込 | N6: 使用見込 | O6: ストック設定 | P6: 必要数 | Q6: 発注ロット | R6: 発注目安 | S6: 発注数 | T6: 発注単価 | U6: 金額 | V6: 備考
B7: 1 | C7: =IF(商品マスタ!$C6="","",商品マスタ!$C6) | D7: =IF($C7="","",商品マスタ!$D6) | E7: =IF($C7="","",商品マスタ!$G6) | F7: =IF($C7="","",IF(商品マスタ!$P6="","理論",商品マスタ!$P6)) | G7: =IF($C7="","",N(商品マスタ!$H6)) | I7: =IF($C7="","",N($H7)*N(商品マスタ!$N6)) | J7: =IF($C7="","",N($I7)-N($G7)) | K7: =IF($C7="","",N(商品マスタ!$I6)) | L7: =IF($C7="","",MAX(1,N(商品マスタ!$J6))) | M7: =IF($C7="","",N(TOP!$C$16)*N($K7)) | N7: =IF($C7="","",ROUNDUP(N($M7)/N($L7),0)) | O7: =IF($C7="","",N(商品マスタ!$R6)) | P7: =IF($C7="","",IF($F7="理論",(N($O7)+N($N7))-N($G7),(N($O7)+N($N7))-N($I7))) | Q7: =IF($C7="","",MAX(1,N(商品マスタ!$K6))) | R7: =IF($C7="","",IF(N($P7)/N($Q7)<=0,"",ROUNDUP(N($P7)/N($Q7),0))) | T7: =IF($C7="","",N(商品マスタ!$M6)) | U7: =IF($S7="","",N($S7)*N($T7))
B8: 2 | C8: =IF(商品マスタ!$C7="","",商品マスタ!$C7) | D8: =IF($C8="","",商品マスタ!$D7) | E8: =IF($C8="","",商品マスタ!$G7) | F8: =IF($C8="","",IF(商品マスタ!$P7="","理論",商品マスタ!$P7)) | G8: =IF($C8="","",N(商品マスタ!$H7)) | I8: =IF($C8="","",N($H8)*N(商品マスタ!$N7)) | J8: =IF($C8="","",N($I8)-N($G8)) | K8: =IF($C8="","",N(商品マスタ!$I7)) | L8: =IF($C8="","",MAX(1,N(商品マスタ!$J7))) | M8: =IF($C8="","",N(TOP!$C$16)*N($K8)) | N8: =IF($C8="","",ROUNDUP(N($M8)/N($L8),0)) | O8: =IF($C8="","",N(商品マスタ!$R7)) | P8: =IF($C8="","",IF($F8="理論",(N($O8)+N($N8))-N($G8),(N($O8)+N($N8))-N($I8))) | Q8: =IF($C8="","",MAX(1,N(商品マスタ!$K7))) | R8: =IF($C8="","",IF(N($P8)/N($Q8)<=0,"",ROUNDUP(N($P8)/N($Q8),0))) | T8: =IF($C8="","",N(商品マスタ!$M7)) | U8: =IF($S8="","",N($S8)*N($T8))
B9: 3 | C9: =IF(商品マスタ!$C8="","",商品マスタ!$C8) | D9: =IF($C9="","",商品マスタ!$D8) | E9: =IF($C9="","",商品マスタ!$G8) | F9: =IF($C9="","",IF(商品マスタ!$P8="","理論",商品マスタ!$P8)) | G9: =IF($C9="","",N(商品マスタ!$H8)) | I9: =IF($C9="","",N($H9)*N(商品マスタ!$N8)) | J9: =IF($C9="","",N($I9)-N($G9)) | K9: =IF($C9="","",N(商品マスタ!$I8)) | L9: =IF($C9="","",MAX(1,N(商品マスタ!$J8))) | M9: =IF($C9="","",N(TOP!$C$16)*N($K9)) | N9: =IF($C9="","",ROUNDUP(N($M9)/N($L9),0)) | O9: =IF($C9="","",N(商品マスタ!$R8)) | P9: =IF($C9="","",IF($F9="理論",(N($O9)+N($N9))-N($G9),(N($O9)+N($N9))-N($I9))) | Q9: =IF($C9="","",MAX(1,N(商品マスタ!$K8))) | R9: =IF($C9="","",IF(N($P9)/N($Q9)<=0,"",ROUNDUP(N($P9)/N($Q9),0))) | T9: =IF($C9="","",N(商品マスタ!$M8)) | U9: =IF($S9="","",N($S9)*N($T9))
B10: 4 | C10: =IF(商品マスタ!$C9="","",商品マスタ!$C9) | D10: =IF($C10="","",商品マスタ!$D9) | E10: =IF($C10="","",商品マスタ!$G9) | F10: =IF($C10="","",IF(商品マスタ!$P9="","理論",商品マスタ!$P9)) | G10: =IF($C10="","",N(商品マスタ!$H9)) | I10: =IF($C10="","",N($H10)*N(商品マスタ!$N9)) | J10: =IF($C10="","",N($I10)-N($G10)) | K10: =IF($C10="","",N(商品マスタ!$I9)) | L10: =IF($C10="","",MAX(1,N(商品マスタ!$J9))) | M10: =IF($C10="","",N(TOP!$C$16)*N($K10)) | N10: =IF($C10="","",ROUNDUP(N($M10)/N($L10),0)) | O10: =IF($C10="","",N(商品マスタ!$R9)) | P10: =IF($C10="","",IF($F10="理論",(N($O10)+N($N10))-N($G10),(N($O10)+N($N10))-N($I10))) | Q10: =IF($C10="","",MAX(1,N(商品マスタ!$K9))) | R10: =IF($C10="","",IF(N($P10)/N($Q10)<=0,"",ROUNDUP(N($P10)/N($Q10),0))) | T10: =IF($C10="","",N(商品マスタ!$M9)) | U10: =IF($S10="","",N($S10)*N($T10))
B11: 5 | C11: =IF(商品マスタ!$C10="","",商品マスタ!$C10) | D11: =IF($C11="","",商品マスタ!$D10) | E11: =IF($C11="","",商品マスタ!$G10) | F11: =IF($C11="","",IF(商品マスタ!$P10="","理論",商品マスタ!$P10)) | G11: =IF($C11="","",N(商品マスタ!$H10)) | I11: =IF($C11="","",N($H11)*N(商品マスタ!$N10)) | J11: =IF($C11="","",N($I11)-N($G11)) | K11: =IF($C11="","",N(商品マスタ!$I10)) | L11: =IF($C11="","",MAX(1,N(商品マスタ!$J10))) | M11: =IF($C11="","",N(TOP!$C$16)*N($K11)) | N11: =IF($C11="","",ROUNDUP(N($M11)/N($L11),0)) | O11: =IF($C11="","",N(商品マスタ!$R10)) | P11: =IF($C11="","",IF($F11="理論",(N($O11)+N($N11))-N($G11),(N($O11)+N($N11))-N($I11))) | Q11: =IF($C11="","",MAX(1,N(商品マスタ!$K10))) | R11: =IF($C11="","",IF(N($P11)/N($Q11)<=0,"",ROUNDUP(N($P11)/N($Q11),0))) | T11: =IF($C11="","",N(商品マスタ!$M10)) | U11: =IF($S11="","",N($S11)*N($T11))
B12: 6 | C12: =IF(商品マスタ!$C11="","",商品マスタ!$C11) | D12: =IF($C12="","",商品マスタ!$D11) | E12: =IF($C12="","",商品マスタ!$G11) | F12: =IF($C12="","",IF(商品マスタ!$P11="","理論",商品マスタ!$P11)) | G12: =IF($C12="","",N(商品マスタ!$H11)) | I12: =IF($C12="","",N($H12)*N(商品マスタ!$N11)) | J12: =IF($C12="","",N($I12)-N($G12)) | K12: =IF($C12="","",N(商品マスタ!$I11)) | L12: =IF($C12="","",MAX(1,N(商品マスタ!$J11))) | M12: =IF($C12="","",N(TOP!$C$16)*N($K12)) | N12: =IF($C12="","",ROUNDUP(N($M12)/N($L12),0)) | O12: =IF($C12="","",N(商品マスタ!$R11)) | P12: =IF($C12="","",IF($F12="理論",(N($O12)+N($N12))-N($G12),(N($O12)+N($N12))-N($I12))) | Q12: =IF($C12="","",MAX(1,N(商品マスタ!$K11))) | R12: =IF($C12="","",IF(N($P12)/N($Q12)<=0,"",ROUNDUP(N($P12)/N($Q12),0))) | T12: =IF($C12="","",N(商品マスタ!$M11)) | U12: =IF($S12="","",N($S12)*N($T12))
B13: 7 | C13: =IF(商品マスタ!$C12="","",商品マスタ!$C12) | D13: =IF($C13="","",商品マスタ!$D12) | E13: =IF($C13="","",商品マスタ!$G12) | F13: =IF($C13="","",IF(商品マスタ!$P12="","理論",商品マスタ!$P12)) | G13: =IF($C13="","",N(商品マスタ!$H12)) | I13: =IF($C13="","",N($H13)*N(商品マスタ!$N12)) | J13: =IF($C13="","",N($I13)-N($G13)) | K13: =IF($C13="","",N(商品マスタ!$I12)) | L13: =IF($C13="","",MAX(1,N(商品マスタ!$J12))) | M13: =IF($C13="","",N(TOP!$C$16)*N($K13)) | N13: =IF($C13="","",ROUNDUP(N($M13)/N($L13),0)) | O13: =IF($C13="","",N(商品マスタ!$R12)) | P13: =IF($C13="","",IF($F13="理論",(N($O13)+N($N13))-N($G13),(N($O13)+N($N13))-N($I13))) | Q13: =IF($C13="","",MAX(1,N(商品マスタ!$K12))) | R13: =IF($C13="","",IF(N($P13)/N($Q13)<=0,"",ROUNDUP(N($P13)/N($Q13),0))) | T13: =IF($C13="","",N(商品マスタ!$M12)) | U13: =IF($S13="","",N($S13)*N($T13))
B14: 8 | C14: =IF(商品マスタ!$C13="","",商品マスタ!$C13) | D14: =IF($C14="","",商品マスタ!$D13) | E14: =IF($C14="","",商品マスタ!$G13) | F14: =IF($C14="","",IF(商品マスタ!$P13="","理論",商品マスタ!$P13)) | G14: =IF($C14="","",N(商品マスタ!$H13)) | I14: =IF($C14="","",N($H14)*N(商品マスタ!$N13)) | J14: =IF($C14="","",N($I14)-N($G14)) | K14: =IF($C14="","",N(商品マスタ!$I13)) | L14: =IF($C14="","",MAX(1,N(商品マスタ!$J13))) | M14: =IF($C14="","",N(TOP!$C$16)*N($K14)) | N14: =IF($C14="","",ROUNDUP(N($M14)/N($L14),0)) | O14: =IF($C14="","",N(商品マスタ!$R13)) | P14: =IF($C14="","",IF($F14="理論",(N($O14)+N($N14))-N($G14),(N($O14)+N($N14))-N($I14))) | Q14: =IF($C14="","",MAX(1,N(商品マスタ!$K13))) | R14: =IF($C14="","",IF(N($P14)/N($Q14)<=0,"",ROUNDUP(N($P14)/N($Q14),0))) | T14: =IF($C14="","",N(商品マスタ!$M13)) | U14: =IF($S14="","",N($S14)*N($T14))
B15: 9 | C15: =IF(商品マスタ!$C14="","",商品マスタ!$C14) | D15: =IF($C15="","",商品マスタ!$D14) | E15: =IF($C15="","",商品マスタ!$G14) | F15: =IF($C15="","",IF(商品マスタ!$P14="","理論",商品マスタ!$P14)) | G15: =IF($C15="","",N(商品マスタ!$H14)) | I15: =IF($C15="","",N($H15)*N(商品マスタ!$N14)) | J15: =IF($C15="","",N($I15)-N($G15)) | K15: =IF($C15="","",N(商品マスタ!$I14)) | L15: =IF($C15="","",MAX(1,N(商品マスタ!$J14))) | M15: =IF($C15="","",N(TOP!$C$16)*N($K15)) | N15: =IF($C15="","",ROUNDUP(N($M15)/N($L15),0)) | O15: =IF($C15="","",N(商品マスタ!$R14)) | P15: =IF($C15="","",IF($F15="理論",(N($O15)+N($N15))-N($G15),(N($O15)+N($N15))-N($I15))) | Q15: =IF($C15="","",MAX(1,N(商品マスタ!$K14))) | R15: =IF($C15="","",IF(N($P15)/N($Q15)<=0,"",ROUNDUP(N($P15)/N($Q15),0))) | T15: =IF($C15="","",N(商品マスタ!$M14)) | U15: =IF($S15="","",N($S15)*N($T15))
B16: 10 | C16: =IF(商品マスタ!$C15="","",商品マスタ!$C15) | D16: =IF($C16="","",商品マスタ!$D15) | E16: =IF($C16="","",商品マスタ!$G15) | F16: =IF($C16="","",IF(商品マスタ!$P15="","理論",商品マスタ!$P15)) | G16: =IF($C16="","",N(商品マスタ!$H15)) | I16: =IF($C16="","",N($H16)*N(商品マスタ!$N15)) | J16: =IF($C16="","",N($I16)-N($G16)) | K16: =IF($C16="","",N(商品マスタ!$I15)) | L16: =IF($C16="","",MAX(1,N(商品マスタ!$J15))) | M16: =IF($C16="","",N(TOP!$C$16)*N($K16)) | N16: =IF($C16="","",ROUNDUP(N($M16)/N($L16),0)) | O16: =IF($C16="","",N(商品マスタ!$R15)) | P16: =IF($C16="","",IF($F16="理論",(N($O16)+N($N16))-N($G16),(N($O16)+N($N16))-N($I16))) | Q16: =IF($C16="","",MAX(1,N(商品マスタ!$K15))) | R16: =IF($C16="","",IF(N($P16)/N($Q16)<=0,"",ROUNDUP(N($P16)/N($Q16),0))) | T16: =IF($C16="","",N(商品マスタ!$M15)) | U16: =IF($S16="","",N($S16)*N($T16))
B17: 11 | C17: =IF(商品マスタ!$C16="","",商品マスタ!$C16) | D17: =IF($C17="","",商品マスタ!$D16) | E17: =IF($C17="","",商品マスタ!$G16) | F17: =IF($C17="","",IF(商品マスタ!$P16="","理論",商品マスタ!$P16)) | G17: =IF($C17="","",N(商品マスタ!$H16)) | I17: =IF($C17="","",N($H17)*N(商品マスタ!$N16)) | J17: =IF($C17="","",N($I17)-N($G17)) | K17: =IF($C17="","",N(商品マスタ!$I16)) | L17: =IF($C17="","",MAX(1,N(商品マスタ!$J16))) | M17: =IF($C17="","",N(TOP!$C$16)*N($K17)) | N17: =IF($C17="","",ROUNDUP(N($M17)/N($L17),0)) | O17: =IF($C17="","",N(商品マスタ!$R16)) | P17: =IF($C17="","",IF($F17="理論",(N($O17)+N($N17))-N($G17),(N($O17)+N($N17))-N($I17))) | Q17: =IF($C17="","",MAX(1,N(商品マスタ!$K16))) | R17: =IF($C17="","",IF(N($P17)/N($Q17)<=0,"",ROUNDUP(N($P17)/N($Q17),0))) | T17: =IF($C17="","",N(商品マスタ!$M16)) | U17: =IF($S17="","",N($S17)*N($T17))
B18: 12 | C18: =IF(商品マスタ!$C17="","",商品マスタ!$C17) | D18: =IF($C18="","",商品マスタ!$D17) | E18: =IF($C18="","",商品マスタ!$G17) | F18: =IF($C18="","",IF(商品マスタ!$P17="","理論",商品マスタ!$P17)) | G18: =IF($C18="","",N(商品マスタ!$H17)) | I18: =IF($C18="","",N($H18)*N(商品マスタ!$N17)) | J18: =IF($C18="","",N($I18)-N($G18)) | K18: =IF($C18="","",N(商品マスタ!$I17)) | L18: =IF($C18="","",MAX(1,N(商品マスタ!$J17))) | M18: =IF($C18="","",N(TOP!$C$16)*N($K18)) | N18: =IF($C18="","",ROUNDUP(N($M18)/N($L18),0)) | O18: =IF($C18="","",N(商品マスタ!$R17)) | P18: =IF($C18="","",IF($F18="理論",(N($O18)+N($N18))-N($G18),(N($O18)+N($N18))-N($I18))) | Q18: =IF($C18="","",MAX(1,N(商品マスタ!$K17))) | R18: =IF($C18="","",IF(N($P18)/N($Q18)<=0,"",ROUNDUP(N($P18)/N($Q18),0))) | T18: =IF($C18="","",N(商品マスタ!$M17)) | U18: =IF($S18="","",N($S18)*N($T18))
... B3006: 3000 | C3006: =IF(商品マスタ!$C3005="","",商品マスタ!$C3005) | D3006: =IF($C3006="","",商品マスタ!$D3005) | E3006: =IF($C3006="","",商品マスタ!$G3005) | F3006: =IF($C3006="","",IF(商品マスタ!$P3005="","理論",商品マスタ!$P3005)) | G3006: =IF($C3006="","",N(商品マスタ!$H3005)) | I3006: =IF($C3006="","",N($H3006)*N(商品マスタ!$N3005)) | J3006: =IF($C3006="","",N($I3006)-N($G3006)) | K3006: =IF($C3006="","",N(商品マスタ!$I3005)) | L3006: =IF($C3006="","",MAX(1,N(商品マスタ!$J3005))) | M3006: =IF($C3006="","",N(TOP!$C$16)*N($K3006)) | N3006: =IF($C3006="","",ROUNDUP(N($M3006)/N($L3006),0)) | O3006: =IF($C3006="","",N(商品マスタ!$R3005)) | P3006: =IF($C3006="","",IF($F3006="理論",(N($O3006)+N($N3006))-N($G3006),(N($O3006)+N($N3006))-N($I3006))) | Q3006: =IF($C3006="","",MAX(1,N(商品マスタ!$K3005))) | R3006: =IF($C3006="","",IF(N($P3006)/N($Q3006)<=0,"",ROUNDUP(N($P3006)/N($Q3006),0))) | T3006: =IF($C3006="","",N(商品マスタ!$M3005)) | U3006: =IF($S3006="","",N($S3006)*N($T3006))

Sheet 購買率算出
B2: 購買率算出
B3: 販売商品ごとの購買率です。期間A/B/Cの実績CSVと実動員から自動で出ます。
B4: 自動 | C4: 自動 | D4: 自動 | E4: 自動 | F4: 自動 | G4: 自動 | H4: 自動 | I4: 自動 | J4: 自動 | K4: 自動 | L4: 自動 | M4: 自動 | N4: 自動 | O4: 自動 | P4: 自動
B5: No | C5: 販売商品コード | D5: 販売商品名 | E5: サイズ | F5: 換算比率 | G5: 期間A 販売数 | H5: 期間B 販売数 | I5: 期間C 販売数 | J5: M換算A | K5: M換算B | L5: M換算C | M5: 購買率A | N5: 購買率B | O5: 購買率C | P5: 採用購買率
B6: 1 | C6: =IF(②実績CSV_期間A!$M2="","",②実績CSV_期間A!$M2&"") | D6: =IF($C6="","",②実績CSV_期間A!$N2) | E6: =IF($C6="","",RIGHT($D6,1)) | F6: =IF($C6="","",IFERROR(INDEX(サイズ換算マスタ!$C$6:$C$8,MATCH($E6,サイズ換算マスタ!$B$6:$B$8,0)),1)) | G6: =IF($C6="","",SUMIFS(②実績CSV_期間A!$AA$2:$AA$5001,②実績CSV_期間A!$M$2:$M$5001,$C6)) | H6: =IF($C6="","",SUMIFS(③実績CSV_期間B!$AA$2:$AA$5001,③実績CSV_期間B!$M$2:$M$5001,$C6)) | I6: =IF($C6="","",SUMIFS(④実績CSV_期間C!$AA$2:$AA$5001,④実績CSV_期間C!$M$2:$M$5001,$C6)) | J6: =IF($C6="","",N($F6)*N($G6)) | K6: =IF($C6="","",N($F6)*N($H6)) | L6: =IF($C6="","",N($F6)*N($I6)) | M6: =IF(OR($C6="",N(TOP!$C$12)=0),"",N($J6)/TOP!$C$12) | N6: =IF(OR($C6="",N(TOP!$C$13)=0),"",N($K6)/TOP!$C$13) | O6: =IF(OR($C6="",N(TOP!$C$14)=0),"",N($L6)/TOP!$C$14) | P6: =IF($C6="","",IFERROR(CHOOSE(MATCH(TOP!$C$10,{"【期間A】","【期間B】","【期間C】"},0),N($M6),N($N6),N($O6)),0))
B7: 2 | C7: =IF(②実績CSV_期間A!$M3="","",②実績CSV_期間A!$M3&"") | D7: =IF($C7="","",②実績CSV_期間A!$N3) | E7: =IF($C7="","",RIGHT($D7,1)) | F7: =IF($C7="","",IFERROR(INDEX(サイズ換算マスタ!$C$6:$C$8,MATCH($E7,サイズ換算マスタ!$B$6:$B$8,0)),1)) | G7: =IF($C7="","",SUMIFS(②実績CSV_期間A!$AA$2:$AA$5001,②実績CSV_期間A!$M$2:$M$5001,$C7)) | H7: =IF($C7="","",SUMIFS(③実績CSV_期間B!$AA$2:$AA$5001,③実績CSV_期間B!$M$2:$M$5001,$C7)) | I7: =IF($C7="","",SUMIFS(④実績CSV_期間C!$AA$2:$AA$5001,④実績CSV_期間C!$M$2:$M$5001,$C7)) | J7: =IF($C7="","",N($F7)*N($G7)) | K7: =IF($C7="","",N($F7)*N($H7)) | L7: =IF($C7="","",N($F7)*N($I7)) | M7: =IF(OR($C7="",N(TOP!$C$12)=0),"",N($J7)/TOP!$C$12) | N7: =IF(OR($C7="",N(TOP!$C$13)=0),"",N($K7)/TOP!$C$13) | O7: =IF(OR($C7="",N(TOP!$C$14)=0),"",N($L7)/TOP!$C$14) | P7: =IF($C7="","",IFERROR(CHOOSE(MATCH(TOP!$C$10,{"【期間A】","【期間B】","【期間C】"},0),N($M7),N($N7),N($O7)),0))
B8: 3 | C8: =IF(②実績CSV_期間A!$M4="","",②実績CSV_期間A!$M4&"") | D8: =IF($C8="","",②実績CSV_期間A!$N4) | E8: =IF($C8="","",RIGHT($D8,1)) | F8: =IF($C8="","",IFERROR(INDEX(サイズ換算マスタ!$C$6:$C$8,MATCH($E8,サイズ換算マスタ!$B$6:$B$8,0)),1)) | G8: =IF($C8="","",SUMIFS(②実績CSV_期間A!$AA$2:$AA$5001,②実績CSV_期間A!$M$2:$M$5001,$C8)) | H8: =IF($C8="","",SUMIFS(③実績CSV_期間B!$AA$2:$AA$5001,③実績CSV_期間B!$M$2:$M$5001,$C8)) | I8: =IF($C8="","",SUMIFS(④実績CSV_期間C!$AA$2:$AA$5001,④実績CSV_期間C!$M$2:$M$5001,$C8)) | J8: =IF($C8="","",N($F8)*N($G8)) | K8: =IF($C8="","",N($F8)*N($H8)) | L8: =IF($C8="","",N($F8)*N($I8)) | M8: =IF(OR($C8="",N(TOP!$C$12)=0),"",N($J8)/TOP!$C$12) | N8: =IF(OR($C8="",N(TOP!$C$13)=0),"",N($K8)/TOP!$C$13) | O8: =IF(OR($C8="",N(TOP!$C$14)=0),"",N($L8)/TOP!$C$14) | P8: =IF($C8="","",IFERROR(CHOOSE(MATCH(TOP!$C$10,{"【期間A】","【期間B】","【期間C】"},0),N($M8),N($N8),N($O8)),0))
B9: 4 | C9: =IF(②実績CSV_期間A!$M5="","",②実績CSV_期間A!$M5&"") | D9: =IF($C9="","",②実績CSV_期間A!$N5) | E9: =IF($C9="","",RIGHT($D9,1)) | F9: =IF($C9="","",IFERROR(INDEX(サイズ換算マスタ!$C$6:$C$8,MATCH($E9,サイズ換算マスタ!$B$6:$B$8,0)),1)) | G9: =IF($C9="","",SUMIFS(②実績CSV_期間A!$AA$2:$AA$5001,②実績CSV_期間A!$M$2:$M$5001,$C9)) | H9: =IF($C9="","",SUMIFS(③実績CSV_期間B!$AA$2:$AA$5001,③実績CSV_期間B!$M$2:$M$5001,$C9)) | I9: =IF($C9="","",SUMIFS(④実績CSV_期間C!$AA$2:$AA$5001,④実績CSV_期間C!$M$2:$M$5001,$C9)) | J9: =IF($C9="","",N($F9)*N($G9)) | K9: =IF($C9="","",N($F9)*N($H9)) | L9: =IF($C9="","",N($F9)*N($I9)) | M9: =IF(OR($C9="",N(TOP!$C$12)=0),"",N($J9)/TOP!$C$12) | N9: =IF(OR($C9="",N(TOP!$C$13)=0),"",N($K9)/TOP!$C$13) | O9: =IF(OR($C9="",N(TOP!$C$14)=0),"",N($L9)/TOP!$C$14) | P9: =IF($C9="","",IFERROR(CHOOSE(MATCH(TOP!$C$10,{"【期間A】","【期間B】","【期間C】"},0),N($M9),N($N9),N($O9)),0))
B10: 5 | C10: =IF(②実績CSV_期間A!$M6="","",②実績CSV_期間A!$M6&"") | D10: =IF($C10="","",②実績CSV_期間A!$N6) | E10: =IF($C10="","",RIGHT($D10,1)) | F10: =IF($C10="","",IFERROR(INDEX(サイズ換算マスタ!$C$6:$C$8,MATCH($E10,サイズ換算マスタ!$B$6:$B$8,0)),1)) | G10: =IF($C10="","",SUMIFS(②実績CSV_期間A!$AA$2:$AA$5001,②実績CSV_期間A!$M$2:$M$5001,$C10)) | H10: =IF($C10="","",SUMIFS(③実績CSV_期間B!$AA$2:$AA$5001,③実績CSV_期間B!$M$2:$M$5001,$C10)) | I10: =IF($C10="","",SUMIFS(④実績CSV_期間C!$AA$2:$AA$5001,④実績CSV_期間C!$M$2:$M$5001,$C10)) | J10: =IF($C10="","",N($F10)*N($G10)) | K10: =IF($C10="","",N($F10)*N($H10)) | L10: =IF($C10="","",N($F10)*N($I10)) | M10: =IF(OR($C10="",N(TOP!$C$12)=0),"",N($J10)/TOP!$C$12) | N10: =IF(OR($C10="",N(TOP!$C$13)=0),"",N($K10)/TOP!$C$13) | O10: =IF(OR($C10="",N(TOP!$C$14)=0),"",N($L10)/TOP!$C$14) | P10: =IF($C10="","",IFERROR(CHOOSE(MATCH(TOP!$C$10,{"【期間A】","【期間B】","【期間C】"},0),N($M10),N($N10),N($O10)),0))
B11: 6 | C11: =IF(②実績CSV_期間A!$M7="","",②実績CSV_期間A!$M7&"") | D11: =IF($C11="","",②実績CSV_期間A!$N7) | E11: =IF($C11="","",RIGHT($D11,1)) | F11: =IF($C11="","",IFERROR(INDEX(サイズ換算マスタ!$C$6:$C$8,MATCH($E11,サイズ換算マスタ!$B$6:$B$8,0)),1)) | G11: =IF($C11="","",SUMIFS(②実績CSV_期間A!$AA$2:$AA$5001,②実績CSV_期間A!$M$2:$M$5001,$C11)) | H11: =IF($C11="","",SUMIFS(③実績CSV_期間B!$AA$2:$AA$5001,③実績CSV_期間B!$M$2:$M$5001,$C11)) | I11: =IF($C11="","",SUMIFS(④実績CSV_期間C!$AA$2:$AA$5001,④実績CSV_期間C!$M$2:$M$5001,$C11)) | J11: =IF($C11="","",N($F11)*N($G11)) | K11: =IF($C11="","",N($F11)*N($H11)) | L11: =IF($C11="","",N($F11)*N($I11)) | M11: =IF(OR($C11="",N(TOP!$C$12)=0),"",N($J11)/TOP!$C$12) | N11: =IF(OR($C11="",N(TOP!$C$13)=0),"",N($K11)/TOP!$C$13) | O11: =IF(OR($C11="",N(TOP!$C$14)=0),"",N($L11)/TOP!$C$14) | P11: =IF($C11="","",IFERROR(CHOOSE(MATCH(TOP!$C$10,{"【期間A】","【期間B】","【期間C】"},0),N($M11),N($N11),N($O11)),0))
B12: 7 | C12: =IF(②実績CSV_期間A!$M8="","",②実績CSV_期間A!$M8&"") | D12: =IF($C12="","",②実績CSV_期間A!$N8) | E12: =IF($C12="","",RIGHT($D12,1)) | F12: =IF($C12="","",IFERROR(INDEX(サイズ換算マスタ!$C$6:$C$8,MATCH($E12,サイズ換算マスタ!$B$6:$B$8,0)),1)) | G12: =IF($C12="","",SUMIFS(②実績CSV_期間A!$AA$2:$AA$5001,②実績CSV_期間A!$M$2:$M$5001,$C12)) | H12: =IF($C12="","",SUMIFS(③実績CSV_期間B!$AA$2:$AA$5001,③実績CSV_期間B!$M$2:$M$5001,$C12)) | I12: =IF($C12="","",SUMIFS(④実績CSV_期間C!$AA$2:$AA$5001,④実績CSV_期間C!$M$2:$M$5001,$C12)) | J12: =IF($C12="","",N($F12)*N($G12)) | K12: =IF($C12="","",N($F12)*N($H12)) | L12: =IF($C12="","",N($F12)*N($I12)) | M12: =IF(OR($C12="",N(TOP!$C$12)=0),"",N($J12)/TOP!$C$12) | N12: =IF(OR($C12="",N(TOP!$C$13)=0),"",N($K12)/TOP!$C$13) | O12: =IF(OR($C12="",N(TOP!$C$14)=0),"",N($L12)/TOP!$C$14) | P12: =IF($C12="","",IFERROR(CHOOSE(MATCH(TOP!$C$10,{"【期間A】","【期間B】","【期間C】"},0),N($M12),N($N12),N($O12)),0))
B13: 8 | C13: =IF(②実績CSV_期間A!$M9="","",②実績CSV_期間A!$M9&"") | D13: =IF($C13="","",②実績CSV_期間A!$N9) | E13: =IF($C13="","",RIGHT($D13,1)) | F13: =IF($C13="","",IFERROR(INDEX(サイズ換算マスタ!$C$6:$C$8,MATCH($E13,サイズ換算マスタ!$B$6:$B$8,0)),1)) | G13: =IF($C13="","",SUMIFS(②実績CSV_期間A!$AA$2:$AA$5001,②実績CSV_期間A!$M$2:$M$5001,$C13)) | H13: =IF($C13="","",SUMIFS(③実績CSV_期間B!$AA$2:$AA$5001,③実績CSV_期間B!$M$2:$M$5001,$C13)) | I13: =IF($C13="","",SUMIFS(④実績CSV_期間C!$AA$2:$AA$5001,④実績CSV_期間C!$M$2:$M$5001,$C13)) | J13: =IF($C13="","",N($F13)*N($G13)) | K13: =IF($C13="","",N($F13)*N($H13)) | L13: =IF($C13="","",N($F13)*N($I13)) | M13: =IF(OR($C13="",N(TOP!$C$12)=0),"",N($J13)/TOP!$C$12) | N13: =IF(OR($C13="",N(TOP!$C$13)=0),"",N($K13)/TOP!$C$13) | O13: =IF(OR($C13="",N(TOP!$C$14)=0),"",N($L13)/TOP!$C$14) | P13: =IF($C13="","",IFERROR(CHOOSE(MATCH(TOP!$C$10,{"【期間A】","【期間B】","【期間C】"},0),N($M13),N($N13),N($O13)),0))
B14: 9 | C14: =IF(②実績CSV_期間A!$M10="","",②実績CSV_期間A!$M10&"") | D14: =IF($C14="","",②実績CSV_期間A!$N10) | E14: =IF($C14="","",RIGHT($D14,1)) | F14: =IF($C14="","",IFERROR(INDEX(サイズ換算マスタ!$C$6:$C$8,MATCH($E14,サイズ換算マスタ!$B$6:$B$8,0)),1)) | G14: =IF($C14="","",SUMIFS(②実績CSV_期間A!$AA$2:$AA$5001,②実績CSV_期間A!$M$2:$M$5001,$C14)) | H14: =IF($C14="","",SUMIFS(③実績CSV_期間B!$AA$2:$AA$5001,③実績CSV_期間B!$M$2:$M$5001,$C14)) | I14: =IF($C14="","",SUMIFS(④実績CSV_期間C!$AA$2:$AA$5001,④実績CSV_期間C!$M$2:$M$5001,$C14)) | J14: =IF($C14="","",N($F14)*N($G14)) | K14: =IF($C14="","",N($F14)*N($H14)) | L14: =IF($C14="","",N($F14)*N($I14)) | M14: =IF(OR($C14="",N(TOP!$C$12)=0),"",N($J14)/TOP!$C$12) | N14: =IF(OR($C14="",N(TOP!$C$13)=0),"",N($K14)/TOP!$C$13) | O14: =IF(OR($C14="",N(TOP!$C$14)=0),"",N($L14)/TOP!$C$14) | P14: =IF($C14="","",IFERROR(CHOOSE(MATCH(TOP!$C$10,{"【期間A】","【期間B】","【期間C】"},0),N($M14),N($N14),N($O14)),0))
B15: 10 | C15: =IF(②実績CSV_期間A!$M11="","",②実績CSV_期間A!$M11&"") | D15: =IF($C15="","",②実績CSV_期間A!$N11) | E15: =IF($C15="","",RIGHT($D15,1)) | F15: =IF($C15="","",IFERROR(INDEX(サイズ換算マスタ!$C$6:$C$8,MATCH($E15,サイズ換算マスタ!$B$6:$B$8,0)),1)) | G15: =IF($C15="","",SUMIFS(②実績CSV_期間A!$AA$2:$AA$5001,②実績CSV_期間A!$M$2:$M$5001,$C15)) | H15: =IF($C15="","",SUMIFS(③実績CSV_期間B!$AA$2:$AA$5001,③実績CSV_期間B!$M$2:$M$5001,$C15)) | I15: =IF($C15="","",SUMIFS(④実績CSV_期間C!$AA$2:$AA$5001,④実績CSV_期間C!$M$2:$M$5001,$C15)) | J15: =IF($C15="","",N($F15)*N($G15)) | K15: =IF($C15="","",N($F15)*N($H15)) | L15: =IF($C15="","",N($F15)*N($I15)) | M15: =IF(OR($C15="",N(TOP!$C$12)=0),"",N($J15)/TOP!$C$12) | N15: =IF(OR($C15="",N(TOP!$C$13)=0),"",N($K15)/TOP!$C$13) | O15: =IF(OR($C15="",N(TOP!$C$14)=0),"",N($L15)/TOP!$C$14) | P15: =IF($C15="","",IFERROR(CHOOSE(MATCH(TOP!$C$10,{"【期間A】","【期間B】","【期間C】"},0),N($M15),N($N15),N($O15)),0))
B16: 11 | C16: =IF(②実績CSV_期間A!$M12="","",②実績CSV_期間A!$M12&"") | D16: =IF($C16="","",②実績CSV_期間A!$N12) | E16: =IF($C16="","",RIGHT($D16,1)) | F16: =IF($C16="","",IFERROR(INDEX(サイズ換算マスタ!$C$6:$C$8,MATCH($E16,サイズ換算マスタ!$B$6:$B$8,0)),1)) | G16: =IF($C16="","",SUMIFS(②実績CSV_期間A!$AA$2:$AA$5001,②実績CSV_期間A!$M$2:$M$5001,$C16)) | H16: =IF($C16="","",SUMIFS(③実績CSV_期間B!$AA$2:$AA$5001,③実績CSV_期間B!$M$2:$M$5001,$C16)) | I16: =IF($C16="","",SUMIFS(④実績CSV_期間C!$AA$2:$AA$5001,④実績CSV_期間C!$M$2:$M$5001,$C16)) | J16: =IF($C16="","",N($F16)*N($G16)) | K16: =IF($C16="","",N($F16)*N($H16)) | L16: =IF($C16="","",N($F16)*N($I16)) | M16: =IF(OR($C16="",N(TOP!$C$12)=0),"",N($J16)/TOP!$C$12) | N16: =IF(OR($C16="",N(TOP!$C$13)=0),"",N($K16)/TOP!$C$13) | O16: =IF(OR($C16="",N(TOP!$C$14)=0),"",N($L16)/TOP!$C$14) | P16: =IF($C16="","",IFERROR(CHOOSE(MATCH(TOP!$C$10,{"【期間A】","【期間B】","【期間C】"},0),N($M16),N($N16),N($O16)),0))
B17: 12 | C17: =IF(②実績CSV_期間A!$M13="","",②実績CSV_期間A!$M13&"") | D17: =IF($C17="","",②実績CSV_期間A!$N13) | E17: =IF($C17="","",RIGHT($D17,1)) | F17: =IF($C17="","",IFERROR(INDEX(サイズ換算マスタ!$C$6:$C$8,MATCH($E17,サイズ換算マスタ!$B$6:$B$8,0)),1)) | G17: =IF($C17="","",SUMIFS(②実績CSV_期間A!$AA$2:$AA$5001,②実績CSV_期間A!$M$2:$M$5001,$C17)) | H17: =IF($C17="","",SUMIFS(③実績CSV_期間B!$AA$2:$AA$5001,③実績CSV_期間B!$M$2:$M$5001,$C17)) | I17: =IF($C17="","",SUMIFS(④実績CSV_期間C!$AA$2:$AA$5001,④実績CSV_期間C!$M$2:$M$5001,$C17)) | J17: =IF($C17="","",N($F17)*N($G17)) | K17: =IF($C17="","",N($F17)*N($H17)) | L17: =IF($C17="","",N($F17)*N($I17)) | M17: =IF(OR($C17="",N(TOP!$C$12)=0),"",N($J17)/TOP!$C$12) | N17: =IF(OR($C17="",N(TOP!$C$13)=0),"",N($K17)/TOP!$C$13) | O17: =IF(OR($C17="",N(TOP!$C$14)=0),"",N($L17)/TOP!$C$14) | P17: =IF($C17="","",IFERROR(CHOOSE(MATCH(TOP!$C$10,{"【期間A】","【期間B】","【期間C】"},0),N($M17),N($N17),N($O17)),0))
... B3005: 3000 | C3005: =IF(②実績CSV_期間A!$M3001="","",②実績CSV_期間A!$M3001&"") | D3005: =IF($C3005="","",②実績CSV_期間A!$N3001) | E3005: =IF($C3005="","",RIGHT($D3005,1)) | F3005: =IF($C3005="","",IFERROR(INDEX(サイズ換算マスタ!$C$6:$C$8,MATCH($E3005,サイズ換算マスタ!$B$6:$B$8,0)),1)) | G3005: =IF($C3005="","",SUMIFS(②実績CSV_期間A!$AA$2:$AA$5001,②実績CSV_期間A!$M$2:$M$5001,$C3005)) | H3005: =IF($C3005="","",SUMIFS(③実績CSV_期間B!$AA$2:$AA$5001,③実績CSV_期間B!$M$2:$M$5001,$C3005)) | I3005: =IF($C3005="","",SUMIFS(④実績CSV_期間C!$AA$2:$AA$5001,④実績CSV_期間C!$M$2:$M$5001,$C3005)) | J3005: =IF($C3005="","",N($F3005)*N($G3005)) | K3005: =IF($C3005="","",N($F3005)*N($H3005)) | L3005: =IF($C3005="","",N($F3005)*N($I3005)) | M3005: =IF(OR($C3005="",N(TOP!$C$12)=0),"",N($J3005)/TOP!$C$12) | N3005: =IF(OR($C3005="",N(TOP!$C$13)=0),"",N($K3005)/TOP!$C$13) | O3005: =IF(OR($C3005="",N(TOP!$C$14)=0),"",N($L3005)/TOP!$C$14) | P3005: =IF($C3005="","",IFERROR(CHOOSE(MATCH(TOP!$C$10,{"【期間A】","【期間B】","【期間C】"},0),N($M3005),N($N3005),N($O3005)),0))

Sheet 商品マスタ
B2: 商品マスタ（在庫商品）
B3: 発注日在庫CSVの商品を並べ、購買率・イールド・発注属性をまとめます。黄色の2列だけが手入力です。
B4: 自動 | C4: 自動 | D4: 自動 | E4: 自動 | F4: 自動 | G4: 入力 | H4: 自動 | I4: 自動 | J4: 自動 | K4: 自動 | L4: 自動 | M4: 自動 | N4: 自動 | O4: 自動 | P4: 入力 | Q4: 入力 | R4: 自動
B5: No | C5: 商品コード | D5: 商品名 | E5: 分類名 | F5: 支払先名 | G5: 温度区分 | H5: 理論在庫 | I5: 算出購買率 | J5: イールド | K5: 発注ロット | L5: 仕入単価 | M5: 発注単価 | N5: パック入り数 | O5: 棚卸単位 | P5: 設定 | Q5: ストック(ケース) | R5: ストック設定
B6: 1 | C6: =IF(①在庫CSV_発注日!$M2="","",①在庫CSV_発注日!$M2&"") | D6: =IF($C6="","",①在庫CSV_発注日!$N2) | E6: =IF($C6="","",①在庫CSV_発注日!$H2) | F6: =IF($C6="","",①在庫CSV_発注日!$L2) | H6: =IF($C6="","",N(①在庫CSV_発注日!$Z2)) | I6: =IF($C6="","",SUMIFS(⑤減算マスタCSV!$L$2:$L$8001,⑤減算マスタCSV!$F$2:$F$8001,$C6,⑤減算マスタCSV!$K$2:$K$8001,1)) | J6: =IF($C6="","",IFERROR(INDEX(⑤減算マスタCSV!$H$2:$H$8001,MATCH($C6,⑤減算マスタCSV!$F$2:$F$8001,0)),1)) | K6: =IF($C6="","",MAX(1,IFERROR(INDEX(⑥商品照会CSV!$M$2:$M$3001,MATCH($C6,⑥商品照会CSV!$A$2:$A$3001,0)),1))) | L6: =IF($C6="","",IFERROR(INDEX(⑥商品照会CSV!$Q$2:$Q$3001,MATCH($C6,⑥商品照会CSV!$A$2:$A$3001,0)),0)) | M6: =IF($C6="","",N($L6)*N($K6)) | N6: =IF($C6="","",MAX(1,IFERROR(INDEX(⑥商品照会CSV!$AK$2:$AK$3001,MATCH($C6,⑥商品照会CSV!$A$2:$A$3001,0)),1))) | O6: =IF($C6="","",IFERROR(IF(INDEX(⑥商品照会CSV!$AN$2:$AN$3001,MATCH($C6,⑥商品照会CSV!$A$2:$A$3001,0))=1,"バラ",IF(INDEX(⑥商品照会CSV!$AM$2:$AM$3001,MATCH($C6,⑥商品照会CSV!$A$2:$A$3001,0))=1,"中間包装","ケース")),"ケース")) | R6: =IF($C6="","",N($Q6)*N($K6))
B7: 2 | C7: =IF(①在庫CSV_発注日!$M3="","",①在庫CSV_発注日!$M3&"") | D7: =IF($C7="","",①在庫CSV_発注日!$N3) | E7: =IF($C7="","",①在庫CSV_発注日!$H3) | F7: =IF($C7="","",①在庫CSV_発注日!$L3) | H7: =IF($C7="","",N(①在庫CSV_発注日!$Z3)) | I7: =IF($C7="","",SUMIFS(⑤減算マスタCSV!$L$2:$L$8001,⑤減算マスタCSV!$F$2:$F$8001,$C7,⑤減算マスタCSV!$K$2:$K$8001,1)) | J7: =IF($C7="","",IFERROR(INDEX(⑤減算マスタCSV!$H$2:$H$8001,MATCH($C7,⑤減算マスタCSV!$F$2:$F$8001,0)),1)) | K7: =IF($C7="","",MAX(1,IFERROR(INDEX(⑥商品照会CSV!$M$2:$M$3001,MATCH($C7,⑥商品照会CSV!$A$2:$A$3001,0)),1))) | L7: =IF($C7="","",IFERROR(INDEX(⑥商品照会CSV!$Q$2:$Q$3001,MATCH($C7,⑥商品照会CSV!$A$2:$A$3001,0)),0)) | M7: =IF($C7="","",N($L7)*N($K7)) | N7: =IF($C7="","",MAX(1,IFERROR(INDEX(⑥商品照会CSV!$AK$2:$AK$3001,MATCH($C7,⑥商品照会CSV!$A$2:$A$3001,0)),1))) | O7: =IF($C7="","",IFERROR(IF(INDEX(⑥商品照会CSV!$AN$2:$AN$3001,MATCH($C7,⑥商品照会CSV!$A$2:$A$3001,0))=1,"バラ",IF(INDEX(⑥商品照会CSV!$AM$2:$AM$3001,MATCH($C7,⑥商品照会CSV!$A$2:$A$3001,0))=1,"中間包装","ケース")),"ケース")) | R7: =IF($C7="","",N($Q7)*N($K7))
B8: 3 | C8: =IF(①在庫CSV_発注日!$M4="","",①在庫CSV_発注日!$M4&"") | D8: =IF($C8="","",①在庫CSV_発注日!$N4) | E8: =IF($C8="","",①在庫CSV_発注日!$H4) | F8: =IF($C8="","",①在庫CSV_発注日!$L4) | H8: =IF($C8="","",N(①在庫CSV_発注日!$Z4)) | I8: =IF($C8="","",SUMIFS(⑤減算マスタCSV!$L$2:$L$8001,⑤減算マスタCSV!$F$2:$F$8001,$C8,⑤減算マスタCSV!$K$2:$K$8001,1)) | J8: =IF($C8="","",IFERROR(INDEX(⑤減算マスタCSV!$H$2:$H$8001,MATCH($C8,⑤減算マスタCSV!$F$2:$F$8001,0)),1)) | K8: =IF($C8="","",MAX(1,IFERROR(INDEX(⑥商品照会CSV!$M$2:$M$3001,MATCH($C8,⑥商品照会CSV!$A$2:$A$3001,0)),1))) | L8: =IF($C8="","",IFERROR(INDEX(⑥商品照会CSV!$Q$2:$Q$3001,MATCH($C8,⑥商品照会CSV!$A$2:$A$3001,0)),0)) | M8: =IF($C8="","",N($L8)*N($K8)) | N8: =IF($C8="","",MAX(1,IFERROR(INDEX(⑥商品照会CSV!$AK$2:$AK$3001,MATCH($C8,⑥商品照会CSV!$A$2:$A$3001,0)),1))) | O8: =IF($C8="","",IFERROR(IF(INDEX(⑥商品照会CSV!$AN$2:$AN$3001,MATCH($C8,⑥商品照会CSV!$A$2:$A$3001,0))=1,"バラ",IF(INDEX(⑥商品照会CSV!$AM$2:$AM$3001,MATCH($C8,⑥商品照会CSV!$A$2:$A$3001,0))=1,"中間包装","ケース")),"ケース")) | R8: =IF($C8="","",N($Q8)*N($K8))
B9: 4 | C9: =IF(①在庫CSV_発注日!$M5="","",①在庫CSV_発注日!$M5&"") | D9: =IF($C9="","",①在庫CSV_発注日!$N5) | E9: =IF($C9="","",①在庫CSV_発注日!$H5) | F9: =IF($C9="","",①在庫CSV_発注日!$L5) | H9: =IF($C9="","",N(①在庫CSV_発注日!$Z5)) | I9: =IF($C9="","",SUMIFS(⑤減算マスタCSV!$L$2:$L$8001,⑤減算マスタCSV!$F$2:$F$8001,$C9,⑤減算マスタCSV!$K$2:$K$8001,1)) | J9: =IF($C9="","",IFERROR(INDEX(⑤減算マスタCSV!$H$2:$H$8001,MATCH($C9,⑤減算マスタCSV!$F$2:$F$8001,0)),1)) | K9: =IF($C9="","",MAX(1,IFERROR(INDEX(⑥商品照会CSV!$M$2:$M$3001,MATCH($C9,⑥商品照会CSV!$A$2:$A$3001,0)),1))) | L9: =IF($C9="","",IFERROR(INDEX(⑥商品照会CSV!$Q$2:$Q$3001,MATCH($C9,⑥商品照会CSV!$A$2:$A$3001,0)),0)) | M9: =IF($C9="","",N($L9)*N($K9)) | N9: =IF($C9="","",MAX(1,IFERROR(INDEX(⑥商品照会CSV!$AK$2:$AK$3001,MATCH($C9,⑥商品照会CSV!$A$2:$A$3001,0)),1))) | O9: =IF($C9="","",IFERROR(IF(INDEX(⑥商品照会CSV!$AN$2:$AN$3001,MATCH($C9,⑥商品照会CSV!$A$2:$A$3001,0))=1,"バラ",IF(INDEX(⑥商品照会CSV!$AM$2:$AM$3001,MATCH($C9,⑥商品照会CSV!$A$2:$A$3001,0))=1,"中間包装","ケース")),"ケース")) | R9: =IF($C9="","",N($Q9)*N($K9))
B10: 5 | C10: =IF(①在庫CSV_発注日!$M6="","",①在庫CSV_発注日!$M6&"") | D10: =IF($C10="","",①在庫CSV_発注日!$N6) | E10: =IF($C10="","",①在庫CSV_発注日!$H6) | F10: =IF($C10="","",①在庫CSV_発注日!$L6) | H10: =IF($C10="","",N(①在庫CSV_発注日!$Z6)) | I10: =IF($C10="","",SUMIFS(⑤減算マスタCSV!$L$2:$L$8001,⑤減算マスタCSV!$F$2:$F$8001,$C10,⑤減算マスタCSV!$K$2:$K$8001,1)) | J10: =IF($C10="","",IFERROR(INDEX(⑤減算マスタCSV!$H$2:$H$8001,MATCH($C10,⑤減算マスタCSV!$F$2:$F$8001,0)),1)) | K10: =IF($C10="","",MAX(1,IFERROR(INDEX(⑥商品照会CSV!$M$2:$M$3001,MATCH($C10,⑥商品照会CSV!$A$2:$A$3001,0)),1))) | L10: =IF($C10="","",IFERROR(INDEX(⑥商品照会CSV!$Q$2:$Q$3001,MATCH($C10,⑥商品照会CSV!$A$2:$A$3001,0)),0)) | M10: =IF($C10="","",N($L10)*N($K10)) | N10: =IF($C10="","",MAX(1,IFERROR(INDEX(⑥商品照会CSV!$AK$2:$AK$3001,MATCH($C10,⑥商品照会CSV!$A$2:$A$3001,0)),1))) | O10: =IF($C10="","",IFERROR(IF(INDEX(⑥商品照会CSV!$AN$2:$AN$3001,MATCH($C10,⑥商品照会CSV!$A$2:$A$3001,0))=1,"バラ",IF(INDEX(⑥商品照会CSV!$AM$2:$AM$3001,MATCH($C10,⑥商品照会CSV!$A$2:$A$3001,0))=1,"中間包装","ケース")),"ケース")) | R10: =IF($C10="","",N($Q10)*N($K10))
B11: 6 | C11: =IF(①在庫CSV_発注日!$M7="","",①在庫CSV_発注日!$M7&"") | D11: =IF($C11="","",①在庫CSV_発注日!$N7) | E11: =IF($C11="","",①在庫CSV_発注日!$H7) | F11: =IF($C11="","",①在庫CSV_発注日!$L7) | H11: =IF($C11="","",N(①在庫CSV_発注日!$Z7)) | I11: =IF($C11="","",SUMIFS(⑤減算マスタCSV!$L$2:$L$8001,⑤減算マスタCSV!$F$2:$F$8001,$C11,⑤減算マスタCSV!$K$2:$K$8001,1)) | J11: =IF($C11="","",IFERROR(INDEX(⑤減算マスタCSV!$H$2:$H$8001,MATCH($C11,⑤減算マスタCSV!$F$2:$F$8001,0)),1)) | K11: =IF($C11="","",MAX(1,IFERROR(INDEX(⑥商品照会CSV!$M$2:$M$3001,MATCH($C11,⑥商品照会CSV!$A$2:$A$3001,0)),1))) | L11: =IF($C11="","",IFERROR(INDEX(⑥商品照会CSV!$Q$2:$Q$3001,MATCH($C11,⑥商品照会CSV!$A$2:$A$3001,0)),0)) | M11: =IF($C11="","",N($L11)*N($K11)) | N11: =IF($C11="","",MAX(1,IFERROR(INDEX(⑥商品照会CSV!$AK$2:$AK$3001,MATCH($C11,⑥商品照会CSV!$A$2:$A$3001,0)),1))) | O11: =IF($C11="","",IFERROR(IF(INDEX(⑥商品照会CSV!$AN$2:$AN$3001,MATCH($C11,⑥商品照会CSV!$A$2:$A$3001,0))=1,"バラ",IF(INDEX(⑥商品照会CSV!$AM$2:$AM$3001,MATCH($C11,⑥商品照会CSV!$A$2:$A$3001,0))=1,"中間包装","ケース")),"ケース")) | R11: =IF($C11="","",N($Q11)*N($K11))
B12: 7 | C12: =IF(①在庫CSV_発注日!$M8="","",①在庫CSV_発注日!$M8&"") | D12: =IF($C12="","",①在庫CSV_発注日!$N8) | E12: =IF($C12="","",①在庫CSV_発注日!$H8) | F12: =IF($C12="","",①在庫CSV_発注日!$L8) | H12: =IF($C12="","",N(①在庫CSV_発注日!$Z8)) | I12: =IF($C12="","",SUMIFS(⑤減算マスタCSV!$L$2:$L$8001,⑤減算マスタCSV!$F$2:$F$8001,$C12,⑤減算マスタCSV!$K$2:$K$8001,1)) | J12: =IF($C12="","",IFERROR(INDEX(⑤減算マスタCSV!$H$2:$H$8001,MATCH($C12,⑤減算マスタCSV!$F$2:$F$8001,0)),1)) | K12: =IF($C12="","",MAX(1,IFERROR(INDEX(⑥商品照会CSV!$M$2:$M$3001,MATCH($C12,⑥商品照会CSV!$A$2:$A$3001,0)),1))) | L12: =IF($C12="","",IFERROR(INDEX(⑥商品照会CSV!$Q$2:$Q$3001,MATCH($C12,⑥商品照会CSV!$A$2:$A$3001,0)),0)) | M12: =IF($C12="","",N($L12)*N($K12)) | N12: =IF($C12="","",MAX(1,IFERROR(INDEX(⑥商品照会CSV!$AK$2:$AK$3001,MATCH($C12,⑥商品照会CSV!$A$2:$A$3001,0)),1))) | O12: =IF($C12="","",IFERROR(IF(INDEX(⑥商品照会CSV!$AN$2:$AN$3001,MATCH($C12,⑥商品照会CSV!$A$2:$A$3001,0))=1,"バラ",IF(INDEX(⑥商品照会CSV!$AM$2:$AM$3001,MATCH($C12,⑥商品照会CSV!$A$2:$A$3001,0))=1,"中間包装","ケース")),"ケース")) | R12: =IF($C12="","",N($Q12)*N($K12))
B13: 8 | C13: =IF(①在庫CSV_発注日!$M9="","",①在庫CSV_発注日!$M9&"") | D13: =IF($C13="","",①在庫CSV_発注日!$N9) | E13: =IF($C13="","",①在庫CSV_発注日!$H9) | F13: =IF($C13="","",①在庫CSV_発注日!$L9) | H13: =IF($C13="","",N(①在庫CSV_発注日!$Z9)) | I13: =IF($C13="","",SUMIFS(⑤減算マスタCSV!$L$2:$L$8001,⑤減算マスタCSV!$F$2:$F$8001,$C13,⑤減算マスタCSV!$K$2:$K$8001,1)) | J13: =IF($C13="","",IFERROR(INDEX(⑤減算マスタCSV!$H$2:$H$8001,MATCH($C13,⑤減算マスタCSV!$F$2:$F$8001,0)),1)) | K13: =IF($C13="","",MAX(1,IFERROR(INDEX(⑥商品照会CSV!$M$2:$M$3001,MATCH($C13,⑥商品照会CSV!$A$2:$A$3001,0)),1))) | L13: =IF($C13="","",IFERROR(INDEX(⑥商品照会CSV!$Q$2:$Q$3001,MATCH($C13,⑥商品照会CSV!$A$2:$A$3001,0)),0)) | M13: =IF($C13="","",N($L13)*N($K13)) | N13: =IF($C13="","",MAX(1,IFERROR(INDEX(⑥商品照会CSV!$AK$2:$AK$3001,MATCH($C13,⑥商品照会CSV!$A$2:$A$3001,0)),1))) | O13: =IF($C13="","",IFERROR(IF(INDEX(⑥商品照会CSV!$AN$2:$AN$3001,MATCH($C13,⑥商品照会CSV!$A$2:$A$3001,0))=1,"バラ",IF(INDEX(⑥商品照会CSV!$AM$2:$AM$3001,MATCH($C13,⑥商品照会CSV!$A$2:$A$3001,0))=1,"中間包装","ケース")),"ケース")) | R13: =IF($C13="","",N($Q13)*N($K13))
B14: 9 | C14: =IF(①在庫CSV_発注日!$M10="","",①在庫CSV_発注日!$M10&"") | D14: =IF($C14="","",①在庫CSV_発注日!$N10) | E14: =IF($C14="","",①在庫CSV_発注日!$H10) | F14: =IF($C14="","",①在庫CSV_発注日!$L10) | H14: =IF($C14="","",N(①在庫CSV_発注日!$Z10)) | I14: =IF($C14="","",SUMIFS(⑤減算マスタCSV!$L$2:$L$8001,⑤減算マスタCSV!$F$2:$F$8001,$C14,⑤減算マスタCSV!$K$2:$K$8001,1)) | J14: =IF($C14="","",IFERROR(INDEX(⑤減算マスタCSV!$H$2:$H$8001,MATCH($C14,⑤減算マスタCSV!$F$2:$F$8001,0)),1)) | K14: =IF($C14="","",MAX(1,IFERROR(INDEX(⑥商品照会CSV!$M$2:$M$3001,MATCH($C14,⑥商品照会CSV!$A$2:$A$3001,0)),1))) | L14: =IF($C14="","",IFERROR(INDEX(⑥商品照会CSV!$Q$2:$Q$3001,MATCH($C14,⑥商品照会CSV!$A$2:$A$3001,0)),0)) | M14: =IF($C14="","",N($L14)*N($K14)) | N14: =IF($C14="","",MAX(1,IFERROR(INDEX(⑥商品照会CSV!$AK$2:$AK$3001,MATCH($C14,⑥商品照会CSV!$A$2:$A$3001,0)),1))) | O14: =IF($C14="","",IFERROR(IF(INDEX(⑥商品照会CSV!$AN$2:$AN$3001,MATCH($C14,⑥商品照会CSV!$A$2:$A$3001,0))=1,"バラ",IF(INDEX(⑥商品照会CSV!$AM$2:$AM$3001,MATCH($C14,⑥商品照会CSV!$A$2:$A$3001,0))=1,"中間包装","ケース")),"ケース")) | R14: =IF($C14="","",N($Q14)*N($K14))
B15: 10 | C15: =IF(①在庫CSV_発注日!$M11="","",①在庫CSV_発注日!$M11&"") | D15: =IF($C15="","",①在庫CSV_発注日!$N11) | E15: =IF($C15="","",①在庫CSV_発注日!$H11) | F15: =IF($C15="","",①在庫CSV_発注日!$L11) | H15: =IF($C15="","",N(①在庫CSV_発注日!$Z11)) | I15: =IF($C15="","",SUMIFS(⑤減算マスタCSV!$L$2:$L$8001,⑤減算マスタCSV!$F$2:$F$8001,$C15,⑤減算マスタCSV!$K$2:$K$8001,1)) | J15: =IF($C15="","",IFERROR(INDEX(⑤減算マスタCSV!$H$2:$H$8001,MATCH($C15,⑤減算マスタCSV!$F$2:$F$8001,0)),1)) | K15: =IF($C15="","",MAX(1,IFERROR(INDEX(⑥商品照会CSV!$M$2:$M$3001,MATCH($C15,⑥商品照会CSV!$A$2:$A$3001,0)),1))) | L15: =IF($C15="","",IFERROR(INDEX(⑥商品照会CSV!$Q$2:$Q$3001,MATCH($C15,⑥商品照会CSV!$A$2:$A$3001,0)),0)) | M15: =IF($C15="","",N($L15)*N($K15)) | N15: =IF($C15="","",MAX(1,IFERROR(INDEX(⑥商品照会CSV!$AK$2:$AK$3001,MATCH($C15,⑥商品照会CSV!$A$2:$A$3001,0)),1))) | O15: =IF($C15="","",IFERROR(IF(INDEX(⑥商品照会CSV!$AN$2:$AN$3001,MATCH($C15,⑥商品照会CSV!$A$2:$A$3001,0))=1,"バラ",IF(INDEX(⑥商品照会CSV!$AM$2:$AM$3001,MATCH($C15,⑥商品照会CSV!$A$2:$A$3001,0))=1,"中間包装","ケース")),"ケース")) | R15: =IF($C15="","",N($Q15)*N($K15))
B16: 11 | C16: =IF(①在庫CSV_発注日!$M12="","",①在庫CSV_発注日!$M12&"") | D16: =IF($C16="","",①在庫CSV_発注日!$N12) | E16: =IF($C16="","",①在庫CSV_発注日!$H12) | F16: =IF($C16="","",①在庫CSV_発注日!$L12) | H16: =IF($C16="","",N(①在庫CSV_発注日!$Z12)) | I16: =IF($C16="","",SUMIFS(⑤減算マスタCSV!$L$2:$L$8001,⑤減算マスタCSV!$F$2:$F$8001,$C16,⑤減算マスタCSV!$K$2:$K$8001,1)) | J16: =IF($C16="","",IFERROR(INDEX(⑤減算マスタCSV!$H$2:$H$8001,MATCH($C16,⑤減算マスタCSV!$F$2:$F$8001,0)),1)) | K16: =IF($C16="","",MAX(1,IFERROR(INDEX(⑥商品照会CSV!$M$2:$M$3001,MATCH($C16,⑥商品照会CSV!$A$2:$A$3001,0)),1))) | L16: =IF($C16="","",IFERROR(INDEX(⑥商品照会CSV!$Q$2:$Q$3001,MATCH($C16,⑥商品照会CSV!$A$2:$A$3001,0)),0)) | M16: =IF($C16="","",N($L16)*N($K16)) | N16: =IF($C16="","",MAX(1,IFERROR(INDEX(⑥商品照会CSV!$AK$2:$AK$3001,MATCH($C16,⑥商品照会CSV!$A$2:$A$3001,0)),1))) | O16: =IF($C16="","",IFERROR(IF(INDEX(⑥商品照会CSV!$AN$2:$AN$3001,MATCH($C16,⑥商品照会CSV!$A$2:$A$3001,0))=1,"バラ",IF(INDEX(⑥商品照会CSV!$AM$2:$AM$3001,MATCH($C16,⑥商品照会CSV!$A$2:$A$3001,0))=1,"中間包装","ケース")),"ケース")) | R16: =IF($C16="","",N($Q16)*N($K16))
B17: 12 | C17: =IF(①在庫CSV_発注日!$M13="","",①在庫CSV_発注日!$M13&"") | D17: =IF($C17="","",①在庫CSV_発注日!$N13) | E17: =IF($C17="","",①在庫CSV_発注日!$H13) | F17: =IF($C17="","",①在庫CSV_発注日!$L13) | H17: =IF($C17="","",N(①在庫CSV_発注日!$Z13)) | I17: =IF($C17="","",SUMIFS(⑤減算マスタCSV!$L$2:$L$8001,⑤減算マスタCSV!$F$2:$F$8001,$C17,⑤減算マスタCSV!$K$2:$K$8001,1)) | J17: =IF($C17="","",IFERROR(INDEX(⑤減算マスタCSV!$H$2:$H$8001,MATCH($C17,⑤減算マスタCSV!$F$2:$F$8001,0)),1)) | K17: =IF($C17="","",MAX(1,IFERROR(INDEX(⑥商品照会CSV!$M$2:$M$3001,MATCH($C17,⑥商品照会CSV!$A$2:$A$3001,0)),1))) | L17: =IF($C17="","",IFERROR(INDEX(⑥商品照会CSV!$Q$2:$Q$3001,MATCH($C17,⑥商品照会CSV!$A$2:$A$3001,0)),0)) | M17: =IF($C17="","",N($L17)*N($K17)) | N17: =IF($C17="","",MAX(1,IFERROR(INDEX(⑥商品照会CSV!$AK$2:$AK$3001,MATCH($C17,⑥商品照会CSV!$A$2:$A$3001,0)),1))) | O17: =IF($C17="","",IFERROR(IF(INDEX(⑥商品照会CSV!$AN$2:$AN$3001,MATCH($C17,⑥商品照会CSV!$A$2:$A$3001,0))=1,"バラ",IF(INDEX(⑥商品照会CSV!$AM$2:$AM$3001,MATCH($C17,⑥商品照会CSV!$A$2:$A$3001,0))=1,"中間包装","ケース")),"ケース")) | R17: =IF($C17="","",N($Q17)*N($K17))
... B3005: 3000 | C3005: =IF(①在庫CSV_発注日!$M3001="","",①在庫CSV_発注日!$M3001&"") | D3005: =IF($C3005="","",①在庫CSV_発注日!$N3001) | E3005: =IF($C3005="","",①在庫CSV_発注日!$H3001) | F3005: =IF($C3005="","",①在庫CSV_発注日!$L3001) | H3005: =IF($C3005="","",N(①在庫CSV_発注日!$Z3001)) | I3005: =IF($C3005="","",SUMIFS(⑤減算マスタCSV!$L$2:$L$8001,⑤減算マスタCSV!$F$2:$F$8001,$C3005,⑤減算マスタCSV!$K$2:$K$8001,1)) | J3005: =IF($C3005="","",IFERROR(INDEX(⑤減算マスタCSV!$H$2:$H$8001,MATCH($C3005,⑤減算マスタCSV!$F$2:$F$8001,0)),1)) | K3005: =IF($C3005="","",MAX(1,IFERROR(INDEX(⑥商品照会CSV!$M$2:$M$3001,MATCH($C3005,⑥商品照会CSV!$A$2:$A$3001,0)),1))) | L3005: =IF($C3005="","",IFERROR(INDEX(⑥商品照会CSV!$Q$2:$Q$3001,MATCH($C3005,⑥商品照会CSV!$A$2:$A$3001,0)),0)) | M3005: =IF($C3005="","",N($L3005)*N($K3005)) | N3005: =IF($C3005="","",MAX(1,IFERROR(INDEX(⑥商品照会CSV!$AK$2:$AK$3001,MATCH($C3005,⑥商品照会CSV!$A$2:$A$3001,0)),1))) | O3005: =IF($C3005="","",IFERROR(IF(INDEX(⑥商品照会CSV!$AN$2:$AN$3001,MATCH($C3005,⑥商品照会CSV!$A$2:$A$3001,0))=1,"バラ",IF(INDEX(⑥商品照会CSV!$AM$2:$AM$3001,MATCH($C3005,⑥商品照会CSV!$A$2:$A$3001,0))=1,"中間包装","ケース")),"ケース")) | R3005: =IF($C3005="","",N($Q3005)*N($K3005))

Sheet サイズ換算マスタ
B2: サイズ換算マスタ
B3: 購買率をM換算するための比率です。現行版では2シートにベタ書きされていました。
B4: 入力 | C4: 入力 | D4: 入力
B5: サイズ | C5: 換算比率 | D5: 備考
B6: Ｓ | C6: 0.88 | D6: Sサイズ
B7: Ｍ | C7: 1 | D7: Mサイズ（基準）
B8: Ｌ | C8: 1.66 | D8: Lサイズ
B10: ※ 商品名の末尾1文字をサイズとみなします。該当しない商品は比率1として扱います。

Sheet 劇場マスタ
B2: 劇場マスタ
B3: 全劇場共通のブックとして配布し、TOPで自劇場を選びます。
B4: 入力 | C4: 入力 | D4: 選択 | E4: 選択 | F4: 選択 | G4: 入力
B5: 劇場コード | C5: 劇場名 | D5: 劇場タイプ | E5: 規模区分 | F5: ドリンク提供方式 | G5: 備考
B6: 0761 | C6: 新宿 | D6: 通常劇場 | E6: 大規模 | F6: 1杯売り
