Workbook

Sheet ホーム
B1: ホーム
B2: 売店発注ツール
B3: =IF('設定'!$C$6="","まだ在庫CSVが貼られていません","きょう "&TEXT('設定'!$C$6,"m/d")&"("&CHOOSE(WEEKDAY('設定'!$C$6),"日","月","火","水","木","金","土")&")"&" "&'設定'!$C$5&" "&'設定'!$C$4)
B5: 毎日やること 上から順に
C7: STEP 1 在庫を貼る › | D7: =COUNTIF('①在庫を貼る'!$V$6:$V$10005,'設定'!$C$4)
C8: 在庫システムの在庫一覧CSVを貼ります。 | D8: 読み込めた行
C9: =IF(COUNTIF('①在庫を貼る'!$V$6:$V$10005,'設定'!$C$4)=0,"● まだ貼られていません",IF('設定'!$C$6<TODAY()-1,"● 在庫が "&TEXT('設定'!$C$6,"m/d")&" のものです（"&(TODAY()-'設定'!$C$6)&"日前）。今日のCSVを貼ってください","○ 貼れています（"&TEXT('設定'!$C$6,"m/d")&" の在庫）"))
C12: STEP 2 発注する › | D12: =COUNTIF('②発注する'!$H$10:$H$409,"●*")
C13: 「切れる日」を見て、黄色の「入庫日・入庫数」を入れます。 | D13: 今日発注が必要
C14: =IF('計算'!$B$3=0,"● 動員が入っていません → 動員を入れる",IF('計算'!$B$2=1,"● これから14日が動員の表の外です → 動員を入れる の「表の開始日」を直す",IF(COUNTIF('②発注する'!$H$10:$H$409,"●*")>0,"● 赤 "&COUNTIF('②発注する'!$H$10:$H$409,"●*")&"品目は今日中に発注。橙 "&COUNTIF('②発注する'!$H$10:$H$409,"△*")&"品目も近く切れます",IF(COUNTIF('②発注する'!$H$10:$H$409,"△*")>0,"△ 今日は急ぎなし。橙 "&COUNTIF('②発注する'!$H$10:$H$409,"△*")&"品目が近く切れます","○ 14日以内に切れる商品はありません"))))
C17: STEP 3 発注書を印刷する › | D17: =SUM('計算'!$CN$6:$CN$405)
C18: 入庫を入れた商品が発注書に集まります。仕入先を選んで印刷。 | D18: 発注予定額（税抜）
C19: =IF(COUNTIF('②発注する'!$O$10:$O$409,"⚠*")>0,"● ⚠ が "&COUNTIF('②発注する'!$O$10:$O$409,"⚠*")&"件あります。STEP 2 で直すまで発注書に載りません",IF(SUM('計算'!$CM$6:$CM$405)=0,"入庫を入れた商品はまだありません","○ "&SUM('計算'!$CM$6:$CM$405)&"品目を発注します"))
B21: 随時
C23: 動員を入れる › | D23: =COUNTIFS('動員を入れる'!$B$16:$B$415,">="&N('設定'!$C$6),'動員を入れる'!$B$16:$B$415,"<="&(N('設定'!$C$6)+13),'動員を入れる'!$D$16:$D$415,">0")
C24: 予測動員を入れると減り数のスピードが変わります。実績は月1回まとめてでも。 | D24: これから14日で予測が入っている日
C25: =IF('計算'!$B$2=1,"● これから14日が表の外です。「表の開始日」を今年の日付にしてください",IF('計算'!$B$3=0,"● 動員が0です。標準の動員（設定）か予測を入れてください",IF(COUNTIFS('動員を入れる'!$B$16:$B$415,">="&N('設定'!$C$6),'動員を入れる'!$B$16:$B$415,"<="&(N('設定'!$C$6)+13),'動員を入れる'!$D$16:$D$415,">0")<14,"△ 予測が無い日は曜日の実績平均（無ければ標準の動員）を使います","○ 14日分そろっています")))
B27: 月1回・社員
C28: 月1回_1ヶ月前の在庫 › | D28: =IF(COUNTIF('月1回_1ヶ月前の在庫'!$V$6:$V$10005,'設定'!$C$4)=0,"未使用（貼らなくても動きます）","○ 貼れています（"&TEXT('設定'!$C$12,"m/d")&" の在庫）")
C29: 取扱商品が変わっていないかの確認用。1ヶ月前の在庫CSVを貼り替えます。
C30: 月1回_2ヶ月前の在庫 › | D30: =IF(COUNTIF('月1回_2ヶ月前の在庫'!$V$6:$V$10005,'設定'!$C$4)=0,"未使用（貼らなくても動きます）","○ 貼れています（"&TEXT('設定'!$C$13,"m/d")&" の在庫）")
C31: 同じく2ヶ月前の在庫CSV。半年ごとに入れ替わる商品もこれで漏れません。
C32: 商品マスタ › | D32: =IF('設定'!$C$11=0,"",IF('設定'!$C$17+'設定'!$C$18+'設定'!$C$19>0,"● マスタに無い商品が "&('設定'!$C$17+'設定'!$C$18+'設定'!$C$19)&"件（②の末尾に出ています）→ マスタに追加して減り数を入れる",IF('設定'!$C$14<'設定'!$C$20,"● 減り数が未設定の商品が "&('設定'!$C$20-'設定'!$C$14)&"件あります","○ 減り数はすべて設定済み（定数 "&'設定'!$C$15&"/"&'設定'!$C$20&"）")))
C33: 定数（最大保管数）と、100人あたりの減り数を商品ごとに決めます。
C34: 劇場マスタ ›
C35: 劇場コードと名前。CSVの劇場コードと一致しているか照合できます。
C36: 設定 ›
C37: 対象劇場・発注から入庫までの日数・標準の動員・担当者・仕入先一覧。
C38: つかいかた ›
C39: 色の意味と、迷ったときの読み方。
B41: 黄色のセルだけ入力します。それ以外は保護されていて書き換えられません。

Sheet ①在庫を貼る
B1: STEP 1 在庫を貼る | N1: ◀ ホーム
B2: 在庫を貼る | H2: =IF(COUNTIF($V$6:$V$10005,'設定'!$C$4)=0,"✖ まだ貼れていません","✔ "&COUNTIF($V$6:$V$10005,'設定'!$C$4)&"行 読み込めました")
B3: 在庫システムから出した「今日の在庫一覧CSV」を貼ります。これが今の在庫になります。 | H3: =IF(COUNTIF($V$6:$V$10005,'設定'!$C$4)=0,"CSVの見出し行を除いたデータを A6 セルに貼り付けてください。貼ったのに0のままなら、設定の劇場コードとCSVの劇場コードが違います。",IF('設定'!$C$11>400,"⚠ 取扱商品が "&'設定'!$C$11&" 件あります。計算できるのは 400 件までなので、超えた分は発注画面に出ません。",IF(COUNTIF($A$6:$A$10005,"<>"&INDEX($A$6:$A$10005,MATCH('設定'!$C$4,$V$6:$V$10005,0)))-COUNTBLANK($A$6:$A$10005)>0,"⚠ 日付の違う行が混ざっています。前のデータを消してから同じ日のCSVだけを貼ってください。",IF('設定'!$C$21>0,"⚠ 同じ商品コードの行が "&'設定'!$C$21&" 件重なっています（在庫は合算して1行で出します）。貼り替えのときに前のデータを消し忘れていませんか。","対象劇場："&'設定'!$C$4&" "&'設定'!$C$5&" CSVの日付："&TEXT('設定'!$C$6,"yyyy/m/d")))))
B4: CSVの見出し行を除いたデータを、A6 セルに貼り付けてください。貼り替えは A6 から S 列までを消してから。 | U4: ← この右の3列は自動です。消さないでください（消えたら社員に）。
A5: 対象日付 | B5: 劇場コード | C5: 劇場名 | D5: 支払先コード | E5: 支払先名 | F5: 大分類コード | G5: 小分類コード | H5: 商品分類名 | I5: 商品コード | J5: 商品名 | K5: 入数 | L5: 在庫数ケース | M5: 在庫数バラ | N5: 総数 | O5: 規定数 | P5: 資産廃棄 | Q5: 税抜単価 | R5: 仕入税区分 | S5: 仕入税率 | U5: マスタに無い商品の連番(自動) | V5: 劇場コード(自動) | W5: 商品コード(自動)
U6: =IF(AND($V6='設定'!$C$4,COUNTIF('商品マスタ'!$B$6:$B$1005,$W6)=0),N(U5)+1,N(U5)) | V6: =IF($B6="","",TEXT($B6,"0000")) | W6: =IF($I6="","",IF(ISNUMBER($I6),TEXT($I6,"0"),$I6))
U7: =IF(AND($V7='設定'!$C$4,COUNTIF('商品マスタ'!$B$6:$B$1005,$W7)=0),N(U6)+1,N(U6)) | V7: =IF($B7="","",TEXT($B7,"0000")) | W7: =IF($I7="","",IF(ISNUMBER($I7),TEXT($I7,"0"),$I7))
U8: =IF(AND($V8='設定'!$C$4,COUNTIF('商品マスタ'!$B$6:$B$1005,$W8)=0),N(U7)+1,N(U7)) | V8: =IF($B8="","",TEXT($B8,"0000")) | W8: =IF($I8="","",IF(ISNUMBER($I8),TEXT($I8,"0"),$I8))
U9: =IF(AND($V9='設定'!$C$4,COUNTIF('商品マスタ'!$B$6:$B$1005,$W9)=0),N(U8)+1,N(U8)) | V9: =IF($B9="","",TEXT($B9,"0000")) | W9: =IF($I9="","",IF(ISNUMBER($I9),TEXT($I9,"0"),$I9))
U10: =IF(AND($V10='設定'!$C$4,COUNTIF('商品マスタ'!$B$6:$B$1005,$W10)=0),N(U9)+1,N(U9)) | V10: =IF($B10="","",TEXT($B10,"0000")) | W10: =IF($I10="","",IF(ISNUMBER($I10),TEXT($I10,"0"),$I10))
U11: =IF(AND($V11='設定'!$C$4,COUNTIF('商品マスタ'!$B$6:$B$1005,$W11)=0),N(U10)+1,N(U10)) | V11: =IF($B11="","",TEXT($B11,"0000")) | W11: =IF($I11="","",IF(ISNUMBER($I11),TEXT($I11,"0"),$I11))
U12: =IF(AND($V12='設定'!$C$4,COUNTIF('商品マスタ'!$B$6:$B$1005,$W12)=0),N(U11)+1,N(U11)) | V12: =IF($B12="","",TEXT($B12,"0000")) | W12: =IF($I12="","",IF(ISNUMBER($I12),TEXT($I12,"0"),$I12))
U13: =IF(AND($V13='設定'!$C$4,COUNTIF('商品マスタ'!$B$6:$B$1005,$W13)=0),N(U12)+1,N(U12)) | V13: =IF($B13="","",TEXT($B13,"0000")) | W13: =IF($I13="","",IF(ISNUMBER($I13),TEXT($I13,"0"),$I13))
U14: =IF(AND($V14='設定'!$C$4,COUNTIF('商品マスタ'!$B$6:$B$1005,$W14)=0),N(U13)+1,N(U13)) | V14: =IF($B14="","",TEXT($B14,"0000")) | W14: =IF($I14="","",IF(ISNUMBER($I14),TEXT($I14,"0"),$I14))
U15: =IF(AND($V15='設定'!$C$4,COUNTIF('商品マスタ'!$B$6:$B$1005,$W15)=0),N(U14)+1,N(U14)) | V15: =IF($B15="","",TEXT($B15,"0000")) | W15: =IF($I15="","",IF(ISNUMBER($I15),TEXT($I15,"0"),$I15))
U16: =IF(AND($V16='設定'!$C$4,COUNTIF('商品マスタ'!$B$6:$B$1005,$W16)=0),N(U15)+1,N(U15)) | V16: =IF($B16="","",TEXT($B16,"0000")) | W16: =IF($I16="","",IF(ISNUMBER($I16),TEXT($I16,"0"),$I16))
U17: =IF(AND($V17='設定'!$C$4,COUNTIF('商品マスタ'!$B$6:$B$1005,$W17)=0),N(U16)+1,N(U16)) | V17: =IF($B17="","",TEXT($B17,"0000")) | W17: =IF($I17="","",IF(ISNUMBER($I17),TEXT($I17,"0"),$I17))
... U10005: =IF(AND($V10005='設定'!$C$4,COUNTIF('商品マスタ'!$B$6:$B$1005,$W10005)=0),N(U10004)+1,N(U10004)) | V10005: =IF($B10005="","",TEXT($B10005,"0000")) | W10005: =IF($I10005="","",IF(ISNUMBER($I10005),TEXT($I10005,"0"),$I10005))

Sheet ②発注する
B1: STEP 2 発注する | AH1: ◀ ホーム
B2: 発注する | E2: =IF('設定'!$C$6="","← まず ①在庫を貼る",IF('設定'!$C$6<TODAY()-1,"⚠ 在庫が "&TEXT('設定'!$C$6,"m/d")&" のものです（"&(TODAY()-'設定'!$C$6)&"日前）→ 今日のCSVを ①在庫を貼る に貼ってください","きょう "&TEXT('設定'!$C$6,"m/d")&"("&CHOOSE(WEEKDAY('設定'!$C$6),"日","月","火","水","木","金","土")&")"&" "&'設定'!$C$5&" CSV "&'設定'!$C$10&"行"))
C4: ● 今日発注しないと間に合わない | D4: △ 近く切れる | H4: ⚠ 直すところ（直すまで発注書に載らない） | I4: 入庫を入れた（発注書に載る） | M4: 発注予定額（税抜） | P4: =IF('計算'!$B$2=1,"⚠ これから14日が動員の表の外です。「動員を入れる」の表の開始日を今年の日付にしてください。",IF('計算'!$B$3=0,"⚠ 動員が入っていません。減り数が計算できないので「動員を入れる」か「設定」の標準の動員を入れてください。","これから14日の動員：平均 "&TEXT('設定'!$C$16,"#,##0")&" 人/日 "&"数字はその日の終わりの在庫。× は切れている。黄色は入庫の日。"))
C5: =COUNTIF($H$10:$H$409,"●*") | D5: =COUNTIF($H$10:$H$409,"△*") | H5: =COUNTIF($O$10:$O$409,"⚠*") | I5: =SUM('計算'!$CM$6:$CM$405) | M5: =SUM('計算'!$CN$6:$CN$405)
B7: 読み方：左から順に。「このままだと」が ● か △ なら、黄色の入庫日（▼で選ぶ）と入庫数を入れる → 「入庫を入れると」で結果を確認。迷ったら「目安」の数。⚠ は直す。2便目は14日のうちに2回入るときだけ。 | O7: 動員 → | P7: =IF(P9="","",'計算'!V$4) | Q7: =IF(Q9="","",'計算'!W$4) | R7: =IF(R9="","",'計算'!X$4) | S7: =IF(S9="","",'計算'!Y$4) | T7: =IF(T9="","",'計算'!Z$4) | U7: =IF(U9="","",'計算'!AA$4) | V7: =IF(V9="","",'計算'!AB$4) | W7: =IF(W9="","",'計算'!AC$4) | ... AC7: =IF(AC9="","",'計算'!AI$4)
D8: 自動 | E8: 自動 | F8: 自動 | G8: 自動 | H8: 自動 | I8: 入力 | J8: 入力 | K8: 自動 | L8: 自動 | M8: 任意 | N8: 任意 | O8: 自動 | P8: =IF(P9="","",CHOOSE(WEEKDAY(P9),"日","月","火","水","木","金","土")) | Q8: =IF(Q9="","",CHOOSE(WEEKDAY(Q9),"日","月","火","水","木","金","土")) | R8: =IF(R9="","",CHOOSE(WEEKDAY(R9),"日","月","火","水","木","金","土")) | S8: =IF(S9="","",CHOOSE(WEEKDAY(S9),"日","月","火","水","木","金","土")) | T8: =IF(T9="","",CHOOSE(WEEKDAY(T9),"日","月","火","水","木","金","土")) | U8: =IF(U9="","",CHOOSE(WEEKDAY(U9),"日","月","火","水","木","金","土")) | V8: =IF(V9="","",CHOOSE(WEEKDAY(V9),"日","月","火","水","木","金","土")) | W8: =IF(W9="","",CHOOSE(WEEKDAY(W9),"日","月","火","水","木","金","土")) | ... AC8: =IF(AC9="","",CHOOSE(WEEKDAY(AC9),"日","月","火","水","木","金","土")) | AD8: 任意 | AE8: 任意 | AF8: 自動 | AG8: 自動
B9: No | C9: 商品名 | D9: 定数(個) | E9: 在庫(個) | F9: 減り数/日 | G9: 切れる日 | H9: このままだと | I9: 入庫日 (届く日) | J9: 入庫数 | K9: 単位 | L9: 目安 | M9: 2便目 入庫日 | N9: 2便目 入庫数 | O9: 入庫を入れると | P9: =IF('設定'!$C$6="","",'設定'!$C$6+0) | Q9: =IF('設定'!$C$6="","",'設定'!$C$6+1) | R9: =IF('設定'!$C$6="","",'設定'!$C$6+2) | S9: =IF('設定'!$C$6="","",'設定'!$C$6+3) | T9: =IF('設定'!$C$6="","",'設定'!$C$6+4) | U9: =IF('設定'!$C$6="","",'設定'!$C$6+5) | V9: =IF('設定'!$C$6="","",'設定'!$C$6+6) | W9: =IF('設定'!$C$6="","",'設定'!$C$6+7) | X9: =IF('設定'!$C$6="","",'設定'!$C$6+8) | Y9: =IF('設定'!$C$6="","",'設定'!$C$6+9) | Z9: =IF('設定'!$C$6="","",'設定'!$C$6+10) | AA9: =IF('設定'!$C$6="","",'設定'!$C$6+11) | AB9: =IF('設定'!$C$6="","",'設定'!$C$6+12) | AC9: =IF('設定'!$C$6="","",'設定'!$C$6+13) | AD9: 数えた在庫 | AE9: 数えた日 | AF9: 商品コード | AG9: 仕入先
B10: =IF('計算'!$C6="","",'計算'!$B6) | C10: =IF('計算'!$C6="","",'計算'!$D6) | D10: =IF('計算'!$C6="","",'計算'!$O6) | E10: =IF('計算'!$C6="","",'計算'!$L6) | F10: =IF('計算'!$C6="","",'計算'!$CD6) | G10: =IF('計算'!$C6="","",'計算'!$CA6) | H10: =IF('計算'!$C6="","",'計算'!$CP6) | K10: =IF('計算'!$C6="","",'計算'!$CR6) | L10: =IF('計算'!$C6="","",'計算'!$CF6) | O10: =IF('計算'!$C6="","",'計算'!$CQ6) | P10: =IF('計算'!$C6="","",IF('計算'!$M6="","",'計算'!$AX6)) | Q10: =IF('計算'!$C6="","",IF('計算'!$M6="","",'計算'!$AY6)) | R10: =IF('計算'!$C6="","",IF('計算'!$M6="","",'計算'!$AZ6)) | S10: =IF('計算'!$C6="","",IF('計算'!$M6="","",'計算'!$BA6)) | T10: =IF('計算'!$C6="","",IF('計算'!$M6="","",'計算'!$BB6)) | U10: =IF('計算'!$C6="","",IF('計算'!$M6="","",'計算'!$BC6)) | V10: =IF('計算'!$C6="","",IF('計算'!$M6="","",'計算'!$BD6)) | W10: =IF('計算'!$C6="","",IF('計算'!$M6="","",'計算'!$BE6)) | X10: =IF('計算'!$C6="","",IF('計算'!$M6="","",'計算'!$BF6)) | Y10: =IF('計算'!$C6="","",IF('計算'!$M6="","",'計算'!$BG6)) | Z10: =IF('計算'!$C6="","",IF('計算'!$M6="","",'計算'!$BH6)) | AA10: =IF('計算'!$C6="","",IF('計算'!$M6="","",'計算'!$BI6)) | AB10: =IF('計算'!$C6="","",IF('計算'!$M6="","",'計算'!$BJ6)) | AC10: =IF('計算'!$C6="","",IF('計算'!$M6="","",'計算'!$BK6)) | AF10: =IF('計算'!$C6="","",'計算'!$C6) | AG10: =IF('計算'!$C6="","",'計算'!$F6)
B11: =IF('計算'!$C7="","",'計算'!$B7) | C11: =IF('計算'!$C7="","",'計算'!$D7) | D11: =IF('計算'!$C7="","",'計算'!$O7) | E11: =IF('計算'!$C7="","",'計算'!$L7) | F11: =IF('計算'!$C7="","",'計算'!$CD7) | G11: =IF('計算'!$C7="","",'計算'!$CA7) | H11: =IF('計算'!$C7="","",'計算'!$CP7) | K11: =IF('計算'!$C7="","",'計算'!$CR7) | L11: =IF('計算'!$C7="","",'計算'!$CF7) | O11: =IF('計算'!$C7="","",'計算'!$CQ7) | P11: =IF('計算'!$C7="","",IF('計算'!$M7="","",'計算'!$AX7)) | Q11: =IF('計算'!$C7="","",IF('計算'!$M7="","",'計算'!$AY7)) | R11: =IF('計算'!$C7="","",IF('計算'!$M7="","",'計算'!$AZ7)) | S11: =IF('計算'!$C7="","",IF('計算'!$M7="","",'計算'!$BA7)) | T11: =IF('計算'!$C7="","",IF('計算'!$M7="","",'計算'!$BB7)) | U11: =IF('計算'!$C7="","",IF('計算'!$M7="","",'計算'!$BC7)) | V11: =IF('計算'!$C7="","",IF('計算'!$M7="","",'計算'!$BD7)) | W11: =IF('計算'!$C7="","",IF('計算'!$M7="","",'計算'!$BE7)) | X11: =IF('計算'!$C7="","",IF('計算'!$M7="","",'計算'!$BF7)) | Y11: =IF('計算'!$C7="","",IF('計算'!$M7="","",'計算'!$BG7)) | Z11: =IF('計算'!$C7="","",IF('計算'!$M7="","",'計算'!$BH7)) | AA11: =IF('計算'!$C7="","",IF('計算'!$M7="","",'計算'!$BI7)) | AB11: =IF('計算'!$C7="","",IF('計算'!$M7="","",'計算'!$BJ7)) | AC11: =IF('計算'!$C7="","",IF('計算'!$M7="","",'計算'!$BK7)) | AF11: =IF('計算'!$C7="","",'計算'!$C7) | AG11: =IF('計算'!$C7="","",'計算'!$F7)
B12: =IF('計算'!$C8="","",'計算'!$B8) | C12: =IF('計算'!$C8="","",'計算'!$D8) | D12: =IF('計算'!$C8="","",'計算'!$O8) | E12: =IF('計算'!$C8="","",'計算'!$L8) | F12: =IF('計算'!$C8="","",'計算'!$CD8) | G12: =IF('計算'!$C8="","",'計算'!$CA8) | H12: =IF('計算'!$C8="","",'計算'!$CP8) | K12: =IF('計算'!$C8="","",'計算'!$CR8) | L12: =IF('計算'!$C8="","",'計算'!$CF8) | O12: =IF('計算'!$C8="","",'計算'!$CQ8) | P12: =IF('計算'!$C8="","",IF('計算'!$M8="","",'計算'!$AX8)) | Q12: =IF('計算'!$C8="","",IF('計算'!$M8="","",'計算'!$AY8)) | R12: =IF('計算'!$C8="","",IF('計算'!$M8="","",'計算'!$AZ8)) | S12: =IF('計算'!$C8="","",IF('計算'!$M8="","",'計算'!$BA8)) | T12: =IF('計算'!$C8="","",IF('計算'!$M8="","",'計算'!$BB8)) | U12: =IF('計算'!$C8="","",IF('計算'!$M8="","",'計算'!$BC8)) | V12: =IF('計算'!$C8="","",IF('計算'!$M8="","",'計算'!$BD8)) | W12: =IF('計算'!$C8="","",IF('計算'!$M8="","",'計算'!$BE8)) | X12: =IF('計算'!$C8="","",IF('計算'!$M8="","",'計算'!$BF8)) | Y12: =IF('計算'!$C8="","",IF('計算'!$M8="","",'計算'!$BG8)) | Z12: =IF('計算'!$C8="","",IF('計算'!$M8="","",'計算'!$BH8)) | AA12: =IF('計算'!$C8="","",IF('計算'!$M8="","",'計算'!$BI8)) | AB12: =IF('計算'!$C8="","",IF('計算'!$M8="","",'計算'!$BJ8)) | AC12: =IF('計算'!$C8="","",IF('計算'!$M8="","",'計算'!$BK8)) | AF12: =IF('計算'!$C8="","",'計算'!$C8) | AG12: =IF('計算'!$C8="","",'計算'!$F8)
B13: =IF('計算'!$C9="","",'計算'!$B9) | C13: =IF('計算'!$C9="","",'計算'!$D9) | D13: =IF('計算'!$C9="","",'計算'!$O9) | E13: =IF('計算'!$C9="","",'計算'!$L9) | F13: =IF('計算'!$C9="","",'計算'!$CD9) | G13: =IF('計算'!$C9="","",'計算'!$CA9) | H13: =IF('計算'!$C9="","",'計算'!$CP9) | K13: =IF('計算'!$C9="","",'計算'!$CR9) | L13: =IF('計算'!$C9="","",'計算'!$CF9) | O13: =IF('計算'!$C9="","",'計算'!$CQ9) | P13: =IF('計算'!$C9="","",IF('計算'!$M9="","",'計算'!$AX9)) | Q13: =IF('計算'!$C9="","",IF('計算'!$M9="","",'計算'!$AY9)) | R13: =IF('計算'!$C9="","",IF('計算'!$M9="","",'計算'!$AZ9)) | S13: =IF('計算'!$C9="","",IF('計算'!$M9="","",'計算'!$BA9)) | T13: =IF('計算'!$C9="","",IF('計算'!$M9="","",'計算'!$BB9)) | U13: =IF('計算'!$C9="","",IF('計算'!$M9="","",'計算'!$BC9)) | V13: =IF('計算'!$C9="","",IF('計算'!$M9="","",'計算'!$BD9)) | W13: =IF('計算'!$C9="","",IF('計算'!$M9="","",'計算'!$BE9)) | X13: =IF('計算'!$C9="","",IF('計算'!$M9="","",'計算'!$BF9)) | Y13: =IF('計算'!$C9="","",IF('計算'!$M9="","",'計算'!$BG9)) | Z13: =IF('計算'!$C9="","",IF('計算'!$M9="","",'計算'!$BH9)) | AA13: =IF('計算'!$C9="","",IF('計算'!$M9="","",'計算'!$BI9)) | AB13: =IF('計算'!$C9="","",IF('計算'!$M9="","",'計算'!$BJ9)) | AC13: =IF('計算'!$C9="","",IF('計算'!$M9="","",'計算'!$BK9)) | AF13: =IF('計算'!$C9="","",'計算'!$C9) | AG13: =IF('計算'!$C9="","",'計算'!$F9)
B14: =IF('計算'!$C10="","",'計算'!$B10) | C14: =IF('計算'!$C10="","",'計算'!$D10) | D14: =IF('計算'!$C10="","",'計算'!$O10) | E14: =IF('計算'!$C10="","",'計算'!$L10) | F14: =IF('計算'!$C10="","",'計算'!$CD10) | G14: =IF('計算'!$C10="","",'計算'!$CA10) | H14: =IF('計算'!$C10="","",'計算'!$CP10) | K14: =IF('計算'!$C10="","",'計算'!$CR10) | L14: =IF('計算'!$C10="","",'計算'!$CF10) | O14: =IF('計算'!$C10="","",'計算'!$CQ10) | P14: =IF('計算'!$C10="","",IF('計算'!$M10="","",'計算'!$AX10)) | Q14: =IF('計算'!$C10="","",IF('計算'!$M10="","",'計算'!$AY10)) | R14: =IF('計算'!$C10="","",IF('計算'!$M10="","",'計算'!$AZ10)) | S14: =IF('計算'!$C10="","",IF('計算'!$M10="","",'計算'!$BA10)) | T14: =IF('計算'!$C10="","",IF('計算'!$M10="","",'計算'!$BB10)) | U14: =IF('計算'!$C10="","",IF('計算'!$M10="","",'計算'!$BC10)) | V14: =IF('計算'!$C10="","",IF('計算'!$M10="","",'計算'!$BD10)) | W14: =IF('計算'!$C10="","",IF('計算'!$M10="","",'計算'!$BE10)) | X14: =IF('計算'!$C10="","",IF('計算'!$M10="","",'計算'!$BF10)) | Y14: =IF('計算'!$C10="","",IF('計算'!$M10="","",'計算'!$BG10)) | Z14: =IF('計算'!$C10="","",IF('計算'!$M10="","",'計算'!$BH10)) | AA14: =IF('計算'!$C10="","",IF('計算'!$M10="","",'計算'!$BI10)) | AB14: =IF('計算'!$C10="","",IF('計算'!$M10="","",'計算'!$BJ10)) | AC14: =IF('計算'!$C10="","",IF('計算'!$M10="","",'計算'!$BK10)) | AF14: =IF('計算'!$C10="","",'計算'!$C10) | AG14: =IF('計算'!$C10="","",'計算'!$F10)
B15: =IF('計算'!$C11="","",'計算'!$B11) | C15: =IF('計算'!$C11="","",'計算'!$D11) | D15: =IF('計算'!$C11="","",'計算'!$O11) | E15: =IF('計算'!$C11="","",'計算'!$L11) | F15: =IF('計算'!$C11="","",'計算'!$CD11) | G15: =IF('計算'!$C11="","",'計算'!$CA11) | H15: =IF('計算'!$C11="","",'計算'!$CP11) | K15: =IF('計算'!$C11="","",'計算'!$CR11) | L15: =IF('計算'!$C11="","",'計算'!$CF11) | O15: =IF('計算'!$C11="","",'計算'!$CQ11) | P15: =IF('計算'!$C11="","",IF('計算'!$M11="","",'計算'!$AX11)) | Q15: =IF('計算'!$C11="","",IF('計算'!$M11="","",'計算'!$AY11)) | R15: =IF('計算'!$C11="","",IF('計算'!$M11="","",'計算'!$AZ11)) | S15: =IF('計算'!$C11="","",IF('計算'!$M11="","",'計算'!$BA11)) | T15: =IF('計算'!$C11="","",IF('計算'!$M11="","",'計算'!$BB11)) | U15: =IF('計算'!$C11="","",IF('計算'!$M11="","",'計算'!$BC11)) | V15: =IF('計算'!$C11="","",IF('計算'!$M11="","",'計算'!$BD11)) | W15: =IF('計算'!$C11="","",IF('計算'!$M11="","",'計算'!$BE11)) | X15: =IF('計算'!$C11="","",IF('計算'!$M11="","",'計算'!$BF11)) | Y15: =IF('計算'!$C11="","",IF('計算'!$M11="","",'計算'!$BG11)) | Z15: =IF('計算'!$C11="","",IF('計算'!$M11="","",'計算'!$BH11)) | AA15: =IF('計算'!$C11="","",IF('計算'!$M11="","",'計算'!$BI11)) | AB15: =IF('計算'!$C11="","",IF('計算'!$M11="","",'計算'!$BJ11)) | AC15: =IF('計算'!$C11="","",IF('計算'!$M11="","",'計算'!$BK11)) | AF15: =IF('計算'!$C11="","",'計算'!$C11) | AG15: =IF('計算'!$C11="","",'計算'!$F11)
B16: =IF('計算'!$C12="","",'計算'!$B12) | C16: =IF('計算'!$C12="","",'計算'!$D12) | D16: =IF('計算'!$C12="","",'計算'!$O12) | E16: =IF('計算'!$C12="","",'計算'!$L12) | F16: =IF('計算'!$C12="","",'計算'!$CD12) | G16: =IF('計算'!$C12="","",'計算'!$CA12) | H16: =IF('計算'!$C12="","",'計算'!$CP12) | K16: =IF('計算'!$C12="","",'計算'!$CR12) | L16: =IF('計算'!$C12="","",'計算'!$CF12) | O16: =IF('計算'!$C12="","",'計算'!$CQ12) | P16: =IF('計算'!$C12="","",IF('計算'!$M12="","",'計算'!$AX12)) | Q16: =IF('計算'!$C12="","",IF('計算'!$M12="","",'計算'!$AY12)) | R16: =IF('計算'!$C12="","",IF('計算'!$M12="","",'計算'!$AZ12)) | S16: =IF('計算'!$C12="","",IF('計算'!$M12="","",'計算'!$BA12)) | T16: =IF('計算'!$C12="","",IF('計算'!$M12="","",'計算'!$BB12)) | U16: =IF('計算'!$C12="","",IF('計算'!$M12="","",'計算'!$BC12)) | V16: =IF('計算'!$C12="","",IF('計算'!$M12="","",'計算'!$BD12)) | W16: =IF('計算'!$C12="","",IF('計算'!$M12="","",'計算'!$BE12)) | X16: =IF('計算'!$C12="","",IF('計算'!$M12="","",'計算'!$BF12)) | Y16: =IF('計算'!$C12="","",IF('計算'!$M12="","",'計算'!$BG12)) | Z16: =IF('計算'!$C12="","",IF('計算'!$M12="","",'計算'!$BH12)) | AA16: =IF('計算'!$C12="","",IF('計算'!$M12="","",'計算'!$BI12)) | AB16: =IF('計算'!$C12="","",IF('計算'!$M12="","",'計算'!$BJ12)) | AC16: =IF('計算'!$C12="","",IF('計算'!$M12="","",'計算'!$BK12)) | AF16: =IF('計算'!$C12="","",'計算'!$C12) | AG16: =IF('計算'!$C12="","",'計算'!$F12)
B17: =IF('計算'!$C13="","",'計算'!$B13) | C17: =IF('計算'!$C13="","",'計算'!$D13) | D17: =IF('計算'!$C13="","",'計算'!$O13) | E17: =IF('計算'!$C13="","",'計算'!$L13) | F17: =IF('計算'!$C13="","",'計算'!$CD13) | G17: =IF('計算'!$C13="","",'計算'!$CA13) | H17: =IF('計算'!$C13="","",'計算'!$CP13) | K17: =IF('計算'!$C13="","",'計算'!$CR13) | L17: =IF('計算'!$C13="","",'計算'!$CF13) | O17: =IF('計算'!$C13="","",'計算'!$CQ13) | P17: =IF('計算'!$C13="","",IF('計算'!$M13="","",'計算'!$AX13)) | Q17: =IF('計算'!$C13="","",IF('計算'!$M13="","",'計算'!$AY13)) | R17: =IF('計算'!$C13="","",IF('計算'!$M13="","",'計算'!$AZ13)) | S17: =IF('計算'!$C13="","",IF('計算'!$M13="","",'計算'!$BA13)) | T17: =IF('計算'!$C13="","",IF('計算'!$M13="","",'計算'!$BB13)) | U17: =IF('計算'!$C13="","",IF('計算'!$M13="","",'計算'!$BC13)) | V17: =IF('計算'!$C13="","",IF('計算'!$M13="","",'計算'!$BD13)) | W17: =IF('計算'!$C13="","",IF('計算'!$M13="","",'計算'!$BE13)) | X17: =IF('計算'!$C13="","",IF('計算'!$M13="","",'計算'!$BF13)) | Y17: =IF('計算'!$C13="","",IF('計算'!$M13="","",'計算'!$BG13)) | Z17: =IF('計算'!$C13="","",IF('計算'!$M13="","",'計算'!$BH13)) | AA17: =IF('計算'!$C13="","",IF('計算'!$M13="","",'計算'!$BI13)) | AB17: =IF('計算'!$C13="","",IF('計算'!$M13="","",'計算'!$BJ13)) | AC17: =IF('計算'!$C13="","",IF('計算'!$M13="","",'計算'!$BK13)) | AF17: =IF('計算'!$C13="","",'計算'!$C13) | AG17: =IF('計算'!$C13="","",'計算'!$F13)
B18: =IF('計算'!$C14="","",'計算'!$B14) | C18: =IF('計算'!$C14="","",'計算'!$D14) | D18: =IF('計算'!$C14="","",'計算'!$O14) | E18: =IF('計算'!$C14="","",'計算'!$L14) | F18: =IF('計算'!$C14="","",'計算'!$CD14) | G18: =IF('計算'!$C14="","",'計算'!$CA14) | H18: =IF('計算'!$C14="","",'計算'!$CP14) | K18: =IF('計算'!$C14="","",'計算'!$CR14) | L18: =IF('計算'!$C14="","",'計算'!$CF14) | O18: =IF('計算'!$C14="","",'計算'!$CQ14) | P18: =IF('計算'!$C14="","",IF('計算'!$M14="","",'計算'!$AX14)) | Q18: =IF('計算'!$C14="","",IF('計算'!$M14="","",'計算'!$AY14)) | R18: =IF('計算'!$C14="","",IF('計算'!$M14="","",'計算'!$AZ14)) | S18: =IF('計算'!$C14="","",IF('計算'!$M14="","",'計算'!$BA14)) | T18: =IF('計算'!$C14="","",IF('計算'!$M14="","",'計算'!$BB14)) | U18: =IF('計算'!$C14="","",IF('計算'!$M14="","",'計算'!$BC14)) | V18: =IF('計算'!$C14="","",IF('計算'!$M14="","",'計算'!$BD14)) | W18: =IF('計算'!$C14="","",IF('計算'!$M14="","",'計算'!$BE14)) | X18: =IF('計算'!$C14="","",IF('計算'!$M14="","",'計算'!$BF14)) | Y18: =IF('計算'!$C14="","",IF('計算'!$M14="","",'計算'!$BG14)) | Z18: =IF('計算'!$C14="","",IF('計算'!$M14="","",'計算'!$BH14)) | AA18: =IF('計算'!$C14="","",IF('計算'!$M14="","",'計算'!$BI14)) | AB18: =IF('計算'!$C14="","",IF('計算'!$M14="","",'計算'!$BJ14)) | AC18: =IF('計算'!$C14="","",IF('計算'!$M14="","",'計算'!$BK14)) | AF18: =IF('計算'!$C14="","",'計算'!$C14) | AG18: =IF('計算'!$C14="","",'計算'!$F14)
B19: =IF('計算'!$C15="","",'計算'!$B15) | C19: =IF('計算'!$C15="","",'計算'!$D15) | D19: =IF('計算'!$C15="","",'計算'!$O15) | E19: =IF('計算'!$C15="","",'計算'!$L15) | F19: =IF('計算'!$C15="","",'計算'!$CD15) | G19: =IF('計算'!$C15="","",'計算'!$CA15) | H19: =IF('計算'!$C15="","",'計算'!$CP15) | K19: =IF('計算'!$C15="","",'計算'!$CR15) | L19: =IF('計算'!$C15="","",'計算'!$CF15) | O19: =IF('計算'!$C15="","",'計算'!$CQ15) | P19: =IF('計算'!$C15="","",IF('計算'!$M15="","",'計算'!$AX15)) | Q19: =IF('計算'!$C15="","",IF('計算'!$M15="","",'計算'!$AY15)) | R19: =IF('計算'!$C15="","",IF('計算'!$M15="","",'計算'!$AZ15)) | S19: =IF('計算'!$C15="","",IF('計算'!$M15="","",'計算'!$BA15)) | T19: =IF('計算'!$C15="","",IF('計算'!$M15="","",'計算'!$BB15)) | U19: =IF('計算'!$C15="","",IF('計算'!$M15="","",'計算'!$BC15)) | V19: =IF('計算'!$C15="","",IF('計算'!$M15="","",'計算'!$BD15)) | W19: =IF('計算'!$C15="","",IF('計算'!$M15="","",'計算'!$BE15)) | X19: =IF('計算'!$C15="","",IF('計算'!$M15="","",'計算'!$BF15)) | Y19: =IF('計算'!$C15="","",IF('計算'!$M15="","",'計算'!$BG15)) | Z19: =IF('計算'!$C15="","",IF('計算'!$M15="","",'計算'!$BH15)) | AA19: =IF('計算'!$C15="","",IF('計算'!$M15="","",'計算'!$BI15)) | AB19: =IF('計算'!$C15="","",IF('計算'!$M15="","",'計算'!$BJ15)) | AC19: =IF('計算'!$C15="","",IF('計算'!$M15="","",'計算'!$BK15)) | AF19: =IF('計算'!$C15="","",'計算'!$C15) | AG19: =IF('計算'!$C15="","",'計算'!$F15)
B20: =IF('計算'!$C16="","",'計算'!$B16) | C20: =IF('計算'!$C16="","",'計算'!$D16) | D20: =IF('計算'!$C16="","",'計算'!$O16) | E20: =IF('計算'!$C16="","",'計算'!$L16) | F20: =IF('計算'!$C16="","",'計算'!$CD16) | G20: =IF('計算'!$C16="","",'計算'!$CA16) | H20: =IF('計算'!$C16="","",'計算'!$CP16) | K20: =IF('計算'!$C16="","",'計算'!$CR16) | L20: =IF('計算'!$C16="","",'計算'!$CF16) | O20: =IF('計算'!$C16="","",'計算'!$CQ16) | P20: =IF('計算'!$C16="","",IF('計算'!$M16="","",'計算'!$AX16)) | Q20: =IF('計算'!$C16="","",IF('計算'!$M16="","",'計算'!$AY16)) | R20: =IF('計算'!$C16="","",IF('計算'!$M16="","",'計算'!$AZ16)) | S20: =IF('計算'!$C16="","",IF('計算'!$M16="","",'計算'!$BA16)) | T20: =IF('計算'!$C16="","",IF('計算'!$M16="","",'計算'!$BB16)) | U20: =IF('計算'!$C16="","",IF('計算'!$M16="","",'計算'!$BC16)) | V20: =IF('計算'!$C16="","",IF('計算'!$M16="","",'計算'!$BD16)) | W20: =IF('計算'!$C16="","",IF('計算'!$M16="","",'計算'!$BE16)) | X20: =IF('計算'!$C16="","",IF('計算'!$M16="","",'計算'!$BF16)) | Y20: =IF('計算'!$C16="","",IF('計算'!$M16="","",'計算'!$BG16)) | Z20: =IF('計算'!$C16="","",IF('計算'!$M16="","",'計算'!$BH16)) | AA20: =IF('計算'!$C16="","",IF('計算'!$M16="","",'計算'!$BI16)) | AB20: =IF('計算'!$C16="","",IF('計算'!$M16="","",'計算'!$BJ16)) | AC20: =IF('計算'!$C16="","",IF('計算'!$M16="","",'計算'!$BK16)) | AF20: =IF('計算'!$C16="","",'計算'!$C16) | AG20: =IF('計算'!$C16="","",'計算'!$F16)
B21: =IF('計算'!$C17="","",'計算'!$B17) | C21: =IF('計算'!$C17="","",'計算'!$D17) | D21: =IF('計算'!$C17="","",'計算'!$O17) | E21: =IF('計算'!$C17="","",'計算'!$L17) | F21: =IF('計算'!$C17="","",'計算'!$CD17) | G21: =IF('計算'!$C17="","",'計算'!$CA17) | H21: =IF('計算'!$C17="","",'計算'!$CP17) | K21: =IF('計算'!$C17="","",'計算'!$CR17) | L21: =IF('計算'!$C17="","",'計算'!$CF17) | O21: =IF('計算'!$C17="","",'計算'!$CQ17) | P21: =IF('計算'!$C17="","",IF('計算'!$M17="","",'計算'!$AX17)) | Q21: =IF('計算'!$C17="","",IF('計算'!$M17="","",'計算'!$AY17)) | R21: =IF('計算'!$C17="","",IF('計算'!$M17="","",'計算'!$AZ17)) | S21: =IF('計算'!$C17="","",IF('計算'!$M17="","",'計算'!$BA17)) | T21: =IF('計算'!$C17="","",IF('計算'!$M17="","",'計算'!$BB17)) | U21: =IF('計算'!$C17="","",IF('計算'!$M17="","",'計算'!$BC17)) | V21: =IF('計算'!$C17="","",IF('計算'!$M17="","",'計算'!$BD17)) | W21: =IF('計算'!$C17="","",IF('計算'!$M17="","",'計算'!$BE17)) | X21: =IF('計算'!$C17="","",IF('計算'!$M17="","",'計算'!$BF17)) | Y21: =IF('計算'!$C17="","",IF('計算'!$M17="","",'計算'!$BG17)) | Z21: =IF('計算'!$C17="","",IF('計算'!$M17="","",'計算'!$BH17)) | AA21: =IF('計算'!$C17="","",IF('計算'!$M17="","",'計算'!$BI17)) | AB21: =IF('計算'!$C17="","",IF('計算'!$M17="","",'計算'!$BJ17)) | AC21: =IF('計算'!$C17="","",IF('計算'!$M17="","",'計算'!$BK17)) | AF21: =IF('計算'!$C17="","",'計算'!$C17) | AG21: =IF('計算'!$C17="","",'計算'!$F17)
... B409: =IF('計算'!$C405="","",'計算'!$B405) | C409: =IF('計算'!$C405="","",'計算'!$D405) | D409: =IF('計算'!$C405="","",'計算'!$O405) | E409: =IF('計算'!$C405="","",'計算'!$L405) | F409: =IF('計算'!$C405="","",'計算'!$CD405) | G409: =IF('計算'!$C405="","",'計算'!$CA405) | H409: =IF('計算'!$C405="","",'計算'!$CP405) | K409: =IF('計算'!$C405="","",'計算'!$CR405) | L409: =IF('計算'!$C405="","",'計算'!$CF405) | O409: =IF('計算'!$C405="","",'計算'!$CQ405) | P409: =IF('計算'!$C405="","",IF('計算'!$M405="","",'計算'!$AX405)) | Q409: =IF('計算'!$C405="","",IF('計算'!$M405="","",'計算'!$AY405)) | R409: =IF('計算'!$C405="","",IF('計算'!$M405="","",'計算'!$AZ405)) | S409: =IF('計算'!$C405="","",IF('計算'!$M405="","",'計算'!$BA405)) | T409: =IF('計算'!$C405="","",IF('計算'!$M405="","",'計算'!$BB405)) | U409: =IF('計算'!$C405="","",IF('計算'!$M405="","",'計算'!$BC405)) | V409: =IF('計算'!$C405="","",IF('計算'!$M405="","",'計算'!$BD405)) | W409: =IF('計算'!$C405="","",IF('計算'!$M405="","",'計算'!$BE405)) | X409: =IF('計算'!$C405="","",IF('計算'!$M405="","",'計算'!$BF405)) | Y409: =IF('計算'!$C405="","",IF('計算'!$M405="","",'計算'!$BG405)) | Z409: =IF('計算'!$C405="","",IF('計算'!$M405="","",'計算'!$BH405)) | AA409: =IF('計算'!$C405="","",IF('計算'!$M405="","",'計算'!$BI405)) | AB409: =IF('計算'!$C405="","",IF('計算'!$M405="","",'計算'!$BJ405)) | AC409: =IF('計算'!$C405="","",IF('計算'!$M405="","",'計算'!$BK405)) | AF409: =IF('計算'!$C405="","",'計算'!$C405) | AG409: =IF('計算'!$C405="","",'計算'!$F405)

Sheet ③発注書
B1: STEP 3 発注書を印刷する | K1: ◀ ホーム
B2: 発 注 書
B3: STEP 2 で入庫を入れた商品がここに集まります（⚠ の行は載りません）。仕入先を選んで印刷してください。
B4: 仕入先 | C4: すべて | G4: ← ここを選ぶ
B5: 発注日 | C5: ='設定'!$C$6
B6: 発注元 | C6: ='設定'!$C$4&" "&'設定'!$C$5
B7: 担当者 | C7: ='設定'!$C$9
H8: 合計（税抜） | J8: =SUM($J$11:$J$110)
B10: No | C10: 仕入先 | D10: 商品コード | E10: 商品名 | F10: 入庫日(届く日) | G10: 単位 | H10: 発注数 | I10: 単価 | J10: 金額
B11: =IF(1<=MAX('計算'!$CT$6:$CT$405)+MAX('計算'!$CU$6:$CU$405),1,"") | C11: =IF($B11="","",IF(1<=MAX('計算'!$CT$6:$CT$405),IFERROR(INDEX('計算'!$F$6:$F$405,MATCH(1,'計算'!$CT$6:$CT$405,0)),""),IFERROR(INDEX('計算'!$F$6:$F$405,MATCH(1-MAX('計算'!$CT$6:$CT$405),'計算'!$CU$6:$CU$405,0)),""))) | D11: =IF($B11="","",IF(1<=MAX('計算'!$CT$6:$CT$405),IFERROR(INDEX('計算'!$C$6:$C$405,MATCH(1,'計算'!$CT$6:$CT$405,0))&"",""),IFERROR(INDEX('計算'!$C$6:$C$405,MATCH(1-MAX('計算'!$CT$6:$CT$405),'計算'!$CU$6:$CU$405,0))&"",""))) | E11: =IF($B11="","",IF(1<=MAX('計算'!$CT$6:$CT$405),IFERROR(INDEX('計算'!$D$6:$D$405,MATCH(1,'計算'!$CT$6:$CT$405,0)),""),IFERROR(INDEX('計算'!$D$6:$D$405,MATCH(1-MAX('計算'!$CT$6:$CT$405),'計算'!$CU$6:$CU$405,0)),""))) | F11: =IF($B11="","",IF(1<=MAX('計算'!$CT$6:$CT$405),IFERROR(INDEX('計算'!$P$6:$P$405,MATCH(1,'計算'!$CT$6:$CT$405,0)),""),IFERROR(INDEX('計算'!$S$6:$S$405,MATCH(1-MAX('計算'!$CT$6:$CT$405),'計算'!$CU$6:$CU$405,0)),""))) | G11: =IF($B11="","",IF(1<=MAX('計算'!$CT$6:$CT$405),IFERROR(INDEX('計算'!$CR$6:$CR$405,MATCH(1,'計算'!$CT$6:$CT$405,0)),""),IFERROR(INDEX('計算'!$CR$6:$CR$405,MATCH(1-MAX('計算'!$CT$6:$CT$405),'計算'!$CU$6:$CU$405,0)),""))) | H11: =IF($B11="","",IF(1<=MAX('計算'!$CT$6:$CT$405),IFERROR(INDEX('計算'!$Q$6:$Q$405,MATCH(1,'計算'!$CT$6:$CT$405,0)),""),IFERROR(INDEX('計算'!$T$6:$T$405,MATCH(1-MAX('計算'!$CT$6:$CT$405),'計算'!$CU$6:$CU$405,0)),""))) | I11: =IF($B11="","",IF(1<=MAX('計算'!$CT$6:$CT$405),IFERROR(INDEX('計算'!$H$6:$H$405,MATCH(1,'計算'!$CT$6:$CT$405,0)),""),IFERROR(INDEX('計算'!$H$6:$H$405,MATCH(1-MAX('計算'!$CT$6:$CT$405),'計算'!$CU$6:$CU$405,0)),""))) | J11: =IF($B11="","",N($H11)*IFERROR(INDEX('計算'!$G$6:$G$405,IF(1<=MAX('計算'!$CT$6:$CT$405),MATCH(1,'計算'!$CT$6:$CT$405,0),MATCH(1-MAX('計算'!$CT$6:$CT$405),'計算'!$CU$6:$CU$405,0))),1)*N($I11))
B12: =IF(2<=MAX('計算'!$CT$6:$CT$405)+MAX('計算'!$CU$6:$CU$405),2,"") | C12: =IF($B12="","",IF(2<=MAX('計算'!$CT$6:$CT$405),IFERROR(INDEX('計算'!$F$6:$F$405,MATCH(2,'計算'!$CT$6:$CT$405,0)),""),IFERROR(INDEX('計算'!$F$6:$F$405,MATCH(2-MAX('計算'!$CT$6:$CT$405),'計算'!$CU$6:$CU$405,0)),""))) | D12: =IF($B12="","",IF(2<=MAX('計算'!$CT$6:$CT$405),IFERROR(INDEX('計算'!$C$6:$C$405,MATCH(2,'計算'!$CT$6:$CT$405,0))&"",""),IFERROR(INDEX('計算'!$C$6:$C$405,MATCH(2-MAX('計算'!$CT$6:$CT$405),'計算'!$CU$6:$CU$405,0))&"",""))) | E12: =IF($B12="","",IF(2<=MAX('計算'!$CT$6:$CT$405),IFERROR(INDEX('計算'!$D$6:$D$405,MATCH(2,'計算'!$CT$6:$CT$405,0)),""),IFERROR(INDEX('計算'!$D$6:$D$405,MATCH(2-MAX('計算'!$CT$6:$CT$405),'計算'!$CU$6:$CU$405,0)),""))) | F12: =IF($B12="","",IF(2<=MAX('計算'!$CT$6:$CT$405),IFERROR(INDEX('計算'!$P$6:$P$405,MATCH(2,'計算'!$CT$6:$CT$405,0)),""),IFERROR(INDEX('計算'!$S$6:$S$405,MATCH(2-MAX('計算'!$CT$6:$CT$405),'計算'!$CU$6:$CU$405,0)),""))) | G12: =IF($B12="","",IF(2<=MAX('計算'!$CT$6:$CT$405),IFERROR(INDEX('計算'!$CR$6:$CR$405,MATCH(2,'計算'!$CT$6:$CT$405,0)),""),IFERROR(INDEX('計算'!$CR$6:$CR$405,MATCH(2-MAX('計算'!$CT$6:$CT$405),'計算'!$CU$6:$CU$405,0)),""))) | H12: =IF($B12="","",IF(2<=MAX('計算'!$CT$6:$CT$405),IFERROR(INDEX('計算'!$Q$6:$Q$405,MATCH(2,'計算'!$CT$6:$CT$405,0)),""),IFERROR(INDEX('計算'!$T$6:$T$405,MATCH(2-MAX('計算'!$CT$6:$CT$405),'計算'!$CU$6:$CU$405,0)),""))) | I12: =IF($B12="","",IF(2<=MAX('計算'!$CT$6:$CT$405),IFERROR(INDEX('計算'!$H$6:$H$405,MATCH(2,'計算'!$CT$6:$CT$405,0)),""),IFERROR(INDEX('計算'!$H$6:$H$405,MATCH(2-MAX('計算'!$CT$6:$CT$405),'計算'!$CU$6:$CU$405,0)),""))) | J12: =IF($B12="","",N($H12)*IFERROR(INDEX('計算'!$G$6:$G$405,IF(2<=MAX('計算'!$CT$6:$CT$405),MATCH(2,'計算'!$CT$6:$CT$405,0),MATCH(2-MAX('計算'!$CT$6:$CT$405),'計算'!$CU$6:$CU$405,0))),1)*N($I12))
B13: =IF(3<=MAX('計算'!$CT$6:$CT$405)+MAX('計算'!$CU$6:$CU$405),3,"") | C13: =IF($B13="","",IF(3<=MAX('計算'!$CT$6:$CT$405),IFERROR(INDEX('計算'!$F$6:$F$405,MATCH(3,'計算'!$CT$6:$CT$405,0)),""),IFERROR(INDEX('計算'!$F$6:$F$405,MATCH(3-MAX('計算'!$CT$6:$CT$405),'計算'!$CU$6:$CU$405,0)),""))) | D13: =IF($B13="","",IF(3<=MAX('計算'!$CT$6:$CT$405),IFERROR(INDEX('計算'!$C$6:$C$405,MATCH(3,'計算'!$CT$6:$CT$405,0))&"",""),IFERROR(INDEX('計算'!$C$6:$C$405,MATCH(3-MAX('計算'!$CT$6:$CT$405),'計算'!$CU$6:$CU$405,0))&"",""))) | E13: =IF($B13="","",IF(3<=MAX('計算'!$CT$6:$CT$405),IFERROR(INDEX('計算'!$D$6:$D$405,MATCH(3,'計算'!$CT$6:$CT$405,0)),""),IFERROR(INDEX('計算'!$D$6:$D$405,MATCH(3-MAX('計算'!$CT$6:$CT$405),'計算'!$CU$6:$CU$405,0)),""))) | F13: =IF($B13="","",IF(3<=MAX('計算'!$CT$6:$CT$405),IFERROR(INDEX('計算'!$P$6:$P$405,MATCH(3,'計算'!$CT$6:$CT$405,0)),""),IFERROR(INDEX('計算'!$S$6:$S$405,MATCH(3-MAX('計算'!$CT$6:$CT$405),'計算'!$CU$6:$CU$405,0)),""))) | G13: =IF($B13="","",IF(3<=MAX('計算'!$CT$6:$CT$405),IFERROR(INDEX('計算'!$CR$6:$CR$405,MATCH(3,'計算'!$CT$6:$CT$405,0)),""),IFERROR(INDEX('計算'!$CR$6:$CR$405,MATCH(3-MAX('計算'!$CT$6:$CT$405),'計算'!$CU$6:$CU$405,0)),""))) | H13: =IF($B13="","",IF(3<=MAX('計算'!$CT$6:$CT$405),IFERROR(INDEX('計算'!$Q$6:$Q$405,MATCH(3,'計算'!$CT$6:$CT$405,0)),""),IFERROR(INDEX('計算'!$T$6:$T$405,MATCH(3-MAX('計算'!$CT$6:$CT$405),'計算'!$CU$6:$CU$405,0)),""))) | I13: =IF($B13="","",IF(3<=MAX('計算'!$CT$6:$CT$405),IFERROR(INDEX('計算'!$H$6:$H$405,MATCH(3,'計算'!$CT$6:$CT$405,0)),""),IFERROR(INDEX('計算'!$H$6:$H$405,MATCH(3-MAX('計算'!$CT$6:$CT$405),'計算'!$CU$6:$CU$405,0)),""))) | J13: =IF($B13="","",N($H13)*IFERROR(INDEX('計算'!$G$6:$G$405,IF(3<=MAX('計算'!$CT$6:$CT$405),MATCH(3,'計算'!$CT$6:$CT$405,0),MATCH(3-MAX('計算'!$CT$6:$CT$405),'計算'!$CU$6:$CU$405,0))),1)*N($I13))
B14: =IF(4<=MAX('計算'!$CT$6:$CT$405)+MAX('計算'!$CU$6:$CU$405),4,"") | C14: =IF($B14="","",IF(4<=MAX('計算'!$CT$6:$CT$405),IFERROR(INDEX('計算'!$F$6:$F$405,MATCH(4,'計算'!$CT$6:$CT$405,0)),""),IFERROR(INDEX('計算'!$F$6:$F$405,MATCH(4-MAX('計算'!$CT$6:$CT$405),'計算'!$CU$6:$CU$405,0)),""))) | D14: =IF($B14="","",IF(4<=MAX('計算'!$CT$6:$CT$405),IFERROR(INDEX('計算'!$C$6:$C$405,MATCH(4,'計算'!$CT$6:$CT$405,0))&"",""),IFERROR(INDEX('計算'!$C$6:$C$405,MATCH(4-MAX('計算'!$CT$6:$CT$405),'計算'!$CU$6:$CU$405,0))&"",""))) | E14: =IF($B14="","",IF(4<=MAX('計算'!$CT$6:$CT$405),IFERROR(INDEX('計算'!$D$6:$D$405,MATCH(4,'計算'!$CT$6:$CT$405,0)),""),IFERROR(INDEX('計算'!$D$6:$D$405,MATCH(4-MAX('計算'!$CT$6:$CT$405),'計算'!$CU$6:$CU$405,0)),""))) | F14: =IF($B14="","",IF(4<=MAX('計算'!$CT$6:$CT$405),IFERROR(INDEX('計算'!$P$6:$P$405,MATCH(4,'計算'!$CT$6:$CT$405,0)),""),IFERROR(INDEX('計算'!$S$6:$S$405,MATCH(4-MAX('計算'!$CT$6:$CT$405),'計算'!$CU$6:$CU$405,0)),""))) | G14: =IF($B14="","",IF(4<=MAX('計算'!$CT$6:$CT$405),IFERROR(INDEX('計算'!$CR$6:$CR$405,MATCH(4,'計算'!$CT$6:$CT$405,0)),""),IFERROR(INDEX('計算'!$CR$6:$CR$405,MATCH(4-MAX('計算'!$CT$6:$CT$405),'計算'!$CU$6:$CU$405,0)),""))) | H14: =IF($B14="","",IF(4<=MAX('計算'!$CT$6:$CT$405),IFERROR(INDEX('計算'!$Q$6:$Q$405,MATCH(4,'計算'!$CT$6:$CT$405,0)),""),IFERROR(INDEX('計算'!$T$6:$T$405,MATCH(4-MAX('計算'!$CT$6:$CT$405),'計算'!$CU$6:$CU$405,0)),""))) | I14: =IF($B14="","",IF(4<=MAX('計算'!$CT$6:$CT$405),IFERROR(INDEX('計算'!$H$6:$H$405,MATCH(4,'計算'!$CT$6:$CT$405,0)),""),IFERROR(INDEX('計算'!$H$6:$H$405,MATCH(4-MAX('計算'!$CT$6:$CT$405),'計算'!$CU$6:$CU$405,0)),""))) | J14: =IF($B14="","",N($H14)*IFERROR(INDEX('計算'!$G$6:$G$405,IF(4<=MAX('計算'!$CT$6:$CT$405),MATCH(4,'計算'!$CT$6:$CT$405,0),MATCH(4-MAX('計算'!$CT$6:$CT$405),'計算'!$CU$6:$CU$405,0))),1)*N($I14))
B15: =IF(5<=MAX('計算'!$CT$6:$CT$405)+MAX('計算'!$CU$6:$CU$405),5,"") | C15: =IF($B15="","",IF(5<=MAX('計算'!$CT$6:$CT$405),IFERROR(INDEX('計算'!$F$6:$F$405,MATCH(5,'計算'!$CT$6:$CT$405,0)),""),IFERROR(INDEX('計算'!$F$6:$F$405,MATCH(5-MAX('計算'!$CT$6:$CT$405),'計算'!$CU$6:$CU$405,0)),""))) | D15: =IF($B15="","",IF(5<=MAX('計算'!$CT$6:$CT$405),IFERROR(INDEX('計算'!$C$6:$C$405,MATCH(5,'計算'!$CT$6:$CT$405,0))&"",""),IFERROR(INDEX('計算'!$C$6:$C$405,MATCH(5-MAX('計算'!$CT$6:$CT$405),'計算'!$CU$6:$CU$405,0))&"",""))) | E15: =IF($B15="","",IF(5<=MAX('計算'!$CT$6:$CT$405),IFERROR(INDEX('計算'!$D$6:$D$405,MATCH(5,'計算'!$CT$6:$CT$405,0)),""),IFERROR(INDEX('計算'!$D$6:$D$405,MATCH(5-MAX('計算'!$CT$6:$CT$405),'計算'!$CU$6:$CU$405,0)),""))) | F15: =IF($B15="","",IF(5<=MAX('計算'!$CT$6:$CT$405),IFERROR(INDEX('計算'!$P$6:$P$405,MATCH(5,'計算'!$CT$6:$CT$405,0)),""),IFERROR(INDEX('計算'!$S$6:$S$405,MATCH(5-MAX('計算'!$CT$6:$CT$405),'計算'!$CU$6:$CU$405,0)),""))) | G15: =IF($B15="","",IF(5<=MAX('計算'!$CT$6:$CT$405),IFERROR(INDEX('計算'!$CR$6:$CR$405,MATCH(5,'計算'!$CT$6:$CT$405,0)),""),IFERROR(INDEX('計算'!$CR$6:$CR$405,MATCH(5-MAX('計算'!$CT$6:$CT$405),'計算'!$CU$6:$CU$405,0)),""))) | H15: =IF($B15="","",IF(5<=MAX('計算'!$CT$6:$CT$405),IFERROR(INDEX('計算'!$Q$6:$Q$405,MATCH(5,'計算'!$CT$6:$CT$405,0)),""),IFERROR(INDEX('計算'!$T$6:$T$405,MATCH(5-MAX('計算'!$CT$6:$CT$405),'計算'!$CU$6:$CU$405,0)),""))) | I15: =IF($B15="","",IF(5<=MAX('計算'!$CT$6:$CT$405),IFERROR(INDEX('計算'!$H$6:$H$405,MATCH(5,'計算'!$CT$6:$CT$405,0)),""),IFERROR(INDEX('計算'!$H$6:$H$405,MATCH(5-MAX('計算'!$CT$6:$CT$405),'計算'!$CU$6:$CU$405,0)),""))) | J15: =IF($B15="","",N($H15)*IFERROR(INDEX('計算'!$G$6:$G$405,IF(5<=MAX('計算'!$CT$6:$CT$405),MATCH(5,'計算'!$CT$6:$CT$405,0),MATCH(5-MAX('計算'!$CT$6:$CT$405),'計算'!$CU$6:$CU$405,0))),1)*N($I15))
B16: =IF(6<=MAX('計算'!$CT$6:$CT$405)+MAX('計算'!$CU$6:$CU$405),6,"") | C16: =IF($B16="","",IF(6<=MAX('計算'!$CT$6:$CT$405),IFERROR(INDEX('計算'!$F$6:$F$405,MATCH(6,'計算'!$CT$6:$CT$405,0)),""),IFERROR(INDEX('計算'!$F$6:$F$405,MATCH(6-MAX('計算'!$CT$6:$CT$405),'計算'!$CU$6:$CU$405,0)),""))) | D16: =IF($B16="","",IF(6<=MAX('計算'!$CT$6:$CT$405),IFERROR(INDEX('計算'!$C$6:$C$405,MATCH(6,'計算'!$CT$6:$CT$405,0))&"",""),IFERROR(INDEX('計算'!$C$6:$C$405,MATCH(6-MAX('計算'!$CT$6:$CT$405),'計算'!$CU$6:$CU$405,0))&"",""))) | E16: =IF($B16="","",IF(6<=MAX('計算'!$CT$6:$CT$405),IFERROR(INDEX('計算'!$D$6:$D$405,MATCH(6,'計算'!$CT$6:$CT$405,0)),""),IFERROR(INDEX('計算'!$D$6:$D$405,MATCH(6-MAX('計算'!$CT$6:$CT$405),'計算'!$CU$6:$CU$405,0)),""))) | F16: =IF($B16="","",IF(6<=MAX('計算'!$CT$6:$CT$405),IFERROR(INDEX('計算'!$P$6:$P$405,MATCH(6,'計算'!$CT$6:$CT$405,0)),""),IFERROR(INDEX('計算'!$S$6:$S$405,MATCH(6-MAX('計算'!$CT$6:$CT$405),'計算'!$CU$6:$CU$405,0)),""))) | G16: =IF($B16="","",IF(6<=MAX('計算'!$CT$6:$CT$405),IFERROR(INDEX('計算'!$CR$6:$CR$405,MATCH(6,'計算'!$CT$6:$CT$405,0)),""),IFERROR(INDEX('計算'!$CR$6:$CR$405,MATCH(6-MAX('計算'!$CT$6:$CT$405),'計算'!$CU$6:$CU$405,0)),""))) | H16: =IF($B16="","",IF(6<=MAX('計算'!$CT$6:$CT$405),IFERROR(INDEX('計算'!$Q$6:$Q$405,MATCH(6,'計算'!$CT$6:$CT$405,0)),""),IFERROR(INDEX('計算'!$T$6:$T$405,MATCH(6-MAX('計算'!$CT$6:$CT$405),'計算'!$CU$6:$CU$405,0)),""))) | I16: =IF($B16="","",IF(6<=MAX('計算'!$CT$6:$CT$405),IFERROR(INDEX('計算'!$H$6:$H$405,MATCH(6,'計算'!$CT$6:$CT$405,0)),""),IFERROR(INDEX('計算'!$H$6:$H$405,MATCH(6-MAX('計算'!$CT$6:$CT$405),'計算'!$CU$6:$CU$405,0)),""))) | J16: =IF($B16="","",N($H16)*IFERROR(INDEX('計算'!$G$6:$G$405,IF(6<=MAX('計算'!$CT$6:$CT$405),MATCH(6,'計算'!$CT$6:$CT$405,0),MATCH(6-MAX('計算'!$CT$6:$CT$405),'計算'!$CU$6:$CU$405,0))),1)*N($I16))
B17: =IF(7<=MAX('計算'!$CT$6:$CT$405)+MAX('計算'!$CU$6:$CU$405),7,"") | C17: =IF($B17="","",IF(7<=MAX('計算'!$CT$6:$CT$405),IFERROR(INDEX('計算'!$F$6:$F$405,MATCH(7,'計算'!$CT$6:$CT$405,0)),""),IFERROR(INDEX('計算'!$F$6:$F$405,MATCH(7-MAX('計算'!$CT$6:$CT$405),'計算'!$CU$6:$CU$405,0)),""))) | D17: =IF($B17="","",IF(7<=MAX('計算'!$CT$6:$CT$405),IFERROR(INDEX('計算'!$C$6:$C$405,MATCH(7,'計算'!$CT$6:$CT$405,0))&"",""),IFERROR(INDEX('計算'!$C$6:$C$405,MATCH(7-MAX('計算'!$CT$6:$CT$405),'計算'!$CU$6:$CU$405,0))&"",""))) | E17: =IF($B17="","",IF(7<=MAX('計算'!$CT$6:$CT$405),IFERROR(INDEX('計算'!$D$6:$D$405,MATCH(7,'計算'!$CT$6:$CT$405,0)),""),IFERROR(INDEX('計算'!$D$6:$D$405,MATCH(7-MAX('計算'!$CT$6:$CT$405),'計算'!$CU$6:$CU$405,0)),""))) | F17: =IF($B17="","",IF(7<=MAX('計算'!$CT$6:$CT$405),IFERROR(INDEX('計算'!$P$6:$P$405,MATCH(7,'計算'!$CT$6:$CT$405,0)),""),IFERROR(INDEX('計算'!$S$6:$S$405,MATCH(7-MAX('計算'!$CT$6:$CT$405),'計算'!$CU$6:$CU$405,0)),""))) | G17: =IF($B17="","",IF(7<=MAX('計算'!$CT$6:$CT$405),IFERROR(INDEX('計算'!$CR$6:$CR$405,MATCH(7,'計算'!$CT$6:$CT$405,0)),""),IFERROR(INDEX('計算'!$CR$6:$CR$405,MATCH(7-MAX('計算'!$CT$6:$CT$405),'計算'!$CU$6:$CU$405,0)),""))) | H17: =IF($B17="","",IF(7<=MAX('計算'!$CT$6:$CT$405),IFERROR(INDEX('計算'!$Q$6:$Q$405,MATCH(7,'計算'!$CT$6:$CT$405,0)),""),IFERROR(INDEX('計算'!$T$6:$T$405,MATCH(7-MAX('計算'!$CT$6:$CT$405),'計算'!$CU$6:$CU$405,0)),""))) | I17: =IF($B17="","",IF(7<=MAX('計算'!$CT$6:$CT$405),IFERROR(INDEX('計算'!$H$6:$H$405,MATCH(7,'計算'!$CT$6:$CT$405,0)),""),IFERROR(INDEX('計算'!$H$6:$H$405,MATCH(7-MAX('計算'!$CT$6:$CT$405),'計算'!$CU$6:$CU$405,0)),""))) | J17: =IF($B17="","",N($H17)*IFERROR(INDEX('計算'!$G$6:$G$405,IF(7<=MAX('計算'!$CT$6:$CT$405),MATCH(7,'計算'!$CT$6:$CT$405,0),MATCH(7-MAX('計算'!$CT$6:$CT$405),'計算'!$CU$6:$CU$405,0))),1)*N($I17))
B18: =IF(8<=MAX('計算'!$CT$6:$CT$405)+MAX('計算'!$CU$6:$CU$405),8,"") | C18: =IF($B18="","",IF(8<=MAX('計算'!$CT$6:$CT$405),IFERROR(INDEX('計算'!$F$6:$F$405,MATCH(8,'計算'!$CT$6:$CT$405,0)),""),IFERROR(INDEX('計算'!$F$6:$F$405,MATCH(8-MAX('計算'!$CT$6:$CT$405),'計算'!$CU$6:$CU$405,0)),""))) | D18: =IF($B18="","",IF(8<=MAX('計算'!$CT$6:$CT$405),IFERROR(INDEX('計算'!$C$6:$C$405,MATCH(8,'計算'!$CT$6:$CT$405,0))&"",""),IFERROR(INDEX('計算'!$C$6:$C$405,MATCH(8-MAX('計算'!$CT$6:$CT$405),'計算'!$CU$6:$CU$405,0))&"",""))) | E18: =IF($B18="","",IF(8<=MAX('計算'!$CT$6:$CT$405),IFERROR(INDEX('計算'!$D$6:$D$405,MATCH(8,'計算'!$CT$6:$CT$405,0)),""),IFERROR(INDEX('計算'!$D$6:$D$405,MATCH(8-MAX('計算'!$CT$6:$CT$405),'計算'!$CU$6:$CU$405,0)),""))) | F18: =IF($B18="","",IF(8<=MAX('計算'!$CT$6:$CT$405),IFERROR(INDEX('計算'!$P$6:$P$405,MATCH(8,'計算'!$CT$6:$CT$405,0)),""),IFERROR(INDEX('計算'!$S$6:$S$405,MATCH(8-MAX('計算'!$CT$6:$CT$405),'計算'!$CU$6:$CU$405,0)),""))) | G18: =IF($B18="","",IF(8<=MAX('計算'!$CT$6:$CT$405),IFERROR(INDEX('計算'!$CR$6:$CR$405,MATCH(8,'計算'!$CT$6:$CT$405,0)),""),IFERROR(INDEX('計算'!$CR$6:$CR$405,MATCH(8-MAX('計算'!$CT$6:$CT$405),'計算'!$CU$6:$CU$405,0)),""))) | H18: =IF($B18="","",IF(8<=MAX('計算'!$CT$6:$CT$405),IFERROR(INDEX('計算'!$Q$6:$Q$405,MATCH(8,'計算'!$CT$6:$CT$405,0)),""),IFERROR(INDEX('計算'!$T$6:$T$405,MATCH(8-MAX('計算'!$CT$6:$CT$405),'計算'!$CU$6:$CU$405,0)),""))) | I18: =IF($B18="","",IF(8<=MAX('計算'!$CT$6:$CT$405),IFERROR(INDEX('計算'!$H$6:$H$405,MATCH(8,'計算'!$CT$6:$CT$405,0)),""),IFERROR(INDEX('計算'!$H$6:$H$405,MATCH(8-MAX('計算'!$CT$6:$CT$405),'計算'!$CU$6:$CU$405,0)),""))) | J18: =IF($B18="","",N($H18)*IFERROR(INDEX('計算'!$G$6:$G$405,IF(8<=MAX('計算'!$CT$6:$CT$405),MATCH(8,'計算'!$CT$6:$CT$405,0),MATCH(8-MAX('計算'!$CT$6:$CT$405),'計算'!$CU$6:$CU$405,0))),1)*N($I18))
B19: =IF(9<=MAX('計算'!$CT$6:$CT$405)+MAX('計算'!$CU$6:$CU$405),9,"") | C19: =IF($B19="","",IF(9<=MAX('計算'!$CT$6:$CT$405),IFERROR(INDEX('計算'!$F$6:$F$405,MATCH(9,'計算'!$CT$6:$CT$405,0)),""),IFERROR(INDEX('計算'!$F$6:$F$405,MATCH(9-MAX('計算'!$CT$6:$CT$405),'計算'!$CU$6:$CU$405,0)),""))) | D19: =IF($B19="","",IF(9<=MAX('計算'!$CT$6:$CT$405),IFERROR(INDEX('計算'!$C$6:$C$405,MATCH(9,'計算'!$CT$6:$CT$405,0))&"",""),IFERROR(INDEX('計算'!$C$6:$C$405,MATCH(9-MAX('計算'!$CT$6:$CT$405),'計算'!$CU$6:$CU$405,0))&"",""))) | E19: =IF($B19="","",IF(9<=MAX('計算'!$CT$6:$CT$405),IFERROR(INDEX('計算'!$D$6:$D$405,MATCH(9,'計算'!$CT$6:$CT$405,0)),""),IFERROR(INDEX('計算'!$D$6:$D$405,MATCH(9-MAX('計算'!$CT$6:$CT$405),'計算'!$CU$6:$CU$405,0)),""))) | F19: =IF($B19="","",IF(9<=MAX('計算'!$CT$6:$CT$405),IFERROR(INDEX('計算'!$P$6:$P$405,MATCH(9,'計算'!$CT$6:$CT$405,0)),""),IFERROR(INDEX('計算'!$S$6:$S$405,MATCH(9-MAX('計算'!$CT$6:$CT$405),'計算'!$CU$6:$CU$405,0)),""))) | G19: =IF($B19="","",IF(9<=MAX('計算'!$CT$6:$CT$405),IFERROR(INDEX('計算'!$CR$6:$CR$405,MATCH(9,'計算'!$CT$6:$CT$405,0)),""),IFERROR(INDEX('計算'!$CR$6:$CR$405,MATCH(9-MAX('計算'!$CT$6:$CT$405),'計算'!$CU$6:$CU$405,0)),""))) | H19: =IF($B19="","",IF(9<=MAX('計算'!$CT$6:$CT$405),IFERROR(INDEX('計算'!$Q$6:$Q$405,MATCH(9,'計算'!$CT$6:$CT$405,0)),""),IFERROR(INDEX('計算'!$T$6:$T$405,MATCH(9-MAX('計算'!$CT$6:$CT$405),'計算'!$CU$6:$CU$405,0)),""))) | I19: =IF($B19="","",IF(9<=MAX('計算'!$CT$6:$CT$405),IFERROR(INDEX('計算'!$H$6:$H$405,MATCH(9,'計算'!$CT$6:$CT$405,0)),""),IFERROR(INDEX('計算'!$H$6:$H$405,MATCH(9-MAX('計算'!$CT$6:$CT$405),'計算'!$CU$6:$CU$405,0)),""))) | J19: =IF($B19="","",N($H19)*IFERROR(INDEX('計算'!$G$6:$G$405,IF(9<=MAX('計算'!$CT$6:$CT$405),MATCH(9,'計算'!$CT$6:$CT$405,0),MATCH(9-MAX('計算'!$CT$6:$CT$405),'計算'!$CU$6:$CU$405,0))),1)*N($I19))
B20: =IF(10<=MAX('計算'!$CT$6:$CT$405)+MAX('計算'!$CU$6:$CU$405),10,"") | C20: =IF($B20="","",IF(10<=MAX('計算'!$CT$6:$CT$405),IFERROR(INDEX('計算'!$F$6:$F$405,MATCH(10,'計算'!$CT$6:$CT$405,0)),""),IFERROR(INDEX('計算'!$F$6:$F$405,MATCH(10-MAX('計算'!$CT$6:$CT$405),'計算'!$CU$6:$CU$405,0)),""))) | D20: =IF($B20="","",IF(10<=MAX('計算'!$CT$6:$CT$405),IFERROR(INDEX('計算'!$C$6:$C$405,MATCH(10,'計算'!$CT$6:$CT$405,0))&"",""),IFERROR(INDEX('計算'!$C$6:$C$405,MATCH(10-MAX('計算'!$CT$6:$CT$405),'計算'!$CU$6:$CU$405,0))&"",""))) | E20: =IF($B20="","",IF(10<=MAX('計算'!$CT$6:$CT$405),IFERROR(INDEX('計算'!$D$6:$D$405,MATCH(10,'計算'!$CT$6:$CT$405,0)),""),IFERROR(INDEX('計算'!$D$6:$D$405,MATCH(10-MAX('計算'!$CT$6:$CT$405),'計算'!$CU$6:$CU$405,0)),""))) | F20: =IF($B20="","",IF(10<=MAX('計算'!$CT$6:$CT$405),IFERROR(INDEX('計算'!$P$6:$P$405,MATCH(10,'計算'!$CT$6:$CT$405,0)),""),IFERROR(INDEX('計算'!$S$6:$S$405,MATCH(10-MAX('計算'!$CT$6:$CT$405),'計算'!$CU$6:$CU$405,0)),""))) | G20: =IF($B20="","",IF(10<=MAX('計算'!$CT$6:$CT$405),IFERROR(INDEX('計算'!$CR$6:$CR$405,MATCH(10,'計算'!$CT$6:$CT$405,0)),""),IFERROR(INDEX('計算'!$CR$6:$CR$405,MATCH(10-MAX('計算'!$CT$6:$CT$405),'計算'!$CU$6:$CU$405,0)),""))) | H20: =IF($B20="","",IF(10<=MAX('計算'!$CT$6:$CT$405),IFERROR(INDEX('計算'!$Q$6:$Q$405,MATCH(10,'計算'!$CT$6:$CT$405,0)),""),IFERROR(INDEX('計算'!$T$6:$T$405,MATCH(10-MAX('計算'!$CT$6:$CT$405),'計算'!$CU$6:$CU$405,0)),""))) | I20: =IF($B20="","",IF(10<=MAX('計算'!$CT$6:$CT$405),IFERROR(INDEX('計算'!$H$6:$H$405,MATCH(10,'計算'!$CT$6:$CT$405,0)),""),IFERROR(INDEX('計算'!$H$6:$H$405,MATCH(10-MAX('計算'!$CT$6:$CT$405),'計算'!$CU$6:$CU$405,0)),""))) | J20: =IF($B20="","",N($H20)*IFERROR(INDEX('計算'!$G$6:$G$405,IF(10<=MAX('計算'!$CT$6:$CT$405),MATCH(10,'計算'!$CT$6:$CT$405,0),MATCH(10-MAX('計算'!$CT$6:$CT$405),'計算'!$CU$6:$CU$405,0))),1)*N($I20))
B21: =IF(11<=MAX('計算'!$CT$6:$CT$405)+MAX('計算'!$CU$6:$CU$405),11,"") | C21: =IF($B21="","",IF(11<=MAX('計算'!$CT$6:$CT$405),IFERROR(INDEX('計算'!$F$6:$F$405,MATCH(11,'計算'!$CT$6:$CT$405,0)),""),IFERROR(INDEX('計算'!$F$6:$F$405,MATCH(11-MAX('計算'!$CT$6:$CT$405),'計算'!$CU$6:$CU$405,0)),""))) | D21: =IF($B21="","",IF(11<=MAX('計算'!$CT$6:$CT$405),IFERROR(INDEX('計算'!$C$6:$C$405,MATCH(11,'計算'!$CT$6:$CT$405,0))&"",""),IFERROR(INDEX('計算'!$C$6:$C$405,MATCH(11-MAX('計算'!$CT$6:$CT$405),'計算'!$CU$6:$CU$405,0))&"",""))) | E21: =IF($B21="","",IF(11<=MAX('計算'!$CT$6:$CT$405),IFERROR(INDEX('計算'!$D$6:$D$405,MATCH(11,'計算'!$CT$6:$CT$405,0)),""),IFERROR(INDEX('計算'!$D$6:$D$405,MATCH(11-MAX('計算'!$CT$6:$CT$405),'計算'!$CU$6:$CU$405,0)),""))) | F21: =IF($B21="","",IF(11<=MAX('計算'!$CT$6:$CT$405),IFERROR(INDEX('計算'!$P$6:$P$405,MATCH(11,'計算'!$CT$6:$CT$405,0)),""),IFERROR(INDEX('計算'!$S$6:$S$405,MATCH(11-MAX('計算'!$CT$6:$CT$405),'計算'!$CU$6:$CU$405,0)),""))) | G21: =IF($B21="","",IF(11<=MAX('計算'!$CT$6:$CT$405),IFERROR(INDEX('計算'!$CR$6:$CR$405,MATCH(11,'計算'!$CT$6:$CT$405,0)),""),IFERROR(INDEX('計算'!$CR$6:$CR$405,MATCH(11-MAX('計算'!$CT$6:$CT$405),'計算'!$CU$6:$CU$405,0)),""))) | H21: =IF($B21="","",IF(11<=MAX('計算'!$CT$6:$CT$405),IFERROR(INDEX('計算'!$Q$6:$Q$405,MATCH(11,'計算'!$CT$6:$CT$405,0)),""),IFERROR(INDEX('計算'!$T$6:$T$405,MATCH(11-MAX('計算'!$CT$6:$CT$405),'計算'!$CU$6:$CU$405,0)),""))) | I21: =IF($B21="","",IF(11<=MAX('計算'!$CT$6:$CT$405),IFERROR(INDEX('計算'!$H$6:$H$405,MATCH(11,'計算'!$CT$6:$CT$405,0)),""),IFERROR(INDEX('計算'!$H$6:$H$405,MATCH(11-MAX('計算'!$CT$6:$CT$405),'計算'!$CU$6:$CU$405,0)),""))) | J21: =IF($B21="","",N($H21)*IFERROR(INDEX('計算'!$G$6:$G$405,IF(11<=MAX('計算'!$CT$6:$CT$405),MATCH(11,'計算'!$CT$6:$CT$405,0),MATCH(11-MAX('計算'!$CT$6:$CT$405),'計算'!$CU$6:$CU$405,0))),1)*N($I21))
B22: =IF(12<=MAX('計算'!$CT$6:$CT$405)+MAX('計算'!$CU$6:$CU$405),12,"") | C22: =IF($B22="","",IF(12<=MAX('計算'!$CT$6:$CT$405),IFERROR(INDEX('計算'!$F$6:$F$405,MATCH(12,'計算'!$CT$6:$CT$405,0)),""),IFERROR(INDEX('計算'!$F$6:$F$405,MATCH(12-MAX('計算'!$CT$6:$CT$405),'計算'!$CU$6:$CU$405,0)),""))) | D22: =IF($B22="","",IF(12<=MAX('計算'!$CT$6:$CT$405),IFERROR(INDEX('計算'!$C$6:$C$405,MATCH(12,'計算'!$CT$6:$CT$405,0))&"",""),IFERROR(INDEX('計算'!$C$6:$C$405,MATCH(12-MAX('計算'!$CT$6:$CT$405),'計算'!$CU$6:$CU$405,0))&"",""))) | E22: =IF($B22="","",IF(12<=MAX('計算'!$CT$6:$CT$405),IFERROR(INDEX('計算'!$D$6:$D$405,MATCH(12,'計算'!$CT$6:$CT$405,0)),""),IFERROR(INDEX('計算'!$D$6:$D$405,MATCH(12-MAX('計算'!$CT$6:$CT$405),'計算'!$CU$6:$CU$405,0)),""))) | F22: =IF($B22="","",IF(12<=MAX('計算'!$CT$6:$CT$405),IFERROR(INDEX('計算'!$P$6:$P$405,MATCH(12,'計算'!$CT$6:$CT$405,0)),""),IFERROR(INDEX('計算'!$S$6:$S$405,MATCH(12-MAX('計算'!$CT$6:$CT$405),'計算'!$CU$6:$CU$405,0)),""))) | G22: =IF($B22="","",IF(12<=MAX('計算'!$CT$6:$CT$405),IFERROR(INDEX('計算'!$CR$6:$CR$405,MATCH(12,'計算'!$CT$6:$CT$405,0)),""),IFERROR(INDEX('計算'!$CR$6:$CR$405,MATCH(12-MAX('計算'!$CT$6:$CT$405),'計算'!$CU$6:$CU$405,0)),""))) | H22: =IF($B22="","",IF(12<=MAX('計算'!$CT$6:$CT$405),IFERROR(INDEX('計算'!$Q$6:$Q$405,MATCH(12,'計算'!$CT$6:$CT$405,0)),""),IFERROR(INDEX('計算'!$T$6:$T$405,MATCH(12-MAX('計算'!$CT$6:$CT$405),'計算'!$CU$6:$CU$405,0)),""))) | I22: =IF($B22="","",IF(12<=MAX('計算'!$CT$6:$CT$405),IFERROR(INDEX('計算'!$H$6:$H$405,MATCH(12,'計算'!$CT$6:$CT$405,0)),""),IFERROR(INDEX('計算'!$H$6:$H$405,MATCH(12-MAX('計算'!$CT$6:$CT$405),'計算'!$CU$6:$CU$405,0)),""))) | J22: =IF($B22="","",N($H22)*IFERROR(INDEX('計算'!$G$6:$G$405,IF(12<=MAX('計算'!$CT$6:$CT$405),MATCH(12,'計算'!$CT$6:$CT$405,0),MATCH(12-MAX('計算'!$CT$6:$CT$405),'計算'!$CU$6:$CU$405,0))),1)*N($I22))
B23: =IF(13<=MAX('計算'!$CT$6:$CT$405)+MAX('計算'!$CU$6:$CU$405),13,"") | C23: =IF($B23="","",IF(13<=MAX('計算'!$CT$6:$CT$405),IFERROR(INDEX('計算'!$F$6:$F$405,MATCH(13,'計算'!$CT$6:$CT$405,0)),""),IFERROR(INDEX('計算'!$F$6:$F$405,MATCH(13-MAX('計算'!$CT$6:$CT$405),'計算'!$CU$6:$CU$405,0)),""))) | D23: =IF($B23="","",IF(13<=MAX('計算'!$CT$6:$CT$405),IFERROR(INDEX('計算'!$C$6:$C$405,MATCH(13,'計算'!$CT$6:$CT$405,0))&"",""),IFERROR(INDEX('計算'!$C$6:$C$405,MATCH(13-MAX('計算'!$CT$6:$CT$405),'計算'!$CU$6:$CU$405,0))&"",""))) | E23: =IF($B23="","",IF(13<=MAX('計算'!$CT$6:$CT$405),IFERROR(INDEX('計算'!$D$6:$D$405,MATCH(13,'計算'!$CT$6:$CT$405,0)),""),IFERROR(INDEX('計算'!$D$6:$D$405,MATCH(13-MAX('計算'!$CT$6:$CT$405),'計算'!$CU$6:$CU$405,0)),""))) | F23: =IF($B23="","",IF(13<=MAX('計算'!$CT$6:$CT$405),IFERROR(INDEX('計算'!$P$6:$P$405,MATCH(13,'計算'!$CT$6:$CT$405,0)),""),IFERROR(INDEX('計算'!$S$6:$S$405,MATCH(13-MAX('計算'!$CT$6:$CT$405),'計算'!$CU$6:$CU$405,0)),""))) | G23: =IF($B23="","",IF(13<=MAX('計算'!$CT$6:$CT$405),IFERROR(INDEX('計算'!$CR$6:$CR$405,MATCH(13,'計算'!$CT$6:$CT$405,0)),""),IFERROR(INDEX('計算'!$CR$6:$CR$405,MATCH(13-MAX('計算'!$CT$6:$CT$405),'計算'!$CU$6:$CU$405,0)),""))) | H23: =IF($B23="","",IF(13<=MAX('計算'!$CT$6:$CT$405),IFERROR(INDEX('計算'!$Q$6:$Q$405,MATCH(13,'計算'!$CT$6:$CT$405,0)),""),IFERROR(INDEX('計算'!$T$6:$T$405,MATCH(13-MAX('計算'!$CT$6:$CT$405),'計算'!$CU$6:$CU$405,0)),""))) | I23: =IF($B23="","",IF(13<=MAX('計算'!$CT$6:$CT$405),IFERROR(INDEX('計算'!$H$6:$H$405,MATCH(13,'計算'!$CT$6:$CT$405,0)),""),IFERROR(INDEX('計算'!$H$6:$H$405,MATCH(13-MAX('計算'!$CT$6:$CT$405),'計算'!$CU$6:$CU$405,0)),""))) | J23: =IF($B23="","",N($H23)*IFERROR(INDEX('計算'!$G$6:$G$405,IF(13<=MAX('計算'!$CT$6:$CT$405),MATCH(13,'計算'!$CT$6:$CT$405,0),MATCH(13-MAX('計算'!$CT$6:$CT$405),'計算'!$CU$6:$CU$405,0))),1)*N($I23))
B24: =IF(14<=MAX('計算'!$CT$6:$CT$405)+MAX('計算'!$CU$6:$CU$405),14,"") | C24: =IF($B24="","",IF(14<=MAX('計算'!$CT$6:$CT$405),IFERROR(INDEX('計算'!$F$6:$F$405,MATCH(14,'計算'!$CT$6:$CT$405,0)),""),IFERROR(INDEX('計算'!$F$6:$F$405,MATCH(14-MAX('計算'!$CT$6:$CT$405),'計算'!$CU$6:$CU$405,0)),""))) | D24: =IF($B24="","",IF(14<=MAX('計算'!$CT$6:$CT$405),IFERROR(INDEX('計算'!$C$6:$C$405,MATCH(14,'計算'!$CT$6:$CT$405,0))&"",""),IFERROR(INDEX('計算'!$C$6:$C$405,MATCH(14-MAX('計算'!$CT$6:$CT$405),'計算'!$CU$6:$CU$405,0))&"",""))) | E24: =IF($B24="","",IF(14<=MAX('計算'!$CT$6:$CT$405),IFERROR(INDEX('計算'!$D$6:$D$405,MATCH(14,'計算'!$CT$6:$CT$405,0)),""),IFERROR(INDEX('計算'!$D$6:$D$405,MATCH(14-MAX('計算'!$CT$6:$CT$405),'計算'!$CU$6:$CU$405,0)),""))) | F24: =IF($B24="","",IF(14<=MAX('計算'!$CT$6:$CT$405),IFERROR(INDEX('計算'!$P$6:$P$405,MATCH(14,'計算'!$CT$6:$CT$405,0)),""),IFERROR(INDEX('計算'!$S$6:$S$405,MATCH(14-MAX('計算'!$CT$6:$CT$405),'計算'!$CU$6:$CU$405,0)),""))) | G24: =IF($B24="","",IF(14<=MAX('計算'!$CT$6:$CT$405),IFERROR(INDEX('計算'!$CR$6:$CR$405,MATCH(14,'計算'!$CT$6:$CT$405,0)),""),IFERROR(INDEX('計算'!$CR$6:$CR$405,MATCH(14-MAX('計算'!$CT$6:$CT$405),'計算'!$CU$6:$CU$405,0)),""))) | H24: =IF($B24="","",IF(14<=MAX('計算'!$CT$6:$CT$405),IFERROR(INDEX('計算'!$Q$6:$Q$405,MATCH(14,'計算'!$CT$6:$CT$405,0)),""),IFERROR(INDEX('計算'!$T$6:$T$405,MATCH(14-MAX('計算'!$CT$6:$CT$405),'計算'!$CU$6:$CU$405,0)),""))) | I24: =IF($B24="","",IF(14<=MAX('計算'!$CT$6:$CT$405),IFERROR(INDEX('計算'!$H$6:$H$405,MATCH(14,'計算'!$CT$6:$CT$405,0)),""),IFERROR(INDEX('計算'!$H$6:$H$405,MATCH(14-MAX('計算'!$CT$6:$CT$405),'計算'!$CU$6:$CU$405,0)),""))) | J24: =IF($B24="","",N($H24)*IFERROR(INDEX('計算'!$G$6:$G$405,IF(14<=MAX('計算'!$CT$6:$CT$405),MATCH(14,'計算'!$CT$6:$CT$405,0),MATCH(14-MAX('計算'!$CT$6:$CT$405),'計算'!$CU$6:$CU$405,0))),1)*N($I24))
B25: =IF(15<=MAX('計算'!$CT$6:$CT$405)+MAX('計算'!$CU$6:$CU$405),15,"") | C25: =IF($B25="","",IF(15<=MAX('計算'!$CT$6:$CT$405),IFERROR(INDEX('計算'!$F$6:$F$405,MATCH(15,'計算'!$CT$6:$CT$405,0)),""),IFERROR(INDEX('計算'!$F$6:$F$405,MATCH(15-MAX('計算'!$CT$6:$CT$405),'計算'!$CU$6:$CU$405,0)),""))) | D25: =IF($B25="","",IF(15<=MAX('計算'!$CT$6:$CT$405),IFERROR(INDEX('計算'!$C$6:$C$405,MATCH(15,'計算'!$CT$6:$CT$405,0))&"",""),IFERROR(INDEX('計算'!$C$6:$C$405,MATCH(15-MAX('計算'!$CT$6:$CT$405),'計算'!$CU$6:$CU$405,0))&"",""))) | E25: =IF($B25="","",IF(15<=MAX('計算'!$CT$6:$CT$405),IFERROR(INDEX('計算'!$D$6:$D$405,MATCH(15,'計算'!$CT$6:$CT$405,0)),""),IFERROR(INDEX('計算'!$D$6:$D$405,MATCH(15-MAX('計算'!$CT$6:$CT$405),'計算'!$CU$6:$CU$405,0)),""))) | F25: =IF($B25="","",IF(15<=MAX('計算'!$CT$6:$CT$405),IFERROR(INDEX('計算'!$P$6:$P$405,MATCH(15,'計算'!$CT$6:$CT$405,0)),""),IFERROR(INDEX('計算'!$S$6:$S$405,MATCH(15-MAX('計算'!$CT$6:$CT$405),'計算'!$CU$6:$CU$405,0)),""))) | G25: =IF($B25="","",IF(15<=MAX('計算'!$CT$6:$CT$405),IFERROR(INDEX('計算'!$CR$6:$CR$405,MATCH(15,'計算'!$CT$6:$CT$405,0)),""),IFERROR(INDEX('計算'!$CR$6:$CR$405,MATCH(15-MAX('計算'!$CT$6:$CT$405),'計算'!$CU$6:$CU$405,0)),""))) | H25: =IF($B25="","",IF(15<=MAX('計算'!$CT$6:$CT$405),IFERROR(INDEX('計算'!$Q$6:$Q$405,MATCH(15,'計算'!$CT$6:$CT$405,0)),""),IFERROR(INDEX('計算'!$T$6:$T$405,MATCH(15-MAX('計算'!$CT$6:$CT$405),'計算'!$CU$6:$CU$405,0)),""))) | I25: =IF($B25="","",IF(15<=MAX('計算'!$CT$6:$CT$405),IFERROR(INDEX('計算'!$H$6:$H$405,MATCH(15,'計算'!$CT$6:$CT$405,0)),""),IFERROR(INDEX('計算'!$H$6:$H$405,MATCH(15-MAX('計算'!$CT$6:$CT$405),'計算'!$CU$6:$CU$405,0)),""))) | J25: =IF($B25="","",N($H25)*IFERROR(INDEX('計算'!$G$6:$G$405,IF(15<=MAX('計算'!$CT$6:$CT$405),MATCH(15,'計算'!$CT$6:$CT$405,0),MATCH(15-MAX('計算'!$CT$6:$CT$405),'計算'!$CU$6:$CU$405,0))),1)*N($I25))
B26: =IF(16<=MAX('計算'!$CT$6:$CT$405)+MAX('計算'!$CU$6:$CU$405),16,"") | C26: =IF($B26="","",IF(16<=MAX('計算'!$CT$6:$CT$405),IFERROR(INDEX('計算'!$F$6:$F$405,MATCH(16,'計算'!$CT$6:$CT$405,0)),""),IFERROR(INDEX('計算'!$F$6:$F$405,MATCH(16-MAX('計算'!$CT$6:$CT$405),'計算'!$CU$6:$CU$405,0)),""))) | D26: =IF($B26="","",IF(16<=MAX('計算'!$CT$6:$CT$405),IFERROR(INDEX('計算'!$C$6:$C$405,MATCH(16,'計算'!$CT$6:$CT$405,0))&"",""),IFERROR(INDEX('計算'!$C$6:$C$405,MATCH(16-MAX('計算'!$CT$6:$CT$405),'計算'!$CU$6:$CU$405,0))&"",""))) | E26: =IF($B26="","",IF(16<=MAX('計算'!$CT$6:$CT$405),IFERROR(INDEX('計算'!$D$6:$D$405,MATCH(16,'計算'!$CT$6:$CT$405,0)),""),IFERROR(INDEX('計算'!$D$6:$D$405,MATCH(16-MAX('計算'!$CT$6:$CT$405),'計算'!$CU$6:$CU$405,0)),""))) | F26: =IF($B26="","",IF(16<=MAX('計算'!$CT$6:$CT$405),IFERROR(INDEX('計算'!$P$6:$P$405,MATCH(16,'計算'!$CT$6:$CT$405,0)),""),IFERROR(INDEX('計算'!$S$6:$S$405,MATCH(16-MAX('計算'!$CT$6:$CT$405),'計算'!$CU$6:$CU$405,0)),""))) | G26: =IF($B26="","",IF(16<=MAX('計算'!$CT$6:$CT$405),IFERROR(INDEX('計算'!$CR$6:$CR$405,MATCH(16,'計算'!$CT$6:$CT$405,0)),""),IFERROR(INDEX('計算'!$CR$6:$CR$405,MATCH(16-MAX('計算'!$CT$6:$CT$405),'計算'!$CU$6:$CU$405,0)),""))) | H26: =IF($B26="","",IF(16<=MAX('計算'!$CT$6:$CT$405),IFERROR(INDEX('計算'!$Q$6:$Q$405,MATCH(16,'計算'!$CT$6:$CT$405,0)),""),IFERROR(INDEX('計算'!$T$6:$T$405,MATCH(16-MAX('計算'!$CT$6:$CT$405),'計算'!$CU$6:$CU$405,0)),""))) | I26: =IF($B26="","",IF(16<=MAX('計算'!$CT$6:$CT$405),IFERROR(INDEX('計算'!$H$6:$H$405,MATCH(16,'計算'!$CT$6:$CT$405,0)),""),IFERROR(INDEX('計算'!$H$6:$H$405,MATCH(16-MAX('計算'!$CT$6:$CT$405),'計算'!$CU$6:$CU$405,0)),""))) | J26: =IF($B26="","",N($H26)*IFERROR(INDEX('計算'!$G$6:$G$405,IF(16<=MAX('計算'!$CT$6:$CT$405),MATCH(16,'計算'!$CT$6:$CT$405,0),MATCH(16-MAX('計算'!$CT$6:$CT$405),'計算'!$CU$6:$CU$405,0))),1)*N($I26))
B27: =IF(17<=MAX('計算'!$CT$6:$CT$405)+MAX('計算'!$CU$6:$CU$405),17,"") | C27: =IF($B27="","",IF(17<=MAX('計算'!$CT$6:$CT$405),IFERROR(INDEX('計算'!$F$6:$F$405,MATCH(17,'計算'!$CT$6:$CT$405,0)),""),IFERROR(INDEX('計算'!$F$6:$F$405,MATCH(17-MAX('計算'!$CT$6:$CT$405),'計算'!$CU$6:$CU$405,0)),""))) | D27: =IF($B27="","",IF(17<=MAX('計算'!$CT$6:$CT$405),IFERROR(INDEX('計算'!$C$6:$C$405,MATCH(17,'計算'!$CT$6:$CT$405,0))&"",""),IFERROR(INDEX('計算'!$C$6:$C$405,MATCH(17-MAX('計算'!$CT$6:$CT$405),'計算'!$CU$6:$CU$405,0))&"",""))) | E27: =IF($B27="","",IF(17<=MAX('計算'!$CT$6:$CT$405),IFERROR(INDEX('計算'!$D$6:$D$405,MATCH(17,'計算'!$CT$6:$CT$405,0)),""),IFERROR(INDEX('計算'!$D$6:$D$405,MATCH(17-MAX('計算'!$CT$6:$CT$405),'計算'!$CU$6:$CU$405,0)),""))) | F27: =IF($B27="","",IF(17<=MAX('計算'!$CT$6:$CT$405),IFERROR(INDEX('計算'!$P$6:$P$405,MATCH(17,'計算'!$CT$6:$CT$405,0)),""),IFERROR(INDEX('計算'!$S$6:$S$405,MATCH(17-MAX('計算'!$CT$6:$CT$405),'計算'!$CU$6:$CU$405,0)),""))) | G27: =IF($B27="","",IF(17<=MAX('計算'!$CT$6:$CT$405),IFERROR(INDEX('計算'!$CR$6:$CR$405,MATCH(17,'計算'!$CT$6:$CT$405,0)),""),IFERROR(INDEX('計算'!$CR$6:$CR$405,MATCH(17-MAX('計算'!$CT$6:$CT$405),'計算'!$CU$6:$CU$405,0)),""))) | H27: =IF($B27="","",IF(17<=MAX('計算'!$CT$6:$CT$405),IFERROR(INDEX('計算'!$Q$6:$Q$405,MATCH(17,'計算'!$CT$6:$CT$405,0)),""),IFERROR(INDEX('計算'!$T$6:$T$405,MATCH(17-MAX('計算'!$CT$6:$CT$405),'計算'!$CU$6:$CU$405,0)),""))) | I27: =IF($B27="","",IF(17<=MAX('計算'!$CT$6:$CT$405),IFERROR(INDEX('計算'!$H$6:$H$405,MATCH(17,'計算'!$CT$6:$CT$405,0)),""),IFERROR(INDEX('計算'!$H$6:$H$405,MATCH(17-MAX('計算'!$CT$6:$CT$405),'計算'!$CU$6:$CU$405,0)),""))) | J27: =IF($B27="","",N($H27)*IFERROR(INDEX('計算'!$G$6:$G$405,IF(17<=MAX('計算'!$CT$6:$CT$405),MATCH(17,'計算'!$CT$6:$CT$405,0),MATCH(17-MAX('計算'!$CT$6:$CT$405),'計算'!$CU$6:$CU$405,0))),1)*N($I27))
B28: =IF(18<=MAX('計算'!$CT$6:$CT$405)+MAX('計算'!$CU$6:$CU$405),18,"") | C28: =IF($B28="","",IF(18<=MAX('計算'!$CT$6:$CT$405),IFERROR(INDEX('計算'!$F$6:$F$405,MATCH(18,'計算'!$CT$6:$CT$405,0)),""),IFERROR(INDEX('計算'!$F$6:$F$405,MATCH(18-MAX('計算'!$CT$6:$CT$405),'計算'!$CU$6:$CU$405,0)),""))) | D28: =IF($B28="","",IF(18<=MAX('計算'!$CT$6:$CT$405),IFERROR(INDEX('計算'!$C$6:$C$405,MATCH(18,'計算'!$CT$6:$CT$405,0))&"",""),IFERROR(INDEX('計算'!$C$6:$C$405,MATCH(18-MAX('計算'!$CT$6:$CT$405),'計算'!$CU$6:$CU$405,0))&"",""))) | E28: =IF($B28="","",IF(18<=MAX('計算'!$CT$6:$CT$405),IFERROR(INDEX('計算'!$D$6:$D$405,MATCH(18,'計算'!$CT$6:$CT$405,0)),""),IFERROR(INDEX('計算'!$D$6:$D$405,MATCH(18-MAX('計算'!$CT$6:$CT$405),'計算'!$CU$6:$CU$405,0)),""))) | F28: =IF($B28="","",IF(18<=MAX('計算'!$CT$6:$CT$405),IFERROR(INDEX('計算'!$P$6:$P$405,MATCH(18,'計算'!$CT$6:$CT$405,0)),""),IFERROR(INDEX('計算'!$S$6:$S$405,MATCH(18-MAX('計算'!$CT$6:$CT$405),'計算'!$CU$6:$CU$405,0)),""))) | G28: =IF($B28="","",IF(18<=MAX('計算'!$CT$6:$CT$405),IFERROR(INDEX('計算'!$CR$6:$CR$405,MATCH(18,'計算'!$CT$6:$CT$405,0)),""),IFERROR(INDEX('計算'!$CR$6:$CR$405,MATCH(18-MAX('計算'!$CT$6:$CT$405),'計算'!$CU$6:$CU$405,0)),""))) | H28: =IF($B28="","",IF(18<=MAX('計算'!$CT$6:$CT$405),IFERROR(INDEX('計算'!$Q$6:$Q$405,MATCH(18,'計算'!$CT$6:$CT$405,0)),""),IFERROR(INDEX('計算'!$T$6:$T$405,MATCH(18-MAX('計算'!$CT$6:$CT$405),'計算'!$CU$6:$CU$405,0)),""))) | I28: =IF($B28="","",IF(18<=MAX('計算'!$CT$6:$CT$405),IFERROR(INDEX('計算'!$H$6:$H$405,MATCH(18,'計算'!$CT$6:$CT$405,0)),""),IFERROR(INDEX('計算'!$H$6:$H$405,MATCH(18-MAX('計算'!$CT$6:$CT$405),'計算'!$CU$6:$CU$405,0)),""))) | J28: =IF($B28="","",N($H28)*IFERROR(INDEX('計算'!$G$6:$G$405,IF(18<=MAX('計算'!$CT$6:$CT$405),MATCH(18,'計算'!$CT$6:$CT$405,0),MATCH(18-MAX('計算'!$CT$6:$CT$405),'計算'!$CU$6:$CU$405,0))),1)*N($I28))
B29: =IF(19<=MAX('計算'!$CT$6:$CT$405)+MAX('計算'!$CU$6:$CU$405),19,"") | C29: =IF($B29="","",IF(19<=MAX('計算'!$CT$6:$CT$405),IFERROR(INDEX('計算'!$F$6:$F$405,MATCH(19,'計算'!$CT$6:$CT$405,0)),""),IFERROR(INDEX('計算'!$F$6:$F$405,MATCH(19-MAX('計算'!$CT$6:$CT$405),'計算'!$CU$6:$CU$405,0)),""))) | D29: =IF($B29="","",IF(19<=MAX('計算'!$CT$6:$CT$405),IFERROR(INDEX('計算'!$C$6:$C$405,MATCH(19,'計算'!$CT$6:$CT$405,0))&"",""),IFERROR(INDEX('計算'!$C$6:$C$405,MATCH(19-MAX('計算'!$CT$6:$CT$405),'計算'!$CU$6:$CU$405,0))&"",""))) | E29: =IF($B29="","",IF(19<=MAX('計算'!$CT$6:$CT$405),IFERROR(INDEX('計算'!$D$6:$D$405,MATCH(19,'計算'!$CT$6:$CT$405,0)),""),IFERROR(INDEX('計算'!$D$6:$D$405,MATCH(19-MAX('計算'!$CT$6:$CT$405),'計算'!$CU$6:$CU$405,0)),""))) | F29: =IF($B29="","",IF(19<=MAX('計算'!$CT$6:$CT$405),IFERROR(INDEX('計算'!$P$6:$P$405,MATCH(19,'計算'!$CT$6:$CT$405,0)),""),IFERROR(INDEX('計算'!$S$6:$S$405,MATCH(19-MAX('計算'!$CT$6:$CT$405),'計算'!$CU$6:$CU$405,0)),""))) | G29: =IF($B29="","",IF(19<=MAX('計算'!$CT$6:$CT$405),IFERROR(INDEX('計算'!$CR$6:$CR$405,MATCH(19,'計算'!$CT$6:$CT$405,0)),""),IFERROR(INDEX('計算'!$CR$6:$CR$405,MATCH(19-MAX('計算'!$CT$6:$CT$405),'計算'!$CU$6:$CU$405,0)),""))) | H29: =IF($B29="","",IF(19<=MAX('計算'!$CT$6:$CT$405),IFERROR(INDEX('計算'!$Q$6:$Q$405,MATCH(19,'計算'!$CT$6:$CT$405,0)),""),IFERROR(INDEX('計算'!$T$6:$T$405,MATCH(19-MAX('計算'!$CT$6:$CT$405),'計算'!$CU$6:$CU$405,0)),""))) | I29: =IF($B29="","",IF(19<=MAX('計算'!$CT$6:$CT$405),IFERROR(INDEX('計算'!$H$6:$H$405,MATCH(19,'計算'!$CT$6:$CT$405,0)),""),IFERROR(INDEX('計算'!$H$6:$H$405,MATCH(19-MAX('計算'!$CT$6:$CT$405),'計算'!$CU$6:$CU$405,0)),""))) | J29: =IF($B29="","",N($H29)*IFERROR(INDEX('計算'!$G$6:$G$405,IF(19<=MAX('計算'!$CT$6:$CT$405),MATCH(19,'計算'!$CT$6:$CT$405,0),MATCH(19-MAX('計算'!$CT$6:$CT$405),'計算'!$CU$6:$CU$405,0))),1)*N($I29))
B30: =IF(20<=MAX('計算'!$CT$6:$CT$405)+MAX('計算'!$CU$6:$CU$405),20,"") | C30: =IF($B30="","",IF(20<=MAX('計算'!$CT$6:$CT$405),IFERROR(INDEX('計算'!$F$6:$F$405,MATCH(20,'計算'!$CT$6:$CT$405,0)),""),IFERROR(INDEX('計算'!$F$6:$F$405,MATCH(20-MAX('計算'!$CT$6:$CT$405),'計算'!$CU$6:$CU$405,0)),""))) | D30: =IF($B30="","",IF(20<=MAX('計算'!$CT$6:$CT$405),IFERROR(INDEX('計算'!$C$6:$C$405,MATCH(20,'計算'!$CT$6:$CT$405,0))&"",""),IFERROR(INDEX('計算'!$C$6:$C$405,MATCH(20-MAX('計算'!$CT$6:$CT$405),'計算'!$CU$6:$CU$405,0))&"",""))) | E30: =IF($B30="","",IF(20<=MAX('計算'!$CT$6:$CT$405),IFERROR(INDEX('計算'!$D$6:$D$405,MATCH(20,'計算'!$CT$6:$CT$405,0)),""),IFERROR(INDEX('計算'!$D$6:$D$405,MATCH(20-MAX('計算'!$CT$6:$CT$405),'計算'!$CU$6:$CU$405,0)),""))) | F30: =IF($B30="","",IF(20<=MAX('計算'!$CT$6:$CT$405),IFERROR(INDEX('計算'!$P$6:$P$405,MATCH(20,'計算'!$CT$6:$CT$405,0)),""),IFERROR(INDEX('計算'!$S$6:$S$405,MATCH(20-MAX('計算'!$CT$6:$CT$405),'計算'!$CU$6:$CU$405,0)),""))) | G30: =IF($B30="","",IF(20<=MAX('計算'!$CT$6:$CT$405),IFERROR(INDEX('計算'!$CR$6:$CR$405,MATCH(20,'計算'!$CT$6:$CT$405,0)),""),IFERROR(INDEX('計算'!$CR$6:$CR$405,MATCH(20-MAX('計算'!$CT$6:$CT$405),'計算'!$CU$6:$CU$405,0)),""))) | H30: =IF($B30="","",IF(20<=MAX('計算'!$CT$6:$CT$405),IFERROR(INDEX('計算'!$Q$6:$Q$405,MATCH(20,'計算'!$CT$6:$CT$405,0)),""),IFERROR(INDEX('計算'!$T$6:$T$405,MATCH(20-MAX('計算'!$CT$6:$CT$405),'計算'!$CU$6:$CU$405,0)),""))) | I30: =IF($B30="","",IF(20<=MAX('計算'!$CT$6:$CT$405),IFERROR(INDEX('計算'!$H$6:$H$405,MATCH(20,'計算'!$CT$6:$CT$405,0)),""),IFERROR(INDEX('計算'!$H$6:$H$405,MATCH(20-MAX('計算'!$CT$6:$CT$405),'計算'!$CU$6:$CU$405,0)),""))) | J30: =IF($B30="","",N($H30)*IFERROR(INDEX('計算'!$G$6:$G$405,IF(20<=MAX('計算'!$CT$6:$CT$405),MATCH(20,'計算'!$CT$6:$CT$405,0),MATCH(20-MAX('計算'!$CT$6:$CT$405),'計算'!$CU$6:$CU$405,0))),1)*N($I30))
B31: =IF(21<=MAX('計算'!$CT$6:$CT$405)+MAX('計算'!$CU$6:$CU$405),21,"") | C31: =IF($B31="","",IF(21<=MAX('計算'!$CT$6:$CT$405),IFERROR(INDEX('計算'!$F$6:$F$405,MATCH(21,'計算'!$CT$6:$CT$405,0)),""),IFERROR(INDEX('計算'!$F$6:$F$405,MATCH(21-MAX('計算'!$CT$6:$CT$405),'計算'!$CU$6:$CU$405,0)),""))) | D31: =IF($B31="","",IF(21<=MAX('計算'!$CT$6:$CT$405),IFERROR(INDEX('計算'!$C$6:$C$405,MATCH(21,'計算'!$CT$6:$CT$405,0))&"",""),IFERROR(INDEX('計算'!$C$6:$C$405,MATCH(21-MAX('計算'!$CT$6:$CT$405),'計算'!$CU$6:$CU$405,0))&"",""))) | E31: =IF($B31="","",IF(21<=MAX('計算'!$CT$6:$CT$405),IFERROR(INDEX('計算'!$D$6:$D$405,MATCH(21,'計算'!$CT$6:$CT$405,0)),""),IFERROR(INDEX('計算'!$D$6:$D$405,MATCH(21-MAX('計算'!$CT$6:$CT$405),'計算'!$CU$6:$CU$405,0)),""))) | F31: =IF($B31="","",IF(21<=MAX('計算'!$CT$6:$CT$405),IFERROR(INDEX('計算'!$P$6:$P$405,MATCH(21,'計算'!$CT$6:$CT$405,0)),""),IFERROR(INDEX('計算'!$S$6:$S$405,MATCH(21-MAX('計算'!$CT$6:$CT$405),'計算'!$CU$6:$CU$405,0)),""))) | G31: =IF($B31="","",IF(21<=MAX('計算'!$CT$6:$CT$405),IFERROR(INDEX('計算'!$CR$6:$CR$405,MATCH(21,'計算'!$CT$6:$CT$405,0)),""),IFERROR(INDEX('計算'!$CR$6:$CR$405,MATCH(21-MAX('計算'!$CT$6:$CT$405),'計算'!$CU$6:$CU$405,0)),""))) | H31: =IF($B31="","",IF(21<=MAX('計算'!$CT$6:$CT$405),IFERROR(INDEX('計算'!$Q$6:$Q$405,MATCH(21,'計算'!$CT$6:$CT$405,0)),""),IFERROR(INDEX('計算'!$T$6:$T$405,MATCH(21-MAX('計算'!$CT$6:$CT$405),'計算'!$CU$6:$CU$405,0)),""))) | I31: =IF($B31="","",IF(21<=MAX('計算'!$CT$6:$CT$405),IFERROR(INDEX('計算'!$H$6:$H$405,MATCH(21,'計算'!$CT$6:$CT$405,0)),""),IFERROR(INDEX('計算'!$H$6:$H$405,MATCH(21-MAX('計算'!$CT$6:$CT$405),'計算'!$CU$6:$CU$405,0)),""))) | J31: =IF($B31="","",N($H31)*IFERROR(INDEX('計算'!$G$6:$G$405,IF(21<=MAX('計算'!$CT$6:$CT$405),MATCH(21,'計算'!$CT$6:$CT$405,0),MATCH(21-MAX('計算'!$CT$6:$CT$405),'計算'!$CU$6:$CU$405,0))),1)*N($I31))
B32: =IF(22<=MAX('計算'!$CT$6:$CT$405)+MAX('計算'!$CU$6:$CU$405),22,"") | C32: =IF($B32="","",IF(22<=MAX('計算'!$CT$6:$CT$405),IFERROR(INDEX('計算'!$F$6:$F$405,MATCH(22,'計算'!$CT$6:$CT$405,0)),""),IFERROR(INDEX('計算'!$F$6:$F$405,MATCH(22-MAX('計算'!$CT$6:$CT$405),'計算'!$CU$6:$CU$405,0)),""))) | D32: =IF($B32="","",IF(22<=MAX('計算'!$CT$6:$CT$405),IFERROR(INDEX('計算'!$C$6:$C$405,MATCH(22,'計算'!$CT$6:$CT$405,0))&"",""),IFERROR(INDEX('計算'!$C$6:$C$405,MATCH(22-MAX('計算'!$CT$6:$CT$405),'計算'!$CU$6:$CU$405,0))&"",""))) | E32: =IF($B32="","",IF(22<=MAX('計算'!$CT$6:$CT$405),IFERROR(INDEX('計算'!$D$6:$D$405,MATCH(22,'計算'!$CT$6:$CT$405,0)),""),IFERROR(INDEX('計算'!$D$6:$D$405,MATCH(22-MAX('計算'!$CT$6:$CT$405),'計算'!$CU$6:$CU$405,0)),""))) | F32: =IF($B32="","",IF(22<=MAX('計算'!$CT$6:$CT$405),IFERROR(INDEX('計算'!$P$6:$P$405,MATCH(22,'計算'!$CT$6:$CT$405,0)),""),IFERROR(INDEX('計算'!$S$6:$S$405,MATCH(22-MAX('計算'!$CT$6:$CT$405),'計算'!$CU$6:$CU$405,0)),""))) | G32: =IF($B32="","",IF(22<=MAX('計算'!$CT$6:$CT$405),IFERROR(INDEX('計算'!$CR$6:$CR$405,MATCH(22,'計算'!$CT$6:$CT$405,0)),""),IFERROR(INDEX('計算'!$CR$6:$CR$405,MATCH(22-MAX('計算'!$CT$6:$CT$405),'計算'!$CU$6:$CU$405,0)),""))) | H32: =IF($B32="","",IF(22<=MAX('計算'!$CT$6:$CT$405),IFERROR(INDEX('計算'!$Q$6:$Q$405,MATCH(22,'計算'!$CT$6:$CT$405,0)),""),IFERROR(INDEX('計算'!$T$6:$T$405,MATCH(22-MAX('計算'!$CT$6:$CT$405),'計算'!$CU$6:$CU$405,0)),""))) | I32: =IF($B32="","",IF(22<=MAX('計算'!$CT$6:$CT$405),IFERROR(INDEX('計算'!$H$6:$H$405,MATCH(22,'計算'!$CT$6:$CT$405,0)),""),IFERROR(INDEX('計算'!$H$6:$H$405,MATCH(22-MAX('計算'!$CT$6:$CT$405),'計算'!$CU$6:$CU$405,0)),""))) | J32: =IF($B32="","",N($H32)*IFERROR(INDEX('計算'!$G$6:$G$405,IF(22<=MAX('計算'!$CT$6:$CT$405),MATCH(22,'計算'!$CT$6:$CT$405,0),MATCH(22-MAX('計算'!$CT$6:$CT$405),'計算'!$CU$6:$CU$405,0))),1)*N($I32))
B33: =IF(23<=MAX('計算'!$CT$6:$CT$405)+MAX('計算'!$CU$6:$CU$405),23,"") | C33: =IF($B33="","",IF(23<=MAX('計算'!$CT$6:$CT$405),IFERROR(INDEX('計算'!$F$6:$F$405,MATCH(23,'計算'!$CT$6:$CT$405,0)),""),IFERROR(INDEX('計算'!$F$6:$F$405,MATCH(23-MAX('計算'!$CT$6:$CT$405),'計算'!$CU$6:$CU$405,0)),""))) | D33: =IF($B33="","",IF(23<=MAX('計算'!$CT$6:$CT$405),IFERROR(INDEX('計算'!$C$6:$C$405,MATCH(23,'計算'!$CT$6:$CT$405,0))&"",""),IFERROR(INDEX('計算'!$C$6:$C$405,MATCH(23-MAX('計算'!$CT$6:$CT$405),'計算'!$CU$6:$CU$405,0))&"",""))) | E33: =IF($B33="","",IF(23<=MAX('計算'!$CT$6:$CT$405),IFERROR(INDEX('計算'!$D$6:$D$405,MATCH(23,'計算'!$CT$6:$CT$405,0)),""),IFERROR(INDEX('計算'!$D$6:$D$405,MATCH(23-MAX('計算'!$CT$6:$CT$405),'計算'!$CU$6:$CU$405,0)),""))) | F33: =IF($B33="","",IF(23<=MAX('計算'!$CT$6:$CT$405),IFERROR(INDEX('計算'!$P$6:$P$405,MATCH(23,'計算'!$CT$6:$CT$405,0)),""),IFERROR(INDEX('計算'!$S$6:$S$405,MATCH(23-MAX('計算'!$CT$6:$CT$405),'計算'!$CU$6:$CU$405,0)),""))) | G33: =IF($B33="","",IF(23<=MAX('計算'!$CT$6:$CT$405),IFERROR(INDEX('計算'!$CR$6:$CR$405,MATCH(23,'計算'!$CT$6:$CT$405,0)),""),IFERROR(INDEX('計算'!$CR$6:$CR$405,MATCH(23-MAX('計算'!$CT$6:$CT$405),'計算'!$CU$6:$CU$405,0)),""))) | H33: =IF($B33="","",IF(23<=MAX('計算'!$CT$6:$CT$405),IFERROR(INDEX('計算'!$Q$6:$Q$405,MATCH(23,'計算'!$CT$6:$CT$405,0)),""),IFERROR(INDEX('計算'!$T$6:$T$405,MATCH(23-MAX('計算'!$CT$6:$CT$405),'計算'!$CU$6:$CU$405,0)),""))) | I33: =IF($B33="","",IF(23<=MAX('計算'!$CT$6:$CT$405),IFERROR(INDEX('計算'!$H$6:$H$405,MATCH(23,'計算'!$CT$6:$CT$405,0)),""),IFERROR(INDEX('計算'!$H$6:$H$405,MATCH(23-MAX('計算'!$CT$6:$CT$405),'計算'!$CU$6:$CU$405,0)),""))) | J33: =IF($B33="","",N($H33)*IFERROR(INDEX('計算'!$G$6:$G$405,IF(23<=MAX('計算'!$CT$6:$CT$405),MATCH(23,'計算'!$CT$6:$CT$405,0),MATCH(23-MAX('計算'!$CT$6:$CT$405),'計算'!$CU$6:$CU$405,0))),1)*N($I33))
B34: =IF(24<=MAX('計算'!$CT$6:$CT$405)+MAX('計算'!$CU$6:$CU$405),24,"") | C34: =IF($B34="","",IF(24<=MAX('計算'!$CT$6:$CT$405),IFERROR(INDEX('計算'!$F$6:$F$405,MATCH(24,'計算'!$CT$6:$CT$405,0)),""),IFERROR(INDEX('計算'!$F$6:$F$405,MATCH(24-MAX('計算'!$CT$6:$CT$405),'計算'!$CU$6:$CU$405,0)),""))) | D34: =IF($B34="","",IF(24<=MAX('計算'!$CT$6:$CT$405),IFERROR(INDEX('計算'!$C$6:$C$405,MATCH(24,'計算'!$CT$6:$CT$405,0))&"",""),IFERROR(INDEX('計算'!$C$6:$C$405,MATCH(24-MAX('計算'!$CT$6:$CT$405),'計算'!$CU$6:$CU$405,0))&"",""))) | E34: =IF($B34="","",IF(24<=MAX('計算'!$CT$6:$CT$405),IFERROR(INDEX('計算'!$D$6:$D$405,MATCH(24,'計算'!$CT$6:$CT$405,0)),""),IFERROR(INDEX('計算'!$D$6:$D$405,MATCH(24-MAX('計算'!$CT$6:$CT$405),'計算'!$CU$6:$CU$405,0)),""))) | F34: =IF($B34="","",IF(24<=MAX('計算'!$CT$6:$CT$405),IFERROR(INDEX('計算'!$P$6:$P$405,MATCH(24,'計算'!$CT$6:$CT$405,0)),""),IFERROR(INDEX('計算'!$S$6:$S$405,MATCH(24-MAX('計算'!$CT$6:$CT$405),'計算'!$CU$6:$CU$405,0)),""))) | G34: =IF($B34="","",IF(24<=MAX('計算'!$CT$6:$CT$405),IFERROR(INDEX('計算'!$CR$6:$CR$405,MATCH(24,'計算'!$CT$6:$CT$405,0)),""),IFERROR(INDEX('計算'!$CR$6:$CR$405,MATCH(24-MAX('計算'!$CT$6:$CT$405),'計算'!$CU$6:$CU$405,0)),""))) | H34: =IF($B34="","",IF(24<=MAX('計算'!$CT$6:$CT$405),IFERROR(INDEX('計算'!$Q$6:$Q$405,MATCH(24,'計算'!$CT$6:$CT$405,0)),""),IFERROR(INDEX('計算'!$T$6:$T$405,MATCH(24-MAX('計算'!$CT$6:$CT$405),'計算'!$CU$6:$CU$405,0)),""))) | I34: =IF($B34="","",IF(24<=MAX('計算'!$CT$6:$CT$405),IFERROR(INDEX('計算'!$H$6:$H$405,MATCH(24,'計算'!$CT$6:$CT$405,0)),""),IFERROR(INDEX('計算'!$H$6:$H$405,MATCH(24-MAX('計算'!$CT$6:$CT$405),'計算'!$CU$6:$CU$405,0)),""))) | J34: =IF($B34="","",N($H34)*IFERROR(INDEX('計算'!$G$6:$G$405,IF(24<=MAX('計算'!$CT$6:$CT$405),MATCH(24,'計算'!$CT$6:$CT$405,0),MATCH(24-MAX('計算'!$CT$6:$CT$405),'計算'!$CU$6:$CU$405,0))),1)*N($I34))
B35: =IF(25<=MAX('計算'!$CT$6:$CT$405)+MAX('計算'!$CU$6:$CU$405),25,"") | C35: =IF($B35="","",IF(25<=MAX('計算'!$CT$6:$CT$405),IFERROR(INDEX('計算'!$F$6:$F$405,MATCH(25,'計算'!$CT$6:$CT$405,0)),""),IFERROR(INDEX('計算'!$F$6:$F$405,MATCH(25-MAX('計算'!$CT$6:$CT$405),'計算'!$CU$6:$CU$405,0)),""))) | D35: =IF($B35="","",IF(25<=MAX('計算'!$CT$6:$CT$405),IFERROR(INDEX('計算'!$C$6:$C$405,MATCH(25,'計算'!$CT$6:$CT$405,0))&"",""),IFERROR(INDEX('計算'!$C$6:$C$405,MATCH(25-MAX('計算'!$CT$6:$CT$405),'計算'!$CU$6:$CU$405,0))&"",""))) | E35: =IF($B35="","",IF(25<=MAX('計算'!$CT$6:$CT$405),IFERROR(INDEX('計算'!$D$6:$D$405,MATCH(25,'計算'!$CT$6:$CT$405,0)),""),IFERROR(INDEX('計算'!$D$6:$D$405,MATCH(25-MAX('計算'!$CT$6:$CT$405),'計算'!$CU$6:$CU$405,0)),""))) | F35: =IF($B35="","",IF(25<=MAX('計算'!$CT$6:$CT$405),IFERROR(INDEX('計算'!$P$6:$P$405,MATCH(25,'計算'!$CT$6:$CT$405,0)),""),IFERROR(INDEX('計算'!$S$6:$S$405,MATCH(25-MAX('計算'!$CT$6:$CT$405),'計算'!$CU$6:$CU$405,0)),""))) | G35: =IF($B35="","",IF(25<=MAX('計算'!$CT$6:$CT$405),IFERROR(INDEX('計算'!$CR$6:$CR$405,MATCH(25,'計算'!$CT$6:$CT$405,0)),""),IFERROR(INDEX('計算'!$CR$6:$CR$405,MATCH(25-MAX('計算'!$CT$6:$CT$405),'計算'!$CU$6:$CU$405,0)),""))) | H35: =IF($B35="","",IF(25<=MAX('計算'!$CT$6:$CT$405),IFERROR(INDEX('計算'!$Q$6:$Q$405,MATCH(25,'計算'!$CT$6:$CT$405,0)),""),IFERROR(INDEX('計算'!$T$6:$T$405,MATCH(25-MAX('計算'!$CT$6:$CT$405),'計算'!$CU$6:$CU$405,0)),""))) | I35: =IF($B35="","",IF(25<=MAX('計算'!$CT$6:$CT$405),IFERROR(INDEX('計算'!$H$6:$H$405,MATCH(25,'計算'!$CT$6:$CT$405,0)),""),IFERROR(INDEX('計算'!$H$6:$H$405,MATCH(25-MAX('計算'!$CT$6:$CT$405),'計算'!$CU$6:$CU$405,0)),""))) | J35: =IF($B35="","",N($H35)*IFERROR(INDEX('計算'!$G$6:$G$405,IF(25<=MAX('計算'!$CT$6:$CT$405),MATCH(25,'計算'!$CT$6:$CT$405,0),MATCH(25-MAX('計算'!$CT$6:$CT$405),'計算'!$CU$6:$CU$405,0))),1)*N($I35))
B36: =IF(26<=MAX('計算'!$CT$6:$CT$405)+MAX('計算'!$CU$6:$CU$405),26,"") | C36: =IF($B36="","",IF(26<=MAX('計算'!$CT$6:$CT$405),IFERROR(INDEX('計算'!$F$6:$F$405,MATCH(26,'計算'!$CT$6:$CT$405,0)),""),IFERROR(INDEX('計算'!$F$6:$F$405,MATCH(26-MAX('計算'!$CT$6:$CT$405),'計算'!$CU$6:$CU$405,0)),""))) | D36: =IF($B36="","",IF(26<=MAX('計算'!$CT$6:$CT$405),IFERROR(INDEX('計算'!$C$6:$C$405,MATCH(26,'計算'!$CT$6:$CT$405,0))&"",""),IFERROR(INDEX('計算'!$C$6:$C$405,MATCH(26-MAX('計算'!$CT$6:$CT$405),'計算'!$CU$6:$CU$405,0))&"",""))) | E36: =IF($B36="","",IF(26<=MAX('計算'!$CT$6:$CT$405),IFERROR(INDEX('計算'!$D$6:$D$405,MATCH(26,'計算'!$CT$6:$CT$405,0)),""),IFERROR(INDEX('計算'!$D$6:$D$405,MATCH(26-MAX('計算'!$CT$6:$CT$405),'計算'!$CU$6:$CU$405,0)),""))) | F36: =IF($B36="","",IF(26<=MAX('計算'!$CT$6:$CT$405),IFERROR(INDEX('計算'!$P$6:$P$405,MATCH(26,'計算'!$CT$6:$CT$405,0)),""),IFERROR(INDEX('計算'!$S$6:$S$405,MATCH(26-MAX('計算'!$CT$6:$CT$405),'計算'!$CU$6:$CU$405,0)),""))) | G36: =IF($B36="","",IF(26<=MAX('計算'!$CT$6:$CT$405),IFERROR(INDEX('計算'!$CR$6:$CR$405,MATCH(26,'計算'!$CT$6:$CT$405,0)),""),IFERROR(INDEX('計算'!$CR$6:$CR$405,MATCH(26-MAX('計算'!$CT$6:$CT$405),'計算'!$CU$6:$CU$405,0)),""))) | H36: =IF($B36="","",IF(26<=MAX('計算'!$CT$6:$CT$405),IFERROR(INDEX('計算'!$Q$6:$Q$405,MATCH(26,'計算'!$CT$6:$CT$405,0)),""),IFERROR(INDEX('計算'!$T$6:$T$405,MATCH(26-MAX('計算'!$CT$6:$CT$405),'計算'!$CU$6:$CU$405,0)),""))) | I36: =IF($B36="","",IF(26<=MAX('計算'!$CT$6:$CT$405),IFERROR(INDEX('計算'!$H$6:$H$405,MATCH(26,'計算'!$CT$6:$CT$405,0)),""),IFERROR(INDEX('計算'!$H$6:$H$405,MATCH(26-MAX('計算'!$CT$6:$CT$405),'計算'!$CU$6:$CU$405,0)),""))) | J36: =IF($B36="","",N($H36)*IFERROR(INDEX('計算'!$G$6:$G$405,IF(26<=MAX('計算'!$CT$6:$CT$405),MATCH(26,'計算'!$CT$6:$CT$405,0),MATCH(26-MAX('計算'!$CT$6:$CT$405),'計算'!$CU$6:$CU$405,0))),1)*N($I36))
B37: =IF(27<=MAX('計算'!$CT$6:$CT$405)+MAX('計算'!$CU$6:$CU$405),27,"") | C37: =IF($B37="","",IF(27<=MAX('計算'!$CT$6:$CT$405),IFERROR(INDEX('計算'!$F$6:$F$405,MATCH(27,'計算'!$CT$6:$CT$405,0)),""),IFERROR(INDEX('計算'!$F$6:$F$405,MATCH(27-MAX('計算'!$CT$6:$CT$405),'計算'!$CU$6:$CU$405,0)),""))) | D37: =IF($B37="","",IF(27<=MAX('計算'!$CT$6:$CT$405),IFERROR(INDEX('計算'!$C$6:$C$405,MATCH(27,'計算'!$CT$6:$CT$405,0))&"",""),IFERROR(INDEX('計算'!$C$6:$C$405,MATCH(27-MAX('計算'!$CT$6:$CT$405),'計算'!$CU$6:$CU$405,0))&"",""))) | E37: =IF($B37="","",IF(27<=MAX('計算'!$CT$6:$CT$405),IFERROR(INDEX('計算'!$D$6:$D$405,MATCH(27,'計算'!$CT$6:$CT$405,0)),""),IFERROR(INDEX('計算'!$D$6:$D$405,MATCH(27-MAX('計算'!$CT$6:$CT$405),'計算'!$CU$6:$CU$405,0)),""))) | F37: =IF($B37="","",IF(27<=MAX('計算'!$CT$6:$CT$405),IFERROR(INDEX('計算'!$P$6:$P$405,MATCH(27,'計算'!$CT$6:$CT$405,0)),""),IFERROR(INDEX('計算'!$S$6:$S$405,MATCH(27-MAX('計算'!$CT$6:$CT$405),'計算'!$CU$6:$CU$405,0)),""))) | G37: =IF($B37="","",IF(27<=MAX('計算'!$CT$6:$CT$405),IFERROR(INDEX('計算'!$CR$6:$CR$405,MATCH(27,'計算'!$CT$6:$CT$405,0)),""),IFERROR(INDEX('計算'!$CR$6:$CR$405,MATCH(27-MAX('計算'!$CT$6:$CT$405),'計算'!$CU$6:$CU$405,0)),""))) | H37: =IF($B37="","",IF(27<=MAX('計算'!$CT$6:$CT$405),IFERROR(INDEX('計算'!$Q$6:$Q$405,MATCH(27,'計算'!$CT$6:$CT$405,0)),""),IFERROR(INDEX('計算'!$T$6:$T$405,MATCH(27-MAX('計算'!$CT$6:$CT$405),'計算'!$CU$6:$CU$405,0)),""))) | I37: =IF($B37="","",IF(27<=MAX('計算'!$CT$6:$CT$405),IFERROR(INDEX('計算'!$H$6:$H$405,MATCH(27,'計算'!$CT$6:$CT$405,0)),""),IFERROR(INDEX('計算'!$H$6:$H$405,MATCH(27-MAX('計算'!$CT$6:$CT$405),'計算'!$CU$6:$CU$405,0)),""))) | J37: =IF($B37="","",N($H37)*IFERROR(INDEX('計算'!$G$6:$G$405,IF(27<=MAX('計算'!$CT$6:$CT$405),MATCH(27,'計算'!$CT$6:$CT$405,0),MATCH(27-MAX('計算'!$CT$6:$CT$405),'計算'!$CU$6:$CU$405,0))),1)*N($I37))
B38: =IF(28<=MAX('計算'!$CT$6:$CT$405)+MAX('計算'!$CU$6:$CU$405),28,"") | C38: =IF($B38="","",IF(28<=MAX('計算'!$CT$6:$CT$405),IFERROR(INDEX('計算'!$F$6:$F$405,MATCH(28,'計算'!$CT$6:$CT$405,0)),""),IFERROR(INDEX('計算'!$F$6:$F$405,MATCH(28-MAX('計算'!$CT$6:$CT$405),'計算'!$CU$6:$CU$405,0)),""))) | D38: =IF($B38="","",IF(28<=MAX('計算'!$CT$6:$CT$405),IFERROR(INDEX('計算'!$C$6:$C$405,MATCH(28,'計算'!$CT$6:$CT$405,0))&"",""),IFERROR(INDEX('計算'!$C$6:$C$405,MATCH(28-MAX('計算'!$CT$6:$CT$405),'計算'!$CU$6:$CU$405,0))&"",""))) | E38: =IF($B38="","",IF(28<=MAX('計算'!$CT$6:$CT$405),IFERROR(INDEX('計算'!$D$6:$D$405,MATCH(28,'計算'!$CT$6:$CT$405,0)),""),IFERROR(INDEX('計算'!$D$6:$D$405,MATCH(28-MAX('計算'!$CT$6:$CT$405),'計算'!$CU$6:$CU$405,0)),""))) | F38: =IF($B38="","",IF(28<=MAX('計算'!$CT$6:$CT$405),IFERROR(INDEX('計算'!$P$6:$P$405,MATCH(28,'計算'!$CT$6:$CT$405,0)),""),IFERROR(INDEX('計算'!$S$6:$S$405,MATCH(28-MAX('計算'!$CT$6:$CT$405),'計算'!$CU$6:$CU$405,0)),""))) | G38: =IF($B38="","",IF(28<=MAX('計算'!$CT$6:$CT$405),IFERROR(INDEX('計算'!$CR$6:$CR$405,MATCH(28,'計算'!$CT$6:$CT$405,0)),""),IFERROR(INDEX('計算'!$CR$6:$CR$405,MATCH(28-MAX('計算'!$CT$6:$CT$405),'計算'!$CU$6:$CU$405,0)),""))) | H38: =IF($B38="","",IF(28<=MAX('計算'!$CT$6:$CT$405),IFERROR(INDEX('計算'!$Q$6:$Q$405,MATCH(28,'計算'!$CT$6:$CT$405,0)),""),IFERROR(INDEX('計算'!$T$6:$T$405,MATCH(28-MAX('計算'!$CT$6:$CT$405),'計算'!$CU$6:$CU$405,0)),""))) | I38: =IF($B38="","",IF(28<=MAX('計算'!$CT$6:$CT$405),IFERROR(INDEX('計算'!$H$6:$H$405,MATCH(28,'計算'!$CT$6:$CT$405,0)),""),IFERROR(INDEX('計算'!$H$6:$H$405,MATCH(28-MAX('計算'!$CT$6:$CT$405),'計算'!$CU$6:$CU$405,0)),""))) | J38: =IF($B38="","",N($H38)*IFERROR(INDEX('計算'!$G$6:$G$405,IF(28<=MAX('計算'!$CT$6:$CT$405),MATCH(28,'計算'!$CT$6:$CT$405,0),MATCH(28-MAX('計算'!$CT$6:$CT$405),'計算'!$CU$6:$CU$405,0))),1)*N($I38))
B39: =IF(29<=MAX('計算'!$CT$6:$CT$405)+MAX('計算'!$CU$6:$CU$405),29,"") | C39: =IF($B39="","",IF(29<=MAX('計算'!$CT$6:$CT$405),IFERROR(INDEX('計算'!$F$6:$F$405,MATCH(29,'計算'!$CT$6:$CT$405,0)),""),IFERROR(INDEX('計算'!$F$6:$F$405,MATCH(29-MAX('計算'!$CT$6:$CT$405),'計算'!$CU$6:$CU$405,0)),""))) | D39: =IF($B39="","",IF(29<=MAX('計算'!$CT$6:$CT$405),IFERROR(INDEX('計算'!$C$6:$C$405,MATCH(29,'計算'!$CT$6:$CT$405,0))&"",""),IFERROR(INDEX('計算'!$C$6:$C$405,MATCH(29-MAX('計算'!$CT$6:$CT$405),'計算'!$CU$6:$CU$405,0))&"",""))) | E39: =IF($B39="","",IF(29<=MAX('計算'!$CT$6:$CT$405),IFERROR(INDEX('計算'!$D$6:$D$405,MATCH(29,'計算'!$CT$6:$CT$405,0)),""),IFERROR(INDEX('計算'!$D$6:$D$405,MATCH(29-MAX('計算'!$CT$6:$CT$405),'計算'!$CU$6:$CU$405,0)),""))) | F39: =IF($B39="","",IF(29<=MAX('計算'!$CT$6:$CT$405),IFERROR(INDEX('計算'!$P$6:$P$405,MATCH(29,'計算'!$CT$6:$CT$405,0)),""),IFERROR(INDEX('計算'!$S$6:$S$405,MATCH(29-MAX('計算'!$CT$6:$CT$405),'計算'!$CU$6:$CU$405,0)),""))) | G39: =IF($B39="","",IF(29<=MAX('計算'!$CT$6:$CT$405),IFERROR(INDEX('計算'!$CR$6:$CR$405,MATCH(29,'計算'!$CT$6:$CT$405,0)),""),IFERROR(INDEX('計算'!$CR$6:$CR$405,MATCH(29-MAX('計算'!$CT$6:$CT$405),'計算'!$CU$6:$CU$405,0)),""))) | H39: =IF($B39="","",IF(29<=MAX('計算'!$CT$6:$CT$405),IFERROR(INDEX('計算'!$Q$6:$Q$405,MATCH(29,'計算'!$CT$6:$CT$405,0)),""),IFERROR(INDEX('計算'!$T$6:$T$405,MATCH(29-MAX('計算'!$CT$6:$CT$405),'計算'!$CU$6:$CU$405,0)),""))) | I39: =IF($B39="","",IF(29<=MAX('計算'!$CT$6:$CT$405),IFERROR(INDEX('計算'!$H$6:$H$405,MATCH(29,'計算'!$CT$6:$CT$405,0)),""),IFERROR(INDEX('計算'!$H$6:$H$405,MATCH(29-MAX('計算'!$CT$6:$CT$405),'計算'!$CU$6:$CU$405,0)),""))) | J39: =IF($B39="","",N($H39)*IFERROR(INDEX('計算'!$G$6:$G$405,IF(29<=MAX('計算'!$CT$6:$CT$405),MATCH(29,'計算'!$CT$6:$CT$405,0),MATCH(29-MAX('計算'!$CT$6:$CT$405),'計算'!$CU$6:$CU$405,0))),1)*N($I39))
B40: =IF(30<=MAX('計算'!$CT$6:$CT$405)+MAX('計算'!$CU$6:$CU$405),30,"") | C40: =IF($B40="","",IF(30<=MAX('計算'!$CT$6:$CT$405),IFERROR(INDEX('計算'!$F$6:$F$405,MATCH(30,'計算'!$CT$6:$CT$405,0)),""),IFERROR(INDEX('計算'!$F$6:$F$405,MATCH(30-MAX('計算'!$CT$6:$CT$405),'計算'!$CU$6:$CU$405,0)),""))) | D40: =IF($B40="","",IF(30<=MAX('計算'!$CT$6:$CT$405),IFERROR(INDEX('計算'!$C$6:$C$405,MATCH(30,'計算'!$CT$6:$CT$405,0))&"",""),IFERROR(INDEX('計算'!$C$6:$C$405,MATCH(30-MAX('計算'!$CT$6:$CT$405),'計算'!$CU$6:$CU$405,0))&"",""))) | E40: =IF($B40="","",IF(30<=MAX('計算'!$CT$6:$CT$405),IFERROR(INDEX('計算'!$D$6:$D$405,MATCH(30,'計算'!$CT$6:$CT$405,0)),""),IFERROR(INDEX('計算'!$D$6:$D$405,MATCH(30-MAX('計算'!$CT$6:$CT$405),'計算'!$CU$6:$CU$405,0)),""))) | F40: =IF($B40="","",IF(30<=MAX('計算'!$CT$6:$CT$405),IFERROR(INDEX('計算'!$P$6:$P$405,MATCH(30,'計算'!$CT$6:$CT$405,0)),""),IFERROR(INDEX('計算'!$S$6:$S$405,MATCH(30-MAX('計算'!$CT$6:$CT$405),'計算'!$CU$6:$CU$405,0)),""))) | G40: =IF($B40="","",IF(30<=MAX('計算'!$CT$6:$CT$405),IFERROR(INDEX('計算'!$CR$6:$CR$405,MATCH(30,'計算'!$CT$6:$CT$405,0)),""),IFERROR(INDEX('計算'!$CR$6:$CR$405,MATCH(30-MAX('計算'!$CT$6:$CT$405),'計算'!$CU$6:$CU$405,0)),""))) | H40: =IF($B40="","",IF(30<=MAX('計算'!$CT$6:$CT$405),IFERROR(INDEX('計算'!$Q$6:$Q$405,MATCH(30,'計算'!$CT$6:$CT$405,0)),""),IFERROR(INDEX('計算'!$T$6:$T$405,MATCH(30-MAX('計算'!$CT$6:$CT$405),'計算'!$CU$6:$CU$405,0)),""))) | I40: =IF($B40="","",IF(30<=MAX('計算'!$CT$6:$CT$405),IFERROR(INDEX('計算'!$H$6:$H$405,MATCH(30,'計算'!$CT$6:$CT$405,0)),""),IFERROR(INDEX('計算'!$H$6:$H$405,MATCH(30-MAX('計算'!$CT$6:$CT$405),'計算'!$CU$6:$CU$405,0)),""))) | J40: =IF($B40="","",N($H40)*IFERROR(INDEX('計算'!$G$6:$G$405,IF(30<=MAX('計算'!$CT$6:$CT$405),MATCH(30,'計算'!$CT$6:$CT$405,0),MATCH(30-MAX('計算'!$CT$6:$CT$405),'計算'!$CU$6:$CU$405,0))),1)*N($I40))
B41: =IF(31<=MAX('計算'!$CT$6:$CT$405)+MAX('計算'!$CU$6:$CU$405),31,"") | C41: =IF($B41="","",IF(31<=MAX('計算'!$CT$6:$CT$405),IFERROR(INDEX('計算'!$F$6:$F$405,MATCH(31,'計算'!$CT$6:$CT$405,0)),""),IFERROR(INDEX('計算'!$F$6:$F$405,MATCH(31-MAX('計算'!$CT$6:$CT$405),'計算'!$CU$6:$CU$405,0)),""))) | D41: =IF($B41="","",IF(31<=MAX('計算'!$CT$6:$CT$405),IFERROR(INDEX('計算'!$C$6:$C$405,MATCH(31,'計算'!$CT$6:$CT$405,0))&"",""),IFERROR(INDEX('計算'!$C$6:$C$405,MATCH(31-MAX('計算'!$CT$6:$CT$405),'計算'!$CU$6:$CU$405,0))&"",""))) | E41: =IF($B41="","",IF(31<=MAX('計算'!$CT$6:$CT$405),IFERROR(INDEX('計算'!$D$6:$D$405,MATCH(31,'計算'!$CT$6:$CT$405,0)),""),IFERROR(INDEX('計算'!$D$6:$D$405,MATCH(31-MAX('計算'!$CT$6:$CT$405),'計算'!$CU$6:$CU$405,0)),""))) | F41: =IF($B41="","",IF(31<=MAX('計算'!$CT$6:$CT$405),IFERROR(INDEX('計算'!$P$6:$P$405,MATCH(31,'計算'!$CT$6:$CT$405,0)),""),IFERROR(INDEX('計算'!$S$6:$S$405,MATCH(31-MAX('計算'!$CT$6:$CT$405),'計算'!$CU$6:$CU$405,0)),""))) | G41: =IF($B41="","",IF(31<=MAX('計算'!$CT$6:$CT$405),IFERROR(INDEX('計算'!$CR$6:$CR$405,MATCH(31,'計算'!$CT$6:$CT$405,0)),""),IFERROR(INDEX('計算'!$CR$6:$CR$405,MATCH(31-MAX('計算'!$CT$6:$CT$405),'計算'!$CU$6:$CU$405,0)),""))) | H41: =IF($B41="","",IF(31<=MAX('計算'!$CT$6:$CT$405),IFERROR(INDEX('計算'!$Q$6:$Q$405,MATCH(31,'計算'!$CT$6:$CT$405,0)),""),IFERROR(INDEX('計算'!$T$6:$T$405,MATCH(31-MAX('計算'!$CT$6:$CT$405),'計算'!$CU$6:$CU$405,0)),""))) | I41: =IF($B41="","",IF(31<=MAX('計算'!$CT$6:$CT$405),IFERROR(INDEX('計算'!$H$6:$H$405,MATCH(31,'計算'!$CT$6:$CT$405,0)),""),IFERROR(INDEX('計算'!$H$6:$H$405,MATCH(31-MAX('計算'!$CT$6:$CT$405),'計算'!$CU$6:$CU$405,0)),""))) | J41: =IF($B41="","",N($H41)*IFERROR(INDEX('計算'!$G$6:$G$405,IF(31<=MAX('計算'!$CT$6:$CT$405),MATCH(31,'計算'!$CT$6:$CT$405,0),MATCH(31-MAX('計算'!$CT$6:$CT$405),'計算'!$CU$6:$CU$405,0))),1)*N($I41))
B42: =IF(32<=MAX('計算'!$CT$6:$CT$405)+MAX('計算'!$CU$6:$CU$405),32,"") | C42: =IF($B42="","",IF(32<=MAX('計算'!$CT$6:$CT$405),IFERROR(INDEX('計算'!$F$6:$F$405,MATCH(32,'計算'!$CT$6:$CT$405,0)),""),IFERROR(INDEX('計算'!$F$6:$F$405,MATCH(32-MAX('計算'!$CT$6:$CT$405),'計算'!$CU$6:$CU$405,0)),""))) | D42: =IF($B42="","",IF(32<=MAX('計算'!$CT$6:$CT$405),IFERROR(INDEX('計算'!$C$6:$C$405,MATCH(32,'計算'!$CT$6:$CT$405,0))&"",""),IFERROR(INDEX('計算'!$C$6:$C$405,MATCH(32-MAX('計算'!$CT$6:$CT$405),'計算'!$CU$6:$CU$405,0))&"",""))) | E42: =IF($B42="","",IF(32<=MAX('計算'!$CT$6:$CT$405),IFERROR(INDEX('計算'!$D$6:$D$405,MATCH(32,'計算'!$CT$6:$CT$405,0)),""),IFERROR(INDEX('計算'!$D$6:$D$405,MATCH(32-MAX('計算'!$CT$6:$CT$405),'計算'!$CU$6:$CU$405,0)),""))) | F42: =IF($B42="","",IF(32<=MAX('計算'!$CT$6:$CT$405),IFERROR(INDEX('計算'!$P$6:$P$405,MATCH(32,'計算'!$CT$6:$CT$405,0)),""),IFERROR(INDEX('計算'!$S$6:$S$405,MATCH(32-MAX('計算'!$CT$6:$CT$405),'計算'!$CU$6:$CU$405,0)),""))) | G42: =IF($B42="","",IF(32<=MAX('計算'!$CT$6:$CT$405),IFERROR(INDEX('計算'!$CR$6:$CR$405,MATCH(32,'計算'!$CT$6:$CT$405,0)),""),IFERROR(INDEX('計算'!$CR$6:$CR$405,MATCH(32-MAX('計算'!$CT$6:$CT$405),'計算'!$CU$6:$CU$405,0)),""))) | H42: =IF($B42="","",IF(32<=MAX('計算'!$CT$6:$CT$405),IFERROR(INDEX('計算'!$Q$6:$Q$405,MATCH(32,'計算'!$CT$6:$CT$405,0)),""),IFERROR(INDEX('計算'!$T$6:$T$405,MATCH(32-MAX('計算'!$CT$6:$CT$405),'計算'!$CU$6:$CU$405,0)),""))) | I42: =IF($B42="","",IF(32<=MAX('計算'!$CT$6:$CT$405),IFERROR(INDEX('計算'!$H$6:$H$405,MATCH(32,'計算'!$CT$6:$CT$405,0)),""),IFERROR(INDEX('計算'!$H$6:$H$405,MATCH(32-MAX('計算'!$CT$6:$CT$405),'計算'!$CU$6:$CU$405,0)),""))) | J42: =IF($B42="","",N($H42)*IFERROR(INDEX('計算'!$G$6:$G$405,IF(32<=MAX('計算'!$CT$6:$CT$405),MATCH(32,'計算'!$CT$6:$CT$405,0),MATCH(32-MAX('計算'!$CT$6:$CT$405),'計算'!$CU$6:$CU$405,0))),1)*N($I42))
B43: =IF(33<=MAX('計算'!$CT$6:$CT$405)+MAX('計算'!$CU$6:$CU$405),33,"") | C43: =IF($B43="","",IF(33<=MAX('計算'!$CT$6:$CT$405),IFERROR(INDEX('計算'!$F$6:$F$405,MATCH(33,'計算'!$CT$6:$CT$405,0)),""),IFERROR(INDEX('計算'!$F$6:$F$405,MATCH(33-MAX('計算'!$CT$6:$CT$405),'計算'!$CU$6:$CU$405,0)),""))) | D43: =IF($B43="","",IF(33<=MAX('計算'!$CT$6:$CT$405),IFERROR(INDEX('計算'!$C$6:$C$405,MATCH(33,'計算'!$CT$6:$CT$405,0))&"",""),IFERROR(INDEX('計算'!$C$6:$C$405,MATCH(33-MAX('計算'!$CT$6:$CT$405),'計算'!$CU$6:$CU$405,0))&"",""))) | E43: =IF($B43="","",IF(33<=MAX('計算'!$CT$6:$CT$405),IFERROR(INDEX('計算'!$D$6:$D$405,MATCH(33,'計算'!$CT$6:$CT$405,0)),""),IFERROR(INDEX('計算'!$D$6:$D$405,MATCH(33-MAX('計算'!$CT$6:$CT$405),'計算'!$CU$6:$CU$405,0)),""))) | F43: =IF($B43="","",IF(33<=MAX('計算'!$CT$6:$CT$405),IFERROR(INDEX('計算'!$P$6:$P$405,MATCH(33,'計算'!$CT$6:$CT$405,0)),""),IFERROR(INDEX('計算'!$S$6:$S$405,MATCH(33-MAX('計算'!$CT$6:$CT$405),'計算'!$CU$6:$CU$405,0)),""))) | G43: =IF($B43="","",IF(33<=MAX('計算'!$CT$6:$CT$405),IFERROR(INDEX('計算'!$CR$6:$CR$405,MATCH(33,'計算'!$CT$6:$CT$405,0)),""),IFERROR(INDEX('計算'!$CR$6:$CR$405,MATCH(33-MAX('計算'!$CT$6:$CT$405),'計算'!$CU$6:$CU$405,0)),""))) | H43: =IF($B43="","",IF(33<=MAX('計算'!$CT$6:$CT$405),IFERROR(INDEX('計算'!$Q$6:$Q$405,MATCH(33,'計算'!$CT$6:$CT$405,0)),""),IFERROR(INDEX('計算'!$T$6:$T$405,MATCH(33-MAX('計算'!$CT$6:$CT$405),'計算'!$CU$6:$CU$405,0)),""))) | I43: =IF($B43="","",IF(33<=MAX('計算'!$CT$6:$CT$405),IFERROR(INDEX('計算'!$H$6:$H$405,MATCH(33,'計算'!$CT$6:$CT$405,0)),""),IFERROR(INDEX('計算'!$H$6:$H$405,MATCH(33-MAX('計算'!$CT$6:$CT$405),'計算'!$CU$6:$CU$405,0)),""))) | J43: =IF($B43="","",N($H43)*IFERROR(INDEX('計算'!$G$6:$G$405,IF(33<=MAX('計算'!$CT$6:$CT$405),MATCH(33,'計算'!$CT$6:$CT$405,0),MATCH(33-MAX('計算'!$CT$6:$CT$405),'計算'!$CU$6:$CU$405,0))),1)*N($I43))
B44: =IF(34<=MAX('計算'!$CT$6:$CT$405)+MAX('計算'!$CU$6:$CU$405),34,"") | C44: =IF($B44="","",IF(34<=MAX('計算'!$CT$6:$CT$405),IFERROR(INDEX('計算'!$F$6:$F$405,MATCH(34,'計算'!$CT$6:$CT$405,0)),""),IFERROR(INDEX('計算'!$F$6:$F$405,MATCH(34-MAX('計算'!$CT$6:$CT$405),'計算'!$CU$6:$CU$405,0)),""))) | D44: =IF($B44="","",IF(34<=MAX('計算'!$CT$6:$CT$405),IFERROR(INDEX('計算'!$C$6:$C$405,MATCH(34,'計算'!$CT$6:$CT$405,0))&"",""),IFERROR(INDEX('計算'!$C$6:$C$405,MATCH(34-MAX('計算'!$CT$6:$CT$405),'計算'!$CU$6:$CU$405,0))&"",""))) | E44: =IF($B44="","",IF(34<=MAX('計算'!$CT$6:$CT$405),IFERROR(INDEX('計算'!$D$6:$D$405,MATCH(34,'計算'!$CT$6:$CT$405,0)),""),IFERROR(INDEX('計算'!$D$6:$D$405,MATCH(34-MAX('計算'!$CT$6:$CT$405),'計算'!$CU$6:$CU$405,0)),""))) | F44: =IF($B44="","",IF(34<=MAX('計算'!$CT$6:$CT$405),IFERROR(INDEX('計算'!$P$6:$P$405,MATCH(34,'計算'!$CT$6:$CT$405,0)),""),IFERROR(INDEX('計算'!$S$6:$S$405,MATCH(34-MAX('計算'!$CT$6:$CT$405),'計算'!$CU$6:$CU$405,0)),""))) | G44: =IF($B44="","",IF(34<=MAX('計算'!$CT$6:$CT$405),IFERROR(INDEX('計算'!$CR$6:$CR$405,MATCH(34,'計算'!$CT$6:$CT$405,0)),""),IFERROR(INDEX('計算'!$CR$6:$CR$405,MATCH(34-MAX('計算'!$CT$6:$CT$405),'計算'!$CU$6:$CU$405,0)),""))) | H44: =IF($B44="","",IF(34<=MAX('計算'!$CT$6:$CT$405),IFERROR(INDEX('計算'!$Q$6:$Q$405,MATCH(34,'計算'!$CT$6:$CT$405,0)),""),IFERROR(INDEX('計算'!$T$6:$T$405,MATCH(34-MAX('計算'!$CT$6:$CT$405),'計算'!$CU$6:$CU$405,0)),""))) | I44: =IF($B44="","",IF(34<=MAX('計算'!$CT$6:$CT$405),IFERROR(INDEX('計算'!$H$6:$H$405,MATCH(34,'計算'!$CT$6:$CT$405,0)),""),IFERROR(INDEX('計算'!$H$6:$H$405,MATCH(34-MAX('計算'!$CT$6:$CT$405),'計算'!$CU$6:$CU$405,0)),""))) | J44: =IF($B44="","",N($H44)*IFERROR(INDEX('計算'!$G$6:$G$405,IF(34<=MAX('計算'!$CT$6:$CT$405),MATCH(34,'計算'!$CT$6:$CT$405,0),MATCH(34-MAX('計算'!$CT$6:$CT$405),'計算'!$CU$6:$CU$405,0))),1)*N($I44))
B45: =IF(35<=MAX('計算'!$CT$6:$CT$405)+MAX('計算'!$CU$6:$CU$405),35,"") | C45: =IF($B45="","",IF(35<=MAX('計算'!$CT$6:$CT$405),IFERROR(INDEX('計算'!$F$6:$F$405,MATCH(35,'計算'!$CT$6:$CT$405,0)),""),IFERROR(INDEX('計算'!$F$6:$F$405,MATCH(35-MAX('計算'!$CT$6:$CT$405),'計算'!$CU$6:$CU$405,0)),""))) | D45: =IF($B45="","",IF(35<=MAX('計算'!$CT$6:$CT$405),IFERROR(INDEX('計算'!$C$6:$C$405,MATCH(35,'計算'!$CT$6:$CT$405,0))&"",""),IFERROR(INDEX('計算'!$C$6:$C$405,MATCH(35-MAX('計算'!$CT$6:$CT$405),'計算'!$CU$6:$CU$405,0))&"",""))) | E45: =IF($B45="","",IF(35<=MAX('計算'!$CT$6:$CT$405),IFERROR(INDEX('計算'!$D$6:$D$405,MATCH(35,'計算'!$CT$6:$CT$405,0)),""),IFERROR(INDEX('計算'!$D$6:$D$405,MATCH(35-MAX('計算'!$CT$6:$CT$405),'計算'!$CU$6:$CU$405,0)),""))) | F45: =IF($B45="","",IF(35<=MAX('計算'!$CT$6:$CT$405),IFERROR(INDEX('計算'!$P$6:$P$405,MATCH(35,'計算'!$CT$6:$CT$405,0)),""),IFERROR(INDEX('計算'!$S$6:$S$405,MATCH(35-MAX('計算'!$CT$6:$CT$405),'計算'!$CU$6:$CU$405,0)),""))) | G45: =IF($B45="","",IF(35<=MAX('計算'!$CT$6:$CT$405),IFERROR(INDEX('計算'!$CR$6:$CR$405,MATCH(35,'計算'!$CT$6:$CT$405,0)),""),IFERROR(INDEX('計算'!$CR$6:$CR$405,MATCH(35-MAX('計算'!$CT$6:$CT$405),'計算'!$CU$6:$CU$405,0)),""))) | H45: =IF($B45="","",IF(35<=MAX('計算'!$CT$6:$CT$405),IFERROR(INDEX('計算'!$Q$6:$Q$405,MATCH(35,'計算'!$CT$6:$CT$405,0)),""),IFERROR(INDEX('計算'!$T$6:$T$405,MATCH(35-MAX('計算'!$CT$6:$CT$405),'計算'!$CU$6:$CU$405,0)),""))) | I45: =IF($B45="","",IF(35<=MAX('計算'!$CT$6:$CT$405),IFERROR(INDEX('計算'!$H$6:$H$405,MATCH(35,'計算'!$CT$6:$CT$405,0)),""),IFERROR(INDEX('計算'!$H$6:$H$405,MATCH(35-MAX('計算'!$CT$6:$CT$405),'計算'!$CU$6:$CU$405,0)),""))) | J45: =IF($B45="","",N($H45)*IFERROR(INDEX('計算'!$G$6:$G$405,IF(35<=MAX('計算'!$CT$6:$CT$405),MATCH(35,'計算'!$CT$6:$CT$405,0),MATCH(35-MAX('計算'!$CT$6:$CT$405),'計算'!$CU$6:$CU$405,0))),1)*N($I45))
B46: =IF(36<=MAX('計算'!$CT$6:$CT$405)+MAX('計算'!$CU$6:$CU$405),36,"") | C46: =IF($B46="","",IF(36<=MAX('計算'!$CT$6:$CT$405),IFERROR(INDEX('計算'!$F$6:$F$405,MATCH(36,'計算'!$CT$6:$CT$405,0)),""),IFERROR(INDEX('計算'!$F$6:$F$405,MATCH(36-MAX('計算'!$CT$6:$CT$405),'計算'!$CU$6:$CU$405,0)),""))) | D46: =IF($B46="","",IF(36<=MAX('計算'!$CT$6:$CT$405),IFERROR(INDEX('計算'!$C$6:$C$405,MATCH(36,'計算'!$CT$6:$CT$405,0))&"",""),IFERROR(INDEX('計算'!$C$6:$C$405,MATCH(36-MAX('計算'!$CT$6:$CT$405),'計算'!$CU$6:$CU$405,0))&"",""))) | E46: =IF($B46="","",IF(36<=MAX('計算'!$CT$6:$CT$405),IFERROR(INDEX('計算'!$D$6:$D$405,MATCH(36,'計算'!$CT$6:$CT$405,0)),""),IFERROR(INDEX('計算'!$D$6:$D$405,MATCH(36-MAX('計算'!$CT$6:$CT$405),'計算'!$CU$6:$CU$405,0)),""))) | F46: =IF($B46="","",IF(36<=MAX('計算'!$CT$6:$CT$405),IFERROR(INDEX('計算'!$P$6:$P$405,MATCH(36,'計算'!$CT$6:$CT$405,0)),""),IFERROR(INDEX('計算'!$S$6:$S$405,MATCH(36-MAX('計算'!$CT$6:$CT$405),'計算'!$CU$6:$CU$405,0)),""))) | G46: =IF($B46="","",IF(36<=MAX('計算'!$CT$6:$CT$405),IFERROR(INDEX('計算'!$CR$6:$CR$405,MATCH(36,'計算'!$CT$6:$CT$405,0)),""),IFERROR(INDEX('計算'!$CR$6:$CR$405,MATCH(36-MAX('計算'!$CT$6:$CT$405),'計算'!$CU$6:$CU$405,0)),""))) | H46: =IF($B46="","",IF(36<=MAX('計算'!$CT$6:$CT$405),IFERROR(INDEX('計算'!$Q$6:$Q$405,MATCH(36,'計算'!$CT$6:$CT$405,0)),""),IFERROR(INDEX('計算'!$T$6:$T$405,MATCH(36-MAX('計算'!$CT$6:$CT$405),'計算'!$CU$6:$CU$405,0)),""))) | I46: =IF($B46="","",IF(36<=MAX('計算'!$CT$6:$CT$405),IFERROR(INDEX('計算'!$H$6:$H$405,MATCH(36,'計算'!$CT$6:$CT$405,0)),""),IFERROR(INDEX('計算'!$H$6:$H$405,MATCH(36-MAX('計算'!$CT$6:$CT$405),'計算'!$CU$6:$CU$405,0)),""))) | J46: =IF($B46="","",N($H46)*IFERROR(INDEX('計算'!$G$6:$G$405,IF(36<=MAX('計算'!$CT$6:$CT$405),MATCH(36,'計算'!$CT$6:$CT$405,0),MATCH(36-MAX('計算'!$CT$6:$CT$405),'計算'!$CU$6:$CU$405,0))),1)*N($I46))
B47: =IF(37<=MAX('計算'!$CT$6:$CT$405)+MAX('計算'!$CU$6:$CU$405),37,"") | C47: =IF($B47="","",IF(37<=MAX('計算'!$CT$6:$CT$405),IFERROR(INDEX('計算'!$F$6:$F$405,MATCH(37,'計算'!$CT$6:$CT$405,0)),""),IFERROR(INDEX('計算'!$F$6:$F$405,MATCH(37-MAX('計算'!$CT$6:$CT$405),'計算'!$CU$6:$CU$405,0)),""))) | D47: =IF($B47="","",IF(37<=MAX('計算'!$CT$6:$CT$405),IFERROR(INDEX('計算'!$C$6:$C$405,MATCH(37,'計算'!$CT$6:$CT$405,0))&"",""),IFERROR(INDEX('計算'!$C$6:$C$405,MATCH(37-MAX('計算'!$CT$6:$CT$405),'計算'!$CU$6:$CU$405,0))&"",""))) | E47: =IF($B47="","",IF(37<=MAX('計算'!$CT$6:$CT$405),IFERROR(INDEX('計算'!$D$6:$D$405,MATCH(37,'計算'!$CT$6:$CT$405,0)),""),IFERROR(INDEX('計算'!$D$6:$D$405,MATCH(37-MAX('計算'!$CT$6:$CT$405),'計算'!$CU$6:$CU$405,0)),""))) | F47: =IF($B47="","",IF(37<=MAX('計算'!$CT$6:$CT$405),IFERROR(INDEX('計算'!$P$6:$P$405,MATCH(37,'計算'!$CT$6:$CT$405,0)),""),IFERROR(INDEX('計算'!$S$6:$S$405,MATCH(37-MAX('計算'!$CT$6:$CT$405),'計算'!$CU$6:$CU$405,0)),""))) | G47: =IF($B47="","",IF(37<=MAX('計算'!$CT$6:$CT$405),IFERROR(INDEX('計算'!$CR$6:$CR$405,MATCH(37,'計算'!$CT$6:$CT$405,0)),""),IFERROR(INDEX('計算'!$CR$6:$CR$405,MATCH(37-MAX('計算'!$CT$6:$CT$405),'計算'!$CU$6:$CU$405,0)),""))) | H47: =IF($B47="","",IF(37<=MAX('計算'!$CT$6:$CT$405),IFERROR(INDEX('計算'!$Q$6:$Q$405,MATCH(37,'計算'!$CT$6:$CT$405,0)),""),IFERROR(INDEX('計算'!$T$6:$T$405,MATCH(37-MAX('計算'!$CT$6:$CT$405),'計算'!$CU$6:$CU$405,0)),""))) | I47: =IF($B47="","",IF(37<=MAX('計算'!$CT$6:$CT$405),IFERROR(INDEX('計算'!$H$6:$H$405,MATCH(37,'計算'!$CT$6:$CT$405,0)),""),IFERROR(INDEX('計算'!$H$6:$H$405,MATCH(37-MAX('計算'!$CT$6:$CT$405),'計算'!$CU$6:$CU$405,0)),""))) | J47: =IF($B47="","",N($H47)*IFERROR(INDEX('計算'!$G$6:$G$405,IF(37<=MAX('計算'!$CT$6:$CT$405),MATCH(37,'計算'!$CT$6:$CT$405,0),MATCH(37-MAX('計算'!$CT$6:$CT$405),'計算'!$CU$6:$CU$405,0))),1)*N($I47))
B48: =IF(38<=MAX('計算'!$CT$6:$CT$405)+MAX('計算'!$CU$6:$CU$405),38,"") | C48: =IF($B48="","",IF(38<=MAX('計算'!$CT$6:$CT$405),IFERROR(INDEX('計算'!$F$6:$F$405,MATCH(38,'計算'!$CT$6:$CT$405,0)),""),IFERROR(INDEX('計算'!$F$6:$F$405,MATCH(38-MAX('計算'!$CT$6:$CT$405),'計算'!$CU$6:$CU$405,0)),""))) | D48: =IF($B48="","",IF(38<=MAX('計算'!$CT$6:$CT$405),IFERROR(INDEX('計算'!$C$6:$C$405,MATCH(38,'計算'!$CT$6:$CT$405,0))&"",""),IFERROR(INDEX('計算'!$C$6:$C$405,MATCH(38-MAX('計算'!$CT$6:$CT$405),'計算'!$CU$6:$CU$405,0))&"",""))) | E48: =IF($B48="","",IF(38<=MAX('計算'!$CT$6:$CT$405),IFERROR(INDEX('計算'!$D$6:$D$405,MATCH(38,'計算'!$CT$6:$CT$405,0)),""),IFERROR(INDEX('計算'!$D$6:$D$405,MATCH(38-MAX('計算'!$CT$6:$CT$405),'計算'!$CU$6:$CU$405,0)),""))) | F48: =IF($B48="","",IF(38<=MAX('計算'!$CT$6:$CT$405),IFERROR(INDEX('計算'!$P$6:$P$405,MATCH(38,'計算'!$CT$6:$CT$405,0)),""),IFERROR(INDEX('計算'!$S$6:$S$405,MATCH(38-MAX('計算'!$CT$6:$CT$405),'計算'!$CU$6:$CU$405,0)),""))) | G48: =IF($B48="","",IF(38<=MAX('計算'!$CT$6:$CT$405),IFERROR(INDEX('計算'!$CR$6:$CR$405,MATCH(38,'計算'!$CT$6:$CT$405,0)),""),IFERROR(INDEX('計算'!$CR$6:$CR$405,MATCH(38-MAX('計算'!$CT$6:$CT$405),'計算'!$CU$6:$CU$405,0)),""))) | H48: =IF($B48="","",IF(38<=MAX('計算'!$CT$6:$CT$405),IFERROR(INDEX('計算'!$Q$6:$Q$405,MATCH(38,'計算'!$CT$6:$CT$405,0)),""),IFERROR(INDEX('計算'!$T$6:$T$405,MATCH(38-MAX('計算'!$CT$6:$CT$405),'計算'!$CU$6:$CU$405,0)),""))) | I48: =IF($B48="","",IF(38<=MAX('計算'!$CT$6:$CT$405),IFERROR(INDEX('計算'!$H$6:$H$405,MATCH(38,'計算'!$CT$6:$CT$405,0)),""),IFERROR(INDEX('計算'!$H$6:$H$405,MATCH(38-MAX('計算'!$CT$6:$CT$405),'計算'!$CU$6:$CU$405,0)),""))) | J48: =IF($B48="","",N($H48)*IFERROR(INDEX('計算'!$G$6:$G$405,IF(38<=MAX('計算'!$CT$6:$CT$405),MATCH(38,'計算'!$CT$6:$CT$405,0),MATCH(38-MAX('計算'!$CT$6:$CT$405),'計算'!$CU$6:$CU$405,0))),1)*N($I48))
B49: =IF(39<=MAX('計算'!$CT$6:$CT$405)+MAX('計算'!$CU$6:$CU$405),39,"") | C49: =IF($B49="","",IF(39<=MAX('計算'!$CT$6:$CT$405),IFERROR(INDEX('計算'!$F$6:$F$405,MATCH(39,'計算'!$CT$6:$CT$405,0)),""),IFERROR(INDEX('計算'!$F$6:$F$405,MATCH(39-MAX('計算'!$CT$6:$CT$405),'計算'!$CU$6:$CU$405,0)),""))) | D49: =IF($B49="","",IF(39<=MAX('計算'!$CT$6:$CT$405),IFERROR(INDEX('計算'!$C$6:$C$405,MATCH(39,'計算'!$CT$6:$CT$405,0))&"",""),IFERROR(INDEX('計算'!$C$6:$C$405,MATCH(39-MAX('計算'!$CT$6:$CT$405),'計算'!$CU$6:$CU$405,0))&"",""))) | E49: =IF($B49="","",IF(39<=MAX('計算'!$CT$6:$CT$405),IFERROR(INDEX('計算'!$D$6:$D$405,MATCH(39,'計算'!$CT$6:$CT$405,0)),""),IFERROR(INDEX('計算'!$D$6:$D$405,MATCH(39-MAX('計算'!$CT$6:$CT$405),'計算'!$CU$6:$CU$405,0)),""))) | F49: =IF($B49="","",IF(39<=MAX('計算'!$CT$6:$CT$405),IFERROR(INDEX('計算'!$P$6:$P$405,MATCH(39,'計算'!$CT$6:$CT$405,0)),""),IFERROR(INDEX('計算'!$S$6:$S$405,MATCH(39-MAX('計算'!$CT$6:$CT$405),'計算'!$CU$6:$CU$405,0)),""))) | G49: =IF($B49="","",IF(39<=MAX('計算'!$CT$6:$CT$405),IFERROR(INDEX('計算'!$CR$6:$CR$405,MATCH(39,'計算'!$CT$6:$CT$405,0)),""),IFERROR(INDEX('計算'!$CR$6:$CR$405,MATCH(39-MAX('計算'!$CT$6:$CT$405),'計算'!$CU$6:$CU$405,0)),""))) | H49: =IF($B49="","",IF(39<=MAX('計算'!$CT$6:$CT$405),IFERROR(INDEX('計算'!$Q$6:$Q$405,MATCH(39,'計算'!$CT$6:$CT$405,0)),""),IFERROR(INDEX('計算'!$T$6:$T$405,MATCH(39-MAX('計算'!$CT$6:$CT$405),'計算'!$CU$6:$CU$405,0)),""))) | I49: =IF($B49="","",IF(39<=MAX('計算'!$CT$6:$CT$405),IFERROR(INDEX('計算'!$H$6:$H$405,MATCH(39,'計算'!$CT$6:$CT$405,0)),""),IFERROR(INDEX('計算'!$H$6:$H$405,MATCH(39-MAX('計算'!$CT$6:$CT$405),'計算'!$CU$6:$CU$405,0)),""))) | J49: =IF($B49="","",N($H49)*IFERROR(INDEX('計算'!$G$6:$G$405,IF(39<=MAX('計算'!$CT$6:$CT$405),MATCH(39,'計算'!$CT$6:$CT$405,0),MATCH(39-MAX('計算'!$CT$6:$CT$405),'計算'!$CU$6:$CU$405,0))),1)*N($I49))
B50: =IF(40<=MAX('計算'!$CT$6:$CT$405)+MAX('計算'!$CU$6:$CU$405),40,"") | C50: =IF($B50="","",IF(40<=MAX('計算'!$CT$6:$CT$405),IFERROR(INDEX('計算'!$F$6:$F$405,MATCH(40,'計算'!$CT$6:$CT$405,0)),""),IFERROR(INDEX('計算'!$F$6:$F$405,MATCH(40-MAX('計算'!$CT$6:$CT$405),'計算'!$CU$6:$CU$405,0)),""))) | D50: =IF($B50="","",IF(40<=MAX('計算'!$CT$6:$CT$405),IFERROR(INDEX('計算'!$C$6:$C$405,MATCH(40,'計算'!$CT$6:$CT$405,0))&"",""),IFERROR(INDEX('計算'!$C$6:$C$405,MATCH(40-MAX('計算'!$CT$6:$CT$405),'計算'!$CU$6:$CU$405,0))&"",""))) | E50: =IF($B50="","",IF(40<=MAX('計算'!$CT$6:$CT$405),IFERROR(INDEX('計算'!$D$6:$D$405,MATCH(40,'計算'!$CT$6:$CT$405,0)),""),IFERROR(INDEX('計算'!$D$6:$D$405,MATCH(40-MAX('計算'!$CT$6:$CT$405),'計算'!$CU$6:$CU$405,0)),""))) | F50: =IF($B50="","",IF(40<=MAX('計算'!$CT$6:$CT$405),IFERROR(INDEX('計算'!$P$6:$P$405,MATCH(40,'計算'!$CT$6:$CT$405,0)),""),IFERROR(INDEX('計算'!$S$6:$S$405,MATCH(40-MAX('計算'!$CT$6:$CT$405),'計算'!$CU$6:$CU$405,0)),""))) | G50: =IF($B50="","",IF(40<=MAX('計算'!$CT$6:$CT$405),IFERROR(INDEX('計算'!$CR$6:$CR$405,MATCH(40,'計算'!$CT$6:$CT$405,0)),""),IFERROR(INDEX('計算'!$CR$6:$CR$405,MATCH(40-MAX('計算'!$CT$6:$CT$405),'計算'!$CU$6:$CU$405,0)),""))) | H50: =IF($B50="","",IF(40<=MAX('計算'!$CT$6:$CT$405),IFERROR(INDEX('計算'!$Q$6:$Q$405,MATCH(40,'計算'!$CT$6:$CT$405,0)),""),IFERROR(INDEX('計算'!$T$6:$T$405,MATCH(40-MAX('計算'!$CT$6:$CT$405),'計算'!$CU$6:$CU$405,0)),""))) | I50: =IF($B50="","",IF(40<=MAX('計算'!$CT$6:$CT$405),IFERROR(INDEX('計算'!$H$6:$H$405,MATCH(40,'計算'!$CT$6:$CT$405,0)),""),IFERROR(INDEX('計算'!$H$6:$H$405,MATCH(40-MAX('計算'!$CT$6:$CT$405),'計算'!$CU$6:$CU$405,0)),""))) | J50: =IF($B50="","",N($H50)*IFERROR(INDEX('計算'!$G$6:$G$405,IF(40<=MAX('計算'!$CT$6:$CT$405),MATCH(40,'計算'!$CT$6:$CT$405,0),MATCH(40-MAX('計算'!$CT$6:$CT$405),'計算'!$CU$6:$CU$405,0))),1)*N($I50))
B51: =IF(41<=MAX('計算'!$CT$6:$CT$405)+MAX('計算'!$CU$6:$CU$405),41,"") | C51: =IF($B51="","",IF(41<=MAX('計算'!$CT$6:$CT$405),IFERROR(INDEX('計算'!$F$6:$F$405,MATCH(41,'計算'!$CT$6:$CT$405,0)),""),IFERROR(INDEX('計算'!$F$6:$F$405,MATCH(41-MAX('計算'!$CT$6:$CT$405),'計算'!$CU$6:$CU$405,0)),""))) | D51: =IF($B51="","",IF(41<=MAX('計算'!$CT$6:$CT$405),IFERROR(INDEX('計算'!$C$6:$C$405,MATCH(41,'計算'!$CT$6:$CT$405,0))&"",""),IFERROR(INDEX('計算'!$C$6:$C$405,MATCH(41-MAX('計算'!$CT$6:$CT$405),'計算'!$CU$6:$CU$405,0))&"",""))) | E51: =IF($B51="","",IF(41<=MAX('計算'!$CT$6:$CT$405),IFERROR(INDEX('計算'!$D$6:$D$405,MATCH(41,'計算'!$CT$6:$CT$405,0)),""),IFERROR(INDEX('計算'!$D$6:$D$405,MATCH(41-MAX('計算'!$CT$6:$CT$405),'計算'!$CU$6:$CU$405,0)),""))) | F51: =IF($B51="","",IF(41<=MAX('計算'!$CT$6:$CT$405),IFERROR(INDEX('計算'!$P$6:$P$405,MATCH(41,'計算'!$CT$6:$CT$405,0)),""),IFERROR(INDEX('計算'!$S$6:$S$405,MATCH(41-MAX('計算'!$CT$6:$CT$405),'計算'!$CU$6:$CU$405,0)),""))) | G51: =IF($B51="","",IF(41<=MAX('計算'!$CT$6:$CT$405),IFERROR(INDEX('計算'!$CR$6:$CR$405,MATCH(41,'計算'!$CT$6:$CT$405,0)),""),IFERROR(INDEX('計算'!$CR$6:$CR$405,MATCH(41-MAX('計算'!$CT$6:$CT$405),'計算'!$CU$6:$CU$405,0)),""))) | H51: =IF($B51="","",IF(41<=MAX('計算'!$CT$6:$CT$405),IFERROR(INDEX('計算'!$Q$6:$Q$405,MATCH(41,'計算'!$CT$6:$CT$405,0)),""),IFERROR(INDEX('計算'!$T$6:$T$405,MATCH(41-MAX('計算'!$CT$6:$CT$405),'計算'!$CU$6:$CU$405,0)),""))) | I51: =IF($B51="","",IF(41<=MAX('計算'!$CT$6:$CT$405),IFERROR(INDEX('計算'!$H$6:$H$405,MATCH(41,'計算'!$CT$6:$CT$405,0)),""),IFERROR(INDEX('計算'!$H$6:$H$405,MATCH(41-MAX('計算'!$CT$6:$CT$405),'計算'!$CU$6:$CU$405,0)),""))) | J51: =IF($B51="","",N($H51)*IFERROR(INDEX('計算'!$G$6:$G$405,IF(41<=MAX('計算'!$CT$6:$CT$405),MATCH(41,'計算'!$CT$6:$CT$405,0),MATCH(41-MAX('計算'!$CT$6:$CT$405),'計算'!$CU$6:$CU$405,0))),1)*N($I51))
B52: =IF(42<=MAX('計算'!$CT$6:$CT$405)+MAX('計算'!$CU$6:$CU$405),42,"") | C52: =IF($B52="","",IF(42<=MAX('計算'!$CT$6:$CT$405),IFERROR(INDEX('計算'!$F$6:$F$405,MATCH(42,'計算'!$CT$6:$CT$405,0)),""),IFERROR(INDEX('計算'!$F$6:$F$405,MATCH(42-MAX('計算'!$CT$6:$CT$405),'計算'!$CU$6:$CU$405,0)),""))) | D52: =IF($B52="","",IF(42<=MAX('計算'!$CT$6:$CT$405),IFERROR(INDEX('計算'!$C$6:$C$405,MATCH(42,'計算'!$CT$6:$CT$405,0))&"",""),IFERROR(INDEX('計算'!$C$6:$C$405,MATCH(42-MAX('計算'!$CT$6:$CT$405),'計算'!$CU$6:$CU$405,0))&"",""))) | E52: =IF($B52="","",IF(42<=MAX('計算'!$CT$6:$CT$405),IFERROR(INDEX('計算'!$D$6:$D$405,MATCH(42,'計算'!$CT$6:$CT$405,0)),""),IFERROR(INDEX('計算'!$D$6:$D$405,MATCH(42-MAX('計算'!$CT$6:$CT$405),'計算'!$CU$6:$CU$405,0)),""))) | F52: =IF($B52="","",IF(42<=MAX('計算'!$CT$6:$CT$405),IFERROR(INDEX('計算'!$P$6:$P$405,MATCH(42,'計算'!$CT$6:$CT$405,0)),""),IFERROR(INDEX('計算'!$S$6:$S$405,MATCH(42-MAX('計算'!$CT$6:$CT$405),'計算'!$CU$6:$CU$405,0)),""))) | G52: =IF($B52="","",IF(42<=MAX('計算'!$CT$6:$CT$405),IFERROR(INDEX('計算'!$CR$6:$CR$405,MATCH(42,'計算'!$CT$6:$CT$405,0)),""),IFERROR(INDEX('計算'!$CR$6:$CR$405,MATCH(42-MAX('計算'!$CT$6:$CT$405),'計算'!$CU$6:$CU$405,0)),""))) | H52: =IF($B52="","",IF(42<=MAX('計算'!$CT$6:$CT$405),IFERROR(INDEX('計算'!$Q$6:$Q$405,MATCH(42,'計算'!$CT$6:$CT$405,0)),""),IFERROR(INDEX('計算'!$T$6:$T$405,MATCH(42-MAX('計算'!$CT$6:$CT$405),'計算'!$CU$6:$CU$405,0)),""))) | I52: =IF($B52="","",IF(42<=MAX('計算'!$CT$6:$CT$405),IFERROR(INDEX('計算'!$H$6:$H$405,MATCH(42,'計算'!$CT$6:$CT$405,0)),""),IFERROR(INDEX('計算'!$H$6:$H$405,MATCH(42-MAX('計算'!$CT$6:$CT$405),'計算'!$CU$6:$CU$405,0)),""))) | J52: =IF($B52="","",N($H52)*IFERROR(INDEX('計算'!$G$6:$G$405,IF(42<=MAX('計算'!$CT$6:$CT$405),MATCH(42,'計算'!$CT$6:$CT$405,0),MATCH(42-MAX('計算'!$CT$6:$CT$405),'計算'!$CU$6:$CU$405,0))),1)*N($I52))
B53: =IF(43<=MAX('計算'!$CT$6:$CT$405)+MAX('計算'!$CU$6:$CU$405),43,"") | C53: =IF($B53="","",IF(43<=MAX('計算'!$CT$6:$CT$405),IFERROR(INDEX('計算'!$F$6:$F$405,MATCH(43,'計算'!$CT$6:$CT$405,0)),""),IFERROR(INDEX('計算'!$F$6:$F$405,MATCH(43-MAX('計算'!$CT$6:$CT$405),'計算'!$CU$6:$CU$405,0)),""))) | D53: =IF($B53="","",IF(43<=MAX('計算'!$CT$6:$CT$405),IFERROR(INDEX('計算'!$C$6:$C$405,MATCH(43,'計算'!$CT$6:$CT$405,0))&"",""),IFERROR(INDEX('計算'!$C$6:$C$405,MATCH(43-MAX('計算'!$CT$6:$CT$405),'計算'!$CU$6:$CU$405,0))&"",""))) | E53: =IF($B53="","",IF(43<=MAX('計算'!$CT$6:$CT$405),IFERROR(INDEX('計算'!$D$6:$D$405,MATCH(43,'計算'!$CT$6:$CT$405,0)),""),IFERROR(INDEX('計算'!$D$6:$D$405,MATCH(43-MAX('計算'!$CT$6:$CT$405),'計算'!$CU$6:$CU$405,0)),""))) | F53: =IF($B53="","",IF(43<=MAX('計算'!$CT$6:$CT$405),IFERROR(INDEX('計算'!$P$6:$P$405,MATCH(43,'計算'!$CT$6:$CT$405,0)),""),IFERROR(INDEX('計算'!$S$6:$S$405,MATCH(43-MAX('計算'!$CT$6:$CT$405),'計算'!$CU$6:$CU$405,0)),""))) | G53: =IF($B53="","",IF(43<=MAX('計算'!$CT$6:$CT$405),IFERROR(INDEX('計算'!$CR$6:$CR$405,MATCH(43,'計算'!$CT$6:$CT$405,0)),""),IFERROR(INDEX('計算'!$CR$6:$CR$405,MATCH(43-MAX('計算'!$CT$6:$CT$405),'計算'!$CU$6:$CU$405,0)),""))) | H53: =IF($B53="","",IF(43<=MAX('計算'!$CT$6:$CT$405),IFERROR(INDEX('計算'!$Q$6:$Q$405,MATCH(43,'計算'!$CT$6:$CT$405,0)),""),IFERROR(INDEX('計算'!$T$6:$T$405,MATCH(43-MAX('計算'!$CT$6:$CT$405),'計算'!$CU$6:$CU$405,0)),""))) | I53: =IF($B53="","",IF(43<=MAX('計算'!$CT$6:$CT$405),IFERROR(INDEX('計算'!$H$6:$H$405,MATCH(43,'計算'!$CT$6:$CT$405,0)),""),IFERROR(INDEX('計算'!$H$6:$H$405,MATCH(43-MAX('計算'!$CT$6:$CT$405),'計算'!$CU$6:$CU$405,0)),""))) | J53: =IF($B53="","",N($H53)*IFERROR(INDEX('計算'!$G$6:$G$405,IF(43<=MAX('計算'!$CT$6:$CT$405),MATCH(43,'計算'!$CT$6:$CT$405,0),MATCH(43-MAX('計算'!$CT$6:$CT$405),'計算'!$CU$6:$CU$405,0))),1)*N($I53))
B54: =IF(44<=MAX('計算'!$CT$6:$CT$405)+MAX('計算'!$CU$6:$CU$405),44,"") | C54: =IF($B54="","",IF(44<=MAX('計算'!$CT$6:$CT$405),IFERROR(INDEX('計算'!$F$6:$F$405,MATCH(44,'計算'!$CT$6:$CT$405,0)),""),IFERROR(INDEX('計算'!$F$6:$F$405,MATCH(44-MAX('計算'!$CT$6:$CT$405),'計算'!$CU$6:$CU$405,0)),""))) | D54: =IF($B54="","",IF(44<=MAX('計算'!$CT$6:$CT$405),IFERROR(INDEX('計算'!$C$6:$C$405,MATCH(44,'計算'!$CT$6:$CT$405,0))&"",""),IFERROR(INDEX('計算'!$C$6:$C$405,MATCH(44-MAX('計算'!$CT$6:$CT$405),'計算'!$CU$6:$CU$405,0))&"",""))) | E54: =IF($B54="","",IF(44<=MAX('計算'!$CT$6:$CT$405),IFERROR(INDEX('計算'!$D$6:$D$405,MATCH(44,'計算'!$CT$6:$CT$405,0)),""),IFERROR(INDEX('計算'!$D$6:$D$405,MATCH(44-MAX('計算'!$CT$6:$CT$405),'計算'!$CU$6:$CU$405,0)),""))) | F54: =IF($B54="","",IF(44<=MAX('計算'!$CT$6:$CT$405),IFERROR(INDEX('計算'!$P$6:$P$405,MATCH(44,'計算'!$CT$6:$CT$405,0)),""),IFERROR(INDEX('計算'!$S$6:$S$405,MATCH(44-MAX('計算'!$CT$6:$CT$405),'計算'!$CU$6:$CU$405,0)),""))) | G54: =IF($B54="","",IF(44<=MAX('計算'!$CT$6:$CT$405),IFERROR(INDEX('計算'!$CR$6:$CR$405,MATCH(44,'計算'!$CT$6:$CT$405,0)),""),IFERROR(INDEX('計算'!$CR$6:$CR$405,MATCH(44-MAX('計算'!$CT$6:$CT$405),'計算'!$CU$6:$CU$405,0)),""))) | H54: =IF($B54="","",IF(44<=MAX('計算'!$CT$6:$CT$405),IFERROR(INDEX('計算'!$Q$6:$Q$405,MATCH(44,'計算'!$CT$6:$CT$405,0)),""),IFERROR(INDEX('計算'!$T$6:$T$405,MATCH(44-MAX('計算'!$CT$6:$CT$405),'計算'!$CU$6:$CU$405,0)),""))) | I54: =IF($B54="","",IF(44<=MAX('計算'!$CT$6:$CT$405),IFERROR(INDEX('計算'!$H$6:$H$405,MATCH(44,'計算'!$CT$6:$CT$405,0)),""),IFERROR(INDEX('計算'!$H$6:$H$405,MATCH(44-MAX('計算'!$CT$6:$CT$405),'計算'!$CU$6:$CU$405,0)),""))) | J54: =IF($B54="","",N($H54)*IFERROR(INDEX('計算'!$G$6:$G$405,IF(44<=MAX('計算'!$CT$6:$CT$405),MATCH(44,'計算'!$CT$6:$CT$405,0),MATCH(44-MAX('計算'!$CT$6:$CT$405),'計算'!$CU$6:$CU$405,0))),1)*N($I54))
B55: =IF(45<=MAX('計算'!$CT$6:$CT$405)+MAX('計算'!$CU$6:$CU$405),45,"") | C55: =IF($B55="","",IF(45<=MAX('計算'!$CT$6:$CT$405),IFERROR(INDEX('計算'!$F$6:$F$405,MATCH(45,'計算'!$CT$6:$CT$405,0)),""),IFERROR(INDEX('計算'!$F$6:$F$405,MATCH(45-MAX('計算'!$CT$6:$CT$405),'計算'!$CU$6:$CU$405,0)),""))) | D55: =IF($B55="","",IF(45<=MAX('計算'!$CT$6:$CT$405),IFERROR(INDEX('計算'!$C$6:$C$405,MATCH(45,'計算'!$CT$6:$CT$405,0))&"",""),IFERROR(INDEX('計算'!$C$6:$C$405,MATCH(45-MAX('計算'!$CT$6:$CT$405),'計算'!$CU$6:$CU$405,0))&"",""))) | E55: =IF($B55="","",IF(45<=MAX('計算'!$CT$6:$CT$405),IFERROR(INDEX('計算'!$D$6:$D$405,MATCH(45,'計算'!$CT$6:$CT$405,0)),""),IFERROR(INDEX('計算'!$D$6:$D$405,MATCH(45-MAX('計算'!$CT$6:$CT$405),'計算'!$CU$6:$CU$405,0)),""))) | F55: =IF($B55="","",IF(45<=MAX('計算'!$CT$6:$CT$405),IFERROR(INDEX('計算'!$P$6:$P$405,MATCH(45,'計算'!$CT$6:$CT$405,0)),""),IFERROR(INDEX('計算'!$S$6:$S$405,MATCH(45-MAX('計算'!$CT$6:$CT$405),'計算'!$CU$6:$CU$405,0)),""))) | G55: =IF($B55="","",IF(45<=MAX('計算'!$CT$6:$CT$405),IFERROR(INDEX('計算'!$CR$6:$CR$405,MATCH(45,'計算'!$CT$6:$CT$405,0)),""),IFERROR(INDEX('計算'!$CR$6:$CR$405,MATCH(45-MAX('計算'!$CT$6:$CT$405),'計算'!$CU$6:$CU$405,0)),""))) | H55: =IF($B55="","",IF(45<=MAX('計算'!$CT$6:$CT$405),IFERROR(INDEX('計算'!$Q$6:$Q$405,MATCH(45,'計算'!$CT$6:$CT$405,0)),""),IFERROR(INDEX('計算'!$T$6:$T$405,MATCH(45-MAX('計算'!$CT$6:$CT$405),'計算'!$CU$6:$CU$405,0)),""))) | I55: =IF($B55="","",IF(45<=MAX('計算'!$CT$6:$CT$405),IFERROR(INDEX('計算'!$H$6:$H$405,MATCH(45,'計算'!$CT$6:$CT$405,0)),""),IFERROR(INDEX('計算'!$H$6:$H$405,MATCH(45-MAX('計算'!$CT$6:$CT$405),'計算'!$CU$6:$CU$405,0)),""))) | J55: =IF($B55="","",N($H55)*IFERROR(INDEX('計算'!$G$6:$G$405,IF(45<=MAX('計算'!$CT$6:$CT$405),MATCH(45,'計算'!$CT$6:$CT$405,0),MATCH(45-MAX('計算'!$CT$6:$CT$405),'計算'!$CU$6:$CU$405,0))),1)*N($I55))
B56: =IF(46<=MAX('計算'!$CT$6:$CT$405)+MAX('計算'!$CU$6:$CU$405),46,"") | C56: =IF($B56="","",IF(46<=MAX('計算'!$CT$6:$CT$405),IFERROR(INDEX('計算'!$F$6:$F$405,MATCH(46,'計算'!$CT$6:$CT$405,0)),""),IFERROR(INDEX('計算'!$F$6:$F$405,MATCH(46-MAX('計算'!$CT$6:$CT$405),'計算'!$CU$6:$CU$405,0)),""))) | D56: =IF($B56="","",IF(46<=MAX('計算'!$CT$6:$CT$405),IFERROR(INDEX('計算'!$C$6:$C$405,MATCH(46,'計算'!$CT$6:$CT$405,0))&"",""),IFERROR(INDEX('計算'!$C$6:$C$405,MATCH(46-MAX('計算'!$CT$6:$CT$405),'計算'!$CU$6:$CU$405,0))&"",""))) | E56: =IF($B56="","",IF(46<=MAX('計算'!$CT$6:$CT$405),IFERROR(INDEX('計算'!$D$6:$D$405,MATCH(46,'計算'!$CT$6:$CT$405,0)),""),IFERROR(INDEX('計算'!$D$6:$D$405,MATCH(46-MAX('計算'!$CT$6:$CT$405),'計算'!$CU$6:$CU$405,0)),""))) | F56: =IF($B56="","",IF(46<=MAX('計算'!$CT$6:$CT$405),IFERROR(INDEX('計算'!$P$6:$P$405,MATCH(46,'計算'!$CT$6:$CT$405,0)),""),IFERROR(INDEX('計算'!$S$6:$S$405,MATCH(46-MAX('計算'!$CT$6:$CT$405),'計算'!$CU$6:$CU$405,0)),""))) | G56: =IF($B56="","",IF(46<=MAX('計算'!$CT$6:$CT$405),IFERROR(INDEX('計算'!$CR$6:$CR$405,MATCH(46,'計算'!$CT$6:$CT$405,0)),""),IFERROR(INDEX('計算'!$CR$6:$CR$405,MATCH(46-MAX('計算'!$CT$6:$CT$405),'計算'!$CU$6:$CU$405,0)),""))) | H56: =IF($B56="","",IF(46<=MAX('計算'!$CT$6:$CT$405),IFERROR(INDEX('計算'!$Q$6:$Q$405,MATCH(46,'計算'!$CT$6:$CT$405,0)),""),IFERROR(INDEX('計算'!$T$6:$T$405,MATCH(46-MAX('計算'!$CT$6:$CT$405),'計算'!$CU$6:$CU$405,0)),""))) | I56: =IF($B56="","",IF(46<=MAX('計算'!$CT$6:$CT$405),IFERROR(INDEX('計算'!$H$6:$H$405,MATCH(46,'計算'!$CT$6:$CT$405,0)),""),IFERROR(INDEX('計算'!$H$6:$H$405,MATCH(46-MAX('計算'!$CT$6:$CT$405),'計算'!$CU$6:$CU$405,0)),""))) | J56: =IF($B56="","",N($H56)*IFERROR(INDEX('計算'!$G$6:$G$405,IF(46<=MAX('計算'!$CT$6:$CT$405),MATCH(46,'計算'!$CT$6:$CT$405,0),MATCH(46-MAX('計算'!$CT$6:$CT$405),'計算'!$CU$6:$CU$405,0))),1)*N($I56))
B57: =IF(47<=MAX('計算'!$CT$6:$CT$405)+MAX('計算'!$CU$6:$CU$405),47,"") | C57: =IF($B57="","",IF(47<=MAX('計算'!$CT$6:$CT$405),IFERROR(INDEX('計算'!$F$6:$F$405,MATCH(47,'計算'!$CT$6:$CT$405,0)),""),IFERROR(INDEX('計算'!$F$6:$F$405,MATCH(47-MAX('計算'!$CT$6:$CT$405),'計算'!$CU$6:$CU$405,0)),""))) | D57: =IF($B57="","",IF(47<=MAX('計算'!$CT$6:$CT$405),IFERROR(INDEX('計算'!$C$6:$C$405,MATCH(47,'計算'!$CT$6:$CT$405,0))&"",""),IFERROR(INDEX('計算'!$C$6:$C$405,MATCH(47-MAX('計算'!$CT$6:$CT$405),'計算'!$CU$6:$CU$405,0))&"",""))) | E57: =IF($B57="","",IF(47<=MAX('計算'!$CT$6:$CT$405),IFERROR(INDEX('計算'!$D$6:$D$405,MATCH(47,'計算'!$CT$6:$CT$405,0)),""),IFERROR(INDEX('計算'!$D$6:$D$405,MATCH(47-MAX('計算'!$CT$6:$CT$405),'計算'!$CU$6:$CU$405,0)),""))) | F57: =IF($B57="","",IF(47<=MAX('計算'!$CT$6:$CT$405),IFERROR(INDEX('計算'!$P$6:$P$405,MATCH(47,'計算'!$CT$6:$CT$405,0)),""),IFERROR(INDEX('計算'!$S$6:$S$405,MATCH(47-MAX('計算'!$CT$6:$CT$405),'計算'!$CU$6:$CU$405,0)),""))) | G57: =IF($B57="","",IF(47<=MAX('計算'!$CT$6:$CT$405),IFERROR(INDEX('計算'!$CR$6:$CR$405,MATCH(47,'計算'!$CT$6:$CT$405,0)),""),IFERROR(INDEX('計算'!$CR$6:$CR$405,MATCH(47-MAX('計算'!$CT$6:$CT$405),'計算'!$CU$6:$CU$405,0)),""))) | H57: =IF($B57="","",IF(47<=MAX('計算'!$CT$6:$CT$405),IFERROR(INDEX('計算'!$Q$6:$Q$405,MATCH(47,'計算'!$CT$6:$CT$405,0)),""),IFERROR(INDEX('計算'!$T$6:$T$405,MATCH(47-MAX('計算'!$CT$6:$CT$405),'計算'!$CU$6:$CU$405,0)),""))) | I57: =IF($B57="","",IF(47<=MAX('計算'!$CT$6:$CT$405),IFERROR(INDEX('計算'!$H$6:$H$405,MATCH(47,'計算'!$CT$6:$CT$405,0)),""),IFERROR(INDEX('計算'!$H$6:$H$405,MATCH(47-MAX('計算'!$CT$6:$CT$405),'計算'!$CU$6:$CU$405,0)),""))) | J57: =IF($B57="","",N($H57)*IFERROR(INDEX('計算'!$G$6:$G$405,IF(47<=MAX('計算'!$CT$6:$CT$405),MATCH(47,'計算'!$CT$6:$CT$405,0),MATCH(47-MAX('計算'!$CT$6:$CT$405),'計算'!$CU$6:$CU$405,0))),1)*N($I57))
B58: =IF(48<=MAX('計算'!$CT$6:$CT$405)+MAX('計算'!$CU$6:$CU$405),48,"") | C58: =IF($B58="","",IF(48<=MAX('計算'!$CT$6:$CT$405),IFERROR(INDEX('計算'!$F$6:$F$405,MATCH(48,'計算'!$CT$6:$CT$405,0)),""),IFERROR(INDEX('計算'!$F$6:$F$405,MATCH(48-MAX('計算'!$CT$6:$CT$405),'計算'!$CU$6:$CU$405,0)),""))) | D58: =IF($B58="","",IF(48<=MAX('計算'!$CT$6:$CT$405),IFERROR(INDEX('計算'!$C$6:$C$405,MATCH(48,'計算'!$CT$6:$CT$405,0))&"",""),IFERROR(INDEX('計算'!$C$6:$C$405,MATCH(48-MAX('計算'!$CT$6:$CT$405),'計算'!$CU$6:$CU$405,0))&"",""))) | E58: =IF($B58="","",IF(48<=MAX('計算'!$CT$6:$CT$405),IFERROR(INDEX('計算'!$D$6:$D$405,MATCH(48,'計算'!$CT$6:$CT$405,0)),""),IFERROR(INDEX('計算'!$D$6:$D$405,MATCH(48-MAX('計算'!$CT$6:$CT$405),'計算'!$CU$6:$CU$405,0)),""))) | F58: =IF($B58="","",IF(48<=MAX('計算'!$CT$6:$CT$405),IFERROR(INDEX('計算'!$P$6:$P$405,MATCH(48,'計算'!$CT$6:$CT$405,0)),""),IFERROR(INDEX('計算'!$S$6:$S$405,MATCH(48-MAX('計算'!$CT$6:$CT$405),'計算'!$CU$6:$CU$405,0)),""))) | G58: =IF($B58="","",IF(48<=MAX('計算'!$CT$6:$CT$405),IFERROR(INDEX('計算'!$CR$6:$CR$405,MATCH(48,'計算'!$CT$6:$CT$405,0)),""),IFERROR(INDEX('計算'!$CR$6:$CR$405,MATCH(48-MAX('計算'!$CT$6:$CT$405),'計算'!$CU$6:$CU$405,0)),""))) | H58: =IF($B58="","",IF(48<=MAX('計算'!$CT$6:$CT$405),IFERROR(INDEX('計算'!$Q$6:$Q$405,MATCH(48,'計算'!$CT$6:$CT$405,0)),""),IFERROR(INDEX('計算'!$T$6:$T$405,MATCH(48-MAX('計算'!$CT$6:$CT$405),'計算'!$CU$6:$CU$405,0)),""))) | I58: =IF($B58="","",IF(48<=MAX('計算'!$CT$6:$CT$405),IFERROR(INDEX('計算'!$H$6:$H$405,MATCH(48,'計算'!$CT$6:$CT$405,0)),""),IFERROR(INDEX('計算'!$H$6:$H$405,MATCH(48-MAX('計算'!$CT$6:$CT$405),'計算'!$CU$6:$CU$405,0)),""))) | J58: =IF($B58="","",N($H58)*IFERROR(INDEX('計算'!$G$6:$G$405,IF(48<=MAX('計算'!$CT$6:$CT$405),MATCH(48,'計算'!$CT$6:$CT$405,0),MATCH(48-MAX('計算'!$CT$6:$CT$405),'計算'!$CU$6:$CU$405,0))),1)*N($I58))
B59: =IF(49<=MAX('計算'!$CT$6:$CT$405)+MAX('計算'!$CU$6:$CU$405),49,"") | C59: =IF($B59="","",IF(49<=MAX('計算'!$CT$6:$CT$405),IFERROR(INDEX('計算'!$F$6:$F$405,MATCH(49,'計算'!$CT$6:$CT$405,0)),""),IFERROR(INDEX('計算'!$F$6:$F$405,MATCH(49-MAX('計算'!$CT$6:$CT$405),'計算'!$CU$6:$CU$405,0)),""))) | D59: =IF($B59="","",IF(49<=MAX('計算'!$CT$6:$CT$405),IFERROR(INDEX('計算'!$C$6:$C$405,MATCH(49,'計算'!$CT$6:$CT$405,0))&"",""),IFERROR(INDEX('計算'!$C$6:$C$405,MATCH(49-MAX('計算'!$CT$6:$CT$405),'計算'!$CU$6:$CU$405,0))&"",""))) | E59: =IF($B59="","",IF(49<=MAX('計算'!$CT$6:$CT$405),IFERROR(INDEX('計算'!$D$6:$D$405,MATCH(49,'計算'!$CT$6:$CT$405,0)),""),IFERROR(INDEX('計算'!$D$6:$D$405,MATCH(49-MAX('計算'!$CT$6:$CT$405),'計算'!$CU$6:$CU$405,0)),""))) | F59: =IF($B59="","",IF(49<=MAX('計算'!$CT$6:$CT$405),IFERROR(INDEX('計算'!$P$6:$P$405,MATCH(49,'計算'!$CT$6:$CT$405,0)),""),IFERROR(INDEX('計算'!$S$6:$S$405,MATCH(49-MAX('計算'!$CT$6:$CT$405),'計算'!$CU$6:$CU$405,0)),""))) | G59: =IF($B59="","",IF(49<=MAX('計算'!$CT$6:$CT$405),IFERROR(INDEX('計算'!$CR$6:$CR$405,MATCH(49,'計算'!$CT$6:$CT$405,0)),""),IFERROR(INDEX('計算'!$CR$6:$CR$405,MATCH(49-MAX('計算'!$CT$6:$CT$405),'計算'!$CU$6:$CU$405,0)),""))) | H59: =IF($B59="","",IF(49<=MAX('計算'!$CT$6:$CT$405),IFERROR(INDEX('計算'!$Q$6:$Q$405,MATCH(49,'計算'!$CT$6:$CT$405,0)),""),IFERROR(INDEX('計算'!$T$6:$T$405,MATCH(49-MAX('計算'!$CT$6:$CT$405),'計算'!$CU$6:$CU$405,0)),""))) | I59: =IF($B59="","",IF(49<=MAX('計算'!$CT$6:$CT$405),IFERROR(INDEX('計算'!$H$6:$H$405,MATCH(49,'計算'!$CT$6:$CT$405,0)),""),IFERROR(INDEX('計算'!$H$6:$H$405,MATCH(49-MAX('計算'!$CT$6:$CT$405),'計算'!$CU$6:$CU$405,0)),""))) | J59: =IF($B59="","",N($H59)*IFERROR(INDEX('計算'!$G$6:$G$405,IF(49<=MAX('計算'!$CT$6:$CT$405),MATCH(49,'計算'!$CT$6:$CT$405,0),MATCH(49-MAX('計算'!$CT$6:$CT$405),'計算'!$CU$6:$CU$405,0))),1)*N($I59))
B60: =IF(50<=MAX('計算'!$CT$6:$CT$405)+MAX('計算'!$CU$6:$CU$405),50,"") | C60: =IF($B60="","",IF(50<=MAX('計算'!$CT$6:$CT$405),IFERROR(INDEX('計算'!$F$6:$F$405,MATCH(50,'計算'!$CT$6:$CT$405,0)),""),IFERROR(INDEX('計算'!$F$6:$F$405,MATCH(50-MAX('計算'!$CT$6:$CT$405),'計算'!$CU$6:$CU$405,0)),""))) | D60: =IF($B60="","",IF(50<=MAX('計算'!$CT$6:$CT$405),IFERROR(INDEX('計算'!$C$6:$C$405,MATCH(50,'計算'!$CT$6:$CT$405,0))&"",""),IFERROR(INDEX('計算'!$C$6:$C$405,MATCH(50-MAX('計算'!$CT$6:$CT$405),'計算'!$CU$6:$CU$405,0))&"",""))) | E60: =IF($B60="","",IF(50<=MAX('計算'!$CT$6:$CT$405),IFERROR(INDEX('計算'!$D$6:$D$405,MATCH(50,'計算'!$CT$6:$CT$405,0)),""),IFERROR(INDEX('計算'!$D$6:$D$405,MATCH(50-MAX('計算'!$CT$6:$CT$405),'計算'!$CU$6:$CU$405,0)),""))) | F60: =IF($B60="","",IF(50<=MAX('計算'!$CT$6:$CT$405),IFERROR(INDEX('計算'!$P$6:$P$405,MATCH(50,'計算'!$CT$6:$CT$405,0)),""),IFERROR(INDEX('計算'!$S$6:$S$405,MATCH(50-MAX('計算'!$CT$6:$CT$405),'計算'!$CU$6:$CU$405,0)),""))) | G60: =IF($B60="","",IF(50<=MAX('計算'!$CT$6:$CT$405),IFERROR(INDEX('計算'!$CR$6:$CR$405,MATCH(50,'計算'!$CT$6:$CT$405,0)),""),IFERROR(INDEX('計算'!$CR$6:$CR$405,MATCH(50-MAX('計算'!$CT$6:$CT$405),'計算'!$CU$6:$CU$405,0)),""))) | H60: =IF($B60="","",IF(50<=MAX('計算'!$CT$6:$CT$405),IFERROR(INDEX('計算'!$Q$6:$Q$405,MATCH(50,'計算'!$CT$6:$CT$405,0)),""),IFERROR(INDEX('計算'!$T$6:$T$405,MATCH(50-MAX('計算'!$CT$6:$CT$405),'計算'!$CU$6:$CU$405,0)),""))) | I60: =IF($B60="","",IF(50<=MAX('計算'!$CT$6:$CT$405),IFERROR(INDEX('計算'!$H$6:$H$405,MATCH(50,'計算'!$CT$6:$CT$405,0)),""),IFERROR(INDEX('計算'!$H$6:$H$405,MATCH(50-MAX('計算'!$CT$6:$CT$405),'計算'!$CU$6:$CU$405,0)),""))) | J60: =IF($B60="","",N($H60)*IFERROR(INDEX('計算'!$G$6:$G$405,IF(50<=MAX('計算'!$CT$6:$CT$405),MATCH(50,'計算'!$CT$6:$CT$405,0),MATCH(50-MAX('計算'!$CT$6:$CT$405),'計算'!$CU$6:$CU$405,0))),1)*N($I60))
B61: =IF(51<=MAX('計算'!$CT$6:$CT$405)+MAX('計算'!$CU$6:$CU$405),51,"") | C61: =IF($B61="","",IF(51<=MAX('計算'!$CT$6:$CT$405),IFERROR(INDEX('計算'!$F$6:$F$405,MATCH(51,'計算'!$CT$6:$CT$405,0)),""),IFERROR(INDEX('計算'!$F$6:$F$405,MATCH(51-MAX('計算'!$CT$6:$CT$405),'計算'!$CU$6:$CU$405,0)),""))) | D61: =IF($B61="","",IF(51<=MAX('計算'!$CT$6:$CT$405),IFERROR(INDEX('計算'!$C$6:$C$405,MATCH(51,'計算'!$CT$6:$CT$405,0))&"",""),IFERROR(INDEX('計算'!$C$6:$C$405,MATCH(51-MAX('計算'!$CT$6:$CT$405),'計算'!$CU$6:$CU$405,0))&"",""))) | E61: =IF($B61="","",IF(51<=MAX('計算'!$CT$6:$CT$405),IFERROR(INDEX('計算'!$D$6:$D$405,MATCH(51,'計算'!$CT$6:$CT$405,0)),""),IFERROR(INDEX('計算'!$D$6:$D$405,MATCH(51-MAX('計算'!$CT$6:$CT$405),'計算'!$CU$6:$CU$405,0)),""))) | F61: =IF($B61="","",IF(51<=MAX('計算'!$CT$6:$CT$405),IFERROR(INDEX('計算'!$P$6:$P$405,MATCH(51,'計算'!$CT$6:$CT$405,0)),""),IFERROR(INDEX('計算'!$S$6:$S$405,MATCH(51-MAX('計算'!$CT$6:$CT$405),'計算'!$CU$6:$CU$405,0)),""))) | G61: =IF($B61="","",IF(51<=MAX('計算'!$CT$6:$CT$405),IFERROR(INDEX('計算'!$CR$6:$CR$405,MATCH(51,'計算'!$CT$6:$CT$405,0)),""),IFERROR(INDEX('計算'!$CR$6:$CR$405,MATCH(51-MAX('計算'!$CT$6:$CT$405),'計算'!$CU$6:$CU$405,0)),""))) | H61: =IF($B61="","",IF(51<=MAX('計算'!$CT$6:$CT$405),IFERROR(INDEX('計算'!$Q$6:$Q$405,MATCH(51,'計算'!$CT$6:$CT$405,0)),""),IFERROR(INDEX('計算'!$T$6:$T$405,MATCH(51-MAX('計算'!$CT$6:$CT$405),'計算'!$CU$6:$CU$405,0)),""))) | I61: =IF($B61="","",IF(51<=MAX('計算'!$CT$6:$CT$405),IFERROR(INDEX('計算'!$H$6:$H$405,MATCH(51,'計算'!$CT$6:$CT$405,0)),""),IFERROR(INDEX('計算'!$H$6:$H$405,MATCH(51-MAX('計算'!$CT$6:$CT$405),'計算'!$CU$6:$CU$405,0)),""))) | J61: =IF($B61="","",N($H61)*IFERROR(INDEX('計算'!$G$6:$G$405,IF(51<=MAX('計算'!$CT$6:$CT$405),MATCH(51,'計算'!$CT$6:$CT$405,0),MATCH(51-MAX('計算'!$CT$6:$CT$405),'計算'!$CU$6:$CU$405,0))),1)*N($I61))
B62: =IF(52<=MAX('計算'!$CT$6:$CT$405)+MAX('計算'!$CU$6:$CU$405),52,"") | C62: =IF($B62="","",IF(52<=MAX('計算'!$CT$6:$CT$405),IFERROR(INDEX('計算'!$F$6:$F$405,MATCH(52,'計算'!$CT$6:$CT$405,0)),""),IFERROR(INDEX('計算'!$F$6:$F$405,MATCH(52-MAX('計算'!$CT$6:$CT$405),'計算'!$CU$6:$CU$405,0)),""))) | D62: =IF($B62="","",IF(52<=MAX('計算'!$CT$6:$CT$405),IFERROR(INDEX('計算'!$C$6:$C$405,MATCH(52,'計算'!$CT$6:$CT$405,0))&"",""),IFERROR(INDEX('計算'!$C$6:$C$405,MATCH(52-MAX('計算'!$CT$6:$CT$405),'計算'!$CU$6:$CU$405,0))&"",""))) | E62: =IF($B62="","",IF(52<=MAX('計算'!$CT$6:$CT$405),IFERROR(INDEX('計算'!$D$6:$D$405,MATCH(52,'計算'!$CT$6:$CT$405,0)),""),IFERROR(INDEX('計算'!$D$6:$D$405,MATCH(52-MAX('計算'!$CT$6:$CT$405),'計算'!$CU$6:$CU$405,0)),""))) | F62: =IF($B62="","",IF(52<=MAX('計算'!$CT$6:$CT$405),IFERROR(INDEX('計算'!$P$6:$P$405,MATCH(52,'計算'!$CT$6:$CT$405,0)),""),IFERROR(INDEX('計算'!$S$6:$S$405,MATCH(52-MAX('計算'!$CT$6:$CT$405),'計算'!$CU$6:$CU$405,0)),""))) | G62: =IF($B62="","",IF(52<=MAX('計算'!$CT$6:$CT$405),IFERROR(INDEX('計算'!$CR$6:$CR$405,MATCH(52,'計算'!$CT$6:$CT$405,0)),""),IFERROR(INDEX('計算'!$CR$6:$CR$405,MATCH(52-MAX('計算'!$CT$6:$CT$405),'計算'!$CU$6:$CU$405,0)),""))) | H62: =IF($B62="","",IF(52<=MAX('計算'!$CT$6:$CT$405),IFERROR(INDEX('計算'!$Q$6:$Q$405,MATCH(52,'計算'!$CT$6:$CT$405,0)),""),IFERROR(INDEX('計算'!$T$6:$T$405,MATCH(52-MAX('計算'!$CT$6:$CT$405),'計算'!$CU$6:$CU$405,0)),""))) | I62: =IF($B62="","",IF(52<=MAX('計算'!$CT$6:$CT$405),IFERROR(INDEX('計算'!$H$6:$H$405,MATCH(52,'計算'!$CT$6:$CT$405,0)),""),IFERROR(INDEX('計算'!$H$6:$H$405,MATCH(52-MAX('計算'!$CT$6:$CT$405),'計算'!$CU$6:$CU$405,0)),""))) | J62: =IF($B62="","",N($H62)*IFERROR(INDEX('計算'!$G$6:$G$405,IF(52<=MAX('計算'!$CT$6:$CT$405),MATCH(52,'計算'!$CT$6:$CT$405,0),MATCH(52-MAX('計算'!$CT$6:$CT$405),'計算'!$CU$6:$CU$405,0))),1)*N($I62))
B63: =IF(53<=MAX('計算'!$CT$6:$CT$405)+MAX('計算'!$CU$6:$CU$405),53,"") | C63: =IF($B63="","",IF(53<=MAX('計算'!$CT$6:$CT$405),IFERROR(INDEX('計算'!$F$6:$F$405,MATCH(53,'計算'!$CT$6:$CT$405,0)),""),IFERROR(INDEX('計算'!$F$6:$F$405,MATCH(53-MAX('計算'!$CT$6:$CT$405),'計算'!$CU$6:$CU$405,0)),""))) | D63: =IF($B63="","",IF(53<=MAX('計算'!$CT$6:$CT$405),IFERROR(INDEX('計算'!$C$6:$C$405,MATCH(53,'計算'!$CT$6:$CT$405,0))&"",""),IFERROR(INDEX('計算'!$C$6:$C$405,MATCH(53-MAX('計算'!$CT$6:$CT$405),'計算'!$CU$6:$CU$405,0))&"",""))) | E63: =IF($B63="","",IF(53<=MAX('計算'!$CT$6:$CT$405),IFERROR(INDEX('計算'!$D$6:$D$405,MATCH(53,'計算'!$CT$6:$CT$405,0)),""),IFERROR(INDEX('計算'!$D$6:$D$405,MATCH(53-MAX('計算'!$CT$6:$CT$405),'計算'!$CU$6:$CU$405,0)),""))) | F63: =IF($B63="","",IF(53<=MAX('計算'!$CT$6:$CT$405),IFERROR(INDEX('計算'!$P$6:$P$405,MATCH(53,'計算'!$CT$6:$CT$405,0)),""),IFERROR(INDEX('計算'!$S$6:$S$405,MATCH(53-MAX('計算'!$CT$6:$CT$405),'計算'!$CU$6:$CU$405,0)),""))) | G63: =IF($B63="","",IF(53<=MAX('計算'!$CT$6:$CT$405),IFERROR(INDEX('計算'!$CR$6:$CR$405,MATCH(53,'計算'!$CT$6:$CT$405,0)),""),IFERROR(INDEX('計算'!$CR$6:$CR$405,MATCH(53-MAX('計算'!$CT$6:$CT$405),'計算'!$CU$6:$CU$405,0)),""))) | H63: =IF($B63="","",IF(53<=MAX('計算'!$CT$6:$CT$405),IFERROR(INDEX('計算'!$Q$6:$Q$405,MATCH(53,'計算'!$CT$6:$CT$405,0)),""),IFERROR(INDEX('計算'!$T$6:$T$405,MATCH(53-MAX('計算'!$CT$6:$CT$405),'計算'!$CU$6:$CU$405,0)),""))) | I63: =IF($B63="","",IF(53<=MAX('計算'!$CT$6:$CT$405),IFERROR(INDEX('計算'!$H$6:$H$405,MATCH(53,'計算'!$CT$6:$CT$405,0)),""),IFERROR(INDEX('計算'!$H$6:$H$405,MATCH(53-MAX('計算'!$CT$6:$CT$405),'計算'!$CU$6:$CU$405,0)),""))) | J63: =IF($B63="","",N($H63)*IFERROR(INDEX('計算'!$G$6:$G$405,IF(53<=MAX('計算'!$CT$6:$CT$405),MATCH(53,'計算'!$CT$6:$CT$405,0),MATCH(53-MAX('計算'!$CT$6:$CT$405),'計算'!$CU$6:$CU$405,0))),1)*N($I63))
B64: =IF(54<=MAX('計算'!$CT$6:$CT$405)+MAX('計算'!$CU$6:$CU$405),54,"") | C64: =IF($B64="","",IF(54<=MAX('計算'!$CT$6:$CT$405),IFERROR(INDEX('計算'!$F$6:$F$405,MATCH(54,'計算'!$CT$6:$CT$405,0)),""),IFERROR(INDEX('計算'!$F$6:$F$405,MATCH(54-MAX('計算'!$CT$6:$CT$405),'計算'!$CU$6:$CU$405,0)),""))) | D64: =IF($B64="","",IF(54<=MAX('計算'!$CT$6:$CT$405),IFERROR(INDEX('計算'!$C$6:$C$405,MATCH(54,'計算'!$CT$6:$CT$405,0))&"",""),IFERROR(INDEX('計算'!$C$6:$C$405,MATCH(54-MAX('計算'!$CT$6:$CT$405),'計算'!$CU$6:$CU$405,0))&"",""))) | E64: =IF($B64="","",IF(54<=MAX('計算'!$CT$6:$CT$405),IFERROR(INDEX('計算'!$D$6:$D$405,MATCH(54,'計算'!$CT$6:$CT$405,0)),""),IFERROR(INDEX('計算'!$D$6:$D$405,MATCH(54-MAX('計算'!$CT$6:$CT$405),'計算'!$CU$6:$CU$405,0)),""))) | F64: =IF($B64="","",IF(54<=MAX('計算'!$CT$6:$CT$405),IFERROR(INDEX('計算'!$P$6:$P$405,MATCH(54,'計算'!$CT$6:$CT$405,0)),""),IFERROR(INDEX('計算'!$S$6:$S$405,MATCH(54-MAX('計算'!$CT$6:$CT$405),'計算'!$CU$6:$CU$405,0)),""))) | G64: =IF($B64="","",IF(54<=MAX('計算'!$CT$6:$CT$405),IFERROR(INDEX('計算'!$CR$6:$CR$405,MATCH(54,'計算'!$CT$6:$CT$405,0)),""),IFERROR(INDEX('計算'!$CR$6:$CR$405,MATCH(54-MAX('計算'!$CT$6:$CT$405),'計算'!$CU$6:$CU$405,0)),""))) | H64: =IF($B64="","",IF(54<=MAX('計算'!$CT$6:$CT$405),IFERROR(INDEX('計算'!$Q$6:$Q$405,MATCH(54,'計算'!$CT$6:$CT$405,0)),""),IFERROR(INDEX('計算'!$T$6:$T$405,MATCH(54-MAX('計算'!$CT$6:$CT$405),'計算'!$CU$6:$CU$405,0)),""))) | I64: =IF($B64="","",IF(54<=MAX('計算'!$CT$6:$CT$405),IFERROR(INDEX('計算'!$H$6:$H$405,MATCH(54,'計算'!$CT$6:$CT$405,0)),""),IFERROR(INDEX('計算'!$H$6:$H$405,MATCH(54-MAX('計算'!$CT$6:$CT$405),'計算'!$CU$6:$CU$405,0)),""))) | J64: =IF($B64="","",N($H64)*IFERROR(INDEX('計算'!$G$6:$G$405,IF(54<=MAX('計算'!$CT$6:$CT$405),MATCH(54,'計算'!$CT$6:$CT$405,0),MATCH(54-MAX('計算'!$CT$6:$CT$405),'計算'!$CU$6:$CU$405,0))),1)*N($I64))
B65: =IF(55<=MAX('計算'!$CT$6:$CT$405)+MAX('計算'!$CU$6:$CU$405),55,"") | C65: =IF($B65="","",IF(55<=MAX('計算'!$CT$6:$CT$405),IFERROR(INDEX('計算'!$F$6:$F$405,MATCH(55,'計算'!$CT$6:$CT$405,0)),""),IFERROR(INDEX('計算'!$F$6:$F$405,MATCH(55-MAX('計算'!$CT$6:$CT$405),'計算'!$CU$6:$CU$405,0)),""))) | D65: =IF($B65="","",IF(55<=MAX('計算'!$CT$6:$CT$405),IFERROR(INDEX('計算'!$C$6:$C$405,MATCH(55,'計算'!$CT$6:$CT$405,0))&"",""),IFERROR(INDEX('計算'!$C$6:$C$405,MATCH(55-MAX('計算'!$CT$6:$CT$405),'計算'!$CU$6:$CU$405,0))&"",""))) | E65: =IF($B65="","",IF(55<=MAX('計算'!$CT$6:$CT$405),IFERROR(INDEX('計算'!$D$6:$D$405,MATCH(55,'計算'!$CT$6:$CT$405,0)),""),IFERROR(INDEX('計算'!$D$6:$D$405,MATCH(55-MAX('計算'!$CT$6:$CT$405),'計算'!$CU$6:$CU$405,0)),""))) | F65: =IF($B65="","",IF(55<=MAX('計算'!$CT$6:$CT$405),IFERROR(INDEX('計算'!$P$6:$P$405,MATCH(55,'計算'!$CT$6:$CT$405,0)),""),IFERROR(INDEX('計算'!$S$6:$S$405,MATCH(55-MAX('計算'!$CT$6:$CT$405),'計算'!$CU$6:$CU$405,0)),""))) | G65: =IF($B65="","",IF(55<=MAX('計算'!$CT$6:$CT$405),IFERROR(INDEX('計算'!$CR$6:$CR$405,MATCH(55,'計算'!$CT$6:$CT$405,0)),""),IFERROR(INDEX('計算'!$CR$6:$CR$405,MATCH(55-MAX('計算'!$CT$6:$CT$405),'計算'!$CU$6:$CU$405,0)),""))) | H65: =IF($B65="","",IF(55<=MAX('計算'!$CT$6:$CT$405),IFERROR(INDEX('計算'!$Q$6:$Q$405,MATCH(55,'計算'!$CT$6:$CT$405,0)),""),IFERROR(INDEX('計算'!$T$6:$T$405,MATCH(55-MAX('計算'!$CT$6:$CT$405),'計算'!$CU$6:$CU$405,0)),""))) | I65: =IF($B65="","",IF(55<=MAX('計算'!$CT$6:$CT$405),IFERROR(INDEX('計算'!$H$6:$H$405,MATCH(55,'計算'!$CT$6:$CT$405,0)),""),IFERROR(INDEX('計算'!$H$6:$H$405,MATCH(55-MAX('計算'!$CT$6:$CT$405),'計算'!$CU$6:$CU$405,0)),""))) | J65: =IF($B65="","",N($H65)*IFERROR(INDEX('計算'!$G$6:$G$405,IF(55<=MAX('計算'!$CT$6:$CT$405),MATCH(55,'計算'!$CT$6:$CT$405,0),MATCH(55-MAX('計算'!$CT$6:$CT$405),'計算'!$CU$6:$CU$405,0))),1)*N($I65))
B66: =IF(56<=MAX('計算'!$CT$6:$CT$405)+MAX('計算'!$CU$6:$CU$405),56,"") | C66: =IF($B66="","",IF(56<=MAX('計算'!$CT$6:$CT$405),IFERROR(INDEX('計算'!$F$6:$F$405,MATCH(56,'計算'!$CT$6:$CT$405,0)),""),IFERROR(INDEX('計算'!$F$6:$F$405,MATCH(56-MAX('計算'!$CT$6:$CT$405),'計算'!$CU$6:$CU$405,0)),""))) | D66: =IF($B66="","",IF(56<=MAX('計算'!$CT$6:$CT$405),IFERROR(INDEX('計算'!$C$6:$C$405,MATCH(56,'計算'!$CT$6:$CT$405,0))&"",""),IFERROR(INDEX('計算'!$C$6:$C$405,MATCH(56-MAX('計算'!$CT$6:$CT$405),'計算'!$CU$6:$CU$405,0))&"",""))) | E66: =IF($B66="","",IF(56<=MAX('計算'!$CT$6:$CT$405),IFERROR(INDEX('計算'!$D$6:$D$405,MATCH(56,'計算'!$CT$6:$CT$405,0)),""),IFERROR(INDEX('計算'!$D$6:$D$405,MATCH(56-MAX('計算'!$CT$6:$CT$405),'計算'!$CU$6:$CU$405,0)),""))) | F66: =IF($B66="","",IF(56<=MAX('計算'!$CT$6:$CT$405),IFERROR(INDEX('計算'!$P$6:$P$405,MATCH(56,'計算'!$CT$6:$CT$405,0)),""),IFERROR(INDEX('計算'!$S$6:$S$405,MATCH(56-MAX('計算'!$CT$6:$CT$405),'計算'!$CU$6:$CU$405,0)),""))) | G66: =IF($B66="","",IF(56<=MAX('計算'!$CT$6:$CT$405),IFERROR(INDEX('計算'!$CR$6:$CR$405,MATCH(56,'計算'!$CT$6:$CT$405,0)),""),IFERROR(INDEX('計算'!$CR$6:$CR$405,MATCH(56-MAX('計算'!$CT$6:$CT$405),'計算'!$CU$6:$CU$405,0)),""))) | H66: =IF($B66="","",IF(56<=MAX('計算'!$CT$6:$CT$405),IFERROR(INDEX('計算'!$Q$6:$Q$405,MATCH(56,'計算'!$CT$6:$CT$405,0)),""),IFERROR(INDEX('計算'!$T$6:$T$405,MATCH(56-MAX('計算'!$CT$6:$CT$405),'計算'!$CU$6:$CU$405,0)),""))) | I66: =IF($B66="","",IF(56<=MAX('計算'!$CT$6:$CT$405),IFERROR(INDEX('計算'!$H$6:$H$405,MATCH(56,'計算'!$CT$6:$CT$405,0)),""),IFERROR(INDEX('計算'!$H$6:$H$405,MATCH(56-MAX('計算'!$CT$6:$CT$405),'計算'!$CU$6:$CU$405,0)),""))) | J66: =IF($B66="","",N($H66)*IFERROR(INDEX('計算'!$G$6:$G$405,IF(56<=MAX('計算'!$CT$6:$CT$405),MATCH(56,'計算'!$CT$6:$CT$405,0),MATCH(56-MAX('計算'!$CT$6:$CT$405),'計算'!$CU$6:$CU$405,0))),1)*N($I66))
B67: =IF(57<=MAX('計算'!$CT$6:$CT$405)+MAX('計算'!$CU$6:$CU$405),57,"") | C67: =IF($B67="","",IF(57<=MAX('計算'!$CT$6:$CT$405),IFERROR(INDEX('計算'!$F$6:$F$405,MATCH(57,'計算'!$CT$6:$CT$405,0)),""),IFERROR(INDEX('計算'!$F$6:$F$405,MATCH(57-MAX('計算'!$CT$6:$CT$405),'計算'!$CU$6:$CU$405,0)),""))) | D67: =IF($B67="","",IF(57<=MAX('計算'!$CT$6:$CT$405),IFERROR(INDEX('計算'!$C$6:$C$405,MATCH(57,'計算'!$CT$6:$CT$405,0))&"",""),IFERROR(INDEX('計算'!$C$6:$C$405,MATCH(57-MAX('計算'!$CT$6:$CT$405),'計算'!$CU$6:$CU$405,0))&"",""))) | E67: =IF($B67="","",IF(57<=MAX('計算'!$CT$6:$CT$405),IFERROR(INDEX('計算'!$D$6:$D$405,MATCH(57,'計算'!$CT$6:$CT$405,0)),""),IFERROR(INDEX('計算'!$D$6:$D$405,MATCH(57-MAX('計算'!$CT$6:$CT$405),'計算'!$CU$6:$CU$405,0)),""))) | F67: =IF($B67="","",IF(57<=MAX('計算'!$CT$6:$CT$405),IFERROR(INDEX('計算'!$P$6:$P$405,MATCH(57,'計算'!$CT$6:$CT$405,0)),""),IFERROR(INDEX('計算'!$S$6:$S$405,MATCH(57-MAX('計算'!$CT$6:$CT$405),'計算'!$CU$6:$CU$405,0)),""))) | G67: =IF($B67="","",IF(57<=MAX('計算'!$CT$6:$CT$405),IFERROR(INDEX('計算'!$CR$6:$CR$405,MATCH(57,'計算'!$CT$6:$CT$405,0)),""),IFERROR(INDEX('計算'!$CR$6:$CR$405,MATCH(57-MAX('計算'!$CT$6:$CT$405),'計算'!$CU$6:$CU$405,0)),""))) | H67: =IF($B67="","",IF(57<=MAX('計算'!$CT$6:$CT$405),IFERROR(INDEX('計算'!$Q$6:$Q$405,MATCH(57,'計算'!$CT$6:$CT$405,0)),""),IFERROR(INDEX('計算'!$T$6:$T$405,MATCH(57-MAX('計算'!$CT$6:$CT$405),'計算'!$CU$6:$CU$405,0)),""))) | I67: =IF($B67="","",IF(57<=MAX('計算'!$CT$6:$CT$405),IFERROR(INDEX('計算'!$H$6:$H$405,MATCH(57,'計算'!$CT$6:$CT$405,0)),""),IFERROR(INDEX('計算'!$H$6:$H$405,MATCH(57-MAX('計算'!$CT$6:$CT$405),'計算'!$CU$6:$CU$405,0)),""))) | J67: =IF($B67="","",N($H67)*IFERROR(INDEX('計算'!$G$6:$G$405,IF(57<=MAX('計算'!$CT$6:$CT$405),MATCH(57,'計算'!$CT$6:$CT$405,0),MATCH(57-MAX('計算'!$CT$6:$CT$405),'計算'!$CU$6:$CU$405,0))),1)*N($I67))
B68: =IF(58<=MAX('計算'!$CT$6:$CT$405)+MAX('計算'!$CU$6:$CU$405),58,"") | C68: =IF($B68="","",IF(58<=MAX('計算'!$CT$6:$CT$405),IFERROR(INDEX('計算'!$F$6:$F$405,MATCH(58,'計算'!$CT$6:$CT$405,0)),""),IFERROR(INDEX('計算'!$F$6:$F$405,MATCH(58-MAX('計算'!$CT$6:$CT$405),'計算'!$CU$6:$CU$405,0)),""))) | D68: =IF($B68="","",IF(58<=MAX('計算'!$CT$6:$CT$405),IFERROR(INDEX('計算'!$C$6:$C$405,MATCH(58,'計算'!$CT$6:$CT$405,0))&"",""),IFERROR(INDEX('計算'!$C$6:$C$405,MATCH(58-MAX('計算'!$CT$6:$CT$405),'計算'!$CU$6:$CU$405,0))&"",""))) | E68: =IF($B68="","",IF(58<=MAX('計算'!$CT$6:$CT$405),IFERROR(INDEX('計算'!$D$6:$D$405,MATCH(58,'計算'!$CT$6:$CT$405,0)),""),IFERROR(INDEX('計算'!$D$6:$D$405,MATCH(58-MAX('計算'!$CT$6:$CT$405),'計算'!$CU$6:$CU$405,0)),""))) | F68: =IF($B68="","",IF(58<=MAX('計算'!$CT$6:$CT$405),IFERROR(INDEX('計算'!$P$6:$P$405,MATCH(58,'計算'!$CT$6:$CT$405,0)),""),IFERROR(INDEX('計算'!$S$6:$S$405,MATCH(58-MAX('計算'!$CT$6:$CT$405),'計算'!$CU$6:$CU$405,0)),""))) | G68: =IF($B68="","",IF(58<=MAX('計算'!$CT$6:$CT$405),IFERROR(INDEX('計算'!$CR$6:$CR$405,MATCH(58,'計算'!$CT$6:$CT$405,0)),""),IFERROR(INDEX('計算'!$CR$6:$CR$405,MATCH(58-MAX('計算'!$CT$6:$CT$405),'計算'!$CU$6:$CU$405,0)),""))) | H68: =IF($B68="","",IF(58<=MAX('計算'!$CT$6:$CT$405),IFERROR(INDEX('計算'!$Q$6:$Q$405,MATCH(58,'計算'!$CT$6:$CT$405,0)),""),IFERROR(INDEX('計算'!$T$6:$T$405,MATCH(58-MAX('計算'!$CT$6:$CT$405),'計算'!$CU$6:$CU$405,0)),""))) | I68: =IF($B68="","",IF(58<=MAX('計算'!$CT$6:$CT$405),IFERROR(INDEX('計算'!$H$6:$H$405,MATCH(58,'計算'!$CT$6:$CT$405,0)),""),IFERROR(INDEX('計算'!$H$6:$H$405,MATCH(58-MAX('計算'!$CT$6:$CT$405),'計算'!$CU$6:$CU$405,0)),""))) | J68: =IF($B68="","",N($H68)*IFERROR(INDEX('計算'!$G$6:$G$405,IF(58<=MAX('計算'!$CT$6:$CT$405),MATCH(58,'計算'!$CT$6:$CT$405,0),MATCH(58-MAX('計算'!$CT$6:$CT$405),'計算'!$CU$6:$CU$405,0))),1)*N($I68))
B69: =IF(59<=MAX('計算'!$CT$6:$CT$405)+MAX('計算'!$CU$6:$CU$405),59,"") | C69: =IF($B69="","",IF(59<=MAX('計算'!$CT$6:$CT$405),IFERROR(INDEX('計算'!$F$6:$F$405,MATCH(59,'計算'!$CT$6:$CT$405,0)),""),IFERROR(INDEX('計算'!$F$6:$F$405,MATCH(59-MAX('計算'!$CT$6:$CT$405),'計算'!$CU$6:$CU$405,0)),""))) | D69: =IF($B69="","",IF(59<=MAX('計算'!$CT$6:$CT$405),IFERROR(INDEX('計算'!$C$6:$C$405,MATCH(59,'計算'!$CT$6:$CT$405,0))&"",""),IFERROR(INDEX('計算'!$C$6:$C$405,MATCH(59-MAX('計算'!$CT$6:$CT$405),'計算'!$CU$6:$CU$405,0))&"",""))) | E69: =IF($B69="","",IF(59<=MAX('計算'!$CT$6:$CT$405),IFERROR(INDEX('計算'!$D$6:$D$405,MATCH(59,'計算'!$CT$6:$CT$405,0)),""),IFERROR(INDEX('計算'!$D$6:$D$405,MATCH(59-MAX('計算'!$CT$6:$CT$405),'計算'!$CU$6:$CU$405,0)),""))) | F69: =IF($B69="","",IF(59<=MAX('計算'!$CT$6:$CT$405),IFERROR(INDEX('計算'!$P$6:$P$405,MATCH(59,'計算'!$CT$6:$CT$405,0)),""),IFERROR(INDEX('計算'!$S$6:$S$405,MATCH(59-MAX('計算'!$CT$6:$CT$405),'計算'!$CU$6:$CU$405,0)),""))) | G69: =IF($B69="","",IF(59<=MAX('計算'!$CT$6:$CT$405),IFERROR(INDEX('計算'!$CR$6:$CR$405,MATCH(59,'計算'!$CT$6:$CT$405,0)),""),IFERROR(INDEX('計算'!$CR$6:$CR$405,MATCH(59-MAX('計算'!$CT$6:$CT$405),'計算'!$CU$6:$CU$405,0)),""))) | H69: =IF($B69="","",IF(59<=MAX('計算'!$CT$6:$CT$405),IFERROR(INDEX('計算'!$Q$6:$Q$405,MATCH(59,'計算'!$CT$6:$CT$405,0)),""),IFERROR(INDEX('計算'!$T$6:$T$405,MATCH(59-MAX('計算'!$CT$6:$CT$405),'計算'!$CU$6:$CU$405,0)),""))) | I69: =IF($B69="","",IF(59<=MAX('計算'!$CT$6:$CT$405),IFERROR(INDEX('計算'!$H$6:$H$405,MATCH(59,'計算'!$CT$6:$CT$405,0)),""),IFERROR(INDEX('計算'!$H$6:$H$405,MATCH(59-MAX('計算'!$CT$6:$CT$405),'計算'!$CU$6:$CU$405,0)),""))) | J69: =IF($B69="","",N($H69)*IFERROR(INDEX('計算'!$G$6:$G$405,IF(59<=MAX('計算'!$CT$6:$CT$405),MATCH(59,'計算'!$CT$6:$CT$405,0),MATCH(59-MAX('計算'!$CT$6:$CT$405),'計算'!$CU$6:$CU$405,0))),1)*N($I69))
B70: =IF(60<=MAX('計算'!$CT$6:$CT$405)+MAX('計算'!$CU$6:$CU$405),60,"") | C70: =IF($B70="","",IF(60<=MAX('計算'!$CT$6:$CT$405),IFERROR(INDEX('計算'!$F$6:$F$405,MATCH(60,'計算'!$CT$6:$CT$405,0)),""),IFERROR(INDEX('計算'!$F$6:$F$405,MATCH(60-MAX('計算'!$CT$6:$CT$405),'計算'!$CU$6:$CU$405,0)),""))) | D70: =IF($B70="","",IF(60<=MAX('計算'!$CT$6:$CT$405),IFERROR(INDEX('計算'!$C$6:$C$405,MATCH(60,'計算'!$CT$6:$CT$405,0))&"",""),IFERROR(INDEX('計算'!$C$6:$C$405,MATCH(60-MAX('計算'!$CT$6:$CT$405),'計算'!$CU$6:$CU$405,0))&"",""))) | E70: =IF($B70="","",IF(60<=MAX('計算'!$CT$6:$CT$405),IFERROR(INDEX('計算'!$D$6:$D$405,MATCH(60,'計算'!$CT$6:$CT$405,0)),""),IFERROR(INDEX('計算'!$D$6:$D$405,MATCH(60-MAX('計算'!$CT$6:$CT$405),'計算'!$CU$6:$CU$405,0)),""))) | F70: =IF($B70="","",IF(60<=MAX('計算'!$CT$6:$CT$405),IFERROR(INDEX('計算'!$P$6:$P$405,MATCH(60,'計算'!$CT$6:$CT$405,0)),""),IFERROR(INDEX('計算'!$S$6:$S$405,MATCH(60-MAX('計算'!$CT$6:$CT$405),'計算'!$CU$6:$CU$405,0)),""))) | G70: =IF($B70="","",IF(60<=MAX('計算'!$CT$6:$CT$405),IFERROR(INDEX('計算'!$CR$6:$CR$405,MATCH(60,'計算'!$CT$6:$CT$405,0)),""),IFERROR(INDEX('計算'!$CR$6:$CR$405,MATCH(60-MAX('計算'!$CT$6:$CT$405),'計算'!$CU$6:$CU$405,0)),""))) | H70: =IF($B70="","",IF(60<=MAX('計算'!$CT$6:$CT$405),IFERROR(INDEX('計算'!$Q$6:$Q$405,MATCH(60,'計算'!$CT$6:$CT$405,0)),""),IFERROR(INDEX('計算'!$T$6:$T$405,MATCH(60-MAX('計算'!$CT$6:$CT$405),'計算'!$CU$6:$CU$405,0)),""))) | I70: =IF($B70="","",IF(60<=MAX('計算'!$CT$6:$CT$405),IFERROR(INDEX('計算'!$H$6:$H$405,MATCH(60,'計算'!$CT$6:$CT$405,0)),""),IFERROR(INDEX('計算'!$H$6:$H$405,MATCH(60-MAX('計算'!$CT$6:$CT$405),'計算'!$CU$6:$CU$405,0)),""))) | J70: =IF($B70="","",N($H70)*IFERROR(INDEX('計算'!$G$6:$G$405,IF(60<=MAX('計算'!$CT$6:$CT$405),MATCH(60,'計算'!$CT$6:$CT$405,0),MATCH(60-MAX('計算'!$CT$6:$CT$405),'計算'!$CU$6:$CU$405,0))),1)*N($I70))
B71: =IF(61<=MAX('計算'!$CT$6:$CT$405)+MAX('計算'!$CU$6:$CU$405),61,"") | C71: =IF($B71="","",IF(61<=MAX('計算'!$CT$6:$CT$405),IFERROR(INDEX('計算'!$F$6:$F$405,MATCH(61,'計算'!$CT$6:$CT$405,0)),""),IFERROR(INDEX('計算'!$F$6:$F$405,MATCH(61-MAX('計算'!$CT$6:$CT$405),'計算'!$CU$6:$CU$405,0)),""))) | D71: =IF($B71="","",IF(61<=MAX('計算'!$CT$6:$CT$405),IFERROR(INDEX('計算'!$C$6:$C$405,MATCH(61,'計算'!$CT$6:$CT$405,0))&"",""),IFERROR(INDEX('計算'!$C$6:$C$405,MATCH(61-MAX('計算'!$CT$6:$CT$405),'計算'!$CU$6:$CU$405,0))&"",""))) | E71: =IF($B71="","",IF(61<=MAX('計算'!$CT$6:$CT$405),IFERROR(INDEX('計算'!$D$6:$D$405,MATCH(61,'計算'!$CT$6:$CT$405,0)),""),IFERROR(INDEX('計算'!$D$6:$D$405,MATCH(61-MAX('計算'!$CT$6:$CT$405),'計算'!$CU$6:$CU$405,0)),""))) | F71: =IF($B71="","",IF(61<=MAX('計算'!$CT$6:$CT$405),IFERROR(INDEX('計算'!$P$6:$P$405,MATCH(61,'計算'!$CT$6:$CT$405,0)),""),IFERROR(INDEX('計算'!$S$6:$S$405,MATCH(61-MAX('計算'!$CT$6:$CT$405),'計算'!$CU$6:$CU$405,0)),""))) | G71: =IF($B71="","",IF(61<=MAX('計算'!$CT$6:$CT$405),IFERROR(INDEX('計算'!$CR$6:$CR$405,MATCH(61,'計算'!$CT$6:$CT$405,0)),""),IFERROR(INDEX('計算'!$CR$6:$CR$405,MATCH(61-MAX('計算'!$CT$6:$CT$405),'計算'!$CU$6:$CU$405,0)),""))) | H71: =IF($B71="","",IF(61<=MAX('計算'!$CT$6:$CT$405),IFERROR(INDEX('計算'!$Q$6:$Q$405,MATCH(61,'計算'!$CT$6:$CT$405,0)),""),IFERROR(INDEX('計算'!$T$6:$T$405,MATCH(61-MAX('計算'!$CT$6:$CT$405),'計算'!$CU$6:$CU$405,0)),""))) | I71: =IF($B71="","",IF(61<=MAX('計算'!$CT$6:$CT$405),IFERROR(INDEX('計算'!$H$6:$H$405,MATCH(61,'計算'!$CT$6:$CT$405,0)),""),IFERROR(INDEX('計算'!$H$6:$H$405,MATCH(61-MAX('計算'!$CT$6:$CT$405),'計算'!$CU$6:$CU$405,0)),""))) | J71: =IF($B71="","",N($H71)*IFERROR(INDEX('計算'!$G$6:$G$405,IF(61<=MAX('計算'!$CT$6:$CT$405),MATCH(61,'計算'!$CT$6:$CT$405,0),MATCH(61-MAX('計算'!$CT$6:$CT$405),'計算'!$CU$6:$CU$405,0))),1)*N($I71))
B72: =IF(62<=MAX('計算'!$CT$6:$CT$405)+MAX('計算'!$CU$6:$CU$405),62,"") | C72: =IF($B72="","",IF(62<=MAX('計算'!$CT$6:$CT$405),IFERROR(INDEX('計算'!$F$6:$F$405,MATCH(62,'計算'!$CT$6:$CT$405,0)),""),IFERROR(INDEX('計算'!$F$6:$F$405,MATCH(62-MAX('計算'!$CT$6:$CT$405),'計算'!$CU$6:$CU$405,0)),""))) | D72: =IF($B72="","",IF(62<=MAX('計算'!$CT$6:$CT$405),IFERROR(INDEX('計算'!$C$6:$C$405,MATCH(62,'計算'!$CT$6:$CT$405,0))&"",""),IFERROR(INDEX('計算'!$C$6:$C$405,MATCH(62-MAX('計算'!$CT$6:$CT$405),'計算'!$CU$6:$CU$405,0))&"",""))) | E72: =IF($B72="","",IF(62<=MAX('計算'!$CT$6:$CT$405),IFERROR(INDEX('計算'!$D$6:$D$405,MATCH(62,'計算'!$CT$6:$CT$405,0)),""),IFERROR(INDEX('計算'!$D$6:$D$405,MATCH(62-MAX('計算'!$CT$6:$CT$405),'計算'!$CU$6:$CU$405,0)),""))) | F72: =IF($B72="","",IF(62<=MAX('計算'!$CT$6:$CT$405),IFERROR(INDEX('計算'!$P$6:$P$405,MATCH(62,'計算'!$CT$6:$CT$405,0)),""),IFERROR(INDEX('計算'!$S$6:$S$405,MATCH(62-MAX('計算'!$CT$6:$CT$405),'計算'!$CU$6:$CU$405,0)),""))) | G72: =IF($B72="","",IF(62<=MAX('計算'!$CT$6:$CT$405),IFERROR(INDEX('計算'!$CR$6:$CR$405,MATCH(62,'計算'!$CT$6:$CT$405,0)),""),IFERROR(INDEX('計算'!$CR$6:$CR$405,MATCH(62-MAX('計算'!$CT$6:$CT$405),'計算'!$CU$6:$CU$405,0)),""))) | H72: =IF($B72="","",IF(62<=MAX('計算'!$CT$6:$CT$405),IFERROR(INDEX('計算'!$Q$6:$Q$405,MATCH(62,'計算'!$CT$6:$CT$405,0)),""),IFERROR(INDEX('計算'!$T$6:$T$405,MATCH(62-MAX('計算'!$CT$6:$CT$405),'計算'!$CU$6:$CU$405,0)),""))) | I72: =IF($B72="","",IF(62<=MAX('計算'!$CT$6:$CT$405),IFERROR(INDEX('計算'!$H$6:$H$405,MATCH(62,'計算'!$CT$6:$CT$405,0)),""),IFERROR(INDEX('計算'!$H$6:$H$405,MATCH(62-MAX('計算'!$CT$6:$CT$405),'計算'!$CU$6:$CU$405,0)),""))) | J72: =IF($B72="","",N($H72)*IFERROR(INDEX('計算'!$G$6:$G$405,IF(62<=MAX('計算'!$CT$6:$CT$405),MATCH(62,'計算'!$CT$6:$CT$405,0),MATCH(62-MAX('計算'!$CT$6:$CT$405),'計算'!$CU$6:$CU$405,0))),1)*N($I72))
B73: =IF(63<=MAX('計算'!$CT$6:$CT$405)+MAX('計算'!$CU$6:$CU$405),63,"") | C73: =IF($B73="","",IF(63<=MAX('計算'!$CT$6:$CT$405),IFERROR(INDEX('計算'!$F$6:$F$405,MATCH(63,'計算'!$CT$6:$CT$405,0)),""),IFERROR(INDEX('計算'!$F$6:$F$405,MATCH(63-MAX('計算'!$CT$6:$CT$405),'計算'!$CU$6:$CU$405,0)),""))) | D73: =IF($B73="","",IF(63<=MAX('計算'!$CT$6:$CT$405),IFERROR(INDEX('計算'!$C$6:$C$405,MATCH(63,'計算'!$CT$6:$CT$405,0))&"",""),IFERROR(INDEX('計算'!$C$6:$C$405,MATCH(63-MAX('計算'!$CT$6:$CT$405),'計算'!$CU$6:$CU$405,0))&"",""))) | E73: =IF($B73="","",IF(63<=MAX('計算'!$CT$6:$CT$405),IFERROR(INDEX('計算'!$D$6:$D$405,MATCH(63,'計算'!$CT$6:$CT$405,0)),""),IFERROR(INDEX('計算'!$D$6:$D$405,MATCH(63-MAX('計算'!$CT$6:$CT$405),'計算'!$CU$6:$CU$405,0)),""))) | F73: =IF($B73="","",IF(63<=MAX('計算'!$CT$6:$CT$405),IFERROR(INDEX('計算'!$P$6:$P$405,MATCH(63,'計算'!$CT$6:$CT$405,0)),""),IFERROR(INDEX('計算'!$S$6:$S$405,MATCH(63-MAX('計算'!$CT$6:$CT$405),'計算'!$CU$6:$CU$405,0)),""))) | G73: =IF($B73="","",IF(63<=MAX('計算'!$CT$6:$CT$405),IFERROR(INDEX('計算'!$CR$6:$CR$405,MATCH(63,'計算'!$CT$6:$CT$405,0)),""),IFERROR(INDEX('計算'!$CR$6:$CR$405,MATCH(63-MAX('計算'!$CT$6:$CT$405),'計算'!$CU$6:$CU$405,0)),""))) | H73: =IF($B73="","",IF(63<=MAX('計算'!$CT$6:$CT$405),IFERROR(INDEX('計算'!$Q$6:$Q$405,MATCH(63,'計算'!$CT$6:$CT$405,0)),""),IFERROR(INDEX('計算'!$T$6:$T$405,MATCH(63-MAX('計算'!$CT$6:$CT$405),'計算'!$CU$6:$CU$405,0)),""))) | I73: =IF($B73="","",IF(63<=MAX('計算'!$CT$6:$CT$405),IFERROR(INDEX('計算'!$H$6:$H$405,MATCH(63,'計算'!$CT$6:$CT$405,0)),""),IFERROR(INDEX('計算'!$H$6:$H$405,MATCH(63-MAX('計算'!$CT$6:$CT$405),'計算'!$CU$6:$CU$405,0)),""))) | J73: =IF($B73="","",N($H73)*IFERROR(INDEX('計算'!$G$6:$G$405,IF(63<=MAX('計算'!$CT$6:$CT$405),MATCH(63,'計算'!$CT$6:$CT$405,0),MATCH(63-MAX('計算'!$CT$6:$CT$405),'計算'!$CU$6:$CU$405,0))),1)*N($I73))
B74: =IF(64<=MAX('計算'!$CT$6:$CT$405)+MAX('計算'!$CU$6:$CU$405),64,"") | C74: =IF($B74="","",IF(64<=MAX('計算'!$CT$6:$CT$405),IFERROR(INDEX('計算'!$F$6:$F$405,MATCH(64,'計算'!$CT$6:$CT$405,0)),""),IFERROR(INDEX('計算'!$F$6:$F$405,MATCH(64-MAX('計算'!$CT$6:$CT$405),'計算'!$CU$6:$CU$405,0)),""))) | D74: =IF($B74="","",IF(64<=MAX('計算'!$CT$6:$CT$405),IFERROR(INDEX('計算'!$C$6:$C$405,MATCH(64,'計算'!$CT$6:$CT$405,0))&"",""),IFERROR(INDEX('計算'!$C$6:$C$405,MATCH(64-MAX('計算'!$CT$6:$CT$405),'計算'!$CU$6:$CU$405,0))&"",""))) | E74: =IF($B74="","",IF(64<=MAX('計算'!$CT$6:$CT$405),IFERROR(INDEX('計算'!$D$6:$D$405,MATCH(64,'計算'!$CT$6:$CT$405,0)),""),IFERROR(INDEX('計算'!$D$6:$D$405,MATCH(64-MAX('計算'!$CT$6:$CT$405),'計算'!$CU$6:$CU$405,0)),""))) | F74: =IF($B74="","",IF(64<=MAX('計算'!$CT$6:$CT$405),IFERROR(INDEX('計算'!$P$6:$P$405,MATCH(64,'計算'!$CT$6:$CT$405,0)),""),IFERROR(INDEX('計算'!$S$6:$S$405,MATCH(64-MAX('計算'!$CT$6:$CT$405),'計算'!$CU$6:$CU$405,0)),""))) | G74: =IF($B74="","",IF(64<=MAX('計算'!$CT$6:$CT$405),IFERROR(INDEX('計算'!$CR$6:$CR$405,MATCH(64,'計算'!$CT$6:$CT$405,0)),""),IFERROR(INDEX('計算'!$CR$6:$CR$405,MATCH(64-MAX('計算'!$CT$6:$CT$405),'計算'!$CU$6:$CU$405,0)),""))) | H74: =IF($B74="","",IF(64<=MAX('計算'!$CT$6:$CT$405),IFERROR(INDEX('計算'!$Q$6:$Q$405,MATCH(64,'計算'!$CT$6:$CT$405,0)),""),IFERROR(INDEX('計算'!$T$6:$T$405,MATCH(64-MAX('計算'!$CT$6:$CT$405),'計算'!$CU$6:$CU$405,0)),""))) | I74: =IF($B74="","",IF(64<=MAX('計算'!$CT$6:$CT$405),IFERROR(INDEX('計算'!$H$6:$H$405,MATCH(64,'計算'!$CT$6:$CT$405,0)),""),IFERROR(INDEX('計算'!$H$6:$H$405,MATCH(64-MAX('計算'!$CT$6:$CT$405),'計算'!$CU$6:$CU$405,0)),""))) | J74: =IF($B74="","",N($H74)*IFERROR(INDEX('計算'!$G$6:$G$405,IF(64<=MAX('計算'!$CT$6:$CT$405),MATCH(64,'計算'!$CT$6:$CT$405,0),MATCH(64-MAX('計算'!$CT$6:$CT$405),'計算'!$CU$6:$CU$405,0))),1)*N($I74))
B75: =IF(65<=MAX('計算'!$CT$6:$CT$405)+MAX('計算'!$CU$6:$CU$405),65,"") | C75: =IF($B75="","",IF(65<=MAX('計算'!$CT$6:$CT$405),IFERROR(INDEX('計算'!$F$6:$F$405,MATCH(65,'計算'!$CT$6:$CT$405,0)),""),IFERROR(INDEX('計算'!$F$6:$F$405,MATCH(65-MAX('計算'!$CT$6:$CT$405),'計算'!$CU$6:$CU$405,0)),""))) | D75: =IF($B75="","",IF(65<=MAX('計算'!$CT$6:$CT$405),IFERROR(INDEX('計算'!$C$6:$C$405,MATCH(65,'計算'!$CT$6:$CT$405,0))&"",""),IFERROR(INDEX('計算'!$C$6:$C$405,MATCH(65-MAX('計算'!$CT$6:$CT$405),'計算'!$CU$6:$CU$405,0))&"",""))) | E75: =IF($B75="","",IF(65<=MAX('計算'!$CT$6:$CT$405),IFERROR(INDEX('計算'!$D$6:$D$405,MATCH(65,'計算'!$CT$6:$CT$405,0)),""),IFERROR(INDEX('計算'!$D$6:$D$405,MATCH(65-MAX('計算'!$CT$6:$CT$405),'計算'!$CU$6:$CU$405,0)),""))) | F75: =IF($B75="","",IF(65<=MAX('計算'!$CT$6:$CT$405),IFERROR(INDEX('計算'!$P$6:$P$405,MATCH(65,'計算'!$CT$6:$CT$405,0)),""),IFERROR(INDEX('計算'!$S$6:$S$405,MATCH(65-MAX('計算'!$CT$6:$CT$405),'計算'!$CU$6:$CU$405,0)),""))) | G75: =IF($B75="","",IF(65<=MAX('計算'!$CT$6:$CT$405),IFERROR(INDEX('計算'!$CR$6:$CR$405,MATCH(65,'計算'!$CT$6:$CT$405,0)),""),IFERROR(INDEX('計算'!$CR$6:$CR$405,MATCH(65-MAX('計算'!$CT$6:$CT$405),'計算'!$CU$6:$CU$405,0)),""))) | H75: =IF($B75="","",IF(65<=MAX('計算'!$CT$6:$CT$405),IFERROR(INDEX('計算'!$Q$6:$Q$405,MATCH(65,'計算'!$CT$6:$CT$405,0)),""),IFERROR(INDEX('計算'!$T$6:$T$405,MATCH(65-MAX('計算'!$CT$6:$CT$405),'計算'!$CU$6:$CU$405,0)),""))) | I75: =IF($B75="","",IF(65<=MAX('計算'!$CT$6:$CT$405),IFERROR(INDEX('計算'!$H$6:$H$405,MATCH(65,'計算'!$CT$6:$CT$405,0)),""),IFERROR(INDEX('計算'!$H$6:$H$405,MATCH(65-MAX('計算'!$CT$6:$CT$405),'計算'!$CU$6:$CU$405,0)),""))) | J75: =IF($B75="","",N($H75)*IFERROR(INDEX('計算'!$G$6:$G$405,IF(65<=MAX('計算'!$CT$6:$CT$405),MATCH(65,'計算'!$CT$6:$CT$405,0),MATCH(65-MAX('計算'!$CT$6:$CT$405),'計算'!$CU$6:$CU$405,0))),1)*N($I75))
B76: =IF(66<=MAX('計算'!$CT$6:$CT$405)+MAX('計算'!$CU$6:$CU$405),66,"") | C76: =IF($B76="","",IF(66<=MAX('計算'!$CT$6:$CT$405),IFERROR(INDEX('計算'!$F$6:$F$405,MATCH(66,'計算'!$CT$6:$CT$405,0)),""),IFERROR(INDEX('計算'!$F$6:$F$405,MATCH(66-MAX('計算'!$CT$6:$CT$405),'計算'!$CU$6:$CU$405,0)),""))) | D76: =IF($B76="","",IF(66<=MAX('計算'!$CT$6:$CT$405),IFERROR(INDEX('計算'!$C$6:$C$405,MATCH(66,'計算'!$CT$6:$CT$405,0))&"",""),IFERROR(INDEX('計算'!$C$6:$C$405,MATCH(66-MAX('計算'!$CT$6:$CT$405),'計算'!$CU$6:$CU$405,0))&"",""))) | E76: =IF($B76="","",IF(66<=MAX('計算'!$CT$6:$CT$405),IFERROR(INDEX('計算'!$D$6:$D$405,MATCH(66,'計算'!$CT$6:$CT$405,0)),""),IFERROR(INDEX('計算'!$D$6:$D$405,MATCH(66-MAX('計算'!$CT$6:$CT$405),'計算'!$CU$6:$CU$405,0)),""))) | F76: =IF($B76="","",IF(66<=MAX('計算'!$CT$6:$CT$405),IFERROR(INDEX('計算'!$P$6:$P$405,MATCH(66,'計算'!$CT$6:$CT$405,0)),""),IFERROR(INDEX('計算'!$S$6:$S$405,MATCH(66-MAX('計算'!$CT$6:$CT$405),'計算'!$CU$6:$CU$405,0)),""))) | G76: =IF($B76="","",IF(66<=MAX('計算'!$CT$6:$CT$405),IFERROR(INDEX('計算'!$CR$6:$CR$405,MATCH(66,'計算'!$CT$6:$CT$405,0)),""),IFERROR(INDEX('計算'!$CR$6:$CR$405,MATCH(66-MAX('計算'!$CT$6:$CT$405),'計算'!$CU$6:$CU$405,0)),""))) | H76: =IF($B76="","",IF(66<=MAX('計算'!$CT$6:$CT$405),IFERROR(INDEX('計算'!$Q$6:$Q$405,MATCH(66,'計算'!$CT$6:$CT$405,0)),""),IFERROR(INDEX('計算'!$T$6:$T$405,MATCH(66-MAX('計算'!$CT$6:$CT$405),'計算'!$CU$6:$CU$405,0)),""))) | I76: =IF($B76="","",IF(66<=MAX('計算'!$CT$6:$CT$405),IFERROR(INDEX('計算'!$H$6:$H$405,MATCH(66,'計算'!$CT$6:$CT$405,0)),""),IFERROR(INDEX('計算'!$H$6:$H$405,MATCH(66-MAX('計算'!$CT$6:$CT$405),'計算'!$CU$6:$CU$405,0)),""))) | J76: =IF($B76="","",N($H76)*IFERROR(INDEX('計算'!$G$6:$G$405,IF(66<=MAX('計算'!$CT$6:$CT$405),MATCH(66,'計算'!$CT$6:$CT$405,0),MATCH(66-MAX('計算'!$CT$6:$CT$405),'計算'!$CU$6:$CU$405,0))),1)*N($I76))
B77: =IF(67<=MAX('計算'!$CT$6:$CT$405)+MAX('計算'!$CU$6:$CU$405),67,"") | C77: =IF($B77="","",IF(67<=MAX('計算'!$CT$6:$CT$405),IFERROR(INDEX('計算'!$F$6:$F$405,MATCH(67,'計算'!$CT$6:$CT$405,0)),""),IFERROR(INDEX('計算'!$F$6:$F$405,MATCH(67-MAX('計算'!$CT$6:$CT$405),'計算'!$CU$6:$CU$405,0)),""))) | D77: =IF($B77="","",IF(67<=MAX('計算'!$CT$6:$CT$405),IFERROR(INDEX('計算'!$C$6:$C$405,MATCH(67,'計算'!$CT$6:$CT$405,0))&"",""),IFERROR(INDEX('計算'!$C$6:$C$405,MATCH(67-MAX('計算'!$CT$6:$CT$405),'計算'!$CU$6:$CU$405,0))&"",""))) | E77: =IF($B77="","",IF(67<=MAX('計算'!$CT$6:$CT$405),IFERROR(INDEX('計算'!$D$6:$D$405,MATCH(67,'計算'!$CT$6:$CT$405,0)),""),IFERROR(INDEX('計算'!$D$6:$D$405,MATCH(67-MAX('計算'!$CT$6:$CT$405),'計算'!$CU$6:$CU$405,0)),""))) | F77: =IF($B77="","",IF(67<=MAX('計算'!$CT$6:$CT$405),IFERROR(INDEX('計算'!$P$6:$P$405,MATCH(67,'計算'!$CT$6:$CT$405,0)),""),IFERROR(INDEX('計算'!$S$6:$S$405,MATCH(67-MAX('計算'!$CT$6:$CT$405),'計算'!$CU$6:$CU$405,0)),""))) | G77: =IF($B77="","",IF(67<=MAX('計算'!$CT$6:$CT$405),IFERROR(INDEX('計算'!$CR$6:$CR$405,MATCH(67,'計算'!$CT$6:$CT$405,0)),""),IFERROR(INDEX('計算'!$CR$6:$CR$405,MATCH(67-MAX('計算'!$CT$6:$CT$405),'計算'!$CU$6:$CU$405,0)),""))) | H77: =IF($B77="","",IF(67<=MAX('計算'!$CT$6:$CT$405),IFERROR(INDEX('計算'!$Q$6:$Q$405,MATCH(67,'計算'!$CT$6:$CT$405,0)),""),IFERROR(INDEX('計算'!$T$6:$T$405,MATCH(67-MAX('計算'!$CT$6:$CT$405),'計算'!$CU$6:$CU$405,0)),""))) | I77: =IF($B77="","",IF(67<=MAX('計算'!$CT$6:$CT$405),IFERROR(INDEX('計算'!$H$6:$H$405,MATCH(67,'計算'!$CT$6:$CT$405,0)),""),IFERROR(INDEX('計算'!$H$6:$H$405,MATCH(67-MAX('計算'!$CT$6:$CT$405),'計算'!$CU$6:$CU$405,0)),""))) | J77: =IF($B77="","",N($H77)*IFERROR(INDEX('計算'!$G$6:$G$405,IF(67<=MAX('計算'!$CT$6:$CT$405),MATCH(67,'計算'!$CT$6:$CT$405,0),MATCH(67-MAX('計算'!$CT$6:$CT$405),'計算'!$CU$6:$CU$405,0))),1)*N($I77))
B78: =IF(68<=MAX('計算'!$CT$6:$CT$405)+MAX('計算'!$CU$6:$CU$405),68,"") | C78: =IF($B78="","",IF(68<=MAX('計算'!$CT$6:$CT$405),IFERROR(INDEX('計算'!$F$6:$F$405,MATCH(68,'計算'!$CT$6:$CT$405,0)),""),IFERROR(INDEX('計算'!$F$6:$F$405,MATCH(68-MAX('計算'!$CT$6:$CT$405),'計算'!$CU$6:$CU$405,0)),""))) | D78: =IF($B78="","",IF(68<=MAX('計算'!$CT$6:$CT$405),IFERROR(INDEX('計算'!$C$6:$C$405,MATCH(68,'計算'!$CT$6:$CT$405,0))&"",""),IFERROR(INDEX('計算'!$C$6:$C$405,MATCH(68-MAX('計算'!$CT$6:$CT$405),'計算'!$CU$6:$CU$405,0))&"",""))) | E78: =IF($B78="","",IF(68<=MAX('計算'!$CT$6:$CT$405),IFERROR(INDEX('計算'!$D$6:$D$405,MATCH(68,'計算'!$CT$6:$CT$405,0)),""),IFERROR(INDEX('計算'!$D$6:$D$405,MATCH(68-MAX('計算'!$CT$6:$CT$405),'計算'!$CU$6:$CU$405,0)),""))) | F78: =IF($B78="","",IF(68<=MAX('計算'!$CT$6:$CT$405),IFERROR(INDEX('計算'!$P$6:$P$405,MATCH(68,'計算'!$CT$6:$CT$405,0)),""),IFERROR(INDEX('計算'!$S$6:$S$405,MATCH(68-MAX('計算'!$CT$6:$CT$405),'計算'!$CU$6:$CU$405,0)),""))) | G78: =IF($B78="","",IF(68<=MAX('計算'!$CT$6:$CT$405),IFERROR(INDEX('計算'!$CR$6:$CR$405,MATCH(68,'計算'!$CT$6:$CT$405,0)),""),IFERROR(INDEX('計算'!$CR$6:$CR$405,MATCH(68-MAX('計算'!$CT$6:$CT$405),'計算'!$CU$6:$CU$405,0)),""))) | H78: =IF($B78="","",IF(68<=MAX('計算'!$CT$6:$CT$405),IFERROR(INDEX('計算'!$Q$6:$Q$405,MATCH(68,'計算'!$CT$6:$CT$405,0)),""),IFERROR(INDEX('計算'!$T$6:$T$405,MATCH(68-MAX('計算'!$CT$6:$CT$405),'計算'!$CU$6:$CU$405,0)),""))) | I78: =IF($B78="","",IF(68<=MAX('計算'!$CT$6:$CT$405),IFERROR(INDEX('計算'!$H$6:$H$405,MATCH(68,'計算'!$CT$6:$CT$405,0)),""),IFERROR(INDEX('計算'!$H$6:$H$405,MATCH(68-MAX('計算'!$CT$6:$CT$405),'計算'!$CU$6:$CU$405,0)),""))) | J78: =IF($B78="","",N($H78)*IFERROR(INDEX('計算'!$G$6:$G$405,IF(68<=MAX('計算'!$CT$6:$CT$405),MATCH(68,'計算'!$CT$6:$CT$405,0),MATCH(68-MAX('計算'!$CT$6:$CT$405),'計算'!$CU$6:$CU$405,0))),1)*N($I78))
B79: =IF(69<=MAX('計算'!$CT$6:$CT$405)+MAX('計算'!$CU$6:$CU$405),69,"") | C79: =IF($B79="","",IF(69<=MAX('計算'!$CT$6:$CT$405),IFERROR(INDEX('計算'!$F$6:$F$405,MATCH(69,'計算'!$CT$6:$CT$405,0)),""),IFERROR(INDEX('計算'!$F$6:$F$405,MATCH(69-MAX('計算'!$CT$6:$CT$405),'計算'!$CU$6:$CU$405,0)),""))) | D79: =IF($B79="","",IF(69<=MAX('計算'!$CT$6:$CT$405),IFERROR(INDEX('計算'!$C$6:$C$405,MATCH(69,'計算'!$CT$6:$CT$405,0))&"",""),IFERROR(INDEX('計算'!$C$6:$C$405,MATCH(69-MAX('計算'!$CT$6:$CT$405),'計算'!$CU$6:$CU$405,0))&"",""))) | E79: =IF($B79="","",IF(69<=MAX('計算'!$CT$6:$CT$405),IFERROR(INDEX('計算'!$D$6:$D$405,MATCH(69,'計算'!$CT$6:$CT$405,0)),""),IFERROR(INDEX('計算'!$D$6:$D$405,MATCH(69-MAX('計算'!$CT$6:$CT$405),'計算'!$CU$6:$CU$405,0)),""))) | F79: =IF($B79="","",IF(69<=MAX('計算'!$CT$6:$CT$405),IFERROR(INDEX('計算'!$P$6:$P$405,MATCH(69,'計算'!$CT$6:$CT$405,0)),""),IFERROR(INDEX('計算'!$S$6:$S$405,MATCH(69-MAX('計算'!$CT$6:$CT$405),'計算'!$CU$6:$CU$405,0)),""))) | G79: =IF($B79="","",IF(69<=MAX('計算'!$CT$6:$CT$405),IFERROR(INDEX('計算'!$CR$6:$CR$405,MATCH(69,'計算'!$CT$6:$CT$405,0)),""),IFERROR(INDEX('計算'!$CR$6:$CR$405,MATCH(69-MAX('計算'!$CT$6:$CT$405),'計算'!$CU$6:$CU$405,0)),""))) | H79: =IF($B79="","",IF(69<=MAX('計算'!$CT$6:$CT$405),IFERROR(INDEX('計算'!$Q$6:$Q$405,MATCH(69,'計算'!$CT$6:$CT$405,0)),""),IFERROR(INDEX('計算'!$T$6:$T$405,MATCH(69-MAX('計算'!$CT$6:$CT$405),'計算'!$CU$6:$CU$405,0)),""))) | I79: =IF($B79="","",IF(69<=MAX('計算'!$CT$6:$CT$405),IFERROR(INDEX('計算'!$H$6:$H$405,MATCH(69,'計算'!$CT$6:$CT$405,0)),""),IFERROR(INDEX('計算'!$H$6:$H$405,MATCH(69-MAX('計算'!$CT$6:$CT$405),'計算'!$CU$6:$CU$405,0)),""))) | J79: =IF($B79="","",N($H79)*IFERROR(INDEX('計算'!$G$6:$G$405,IF(69<=MAX('計算'!$CT$6:$CT$405),MATCH(69,'計算'!$CT$6:$CT$405,0),MATCH(69-MAX('計算'!$CT$6:$CT$405),'計算'!$CU$6:$CU$405,0))),1)*N($I79))
B80: =IF(70<=MAX('計算'!$CT$6:$CT$405)+MAX('計算'!$CU$6:$CU$405),70,"") | C80: =IF($B80="","",IF(70<=MAX('計算'!$CT$6:$CT$405),IFERROR(INDEX('計算'!$F$6:$F$405,MATCH(70,'計算'!$CT$6:$CT$405,0)),""),IFERROR(INDEX('計算'!$F$6:$F$405,MATCH(70-MAX('計算'!$CT$6:$CT$405),'計算'!$CU$6:$CU$405,0)),""))) | D80: =IF($B80="","",IF(70<=MAX('計算'!$CT$6:$CT$405),IFERROR(INDEX('計算'!$C$6:$C$405,MATCH(70,'計算'!$CT$6:$CT$405,0))&"",""),IFERROR(INDEX('計算'!$C$6:$C$405,MATCH(70-MAX('計算'!$CT$6:$CT$405),'計算'!$CU$6:$CU$405,0))&"",""))) | E80: =IF($B80="","",IF(70<=MAX('計算'!$CT$6:$CT$405),IFERROR(INDEX('計算'!$D$6:$D$405,MATCH(70,'計算'!$CT$6:$CT$405,0)),""),IFERROR(INDEX('計算'!$D$6:$D$405,MATCH(70-MAX('計算'!$CT$6:$CT$405),'計算'!$CU$6:$CU$405,0)),""))) | F80: =IF($B80="","",IF(70<=MAX('計算'!$CT$6:$CT$405),IFERROR(INDEX('計算'!$P$6:$P$405,MATCH(70,'計算'!$CT$6:$CT$405,0)),""),IFERROR(INDEX('計算'!$S$6:$S$405,MATCH(70-MAX('計算'!$CT$6:$CT$405),'計算'!$CU$6:$CU$405,0)),""))) | G80: =IF($B80="","",IF(70<=MAX('計算'!$CT$6:$CT$405),IFERROR(INDEX('計算'!$CR$6:$CR$405,MATCH(70,'計算'!$CT$6:$CT$405,0)),""),IFERROR(INDEX('計算'!$CR$6:$CR$405,MATCH(70-MAX('計算'!$CT$6:$CT$405),'計算'!$CU$6:$CU$405,0)),""))) | H80: =IF($B80="","",IF(70<=MAX('計算'!$CT$6:$CT$405),IFERROR(INDEX('計算'!$Q$6:$Q$405,MATCH(70,'計算'!$CT$6:$CT$405,0)),""),IFERROR(INDEX('計算'!$T$6:$T$405,MATCH(70-MAX('計算'!$CT$6:$CT$405),'計算'!$CU$6:$CU$405,0)),""))) | I80: =IF($B80="","",IF(70<=MAX('計算'!$CT$6:$CT$405),IFERROR(INDEX('計算'!$H$6:$H$405,MATCH(70,'計算'!$CT$6:$CT$405,0)),""),IFERROR(INDEX('計算'!$H$6:$H$405,MATCH(70-MAX('計算'!$CT$6:$CT$405),'計算'!$CU$6:$CU$405,0)),""))) | J80: =IF($B80="","",N($H80)*IFERROR(INDEX('計算'!$G$6:$G$405,IF(70<=MAX('計算'!$CT$6:$CT$405),MATCH(70,'計算'!$CT$6:$CT$405,0),MATCH(70-MAX('計算'!$CT$6:$CT$405),'計算'!$CU$6:$CU$405,0))),1)*N($I80))
B81: =IF(71<=MAX('計算'!$CT$6:$CT$405)+MAX('計算'!$CU$6:$CU$405),71,"") | C81: =IF($B81="","",IF(71<=MAX('計算'!$CT$6:$CT$405),IFERROR(INDEX('計算'!$F$6:$F$405,MATCH(71,'計算'!$CT$6:$CT$405,0)),""),IFERROR(INDEX('計算'!$F$6:$F$405,MATCH(71-MAX('計算'!$CT$6:$CT$405),'計算'!$CU$6:$CU$405,0)),""))) | D81: =IF($B81="","",IF(71<=MAX('計算'!$CT$6:$CT$405),IFERROR(INDEX('計算'!$C$6:$C$405,MATCH(71,'計算'!$CT$6:$CT$405,0))&"",""),IFERROR(INDEX('計算'!$C$6:$C$405,MATCH(71-MAX('計算'!$CT$6:$CT$405),'計算'!$CU$6:$CU$405,0))&"",""))) | E81: =IF($B81="","",IF(71<=MAX('計算'!$CT$6:$CT$405),IFERROR(INDEX('計算'!$D$6:$D$405,MATCH(71,'計算'!$CT$6:$CT$405,0)),""),IFERROR(INDEX('計算'!$D$6:$D$405,MATCH(71-MAX('計算'!$CT$6:$CT$405),'計算'!$CU$6:$CU$405,0)),""))) | F81: =IF($B81="","",IF(71<=MAX('計算'!$CT$6:$CT$405),IFERROR(INDEX('計算'!$P$6:$P$405,MATCH(71,'計算'!$CT$6:$CT$405,0)),""),IFERROR(INDEX('計算'!$S$6:$S$405,MATCH(71-MAX('計算'!$CT$6:$CT$405),'計算'!$CU$6:$CU$405,0)),""))) | G81: =IF($B81="","",IF(71<=MAX('計算'!$CT$6:$CT$405),IFERROR(INDEX('計算'!$CR$6:$CR$405,MATCH(71,'計算'!$CT$6:$CT$405,0)),""),IFERROR(INDEX('計算'!$CR$6:$CR$405,MATCH(71-MAX('計算'!$CT$6:$CT$405),'計算'!$CU$6:$CU$405,0)),""))) | H81: =IF($B81="","",IF(71<=MAX('計算'!$CT$6:$CT$405),IFERROR(INDEX('計算'!$Q$6:$Q$405,MATCH(71,'計算'!$CT$6:$CT$405,0)),""),IFERROR(INDEX('計算'!$T$6:$T$405,MATCH(71-MAX('計算'!$CT$6:$CT$405),'計算'!$CU$6:$CU$405,0)),""))) | I81: =IF($B81="","",IF(71<=MAX('計算'!$CT$6:$CT$405),IFERROR(INDEX('計算'!$H$6:$H$405,MATCH(71,'計算'!$CT$6:$CT$405,0)),""),IFERROR(INDEX('計算'!$H$6:$H$405,MATCH(71-MAX('計算'!$CT$6:$CT$405),'計算'!$CU$6:$CU$405,0)),""))) | J81: =IF($B81="","",N($H81)*IFERROR(INDEX('計算'!$G$6:$G$405,IF(71<=MAX('計算'!$CT$6:$CT$405),MATCH(71,'計算'!$CT$6:$CT$405,0),MATCH(71-MAX('計算'!$CT$6:$CT$405),'計算'!$CU$6:$CU$405,0))),1)*N($I81))
B82: =IF(72<=MAX('計算'!$CT$6:$CT$405)+MAX('計算'!$CU$6:$CU$405),72,"") | C82: =IF($B82="","",IF(72<=MAX('計算'!$CT$6:$CT$405),IFERROR(INDEX('計算'!$F$6:$F$405,MATCH(72,'計算'!$CT$6:$CT$405,0)),""),IFERROR(INDEX('計算'!$F$6:$F$405,MATCH(72-MAX('計算'!$CT$6:$CT$405),'計算'!$CU$6:$CU$405,0)),""))) | D82: =IF($B82="","",IF(72<=MAX('計算'!$CT$6:$CT$405),IFERROR(INDEX('計算'!$C$6:$C$405,MATCH(72,'計算'!$CT$6:$CT$405,0))&"",""),IFERROR(INDEX('計算'!$C$6:$C$405,MATCH(72-MAX('計算'!$CT$6:$CT$405),'計算'!$CU$6:$CU$405,0))&"",""))) | E82: =IF($B82="","",IF(72<=MAX('計算'!$CT$6:$CT$405),IFERROR(INDEX('計算'!$D$6:$D$405,MATCH(72,'計算'!$CT$6:$CT$405,0)),""),IFERROR(INDEX('計算'!$D$6:$D$405,MATCH(72-MAX('計算'!$CT$6:$CT$405),'計算'!$CU$6:$CU$405,0)),""))) | F82: =IF($B82="","",IF(72<=MAX('計算'!$CT$6:$CT$405),IFERROR(INDEX('計算'!$P$6:$P$405,MATCH(72,'計算'!$CT$6:$CT$405,0)),""),IFERROR(INDEX('計算'!$S$6:$S$405,MATCH(72-MAX('計算'!$CT$6:$CT$405),'計算'!$CU$6:$CU$405,0)),""))) | G82: =IF($B82="","",IF(72<=MAX('計算'!$CT$6:$CT$405),IFERROR(INDEX('計算'!$CR$6:$CR$405,MATCH(72,'計算'!$CT$6:$CT$405,0)),""),IFERROR(INDEX('計算'!$CR$6:$CR$405,MATCH(72-MAX('計算'!$CT$6:$CT$405),'計算'!$CU$6:$CU$405,0)),""))) | H82: =IF($B82="","",IF(72<=MAX('計算'!$CT$6:$CT$405),IFERROR(INDEX('計算'!$Q$6:$Q$405,MATCH(72,'計算'!$CT$6:$CT$405,0)),""),IFERROR(INDEX('計算'!$T$6:$T$405,MATCH(72-MAX('計算'!$CT$6:$CT$405),'計算'!$CU$6:$CU$405,0)),""))) | I82: =IF($B82="","",IF(72<=MAX('計算'!$CT$6:$CT$405),IFERROR(INDEX('計算'!$H$6:$H$405,MATCH(72,'計算'!$CT$6:$CT$405,0)),""),IFERROR(INDEX('計算'!$H$6:$H$405,MATCH(72-MAX('計算'!$CT$6:$CT$405),'計算'!$CU$6:$CU$405,0)),""))) | J82: =IF($B82="","",N($H82)*IFERROR(INDEX('計算'!$G$6:$G$405,IF(72<=MAX('計算'!$CT$6:$CT$405),MATCH(72,'計算'!$CT$6:$CT$405,0),MATCH(72-MAX('計算'!$CT$6:$CT$405),'計算'!$CU$6:$CU$405,0))),1)*N($I82))
B83: =IF(73<=MAX('計算'!$CT$6:$CT$405)+MAX('計算'!$CU$6:$CU$405),73,"") | C83: =IF($B83="","",IF(73<=MAX('計算'!$CT$6:$CT$405),IFERROR(INDEX('計算'!$F$6:$F$405,MATCH(73,'計算'!$CT$6:$CT$405,0)),""),IFERROR(INDEX('計算'!$F$6:$F$405,MATCH(73-MAX('計算'!$CT$6:$CT$405),'計算'!$CU$6:$CU$405,0)),""))) | D83: =IF($B83="","",IF(73<=MAX('計算'!$CT$6:$CT$405),IFERROR(INDEX('計算'!$C$6:$C$405,MATCH(73,'計算'!$CT$6:$CT$405,0))&"",""),IFERROR(INDEX('計算'!$C$6:$C$405,MATCH(73-MAX('計算'!$CT$6:$CT$405),'計算'!$CU$6:$CU$405,0))&"",""))) | E83: =IF($B83="","",IF(73<=MAX('計算'!$CT$6:$CT$405),IFERROR(INDEX('計算'!$D$6:$D$405,MATCH(73,'計算'!$CT$6:$CT$405,0)),""),IFERROR(INDEX('計算'!$D$6:$D$405,MATCH(73-MAX('計算'!$CT$6:$CT$405),'計算'!$CU$6:$CU$405,0)),""))) | F83: =IF($B83="","",IF(73<=MAX('計算'!$CT$6:$CT$405),IFERROR(INDEX('計算'!$P$6:$P$405,MATCH(73,'計算'!$CT$6:$CT$405,0)),""),IFERROR(INDEX('計算'!$S$6:$S$405,MATCH(73-MAX('計算'!$CT$6:$CT$405),'計算'!$CU$6:$CU$405,0)),""))) | G83: =IF($B83="","",IF(73<=MAX('計算'!$CT$6:$CT$405),IFERROR(INDEX('計算'!$CR$6:$CR$405,MATCH(73,'計算'!$CT$6:$CT$405,0)),""),IFERROR(INDEX('計算'!$CR$6:$CR$405,MATCH(73-MAX('計算'!$CT$6:$CT$405),'計算'!$CU$6:$CU$405,0)),""))) | H83: =IF($B83="","",IF(73<=MAX('計算'!$CT$6:$CT$405),IFERROR(INDEX('計算'!$Q$6:$Q$405,MATCH(73,'計算'!$CT$6:$CT$405,0)),""),IFERROR(INDEX('計算'!$T$6:$T$405,MATCH(73-MAX('計算'!$CT$6:$CT$405),'計算'!$CU$6:$CU$405,0)),""))) | I83: =IF($B83="","",IF(73<=MAX('計算'!$CT$6:$CT$405),IFERROR(INDEX('計算'!$H$6:$H$405,MATCH(73,'計算'!$CT$6:$CT$405,0)),""),IFERROR(INDEX('計算'!$H$6:$H$405,MATCH(73-MAX('計算'!$CT$6:$CT$405),'計算'!$CU$6:$CU$405,0)),""))) | J83: =IF($B83="","",N($H83)*IFERROR(INDEX('計算'!$G$6:$G$405,IF(73<=MAX('計算'!$CT$6:$CT$405),MATCH(73,'計算'!$CT$6:$CT$405,0),MATCH(73-MAX('計算'!$CT$6:$CT$405),'計算'!$CU$6:$CU$405,0))),1)*N($I83))
B84: =IF(74<=MAX('計算'!$CT$6:$CT$405)+MAX('計算'!$CU$6:$CU$405),74,"") | C84: =IF($B84="","",IF(74<=MAX('計算'!$CT$6:$CT$405),IFERROR(INDEX('計算'!$F$6:$F$405,MATCH(74,'計算'!$CT$6:$CT$405,0)),""),IFERROR(INDEX('計算'!$F$6:$F$405,MATCH(74-MAX('計算'!$CT$6:$CT$405),'計算'!$CU$6:$CU$405,0)),""))) | D84: =IF($B84="","",IF(74<=MAX('計算'!$CT$6:$CT$405),IFERROR(INDEX('計算'!$C$6:$C$405,MATCH(74,'計算'!$CT$6:$CT$405,0))&"",""),IFERROR(INDEX('計算'!$C$6:$C$405,MATCH(74-MAX('計算'!$CT$6:$CT$405),'計算'!$CU$6:$CU$405,0))&"",""))) | E84: =IF($B84="","",IF(74<=MAX('計算'!$CT$6:$CT$405),IFERROR(INDEX('計算'!$D$6:$D$405,MATCH(74,'計算'!$CT$6:$CT$405,0)),""),IFERROR(INDEX('計算'!$D$6:$D$405,MATCH(74-MAX('計算'!$CT$6:$CT$405),'計算'!$CU$6:$CU$405,0)),""))) | F84: =IF($B84="","",IF(74<=MAX('計算'!$CT$6:$CT$405),IFERROR(INDEX('計算'!$P$6:$P$405,MATCH(74,'計算'!$CT$6:$CT$405,0)),""),IFERROR(INDEX('計算'!$S$6:$S$405,MATCH(74-MAX('計算'!$CT$6:$CT$405),'計算'!$CU$6:$CU$405,0)),""))) | G84: =IF($B84="","",IF(74<=MAX('計算'!$CT$6:$CT$405),IFERROR(INDEX('計算'!$CR$6:$CR$405,MATCH(74,'計算'!$CT$6:$CT$405,0)),""),IFERROR(INDEX('計算'!$CR$6:$CR$405,MATCH(74-MAX('計算'!$CT$6:$CT$405),'計算'!$CU$6:$CU$405,0)),""))) | H84: =IF($B84="","",IF(74<=MAX('計算'!$CT$6:$CT$405),IFERROR(INDEX('計算'!$Q$6:$Q$405,MATCH(74,'計算'!$CT$6:$CT$405,0)),""),IFERROR(INDEX('計算'!$T$6:$T$405,MATCH(74-MAX('計算'!$CT$6:$CT$405),'計算'!$CU$6:$CU$405,0)),""))) | I84: =IF($B84="","",IF(74<=MAX('計算'!$CT$6:$CT$405),IFERROR(INDEX('計算'!$H$6:$H$405,MATCH(74,'計算'!$CT$6:$CT$405,0)),""),IFERROR(INDEX('計算'!$H$6:$H$405,MATCH(74-MAX('計算'!$CT$6:$CT$405),'計算'!$CU$6:$CU$405,0)),""))) | J84: =IF($B84="","",N($H84)*IFERROR(INDEX('計算'!$G$6:$G$405,IF(74<=MAX('計算'!$CT$6:$CT$405),MATCH(74,'計算'!$CT$6:$CT$405,0),MATCH(74-MAX('計算'!$CT$6:$CT$405),'計算'!$CU$6:$CU$405,0))),1)*N($I84))
B85: =IF(75<=MAX('計算'!$CT$6:$CT$405)+MAX('計算'!$CU$6:$CU$405),75,"") | C85: =IF($B85="","",IF(75<=MAX('計算'!$CT$6:$CT$405),IFERROR(INDEX('計算'!$F$6:$F$405,MATCH(75,'計算'!$CT$6:$CT$405,0)),""),IFERROR(INDEX('計算'!$F$6:$F$405,MATCH(75-MAX('計算'!$CT$6:$CT$405),'計算'!$CU$6:$CU$405,0)),""))) | D85: =IF($B85="","",IF(75<=MAX('計算'!$CT$6:$CT$405),IFERROR(INDEX('計算'!$C$6:$C$405,MATCH(75,'計算'!$CT$6:$CT$405,0))&"",""),IFERROR(INDEX('計算'!$C$6:$C$405,MATCH(75-MAX('計算'!$CT$6:$CT$405),'計算'!$CU$6:$CU$405,0))&"",""))) | E85: =IF($B85="","",IF(75<=MAX('計算'!$CT$6:$CT$405),IFERROR(INDEX('計算'!$D$6:$D$405,MATCH(75,'計算'!$CT$6:$CT$405,0)),""),IFERROR(INDEX('計算'!$D$6:$D$405,MATCH(75-MAX('計算'!$CT$6:$CT$405),'計算'!$CU$6:$CU$405,0)),""))) | F85: =IF($B85="","",IF(75<=MAX('計算'!$CT$6:$CT$405),IFERROR(INDEX('計算'!$P$6:$P$405,MATCH(75,'計算'!$CT$6:$CT$405,0)),""),IFERROR(INDEX('計算'!$S$6:$S$405,MATCH(75-MAX('計算'!$CT$6:$CT$405),'計算'!$CU$6:$CU$405,0)),""))) | G85: =IF($B85="","",IF(75<=MAX('計算'!$CT$6:$CT$405),IFERROR(INDEX('計算'!$CR$6:$CR$405,MATCH(75,'計算'!$CT$6:$CT$405,0)),""),IFERROR(INDEX('計算'!$CR$6:$CR$405,MATCH(75-MAX('計算'!$CT$6:$CT$405),'計算'!$CU$6:$CU$405,0)),""))) | H85: =IF($B85="","",IF(75<=MAX('計算'!$CT$6:$CT$405),IFERROR(INDEX('計算'!$Q$6:$Q$405,MATCH(75,'計算'!$CT$6:$CT$405,0)),""),IFERROR(INDEX('計算'!$T$6:$T$405,MATCH(75-MAX('計算'!$CT$6:$CT$405),'計算'!$CU$6:$CU$405,0)),""))) | I85: =IF($B85="","",IF(75<=MAX('計算'!$CT$6:$CT$405),IFERROR(INDEX('計算'!$H$6:$H$405,MATCH(75,'計算'!$CT$6:$CT$405,0)),""),IFERROR(INDEX('計算'!$H$6:$H$405,MATCH(75-MAX('計算'!$CT$6:$CT$405),'計算'!$CU$6:$CU$405,0)),""))) | J85: =IF($B85="","",N($H85)*IFERROR(INDEX('計算'!$G$6:$G$405,IF(75<=MAX('計算'!$CT$6:$CT$405),MATCH(75,'計算'!$CT$6:$CT$405,0),MATCH(75-MAX('計算'!$CT$6:$CT$405),'計算'!$CU$6:$CU$405,0))),1)*N($I85))
B86: =IF(76<=MAX('計算'!$CT$6:$CT$405)+MAX('計算'!$CU$6:$CU$405),76,"") | C86: =IF($B86="","",IF(76<=MAX('計算'!$CT$6:$CT$405),IFERROR(INDEX('計算'!$F$6:$F$405,MATCH(76,'計算'!$CT$6:$CT$405,0)),""),IFERROR(INDEX('計算'!$F$6:$F$405,MATCH(76-MAX('計算'!$CT$6:$CT$405),'計算'!$CU$6:$CU$405,0)),""))) | D86: =IF($B86="","",IF(76<=MAX('計算'!$CT$6:$CT$405),IFERROR(INDEX('計算'!$C$6:$C$405,MATCH(76,'計算'!$CT$6:$CT$405,0))&"",""),IFERROR(INDEX('計算'!$C$6:$C$405,MATCH(76-MAX('計算'!$CT$6:$CT$405),'計算'!$CU$6:$CU$405,0))&"",""))) | E86: =IF($B86="","",IF(76<=MAX('計算'!$CT$6:$CT$405),IFERROR(INDEX('計算'!$D$6:$D$405,MATCH(76,'計算'!$CT$6:$CT$405,0)),""),IFERROR(INDEX('計算'!$D$6:$D$405,MATCH(76-MAX('計算'!$CT$6:$CT$405),'計算'!$CU$6:$CU$405,0)),""))) | F86: =IF($B86="","",IF(76<=MAX('計算'!$CT$6:$CT$405),IFERROR(INDEX('計算'!$P$6:$P$405,MATCH(76,'計算'!$CT$6:$CT$405,0)),""),IFERROR(INDEX('計算'!$S$6:$S$405,MATCH(76-MAX('計算'!$CT$6:$CT$405),'計算'!$CU$6:$CU$405,0)),""))) | G86: =IF($B86="","",IF(76<=MAX('計算'!$CT$6:$CT$405),IFERROR(INDEX('計算'!$CR$6:$CR$405,MATCH(76,'計算'!$CT$6:$CT$405,0)),""),IFERROR(INDEX('計算'!$CR$6:$CR$405,MATCH(76-MAX('計算'!$CT$6:$CT$405),'計算'!$CU$6:$CU$405,0)),""))) | H86: =IF($B86="","",IF(76<=MAX('計算'!$CT$6:$CT$405),IFERROR(INDEX('計算'!$Q$6:$Q$405,MATCH(76,'計算'!$CT$6:$CT$405,0)),""),IFERROR(INDEX('計算'!$T$6:$T$405,MATCH(76-MAX('計算'!$CT$6:$CT$405),'計算'!$CU$6:$CU$405,0)),""))) | I86: =IF($B86="","",IF(76<=MAX('計算'!$CT$6:$CT$405),IFERROR(INDEX('計算'!$H$6:$H$405,MATCH(76,'計算'!$CT$6:$CT$405,0)),""),IFERROR(INDEX('計算'!$H$6:$H$405,MATCH(76-MAX('計算'!$CT$6:$CT$405),'計算'!$CU$6:$CU$405,0)),""))) | J86: =IF($B86="","",N($H86)*IFERROR(INDEX('計算'!$G$6:$G$405,IF(76<=MAX('計算'!$CT$6:$CT$405),MATCH(76,'計算'!$CT$6:$CT$405,0),MATCH(76-MAX('計算'!$CT$6:$CT$405),'計算'!$CU$6:$CU$405,0))),1)*N($I86))
B87: =IF(77<=MAX('計算'!$CT$6:$CT$405)+MAX('計算'!$CU$6:$CU$405),77,"") | C87: =IF($B87="","",IF(77<=MAX('計算'!$CT$6:$CT$405),IFERROR(INDEX('計算'!$F$6:$F$405,MATCH(77,'計算'!$CT$6:$CT$405,0)),""),IFERROR(INDEX('計算'!$F$6:$F$405,MATCH(77-MAX('計算'!$CT$6:$CT$405),'計算'!$CU$6:$CU$405,0)),""))) | D87: =IF($B87="","",IF(77<=MAX('計算'!$CT$6:$CT$405),IFERROR(INDEX('計算'!$C$6:$C$405,MATCH(77,'計算'!$CT$6:$CT$405,0))&"",""),IFERROR(INDEX('計算'!$C$6:$C$405,MATCH(77-MAX('計算'!$CT$6:$CT$405),'計算'!$CU$6:$CU$405,0))&"",""))) | E87: =IF($B87="","",IF(77<=MAX('計算'!$CT$6:$CT$405),IFERROR(INDEX('計算'!$D$6:$D$405,MATCH(77,'計算'!$CT$6:$CT$405,0)),""),IFERROR(INDEX('計算'!$D$6:$D$405,MATCH(77-MAX('計算'!$CT$6:$CT$405),'計算'!$CU$6:$CU$405,0)),""))) | F87: =IF($B87="","",IF(77<=MAX('計算'!$CT$6:$CT$405),IFERROR(INDEX('計算'!$P$6:$P$405,MATCH(77,'計算'!$CT$6:$CT$405,0)),""),IFERROR(INDEX('計算'!$S$6:$S$405,MATCH(77-MAX('計算'!$CT$6:$CT$405),'計算'!$CU$6:$CU$405,0)),""))) | G87: =IF($B87="","",IF(77<=MAX('計算'!$CT$6:$CT$405),IFERROR(INDEX('計算'!$CR$6:$CR$405,MATCH(77,'計算'!$CT$6:$CT$405,0)),""),IFERROR(INDEX('計算'!$CR$6:$CR$405,MATCH(77-MAX('計算'!$CT$6:$CT$405),'計算'!$CU$6:$CU$405,0)),""))) | H87: =IF($B87="","",IF(77<=MAX('計算'!$CT$6:$CT$405),IFERROR(INDEX('計算'!$Q$6:$Q$405,MATCH(77,'計算'!$CT$6:$CT$405,0)),""),IFERROR(INDEX('計算'!$T$6:$T$405,MATCH(77-MAX('計算'!$CT$6:$CT$405),'計算'!$CU$6:$CU$405,0)),""))) | I87: =IF($B87="","",IF(77<=MAX('計算'!$CT$6:$CT$405),IFERROR(INDEX('計算'!$H$6:$H$405,MATCH(77,'計算'!$CT$6:$CT$405,0)),""),IFERROR(INDEX('計算'!$H$6:$H$405,MATCH(77-MAX('計算'!$CT$6:$CT$405),'計算'!$CU$6:$CU$405,0)),""))) | J87: =IF($B87="","",N($H87)*IFERROR(INDEX('計算'!$G$6:$G$405,IF(77<=MAX('計算'!$CT$6:$CT$405),MATCH(77,'計算'!$CT$6:$CT$405,0),MATCH(77-MAX('計算'!$CT$6:$CT$405),'計算'!$CU$6:$CU$405,0))),1)*N($I87))
B88: =IF(78<=MAX('計算'!$CT$6:$CT$405)+MAX('計算'!$CU$6:$CU$405),78,"") | C88: =IF($B88="","",IF(78<=MAX('計算'!$CT$6:$CT$405),IFERROR(INDEX('計算'!$F$6:$F$405,MATCH(78,'計算'!$CT$6:$CT$405,0)),""),IFERROR(INDEX('計算'!$F$6:$F$405,MATCH(78-MAX('計算'!$CT$6:$CT$405),'計算'!$CU$6:$CU$405,0)),""))) | D88: =IF($B88="","",IF(78<=MAX('計算'!$CT$6:$CT$405),IFERROR(INDEX('計算'!$C$6:$C$405,MATCH(78,'計算'!$CT$6:$CT$405,0))&"",""),IFERROR(INDEX('計算'!$C$6:$C$405,MATCH(78-MAX('計算'!$CT$6:$CT$405),'計算'!$CU$6:$CU$405,0))&"",""))) | E88: =IF($B88="","",IF(78<=MAX('計算'!$CT$6:$CT$405),IFERROR(INDEX('計算'!$D$6:$D$405,MATCH(78,'計算'!$CT$6:$CT$405,0)),""),IFERROR(INDEX('計算'!$D$6:$D$405,MATCH(78-MAX('計算'!$CT$6:$CT$405),'計算'!$CU$6:$CU$405,0)),""))) | F88: =IF($B88="","",IF(78<=MAX('計算'!$CT$6:$CT$405),IFERROR(INDEX('計算'!$P$6:$P$405,MATCH(78,'計算'!$CT$6:$CT$405,0)),""),IFERROR(INDEX('計算'!$S$6:$S$405,MATCH(78-MAX('計算'!$CT$6:$CT$405),'計算'!$CU$6:$CU$405,0)),""))) | G88: =IF($B88="","",IF(78<=MAX('計算'!$CT$6:$CT$405),IFERROR(INDEX('計算'!$CR$6:$CR$405,MATCH(78,'計算'!$CT$6:$CT$405,0)),""),IFERROR(INDEX('計算'!$CR$6:$CR$405,MATCH(78-MAX('計算'!$CT$6:$CT$405),'計算'!$CU$6:$CU$405,0)),""))) | H88: =IF($B88="","",IF(78<=MAX('計算'!$CT$6:$CT$405),IFERROR(INDEX('計算'!$Q$6:$Q$405,MATCH(78,'計算'!$CT$6:$CT$405,0)),""),IFERROR(INDEX('計算'!$T$6:$T$405,MATCH(78-MAX('計算'!$CT$6:$CT$405),'計算'!$CU$6:$CU$405,0)),""))) | I88: =IF($B88="","",IF(78<=MAX('計算'!$CT$6:$CT$405),IFERROR(INDEX('計算'!$H$6:$H$405,MATCH(78,'計算'!$CT$6:$CT$405,0)),""),IFERROR(INDEX('計算'!$H$6:$H$405,MATCH(78-MAX('計算'!$CT$6:$CT$405),'計算'!$CU$6:$CU$405,0)),""))) | J88: =IF($B88="","",N($H88)*IFERROR(INDEX('計算'!$G$6:$G$405,IF(78<=MAX('計算'!$CT$6:$CT$405),MATCH(78,'計算'!$CT$6:$CT$405,0),MATCH(78-MAX('計算'!$CT$6:$CT$405),'計算'!$CU$6:$CU$405,0))),1)*N($I88))
B89: =IF(79<=MAX('計算'!$CT$6:$CT$405)+MAX('計算'!$CU$6:$CU$405),79,"") | C89: =IF($B89="","",IF(79<=MAX('計算'!$CT$6:$CT$405),IFERROR(INDEX('計算'!$F$6:$F$405,MATCH(79,'計算'!$CT$6:$CT$405,0)),""),IFERROR(INDEX('計算'!$F$6:$F$405,MATCH(79-MAX('計算'!$CT$6:$CT$405),'計算'!$CU$6:$CU$405,0)),""))) | D89: =IF($B89="","",IF(79<=MAX('計算'!$CT$6:$CT$405),IFERROR(INDEX('計算'!$C$6:$C$405,MATCH(79,'計算'!$CT$6:$CT$405,0))&"",""),IFERROR(INDEX('計算'!$C$6:$C$405,MATCH(79-MAX('計算'!$CT$6:$CT$405),'計算'!$CU$6:$CU$405,0))&"",""))) | E89: =IF($B89="","",IF(79<=MAX('計算'!$CT$6:$CT$405),IFERROR(INDEX('計算'!$D$6:$D$405,MATCH(79,'計算'!$CT$6:$CT$405,0)),""),IFERROR(INDEX('計算'!$D$6:$D$405,MATCH(79-MAX('計算'!$CT$6:$CT$405),'計算'!$CU$6:$CU$405,0)),""))) | F89: =IF($B89="","",IF(79<=MAX('計算'!$CT$6:$CT$405),IFERROR(INDEX('計算'!$P$6:$P$405,MATCH(79,'計算'!$CT$6:$CT$405,0)),""),IFERROR(INDEX('計算'!$S$6:$S$405,MATCH(79-MAX('計算'!$CT$6:$CT$405),'計算'!$CU$6:$CU$405,0)),""))) | G89: =IF($B89="","",IF(79<=MAX('計算'!$CT$6:$CT$405),IFERROR(INDEX('計算'!$CR$6:$CR$405,MATCH(79,'計算'!$CT$6:$CT$405,0)),""),IFERROR(INDEX('計算'!$CR$6:$CR$405,MATCH(79-MAX('計算'!$CT$6:$CT$405),'計算'!$CU$6:$CU$405,0)),""))) | H89: =IF($B89="","",IF(79<=MAX('計算'!$CT$6:$CT$405),IFERROR(INDEX('計算'!$Q$6:$Q$405,MATCH(79,'計算'!$CT$6:$CT$405,0)),""),IFERROR(INDEX('計算'!$T$6:$T$405,MATCH(79-MAX('計算'!$CT$6:$CT$405),'計算'!$CU$6:$CU$405,0)),""))) | I89: =IF($B89="","",IF(79<=MAX('計算'!$CT$6:$CT$405),IFERROR(INDEX('計算'!$H$6:$H$405,MATCH(79,'計算'!$CT$6:$CT$405,0)),""),IFERROR(INDEX('計算'!$H$6:$H$405,MATCH(79-MAX('計算'!$CT$6:$CT$405),'計算'!$CU$6:$CU$405,0)),""))) | J89: =IF($B89="","",N($H89)*IFERROR(INDEX('計算'!$G$6:$G$405,IF(79<=MAX('計算'!$CT$6:$CT$405),MATCH(79,'計算'!$CT$6:$CT$405,0),MATCH(79-MAX('計算'!$CT$6:$CT$405),'計算'!$CU$6:$CU$405,0))),1)*N($I89))
B90: =IF(80<=MAX('計算'!$CT$6:$CT$405)+MAX('計算'!$CU$6:$CU$405),80,"") | C90: =IF($B90="","",IF(80<=MAX('計算'!$CT$6:$CT$405),IFERROR(INDEX('計算'!$F$6:$F$405,MATCH(80,'計算'!$CT$6:$CT$405,0)),""),IFERROR(INDEX('計算'!$F$6:$F$405,MATCH(80-MAX('計算'!$CT$6:$CT$405),'計算'!$CU$6:$CU$405,0)),""))) | D90: =IF($B90="","",IF(80<=MAX('計算'!$CT$6:$CT$405),IFERROR(INDEX('計算'!$C$6:$C$405,MATCH(80,'計算'!$CT$6:$CT$405,0))&"",""),IFERROR(INDEX('計算'!$C$6:$C$405,MATCH(80-MAX('計算'!$CT$6:$CT$405),'計算'!$CU$6:$CU$405,0))&"",""))) | E90: =IF($B90="","",IF(80<=MAX('計算'!$CT$6:$CT$405),IFERROR(INDEX('計算'!$D$6:$D$405,MATCH(80,'計算'!$CT$6:$CT$405,0)),""),IFERROR(INDEX('計算'!$D$6:$D$405,MATCH(80-MAX('計算'!$CT$6:$CT$405),'計算'!$CU$6:$CU$405,0)),""))) | F90: =IF($B90="","",IF(80<=MAX('計算'!$CT$6:$CT$405),IFERROR(INDEX('計算'!$P$6:$P$405,MATCH(80,'計算'!$CT$6:$CT$405,0)),""),IFERROR(INDEX('計算'!$S$6:$S$405,MATCH(80-MAX('計算'!$CT$6:$CT$405),'計算'!$CU$6:$CU$405,0)),""))) | G90: =IF($B90="","",IF(80<=MAX('計算'!$CT$6:$CT$405),IFERROR(INDEX('計算'!$CR$6:$CR$405,MATCH(80,'計算'!$CT$6:$CT$405,0)),""),IFERROR(INDEX('計算'!$CR$6:$CR$405,MATCH(80-MAX('計算'!$CT$6:$CT$405),'計算'!$CU$6:$CU$405,0)),""))) | H90: =IF($B90="","",IF(80<=MAX('計算'!$CT$6:$CT$405),IFERROR(INDEX('計算'!$Q$6:$Q$405,MATCH(80,'計算'!$CT$6:$CT$405,0)),""),IFERROR(INDEX('計算'!$T$6:$T$405,MATCH(80-MAX('計算'!$CT$6:$CT$405),'計算'!$CU$6:$CU$405,0)),""))) | I90: =IF($B90="","",IF(80<=MAX('計算'!$CT$6:$CT$405),IFERROR(INDEX('計算'!$H$6:$H$405,MATCH(80,'計算'!$CT$6:$CT$405,0)),""),IFERROR(INDEX('計算'!$H$6:$H$405,MATCH(80-MAX('計算'!$CT$6:$CT$405),'計算'!$CU$6:$CU$405,0)),""))) | J90: =IF($B90="","",N($H90)*IFERROR(INDEX('計算'!$G$6:$G$405,IF(80<=MAX('計算'!$CT$6:$CT$405),MATCH(80,'計算'!$CT$6:$CT$405,0),MATCH(80-MAX('計算'!$CT$6:$CT$405),'計算'!$CU$6:$CU$405,0))),1)*N($I90))
B91: =IF(81<=MAX('計算'!$CT$6:$CT$405)+MAX('計算'!$CU$6:$CU$405),81,"") | C91: =IF($B91="","",IF(81<=MAX('計算'!$CT$6:$CT$405),IFERROR(INDEX('計算'!$F$6:$F$405,MATCH(81,'計算'!$CT$6:$CT$405,0)),""),IFERROR(INDEX('計算'!$F$6:$F$405,MATCH(81-MAX('計算'!$CT$6:$CT$405),'計算'!$CU$6:$CU$405,0)),""))) | D91: =IF($B91="","",IF(81<=MAX('計算'!$CT$6:$CT$405),IFERROR(INDEX('計算'!$C$6:$C$405,MATCH(81,'計算'!$CT$6:$CT$405,0))&"",""),IFERROR(INDEX('計算'!$C$6:$C$405,MATCH(81-MAX('計算'!$CT$6:$CT$405),'計算'!$CU$6:$CU$405,0))&"",""))) | E91: =IF($B91="","",IF(81<=MAX('計算'!$CT$6:$CT$405),IFERROR(INDEX('計算'!$D$6:$D$405,MATCH(81,'計算'!$CT$6:$CT$405,0)),""),IFERROR(INDEX('計算'!$D$6:$D$405,MATCH(81-MAX('計算'!$CT$6:$CT$405),'計算'!$CU$6:$CU$405,0)),""))) | F91: =IF($B91="","",IF(81<=MAX('計算'!$CT$6:$CT$405),IFERROR(INDEX('計算'!$P$6:$P$405,MATCH(81,'計算'!$CT$6:$CT$405,0)),""),IFERROR(INDEX('計算'!$S$6:$S$405,MATCH(81-MAX('計算'!$CT$6:$CT$405),'計算'!$CU$6:$CU$405,0)),""))) | G91: =IF($B91="","",IF(81<=MAX('計算'!$CT$6:$CT$405),IFERROR(INDEX('計算'!$CR$6:$CR$405,MATCH(81,'計算'!$CT$6:$CT$405,0)),""),IFERROR(INDEX('計算'!$CR$6:$CR$405,MATCH(81-MAX('計算'!$CT$6:$CT$405),'計算'!$CU$6:$CU$405,0)),""))) | H91: =IF($B91="","",IF(81<=MAX('計算'!$CT$6:$CT$405),IFERROR(INDEX('計算'!$Q$6:$Q$405,MATCH(81,'計算'!$CT$6:$CT$405,0)),""),IFERROR(INDEX('計算'!$T$6:$T$405,MATCH(81-MAX('計算'!$CT$6:$CT$405),'計算'!$CU$6:$CU$405,0)),""))) | I91: =IF($B91="","",IF(81<=MAX('計算'!$CT$6:$CT$405),IFERROR(INDEX('計算'!$H$6:$H$405,MATCH(81,'計算'!$CT$6:$CT$405,0)),""),IFERROR(INDEX('計算'!$H$6:$H$405,MATCH(81-MAX('計算'!$CT$6:$CT$405),'計算'!$CU$6:$CU$405,0)),""))) | J91: =IF($B91="","",N($H91)*IFERROR(INDEX('計算'!$G$6:$G$405,IF(81<=MAX('計算'!$CT$6:$CT$405),MATCH(81,'計算'!$CT$6:$CT$405,0),MATCH(81-MAX('計算'!$CT$6:$CT$405),'計算'!$CU$6:$CU$405,0))),1)*N($I91))
B92: =IF(82<=MAX('計算'!$CT$6:$CT$405)+MAX('計算'!$CU$6:$CU$405),82,"") | C92: =IF($B92="","",IF(82<=MAX('計算'!$CT$6:$CT$405),IFERROR(INDEX('計算'!$F$6:$F$405,MATCH(82,'計算'!$CT$6:$CT$405,0)),""),IFERROR(INDEX('計算'!$F$6:$F$405,MATCH(82-MAX('計算'!$CT$6:$CT$405),'計算'!$CU$6:$CU$405,0)),""))) | D92: =IF($B92="","",IF(82<=MAX('計算'!$CT$6:$CT$405),IFERROR(INDEX('計算'!$C$6:$C$405,MATCH(82,'計算'!$CT$6:$CT$405,0))&"",""),IFERROR(INDEX('計算'!$C$6:$C$405,MATCH(82-MAX('計算'!$CT$6:$CT$405),'計算'!$CU$6:$CU$405,0))&"",""))) | E92: =IF($B92="","",IF(82<=MAX('計算'!$CT$6:$CT$405),IFERROR(INDEX('計算'!$D$6:$D$405,MATCH(82,'計算'!$CT$6:$CT$405,0)),""),IFERROR(INDEX('計算'!$D$6:$D$405,MATCH(82-MAX('計算'!$CT$6:$CT$405),'計算'!$CU$6:$CU$405,0)),""))) | F92: =IF($B92="","",IF(82<=MAX('計算'!$CT$6:$CT$405),IFERROR(INDEX('計算'!$P$6:$P$405,MATCH(82,'計算'!$CT$6:$CT$405,0)),""),IFERROR(INDEX('計算'!$S$6:$S$405,MATCH(82-MAX('計算'!$CT$6:$CT$405),'計算'!$CU$6:$CU$405,0)),""))) | G92: =IF($B92="","",IF(82<=MAX('計算'!$CT$6:$CT$405),IFERROR(INDEX('計算'!$CR$6:$CR$405,MATCH(82,'計算'!$CT$6:$CT$405,0)),""),IFERROR(INDEX('計算'!$CR$6:$CR$405,MATCH(82-MAX('計算'!$CT$6:$CT$405),'計算'!$CU$6:$CU$405,0)),""))) | H92: =IF($B92="","",IF(82<=MAX('計算'!$CT$6:$CT$405),IFERROR(INDEX('計算'!$Q$6:$Q$405,MATCH(82,'計算'!$CT$6:$CT$405,0)),""),IFERROR(INDEX('計算'!$T$6:$T$405,MATCH(82-MAX('計算'!$CT$6:$CT$405),'計算'!$CU$6:$CU$405,0)),""))) | I92: =IF($B92="","",IF(82<=MAX('計算'!$CT$6:$CT$405),IFERROR(INDEX('計算'!$H$6:$H$405,MATCH(82,'計算'!$CT$6:$CT$405,0)),""),IFERROR(INDEX('計算'!$H$6:$H$405,MATCH(82-MAX('計算'!$CT$6:$CT$405),'計算'!$CU$6:$CU$405,0)),""))) | J92: =IF($B92="","",N($H92)*IFERROR(INDEX('計算'!$G$6:$G$405,IF(82<=MAX('計算'!$CT$6:$CT$405),MATCH(82,'計算'!$CT$6:$CT$405,0),MATCH(82-MAX('計算'!$CT$6:$CT$405),'計算'!$CU$6:$CU$405,0))),1)*N($I92))
B93: =IF(83<=MAX('計算'!$CT$6:$CT$405)+MAX('計算'!$CU$6:$CU$405),83,"") | C93: =IF($B93="","",IF(83<=MAX('計算'!$CT$6:$CT$405),IFERROR(INDEX('計算'!$F$6:$F$405,MATCH(83,'計算'!$CT$6:$CT$405,0)),""),IFERROR(INDEX('計算'!$F$6:$F$405,MATCH(83-MAX('計算'!$CT$6:$CT$405),'計算'!$CU$6:$CU$405,0)),""))) | D93: =IF($B93="","",IF(83<=MAX('計算'!$CT$6:$CT$405),IFERROR(INDEX('計算'!$C$6:$C$405,MATCH(83,'計算'!$CT$6:$CT$405,0))&"",""),IFERROR(INDEX('計算'!$C$6:$C$405,MATCH(83-MAX('計算'!$CT$6:$CT$405),'計算'!$CU$6:$CU$405,0))&"",""))) | E93: =IF($B93="","",IF(83<=MAX('計算'!$CT$6:$CT$405),IFERROR(INDEX('計算'!$D$6:$D$405,MATCH(83,'計算'!$CT$6:$CT$405,0)),""),IFERROR(INDEX('計算'!$D$6:$D$405,MATCH(83-MAX('計算'!$CT$6:$CT$405),'計算'!$CU$6:$CU$405,0)),""))) | F93: =IF($B93="","",IF(83<=MAX('計算'!$CT$6:$CT$405),IFERROR(INDEX('計算'!$P$6:$P$405,MATCH(83,'計算'!$CT$6:$CT$405,0)),""),IFERROR(INDEX('計算'!$S$6:$S$405,MATCH(83-MAX('計算'!$CT$6:$CT$405),'計算'!$CU$6:$CU$405,0)),""))) | G93: =IF($B93="","",IF(83<=MAX('計算'!$CT$6:$CT$405),IFERROR(INDEX('計算'!$CR$6:$CR$405,MATCH(83,'計算'!$CT$6:$CT$405,0)),""),IFERROR(INDEX('計算'!$CR$6:$CR$405,MATCH(83-MAX('計算'!$CT$6:$CT$405),'計算'!$CU$6:$CU$405,0)),""))) | H93: =IF($B93="","",IF(83<=MAX('計算'!$CT$6:$CT$405),IFERROR(INDEX('計算'!$Q$6:$Q$405,MATCH(83,'計算'!$CT$6:$CT$405,0)),""),IFERROR(INDEX('計算'!$T$6:$T$405,MATCH(83-MAX('計算'!$CT$6:$CT$405),'計算'!$CU$6:$CU$405,0)),""))) | I93: =IF($B93="","",IF(83<=MAX('計算'!$CT$6:$CT$405),IFERROR(INDEX('計算'!$H$6:$H$405,MATCH(83,'計算'!$CT$6:$CT$405,0)),""),IFERROR(INDEX('計算'!$H$6:$H$405,MATCH(83-MAX('計算'!$CT$6:$CT$405),'計算'!$CU$6:$CU$405,0)),""))) | J93: =IF($B93="","",N($H93)*IFERROR(INDEX('計算'!$G$6:$G$405,IF(83<=MAX('計算'!$CT$6:$CT$405),MATCH(83,'計算'!$CT$6:$CT$405,0),MATCH(83-MAX('計算'!$CT$6:$CT$405),'計算'!$CU$6:$CU$405,0))),1)*N($I93))
B94: =IF(84<=MAX('計算'!$CT$6:$CT$405)+MAX('計算'!$CU$6:$CU$405),84,"") | C94: =IF($B94="","",IF(84<=MAX('計算'!$CT$6:$CT$405),IFERROR(INDEX('計算'!$F$6:$F$405,MATCH(84,'計算'!$CT$6:$CT$405,0)),""),IFERROR(INDEX('計算'!$F$6:$F$405,MATCH(84-MAX('計算'!$CT$6:$CT$405),'計算'!$CU$6:$CU$405,0)),""))) | D94: =IF($B94="","",IF(84<=MAX('計算'!$CT$6:$CT$405),IFERROR(INDEX('計算'!$C$6:$C$405,MATCH(84,'計算'!$CT$6:$CT$405,0))&"",""),IFERROR(INDEX('計算'!$C$6:$C$405,MATCH(84-MAX('計算'!$CT$6:$CT$405),'計算'!$CU$6:$CU$405,0))&"",""))) | E94: =IF($B94="","",IF(84<=MAX('計算'!$CT$6:$CT$405),IFERROR(INDEX('計算'!$D$6:$D$405,MATCH(84,'計算'!$CT$6:$CT$405,0)),""),IFERROR(INDEX('計算'!$D$6:$D$405,MATCH(84-MAX('計算'!$CT$6:$CT$405),'計算'!$CU$6:$CU$405,0)),""))) | F94: =IF($B94="","",IF(84<=MAX('計算'!$CT$6:$CT$405),IFERROR(INDEX('計算'!$P$6:$P$405,MATCH(84,'計算'!$CT$6:$CT$405,0)),""),IFERROR(INDEX('計算'!$S$6:$S$405,MATCH(84-MAX('計算'!$CT$6:$CT$405),'計算'!$CU$6:$CU$405,0)),""))) | G94: =IF($B94="","",IF(84<=MAX('計算'!$CT$6:$CT$405),IFERROR(INDEX('計算'!$CR$6:$CR$405,MATCH(84,'計算'!$CT$6:$CT$405,0)),""),IFERROR(INDEX('計算'!$CR$6:$CR$405,MATCH(84-MAX('計算'!$CT$6:$CT$405),'計算'!$CU$6:$CU$405,0)),""))) | H94: =IF($B94="","",IF(84<=MAX('計算'!$CT$6:$CT$405),IFERROR(INDEX('計算'!$Q$6:$Q$405,MATCH(84,'計算'!$CT$6:$CT$405,0)),""),IFERROR(INDEX('計算'!$T$6:$T$405,MATCH(84-MAX('計算'!$CT$6:$CT$405),'計算'!$CU$6:$CU$405,0)),""))) | I94: =IF($B94="","",IF(84<=MAX('計算'!$CT$6:$CT$405),IFERROR(INDEX('計算'!$H$6:$H$405,MATCH(84,'計算'!$CT$6:$CT$405,0)),""),IFERROR(INDEX('計算'!$H$6:$H$405,MATCH(84-MAX('計算'!$CT$6:$CT$405),'計算'!$CU$6:$CU$405,0)),""))) | J94: =IF($B94="","",N($H94)*IFERROR(INDEX('計算'!$G$6:$G$405,IF(84<=MAX('計算'!$CT$6:$CT$405),MATCH(84,'計算'!$CT$6:$CT$405,0),MATCH(84-MAX('計算'!$CT$6:$CT$405),'計算'!$CU$6:$CU$405,0))),1)*N($I94))
B95: =IF(85<=MAX('計算'!$CT$6:$CT$405)+MAX('計算'!$CU$6:$CU$405),85,"") | C95: =IF($B95="","",IF(85<=MAX('計算'!$CT$6:$CT$405),IFERROR(INDEX('計算'!$F$6:$F$405,MATCH(85,'計算'!$CT$6:$CT$405,0)),""),IFERROR(INDEX('計算'!$F$6:$F$405,MATCH(85-MAX('計算'!$CT$6:$CT$405),'計算'!$CU$6:$CU$405,0)),""))) | D95: =IF($B95="","",IF(85<=MAX('計算'!$CT$6:$CT$405),IFERROR(INDEX('計算'!$C$6:$C$405,MATCH(85,'計算'!$CT$6:$CT$405,0))&"",""),IFERROR(INDEX('計算'!$C$6:$C$405,MATCH(85-MAX('計算'!$CT$6:$CT$405),'計算'!$CU$6:$CU$405,0))&"",""))) | E95: =IF($B95="","",IF(85<=MAX('計算'!$CT$6:$CT$405),IFERROR(INDEX('計算'!$D$6:$D$405,MATCH(85,'計算'!$CT$6:$CT$405,0)),""),IFERROR(INDEX('計算'!$D$6:$D$405,MATCH(85-MAX('計算'!$CT$6:$CT$405),'計算'!$CU$6:$CU$405,0)),""))) | F95: =IF($B95="","",IF(85<=MAX('計算'!$CT$6:$CT$405),IFERROR(INDEX('計算'!$P$6:$P$405,MATCH(85,'計算'!$CT$6:$CT$405,0)),""),IFERROR(INDEX('計算'!$S$6:$S$405,MATCH(85-MAX('計算'!$CT$6:$CT$405),'計算'!$CU$6:$CU$405,0)),""))) | G95: =IF($B95="","",IF(85<=MAX('計算'!$CT$6:$CT$405),IFERROR(INDEX('計算'!$CR$6:$CR$405,MATCH(85,'計算'!$CT$6:$CT$405,0)),""),IFERROR(INDEX('計算'!$CR$6:$CR$405,MATCH(85-MAX('計算'!$CT$6:$CT$405),'計算'!$CU$6:$CU$405,0)),""))) | H95: =IF($B95="","",IF(85<=MAX('計算'!$CT$6:$CT$405),IFERROR(INDEX('計算'!$Q$6:$Q$405,MATCH(85,'計算'!$CT$6:$CT$405,0)),""),IFERROR(INDEX('計算'!$T$6:$T$405,MATCH(85-MAX('計算'!$CT$6:$CT$405),'計算'!$CU$6:$CU$405,0)),""))) | I95: =IF($B95="","",IF(85<=MAX('計算'!$CT$6:$CT$405),IFERROR(INDEX('計算'!$H$6:$H$405,MATCH(85,'計算'!$CT$6:$CT$405,0)),""),IFERROR(INDEX('計算'!$H$6:$H$405,MATCH(85-MAX('計算'!$CT$6:$CT$405),'計算'!$CU$6:$CU$405,0)),""))) | J95: =IF($B95="","",N($H95)*IFERROR(INDEX('計算'!$G$6:$G$405,IF(85<=MAX('計算'!$CT$6:$CT$405),MATCH(85,'計算'!$CT$6:$CT$405,0),MATCH(85-MAX('計算'!$CT$6:$CT$405),'計算'!$CU$6:$CU$405,0))),1)*N($I95))
B96: =IF(86<=MAX('計算'!$CT$6:$CT$405)+MAX('計算'!$CU$6:$CU$405),86,"") | C96: =IF($B96="","",IF(86<=MAX('計算'!$CT$6:$CT$405),IFERROR(INDEX('計算'!$F$6:$F$405,MATCH(86,'計算'!$CT$6:$CT$405,0)),""),IFERROR(INDEX('計算'!$F$6:$F$405,MATCH(86-MAX('計算'!$CT$6:$CT$405),'計算'!$CU$6:$CU$405,0)),""))) | D96: =IF($B96="","",IF(86<=MAX('計算'!$CT$6:$CT$405),IFERROR(INDEX('計算'!$C$6:$C$405,MATCH(86,'計算'!$CT$6:$CT$405,0))&"",""),IFERROR(INDEX('計算'!$C$6:$C$405,MATCH(86-MAX('計算'!$CT$6:$CT$405),'計算'!$CU$6:$CU$405,0))&"",""))) | E96: =IF($B96="","",IF(86<=MAX('計算'!$CT$6:$CT$405),IFERROR(INDEX('計算'!$D$6:$D$405,MATCH(86,'計算'!$CT$6:$CT$405,0)),""),IFERROR(INDEX('計算'!$D$6:$D$405,MATCH(86-MAX('計算'!$CT$6:$CT$405),'計算'!$CU$6:$CU$405,0)),""))) | F96: =IF($B96="","",IF(86<=MAX('計算'!$CT$6:$CT$405),IFERROR(INDEX('計算'!$P$6:$P$405,MATCH(86,'計算'!$CT$6:$CT$405,0)),""),IFERROR(INDEX('計算'!$S$6:$S$405,MATCH(86-MAX('計算'!$CT$6:$CT$405),'計算'!$CU$6:$CU$405,0)),""))) | G96: =IF($B96="","",IF(86<=MAX('計算'!$CT$6:$CT$405),IFERROR(INDEX('計算'!$CR$6:$CR$405,MATCH(86,'計算'!$CT$6:$CT$405,0)),""),IFERROR(INDEX('計算'!$CR$6:$CR$405,MATCH(86-MAX('計算'!$CT$6:$CT$405),'計算'!$CU$6:$CU$405,0)),""))) | H96: =IF($B96="","",IF(86<=MAX('計算'!$CT$6:$CT$405),IFERROR(INDEX('計算'!$Q$6:$Q$405,MATCH(86,'計算'!$CT$6:$CT$405,0)),""),IFERROR(INDEX('計算'!$T$6:$T$405,MATCH(86-MAX('計算'!$CT$6:$CT$405),'計算'!$CU$6:$CU$405,0)),""))) | I96: =IF($B96="","",IF(86<=MAX('計算'!$CT$6:$CT$405),IFERROR(INDEX('計算'!$H$6:$H$405,MATCH(86,'計算'!$CT$6:$CT$405,0)),""),IFERROR(INDEX('計算'!$H$6:$H$405,MATCH(86-MAX('計算'!$CT$6:$CT$405),'計算'!$CU$6:$CU$405,0)),""))) | J96: =IF($B96="","",N($H96)*IFERROR(INDEX('計算'!$G$6:$G$405,IF(86<=MAX('計算'!$CT$6:$CT$405),MATCH(86,'計算'!$CT$6:$CT$405,0),MATCH(86-MAX('計算'!$CT$6:$CT$405),'計算'!$CU$6:$CU$405,0))),1)*N($I96))
B97: =IF(87<=MAX('計算'!$CT$6:$CT$405)+MAX('計算'!$CU$6:$CU$405),87,"") | C97: =IF($B97="","",IF(87<=MAX('計算'!$CT$6:$CT$405),IFERROR(INDEX('計算'!$F$6:$F$405,MATCH(87,'計算'!$CT$6:$CT$405,0)),""),IFERROR(INDEX('計算'!$F$6:$F$405,MATCH(87-MAX('計算'!$CT$6:$CT$405),'計算'!$CU$6:$CU$405,0)),""))) | D97: =IF($B97="","",IF(87<=MAX('計算'!$CT$6:$CT$405),IFERROR(INDEX('計算'!$C$6:$C$405,MATCH(87,'計算'!$CT$6:$CT$405,0))&"",""),IFERROR(INDEX('計算'!$C$6:$C$405,MATCH(87-MAX('計算'!$CT$6:$CT$405),'計算'!$CU$6:$CU$405,0))&"",""))) | E97: =IF($B97="","",IF(87<=MAX('計算'!$CT$6:$CT$405),IFERROR(INDEX('計算'!$D$6:$D$405,MATCH(87,'計算'!$CT$6:$CT$405,0)),""),IFERROR(INDEX('計算'!$D$6:$D$405,MATCH(87-MAX('計算'!$CT$6:$CT$405),'計算'!$CU$6:$CU$405,0)),""))) | F97: =IF($B97="","",IF(87<=MAX('計算'!$CT$6:$CT$405),IFERROR(INDEX('計算'!$P$6:$P$405,MATCH(87,'計算'!$CT$6:$CT$405,0)),""),IFERROR(INDEX('計算'!$S$6:$S$405,MATCH(87-MAX('計算'!$CT$6:$CT$405),'計算'!$CU$6:$CU$405,0)),""))) | G97: =IF($B97="","",IF(87<=MAX('計算'!$CT$6:$CT$405),IFERROR(INDEX('計算'!$CR$6:$CR$405,MATCH(87,'計算'!$CT$6:$CT$405,0)),""),IFERROR(INDEX('計算'!$CR$6:$CR$405,MATCH(87-MAX('計算'!$CT$6:$CT$405),'計算'!$CU$6:$CU$405,0)),""))) | H97: =IF($B97="","",IF(87<=MAX('計算'!$CT$6:$CT$405),IFERROR(INDEX('計算'!$Q$6:$Q$405,MATCH(87,'計算'!$CT$6:$CT$405,0)),""),IFERROR(INDEX('計算'!$T$6:$T$405,MATCH(87-MAX('計算'!$CT$6:$CT$405),'計算'!$CU$6:$CU$405,0)),""))) | I97: =IF($B97="","",IF(87<=MAX('計算'!$CT$6:$CT$405),IFERROR(INDEX('計算'!$H$6:$H$405,MATCH(87,'計算'!$CT$6:$CT$405,0)),""),IFERROR(INDEX('計算'!$H$6:$H$405,MATCH(87-MAX('計算'!$CT$6:$CT$405),'計算'!$CU$6:$CU$405,0)),""))) | J97: =IF($B97="","",N($H97)*IFERROR(INDEX('計算'!$G$6:$G$405,IF(87<=MAX('計算'!$CT$6:$CT$405),MATCH(87,'計算'!$CT$6:$CT$405,0),MATCH(87-MAX('計算'!$CT$6:$CT$405),'計算'!$CU$6:$CU$405,0))),1)*N($I97))
B98: =IF(88<=MAX('計算'!$CT$6:$CT$405)+MAX('計算'!$CU$6:$CU$405),88,"") | C98: =IF($B98="","",IF(88<=MAX('計算'!$CT$6:$CT$405),IFERROR(INDEX('計算'!$F$6:$F$405,MATCH(88,'計算'!$CT$6:$CT$405,0)),""),IFERROR(INDEX('計算'!$F$6:$F$405,MATCH(88-MAX('計算'!$CT$6:$CT$405),'計算'!$CU$6:$CU$405,0)),""))) | D98: =IF($B98="","",IF(88<=MAX('計算'!$CT$6:$CT$405),IFERROR(INDEX('計算'!$C$6:$C$405,MATCH(88,'計算'!$CT$6:$CT$405,0))&"",""),IFERROR(INDEX('計算'!$C$6:$C$405,MATCH(88-MAX('計算'!$CT$6:$CT$405),'計算'!$CU$6:$CU$405,0))&"",""))) | E98: =IF($B98="","",IF(88<=MAX('計算'!$CT$6:$CT$405),IFERROR(INDEX('計算'!$D$6:$D$405,MATCH(88,'計算'!$CT$6:$CT$405,0)),""),IFERROR(INDEX('計算'!$D$6:$D$405,MATCH(88-MAX('計算'!$CT$6:$CT$405),'計算'!$CU$6:$CU$405,0)),""))) | F98: =IF($B98="","",IF(88<=MAX('計算'!$CT$6:$CT$405),IFERROR(INDEX('計算'!$P$6:$P$405,MATCH(88,'計算'!$CT$6:$CT$405,0)),""),IFERROR(INDEX('計算'!$S$6:$S$405,MATCH(88-MAX('計算'!$CT$6:$CT$405),'計算'!$CU$6:$CU$405,0)),""))) | G98: =IF($B98="","",IF(88<=MAX('計算'!$CT$6:$CT$405),IFERROR(INDEX('計算'!$CR$6:$CR$405,MATCH(88,'計算'!$CT$6:$CT$405,0)),""),IFERROR(INDEX('計算'!$CR$6:$CR$405,MATCH(88-MAX('計算'!$CT$6:$CT$405),'計算'!$CU$6:$CU$405,0)),""))) | H98: =IF($B98="","",IF(88<=MAX('計算'!$CT$6:$CT$405),IFERROR(INDEX('計算'!$Q$6:$Q$405,MATCH(88,'計算'!$CT$6:$CT$405,0)),""),IFERROR(INDEX('計算'!$T$6:$T$405,MATCH(88-MAX('計算'!$CT$6:$CT$405),'計算'!$CU$6:$CU$405,0)),""))) | I98: =IF($B98="","",IF(88<=MAX('計算'!$CT$6:$CT$405),IFERROR(INDEX('計算'!$H$6:$H$405,MATCH(88,'計算'!$CT$6:$CT$405,0)),""),IFERROR(INDEX('計算'!$H$6:$H$405,MATCH(88-MAX('計算'!$CT$6:$CT$405),'計算'!$CU$6:$CU$405,0)),""))) | J98: =IF($B98="","",N($H98)*IFERROR(INDEX('計算'!$G$6:$G$405,IF(88<=MAX('計算'!$CT$6:$CT$405),MATCH(88,'計算'!$CT$6:$CT$405,0),MATCH(88-MAX('計算'!$CT$6:$CT$405),'計算'!$CU$6:$CU$405,0))),1)*N($I98))
B99: =IF(89<=MAX('計算'!$CT$6:$CT$405)+MAX('計算'!$CU$6:$CU$405),89,"") | C99: =IF($B99="","",IF(89<=MAX('計算'!$CT$6:$CT$405),IFERROR(INDEX('計算'!$F$6:$F$405,MATCH(89,'計算'!$CT$6:$CT$405,0)),""),IFERROR(INDEX('計算'!$F$6:$F$405,MATCH(89-MAX('計算'!$CT$6:$CT$405),'計算'!$CU$6:$CU$405,0)),""))) | D99: =IF($B99="","",IF(89<=MAX('計算'!$CT$6:$CT$405),IFERROR(INDEX('計算'!$C$6:$C$405,MATCH(89,'計算'!$CT$6:$CT$405,0))&"",""),IFERROR(INDEX('計算'!$C$6:$C$405,MATCH(89-MAX('計算'!$CT$6:$CT$405),'計算'!$CU$6:$CU$405,0))&"",""))) | E99: =IF($B99="","",IF(89<=MAX('計算'!$CT$6:$CT$405),IFERROR(INDEX('計算'!$D$6:$D$405,MATCH(89,'計算'!$CT$6:$CT$405,0)),""),IFERROR(INDEX('計算'!$D$6:$D$405,MATCH(89-MAX('計算'!$CT$6:$CT$405),'計算'!$CU$6:$CU$405,0)),""))) | F99: =IF($B99="","",IF(89<=MAX('計算'!$CT$6:$CT$405),IFERROR(INDEX('計算'!$P$6:$P$405,MATCH(89,'計算'!$CT$6:$CT$405,0)),""),IFERROR(INDEX('計算'!$S$6:$S$405,MATCH(89-MAX('計算'!$CT$6:$CT$405),'計算'!$CU$6:$CU$405,0)),""))) | G99: =IF($B99="","",IF(89<=MAX('計算'!$CT$6:$CT$405),IFERROR(INDEX('計算'!$CR$6:$CR$405,MATCH(89,'計算'!$CT$6:$CT$405,0)),""),IFERROR(INDEX('計算'!$CR$6:$CR$405,MATCH(89-MAX('計算'!$CT$6:$CT$405),'計算'!$CU$6:$CU$405,0)),""))) | H99: =IF($B99="","",IF(89<=MAX('計算'!$CT$6:$CT$405),IFERROR(INDEX('計算'!$Q$6:$Q$405,MATCH(89,'計算'!$CT$6:$CT$405,0)),""),IFERROR(INDEX('計算'!$T$6:$T$405,MATCH(89-MAX('計算'!$CT$6:$CT$405),'計算'!$CU$6:$CU$405,0)),""))) | I99: =IF($B99="","",IF(89<=MAX('計算'!$CT$6:$CT$405),IFERROR(INDEX('計算'!$H$6:$H$405,MATCH(89,'計算'!$CT$6:$CT$405,0)),""),IFERROR(INDEX('計算'!$H$6:$H$405,MATCH(89-MAX('計算'!$CT$6:$CT$405),'計算'!$CU$6:$CU$405,0)),""))) | J99: =IF($B99="","",N($H99)*IFERROR(INDEX('計算'!$G$6:$G$405,IF(89<=MAX('計算'!$CT$6:$CT$405),MATCH(89,'計算'!$CT$6:$CT$405,0),MATCH(89-MAX('計算'!$CT$6:$CT$405),'計算'!$CU$6:$CU$405,0))),1)*N($I99))
B100: =IF(90<=MAX('計算'!$CT$6:$CT$405)+MAX('計算'!$CU$6:$CU$405),90,"") | C100: =IF($B100="","",IF(90<=MAX('計算'!$CT$6:$CT$405),IFERROR(INDEX('計算'!$F$6:$F$405,MATCH(90,'計算'!$CT$6:$CT$405,0)),""),IFERROR(INDEX('計算'!$F$6:$F$405,MATCH(90-MAX('計算'!$CT$6:$CT$405),'計算'!$CU$6:$CU$405,0)),""))) | D100: =IF($B100="","",IF(90<=MAX('計算'!$CT$6:$CT$405),IFERROR(INDEX('計算'!$C$6:$C$405,MATCH(90,'計算'!$CT$6:$CT$405,0))&"",""),IFERROR(INDEX('計算'!$C$6:$C$405,MATCH(90-MAX('計算'!$CT$6:$CT$405),'計算'!$CU$6:$CU$405,0))&"",""))) | E100: =IF($B100="","",IF(90<=MAX('計算'!$CT$6:$CT$405),IFERROR(INDEX('計算'!$D$6:$D$405,MATCH(90,'計算'!$CT$6:$CT$405,0)),""),IFERROR(INDEX('計算'!$D$6:$D$405,MATCH(90-MAX('計算'!$CT$6:$CT$405),'計算'!$CU$6:$CU$405,0)),""))) | F100: =IF($B100="","",IF(90<=MAX('計算'!$CT$6:$CT$405),IFERROR(INDEX('計算'!$P$6:$P$405,MATCH(90,'計算'!$CT$6:$CT$405,0)),""),IFERROR(INDEX('計算'!$S$6:$S$405,MATCH(90-MAX('計算'!$CT$6:$CT$405),'計算'!$CU$6:$CU$405,0)),""))) | G100: =IF($B100="","",IF(90<=MAX('計算'!$CT$6:$CT$405),IFERROR(INDEX('計算'!$CR$6:$CR$405,MATCH(90,'計算'!$CT$6:$CT$405,0)),""),IFERROR(INDEX('計算'!$CR$6:$CR$405,MATCH(90-MAX('計算'!$CT$6:$CT$405),'計算'!$CU$6:$CU$405,0)),""))) | H100: =IF($B100="","",IF(90<=MAX('計算'!$CT$6:$CT$405),IFERROR(INDEX('計算'!$Q$6:$Q$405,MATCH(90,'計算'!$CT$6:$CT$405,0)),""),IFERROR(INDEX('計算'!$T$6:$T$405,MATCH(90-MAX('計算'!$CT$6:$CT$405),'計算'!$CU$6:$CU$405,0)),""))) | I100: =IF($B100="","",IF(90<=MAX('計算'!$CT$6:$CT$405),IFERROR(INDEX('計算'!$H$6:$H$405,MATCH(90,'計算'!$CT$6:$CT$405,0)),""),IFERROR(INDEX('計算'!$H$6:$H$405,MATCH(90-MAX('計算'!$CT$6:$CT$405),'計算'!$CU$6:$CU$405,0)),""))) | J100: =IF($B100="","",N($H100)*IFERROR(INDEX('計算'!$G$6:$G$405,IF(90<=MAX('計算'!$CT$6:$CT$405),MATCH(90,'計算'!$CT$6:$CT$405,0),MATCH(90-MAX('計算'!$CT$6:$CT$405),'計算'!$CU$6:$CU$405,0))),1)*N($I100))
B101: =IF(91<=MAX('計算'!$CT$6:$CT$405)+MAX('計算'!$CU$6:$CU$405),91,"") | C101: =IF($B101="","",IF(91<=MAX('計算'!$CT$6:$CT$405),IFERROR(INDEX('計算'!$F$6:$F$405,MATCH(91,'計算'!$CT$6:$CT$405,0)),""),IFERROR(INDEX('計算'!$F$6:$F$405,MATCH(91-MAX('計算'!$CT$6:$CT$405),'計算'!$CU$6:$CU$405,0)),""))) | D101: =IF($B101="","",IF(91<=MAX('計算'!$CT$6:$CT$405),IFERROR(INDEX('計算'!$C$6:$C$405,MATCH(91,'計算'!$CT$6:$CT$405,0))&"",""),IFERROR(INDEX('計算'!$C$6:$C$405,MATCH(91-MAX('計算'!$CT$6:$CT$405),'計算'!$CU$6:$CU$405,0))&"",""))) | E101: =IF($B101="","",IF(91<=MAX('計算'!$CT$6:$CT$405),IFERROR(INDEX('計算'!$D$6:$D$405,MATCH(91,'計算'!$CT$6:$CT$405,0)),""),IFERROR(INDEX('計算'!$D$6:$D$405,MATCH(91-MAX('計算'!$CT$6:$CT$405),'計算'!$CU$6:$CU$405,0)),""))) | F101: =IF($B101="","",IF(91<=MAX('計算'!$CT$6:$CT$405),IFERROR(INDEX('計算'!$P$6:$P$405,MATCH(91,'計算'!$CT$6:$CT$405,0)),""),IFERROR(INDEX('計算'!$S$6:$S$405,MATCH(91-MAX('計算'!$CT$6:$CT$405),'計算'!$CU$6:$CU$405,0)),""))) | G101: =IF($B101="","",IF(91<=MAX('計算'!$CT$6:$CT$405),IFERROR(INDEX('計算'!$CR$6:$CR$405,MATCH(91,'計算'!$CT$6:$CT$405,0)),""),IFERROR(INDEX('計算'!$CR$6:$CR$405,MATCH(91-MAX('計算'!$CT$6:$CT$405),'計算'!$CU$6:$CU$405,0)),""))) | H101: =IF($B101="","",IF(91<=MAX('計算'!$CT$6:$CT$405),IFERROR(INDEX('計算'!$Q$6:$Q$405,MATCH(91,'計算'!$CT$6:$CT$405,0)),""),IFERROR(INDEX('計算'!$T$6:$T$405,MATCH(91-MAX('計算'!$CT$6:$CT$405),'計算'!$CU$6:$CU$405,0)),""))) | I101: =IF($B101="","",IF(91<=MAX('計算'!$CT$6:$CT$405),IFERROR(INDEX('計算'!$H$6:$H$405,MATCH(91,'計算'!$CT$6:$CT$405,0)),""),IFERROR(INDEX('計算'!$H$6:$H$405,MATCH(91-MAX('計算'!$CT$6:$CT$405),'計算'!$CU$6:$CU$405,0)),""))) | J101: =IF($B101="","",N($H101)*IFERROR(INDEX('計算'!$G$6:$G$405,IF(91<=MAX('計算'!$CT$6:$CT$405),MATCH(91,'計算'!$CT$6:$CT$405,0),MATCH(91-MAX('計算'!$CT$6:$CT$405),'計算'!$CU$6:$CU$405,0))),1)*N($I101))
...

Sheet 動員を入れる
B1: 随時 動員を入れる | P1: ◀ ホーム
B2: 動員を入れる
B3: 予測は読みが変わる日だけ。実績は月1回まとめてでも構いません。空欄の日は曜日の実績平均→標準の動員の順で埋まります。
B5: 表の開始日 | E5: ← 空欄なら今年の1月1日から400日分。年が変わったら新しい年の1月1日を入れます。動かすと入力済みの行がずれるので、年に1回だけ。 | J5: 曜日ごとの実績平均（直近8週）
J6: 自動 | K6: 自動 | L6: 自動
J7: 曜日 | K7: 実績の平均 | L7: 日数
J8: 月 | K8: =IFERROR(AVERAGEIFS('動員を入れる'!$E$16:$E$415,'動員を入れる'!$C$16:$C$415,$J8,'動員を入れる'!$B$16:$B$415,">="&(N('設定'!$C$6)-56),'動員を入れる'!$B$16:$B$415,"<"&N('設定'!$C$6)),"") | L8: =COUNTIFS('動員を入れる'!$C$16:$C$415,$J8,'動員を入れる'!$B$16:$B$415,">="&(N('設定'!$C$6)-56),'動員を入れる'!$B$16:$B$415,"<"&N('設定'!$C$6),'動員を入れる'!$E$16:$E$415,">0")
J9: 火 | K9: =IFERROR(AVERAGEIFS('動員を入れる'!$E$16:$E$415,'動員を入れる'!$C$16:$C$415,$J9,'動員を入れる'!$B$16:$B$415,">="&(N('設定'!$C$6)-56),'動員を入れる'!$B$16:$B$415,"<"&N('設定'!$C$6)),"") | L9: =COUNTIFS('動員を入れる'!$C$16:$C$415,$J9,'動員を入れる'!$B$16:$B$415,">="&(N('設定'!$C$6)-56),'動員を入れる'!$B$16:$B$415,"<"&N('設定'!$C$6),'動員を入れる'!$E$16:$E$415,">0")
J10: 水 | K10: =IFERROR(AVERAGEIFS('動員を入れる'!$E$16:$E$415,'動員を入れる'!$C$16:$C$415,$J10,'動員を入れる'!$B$16:$B$415,">="&(N('設定'!$C$6)-56),'動員を入れる'!$B$16:$B$415,"<"&N('設定'!$C$6)),"") | L10: =COUNTIFS('動員を入れる'!$C$16:$C$415,$J10,'動員を入れる'!$B$16:$B$415,">="&(N('設定'!$C$6)-56),'動員を入れる'!$B$16:$B$415,"<"&N('設定'!$C$6),'動員を入れる'!$E$16:$E$415,">0")
J11: 木 | K11: =IFERROR(AVERAGEIFS('動員を入れる'!$E$16:$E$415,'動員を入れる'!$C$16:$C$415,$J11,'動員を入れる'!$B$16:$B$415,">="&(N('設定'!$C$6)-56),'動員を入れる'!$B$16:$B$415,"<"&N('設定'!$C$6)),"") | L11: =COUNTIFS('動員を入れる'!$C$16:$C$415,$J11,'動員を入れる'!$B$16:$B$415,">="&(N('設定'!$C$6)-56),'動員を入れる'!$B$16:$B$415,"<"&N('設定'!$C$6),'動員を入れる'!$E$16:$E$415,">0")
J12: 金 | K12: =IFERROR(AVERAGEIFS('動員を入れる'!$E$16:$E$415,'動員を入れる'!$C$16:$C$415,$J12,'動員を入れる'!$B$16:$B$415,">="&(N('設定'!$C$6)-56),'動員を入れる'!$B$16:$B$415,"<"&N('設定'!$C$6)),"") | L12: =COUNTIFS('動員を入れる'!$C$16:$C$415,$J12,'動員を入れる'!$B$16:$B$415,">="&(N('設定'!$C$6)-56),'動員を入れる'!$B$16:$B$415,"<"&N('設定'!$C$6),'動員を入れる'!$E$16:$E$415,">0")
B13: 薄い黄色の帯＝これから14日（発注に使う範囲）。橙の実績＝入れ忘れ。 | J13: 土 | K13: =IFERROR(AVERAGEIFS('動員を入れる'!$E$16:$E$415,'動員を入れる'!$C$16:$C$415,$J13,'動員を入れる'!$B$16:$B$415,">="&(N('設定'!$C$6)-56),'動員を入れる'!$B$16:$B$415,"<"&N('設定'!$C$6)),"") | L13: =COUNTIFS('動員を入れる'!$C$16:$C$415,$J13,'動員を入れる'!$B$16:$B$415,">="&(N('設定'!$C$6)-56),'動員を入れる'!$B$16:$B$415,"<"&N('設定'!$C$6),'動員を入れる'!$E$16:$E$415,">0")
B14: 自動 | C14: 自動 | D14: 入力 | E14: 入力 | F14: 入力 | G14: 自動 | J14: 日 | K14: =IFERROR(AVERAGEIFS('動員を入れる'!$E$16:$E$415,'動員を入れる'!$C$16:$C$415,$J14,'動員を入れる'!$B$16:$B$415,">="&(N('設定'!$C$6)-56),'動員を入れる'!$B$16:$B$415,"<"&N('設定'!$C$6)),"") | L14: =COUNTIFS('動員を入れる'!$C$16:$C$415,$J14,'動員を入れる'!$B$16:$B$415,">="&(N('設定'!$C$6)-56),'動員を入れる'!$B$16:$B$415,"<"&N('設定'!$C$6),'動員を入れる'!$E$16:$E$415,">0")
B15: 日付 | C15: 曜日 | D15: 予測動員 | E15: 実績動員 | F15: 主な作品・備考 | G15: 採用する動員
B16: =IF(IF($C$5<>"",$C$5,IF('設定'!$C$6="","",DATE(YEAR('設定'!$C$6),1,1)))="","",IF($C$5<>"",$C$5,IF('設定'!$C$6="","",DATE(YEAR('設定'!$C$6),1,1)))+0) | C16: =IF($B16="","",CHOOSE(WEEKDAY($B16),"日","月","火","水","木","金","土")) | G16: =IF($B16="","",IF(ISNUMBER($E16),$E16,IF(ISNUMBER($D16),$D16,ROUND(IF(N(IFERROR(INDEX('動員を入れる'!$K$8:$K$14,MATCH($C16,'動員を入れる'!$J$8:$J$14,0)),0))>0,IFERROR(INDEX('動員を入れる'!$K$8:$K$14,MATCH($C16,'動員を入れる'!$J$8:$J$14,0)),0),N('設定'!$C$8)),0))))
B17: =IF(IF($C$5<>"",$C$5,IF('設定'!$C$6="","",DATE(YEAR('設定'!$C$6),1,1)))="","",IF($C$5<>"",$C$5,IF('設定'!$C$6="","",DATE(YEAR('設定'!$C$6),1,1)))+1) | C17: =IF($B17="","",CHOOSE(WEEKDAY($B17),"日","月","火","水","木","金","土")) | G17: =IF($B17="","",IF(ISNUMBER($E17),$E17,IF(ISNUMBER($D17),$D17,ROUND(IF(N(IFERROR(INDEX('動員を入れる'!$K$8:$K$14,MATCH($C17,'動員を入れる'!$J$8:$J$14,0)),0))>0,IFERROR(INDEX('動員を入れる'!$K$8:$K$14,MATCH($C17,'動員を入れる'!$J$8:$J$14,0)),0),N('設定'!$C$8)),0))))
B18: =IF(IF($C$5<>"",$C$5,IF('設定'!$C$6="","",DATE(YEAR('設定'!$C$6),1,1)))="","",IF($C$5<>"",$C$5,IF('設定'!$C$6="","",DATE(YEAR('設定'!$C$6),1,1)))+2) | C18: =IF($B18="","",CHOOSE(WEEKDAY($B18),"日","月","火","水","木","金","土")) | G18: =IF($B18="","",IF(ISNUMBER($E18),$E18,IF(ISNUMBER($D18),$D18,ROUND(IF(N(IFERROR(INDEX('動員を入れる'!$K$8:$K$14,MATCH($C18,'動員を入れる'!$J$8:$J$14,0)),0))>0,IFERROR(INDEX('動員を入れる'!$K$8:$K$14,MATCH($C18,'動員を入れる'!$J$8:$J$14,0)),0),N('設定'!$C$8)),0))))
B19: =IF(IF($C$5<>"",$C$5,IF('設定'!$C$6="","",DATE(YEAR('設定'!$C$6),1,1)))="","",IF($C$5<>"",$C$5,IF('設定'!$C$6="","",DATE(YEAR('設定'!$C$6),1,1)))+3) | C19: =IF($B19="","",CHOOSE(WEEKDAY($B19),"日","月","火","水","木","金","土")) | G19: =IF($B19="","",IF(ISNUMBER($E19),$E19,IF(ISNUMBER($D19),$D19,ROUND(IF(N(IFERROR(INDEX('動員を入れる'!$K$8:$K$14,MATCH($C19,'動員を入れる'!$J$8:$J$14,0)),0))>0,IFERROR(INDEX('動員を入れる'!$K$8:$K$14,MATCH($C19,'動員を入れる'!$J$8:$J$14,0)),0),N('設定'!$C$8)),0))))
B20: =IF(IF($C$5<>"",$C$5,IF('設定'!$C$6="","",DATE(YEAR('設定'!$C$6),1,1)))="","",IF($C$5<>"",$C$5,IF('設定'!$C$6="","",DATE(YEAR('設定'!$C$6),1,1)))+4) | C20: =IF($B20="","",CHOOSE(WEEKDAY($B20),"日","月","火","水","木","金","土")) | G20: =IF($B20="","",IF(ISNUMBER($E20),$E20,IF(ISNUMBER($D20),$D20,ROUND(IF(N(IFERROR(INDEX('動員を入れる'!$K$8:$K$14,MATCH($C20,'動員を入れる'!$J$8:$J$14,0)),0))>0,IFERROR(INDEX('動員を入れる'!$K$8:$K$14,MATCH($C20,'動員を入れる'!$J$8:$J$14,0)),0),N('設定'!$C$8)),0))))
B21: =IF(IF($C$5<>"",$C$5,IF('設定'!$C$6="","",DATE(YEAR('設定'!$C$6),1,1)))="","",IF($C$5<>"",$C$5,IF('設定'!$C$6="","",DATE(YEAR('設定'!$C$6),1,1)))+5) | C21: =IF($B21="","",CHOOSE(WEEKDAY($B21),"日","月","火","水","木","金","土")) | G21: =IF($B21="","",IF(ISNUMBER($E21),$E21,IF(ISNUMBER($D21),$D21,ROUND(IF(N(IFERROR(INDEX('動員を入れる'!$K$8:$K$14,MATCH($C21,'動員を入れる'!$J$8:$J$14,0)),0))>0,IFERROR(INDEX('動員を入れる'!$K$8:$K$14,MATCH($C21,'動員を入れる'!$J$8:$J$14,0)),0),N('設定'!$C$8)),0))))
B22: =IF(IF($C$5<>"",$C$5,IF('設定'!$C$6="","",DATE(YEAR('設定'!$C$6),1,1)))="","",IF($C$5<>"",$C$5,IF('設定'!$C$6="","",DATE(YEAR('設定'!$C$6),1,1)))+6) | C22: =IF($B22="","",CHOOSE(WEEKDAY($B22),"日","月","火","水","木","金","土")) | G22: =IF($B22="","",IF(ISNUMBER($E22),$E22,IF(ISNUMBER($D22),$D22,ROUND(IF(N(IFERROR(INDEX('動員を入れる'!$K$8:$K$14,MATCH($C22,'動員を入れる'!$J$8:$J$14,0)),0))>0,IFERROR(INDEX('動員を入れる'!$K$8:$K$14,MATCH($C22,'動員を入れる'!$J$8:$J$14,0)),0),N('設定'!$C$8)),0))))
B23: =IF(IF($C$5<>"",$C$5,IF('設定'!$C$6="","",DATE(YEAR('設定'!$C$6),1,1)))="","",IF($C$5<>"",$C$5,IF('設定'!$C$6="","",DATE(YEAR('設定'!$C$6),1,1)))+7) | C23: =IF($B23="","",CHOOSE(WEEKDAY($B23),"日","月","火","水","木","金","土")) | G23: =IF($B23="","",IF(ISNUMBER($E23),$E23,IF(ISNUMBER($D23),$D23,ROUND(IF(N(IFERROR(INDEX('動員を入れる'!$K$8:$K$14,MATCH($C23,'動員を入れる'!$J$8:$J$14,0)),0))>0,IFERROR(INDEX('動員を入れる'!$K$8:$K$14,MATCH($C23,'動員を入れる'!$J$8:$J$14,0)),0),N('設定'!$C$8)),0))))
B24: =IF(IF($C$5<>"",$C$5,IF('設定'!$C$6="","",DATE(YEAR('設定'!$C$6),1,1)))="","",IF($C$5<>"",$C$5,IF('設定'!$C$6="","",DATE(YEAR('設定'!$C$6),1,1)))+8) | C24: =IF($B24="","",CHOOSE(WEEKDAY($B24),"日","月","火","水","木","金","土")) | G24: =IF($B24="","",IF(ISNUMBER($E24),$E24,IF(ISNUMBER($D24),$D24,ROUND(IF(N(IFERROR(INDEX('動員を入れる'!$K$8:$K$14,MATCH($C24,'動員を入れる'!$J$8:$J$14,0)),0))>0,IFERROR(INDEX('動員を入れる'!$K$8:$K$14,MATCH($C24,'動員を入れる'!$J$8:$J$14,0)),0),N('設定'!$C$8)),0))))
B25: =IF(IF($C$5<>"",$C$5,IF('設定'!$C$6="","",DATE(YEAR('設定'!$C$6),1,1)))="","",IF($C$5<>"",$C$5,IF('設定'!$C$6="","",DATE(YEAR('設定'!$C$6),1,1)))+9) | C25: =IF($B25="","",CHOOSE(WEEKDAY($B25),"日","月","火","水","木","金","土")) | G25: =IF($B25="","",IF(ISNUMBER($E25),$E25,IF(ISNUMBER($D25),$D25,ROUND(IF(N(IFERROR(INDEX('動員を入れる'!$K$8:$K$14,MATCH($C25,'動員を入れる'!$J$8:$J$14,0)),0))>0,IFERROR(INDEX('動員を入れる'!$K$8:$K$14,MATCH($C25,'動員を入れる'!$J$8:$J$14,0)),0),N('設定'!$C$8)),0))))
B26: =IF(IF($C$5<>"",$C$5,IF('設定'!$C$6="","",DATE(YEAR('設定'!$C$6),1,1)))="","",IF($C$5<>"",$C$5,IF('設定'!$C$6="","",DATE(YEAR('設定'!$C$6),1,1)))+10) | C26: =IF($B26="","",CHOOSE(WEEKDAY($B26),"日","月","火","水","木","金","土")) | G26: =IF($B26="","",IF(ISNUMBER($E26),$E26,IF(ISNUMBER($D26),$D26,ROUND(IF(N(IFERROR(INDEX('動員を入れる'!$K$8:$K$14,MATCH($C26,'動員を入れる'!$J$8:$J$14,0)),0))>0,IFERROR(INDEX('動員を入れる'!$K$8:$K$14,MATCH($C26,'動員を入れる'!$J$8:$J$14,0)),0),N('設定'!$C$8)),0))))
B27: =IF(IF($C$5<>"",$C$5,IF('設定'!$C$6="","",DATE(YEAR('設定'!$C$6),1,1)))="","",IF($C$5<>"",$C$5,IF('設定'!$C$6="","",DATE(YEAR('設定'!$C$6),1,1)))+11) | C27: =IF($B27="","",CHOOSE(WEEKDAY($B27),"日","月","火","水","木","金","土")) | G27: =IF($B27="","",IF(ISNUMBER($E27),$E27,IF(ISNUMBER($D27),$D27,ROUND(IF(N(IFERROR(INDEX('動員を入れる'!$K$8:$K$14,MATCH($C27,'動員を入れる'!$J$8:$J$14,0)),0))>0,IFERROR(INDEX('動員を入れる'!$K$8:$K$14,MATCH($C27,'動員を入れる'!$J$8:$J$14,0)),0),N('設定'!$C$8)),0))))
B28: =IF(IF($C$5<>"",$C$5,IF('設定'!$C$6="","",DATE(YEAR('設定'!$C$6),1,1)))="","",IF($C$5<>"",$C$5,IF('設定'!$C$6="","",DATE(YEAR('設定'!$C$6),1,1)))+12) | C28: =IF($B28="","",CHOOSE(WEEKDAY($B28),"日","月","火","水","木","金","土")) | G28: =IF($B28="","",IF(ISNUMBER($E28),$E28,IF(ISNUMBER($D28),$D28,ROUND(IF(N(IFERROR(INDEX('動員を入れる'!$K$8:$K$14,MATCH($C28,'動員を入れる'!$J$8:$J$14,0)),0))>0,IFERROR(INDEX('動員を入れる'!$K$8:$K$14,MATCH($C28,'動員を入れる'!$J$8:$J$14,0)),0),N('設定'!$C$8)),0))))
B29: =IF(IF($C$5<>"",$C$5,IF('設定'!$C$6="","",DATE(YEAR('設定'!$C$6),1,1)))="","",IF($C$5<>"",$C$5,IF('設定'!$C$6="","",DATE(YEAR('設定'!$C$6),1,1)))+13) | C29: =IF($B29="","",CHOOSE(WEEKDAY($B29),"日","月","火","水","木","金","土")) | G29: =IF($B29="","",IF(ISNUMBER($E29),$E29,IF(ISNUMBER($D29),$D29,ROUND(IF(N(IFERROR(INDEX('動員を入れる'!$K$8:$K$14,MATCH($C29,'動員を入れる'!$J$8:$J$14,0)),0))>0,IFERROR(INDEX('動員を入れる'!$K$8:$K$14,MATCH($C29,'動員を入れる'!$J$8:$J$14,0)),0),N('設定'!$C$8)),0))))
B30: =IF(IF($C$5<>"",$C$5,IF('設定'!$C$6="","",DATE(YEAR('設定'!$C$6),1,1)))="","",IF($C$5<>"",$C$5,IF('設定'!$C$6="","",DATE(YEAR('設定'!$C$6),1,1)))+14) | C30: =IF($B30="","",CHOOSE(WEEKDAY($B30),"日","月","火","水","木","金","土")) | G30: =IF($B30="","",IF(ISNUMBER($E30),$E30,IF(ISNUMBER($D30),$D30,ROUND(IF(N(IFERROR(INDEX('動員を入れる'!$K$8:$K$14,MATCH($C30,'動員を入れる'!$J$8:$J$14,0)),0))>0,IFERROR(INDEX('動員を入れる'!$K$8:$K$14,MATCH($C30,'動員を入れる'!$J$8:$J$14,0)),0),N('設定'!$C$8)),0))))
B31: =IF(IF($C$5<>"",$C$5,IF('設定'!$C$6="","",DATE(YEAR('設定'!$C$6),1,1)))="","",IF($C$5<>"",$C$5,IF('設定'!$C$6="","",DATE(YEAR('設定'!$C$6),1,1)))+15) | C31: =IF($B31="","",CHOOSE(WEEKDAY($B31),"日","月","火","水","木","金","土")) | G31: =IF($B31="","",IF(ISNUMBER($E31),$E31,IF(ISNUMBER($D31),$D31,ROUND(IF(N(IFERROR(INDEX('動員を入れる'!$K$8:$K$14,MATCH($C31,'動員を入れる'!$J$8:$J$14,0)),0))>0,IFERROR(INDEX('動員を入れる'!$K$8:$K$14,MATCH($C31,'動員を入れる'!$J$8:$J$14,0)),0),N('設定'!$C$8)),0))))
B32: =IF(IF($C$5<>"",$C$5,IF('設定'!$C$6="","",DATE(YEAR('設定'!$C$6),1,1)))="","",IF($C$5<>"",$C$5,IF('設定'!$C$6="","",DATE(YEAR('設定'!$C$6),1,1)))+16) | C32: =IF($B32="","",CHOOSE(WEEKDAY($B32),"日","月","火","水","木","金","土")) | G32: =IF($B32="","",IF(ISNUMBER($E32),$E32,IF(ISNUMBER($D32),$D32,ROUND(IF(N(IFERROR(INDEX('動員を入れる'!$K$8:$K$14,MATCH($C32,'動員を入れる'!$J$8:$J$14,0)),0))>0,IFERROR(INDEX('動員を入れる'!$K$8:$K$14,MATCH($C32,'動員を入れる'!$J$8:$J$14,0)),0),N('設定'!$C$8)),0))))
B33: =IF(IF($C$5<>"",$C$5,IF('設定'!$C$6="","",DATE(YEAR('設定'!$C$6),1,1)))="","",IF($C$5<>"",$C$5,IF('設定'!$C$6="","",DATE(YEAR('設定'!$C$6),1,1)))+17) | C33: =IF($B33="","",CHOOSE(WEEKDAY($B33),"日","月","火","水","木","金","土")) | G33: =IF($B33="","",IF(ISNUMBER($E33),$E33,IF(ISNUMBER($D33),$D33,ROUND(IF(N(IFERROR(INDEX('動員を入れる'!$K$8:$K$14,MATCH($C33,'動員を入れる'!$J$8:$J$14,0)),0))>0,IFERROR(INDEX('動員を入れる'!$K$8:$K$14,MATCH($C33,'動員を入れる'!$J$8:$J$14,0)),0),N('設定'!$C$8)),0))))
B34: =IF(IF($C$5<>"",$C$5,IF('設定'!$C$6="","",DATE(YEAR('設定'!$C$6),1,1)))="","",IF($C$5<>"",$C$5,IF('設定'!$C$6="","",DATE(YEAR('設定'!$C$6),1,1)))+18) | C34: =IF($B34="","",CHOOSE(WEEKDAY($B34),"日","月","火","水","木","金","土")) | G34: =IF($B34="","",IF(ISNUMBER($E34),$E34,IF(ISNUMBER($D34),$D34,ROUND(IF(N(IFERROR(INDEX('動員を入れる'!$K$8:$K$14,MATCH($C34,'動員を入れる'!$J$8:$J$14,0)),0))>0,IFERROR(INDEX('動員を入れる'!$K$8:$K$14,MATCH($C34,'動員を入れる'!$J$8:$J$14,0)),0),N('設定'!$C$8)),0))))
B35: =IF(IF($C$5<>"",$C$5,IF('設定'!$C$6="","",DATE(YEAR('設定'!$C$6),1,1)))="","",IF($C$5<>"",$C$5,IF('設定'!$C$6="","",DATE(YEAR('設定'!$C$6),1,1)))+19) | C35: =IF($B35="","",CHOOSE(WEEKDAY($B35),"日","月","火","水","木","金","土")) | G35: =IF($B35="","",IF(ISNUMBER($E35),$E35,IF(ISNUMBER($D35),$D35,ROUND(IF(N(IFERROR(INDEX('動員を入れる'!$K$8:$K$14,MATCH($C35,'動員を入れる'!$J$8:$J$14,0)),0))>0,IFERROR(INDEX('動員を入れる'!$K$8:$K$14,MATCH($C35,'動員を入れる'!$J$8:$J$14,0)),0),N('設定'!$C$8)),0))))
B36: =IF(IF($C$5<>"",$C$5,IF('設定'!$C$6="","",DATE(YEAR('設定'!$C$6),1,1)))="","",IF($C$5<>"",$C$5,IF('設定'!$C$6="","",DATE(YEAR('設定'!$C$6),1,1)))+20) | C36: =IF($B36="","",CHOOSE(WEEKDAY($B36),"日","月","火","水","木","金","土")) | G36: =IF($B36="","",IF(ISNUMBER($E36),$E36,IF(ISNUMBER($D36),$D36,ROUND(IF(N(IFERROR(INDEX('動員を入れる'!$K$8:$K$14,MATCH($C36,'動員を入れる'!$J$8:$J$14,0)),0))>0,IFERROR(INDEX('動員を入れる'!$K$8:$K$14,MATCH($C36,'動員を入れる'!$J$8:$J$14,0)),0),N('設定'!$C$8)),0))))
B37: =IF(IF($C$5<>"",$C$5,IF('設定'!$C$6="","",DATE(YEAR('設定'!$C$6),1,1)))="","",IF($C$5<>"",$C$5,IF('設定'!$C$6="","",DATE(YEAR('設定'!$C$6),1,1)))+21) | C37: =IF($B37="","",CHOOSE(WEEKDAY($B37),"日","月","火","水","木","金","土")) | G37: =IF($B37="","",IF(ISNUMBER($E37),$E37,IF(ISNUMBER($D37),$D37,ROUND(IF(N(IFERROR(INDEX('動員を入れる'!$K$8:$K$14,MATCH($C37,'動員を入れる'!$J$8:$J$14,0)),0))>0,IFERROR(INDEX('動員を入れる'!$K$8:$K$14,MATCH($C37,'動員を入れる'!$J$8:$J$14,0)),0),N('設定'!$C$8)),0))))
B38: =IF(IF($C$5<>"",$C$5,IF('設定'!$C$6="","",DATE(YEAR('設定'!$C$6),1,1)))="","",IF($C$5<>"",$C$5,IF('設定'!$C$6="","",DATE(YEAR('設定'!$C$6),1,1)))+22) | C38: =IF($B38="","",CHOOSE(WEEKDAY($B38),"日","月","火","水","木","金","土")) | G38: =IF($B38="","",IF(ISNUMBER($E38),$E38,IF(ISNUMBER($D38),$D38,ROUND(IF(N(IFERROR(INDEX('動員を入れる'!$K$8:$K$14,MATCH($C38,'動員を入れる'!$J$8:$J$14,0)),0))>0,IFERROR(INDEX('動員を入れる'!$K$8:$K$14,MATCH($C38,'動員を入れる'!$J$8:$J$14,0)),0),N('設定'!$C$8)),0))))
B39: =IF(IF($C$5<>"",$C$5,IF('設定'!$C$6="","",DATE(YEAR('設定'!$C$6),1,1)))="","",IF($C$5<>"",$C$5,IF('設定'!$C$6="","",DATE(YEAR('設定'!$C$6),1,1)))+23) | C39: =IF($B39="","",CHOOSE(WEEKDAY($B39),"日","月","火","水","木","金","土")) | G39: =IF($B39="","",IF(ISNUMBER($E39),$E39,IF(ISNUMBER($D39),$D39,ROUND(IF(N(IFERROR(INDEX('動員を入れる'!$K$8:$K$14,MATCH($C39,'動員を入れる'!$J$8:$J$14,0)),0))>0,IFERROR(INDEX('動員を入れる'!$K$8:$K$14,MATCH($C39,'動員を入れる'!$J$8:$J$14,0)),0),N('設定'!$C$8)),0))))
