Workbook

Sheet はじめに
B2: 売店発注ツール
D5: 毎日やること これだけです
D6: シートの①②③を左から順にやれば、その日の発注は終わります。
D7: 黄色いセルだけ入力します。それ以外のセルは触らないでください。
C9: ①今日の在庫を貼る | D9: 在庫システムから出した「今日の在庫一覧CSV」を貼る
D10: CSVを開いて、見出し行を除いたデータ部分をコピーし、A2セルに貼り付けます。
D11: 貼り付けたら、シート上部の「該当行数」が0以外になっているか見てください。
D12: 0のままなら貼り付けに失敗しています。もう一度やり直してください。
C13: ②発注数を決める | D13: 帯を見ながら、黄色の「発注数」に数字を入れる
D14: 帯が赤い商品は、今日発注しないと在庫が切れます。
D15: 迷ったら「推奨(ケース)」に出ている数字をそのまま入れて構いません。
D16: 数字を入れると帯が伸びます。伸びた先まで在庫が持つ、という意味です。
D17: 右上に「保管スペースの埋まり具合」が出ます。100%を超えると入りきりません。
C18: ③発注書 | D18: 発注先を選んで、印刷する
D19: ②で入れた数量がここに集まります。発注先を選ぶとその仕入先の分だけになります。
D20: そのまま印刷して、いつもの方法で発注してください。
D22: 発注したら「発注管理」シートに記録します。入荷したら入荷日も入れてください。
C24: 発注のしくみ | D24: 「何を計算しているのか」を図で見る（最初に1回だけ読めば十分です）
D25: 定数がどこにあるか、そこから発注数がどう出るかを1枚にまとめてあります。
D27: 色の意味
D28: 黄色のセル … 入力するところ
D29: 白・灰色のセル … 自動で計算されるところ（触らない）
D30: 赤い帯 … 今日発注しないと間に合わない
D31: オレンジの帯 … 次の発注までに在庫が切れる
D32: 緑の帯 … 在庫に余裕がある
D34: 社員の方がやること
C35: 月1回_前回の在庫を貼る | D35: 月に1回、2ヶ月前の在庫一覧CSVを貼り替える
D36: 今日の在庫と突き合わせて、期間の消費量を出します。
D37: 商品が入れ替わっても発注から漏れないよう、両方の商品を見ています。
C38: 随時_動員を入れる | D38: 大きな作品の公開週など、来場者の読みが変わる日に入力する
D39: 空欄の日は劇場の標準来場者数が自動で使われます。毎日入れる必要はありません。
C40: ダッシュボード | D40: 劇場全体の状況を確認する
C41: 商品マスタ | D41: リードタイム・最低ロット・PI値を登録する
C42: 定数マスタ | D42: 劇場・規模区分・季節の係数・保管設備を決める
D43: 人が決める数字はこの1枚に集めてあります。
D44: ⑤保管設備に冷蔵庫やストッカーを登録すると、収容ケース数が自動で集計され、
D45: ②の「保管スペースの埋まり具合」に反映されます。
C46: 設定（最初に1回） | D46: 対象の劇場と、発注数の算出基準を選ぶ
D48: 発注数はどう決まっているか
D49: この商品は1日に何個くらい減るか（実績、または来場者予測 × PI値）
D50: ↓
D51: 届くまでの日数と、次に発注するまでの日数のあいだに何個必要か
D52: ↓
D53: その必要数から、今ある在庫と発注済みの分を引く
D54: ↓
D55: 入数で割って、ケース単位に切り上げる ＝ 推奨発注数
D57: 式で書くと次のとおりです。
D58: 安全在庫 ＝ 1日あたり消費 × 安全在庫日数
D59: 発注点 ＝ 1日あたり消費 ×（リードタイム＋発注サイクル）＋ 安全在庫
D60: 推奨発注数 ＝ 発注点 − 今の在庫 − 発注済み未入荷
... D65: ・「マスタ未登録」と出る → 新商品です。商品マスタに追加してください

Sheet 発注のしくみ
B2: 発注のしくみ
B3: このツールが何をしているかの説明です。最初に1回読めば、あとは②発注数を決めるシートだけ見れば発注できます。
B5: 発注は3つのことしかしていません
B6: ① 決めておく | M6: ➡ | O6: ② 今の在庫を読む | Z6: ➡ | AB6: ③ 足りない分だけ発注
B7: 「この商品は、いつも何個持っておくか」を先に決めておきます。これが定数です。毎日は変わりません。 | O7: 在庫システムのCSVを貼るだけです。総数（＝ケース×入数＋バラ）が、そのまま今の在庫になります。 | AB7: 持っておくべき数から、今の在庫と発注済みの分を引きます。残った数が、今日発注する数です。
B10: 置き場所： 定数マスタ ／ 商品マスタ | O10: 置き場所： ①今日の在庫を貼る | AB10: 置き場所： ②発注数を決める → ③発注書
B11: 触るのは社員だけ。ふだんは開きません。 | O11: 毎日やるのはここだけです。 | AB11: 数字は自動で出ます。そのまま入れて構いません。
B13: 1. 定数はどこにあるか
B14: 人が決める数字は、この2枚にしかありません。「今の値」はあなたの劇場の現在値です（設定シートで選んだ劇場）。
B15: 決めておくこと | J15: 置き場所 | P15: ブロック | V15: 今の値 | AB15: 見直す頻度 | AH15: 誰が決める
B16: 劇場の規模と、ドリンクの提供方式 | J16: 定数マスタ | P16: ① 劇場マスタ | V16: =IF('設定（最初に1回）'!$C$10="","未設定",'設定（最初に1回）'!$C$10&" ／ "&'設定（最初に1回）'!$C$11) -> 大規模 ／ 1杯売り | AB16: 開店時・方式の変更時 | AH16: 本社・支配人
B17: 規模ごとの標準来場者数 | J17: 定数マスタ | P17: ② 規模区分 | V17: ='設定（最初に1回）'!$C$14 -> 3000 | AB17: 年1回 | AH17: 本社
B18: 安全在庫日数（何日ぶん余裕を持つか） | J18: 定数マスタ | P18: ② 規模区分 | V18: ='設定（最初に1回）'!$C$12 -> 4 | AB18: 年1回 | AH18: 本社
B19: 月ごとの繁閑（季節係数） | J19: 定数マスタ | P19: ③ 月別係数 | V19: ='設定（最初に1回）'!$C$15 -> 1.45 | AB19: 年1回 | AH19: 本社
B20: GW・大型作品公開などの特別期間 | J20: 定数マスタ | P20: ④ 特別期間 | V20: =COUNTIF(定数マスタ!$W$6:$W$25,"?*")&" 件 登録済み" -> 3 件 登録済み | AB20: 都度 | AH20: 支配人・副支配人
B21: 冷蔵庫・ストッカーの容量（常温／冷蔵／冷凍） | J21: 定数マスタ | P21: ⑤ 保管設備 | V21: =IF('設定（最初に1回）'!$C$4="","",TEXT(SUMIFS(定数マスタ!$G$110:$G$309,定数マスタ!$B$110:$B$309,'設定（最初に1回）'!$C$4,定数マスタ!$C$110:$C$309,"常温"),"#,##0")&" ／ "&TEXT(SUMIFS(定数マスタ!$G$110:$G$309,定数マスタ!$B$110:$B$309,'設定（最初に1回）'!$C$4,定数マスタ!$C$110:$C$309,"冷蔵"),"#,##0")&" ／ "&TEXT(SUMIFS(定数マスタ!$G$110:$G$309,定数マスタ!$B$110:$B$309,'設定（最初に1回）'!$C$4,定数マスタ!$C$110:$C$309,"冷凍"),"#,##0")&" ケース") -> 2,400 ／ 720 ／ 320 ケース | AB21: 設備の入れ替え時 | AH21: 支配人・副支配人
B22: 発注できる曜日（グループごと） | J22: 定数マスタ | P22: ⑥ 発注サイクル | V22: ="冷凍 "&IFERROR(INDEX(定数マスタ!$S$110:$S$119,MATCH("冷凍品",定数マスタ!$J$110:$J$119,0)),"")&"日 ／ 包材 "&IFERROR(INDEX(定数マスタ!$S$110:$S$119,MATCH("常温包材",定数マスタ!$J$110:$J$119,0)),"")&"日" -> 冷凍 2.3日 ／ 包材 7日 | AB22: 便が変わったとき | AH22: 本社
B23: 入数・単価・リードタイム・最低ロット | J23: 商品マスタ | P23: （商品ごと） | V23: =SUMPRODUCT(--(商品マスタ!$B$6:$B$1005<>""))&" 商品 登録済み" -> 132 商品 登録済み | AB23: 商品の入れ替え時 | AH23: 社員
B24: 商品の保管区分と発注グループ | J24: 商品マスタ | P24: （商品ごと） | V24: =SUMPRODUCT(--(商品マスタ!$L$6:$L$1005<>""))&" 商品 設定済み" -> 132 商品 設定済み | AB24: 商品の入れ替え時 | AH24: 社員
B25: PI値（来場者100人あたりの消費数） | J25: 商品マスタ | P25: （商品ごと） | V25: =IF('設定（最初に1回）'!$C$9="実績消費","使っていません",SUMPRODUCT(--(商品マスタ!$M$6:$M$1005<>""))&" 商品 設定済み") -> 使っていません | AB25: PI値を使うときだけ | AH25: 社員
B27: ※ 黄色いシート名が置き場所です。定数はこの2枚以外にはありません。②発注数を決めるシートや発注計算シートに、直接数字を書き込む必要はありません。
B29: 2. その定数から、発注数が出るまで
B30: 1商品を選ぶと、その商品の実際の数字で順番に追えます。空欄のままなら、いま一番多く発注が必要な商品を自動で表示します。
B31: 追いかける商品 | R31: ▼から選べます。選び直すと下の数字がすべて入れ替わります。 | AN31: =IF($F$31="",IFERROR(INDEX(発注計算!$D$6:$D$405,MATCH(MAX(発注計算!$AH$6:$AH$405),発注計算!$AH$6:$AH$405,0)),""),$F$31) -> Ｒｅｉｓｔポップコーン豆
AN32: =IFERROR(MATCH($AN$31,発注計算!$D$6:$D$405,0),0) -> 40
D33: 見ている数字 | O33: 値 | T33: どこから来た数字か
B34: 定数 | D34: 1日にどれだけ減るか | O34: =IF($AN$32=0,"",INDEX(発注計算!$S$6:$S$405,$AN$32)) -> 3.7868852 | T34: =IF('設定（最初に1回）'!$C$9="実績消費","①今日の在庫 と 月1回_前回の在庫 の差から計算","商品マスタ の PI値 × 随時_動員を入れる の来場者予測") -> ①今日の在庫 と 月1回_前回の在庫 の差から計算
B35: 定数 | D35: 届くまでの日数（リードタイム） | O35: =IF($AN$32=0,"",INDEX(発注計算!$I$6:$I$405,$AN$32)) -> 2 | T35: ="商品マスタ の L/T日数" -> 商品マスタ の L/T日数
B36: 定数 | D36: 次の発注までの日数（発注サイクル） | O36: =IF($AN$32=0,"",INDEX(発注計算!$AG$6:$AG$405,$AN$32)) -> 7 | T36: =IF($AN$32=0,"","定数マスタ ⑥発注サイクル グループ："&INDEX(発注計算!$AF$6:$AF$405,$AN$32)) -> 定数マスタ ⑥発注サイクル グループ：その他常温
B37: 定数 | D37: 切らさないための余裕（安全在庫） | O37: =IF($AN$32=0,"",INDEX(発注計算!$U$6:$U$405,$AN$32)) -> 16 | T37: ="定数マスタ ②規模区分 の安全在庫日数 "&TEXT('設定（最初に1回）'!$C$12,"0.0")&"日ぶん" -> 定数マスタ ②規模区分 の安全在庫日数 4.0日ぶん
B38: ＝ | D38: 持っておくべき数（発注点） | O38: =IF($AN$32=0,"",INDEX(発注計算!$V$6:$V$405,$AN$32)) -> 51 | T38: ="1日に減る数 ×（届くまで＋次の発注まで）＋ 安全在庫" -> 1日に減る数 ×（届くまで＋次の発注まで）＋ 安全在庫
B39: 在庫 | D39: いま在庫にある数 | O39: =IF($AN$32=0,"",INDEX(発注計算!$K$6:$K$405,$AN$32)) -> 9 | T39: ="①今日の在庫を貼る（CSVの総数）" -> ①今日の在庫を貼る（CSVの総数）
B40: 在庫 | D40: 発注済みで、まだ届いていない数 | O40: =IF($AN$32=0,"",INDEX(発注計算!$W$6:$W$405,$AN$32)) -> 0 | T40: ="発注管理 の 発注済み" -> 発注管理 の 発注済み
B41: ＝ | D41: 足りない数 | O41: =IF($AN$32=0,"",INDEX(発注計算!$X$6:$X$405,$AN$32)) -> 42 | T41: ="持っておくべき数 − いまの在庫 − 発注済み" -> 持っておくべき数 − いまの在庫 − 発注済み
B42: 発注 | D42: 1ケースに何個入っているか（入数） | O42: =IF($AN$32=0,"",INDEX(発注計算!$G$6:$G$405,$AN$32)) -> 1 | T42: ="商品マスタ の 入数" -> 商品マスタ の 入数
B43: ＝ | D43: 発注する数（ケース） | O43: =IF($AN$32=0,"",INDEX(発注計算!$Y$6:$Y$405,$AN$32)) -> 42 | T43: ="足りない数 ÷ 入数 を切り上げ。最低ロットの単位に丸めます" -> 足りない数 ÷ 入数 を切り上げ。最低ロットの単位に丸めます
B45: 同じことを図にすると | AN45: =IF($AN$32=0,0,N(INDEX(発注計算!$V$6:$V$405,$AN$32))) -> 51
B46: 帯全体が「持っておくべき数（発注点）」です。緑がいまの在庫、黄が発注済みで届く分、赤が足りていない分＝今日発注する分です。 | AN46: =IF($AN$32=0,0,MAX(0,N(INDEX(発注計算!$K$6:$K$405,$AN$32)))) -> 9
AN47: =IF($AN$32=0,0,N(INDEX(発注計算!$W$6:$W$405,$AN$32))) -> 0
B48: 1 | C48: 2 | D48: 3 | E48: 4 | F48: 5 | G48: 6 | H48: 7 | I48: 8 | J48: 9 | K48: 10 | L48: 11 | M48: 12 | N48: 13 | O48: 14 | P48: 15 | Q48: 16 | R48: 17 | S48: 18 | T48: 19 | U48: 20 | V48: 21 | W48: 22 | X48: 23 | Y48: 24 | Z48: 25 | AA48: 26 | AB48: 27 | AC48: 28 | AD48: 29 | AE48: 30 | AF48: 31 | AG48: 32 | AH48: 33 | AI48: 34 | AJ48: 35 | AK48: 36 | AN48: =IF($AN$45<=0,36,MIN(36,ROUND($AN$46/$AN$45*36,0))) -> 6
C49: いまの在庫 | K49: 発注済みで届く分 | S49: 今日発注する分 | Z49: 帯の右端 ＝ 持っておくべき数（発注点） | AN49: =IF($AN$45<=0,36,MIN(36,ROUND(($AN$46+$AN$47)/$AN$45*36,0))) -> 6
B51: よくある質問
B52: Q. 購買率やPI値は使わないのですか？
B53: A. 定数の考え方（＝持っておくべき数を決めて、差を発注する）で回すなら、ふだんは要りません。1日にどれだけ減るかは、在庫2時点の差＝実績から出しています。PI値を使うのは、過去の実績があてにならない週（大型作品の公開週、GWなど）だけです。設定シートの「算出基準」をPI値予測（または最大値）にすると切り替わります。
B56: Q. 発注できる曜日が商品によって違いますが？
B57: A. 定数マスタ ⑥発注サイクルにグループごとの曜日を入れてあります。冷凍品とドリンクシロップは週3回（月水金）、常温包材は木曜の1回だけです。週1回の商品は次の便まで7日あるため、そのぶん多めに持つ計算になります。
B60: Q. 在庫がマイナスになっています
B61: A. 納品がまだシステムに入っていない状態です。現物を数えて、在庫システム側を直してから貼り直してください。

Sheet ①今日の在庫を貼る
B2: 今日の在庫を貼る | H2: =IF(COUNTIF($B$6:$B$10005,'設定（最初に1回）'!$C$4)=0,"✖ まだ貼れていません","✔ "&COUNTIF($B$6:$B$10005,'設定（最初に1回）'!$C$4)&"行 読み込めました") -> ✔ 134行 読み込めました
B3: 在庫システムから出力した、今日の在庫一覧CSVです。これが理論在庫になります。 | H3: =IF(COUNTIF($B$6:$B$10005,'設定（最初に1回）'!$C$4)=0,"CSVの見出し行を除いたデータを A6 セルに貼り付けてください。貼ったのに0のままなら、劇場コードが数値になっています。","対象劇場：" & '設定（最初に1回）'!$C$4 & " " & '設定（最初に1回）'!$C$5) -> 対象劇場：0761 新宿
B4: CSVの見出し行を除いたデータを、A6 セルに貼り付けてください。
A5: 対象日付 | B5: 劇場コード | C5: 劇場名 | D5: 支払先コード | E5: 支払先名 | F5: 大分類コード | G5: 小分類コード | H5: 商品分類名 | I5: 商品コード | J5: 商品名 | K5: 入数 | L5: 在庫数ケース | M5: 在庫数バラ | N5: 総数 | O5: 規定数 | P5: 資産廃棄 | Q5: 税抜単価 | R5: 仕入税区分 | S5: 仕入税率 | U5: 連番(自動)
A6: 20260501 | B6: 0761 | C6: 新宿 | D6: 10400001 | E6: 株式会社 カクヤス | F6: 01 | G6: 04 | H6: アルコール | I6: 1812000008585 | J6: プレミアムモルツ ２０Ｌ | K6: 1 | L6: 4 | M6: 0 | N6: 4 | P6: 0 | Q6: 11300 | R6: 外税 | S6: 0.1 | U6: =IF($B6='設定（最初に1回）'!$C$4,N(U5)+1,N(U5)) -> 1
A7: 20260501 | B7: 0761 | C7: 新宿 | D7: 10400001 | E7: 株式会社 カクヤス | F7: 01 | G7: 04 | H7: アルコール | I7: 1812000010991 | J7: ミオネット ベビーボトル２００ｍ | K7: 24 | L7: 0 | M7: 0 | N7: 0 | P7: 0 | Q7: 587 | R7: 外税 | S7: 0.1 | U7: =IF($B7='設定（最初に1回）'!$C$4,N(U6)+1,N(U6)) -> 2
A8: 20260501 | B8: 0761 | C8: 新宿 | D8: 10400001 | E8: 株式会社 カクヤス | F8: 01 | G8: 04 | H8: アルコール | I8: 1812000011745 | J8: フォルタン リトラル 赤 | K8: 48 | L8: 0 | M8: 10 | N8: 10 | P8: 0 | Q8: 357 | R8: 外税 | S8: 0.1 | U8: =IF($B8='設定（最初に1回）'!$C$4,N(U7)+1,N(U7)) -> 3
A9: 20260501 | B9: 0761 | C9: 新宿 | D9: 10400001 | E9: 株式会社 カクヤス | F9: 01 | G9: 04 | H9: アルコール | I9: 1812000011752 | J9: フォルタン リトラル 白 | K9: 48 | L9: 0 | M9: 3 | N9: 3 | P9: 0 | Q9: 357 | R9: 外税 | S9: 0.1 | U9: =IF($B9='設定（最初に1回）'!$C$4,N(U8)+1,N(U8)) -> 4
A10: 20260501 | B10: 0761 | C10: 新宿 | D10: 10400001 | E10: 株式会社 カクヤス | F10: 01 | G10: 04 | H10: アルコール | I10: 1812000013343 | J10: フレシネコルドンネグロ２００ｍｌ | K10: 24 | L10: 2 | M10: 19 | N10: 67 | P10: 0 | Q10: 585 | R10: 外税 | S10: 0.1 | U10: =IF($B10='設定（最初に1回）'!$C$4,N(U9)+1,N(U9)) -> 5
A11: 20260501 | B11: 0761 | C11: 新宿 | D11: 10400001 | E11: 株式会社 カクヤス | F11: 01 | G11: 04 | H11: アルコール | I11: 1813000187270 | J11: サントリー角ハイボール | K11: 30 | L11: 6 | M11: 2 | N11: 182 | P11: 0 | Q11: 118 | R11: 外税 | S11: 0.1 | U11: =IF($B11='設定（最初に1回）'!$C$4,N(U10)+1,N(U10)) -> 6
A12: 20260501 | B12: 0761 | C12: 新宿 | D12: 19903001 | E12: オザックス株式会社 | F12: 01 | G12: 01 | H12: コールド | I12: 1812000000237 | J12: アイスティシロップ | K12: 1 | L12: 2 | M12: 0 | N12: 2 | P12: 0 | Q12: 3756 | R12: 外税 | S12: 0.08 | U12: =IF($B12='設定（最初に1回）'!$C$4,N(U11)+1,N(U11)) -> 7
A13: 20260501 | B13: 0761 | C13: 新宿 | D13: 19903001 | E13: オザックス株式会社 | F13: 01 | G13: 01 | H13: コールド | I13: 1812000000251 | J13: 烏龍茶１０倍シロップ | K13: 1 | L13: 2 | M13: 0 | N13: 2 | P13: 0 | Q13: 4382 | R13: 外税 | S13: 0.08 | U13: =IF($B13='設定（最初に1回）'!$C$4,N(U12)+1,N(U12)) -> 8
A14: 20260501 | B14: 0761 | C14: 新宿 | D14: 19903001 | E14: オザックス株式会社 | F14: 01 | G14: 01 | H14: コールド | I14: 1812000007441 | J14: ミニッツメイドオレンジＦＫＡ | K14: 1 | L14: 0 | M14: 0 | N14: 0 | P14: 0 | Q14: 2890 | R14: 外税 | S14: 0.08 | U14: =IF($B14='設定（最初に1回）'!$C$4,N(U13)+1,N(U13)) -> 9
A15: 20260501 | B15: 0761 | C15: 新宿 | D15: 19903001 | E15: オザックス株式会社 | F15: 01 | G15: 01 | H15: コールド | I15: 1812000013169 | J15: ミニッツメイドアップル | K15: 1 | L15: 2 | M15: 0 | N15: 2 | P15: 0 | Q15: 3636 | R15: 外税 | S15: 0.08 | U15: =IF($B15='設定（最初に1回）'!$C$4,N(U14)+1,N(U14)) -> 10
A16: 20260501 | B16: 0761 | C16: 新宿 | D16: 19903001 | E16: オザックス株式会社 | F16: 01 | G16: 01 | H16: コールド | I16: 4902102081283 | J16: ＰＸＴ爽健美茶１Ｇ | K16: 1 | L16: 73 | M16: 0 | N16: 73 | P16: 0 | Q16: 3756 | R16: 外税 | S16: 0.08 | U16: =IF($B16='設定（最初に1回）'!$C$4,N(U15)+1,N(U15)) -> 11
A17: 20260501 | B17: 0761 | C17: 新宿 | D17: 19903001 | E17: オザックス株式会社 | F17: 01 | G17: 01 | H17: コールド | I17: 4902102112901 | J17: フラットＢＩＢメロンＳ２．５Ｇ | K17: 1 | L17: 83 | M17: 0 | N17: 83 | P17: 0 | Q17: 7510 | R17: 外税 | S17: 0.08 | U17: =IF($B17='設定（最初に1回）'!$C$4,N(U16)+1,N(U16)) -> 12
... A310: 20260501 | B310: 0902 | C310: 郊外シネマ | D310: 10400001 | E310: 株式会社 カクヤス | F310: 01 | G310: 04 | H310: アルコール | I310: 9809020000002 | J310: （新商品）コラボカップ | K310: 1 | L310: 65 | M310: 0 | N310: 65 | P310: 0 | Q310: 118 | R310: 外税 | S310: 0.1 | U310: =IF($B310='設定（最初に1回）'!$C$4,N(U309)+1,N(U309)) -> 134
U311: =IF($B311='設定（最初に1回）'!$C$4,N(U310)+1,N(U310)) -> 134
U312: =IF($B312='設定（最初に1回）'!$C$4,N(U311)+1,N(U311)) -> 134
U313: =IF($B313='設定（最初に1回）'!$C$4,N(U312)+1,N(U312)) -> 134
U314: =IF($B314='設定（最初に1回）'!$C$4,N(U313)+1,N(U313)) -> 134
U315: =IF($B315='設定（最初に1回）'!$C$4,N(U314)+1,N(U314)) -> 134
U316: =IF($B316='設定（最初に1回）'!$C$4,N(U315)+1,N(U315)) -> 134
U317: =IF($B317='設定（最初に1回）'!$C$4,N(U316)+1,N(U316)) -> 134
U318: =IF($B318='設定（最初に1回）'!$C$4,N(U317)+1,N(U317)) -> 134
U319: =IF($B319='設定（最初に1回）'!$C$4,N(U318)+1,N(U318)) -> 134
U320: =IF($B320='設定（最初に1回）'!$C$4,N(U319)+1,N(U319)) -> 134
U321: =IF($B321='設定（最初に1回）'!$C$4,N(U320)+1,N(U320)) -> 134
U322: =IF($B322='設定（最初に1回）'!$C$4,N(U321)+1,N(U321)) -> 134
... U10005: =IF($B10005='設定（最初に1回）'!$C$4,N(U10004)+1,N(U10004)) -> 134

Sheet ②発注数を決める
B2: タイムテーブル
B4: 今日の結論 | G4: 発注予定額（税抜） | L4: 保管スペースの埋まり具合（今の在庫＋発注ぶん ÷ 収容ケース数）
B5: =COUNTIF(②発注数を決める!$G$10:$G$409,"今日が期限")+COUNTIF(②発注数を決める!$G$10:$G$409,"要発注") -> 45 | D5: 品目に発注が必要です | G5: =SUM(②発注数を決める!$K$10:$K$409) -> 158719 | L5: 常温 | P5: 冷蔵 | T5: 冷凍
L6: =IF(IFERROR(INDEX(定数マスタ!$I$6:$I$105,MATCH('設定（最初に1回）'!$C$4,定数マスタ!$B$6:$B$105,0)),0)=0,"収容未設定",(SUMIF(発注計算!$AD$6:$AD$405,"常温",発注計算!$AE$6:$AE$405)+SUMIF(発注計算!$AD$6:$AD$405,"常温",②発注数を決める!$J$10:$J$409))/IFERROR(INDEX(定数マスタ!$I$6:$I$105,MATCH('設定（最初に1回）'!$C$4,定数マスタ!$B$6:$B$105,0)),0)) -> 0.67458333 | P6: =IF(IFERROR(INDEX(定数マスタ!$J$6:$J$105,MATCH('設定（最初に1回）'!$C$4,定数マスタ!$B$6:$B$105,0)),0)=0,"収容未設定",(SUMIF(発注計算!$AD$6:$AD$405,"冷蔵",発注計算!$AE$6:$AE$405)+SUMIF(発注計算!$AD$6:$AD$405,"冷蔵",②発注数を決める!$J$10:$J$409))/IFERROR(INDEX(定数マスタ!$J$6:$J$105,MATCH('設定（最初に1回）'!$C$4,定数マスタ!$B$6:$B$105,0)),0)) -> 0.71805556 | T6: =IF(IFERROR(INDEX(定数マスタ!$K$6:$K$105,MATCH('設定（最初に1回）'!$C$4,定数マスタ!$B$6:$B$105,0)),0)=0,"収容未設定",(SUMIF(発注計算!$AD$6:$AD$405,"冷凍",発注計算!$AE$6:$AE$405)+SUMIF(発注計算!$AD$6:$AD$405,"冷凍",②発注数を決める!$J$10:$J$409))/IFERROR(INDEX(定数マスタ!$K$6:$K$105,MATCH('設定（最初に1回）'!$C$4,定数マスタ!$B$6:$B$105,0)),0)) -> 0.915625
B7: =IF($B$5=0,"すべての商品が発注サイクルを越える在庫を持っています。","うち "&COUNTIF(②発注数を決める!$G$10:$G$409,"今日が期限")&"品目は今日発注しないとリードタイムに間に合いません。 "&COUNTIF(②発注数を決める!$G$10:$G$409,"要発注")&"品目は次の発注サイクル（"&'設定（最初に1回）'!$C$13&"日）内に在庫が切れます。") -> うち 36品目は今日発注しないとリードタイムに間に合いません。 9品目は次の発注サイクル（7日）内に在庫が切れます。 | L7: =IF(IFERROR(INDEX(定数マスタ!$I$6:$I$105,MATCH('設定（最初に1回）'!$C$4,定数マスタ!$B$6:$B$105,0)),0)=0,"定数マスタ⑤に設備を登録してください",(SUMIF(発注計算!$AD$6:$AD$405,"常温",発注計算!$AE$6:$AE$405)+SUMIF(発注計算!$AD$6:$AD$405,"常温",②発注数を決める!$J$10:$J$409))&" / "&IFERROR(INDEX(定数マスタ!$I$6:$I$105,MATCH('設定（最初に1回）'!$C$4,定数マスタ!$B$6:$B$105,0)),0)&"ケース") -> 1619 / 2400ケース | P7: =IF(IFERROR(INDEX(定数マスタ!$J$6:$J$105,MATCH('設定（最初に1回）'!$C$4,定数マスタ!$B$6:$B$105,0)),0)=0,"定数マスタ⑤に設備を登録してください",(SUMIF(発注計算!$AD$6:$AD$405,"冷蔵",発注計算!$AE$6:$AE$405)+SUMIF(発注計算!$AD$6:$AD$405,"冷蔵",②発注数を決める!$J$10:$J$409))&" / "&IFERROR(INDEX(定数マスタ!$J$6:$J$105,MATCH('設定（最初に1回）'!$C$4,定数マスタ!$B$6:$B$105,0)),0)&"ケース") -> 517 / 720ケース | T7: =IF(IFERROR(INDEX(定数マスタ!$K$6:$K$105,MATCH('設定（最初に1回）'!$C$4,定数マスタ!$B$6:$B$105,0)),0)=0,"定数マスタ⑤に設備を登録してください",(SUMIF(発注計算!$AD$6:$AD$405,"冷凍",発注計算!$AE$6:$AE$405)+SUMIF(発注計算!$AD$6:$AD$405,"冷凍",②発注数を決める!$J$10:$J$409))&" / "&IFERROR(INDEX(定数マスタ!$K$6:$K$105,MATCH('設定（最初に1回）'!$C$4,定数マスタ!$B$6:$B$105,0)),0)&"ケース") -> 293 / 320ケース
B8: 自動 | C8: 自動 | D8: 自動 | E8: 自動 | F8: 自動 | G8: 自動 | H8: 自動 | I8: 自動 | J8: 入力 | K8: 自動 | L8: 1 | M8: 2 | N8: 3 | O8: 4 | P8: 5 | Q8: 6 | R8: 7 | S8: 8 | T8: 9 | U8: 10 | V8: 11 | W8: 12 | X8: 13 | Y8: 14
B9: No | C9: 商品名 | D9: 分類 | E9: 残り日数 | F9: デッドライン | G9: 状態 | H9: 発注後日数 | I9: 推奨(ケース) | J9: 発注数 | K9: 金額 | L9: =IF('設定（最初に1回）'!$C$6="","",'設定（最初に1回）'!$C$6+0) -> 46143 | M9: =IF('設定（最初に1回）'!$C$6="","",'設定（最初に1回）'!$C$6+1) -> 46144 | N9: =IF('設定（最初に1回）'!$C$6="","",'設定（最初に1回）'!$C$6+2) -> 46145 | O9: =IF('設定（最初に1回）'!$C$6="","",'設定（最初に1回）'!$C$6+3) -> 46146 | P9: =IF('設定（最初に1回）'!$C$6="","",'設定（最初に1回）'!$C$6+4) -> 46147 | Q9: =IF('設定（最初に1回）'!$C$6="","",'設定（最初に1回）'!$C$6+5) -> 46148 | R9: =IF('設定（最初に1回）'!$C$6="","",'設定（最初に1回）'!$C$6+6) -> 46149 | S9: =IF('設定（最初に1回）'!$C$6="","",'設定（最初に1回）'!$C$6+7) -> 46150 | T9: =IF('設定（最初に1回）'!$C$6="","",'設定（最初に1回）'!$C$6+8) -> 46151 | U9: =IF('設定（最初に1回）'!$C$6="","",'設定（最初に1回）'!$C$6+9) -> 46152 | V9: =IF('設定（最初に1回）'!$C$6="","",'設定（最初に1回）'!$C$6+10) -> 46153 | W9: =IF('設定（最初に1回）'!$C$6="","",'設定（最初に1回）'!$C$6+11) -> 46154 | X9: =IF('設定（最初に1回）'!$C$6="","",'設定（最初に1回）'!$C$6+12) -> 46155 | Y9: =IF('設定（最初に1回）'!$C$6="","",'設定（最初に1回）'!$C$6+13) -> 46156 | Z9: 発注書用
B10: 1 | C10: =IF(発注計算!$C6="","",発注計算!$D6) -> プレミアムモルツ ２０Ｌ | D10: =IF(発注計算!$C6="","",発注計算!$E6) -> アルコール | E10: =IF(発注計算!$C6="","",発注計算!$T6) -> 2.3461538 | F10: =IF(ISNUMBER($E10),$E10-N(発注計算!$I6),"") -> 0.34615385 | G10: =IF(発注計算!$C6="","",IF(NOT(ISNUMBER($F10)),"データなし",IF($F10<=0,"今日が期限",IF($F10<=N(発注計算!$AG6),"要発注","余裕")))) -> 要発注 | H10: =IF(OR(発注計算!$C6="",NOT(ISNUMBER(発注計算!$S6)),発注計算!$S6<=0),"",(発注計算!$K6+N($J10)*N(発注計算!$G6))/発注計算!$S6) -> 5.8653846 | I10: =IF(発注計算!$C6="","",発注計算!$Y6) -> 19 | J10: 6 | K10: =IF($J10="","",N($J10)*N(発注計算!$H6)) -> 67800 | Z10: =IF(OR(N($J10)<=0,AND(③発注書!$C$5<>"すべて",発注計算!$F6<>③発注書!$C$5)),N(Z9),N(Z9)+1) -> 1
B11: 2 | C11: =IF(発注計算!$C7="","",発注計算!$D7) -> ミオネット ベビーボトル２００ｍ | D11: =IF(発注計算!$C7="","",発注計算!$E7) -> アルコール | E11: =IF(発注計算!$C7="","",発注計算!$T7) -> 0 | F11: =IF(ISNUMBER($E11),$E11-N(発注計算!$I7),"") -> -3 | G11: =IF(発注計算!$C7="","",IF(NOT(ISNUMBER($F11)),"データなし",IF($F11<=0,"今日が期限",IF($F11<=N(発注計算!$AG7),"要発注","余裕")))) -> 今日が期限 | H11: =IF(OR(発注計算!$C7="",NOT(ISNUMBER(発注計算!$S7)),発注計算!$S7<=0),"",(発注計算!$K7+N($J11)*N(発注計算!$G7))/発注計算!$S7) -> 2196 | I11: =IF(発注計算!$C7="","",発注計算!$Y7) -> 1 | J11: 3 | K11: =IF($J11="","",N($J11)*N(発注計算!$H7)) -> 1761 | Z11: =IF(OR(N($J11)<=0,AND(③発注書!$C$5<>"すべて",発注計算!$F7<>③発注書!$C$5)),N(Z10),N(Z10)+1) -> 2
B12: 3 | C12: =IF(発注計算!$C8="","",発注計算!$D8) -> フォルタン リトラル 赤 | D12: =IF(発注計算!$C8="","",発注計算!$E8) -> アルコール | E12: =IF(発注計算!$C8="","",発注計算!$T8) -> 13.863636 | F12: =IF(ISNUMBER($E12),$E12-N(発注計算!$I8),"") -> 10.863636 | G12: =IF(発注計算!$C8="","",IF(NOT(ISNUMBER($F12)),"データなし",IF($F12<=0,"今日が期限",IF($F12<=N(発注計算!$AG8),"要発注","余裕")))) -> 余裕 | H12: =IF(OR(発注計算!$C8="",NOT(ISNUMBER(発注計算!$S8)),発注計算!$S8<=0),"",(発注計算!$K8+N($J12)*N(発注計算!$G8))/発注計算!$S8) -> 679.31818 | I12: =IF(発注計算!$C8="","",発注計算!$Y8) -> 5 | J12: 10 | K12: =IF($J12="","",N($J12)*N(発注計算!$H8)) -> 3570 | Z12: =IF(OR(N($J12)<=0,AND(③発注書!$C$5<>"すべて",発注計算!$F8<>③発注書!$C$5)),N(Z11),N(Z11)+1) -> 3
B13: 4 | C13: =IF(発注計算!$C9="","",発注計算!$D9) -> フォルタン リトラル 白 | D13: =IF(発注計算!$C9="","",発注計算!$E9) -> アルコール | E13: =IF(発注計算!$C9="","",発注計算!$T9) -> 2.3461538 | F13: =IF(ISNUMBER($E13),$E13-N(発注計算!$I9),"") -> -0.65384615 | G13: =IF(発注計算!$C9="","",IF(NOT(ISNUMBER($F13)),"データなし",IF($F13<=0,"今日が期限",IF($F13<=N(発注計算!$AG9),"要発注","余裕")))) -> 今日が期限 | H13: =IF(OR(発注計算!$C9="",NOT(ISNUMBER(発注計算!$S9)),発注計算!$S9<=0),"",(発注計算!$K9+N($J13)*N(発注計算!$G9))/発注計算!$S9) -> 2.3461538 | I13: =IF(発注計算!$C9="","",発注計算!$Y9) -> 2 | K13: =IF($J13="","",N($J13)*N(発注計算!$H9)) | Z13: =IF(OR(N($J13)<=0,AND(③発注書!$C$5<>"すべて",発注計算!$F9<>③発注書!$C$5)),N(Z12),N(Z12)+1) -> 3
B14: 5 | C14: =IF(発注計算!$C10="","",発注計算!$D10) -> フレシネコルドンネグロ２００ｍｌ | D14: =IF(発注計算!$C10="","",発注計算!$E10) -> アルコール | E14: =IF(発注計算!$C10="","",発注計算!$T10) -> 20.232673 | F14: =IF(ISNUMBER($E14),$E14-N(発注計算!$I10),"") -> 16.232673 | G14: =IF(発注計算!$C10="","",IF(NOT(ISNUMBER($F14)),"データなし",IF($F14<=0,"今日が期限",IF($F14<=N(発注計算!$AG10),"要発注","余裕")))) -> 余裕 | H14: =IF(OR(発注計算!$C10="",NOT(ISNUMBER(発注計算!$S10)),発注計算!$S10<=0),"",(発注計算!$K10+N($J14)*N(発注計算!$G10))/発注計算!$S10) -> 49.222772 | I14: =IF(発注計算!$C10="","",発注計算!$Y10) -> 0 | J14: 4 | K14: =IF($J14="","",N($J14)*N(発注計算!$H10)) -> 2340 | Z14: =IF(OR(N($J14)<=0,AND(③発注書!$C$5<>"すべて",発注計算!$F10<>③発注書!$C$5)),N(Z13),N(Z13)+1) -> 4
B15: 6 | C15: =IF(発注計算!$C11="","",発注計算!$D11) -> サントリー角ハイボール | D15: =IF(発注計算!$C11="","",発注計算!$E11) -> アルコール | E15: =IF(発注計算!$C11="","",発注計算!$T11) -> 10.644295 | F15: =IF(ISNUMBER($E15),$E15-N(発注計算!$I11),"") -> 7.6442953 | G15: =IF(発注計算!$C11="","",IF(NOT(ISNUMBER($F15)),"データなし",IF($F15<=0,"今日が期限",IF($F15<=N(発注計算!$AG11),"要発注","余裕")))) -> 余裕 | H15: =IF(OR(発注計算!$C11="",NOT(ISNUMBER(発注計算!$S11)),発注計算!$S11<=0),"",(発注計算!$K11+N($J15)*N(発注計算!$G11))/発注計算!$S11) -> 10.644295 | I15: =IF(発注計算!$C11="","",発注計算!$Y11) -> 2 | K15: =IF($J15="","",N($J15)*N(発注計算!$H11)) | Z15: =IF(OR(N($J15)<=0,AND(③発注書!$C$5<>"すべて",発注計算!$F11<>③発注書!$C$5)),N(Z14),N(Z14)+1) -> 4
B16: 7 | C16: =IF(発注計算!$C12="","",発注計算!$D12) -> アイスティシロップ | D16: =IF(発注計算!$C12="","",発注計算!$E12) -> コールド | E16: =IF(発注計算!$C12="","",発注計算!$T12) -> 1.2708333 | F16: =IF(ISNUMBER($E16),$E16-N(発注計算!$I12),"") -> -0.72916667 | G16: =IF(発注計算!$C12="","",IF(NOT(ISNUMBER($F16)),"データなし",IF($F16<=0,"今日が期限",IF($F16<=N(発注計算!$AG12),"要発注","余裕")))) -> 今日が期限 | H16: =IF(OR(発注計算!$C12="",NOT(ISNUMBER(発注計算!$S12)),発注計算!$S12<=0),"",(発注計算!$K12+N($J16)*N(発注計算!$G12))/発注計算!$S12) -> 1.2708333 | I16: =IF(発注計算!$C12="","",発注計算!$Y12) -> 12 | K16: =IF($J16="","",N($J16)*N(発注計算!$H12)) | Z16: =IF(OR(N($J16)<=0,AND(③発注書!$C$5<>"すべて",発注計算!$F12<>③発注書!$C$5)),N(Z15),N(Z15)+1) -> 4
B17: 8 | C17: =IF(発注計算!$C13="","",発注計算!$D13) -> 烏龍茶１０倍シロップ | D17: =IF(発注計算!$C13="","",発注計算!$E13) -> コールド | E17: =IF(発注計算!$C13="","",発注計算!$T13) -> 1.7941176 | F17: =IF(ISNUMBER($E17),$E17-N(発注計算!$I13),"") -> -3.2058824 | G17: =IF(発注計算!$C13="","",IF(NOT(ISNUMBER($F17)),"データなし",IF($F17<=0,"今日が期限",IF($F17<=N(発注計算!$AG13),"要発注","余裕")))) -> 今日が期限 | H17: =IF(OR(発注計算!$C13="",NOT(ISNUMBER(発注計算!$S13)),発注計算!$S13<=0),"",(発注計算!$K13+N($J17)*N(発注計算!$G13))/発注計算!$S13) -> 8.9705882 | I17: =IF(発注計算!$C13="","",発注計算!$Y13) -> 12 | J17: 8 | K17: =IF($J17="","",N($J17)*N(発注計算!$H13)) -> 35056 | Z17: =IF(OR(N($J17)<=0,AND(③発注書!$C$5<>"すべて",発注計算!$F13<>③発注書!$C$5)),N(Z16),N(Z16)+1) -> 5
B18: 9 | C18: =IF(発注計算!$C14="","",発注計算!$D14) -> ミニッツメイドオレンジＦＫＡ | D18: =IF(発注計算!$C14="","",発注計算!$E14) -> コールド | E18: =IF(発注計算!$C14="","",発注計算!$T14) -> 0 | F18: =IF(ISNUMBER($E18),$E18-N(発注計算!$I14),"") -> -3 | G18: =IF(発注計算!$C14="","",IF(NOT(ISNUMBER($F18)),"データなし",IF($F18<=0,"今日が期限",IF($F18<=N(発注計算!$AG14),"要発注","余裕")))) -> 今日が期限 | H18: =IF(OR(発注計算!$C14="",NOT(ISNUMBER(発注計算!$S14)),発注計算!$S14<=0),"",(発注計算!$K14+N($J18)*N(発注計算!$G14))/発注計算!$S14) -> 0 | I18: =IF(発注計算!$C14="","",発注計算!$Y14) -> 2 | K18: =IF($J18="","",N($J18)*N(発注計算!$H14)) | Z18: =IF(OR(N($J18)<=0,AND(③発注書!$C$5<>"すべて",発注計算!$F14<>③発注書!$C$5)),N(Z17),N(Z17)+1) -> 5
B19: 10 | C19: =IF(発注計算!$C15="","",発注計算!$D15) -> ミニッツメイドアップル | D19: =IF(発注計算!$C15="","",発注計算!$E15) -> コールド | E19: =IF(発注計算!$C15="","",発注計算!$T15) -> 61 | F19: =IF(ISNUMBER($E19),$E19-N(発注計算!$I15),"") -> 58 | G19: =IF(発注計算!$C15="","",IF(NOT(ISNUMBER($F19)),"データなし",IF($F19<=0,"今日が期限",IF($F19<=N(発注計算!$AG15),"要発注","余裕")))) -> 余裕 | H19: =IF(OR(発注計算!$C15="",NOT(ISNUMBER(発注計算!$S15)),発注計算!$S15<=0),"",(発注計算!$K15+N($J19)*N(発注計算!$G15))/発注計算!$S15) -> 61 | I19: =IF(発注計算!$C15="","",発注計算!$Y15) -> 0 | K19: =IF($J19="","",N($J19)*N(発注計算!$H15)) | Z19: =IF(OR(N($J19)<=0,AND(③発注書!$C$5<>"すべて",発注計算!$F15<>③発注書!$C$5)),N(Z18),N(Z18)+1) -> 5
B20: 11 | C20: =IF(発注計算!$C16="","",発注計算!$D16) -> ＰＸＴ爽健美茶１Ｇ | D20: =IF(発注計算!$C16="","",発注計算!$E16) -> コールド | E20: =IF(発注計算!$C16="","",発注計算!$T16) -> 42.409524 | F20: =IF(ISNUMBER($E20),$E20-N(発注計算!$I16),"") -> 37.409524 | G20: =IF(発注計算!$C16="","",IF(NOT(ISNUMBER($F20)),"データなし",IF($F20<=0,"今日が期限",IF($F20<=N(発注計算!$AG16),"要発注","余裕")))) -> 余裕 | H20: =IF(OR(発注計算!$C16="",NOT(ISNUMBER(発注計算!$S16)),発注計算!$S16<=0),"",(発注計算!$K16+N($J20)*N(発注計算!$G16))/発注計算!$S16) -> 43.571429 | I20: =IF(発注計算!$C16="","",発注計算!$Y16) -> 0 | J20: 2 | K20: =IF($J20="","",N($J20)*N(発注計算!$H16)) -> 7512 | Z20: =IF(OR(N($J20)<=0,AND(③発注書!$C$5<>"すべて",発注計算!$F16<>③発注書!$C$5)),N(Z19),N(Z19)+1) -> 6
B21: 12 | C21: =IF(発注計算!$C17="","",発注計算!$D17) -> フラットＢＩＢメロンＳ２．５Ｇ | D21: =IF(発注計算!$C17="","",発注計算!$E17) -> コールド | E21: =IF(発注計算!$C17="","",発注計算!$T17) -> 120.54762 | F21: =IF(ISNUMBER($E21),$E21-N(発注計算!$I17),"") -> 113.54762 | G21: =IF(発注計算!$C17="","",IF(NOT(ISNUMBER($F21)),"データなし",IF($F21<=0,"今日が期限",IF($F21<=N(発注計算!$AG17),"要発注","余裕")))) -> 余裕 | H21: =IF(OR(発注計算!$C17="",NOT(ISNUMBER(発注計算!$S17)),発注計算!$S17<=0),"",(発注計算!$K17+N($J21)*N(発注計算!$G17))/発注計算!$S17) -> 120.54762 | I21: =IF(発注計算!$C17="","",発注計算!$Y17) -> 0 | K21: =IF($J21="","",N($J21)*N(発注計算!$H17)) | Z21: =IF(OR(N($J21)<=0,AND(③発注書!$C$5<>"すべて",発注計算!$F17<>③発注書!$C$5)),N(Z20),N(Z20)+1) -> 6
B22: 13 | C22: =IF(発注計算!$C18="","",発注計算!$D18) -> フラットＢＩＢコカコーラ２．５Ｇ | D22: =IF(発注計算!$C18="","",発注計算!$E18) -> コールド | E22: =IF(発注計算!$C18="","",発注計算!$T18) -> 76.604651 | F22: =IF(ISNUMBER($E22),$E22-N(発注計算!$I18),"") -> 72.604651 | G22: =IF(発注計算!$C18="","",IF(NOT(ISNUMBER($F22)),"データなし",IF($F22<=0,"今日が期限",IF($F22<=N(発注計算!$AG18),"要発注","余裕")))) -> 余裕 | H22: =IF(OR(発注計算!$C18="",NOT(ISNUMBER(発注計算!$S18)),発注計算!$S18<=0),"",(発注計算!$K18+N($J22)*N(発注計算!$G18))/発注計算!$S18) -> 76.604651 | I22: =IF(発注計算!$C18="","",発注計算!$Y18) -> 0 | K22: =IF($J22="","",N($J22)*N(発注計算!$H18)) | Z22: =IF(OR(N($J22)<=0,AND(③発注書!$C$5<>"すべて",発注計算!$F18<>③発注書!$C$5)),N(Z21),N(Z21)+1) -> 6
B23: 14 | C23: =IF(発注計算!$C19="","",発注計算!$D19) -> フラットＢＩＢコーラゼロ２．５Ｇ | D23: =IF(発注計算!$C19="","",発注計算!$E19) -> コールド | E23: =IF(発注計算!$C19="","",発注計算!$T19) -> 123.96774 | F23: =IF(ISNUMBER($E23),$E23-N(発注計算!$I19),"") -> 121.96774 | G23: =IF(発注計算!$C19="","",IF(NOT(ISNUMBER($F23)),"データなし",IF($F23<=0,"今日が期限",IF($F23<=N(発注計算!$AG19),"要発注","余裕")))) -> 余裕 | H23: =IF(OR(発注計算!$C19="",NOT(ISNUMBER(発注計算!$S19)),発注計算!$S19<=0),"",(発注計算!$K19+N($J23)*N(発注計算!$G19))/発注計算!$S19) -> 133.80645 | I23: =IF(発注計算!$C19="","",発注計算!$Y19) -> 0 | J23: 5 | K23: =IF($J23="","",N($J23)*N(発注計算!$H19)) -> 40680 | Z23: =IF(OR(N($J23)<=0,AND(③発注書!$C$5<>"すべて",発注計算!$F19<>③発注書!$C$5)),N(Z22),N(Z22)+1) -> 7
B24: 15 | C24: =IF(発注計算!$C20="","",発注計算!$D20) -> フラットＢＩＢジンジャー２．５Ｇ | D24: =IF(発注計算!$C20="","",発注計算!$E20) -> コールド | E24: =IF(発注計算!$C20="","",発注計算!$T20) -> 24.206349 | F24: =IF(ISNUMBER($E24),$E24-N(発注計算!$I20),"") -> 17.206349 | G24: =IF(発注計算!$C20="","",IF(NOT(ISNUMBER($F24)),"データなし",IF($F24<=0,"今日が期限",IF($F24<=N(発注計算!$AG20),"要発注","余裕")))) -> 余裕 | H24: =IF(OR(発注計算!$C20="",NOT(ISNUMBER(発注計算!$S20)),発注計算!$S20<=0),"",(発注計算!$K20+N($J24)*N(発注計算!$G20))/発注計算!$S20) -> 24.206349 | I24: =IF(発注計算!$C20="","",発注計算!$Y20) -> 0 | K24: =IF($J24="","",N($J24)*N(発注計算!$H20)) | Z24: =IF(OR(N($J24)<=0,AND(③発注書!$C$5<>"すべて",発注計算!$F20<>③発注書!$C$5)),N(Z23),N(Z23)+1) -> 7
B25: 16 | C25: =IF(発注計算!$C21="","",発注計算!$D21) -> フラットＢＩＢスプライト２．５Ｇ | D25: =IF(発注計算!$C21="","",発注計算!$E21) -> コールド | E25: =IF(発注計算!$C21="","",発注計算!$T21) -> 0.66304348 | F25: =IF(ISNUMBER($E25),$E25-N(発注計算!$I21),"") -> -6.3369565 | G25: =IF(発注計算!$C21="","",IF(NOT(ISNUMBER($F25)),"データなし",IF($F25<=0,"今日が期限",IF($F25<=N(発注計算!$AG21),"要発注","余裕")))) -> 今日が期限 | H25: =IF(OR(発注計算!$C21="",NOT(ISNUMBER(発注計算!$S21)),発注計算!$S21<=0),"",(発注計算!$K21+N($J25)*N(発注計算!$G21))/発注計算!$S21) -> 0.66304348 | I25: =IF(発注計算!$C21="","",発注計算!$Y21) -> 21 | K25: =IF($J25="","",N($J25)*N(発注計算!$H21)) | Z25: =IF(OR(N($J25)<=0,AND(③発注書!$C$5<>"すべて",発注計算!$F21<>③発注書!$C$5)),N(Z24),N(Z24)+1) -> 7
B26: 17 | C26: =IF(発注計算!$C22="","",発注計算!$D22) -> フラットＢＩＢカルピス２．５Ｇ | D26: =IF(発注計算!$C22="","",発注計算!$E22) -> コールド | E26: =IF(発注計算!$C22="","",発注計算!$T22) -> 3.2972973 | F26: =IF(ISNUMBER($E26),$E26-N(発注計算!$I22),"") -> -1.7027027 | G26: =IF(発注計算!$C22="","",IF(NOT(ISNUMBER($F26)),"データなし",IF($F26<=0,"今日が期限",IF($F26<=N(発注計算!$AG22),"要発注","余裕")))) -> 今日が期限 | H26: =IF(OR(発注計算!$C22="",NOT(ISNUMBER(発注計算!$S22)),発注計算!$S22<=0),"",(発注計算!$K22+N($J26)*N(発注計算!$G22))/発注計算!$S22) -> 3.2972973 | I26: =IF(発注計算!$C22="","",発注計算!$Y22) -> 6 | K26: =IF($J26="","",N($J26)*N(発注計算!$H22)) | Z26: =IF(OR(N($J26)<=0,AND(③発注書!$C$5<>"すべて",発注計算!$F22<>③発注書!$C$5)),N(Z25),N(Z25)+1) -> 7
B27: 18 | C27: =IF(発注計算!$C23="","",発注計算!$D23) -> （コスタ）新コーヒー豆 | D27: =IF(発注計算!$C23="","",発注計算!$E23) -> コーヒー | E27: =IF(発注計算!$C23="","",発注計算!$T23) -> 53.906977 | F27: =IF(ISNUMBER($E27),$E27-N(発注計算!$I23),"") -> 46.906977 | G27: =IF(発注計算!$C23="","",IF(NOT(ISNUMBER($F27)),"データなし",IF($F27<=0,"今日が期限",IF($F27<=N(発注計算!$AG23),"要発注","余裕")))) -> 余裕 | H27: =IF(OR(発注計算!$C23="",NOT(ISNUMBER(発注計算!$S23)),発注計算!$S23<=0),"",(発注計算!$K23+N($J27)*N(発注計算!$G23))/発注計算!$S23) -> 53.906977 | I27: =IF(発注計算!$C23="","",発注計算!$Y23) -> 0 | K27: =IF($J27="","",N($J27)*N(発注計算!$H23)) | Z27: =IF(OR(N($J27)<=0,AND(③発注書!$C$5<>"すべて",発注計算!$F23<>③発注書!$C$5)),N(Z26),N(Z26)+1) -> 7
B28: 19 | C28: =IF(発注計算!$C24="","",発注計算!$D24) -> めいらく北海道特選３．６牛乳 | D28: =IF(発注計算!$C24="","",発注計算!$E24) -> コーヒー | E28: =IF(発注計算!$C24="","",発注計算!$T24) -> 7.5703013 | F28: =IF(ISNUMBER($E28),$E28-N(発注計算!$I24),"") -> 2.5703013 | G28: =IF(発注計算!$C24="","",IF(NOT(ISNUMBER($F28)),"データなし",IF($F28<=0,"今日が期限",IF($F28<=N(発注計算!$AG24),"要発注","余裕")))) -> 要発注 | H28: =IF(OR(発注計算!$C24="",NOT(ISNUMBER(発注計算!$S24)),発注計算!$S24<=0),"",(発注計算!$K24+N($J28)*N(発注計算!$G24))/発注計算!$S24) -> 7.5703013 | I28: =IF(発注計算!$C24="","",発注計算!$Y24) -> 20 | K28: =IF($J28="","",N($J28)*N(発注計算!$H24)) | Z28: =IF(OR(N($J28)<=0,AND(③発注書!$C$5<>"すべて",発注計算!$F24<>③発注書!$C$5)),N(Z27),N(Z27)+1) -> 7
B29: 20 | C29: =IF(発注計算!$C25="","",発注計算!$D25) -> ミルクティーパウダー | D29: =IF(発注計算!$C25="","",発注計算!$E25) -> ホット | E29: =IF(発注計算!$C25="","",発注計算!$T25) -> 60.164384 | F29: =IF(ISNUMBER($E29),$E29-N(発注計算!$I25),"") -> 56.164384 | G29: =IF(発注計算!$C25="","",IF(NOT(ISNUMBER($F29)),"データなし",IF($F29<=0,"今日が期限",IF($F29<=N(発注計算!$AG25),"要発注","余裕")))) -> 余裕 | H29: =IF(OR(発注計算!$C25="",NOT(ISNUMBER(発注計算!$S25)),発注計算!$S25<=0),"",(発注計算!$K25+N($J29)*N(発注計算!$G25))/発注計算!$S25) -> 60.164384 | I29: =IF(発注計算!$C25="","",発注計算!$Y25) -> 0 | K29: =IF($J29="","",N($J29)*N(発注計算!$H25)) | Z29: =IF(OR(N($J29)<=0,AND(③発注書!$C$5<>"すべて",発注計算!$F25<>③発注書!$C$5)),N(Z28),N(Z28)+1) -> 7
B30: 21 | C30: =IF(発注計算!$C26="","",発注計算!$D26) -> ココアカントリーＫオフパウダー | D30: =IF(発注計算!$C26="","",発注計算!$E26) -> ホット | E30: =IF(発注計算!$C26="","",発注計算!$T26) -> 109.8 | F30: =IF(ISNUMBER($E30),$E30-N(発注計算!$I26),"") -> 104.8 | G30: =IF(発注計算!$C26="","",IF(NOT(ISNUMBER($F30)),"データなし",IF($F30<=0,"今日が期限",IF($F30<=N(発注計算!$AG26),"要発注","余裕")))) -> 余裕 | H30: =IF(OR(発注計算!$C26="",NOT(ISNUMBER(発注計算!$S26)),発注計算!$S26<=0),"",(発注計算!$K26+N($J30)*N(発注計算!$G26))/発注計算!$S26) -> 109.8 | I30: =IF(発注計算!$C26="","",発注計算!$Y26) -> 0 | K30: =IF($J30="","",N($J30)*N(発注計算!$H26)) | Z30: =IF(OR(N($J30)<=0,AND(③発注書!$C$5<>"すべて",発注計算!$F26<>③発注書!$C$5)),N(Z29),N(Z29)+1) -> 7
B31: 22 | C31: =IF(発注計算!$C27="","",発注計算!$D27) -> ミレイユ抹茶オレ パウダー | D31: =IF(発注計算!$C27="","",発注計算!$E27) -> ホット | E31: =IF(発注計算!$C27="","",発注計算!$T27) -> 77.636364 | F31: =IF(ISNUMBER($E31),$E31-N(発注計算!$I27),"") -> 75.636364 | G31: =IF(発注計算!$C27="","",IF(NOT(ISNUMBER($F31)),"データなし",IF($F31<=0,"今日が期限",IF($F31<=N(発注計算!$AG27),"要発注","余裕")))) -> 余裕 | H31: =IF(OR(発注計算!$C27="",NOT(ISNUMBER(発注計算!$S27)),発注計算!$S27<=0),"",(発注計算!$K27+N($J31)*N(発注計算!$G27))/発注計算!$S27) -> 77.636364 | I31: =IF(発注計算!$C27="","",発注計算!$Y27) -> 0 | K31: =IF($J31="","",N($J31)*N(発注計算!$H27)) | Z31: =IF(OR(N($J31)<=0,AND(③発注書!$C$5<>"すべて",発注計算!$F27<>③発注書!$C$5)),N(Z30),N(Z30)+1) -> 7
B32: 23 | C32: =IF(発注計算!$C28="","",発注計算!$D28) -> 台湾レモン ナタデココ 入り | D32: =IF(発注計算!$C28="","",発注計算!$E28) -> その他ドリンク | E32: =IF(発注計算!$C28="","",発注計算!$T28) -> 46.345345 | F32: =IF(ISNUMBER($E32),$E32-N(発注計算!$I28),"") -> 39.345345 | G32: =IF(発注計算!$C28="","",IF(NOT(ISNUMBER($F32)),"データなし",IF($F32<=0,"今日が期限",IF($F32<=N(発注計算!$AG28),"要発注","余裕")))) -> 余裕 | H32: =IF(OR(発注計算!$C28="",NOT(ISNUMBER(発注計算!$S28)),発注計算!$S28<=0),"",(発注計算!$K28+N($J32)*N(発注計算!$G28))/発注計算!$S28) -> 46.345345 | I32: =IF(発注計算!$C28="","",発注計算!$Y28) -> 0 | K32: =IF($J32="","",N($J32)*N(発注計算!$H28)) | Z32: =IF(OR(N($J32)<=0,AND(③発注書!$C$5<>"すべて",発注計算!$F28<>③発注書!$C$5)),N(Z31),N(Z31)+1) -> 7
B33: 24 | C33: =IF(発注計算!$C29="","",発注計算!$D29) -> 黒糖ブラックタピオカ | D33: =IF(発注計算!$C29="","",発注計算!$E29) -> その他ドリンク | E33: =IF(発注計算!$C29="","",発注計算!$T29) -> 5.3203008 | F33: =IF(ISNUMBER($E33),$E33-N(発注計算!$I29),"") -> -1.6796992 | G33: =IF(発注計算!$C29="","",IF(NOT(ISNUMBER($F33)),"データなし",IF($F33<=0,"今日が期限",IF($F33<=N(発注計算!$AG29),"要発注","余裕")))) -> 今日が期限 | H33: =IF(OR(発注計算!$C29="",NOT(ISNUMBER(発注計算!$S29)),発注計算!$S29<=0),"",(発注計算!$K29+N($J33)*N(発注計算!$G29))/発注計算!$S29) -> 5.3203008 | I33: =IF(発注計算!$C29="","",発注計算!$Y29) -> 1 | K33: =IF($J33="","",N($J33)*N(発注計算!$H29)) | Z33: =IF(OR(N($J33)<=0,AND(③発注書!$C$5<>"すべて",発注計算!$F29<>③発注書!$C$5)),N(Z32),N(Z32)+1) -> 7
B34: 25 | C34: =IF(発注計算!$C30="","",発注計算!$D30) -> とろけるフローズンゼリマスカット | D34: =IF(発注計算!$C30="","",発注計算!$E30) -> その他ドリンク | E34: =IF(発注計算!$C30="","",発注計算!$T30) -> 61 | F34: =IF(ISNUMBER($E34),$E34-N(発注計算!$I30),"") -> 58 | G34: =IF(発注計算!$C30="","",IF(NOT(ISNUMBER($F34)),"データなし",IF($F34<=0,"今日が期限",IF($F34<=N(発注計算!$AG30),"要発注","余裕")))) -> 余裕 | H34: =IF(OR(発注計算!$C30="",NOT(ISNUMBER(発注計算!$S30)),発注計算!$S30<=0),"",(発注計算!$K30+N($J34)*N(発注計算!$G30))/発注計算!$S30) -> 61 | I34: =IF(発注計算!$C30="","",発注計算!$Y30) -> 5 | K34: =IF($J34="","",N($J34)*N(発注計算!$H30)) | Z34: =IF(OR(N($J34)<=0,AND(③発注書!$C$5<>"すべて",発注計算!$F30<>③発注書!$C$5)),N(Z33),N(Z33)+1) -> 7
B35: 26 | C35: =IF(発注計算!$C31="","",発注計算!$D31) -> 超ストロベリーフローズン | D35: =IF(発注計算!$C31="","",発注計算!$E31) -> その他ドリンク | E35: =IF(発注計算!$C31="","",発注計算!$T31) -> 1.6397849 | F35: =IF(ISNUMBER($E35),$E35-N(発注計算!$I31),"") -> -2.3602151 | G35: =IF(発注計算!$C31="","",IF(NOT(ISNUMBER($F35)),"データなし",IF($F35<=0,"今日が期限",IF($F35<=N(発注計算!$AG31),"要発注","余裕")))) -> 今日が期限 | H35: =IF(OR(発注計算!$C31="",NOT(ISNUMBER(発注計算!$S31)),発注計算!$S31<=0),"",(発注計算!$K31+N($J35)*N(発注計算!$G31))/発注計算!$S31) -> 1.6397849 | I35: =IF(発注計算!$C31="","",発注計算!$Y31) -> 1 | K35: =IF($J35="","",N($J35)*N(発注計算!$H31)) | Z35: =IF(OR(N($J35)<=0,AND(③発注書!$C$5<>"すべて",発注計算!$F31<>③発注書!$C$5)),N(Z34),N(Z34)+1) -> 7
... B409: 400 | C409: =IF(発注計算!$C405="","",発注計算!$D405) | D409: =IF(発注計算!$C405="","",発注計算!$E405) | E409: =IF(発注計算!$C405="","",発注計算!$T405) | F409: =IF(ISNUMBER($E409),$E409-N(発注計算!$I405),"") | G409: =IF(発注計算!$C405="","",IF(NOT(ISNUMBER($F409)),"データなし",IF($F409<=0,"今日が期限",IF($F409<=N(発注計算!$AG405),"要発注","余裕")))) | H409: =IF(OR(発注計算!$C405="",NOT(ISNUMBER(発注計算!$S405)),発注計算!$S405<=0),"",(発注計算!$K405+N($J409)*N(発注計算!$G405))/発注計算!$S405) | I409: =IF(発注計算!$C405="","",発注計算!$Y405) | K409: =IF($J409="","",N($J409)*N(発注計算!$H405)) | Z409: =IF(OR(N($J409)<=0,AND(③発注書!$C$5<>"すべて",発注計算!$F405<>③発注書!$C$5)),N(Z408),N(Z408)+1) -> 7
M411: 今日が期限（今日発注しないと間に合わない）
M412: 要発注（発注サイクル内に在庫が切れる）
M413: 余裕
M414: 発注すると伸びる分
L415: │ | M415: 発注デッドライン（在庫が尽きる日 − リードタイム）
L417: 横軸は当日基準日からの14日間です。帯の長さがその商品の在庫が持つ日数を表します。
L418: 発注数を入れると、伸びた分がバター色で帯の先に足されます。

Sheet ③発注書
B2: 発 注 書
B3: タイムテーブルで入れた発注数がここに集まります。発注先を選んで印刷してください。
N4: 発注先の選択肢
B5: 発注先 | C5: すべて | G5: ← ここを選ぶ | N5: すべて
B6: 発注日 | C6: =IF('設定（最初に1回）'!$C$6="","",TEXT('設定（最初に1回）'!$C$6,"yyyy/m/d")&"（"&CHOOSE(WEEKDAY('設定（最初に1回）'!$C$6),"日","月","火","水","木","金","土")&"）") -> 2026/5/1（金） | G6: 自動 | N6: オザックス株式会社
B7: 発注元 | C7: =IF('設定（最初に1回）'!$C$5="","",'設定（最初に1回）'!$C$4&" "&'設定（最初に1回）'!$C$5) -> 0761 新宿 | G7: 自動 | N7: 株式会社 カクヤス
B8: 担当者 | C8: ='設定（最初に1回）'!$C$16 -> 笹川 | G8: 自動 | N8: エパックス（株）
B9: 自動 | C9: 自動 | D9: 自動 | E9: 自動 | F9: 自動 | G9: 自動 | H9: 自動 | I9: 自動 | J9: 自動 | N9: 松竹株式会社（コンセ）
B10: No | C10: 仕入先 | D10: 商品コード | E10: 商品名 | F10: 発注単位 | G10: 入数 | H10: 発注数 | I10: 単価 | J10: 金額 | N10: 株式会社ムービック【コンセ】
B11: =IF(1<=MAX(②発注数を決める!$Z$10:$Z$409),1,"") -> 1 | C11: =IF($B11="","",IFERROR(INDEX(発注計算!$F$6:$F$405,MATCH(1,②発注数を決める!$Z$10:$Z$409,0)),"")) -> 株式会社 カクヤス | D11: =IF($B11="","",IFERROR(INDEX(発注計算!$C$6:$C$405,MATCH(1,②発注数を決める!$Z$10:$Z$409,0))&"","")) -> 1812000008585 | E11: =IF($B11="","",IFERROR(INDEX(②発注数を決める!$C$10:$C$409,MATCH(1,②発注数を決める!$Z$10:$Z$409,0))&"","")) -> プレミアムモルツ ２０Ｌ | F11: =IF($B11="","",IFERROR(INDEX(商品マスタ!$J$6:$J$1005,MATCH($D11,商品マスタ!$B$6:$B$1005,0)),"ケース")) -> ケース | G11: =IF($B11="","",IFERROR(INDEX(発注計算!$G$6:$G$405,MATCH(1,②発注数を決める!$Z$10:$Z$409,0)),"")) -> 1 | H11: =IF($B11="","",IFERROR(INDEX(②発注数を決める!$J$10:$J$409,MATCH(1,②発注数を決める!$Z$10:$Z$409,0)),"")) -> 6 | I11: =IF($B11="","",IFERROR(INDEX(発注計算!$H$6:$H$405,MATCH(1,②発注数を決める!$Z$10:$Z$409,0)),"")) -> 11300 | J11: =IF($B11="","",N($H11)*N($I11)) -> 67800 | N11: 東映ジョイ（コンセ）
B12: =IF(2<=MAX(②発注数を決める!$Z$10:$Z$409),2,"") -> 2 | C12: =IF($B12="","",IFERROR(INDEX(発注計算!$F$6:$F$405,MATCH(2,②発注数を決める!$Z$10:$Z$409,0)),"")) -> 株式会社 カクヤス | D12: =IF($B12="","",IFERROR(INDEX(発注計算!$C$6:$C$405,MATCH(2,②発注数を決める!$Z$10:$Z$409,0))&"","")) -> 1812000010991 | E12: =IF($B12="","",IFERROR(INDEX(②発注数を決める!$C$10:$C$409,MATCH(2,②発注数を決める!$Z$10:$Z$409,0))&"","")) -> ミオネット ベビーボトル２００ｍ | F12: =IF($B12="","",IFERROR(INDEX(商品マスタ!$J$6:$J$1005,MATCH($D12,商品マスタ!$B$6:$B$1005,0)),"ケース")) -> ケース | G12: =IF($B12="","",IFERROR(INDEX(発注計算!$G$6:$G$405,MATCH(2,②発注数を決める!$Z$10:$Z$409,0)),"")) -> 24 | H12: =IF($B12="","",IFERROR(INDEX(②発注数を決める!$J$10:$J$409,MATCH(2,②発注数を決める!$Z$10:$Z$409,0)),"")) -> 3 | I12: =IF($B12="","",IFERROR(INDEX(発注計算!$H$6:$H$405,MATCH(2,②発注数を決める!$Z$10:$Z$409,0)),"")) -> 587 | J12: =IF($B12="","",N($H12)*N($I12)) -> 1761 | N12: ㈱トップス
B13: =IF(3<=MAX(②発注数を決める!$Z$10:$Z$409),3,"") -> 3 | C13: =IF($B13="","",IFERROR(INDEX(発注計算!$F$6:$F$405,MATCH(3,②発注数を決める!$Z$10:$Z$409,0)),"")) -> 株式会社 カクヤス | D13: =IF($B13="","",IFERROR(INDEX(発注計算!$C$6:$C$405,MATCH(3,②発注数を決める!$Z$10:$Z$409,0))&"","")) -> 1812000011745 | E13: =IF($B13="","",IFERROR(INDEX(②発注数を決める!$C$10:$C$409,MATCH(3,②発注数を決める!$Z$10:$Z$409,0))&"","")) -> フォルタン リトラル 赤 | F13: =IF($B13="","",IFERROR(INDEX(商品マスタ!$J$6:$J$1005,MATCH($D13,商品マスタ!$B$6:$B$1005,0)),"ケース")) -> ケース | G13: =IF($B13="","",IFERROR(INDEX(発注計算!$G$6:$G$405,MATCH(3,②発注数を決める!$Z$10:$Z$409,0)),"")) -> 48 | H13: =IF($B13="","",IFERROR(INDEX(②発注数を決める!$J$10:$J$409,MATCH(3,②発注数を決める!$Z$10:$Z$409,0)),"")) -> 10 | I13: =IF($B13="","",IFERROR(INDEX(発注計算!$H$6:$H$405,MATCH(3,②発注数を決める!$Z$10:$Z$409,0)),"")) -> 357 | J13: =IF($B13="","",N($H13)*N($I13)) -> 3570 | N13: ㈱そごう・西武
B14: =IF(4<=MAX(②発注数を決める!$Z$10:$Z$409),4,"") -> 4 | C14: =IF($B14="","",IFERROR(INDEX(発注計算!$F$6:$F$405,MATCH(4,②発注数を決める!$Z$10:$Z$409,0)),"")) -> 株式会社 カクヤス | D14: =IF($B14="","",IFERROR(INDEX(発注計算!$C$6:$C$405,MATCH(4,②発注数を決める!$Z$10:$Z$409,0))&"","")) -> 1812000013343 | E14: =IF($B14="","",IFERROR(INDEX(②発注数を決める!$C$10:$C$409,MATCH(4,②発注数を決める!$Z$10:$Z$409,0))&"","")) -> フレシネコルドンネグロ２００ｍｌ | F14: =IF($B14="","",IFERROR(INDEX(商品マスタ!$J$6:$J$1005,MATCH($D14,商品マスタ!$B$6:$B$1005,0)),"ケース")) -> ケース | G14: =IF($B14="","",IFERROR(INDEX(発注計算!$G$6:$G$405,MATCH(4,②発注数を決める!$Z$10:$Z$409,0)),"")) -> 24 | H14: =IF($B14="","",IFERROR(INDEX(②発注数を決める!$J$10:$J$409,MATCH(4,②発注数を決める!$Z$10:$Z$409,0)),"")) -> 4 | I14: =IF($B14="","",IFERROR(INDEX(発注計算!$H$6:$H$405,MATCH(4,②発注数を決める!$Z$10:$Z$409,0)),"")) -> 585 | J14: =IF($B14="","",N($H14)*N($I14)) -> 2340 | N14: 本社 番組編成部 マーケティング室
B15: =IF(5<=MAX(②発注数を決める!$Z$10:$Z$409),5,"") -> 5 | C15: =IF($B15="","",IFERROR(INDEX(発注計算!$F$6:$F$405,MATCH(5,②発注数を決める!$Z$10:$Z$409,0)),"")) -> オザックス株式会社 | D15: =IF($B15="","",IFERROR(INDEX(発注計算!$C$6:$C$405,MATCH(5,②発注数を決める!$Z$10:$Z$409,0))&"","")) -> 1812000000251 | E15: =IF($B15="","",IFERROR(INDEX(②発注数を決める!$C$10:$C$409,MATCH(5,②発注数を決める!$Z$10:$Z$409,0))&"","")) -> 烏龍茶１０倍シロップ | F15: =IF($B15="","",IFERROR(INDEX(商品マスタ!$J$6:$J$1005,MATCH($D15,商品マスタ!$B$6:$B$1005,0)),"ケース")) -> ケース | G15: =IF($B15="","",IFERROR(INDEX(発注計算!$G$6:$G$405,MATCH(5,②発注数を決める!$Z$10:$Z$409,0)),"")) -> 1 | H15: =IF($B15="","",IFERROR(INDEX(②発注数を決める!$J$10:$J$409,MATCH(5,②発注数を決める!$Z$10:$Z$409,0)),"")) -> 8 | I15: =IF($B15="","",IFERROR(INDEX(発注計算!$H$6:$H$405,MATCH(5,②発注数を決める!$Z$10:$Z$409,0)),"")) -> 4382 | J15: =IF($B15="","",N($H15)*N($I15)) -> 35056
B16: =IF(6<=MAX(②発注数を決める!$Z$10:$Z$409),6,"") -> 6 | C16: =IF($B16="","",IFERROR(INDEX(発注計算!$F$6:$F$405,MATCH(6,②発注数を決める!$Z$10:$Z$409,0)),"")) -> オザックス株式会社 | D16: =IF($B16="","",IFERROR(INDEX(発注計算!$C$6:$C$405,MATCH(6,②発注数を決める!$Z$10:$Z$409,0))&"","")) -> 4902102081283 | E16: =IF($B16="","",IFERROR(INDEX(②発注数を決める!$C$10:$C$409,MATCH(6,②発注数を決める!$Z$10:$Z$409,0))&"","")) -> ＰＸＴ爽健美茶１Ｇ | F16: =IF($B16="","",IFERROR(INDEX(商品マスタ!$J$6:$J$1005,MATCH($D16,商品マスタ!$B$6:$B$1005,0)),"ケース")) -> ケース | G16: =IF($B16="","",IFERROR(INDEX(発注計算!$G$6:$G$405,MATCH(6,②発注数を決める!$Z$10:$Z$409,0)),"")) -> 1 | H16: =IF($B16="","",IFERROR(INDEX(②発注数を決める!$J$10:$J$409,MATCH(6,②発注数を決める!$Z$10:$Z$409,0)),"")) -> 2 | I16: =IF($B16="","",IFERROR(INDEX(発注計算!$H$6:$H$405,MATCH(6,②発注数を決める!$Z$10:$Z$409,0)),"")) -> 3756 | J16: =IF($B16="","",N($H16)*N($I16)) -> 7512
B17: =IF(7<=MAX(②発注数を決める!$Z$10:$Z$409),7,"") -> 7 | C17: =IF($B17="","",IFERROR(INDEX(発注計算!$F$6:$F$405,MATCH(7,②発注数を決める!$Z$10:$Z$409,0)),"")) -> オザックス株式会社 | D17: =IF($B17="","",IFERROR(INDEX(発注計算!$C$6:$C$405,MATCH(7,②発注数を決める!$Z$10:$Z$409,0))&"","")) -> 4902102113014 | E17: =IF($B17="","",IFERROR(INDEX(②発注数を決める!$C$10:$C$409,MATCH(7,②発注数を決める!$Z$10:$Z$409,0))&"","")) -> フラットＢＩＢコーラゼロ２．５Ｇ | F17: =IF($B17="","",IFERROR(INDEX(商品マスタ!$J$6:$J$1005,MATCH($D17,商品マスタ!$B$6:$B$1005,0)),"ケース")) -> ケース | G17: =IF($B17="","",IFERROR(INDEX(発注計算!$G$6:$G$405,MATCH(7,②発注数を決める!$Z$10:$Z$409,0)),"")) -> 1 | H17: =IF($B17="","",IFERROR(INDEX(②発注数を決める!$J$10:$J$409,MATCH(7,②発注数を決める!$Z$10:$Z$409,0)),"")) -> 5 | I17: =IF($B17="","",IFERROR(INDEX(発注計算!$H$6:$H$405,MATCH(7,②発注数を決める!$Z$10:$Z$409,0)),"")) -> 8136 | J17: =IF($B17="","",N($H17)*N($I17)) -> 40680
B18: =IF(8<=MAX(②発注数を決める!$Z$10:$Z$409),8,"") | C18: =IF($B18="","",IFERROR(INDEX(発注計算!$F$6:$F$405,MATCH(8,②発注数を決める!$Z$10:$Z$409,0)),"")) | D18: =IF($B18="","",IFERROR(INDEX(発注計算!$C$6:$C$405,MATCH(8,②発注数を決める!$Z$10:$Z$409,0))&"","")) | E18: =IF($B18="","",IFERROR(INDEX(②発注数を決める!$C$10:$C$409,MATCH(8,②発注数を決める!$Z$10:$Z$409,0))&"","")) | F18: =IF($B18="","",IFERROR(INDEX(商品マスタ!$J$6:$J$1005,MATCH($D18,商品マスタ!$B$6:$B$1005,0)),"ケース")) | G18: =IF($B18="","",IFERROR(INDEX(発注計算!$G$6:$G$405,MATCH(8,②発注数を決める!$Z$10:$Z$409,0)),"")) | H18: =IF($B18="","",IFERROR(INDEX(②発注数を決める!$J$10:$J$409,MATCH(8,②発注数を決める!$Z$10:$Z$409,0)),"")) | I18: =IF($B18="","",IFERROR(INDEX(発注計算!$H$6:$H$405,MATCH(8,②発注数を決める!$Z$10:$Z$409,0)),"")) | J18: =IF($B18="","",N($H18)*N($I18))
B19: =IF(9<=MAX(②発注数を決める!$Z$10:$Z$409),9,"") | C19: =IF($B19="","",IFERROR(INDEX(発注計算!$F$6:$F$405,MATCH(9,②発注数を決める!$Z$10:$Z$409,0)),"")) | D19: =IF($B19="","",IFERROR(INDEX(発注計算!$C$6:$C$405,MATCH(9,②発注数を決める!$Z$10:$Z$409,0))&"","")) | E19: =IF($B19="","",IFERROR(INDEX(②発注数を決める!$C$10:$C$409,MATCH(9,②発注数を決める!$Z$10:$Z$409,0))&"","")) | F19: =IF($B19="","",IFERROR(INDEX(商品マスタ!$J$6:$J$1005,MATCH($D19,商品マスタ!$B$6:$B$1005,0)),"ケース")) | G19: =IF($B19="","",IFERROR(INDEX(発注計算!$G$6:$G$405,MATCH(9,②発注数を決める!$Z$10:$Z$409,0)),"")) | H19: =IF($B19="","",IFERROR(INDEX(②発注数を決める!$J$10:$J$409,MATCH(9,②発注数を決める!$Z$10:$Z$409,0)),"")) | I19: =IF($B19="","",IFERROR(INDEX(発注計算!$H$6:$H$405,MATCH(9,②発注数を決める!$Z$10:$Z$409,0)),"")) | J19: =IF($B19="","",N($H19)*N($I19))
B20: =IF(10<=MAX(②発注数を決める!$Z$10:$Z$409),10,"") | C20: =IF($B20="","",IFERROR(INDEX(発注計算!$F$6:$F$405,MATCH(10,②発注数を決める!$Z$10:$Z$409,0)),"")) | D20: =IF($B20="","",IFERROR(INDEX(発注計算!$C$6:$C$405,MATCH(10,②発注数を決める!$Z$10:$Z$409,0))&"","")) | E20: =IF($B20="","",IFERROR(INDEX(②発注数を決める!$C$10:$C$409,MATCH(10,②発注数を決める!$Z$10:$Z$409,0))&"","")) | F20: =IF($B20="","",IFERROR(INDEX(商品マスタ!$J$6:$J$1005,MATCH($D20,商品マスタ!$B$6:$B$1005,0)),"ケース")) | G20: =IF($B20="","",IFERROR(INDEX(発注計算!$G$6:$G$405,MATCH(10,②発注数を決める!$Z$10:$Z$409,0)),"")) | H20: =IF($B20="","",IFERROR(INDEX(②発注数を決める!$J$10:$J$409,MATCH(10,②発注数を決める!$Z$10:$Z$409,0)),"")) | I20: =IF($B20="","",IFERROR(INDEX(発注計算!$H$6:$H$405,MATCH(10,②発注数を決める!$Z$10:$Z$409,0)),"")) | J20: =IF($B20="","",N($H20)*N($I20))
B21: =IF(11<=MAX(②発注数を決める!$Z$10:$Z$409),11,"") | C21: =IF($B21="","",IFERROR(INDEX(発注計算!$F$6:$F$405,MATCH(11,②発注数を決める!$Z$10:$Z$409,0)),"")) | D21: =IF($B21="","",IFERROR(INDEX(発注計算!$C$6:$C$405,MATCH(11,②発注数を決める!$Z$10:$Z$409,0))&"","")) | E21: =IF($B21="","",IFERROR(INDEX(②発注数を決める!$C$10:$C$409,MATCH(11,②発注数を決める!$Z$10:$Z$409,0))&"","")) | F21: =IF($B21="","",IFERROR(INDEX(商品マスタ!$J$6:$J$1005,MATCH($D21,商品マスタ!$B$6:$B$1005,0)),"ケース")) | G21: =IF($B21="","",IFERROR(INDEX(発注計算!$G$6:$G$405,MATCH(11,②発注数を決める!$Z$10:$Z$409,0)),"")) | H21: =IF($B21="","",IFERROR(INDEX(②発注数を決める!$J$10:$J$409,MATCH(11,②発注数を決める!$Z$10:$Z$409,0)),"")) | I21: =IF($B21="","",IFERROR(INDEX(発注計算!$H$6:$H$405,MATCH(11,②発注数を決める!$Z$10:$Z$409,0)),"")) | J21: =IF($B21="","",N($H21)*N($I21))
B22: =IF(12<=MAX(②発注数を決める!$Z$10:$Z$409),12,"") | C22: =IF($B22="","",IFERROR(INDEX(発注計算!$F$6:$F$405,MATCH(12,②発注数を決める!$Z$10:$Z$409,0)),"")) | D22: =IF($B22="","",IFERROR(INDEX(発注計算!$C$6:$C$405,MATCH(12,②発注数を決める!$Z$10:$Z$409,0))&"","")) | E22: =IF($B22="","",IFERROR(INDEX(②発注数を決める!$C$10:$C$409,MATCH(12,②発注数を決める!$Z$10:$Z$409,0))&"","")) | F22: =IF($B22="","",IFERROR(INDEX(商品マスタ!$J$6:$J$1005,MATCH($D22,商品マスタ!$B$6:$B$1005,0)),"ケース")) | G22: =IF($B22="","",IFERROR(INDEX(発注計算!$G$6:$G$405,MATCH(12,②発注数を決める!$Z$10:$Z$409,0)),"")) | H22: =IF($B22="","",IFERROR(INDEX(②発注数を決める!$J$10:$J$409,MATCH(12,②発注数を決める!$Z$10:$Z$409,0)),"")) | I22: =IF($B22="","",IFERROR(INDEX(発注計算!$H$6:$H$405,MATCH(12,②発注数を決める!$Z$10:$Z$409,0)),"")) | J22: =IF($B22="","",N($H22)*N($I22))
B23: =IF(13<=MAX(②発注数を決める!$Z$10:$Z$409),13,"") | C23: =IF($B23="","",IFERROR(INDEX(発注計算!$F$6:$F$405,MATCH(13,②発注数を決める!$Z$10:$Z$409,0)),"")) | D23: =IF($B23="","",IFERROR(INDEX(発注計算!$C$6:$C$405,MATCH(13,②発注数を決める!$Z$10:$Z$409,0))&"","")) | E23: =IF($B23="","",IFERROR(INDEX(②発注数を決める!$C$10:$C$409,MATCH(13,②発注数を決める!$Z$10:$Z$409,0))&"","")) | F23: =IF($B23="","",IFERROR(INDEX(商品マスタ!$J$6:$J$1005,MATCH($D23,商品マスタ!$B$6:$B$1005,0)),"ケース")) | G23: =IF($B23="","",IFERROR(INDEX(発注計算!$G$6:$G$405,MATCH(13,②発注数を決める!$Z$10:$Z$409,0)),"")) | H23: =IF($B23="","",IFERROR(INDEX(②発注数を決める!$J$10:$J$409,MATCH(13,②発注数を決める!$Z$10:$Z$409,0)),"")) | I23: =IF($B23="","",IFERROR(INDEX(発注計算!$H$6:$H$405,MATCH(13,②発注数を決める!$Z$10:$Z$409,0)),"")) | J23: =IF($B23="","",N($H23)*N($I23))
B24: =IF(14<=MAX(②発注数を決める!$Z$10:$Z$409),14,"") | C24: =IF($B24="","",IFERROR(INDEX(発注計算!$F$6:$F$405,MATCH(14,②発注数を決める!$Z$10:$Z$409,0)),"")) | D24: =IF($B24="","",IFERROR(INDEX(発注計算!$C$6:$C$405,MATCH(14,②発注数を決める!$Z$10:$Z$409,0))&"","")) | E24: =IF($B24="","",IFERROR(INDEX(②発注数を決める!$C$10:$C$409,MATCH(14,②発注数を決める!$Z$10:$Z$409,0))&"","")) | F24: =IF($B24="","",IFERROR(INDEX(商品マスタ!$J$6:$J$1005,MATCH($D24,商品マスタ!$B$6:$B$1005,0)),"ケース")) | G24: =IF($B24="","",IFERROR(INDEX(発注計算!$G$6:$G$405,MATCH(14,②発注数を決める!$Z$10:$Z$409,0)),"")) | H24: =IF($B24="","",IFERROR(INDEX(②発注数を決める!$J$10:$J$409,MATCH(14,②発注数を決める!$Z$10:$Z$409,0)),"")) | I24: =IF($B24="","",IFERROR(INDEX(発注計算!$H$6:$H$405,MATCH(14,②発注数を決める!$Z$10:$Z$409,0)),"")) | J24: =IF($B24="","",N($H24)*N($I24))
B25: =IF(15<=MAX(②発注数を決める!$Z$10:$Z$409),15,"") | C25: =IF($B25="","",IFERROR(INDEX(発注計算!$F$6:$F$405,MATCH(15,②発注数を決める!$Z$10:$Z$409,0)),"")) | D25: =IF($B25="","",IFERROR(INDEX(発注計算!$C$6:$C$405,MATCH(15,②発注数を決める!$Z$10:$Z$409,0))&"","")) | E25: =IF($B25="","",IFERROR(INDEX(②発注数を決める!$C$10:$C$409,MATCH(15,②発注数を決める!$Z$10:$Z$409,0))&"","")) | F25: =IF($B25="","",IFERROR(INDEX(商品マスタ!$J$6:$J$1005,MATCH($D25,商品マスタ!$B$6:$B$1005,0)),"ケース")) | G25: =IF($B25="","",IFERROR(INDEX(発注計算!$G$6:$G$405,MATCH(15,②発注数を決める!$Z$10:$Z$409,0)),"")) | H25: =IF($B25="","",IFERROR(INDEX(②発注数を決める!$J$10:$J$409,MATCH(15,②発注数を決める!$Z$10:$Z$409,0)),"")) | I25: =IF($B25="","",IFERROR(INDEX(発注計算!$H$6:$H$405,MATCH(15,②発注数を決める!$Z$10:$Z$409,0)),"")) | J25: =IF($B25="","",N($H25)*N($I25))
B26: =IF(16<=MAX(②発注数を決める!$Z$10:$Z$409),16,"") | C26: =IF($B26="","",IFERROR(INDEX(発注計算!$F$6:$F$405,MATCH(16,②発注数を決める!$Z$10:$Z$409,0)),"")) | D26: =IF($B26="","",IFERROR(INDEX(発注計算!$C$6:$C$405,MATCH(16,②発注数を決める!$Z$10:$Z$409,0))&"","")) | E26: =IF($B26="","",IFERROR(INDEX(②発注数を決める!$C$10:$C$409,MATCH(16,②発注数を決める!$Z$10:$Z$409,0))&"","")) | F26: =IF($B26="","",IFERROR(INDEX(商品マスタ!$J$6:$J$1005,MATCH($D26,商品マスタ!$B$6:$B$1005,0)),"ケース")) | G26: =IF($B26="","",IFERROR(INDEX(発注計算!$G$6:$G$405,MATCH(16,②発注数を決める!$Z$10:$Z$409,0)),"")) | H26: =IF($B26="","",IFERROR(INDEX(②発注数を決める!$J$10:$J$409,MATCH(16,②発注数を決める!$Z$10:$Z$409,0)),"")) | I26: =IF($B26="","",IFERROR(INDEX(発注計算!$H$6:$H$405,MATCH(16,②発注数を決める!$Z$10:$Z$409,0)),"")) | J26: =IF($B26="","",N($H26)*N($I26))
B27: =IF(17<=MAX(②発注数を決める!$Z$10:$Z$409),17,"") | C27: =IF($B27="","",IFERROR(INDEX(発注計算!$F$6:$F$405,MATCH(17,②発注数を決める!$Z$10:$Z$409,0)),"")) | D27: =IF($B27="","",IFERROR(INDEX(発注計算!$C$6:$C$405,MATCH(17,②発注数を決める!$Z$10:$Z$409,0))&"","")) | E27: =IF($B27="","",IFERROR(INDEX(②発注数を決める!$C$10:$C$409,MATCH(17,②発注数を決める!$Z$10:$Z$409,0))&"","")) | F27: =IF($B27="","",IFERROR(INDEX(商品マスタ!$J$6:$J$1005,MATCH($D27,商品マスタ!$B$6:$B$1005,0)),"ケース")) | G27: =IF($B27="","",IFERROR(INDEX(発注計算!$G$6:$G$405,MATCH(17,②発注数を決める!$Z$10:$Z$409,0)),"")) | H27: =IF($B27="","",IFERROR(INDEX(②発注数を決める!$J$10:$J$409,MATCH(17,②発注数を決める!$Z$10:$Z$409,0)),"")) | I27: =IF($B27="","",IFERROR(INDEX(発注計算!$H$6:$H$405,MATCH(17,②発注数を決める!$Z$10:$Z$409,0)),"")) | J27: =IF($B27="","",N($H27)*N($I27))
B28: =IF(18<=MAX(②発注数を決める!$Z$10:$Z$409),18,"") | C28: =IF($B28="","",IFERROR(INDEX(発注計算!$F$6:$F$405,MATCH(18,②発注数を決める!$Z$10:$Z$409,0)),"")) | D28: =IF($B28="","",IFERROR(INDEX(発注計算!$C$6:$C$405,MATCH(18,②発注数を決める!$Z$10:$Z$409,0))&"","")) | E28: =IF($B28="","",IFERROR(INDEX(②発注数を決める!$C$10:$C$409,MATCH(18,②発注数を決める!$Z$10:$Z$409,0))&"","")) | F28: =IF($B28="","",IFERROR(INDEX(商品マスタ!$J$6:$J$1005,MATCH($D28,商品マスタ!$B$6:$B$1005,0)),"ケース")) | G28: =IF($B28="","",IFERROR(INDEX(発注計算!$G$6:$G$405,MATCH(18,②発注数を決める!$Z$10:$Z$409,0)),"")) | H28: =IF($B28="","",IFERROR(INDEX(②発注数を決める!$J$10:$J$409,MATCH(18,②発注数を決める!$Z$10:$Z$409,0)),"")) | I28: =IF($B28="","",IFERROR(INDEX(発注計算!$H$6:$H$405,MATCH(18,②発注数を決める!$Z$10:$Z$409,0)),"")) | J28: =IF($B28="","",N($H28)*N($I28))
B29: =IF(19<=MAX(②発注数を決める!$Z$10:$Z$409),19,"") | C29: =IF($B29="","",IFERROR(INDEX(発注計算!$F$6:$F$405,MATCH(19,②発注数を決める!$Z$10:$Z$409,0)),"")) | D29: =IF($B29="","",IFERROR(INDEX(発注計算!$C$6:$C$405,MATCH(19,②発注数を決める!$Z$10:$Z$409,0))&"","")) | E29: =IF($B29="","",IFERROR(INDEX(②発注数を決める!$C$10:$C$409,MATCH(19,②発注数を決める!$Z$10:$Z$409,0))&"","")) | F29: =IF($B29="","",IFERROR(INDEX(商品マスタ!$J$6:$J$1005,MATCH($D29,商品マスタ!$B$6:$B$1005,0)),"ケース")) | G29: =IF($B29="","",IFERROR(INDEX(発注計算!$G$6:$G$405,MATCH(19,②発注数を決める!$Z$10:$Z$409,0)),"")) | H29: =IF($B29="","",IFERROR(INDEX(②発注数を決める!$J$10:$J$409,MATCH(19,②発注数を決める!$Z$10:$Z$409,0)),"")) | I29: =IF($B29="","",IFERROR(INDEX(発注計算!$H$6:$H$405,MATCH(19,②発注数を決める!$Z$10:$Z$409,0)),"")) | J29: =IF($B29="","",N($H29)*N($I29))
B30: =IF(20<=MAX(②発注数を決める!$Z$10:$Z$409),20,"") | C30: =IF($B30="","",IFERROR(INDEX(発注計算!$F$6:$F$405,MATCH(20,②発注数を決める!$Z$10:$Z$409,0)),"")) | D30: =IF($B30="","",IFERROR(INDEX(発注計算!$C$6:$C$405,MATCH(20,②発注数を決める!$Z$10:$Z$409,0))&"","")) | E30: =IF($B30="","",IFERROR(INDEX(②発注数を決める!$C$10:$C$409,MATCH(20,②発注数を決める!$Z$10:$Z$409,0))&"","")) | F30: =IF($B30="","",IFERROR(INDEX(商品マスタ!$J$6:$J$1005,MATCH($D30,商品マスタ!$B$6:$B$1005,0)),"ケース")) | G30: =IF($B30="","",IFERROR(INDEX(発注計算!$G$6:$G$405,MATCH(20,②発注数を決める!$Z$10:$Z$409,0)),"")) | H30: =IF($B30="","",IFERROR(INDEX(②発注数を決める!$J$10:$J$409,MATCH(20,②発注数を決める!$Z$10:$Z$409,0)),"")) | I30: =IF($B30="","",IFERROR(INDEX(発注計算!$H$6:$H$405,MATCH(20,②発注数を決める!$Z$10:$Z$409,0)),"")) | J30: =IF($B30="","",N($H30)*N($I30))
B31: =IF(21<=MAX(②発注数を決める!$Z$10:$Z$409),21,"") | C31: =IF($B31="","",IFERROR(INDEX(発注計算!$F$6:$F$405,MATCH(21,②発注数を決める!$Z$10:$Z$409,0)),"")) | D31: =IF($B31="","",IFERROR(INDEX(発注計算!$C$6:$C$405,MATCH(21,②発注数を決める!$Z$10:$Z$409,0))&"","")) | E31: =IF($B31="","",IFERROR(INDEX(②発注数を決める!$C$10:$C$409,MATCH(21,②発注数を決める!$Z$10:$Z$409,0))&"","")) | F31: =IF($B31="","",IFERROR(INDEX(商品マスタ!$J$6:$J$1005,MATCH($D31,商品マスタ!$B$6:$B$1005,0)),"ケース")) | G31: =IF($B31="","",IFERROR(INDEX(発注計算!$G$6:$G$405,MATCH(21,②発注数を決める!$Z$10:$Z$409,0)),"")) | H31: =IF($B31="","",IFERROR(INDEX(②発注数を決める!$J$10:$J$409,MATCH(21,②発注数を決める!$Z$10:$Z$409,0)),"")) | I31: =IF($B31="","",IFERROR(INDEX(発注計算!$H$6:$H$405,MATCH(21,②発注数を決める!$Z$10:$Z$409,0)),"")) | J31: =IF($B31="","",N($H31)*N($I31))
B32: =IF(22<=MAX(②発注数を決める!$Z$10:$Z$409),22,"") | C32: =IF($B32="","",IFERROR(INDEX(発注計算!$F$6:$F$405,MATCH(22,②発注数を決める!$Z$10:$Z$409,0)),"")) | D32: =IF($B32="","",IFERROR(INDEX(発注計算!$C$6:$C$405,MATCH(22,②発注数を決める!$Z$10:$Z$409,0))&"","")) | E32: =IF($B32="","",IFERROR(INDEX(②発注数を決める!$C$10:$C$409,MATCH(22,②発注数を決める!$Z$10:$Z$409,0))&"","")) | F32: =IF($B32="","",IFERROR(INDEX(商品マスタ!$J$6:$J$1005,MATCH($D32,商品マスタ!$B$6:$B$1005,0)),"ケース")) | G32: =IF($B32="","",IFERROR(INDEX(発注計算!$G$6:$G$405,MATCH(22,②発注数を決める!$Z$10:$Z$409,0)),"")) | H32: =IF($B32="","",IFERROR(INDEX(②発注数を決める!$J$10:$J$409,MATCH(22,②発注数を決める!$Z$10:$Z$409,0)),"")) | I32: =IF($B32="","",IFERROR(INDEX(発注計算!$H$6:$H$405,MATCH(22,②発注数を決める!$Z$10:$Z$409,0)),"")) | J32: =IF($B32="","",N($H32)*N($I32))
B33: =IF(23<=MAX(②発注数を決める!$Z$10:$Z$409),23,"") | C33: =IF($B33="","",IFERROR(INDEX(発注計算!$F$6:$F$405,MATCH(23,②発注数を決める!$Z$10:$Z$409,0)),"")) | D33: =IF($B33="","",IFERROR(INDEX(発注計算!$C$6:$C$405,MATCH(23,②発注数を決める!$Z$10:$Z$409,0))&"","")) | E33: =IF($B33="","",IFERROR(INDEX(②発注数を決める!$C$10:$C$409,MATCH(23,②発注数を決める!$Z$10:$Z$409,0))&"","")) | F33: =IF($B33="","",IFERROR(INDEX(商品マスタ!$J$6:$J$1005,MATCH($D33,商品マスタ!$B$6:$B$1005,0)),"ケース")) | G33: =IF($B33="","",IFERROR(INDEX(発注計算!$G$6:$G$405,MATCH(23,②発注数を決める!$Z$10:$Z$409,0)),"")) | H33: =IF($B33="","",IFERROR(INDEX(②発注数を決める!$J$10:$J$409,MATCH(23,②発注数を決める!$Z$10:$Z$409,0)),"")) | I33: =IF($B33="","",IFERROR(INDEX(発注計算!$H$6:$H$405,MATCH(23,②発注数を決める!$Z$10:$Z$409,0)),"")) | J33: =IF($B33="","",N($H33)*N($I33))
B34: =IF(24<=MAX(②発注数を決める!$Z$10:$Z$409),24,"") | C34: =IF($B34="","",IFERROR(INDEX(発注計算!$F$6:$F$405,MATCH(24,②発注数を決める!$Z$10:$Z$409,0)),"")) | D34: =IF($B34="","",IFERROR(INDEX(発注計算!$C$6:$C$405,MATCH(24,②発注数を決める!$Z$10:$Z$409,0))&"","")) | E34: =IF($B34="","",IFERROR(INDEX(②発注数を決める!$C$10:$C$409,MATCH(24,②発注数を決める!$Z$10:$Z$409,0))&"","")) | F34: =IF($B34="","",IFERROR(INDEX(商品マスタ!$J$6:$J$1005,MATCH($D34,商品マスタ!$B$6:$B$1005,0)),"ケース")) | G34: =IF($B34="","",IFERROR(INDEX(発注計算!$G$6:$G$405,MATCH(24,②発注数を決める!$Z$10:$Z$409,0)),"")) | H34: =IF($B34="","",IFERROR(INDEX(②発注数を決める!$J$10:$J$409,MATCH(24,②発注数を決める!$Z$10:$Z$409,0)),"")) | I34: =IF($B34="","",IFERROR(INDEX(発注計算!$H$6:$H$405,MATCH(24,②発注数を決める!$Z$10:$Z$409,0)),"")) | J34: =IF($B34="","",N($H34)*N($I34))
B35: =IF(25<=MAX(②発注数を決める!$Z$10:$Z$409),25,"") | C35: =IF($B35="","",IFERROR(INDEX(発注計算!$F$6:$F$405,MATCH(25,②発注数を決める!$Z$10:$Z$409,0)),"")) | D35: =IF($B35="","",IFERROR(INDEX(発注計算!$C$6:$C$405,MATCH(25,②発注数を決める!$Z$10:$Z$409,0))&"","")) | E35: =IF($B35="","",IFERROR(INDEX(②発注数を決める!$C$10:$C$409,MATCH(25,②発注数を決める!$Z$10:$Z$409,0))&"","")) | F35: =IF($B35="","",IFERROR(INDEX(商品マスタ!$J$6:$J$1005,MATCH($D35,商品マスタ!$B$6:$B$1005,0)),"ケース")) | G35: =IF($B35="","",IFERROR(INDEX(発注計算!$G$6:$G$405,MATCH(25,②発注数を決める!$Z$10:$Z$409,0)),"")) | H35: =IF($B35="","",IFERROR(INDEX(②発注数を決める!$J$10:$J$409,MATCH(25,②発注数を決める!$Z$10:$Z$409,0)),"")) | I35: =IF($B35="","",IFERROR(INDEX(発注計算!$H$6:$H$405,MATCH(25,②発注数を決める!$Z$10:$Z$409,0)),"")) | J35: =IF($B35="","",N($H35)*N($I35))
B36: =IF(26<=MAX(②発注数を決める!$Z$10:$Z$409),26,"") | C36: =IF($B36="","",IFERROR(INDEX(発注計算!$F$6:$F$405,MATCH(26,②発注数を決める!$Z$10:$Z$409,0)),"")) | D36: =IF($B36="","",IFERROR(INDEX(発注計算!$C$6:$C$405,MATCH(26,②発注数を決める!$Z$10:$Z$409,0))&"","")) | E36: =IF($B36="","",IFERROR(INDEX(②発注数を決める!$C$10:$C$409,MATCH(26,②発注数を決める!$Z$10:$Z$409,0))&"","")) | F36: =IF($B36="","",IFERROR(INDEX(商品マスタ!$J$6:$J$1005,MATCH($D36,商品マスタ!$B$6:$B$1005,0)),"ケース")) | G36: =IF($B36="","",IFERROR(INDEX(発注計算!$G$6:$G$405,MATCH(26,②発注数を決める!$Z$10:$Z$409,0)),"")) | H36: =IF($B36="","",IFERROR(INDEX(②発注数を決める!$J$10:$J$409,MATCH(26,②発注数を決める!$Z$10:$Z$409,0)),"")) | I36: =IF($B36="","",IFERROR(INDEX(発注計算!$H$6:$H$405,MATCH(26,②発注数を決める!$Z$10:$Z$409,0)),"")) | J36: =IF($B36="","",N($H36)*N($I36))
B37: =IF(27<=MAX(②発注数を決める!$Z$10:$Z$409),27,"") | C37: =IF($B37="","",IFERROR(INDEX(発注計算!$F$6:$F$405,MATCH(27,②発注数を決める!$Z$10:$Z$409,0)),"")) | D37: =IF($B37="","",IFERROR(INDEX(発注計算!$C$6:$C$405,MATCH(27,②発注数を決める!$Z$10:$Z$409,0))&"","")) | E37: =IF($B37="","",IFERROR(INDEX(②発注数を決める!$C$10:$C$409,MATCH(27,②発注数を決める!$Z$10:$Z$409,0))&"","")) | F37: =IF($B37="","",IFERROR(INDEX(商品マスタ!$J$6:$J$1005,MATCH($D37,商品マスタ!$B$6:$B$1005,0)),"ケース")) | G37: =IF($B37="","",IFERROR(INDEX(発注計算!$G$6:$G$405,MATCH(27,②発注数を決める!$Z$10:$Z$409,0)),"")) | H37: =IF($B37="","",IFERROR(INDEX(②発注数を決める!$J$10:$J$409,MATCH(27,②発注数を決める!$Z$10:$Z$409,0)),"")) | I37: =IF($B37="","",IFERROR(INDEX(発注計算!$H$6:$H$405,MATCH(27,②発注数を決める!$Z$10:$Z$409,0)),"")) | J37: =IF($B37="","",N($H37)*N($I37))
B38: =IF(28<=MAX(②発注数を決める!$Z$10:$Z$409),28,"") | C38: =IF($B38="","",IFERROR(INDEX(発注計算!$F$6:$F$405,MATCH(28,②発注数を決める!$Z$10:$Z$409,0)),"")) | D38: =IF($B38="","",IFERROR(INDEX(発注計算!$C$6:$C$405,MATCH(28,②発注数を決める!$Z$10:$Z$409,0))&"","")) | E38: =IF($B38="","",IFERROR(INDEX(②発注数を決める!$C$10:$C$409,MATCH(28,②発注数を決める!$Z$10:$Z$409,0))&"","")) | F38: =IF($B38="","",IFERROR(INDEX(商品マスタ!$J$6:$J$1005,MATCH($D38,商品マスタ!$B$6:$B$1005,0)),"ケース")) | G38: =IF($B38="","",IFERROR(INDEX(発注計算!$G$6:$G$405,MATCH(28,②発注数を決める!$Z$10:$Z$409,0)),"")) | H38: =IF($B38="","",IFERROR(INDEX(②発注数を決める!$J$10:$J$409,MATCH(28,②発注数を決める!$Z$10:$Z$409,0)),"")) | I38: =IF($B38="","",IFERROR(INDEX(発注計算!$H$6:$H$405,MATCH(28,②発注数を決める!$Z$10:$Z$409,0)),"")) | J38: =IF($B38="","",N($H38)*N($I38))
B39: =IF(29<=MAX(②発注数を決める!$Z$10:$Z$409),29,"") | C39: =IF($B39="","",IFERROR(INDEX(発注計算!$F$6:$F$405,MATCH(29,②発注数を決める!$Z$10:$Z$409,0)),"")) | D39: =IF($B39="","",IFERROR(INDEX(発注計算!$C$6:$C$405,MATCH(29,②発注数を決める!$Z$10:$Z$409,0))&"","")) | E39: =IF($B39="","",IFERROR(INDEX(②発注数を決める!$C$10:$C$409,MATCH(29,②発注数を決める!$Z$10:$Z$409,0))&"","")) | F39: =IF($B39="","",IFERROR(INDEX(商品マスタ!$J$6:$J$1005,MATCH($D39,商品マスタ!$B$6:$B$1005,0)),"ケース")) | G39: =IF($B39="","",IFERROR(INDEX(発注計算!$G$6:$G$405,MATCH(29,②発注数を決める!$Z$10:$Z$409,0)),"")) | H39: =IF($B39="","",IFERROR(INDEX(②発注数を決める!$J$10:$J$409,MATCH(29,②発注数を決める!$Z$10:$Z$409,0)),"")) | I39: =IF($B39="","",IFERROR(INDEX(発注計算!$H$6:$H$405,MATCH(29,②発注数を決める!$Z$10:$Z$409,0)),"")) | J39: =IF($B39="","",N($H39)*N($I39))
B40: =IF(30<=MAX(②発注数を決める!$Z$10:$Z$409),30,"") | C40: =IF($B40="","",IFERROR(INDEX(発注計算!$F$6:$F$405,MATCH(30,②発注数を決める!$Z$10:$Z$409,0)),"")) | D40: =IF($B40="","",IFERROR(INDEX(発注計算!$C$6:$C$405,MATCH(30,②発注数を決める!$Z$10:$Z$409,0))&"","")) | E40: =IF($B40="","",IFERROR(INDEX(②発注数を決める!$C$10:$C$409,MATCH(30,②発注数を決める!$Z$10:$Z$409,0))&"","")) | F40: =IF($B40="","",IFERROR(INDEX(商品マスタ!$J$6:$J$1005,MATCH($D40,商品マスタ!$B$6:$B$1005,0)),"ケース")) | G40: =IF($B40="","",IFERROR(INDEX(発注計算!$G$6:$G$405,MATCH(30,②発注数を決める!$Z$10:$Z$409,0)),"")) | H40: =IF($B40="","",IFERROR(INDEX(②発注数を決める!$J$10:$J$409,MATCH(30,②発注数を決める!$Z$10:$Z$409,0)),"")) | I40: =IF($B40="","",IFERROR(INDEX(発注計算!$H$6:$H$405,MATCH(30,②発注数を決める!$Z$10:$Z$409,0)),"")) | J40: =IF($B40="","",N($H40)*N($I40))
B41: =IF(31<=MAX(②発注数を決める!$Z$10:$Z$409),31,"") | C41: =IF($B41="","",IFERROR(INDEX(発注計算!$F$6:$F$405,MATCH(31,②発注数を決める!$Z$10:$Z$409,0)),"")) | D41: =IF($B41="","",IFERROR(INDEX(発注計算!$C$6:$C$405,MATCH(31,②発注数を決める!$Z$10:$Z$409,0))&"","")) | E41: =IF($B41="","",IFERROR(INDEX(②発注数を決める!$C$10:$C$409,MATCH(31,②発注数を決める!$Z$10:$Z$409,0))&"","")) | F41: =IF($B41="","",IFERROR(INDEX(商品マスタ!$J$6:$J$1005,MATCH($D41,商品マスタ!$B$6:$B$1005,0)),"ケース")) | G41: =IF($B41="","",IFERROR(INDEX(発注計算!$G$6:$G$405,MATCH(31,②発注数を決める!$Z$10:$Z$409,0)),"")) | H41: =IF($B41="","",IFERROR(INDEX(②発注数を決める!$J$10:$J$409,MATCH(31,②発注数を決める!$Z$10:$Z$409,0)),"")) | I41: =IF($B41="","",IFERROR(INDEX(発注計算!$H$6:$H$405,MATCH(31,②発注数を決める!$Z$10:$Z$409,0)),"")) | J41: =IF($B41="","",N($H41)*N($I41))
B42: =IF(32<=MAX(②発注数を決める!$Z$10:$Z$409),32,"") | C42: =IF($B42="","",IFERROR(INDEX(発注計算!$F$6:$F$405,MATCH(32,②発注数を決める!$Z$10:$Z$409,0)),"")) | D42: =IF($B42="","",IFERROR(INDEX(発注計算!$C$6:$C$405,MATCH(32,②発注数を決める!$Z$10:$Z$409,0))&"","")) | E42: =IF($B42="","",IFERROR(INDEX(②発注数を決める!$C$10:$C$409,MATCH(32,②発注数を決める!$Z$10:$Z$409,0))&"","")) | F42: =IF($B42="","",IFERROR(INDEX(商品マスタ!$J$6:$J$1005,MATCH($D42,商品マスタ!$B$6:$B$1005,0)),"ケース")) | G42: =IF($B42="","",IFERROR(INDEX(発注計算!$G$6:$G$405,MATCH(32,②発注数を決める!$Z$10:$Z$409,0)),"")) | H42: =IF($B42="","",IFERROR(INDEX(②発注数を決める!$J$10:$J$409,MATCH(32,②発注数を決める!$Z$10:$Z$409,0)),"")) | I42: =IF($B42="","",IFERROR(INDEX(発注計算!$H$6:$H$405,MATCH(32,②発注数を決める!$Z$10:$Z$409,0)),"")) | J42: =IF($B42="","",N($H42)*N($I42))
B43: =IF(33<=MAX(②発注数を決める!$Z$10:$Z$409),33,"") | C43: =IF($B43="","",IFERROR(INDEX(発注計算!$F$6:$F$405,MATCH(33,②発注数を決める!$Z$10:$Z$409,0)),"")) | D43: =IF($B43="","",IFERROR(INDEX(発注計算!$C$6:$C$405,MATCH(33,②発注数を決める!$Z$10:$Z$409,0))&"","")) | E43: =IF($B43="","",IFERROR(INDEX(②発注数を決める!$C$10:$C$409,MATCH(33,②発注数を決める!$Z$10:$Z$409,0))&"","")) | F43: =IF($B43="","",IFERROR(INDEX(商品マスタ!$J$6:$J$1005,MATCH($D43,商品マスタ!$B$6:$B$1005,0)),"ケース")) | G43: =IF($B43="","",IFERROR(INDEX(発注計算!$G$6:$G$405,MATCH(33,②発注数を決める!$Z$10:$Z$409,0)),"")) | H43: =IF($B43="","",IFERROR(INDEX(②発注数を決める!$J$10:$J$409,MATCH(33,②発注数を決める!$Z$10:$Z$409,0)),"")) | I43: =IF($B43="","",IFERROR(INDEX(発注計算!$H$6:$H$405,MATCH(33,②発注数を決める!$Z$10:$Z$409,0)),"")) | J43: =IF($B43="","",N($H43)*N($I43))
B44: =IF(34<=MAX(②発注数を決める!$Z$10:$Z$409),34,"") | C44: =IF($B44="","",IFERROR(INDEX(発注計算!$F$6:$F$405,MATCH(34,②発注数を決める!$Z$10:$Z$409,0)),"")) | D44: =IF($B44="","",IFERROR(INDEX(発注計算!$C$6:$C$405,MATCH(34,②発注数を決める!$Z$10:$Z$409,0))&"","")) | E44: =IF($B44="","",IFERROR(INDEX(②発注数を決める!$C$10:$C$409,MATCH(34,②発注数を決める!$Z$10:$Z$409,0))&"","")) | F44: =IF($B44="","",IFERROR(INDEX(商品マスタ!$J$6:$J$1005,MATCH($D44,商品マスタ!$B$6:$B$1005,0)),"ケース")) | G44: =IF($B44="","",IFERROR(INDEX(発注計算!$G$6:$G$405,MATCH(34,②発注数を決める!$Z$10:$Z$409,0)),"")) | H44: =IF($B44="","",IFERROR(INDEX(②発注数を決める!$J$10:$J$409,MATCH(34,②発注数を決める!$Z$10:$Z$409,0)),"")) | I44: =IF($B44="","",IFERROR(INDEX(発注計算!$H$6:$H$405,MATCH(34,②発注数を決める!$Z$10:$Z$409,0)),"")) | J44: =IF($B44="","",N($H44)*N($I44))
B45: =IF(35<=MAX(②発注数を決める!$Z$10:$Z$409),35,"") | C45: =IF($B45="","",IFERROR(INDEX(発注計算!$F$6:$F$405,MATCH(35,②発注数を決める!$Z$10:$Z$409,0)),"")) | D45: =IF($B45="","",IFERROR(INDEX(発注計算!$C$6:$C$405,MATCH(35,②発注数を決める!$Z$10:$Z$409,0))&"","")) | E45: =IF($B45="","",IFERROR(INDEX(②発注数を決める!$C$10:$C$409,MATCH(35,②発注数を決める!$Z$10:$Z$409,0))&"","")) | F45: =IF($B45="","",IFERROR(INDEX(商品マスタ!$J$6:$J$1005,MATCH($D45,商品マスタ!$B$6:$B$1005,0)),"ケース")) | G45: =IF($B45="","",IFERROR(INDEX(発注計算!$G$6:$G$405,MATCH(35,②発注数を決める!$Z$10:$Z$409,0)),"")) | H45: =IF($B45="","",IFERROR(INDEX(②発注数を決める!$J$10:$J$409,MATCH(35,②発注数を決める!$Z$10:$Z$409,0)),"")) | I45: =IF($B45="","",IFERROR(INDEX(発注計算!$H$6:$H$405,MATCH(35,②発注数を決める!$Z$10:$Z$409,0)),"")) | J45: =IF($B45="","",N($H45)*N($I45))
B46: =IF(36<=MAX(②発注数を決める!$Z$10:$Z$409),36,"") | C46: =IF($B46="","",IFERROR(INDEX(発注計算!$F$6:$F$405,MATCH(36,②発注数を決める!$Z$10:$Z$409,0)),"")) | D46: =IF($B46="","",IFERROR(INDEX(発注計算!$C$6:$C$405,MATCH(36,②発注数を決める!$Z$10:$Z$409,0))&"","")) | E46: =IF($B46="","",IFERROR(INDEX(②発注数を決める!$C$10:$C$409,MATCH(36,②発注数を決める!$Z$10:$Z$409,0))&"","")) | F46: =IF($B46="","",IFERROR(INDEX(商品マスタ!$J$6:$J$1005,MATCH($D46,商品マスタ!$B$6:$B$1005,0)),"ケース")) | G46: =IF($B46="","",IFERROR(INDEX(発注計算!$G$6:$G$405,MATCH(36,②発注数を決める!$Z$10:$Z$409,0)),"")) | H46: =IF($B46="","",IFERROR(INDEX(②発注数を決める!$J$10:$J$409,MATCH(36,②発注数を決める!$Z$10:$Z$409,0)),"")) | I46: =IF($B46="","",IFERROR(INDEX(発注計算!$H$6:$H$405,MATCH(36,②発注数を決める!$Z$10:$Z$409,0)),"")) | J46: =IF($B46="","",N($H46)*N($I46))
B47: =IF(37<=MAX(②発注数を決める!$Z$10:$Z$409),37,"") | C47: =IF($B47="","",IFERROR(INDEX(発注計算!$F$6:$F$405,MATCH(37,②発注数を決める!$Z$10:$Z$409,0)),"")) | D47: =IF($B47="","",IFERROR(INDEX(発注計算!$C$6:$C$405,MATCH(37,②発注数を決める!$Z$10:$Z$409,0))&"","")) | E47: =IF($B47="","",IFERROR(INDEX(②発注数を決める!$C$10:$C$409,MATCH(37,②発注数を決める!$Z$10:$Z$409,0))&"","")) | F47: =IF($B47="","",IFERROR(INDEX(商品マスタ!$J$6:$J$1005,MATCH($D47,商品マスタ!$B$6:$B$1005,0)),"ケース")) | G47: =IF($B47="","",IFERROR(INDEX(発注計算!$G$6:$G$405,MATCH(37,②発注数を決める!$Z$10:$Z$409,0)),"")) | H47: =IF($B47="","",IFERROR(INDEX(②発注数を決める!$J$10:$J$409,MATCH(37,②発注数を決める!$Z$10:$Z$409,0)),"")) | I47: =IF($B47="","",IFERROR(INDEX(発注計算!$H$6:$H$405,MATCH(37,②発注数を決める!$Z$10:$Z$409,0)),"")) | J47: =IF($B47="","",N($H47)*N($I47))
B48: =IF(38<=MAX(②発注数を決める!$Z$10:$Z$409),38,"") | C48: =IF($B48="","",IFERROR(INDEX(発注計算!$F$6:$F$405,MATCH(38,②発注数を決める!$Z$10:$Z$409,0)),"")) | D48: =IF($B48="","",IFERROR(INDEX(発注計算!$C$6:$C$405,MATCH(38,②発注数を決める!$Z$10:$Z$409,0))&"","")) | E48: =IF($B48="","",IFERROR(INDEX(②発注数を決める!$C$10:$C$409,MATCH(38,②発注数を決める!$Z$10:$Z$409,0))&"","")) | F48: =IF($B48="","",IFERROR(INDEX(商品マスタ!$J$6:$J$1005,MATCH($D48,商品マスタ!$B$6:$B$1005,0)),"ケース")) | G48: =IF($B48="","",IFERROR(INDEX(発注計算!$G$6:$G$405,MATCH(38,②発注数を決める!$Z$10:$Z$409,0)),"")) | H48: =IF($B48="","",IFERROR(INDEX(②発注数を決める!$J$10:$J$409,MATCH(38,②発注数を決める!$Z$10:$Z$409,0)),"")) | I48: =IF($B48="","",IFERROR(INDEX(発注計算!$H$6:$H$405,MATCH(38,②発注数を決める!$Z$10:$Z$409,0)),"")) | J48: =IF($B48="","",N($H48)*N($I48))
B49: =IF(39<=MAX(②発注数を決める!$Z$10:$Z$409),39,"") | C49: =IF($B49="","",IFERROR(INDEX(発注計算!$F$6:$F$405,MATCH(39,②発注数を決める!$Z$10:$Z$409,0)),"")) | D49: =IF($B49="","",IFERROR(INDEX(発注計算!$C$6:$C$405,MATCH(39,②発注数を決める!$Z$10:$Z$409,0))&"","")) | E49: =IF($B49="","",IFERROR(INDEX(②発注数を決める!$C$10:$C$409,MATCH(39,②発注数を決める!$Z$10:$Z$409,0))&"","")) | F49: =IF($B49="","",IFERROR(INDEX(商品マスタ!$J$6:$J$1005,MATCH($D49,商品マスタ!$B$6:$B$1005,0)),"ケース")) | G49: =IF($B49="","",IFERROR(INDEX(発注計算!$G$6:$G$405,MATCH(39,②発注数を決める!$Z$10:$Z$409,0)),"")) | H49: =IF($B49="","",IFERROR(INDEX(②発注数を決める!$J$10:$J$409,MATCH(39,②発注数を決める!$Z$10:$Z$409,0)),"")) | I49: =IF($B49="","",IFERROR(INDEX(発注計算!$H$6:$H$405,MATCH(39,②発注数を決める!$Z$10:$Z$409,0)),"")) | J49: =IF($B49="","",N($H49)*N($I49))
B50: =IF(40<=MAX(②発注数を決める!$Z$10:$Z$409),40,"") | C50: =IF($B50="","",IFERROR(INDEX(発注計算!$F$6:$F$405,MATCH(40,②発注数を決める!$Z$10:$Z$409,0)),"")) | D50: =IF($B50="","",IFERROR(INDEX(発注計算!$C$6:$C$405,MATCH(40,②発注数を決める!$Z$10:$Z$409,0))&"","")) | E50: =IF($B50="","",IFERROR(INDEX(②発注数を決める!$C$10:$C$409,MATCH(40,②発注数を決める!$Z$10:$Z$409,0))&"","")) | F50: =IF($B50="","",IFERROR(INDEX(商品マスタ!$J$6:$J$1005,MATCH($D50,商品マスタ!$B$6:$B$1005,0)),"ケース")) | G50: =IF($B50="","",IFERROR(INDEX(発注計算!$G$6:$G$405,MATCH(40,②発注数を決める!$Z$10:$Z$409,0)),"")) | H50: =IF($B50="","",IFERROR(INDEX(②発注数を決める!$J$10:$J$409,MATCH(40,②発注数を決める!$Z$10:$Z$409,0)),"")) | I50: =IF($B50="","",IFERROR(INDEX(発注計算!$H$6:$H$405,MATCH(40,②発注数を決める!$Z$10:$Z$409,0)),"")) | J50: =IF($B50="","",N($H50)*N($I50))
B51: =IF(41<=MAX(②発注数を決める!$Z$10:$Z$409),41,"") | C51: =IF($B51="","",IFERROR(INDEX(発注計算!$F$6:$F$405,MATCH(41,②発注数を決める!$Z$10:$Z$409,0)),"")) | D51: =IF($B51="","",IFERROR(INDEX(発注計算!$C$6:$C$405,MATCH(41,②発注数を決める!$Z$10:$Z$409,0))&"","")) | E51: =IF($B51="","",IFERROR(INDEX(②発注数を決める!$C$10:$C$409,MATCH(41,②発注数を決める!$Z$10:$Z$409,0))&"","")) | F51: =IF($B51="","",IFERROR(INDEX(商品マスタ!$J$6:$J$1005,MATCH($D51,商品マスタ!$B$6:$B$1005,0)),"ケース")) | G51: =IF($B51="","",IFERROR(INDEX(発注計算!$G$6:$G$405,MATCH(41,②発注数を決める!$Z$10:$Z$409,0)),"")) | H51: =IF($B51="","",IFERROR(INDEX(②発注数を決める!$J$10:$J$409,MATCH(41,②発注数を決める!$Z$10:$Z$409,0)),"")) | I51: =IF($B51="","",IFERROR(INDEX(発注計算!$H$6:$H$405,MATCH(41,②発注数を決める!$Z$10:$Z$409,0)),"")) | J51: =IF($B51="","",N($H51)*N($I51))
B52: =IF(42<=MAX(②発注数を決める!$Z$10:$Z$409),42,"") | C52: =IF($B52="","",IFERROR(INDEX(発注計算!$F$6:$F$405,MATCH(42,②発注数を決める!$Z$10:$Z$409,0)),"")) | D52: =IF($B52="","",IFERROR(INDEX(発注計算!$C$6:$C$405,MATCH(42,②発注数を決める!$Z$10:$Z$409,0))&"","")) | E52: =IF($B52="","",IFERROR(INDEX(②発注数を決める!$C$10:$C$409,MATCH(42,②発注数を決める!$Z$10:$Z$409,0))&"","")) | F52: =IF($B52="","",IFERROR(INDEX(商品マスタ!$J$6:$J$1005,MATCH($D52,商品マスタ!$B$6:$B$1005,0)),"ケース")) | G52: =IF($B52="","",IFERROR(INDEX(発注計算!$G$6:$G$405,MATCH(42,②発注数を決める!$Z$10:$Z$409,0)),"")) | H52: =IF($B52="","",IFERROR(INDEX(②発注数を決める!$J$10:$J$409,MATCH(42,②発注数を決める!$Z$10:$Z$409,0)),"")) | I52: =IF($B52="","",IFERROR(INDEX(発注計算!$H$6:$H$405,MATCH(42,②発注数を決める!$Z$10:$Z$409,0)),"")) | J52: =IF($B52="","",N($H52)*N($I52))
B53: =IF(43<=MAX(②発注数を決める!$Z$10:$Z$409),43,"") | C53: =IF($B53="","",IFERROR(INDEX(発注計算!$F$6:$F$405,MATCH(43,②発注数を決める!$Z$10:$Z$409,0)),"")) | D53: =IF($B53="","",IFERROR(INDEX(発注計算!$C$6:$C$405,MATCH(43,②発注数を決める!$Z$10:$Z$409,0))&"","")) | E53: =IF($B53="","",IFERROR(INDEX(②発注数を決める!$C$10:$C$409,MATCH(43,②発注数を決める!$Z$10:$Z$409,0))&"","")) | F53: =IF($B53="","",IFERROR(INDEX(商品マスタ!$J$6:$J$1005,MATCH($D53,商品マスタ!$B$6:$B$1005,0)),"ケース")) | G53: =IF($B53="","",IFERROR(INDEX(発注計算!$G$6:$G$405,MATCH(43,②発注数を決める!$Z$10:$Z$409,0)),"")) | H53: =IF($B53="","",IFERROR(INDEX(②発注数を決める!$J$10:$J$409,MATCH(43,②発注数を決める!$Z$10:$Z$409,0)),"")) | I53: =IF($B53="","",IFERROR(INDEX(発注計算!$H$6:$H$405,MATCH(43,②発注数を決める!$Z$10:$Z$409,0)),"")) | J53: =IF($B53="","",N($H53)*N($I53))
B54: =IF(44<=MAX(②発注数を決める!$Z$10:$Z$409),44,"") | C54: =IF($B54="","",IFERROR(INDEX(発注計算!$F$6:$F$405,MATCH(44,②発注数を決める!$Z$10:$Z$409,0)),"")) | D54: =IF($B54="","",IFERROR(INDEX(発注計算!$C$6:$C$405,MATCH(44,②発注数を決める!$Z$10:$Z$409,0))&"","")) | E54: =IF($B54="","",IFERROR(INDEX(②発注数を決める!$C$10:$C$409,MATCH(44,②発注数を決める!$Z$10:$Z$409,0))&"","")) | F54: =IF($B54="","",IFERROR(INDEX(商品マスタ!$J$6:$J$1005,MATCH($D54,商品マスタ!$B$6:$B$1005,0)),"ケース")) | G54: =IF($B54="","",IFERROR(INDEX(発注計算!$G$6:$G$405,MATCH(44,②発注数を決める!$Z$10:$Z$409,0)),"")) | H54: =IF($B54="","",IFERROR(INDEX(②発注数を決める!$J$10:$J$409,MATCH(44,②発注数を決める!$Z$10:$Z$409,0)),"")) | I54: =IF($B54="","",IFERROR(INDEX(発注計算!$H$6:$H$405,MATCH(44,②発注数を決める!$Z$10:$Z$409,0)),"")) | J54: =IF($B54="","",N($H54)*N($I54))
B55: =IF(45<=MAX(②発注数を決める!$Z$10:$Z$409),45,"") | C55: =IF($B55="","",IFERROR(INDEX(発注計算!$F$6:$F$405,MATCH(45,②発注数を決める!$Z$10:$Z$409,0)),"")) | D55: =IF($B55="","",IFERROR(INDEX(発注計算!$C$6:$C$405,MATCH(45,②発注数を決める!$Z$10:$Z$409,0))&"","")) | E55: =IF($B55="","",IFERROR(INDEX(②発注数を決める!$C$10:$C$409,MATCH(45,②発注数を決める!$Z$10:$Z$409,0))&"","")) | F55: =IF($B55="","",IFERROR(INDEX(商品マスタ!$J$6:$J$1005,MATCH($D55,商品マスタ!$B$6:$B$1005,0)),"ケース")) | G55: =IF($B55="","",IFERROR(INDEX(発注計算!$G$6:$G$405,MATCH(45,②発注数を決める!$Z$10:$Z$409,0)),"")) | H55: =IF($B55="","",IFERROR(INDEX(②発注数を決める!$J$10:$J$409,MATCH(45,②発注数を決める!$Z$10:$Z$409,0)),"")) | I55: =IF($B55="","",IFERROR(INDEX(発注計算!$H$6:$H$405,MATCH(45,②発注数を決める!$Z$10:$Z$409,0)),"")) | J55: =IF($B55="","",N($H55)*N($I55))
B56: =IF(46<=MAX(②発注数を決める!$Z$10:$Z$409),46,"") | C56: =IF($B56="","",IFERROR(INDEX(発注計算!$F$6:$F$405,MATCH(46,②発注数を決める!$Z$10:$Z$409,0)),"")) | D56: =IF($B56="","",IFERROR(INDEX(発注計算!$C$6:$C$405,MATCH(46,②発注数を決める!$Z$10:$Z$409,0))&"","")) | E56: =IF($B56="","",IFERROR(INDEX(②発注数を決める!$C$10:$C$409,MATCH(46,②発注数を決める!$Z$10:$Z$409,0))&"","")) | F56: =IF($B56="","",IFERROR(INDEX(商品マスタ!$J$6:$J$1005,MATCH($D56,商品マスタ!$B$6:$B$1005,0)),"ケース")) | G56: =IF($B56="","",IFERROR(INDEX(発注計算!$G$6:$G$405,MATCH(46,②発注数を決める!$Z$10:$Z$409,0)),"")) | H56: =IF($B56="","",IFERROR(INDEX(②発注数を決める!$J$10:$J$409,MATCH(46,②発注数を決める!$Z$10:$Z$409,0)),"")) | I56: =IF($B56="","",IFERROR(INDEX(発注計算!$H$6:$H$405,MATCH(46,②発注数を決める!$Z$10:$Z$409,0)),"")) | J56: =IF($B56="","",N($H56)*N($I56))
B57: =IF(47<=MAX(②発注数を決める!$Z$10:$Z$409),47,"") | C57: =IF($B57="","",IFERROR(INDEX(発注計算!$F$6:$F$405,MATCH(47,②発注数を決める!$Z$10:$Z$409,0)),"")) | D57: =IF($B57="","",IFERROR(INDEX(発注計算!$C$6:$C$405,MATCH(47,②発注数を決める!$Z$10:$Z$409,0))&"","")) | E57: =IF($B57="","",IFERROR(INDEX(②発注数を決める!$C$10:$C$409,MATCH(47,②発注数を決める!$Z$10:$Z$409,0))&"","")) | F57: =IF($B57="","",IFERROR(INDEX(商品マスタ!$J$6:$J$1005,MATCH($D57,商品マスタ!$B$6:$B$1005,0)),"ケース")) | G57: =IF($B57="","",IFERROR(INDEX(発注計算!$G$6:$G$405,MATCH(47,②発注数を決める!$Z$10:$Z$409,0)),"")) | H57: =IF($B57="","",IFERROR(INDEX(②発注数を決める!$J$10:$J$409,MATCH(47,②発注数を決める!$Z$10:$Z$409,0)),"")) | I57: =IF($B57="","",IFERROR(INDEX(発注計算!$H$6:$H$405,MATCH(47,②発注数を決める!$Z$10:$Z$409,0)),"")) | J57: =IF($B57="","",N($H57)*N($I57))
B58: =IF(48<=MAX(②発注数を決める!$Z$10:$Z$409),48,"") | C58: =IF($B58="","",IFERROR(INDEX(発注計算!$F$6:$F$405,MATCH(48,②発注数を決める!$Z$10:$Z$409,0)),"")) | D58: =IF($B58="","",IFERROR(INDEX(発注計算!$C$6:$C$405,MATCH(48,②発注数を決める!$Z$10:$Z$409,0))&"","")) | E58: =IF($B58="","",IFERROR(INDEX(②発注数を決める!$C$10:$C$409,MATCH(48,②発注数を決める!$Z$10:$Z$409,0))&"","")) | F58: =IF($B58="","",IFERROR(INDEX(商品マスタ!$J$6:$J$1005,MATCH($D58,商品マスタ!$B$6:$B$1005,0)),"ケース")) | G58: =IF($B58="","",IFERROR(INDEX(発注計算!$G$6:$G$405,MATCH(48,②発注数を決める!$Z$10:$Z$409,0)),"")) | H58: =IF($B58="","",IFERROR(INDEX(②発注数を決める!$J$10:$J$409,MATCH(48,②発注数を決める!$Z$10:$Z$409,0)),"")) | I58: =IF($B58="","",IFERROR(INDEX(発注計算!$H$6:$H$405,MATCH(48,②発注数を決める!$Z$10:$Z$409,0)),"")) | J58: =IF($B58="","",N($H58)*N($I58))
B59: =IF(49<=MAX(②発注数を決める!$Z$10:$Z$409),49,"") | C59: =IF($B59="","",IFERROR(INDEX(発注計算!$F$6:$F$405,MATCH(49,②発注数を決める!$Z$10:$Z$409,0)),"")) | D59: =IF($B59="","",IFERROR(INDEX(発注計算!$C$6:$C$405,MATCH(49,②発注数を決める!$Z$10:$Z$409,0))&"","")) | E59: =IF($B59="","",IFERROR(INDEX(②発注数を決める!$C$10:$C$409,MATCH(49,②発注数を決める!$Z$10:$Z$409,0))&"","")) | F59: =IF($B59="","",IFERROR(INDEX(商品マスタ!$J$6:$J$1005,MATCH($D59,商品マスタ!$B$6:$B$1005,0)),"ケース")) | G59: =IF($B59="","",IFERROR(INDEX(発注計算!$G$6:$G$405,MATCH(49,②発注数を決める!$Z$10:$Z$409,0)),"")) | H59: =IF($B59="","",IFERROR(INDEX(②発注数を決める!$J$10:$J$409,MATCH(49,②発注数を決める!$Z$10:$Z$409,0)),"")) | I59: =IF($B59="","",IFERROR(INDEX(発注計算!$H$6:$H$405,MATCH(49,②発注数を決める!$Z$10:$Z$409,0)),"")) | J59: =IF($B59="","",N($H59)*N($I59))
B60: =IF(50<=MAX(②発注数を決める!$Z$10:$Z$409),50,"") | C60: =IF($B60="","",IFERROR(INDEX(発注計算!$F$6:$F$405,MATCH(50,②発注数を決める!$Z$10:$Z$409,0)),"")) | D60: =IF($B60="","",IFERROR(INDEX(発注計算!$C$6:$C$405,MATCH(50,②発注数を決める!$Z$10:$Z$409,0))&"","")) | E60: =IF($B60="","",IFERROR(INDEX(②発注数を決める!$C$10:$C$409,MATCH(50,②発注数を決める!$Z$10:$Z$409,0))&"","")) | F60: =IF($B60="","",IFERROR(INDEX(商品マスタ!$J$6:$J$1005,MATCH($D60,商品マスタ!$B$6:$B$1005,0)),"ケース")) | G60: =IF($B60="","",IFERROR(INDEX(発注計算!$G$6:$G$405,MATCH(50,②発注数を決める!$Z$10:$Z$409,0)),"")) | H60: =IF($B60="","",IFERROR(INDEX(②発注数を決める!$J$10:$J$409,MATCH(50,②発注数を決める!$Z$10:$Z$409,0)),"")) | I60: =IF($B60="","",IFERROR(INDEX(発注計算!$H$6:$H$405,MATCH(50,②発注数を決める!$Z$10:$Z$409,0)),"")) | J60: =IF($B60="","",N($H60)*N($I60))
B61: =IF(51<=MAX(②発注数を決める!$Z$10:$Z$409),51,"") | C61: =IF($B61="","",IFERROR(INDEX(発注計算!$F$6:$F$405,MATCH(51,②発注数を決める!$Z$10:$Z$409,0)),"")) | D61: =IF($B61="","",IFERROR(INDEX(発注計算!$C$6:$C$405,MATCH(51,②発注数を決める!$Z$10:$Z$409,0))&"","")) | E61: =IF($B61="","",IFERROR(INDEX(②発注数を決める!$C$10:$C$409,MATCH(51,②発注数を決める!$Z$10:$Z$409,0))&"","")) | F61: =IF($B61="","",IFERROR(INDEX(商品マスタ!$J$6:$J$1005,MATCH($D61,商品マスタ!$B$6:$B$1005,0)),"ケース")) | G61: =IF($B61="","",IFERROR(INDEX(発注計算!$G$6:$G$405,MATCH(51,②発注数を決める!$Z$10:$Z$409,0)),"")) | H61: =IF($B61="","",IFERROR(INDEX(②発注数を決める!$J$10:$J$409,MATCH(51,②発注数を決める!$Z$10:$Z$409,0)),"")) | I61: =IF($B61="","",IFERROR(INDEX(発注計算!$H$6:$H$405,MATCH(51,②発注数を決める!$Z$10:$Z$409,0)),"")) | J61: =IF($B61="","",N($H61)*N($I61))
B62: =IF(52<=MAX(②発注数を決める!$Z$10:$Z$409),52,"") | C62: =IF($B62="","",IFERROR(INDEX(発注計算!$F$6:$F$405,MATCH(52,②発注数を決める!$Z$10:$Z$409,0)),"")) | D62: =IF($B62="","",IFERROR(INDEX(発注計算!$C$6:$C$405,MATCH(52,②発注数を決める!$Z$10:$Z$409,0))&"","")) | E62: =IF($B62="","",IFERROR(INDEX(②発注数を決める!$C$10:$C$409,MATCH(52,②発注数を決める!$Z$10:$Z$409,0))&"","")) | F62: =IF($B62="","",IFERROR(INDEX(商品マスタ!$J$6:$J$1005,MATCH($D62,商品マスタ!$B$6:$B$1005,0)),"ケース")) | G62: =IF($B62="","",IFERROR(INDEX(発注計算!$G$6:$G$405,MATCH(52,②発注数を決める!$Z$10:$Z$409,0)),"")) | H62: =IF($B62="","",IFERROR(INDEX(②発注数を決める!$J$10:$J$409,MATCH(52,②発注数を決める!$Z$10:$Z$409,0)),"")) | I62: =IF($B62="","",IFERROR(INDEX(発注計算!$H$6:$H$405,MATCH(52,②発注数を決める!$Z$10:$Z$409,0)),"")) | J62: =IF($B62="","",N($H62)*N($I62))
B63: =IF(53<=MAX(②発注数を決める!$Z$10:$Z$409),53,"") | C63: =IF($B63="","",IFERROR(INDEX(発注計算!$F$6:$F$405,MATCH(53,②発注数を決める!$Z$10:$Z$409,0)),"")) | D63: =IF($B63="","",IFERROR(INDEX(発注計算!$C$6:$C$405,MATCH(53,②発注数を決める!$Z$10:$Z$409,0))&"","")) | E63: =IF($B63="","",IFERROR(INDEX(②発注数を決める!$C$10:$C$409,MATCH(53,②発注数を決める!$Z$10:$Z$409,0))&"","")) | F63: =IF($B63="","",IFERROR(INDEX(商品マスタ!$J$6:$J$1005,MATCH($D63,商品マスタ!$B$6:$B$1005,0)),"ケース")) | G63: =IF($B63="","",IFERROR(INDEX(発注計算!$G$6:$G$405,MATCH(53,②発注数を決める!$Z$10:$Z$409,0)),"")) | H63: =IF($B63="","",IFERROR(INDEX(②発注数を決める!$J$10:$J$409,MATCH(53,②発注数を決める!$Z$10:$Z$409,0)),"")) | I63: =IF($B63="","",IFERROR(INDEX(発注計算!$H$6:$H$405,MATCH(53,②発注数を決める!$Z$10:$Z$409,0)),"")) | J63: =IF($B63="","",N($H63)*N($I63))
B64: =IF(54<=MAX(②発注数を決める!$Z$10:$Z$409),54,"") | C64: =IF($B64="","",IFERROR(INDEX(発注計算!$F$6:$F$405,MATCH(54,②発注数を決める!$Z$10:$Z$409,0)),"")) | D64: =IF($B64="","",IFERROR(INDEX(発注計算!$C$6:$C$405,MATCH(54,②発注数を決める!$Z$10:$Z$409,0))&"","")) | E64: =IF($B64="","",IFERROR(INDEX(②発注数を決める!$C$10:$C$409,MATCH(54,②発注数を決める!$Z$10:$Z$409,0))&"","")) | F64: =IF($B64="","",IFERROR(INDEX(商品マスタ!$J$6:$J$1005,MATCH($D64,商品マスタ!$B$6:$B$1005,0)),"ケース")) | G64: =IF($B64="","",IFERROR(INDEX(発注計算!$G$6:$G$405,MATCH(54,②発注数を決める!$Z$10:$Z$409,0)),"")) | H64: =IF($B64="","",IFERROR(INDEX(②発注数を決める!$J$10:$J$409,MATCH(54,②発注数を決める!$Z$10:$Z$409,0)),"")) | I64: =IF($B64="","",IFERROR(INDEX(発注計算!$H$6:$H$405,MATCH(54,②発注数を決める!$Z$10:$Z$409,0)),"")) | J64: =IF($B64="","",N($H64)*N($I64))
B65: =IF(55<=MAX(②発注数を決める!$Z$10:$Z$409),55,"") | C65: =IF($B65="","",IFERROR(INDEX(発注計算!$F$6:$F$405,MATCH(55,②発注数を決める!$Z$10:$Z$409,0)),"")) | D65: =IF($B65="","",IFERROR(INDEX(発注計算!$C$6:$C$405,MATCH(55,②発注数を決める!$Z$10:$Z$409,0))&"","")) | E65: =IF($B65="","",IFERROR(INDEX(②発注数を決める!$C$10:$C$409,MATCH(55,②発注数を決める!$Z$10:$Z$409,0))&"","")) | F65: =IF($B65="","",IFERROR(INDEX(商品マスタ!$J$6:$J$1005,MATCH($D65,商品マスタ!$B$6:$B$1005,0)),"ケース")) | G65: =IF($B65="","",IFERROR(INDEX(発注計算!$G$6:$G$405,MATCH(55,②発注数を決める!$Z$10:$Z$409,0)),"")) | H65: =IF($B65="","",IFERROR(INDEX(②発注数を決める!$J$10:$J$409,MATCH(55,②発注数を決める!$Z$10:$Z$409,0)),"")) | I65: =IF($B65="","",IFERROR(INDEX(発注計算!$H$6:$H$405,MATCH(55,②発注数を決める!$Z$10:$Z$409,0)),"")) | J65: =IF($B65="","",N($H65)*N($I65))
B66: =IF(56<=MAX(②発注数を決める!$Z$10:$Z$409),56,"") | C66: =IF($B66="","",IFERROR(INDEX(発注計算!$F$6:$F$405,MATCH(56,②発注数を決める!$Z$10:$Z$409,0)),"")) | D66: =IF($B66="","",IFERROR(INDEX(発注計算!$C$6:$C$405,MATCH(56,②発注数を決める!$Z$10:$Z$409,0))&"","")) | E66: =IF($B66="","",IFERROR(INDEX(②発注数を決める!$C$10:$C$409,MATCH(56,②発注数を決める!$Z$10:$Z$409,0))&"","")) | F66: =IF($B66="","",IFERROR(INDEX(商品マスタ!$J$6:$J$1005,MATCH($D66,商品マスタ!$B$6:$B$1005,0)),"ケース")) | G66: =IF($B66="","",IFERROR(INDEX(発注計算!$G$6:$G$405,MATCH(56,②発注数を決める!$Z$10:$Z$409,0)),"")) | H66: =IF($B66="","",IFERROR(INDEX(②発注数を決める!$J$10:$J$409,MATCH(56,②発注数を決める!$Z$10:$Z$409,0)),"")) | I66: =IF($B66="","",IFERROR(INDEX(発注計算!$H$6:$H$405,MATCH(56,②発注数を決める!$Z$10:$Z$409,0)),"")) | J66: =IF($B66="","",N($H66)*N($I66))
B67: =IF(57<=MAX(②発注数を決める!$Z$10:$Z$409),57,"") | C67: =IF($B67="","",IFERROR(INDEX(発注計算!$F$6:$F$405,MATCH(57,②発注数を決める!$Z$10:$Z$409,0)),"")) | D67: =IF($B67="","",IFERROR(INDEX(発注計算!$C$6:$C$405,MATCH(57,②発注数を決める!$Z$10:$Z$409,0))&"","")) | E67: =IF($B67="","",IFERROR(INDEX(②発注数を決める!$C$10:$C$409,MATCH(57,②発注数を決める!$Z$10:$Z$409,0))&"","")) | F67: =IF($B67="","",IFERROR(INDEX(商品マスタ!$J$6:$J$1005,MATCH($D67,商品マスタ!$B$6:$B$1005,0)),"ケース")) | G67: =IF($B67="","",IFERROR(INDEX(発注計算!$G$6:$G$405,MATCH(57,②発注数を決める!$Z$10:$Z$409,0)),"")) | H67: =IF($B67="","",IFERROR(INDEX(②発注数を決める!$J$10:$J$409,MATCH(57,②発注数を決める!$Z$10:$Z$409,0)),"")) | I67: =IF($B67="","",IFERROR(INDEX(発注計算!$H$6:$H$405,MATCH(57,②発注数を決める!$Z$10:$Z$409,0)),"")) | J67: =IF($B67="","",N($H67)*N($I67))
B68: =IF(58<=MAX(②発注数を決める!$Z$10:$Z$409),58,"") | C68: =IF($B68="","",IFERROR(INDEX(発注計算!$F$6:$F$405,MATCH(58,②発注数を決める!$Z$10:$Z$409,0)),"")) | D68: =IF($B68="","",IFERROR(INDEX(発注計算!$C$6:$C$405,MATCH(58,②発注数を決める!$Z$10:$Z$409,0))&"","")) | E68: =IF($B68="","",IFERROR(INDEX(②発注数を決める!$C$10:$C$409,MATCH(58,②発注数を決める!$Z$10:$Z$409,0))&"","")) | F68: =IF($B68="","",IFERROR(INDEX(商品マスタ!$J$6:$J$1005,MATCH($D68,商品マスタ!$B$6:$B$1005,0)),"ケース")) | G68: =IF($B68="","",IFERROR(INDEX(発注計算!$G$6:$G$405,MATCH(58,②発注数を決める!$Z$10:$Z$409,0)),"")) | H68: =IF($B68="","",IFERROR(INDEX(②発注数を決める!$J$10:$J$409,MATCH(58,②発注数を決める!$Z$10:$Z$409,0)),"")) | I68: =IF($B68="","",IFERROR(INDEX(発注計算!$H$6:$H$405,MATCH(58,②発注数を決める!$Z$10:$Z$409,0)),"")) | J68: =IF($B68="","",N($H68)*N($I68))
B69: =IF(59<=MAX(②発注数を決める!$Z$10:$Z$409),59,"") | C69: =IF($B69="","",IFERROR(INDEX(発注計算!$F$6:$F$405,MATCH(59,②発注数を決める!$Z$10:$Z$409,0)),"")) | D69: =IF($B69="","",IFERROR(INDEX(発注計算!$C$6:$C$405,MATCH(59,②発注数を決める!$Z$10:$Z$409,0))&"","")) | E69: =IF($B69="","",IFERROR(INDEX(②発注数を決める!$C$10:$C$409,MATCH(59,②発注数を決める!$Z$10:$Z$409,0))&"","")) | F69: =IF($B69="","",IFERROR(INDEX(商品マスタ!$J$6:$J$1005,MATCH($D69,商品マスタ!$B$6:$B$1005,0)),"ケース")) | G69: =IF($B69="","",IFERROR(INDEX(発注計算!$G$6:$G$405,MATCH(59,②発注数を決める!$Z$10:$Z$409,0)),"")) | H69: =IF($B69="","",IFERROR(INDEX(②発注数を決める!$J$10:$J$409,MATCH(59,②発注数を決める!$Z$10:$Z$409,0)),"")) | I69: =IF($B69="","",IFERROR(INDEX(発注計算!$H$6:$H$405,MATCH(59,②発注数を決める!$Z$10:$Z$409,0)),"")) | J69: =IF($B69="","",N($H69)*N($I69))
B70: =IF(60<=MAX(②発注数を決める!$Z$10:$Z$409),60,"") | C70: =IF($B70="","",IFERROR(INDEX(発注計算!$F$6:$F$405,MATCH(60,②発注数を決める!$Z$10:$Z$409,0)),"")) | D70: =IF($B70="","",IFERROR(INDEX(発注計算!$C$6:$C$405,MATCH(60,②発注数を決める!$Z$10:$Z$409,0))&"","")) | E70: =IF($B70="","",IFERROR(INDEX(②発注数を決める!$C$10:$C$409,MATCH(60,②発注数を決める!$Z$10:$Z$409,0))&"","")) | F70: =IF($B70="","",IFERROR(INDEX(商品マスタ!$J$6:$J$1005,MATCH($D70,商品マスタ!$B$6:$B$1005,0)),"ケース")) | G70: =IF($B70="","",IFERROR(INDEX(発注計算!$G$6:$G$405,MATCH(60,②発注数を決める!$Z$10:$Z$409,0)),"")) | H70: =IF($B70="","",IFERROR(INDEX(②発注数を決める!$J$10:$J$409,MATCH(60,②発注数を決める!$Z$10:$Z$409,0)),"")) | I70: =IF($B70="","",IFERROR(INDEX(発注計算!$H$6:$H$405,MATCH(60,②発注数を決める!$Z$10:$Z$409,0)),"")) | J70: =IF($B70="","",N($H70)*N($I70))
B71: =IF(61<=MAX(②発注数を決める!$Z$10:$Z$409),61,"") | C71: =IF($B71="","",IFERROR(INDEX(発注計算!$F$6:$F$405,MATCH(61,②発注数を決める!$Z$10:$Z$409,0)),"")) | D71: =IF($B71="","",IFERROR(INDEX(発注計算!$C$6:$C$405,MATCH(61,②発注数を決める!$Z$10:$Z$409,0))&"","")) | E71: =IF($B71="","",IFERROR(INDEX(②発注数を決める!$C$10:$C$409,MATCH(61,②発注数を決める!$Z$10:$Z$409,0))&"","")) | F71: =IF($B71="","",IFERROR(INDEX(商品マスタ!$J$6:$J$1005,MATCH($D71,商品マスタ!$B$6:$B$1005,0)),"ケース")) | G71: =IF($B71="","",IFERROR(INDEX(発注計算!$G$6:$G$405,MATCH(61,②発注数を決める!$Z$10:$Z$409,0)),"")) | H71: =IF($B71="","",IFERROR(INDEX(②発注数を決める!$J$10:$J$409,MATCH(61,②発注数を決める!$Z$10:$Z$409,0)),"")) | I71: =IF($B71="","",IFERROR(INDEX(発注計算!$H$6:$H$405,MATCH(61,②発注数を決める!$Z$10:$Z$409,0)),"")) | J71: =IF($B71="","",N($H71)*N($I71))
B72: =IF(62<=MAX(②発注数を決める!$Z$10:$Z$409),62,"") | C72: =IF($B72="","",IFERROR(INDEX(発注計算!$F$6:$F$405,MATCH(62,②発注数を決める!$Z$10:$Z$409,0)),"")) | D72: =IF($B72="","",IFERROR(INDEX(発注計算!$C$6:$C$405,MATCH(62,②発注数を決める!$Z$10:$Z$409,0))&"","")) | E72: =IF($B72="","",IFERROR(INDEX(②発注数を決める!$C$10:$C$409,MATCH(62,②発注数を決める!$Z$10:$Z$409,0))&"","")) | F72: =IF($B72="","",IFERROR(INDEX(商品マスタ!$J$6:$J$1005,MATCH($D72,商品マスタ!$B$6:$B$1005,0)),"ケース")) | G72: =IF($B72="","",IFERROR(INDEX(発注計算!$G$6:$G$405,MATCH(62,②発注数を決める!$Z$10:$Z$409,0)),"")) | H72: =IF($B72="","",IFERROR(INDEX(②発注数を決める!$J$10:$J$409,MATCH(62,②発注数を決める!$Z$10:$Z$409,0)),"")) | I72: =IF($B72="","",IFERROR(INDEX(発注計算!$H$6:$H$405,MATCH(62,②発注数を決める!$Z$10:$Z$409,0)),"")) | J72: =IF($B72="","",N($H72)*N($I72))
B73: =IF(63<=MAX(②発注数を決める!$Z$10:$Z$409),63,"") | C73: =IF($B73="","",IFERROR(INDEX(発注計算!$F$6:$F$405,MATCH(63,②発注数を決める!$Z$10:$Z$409,0)),"")) | D73: =IF($B73="","",IFERROR(INDEX(発注計算!$C$6:$C$405,MATCH(63,②発注数を決める!$Z$10:$Z$409,0))&"","")) | E73: =IF($B73="","",IFERROR(INDEX(②発注数を決める!$C$10:$C$409,MATCH(63,②発注数を決める!$Z$10:$Z$409,0))&"","")) | F73: =IF($B73="","",IFERROR(INDEX(商品マスタ!$J$6:$J$1005,MATCH($D73,商品マスタ!$B$6:$B$1005,0)),"ケース")) | G73: =IF($B73="","",IFERROR(INDEX(発注計算!$G$6:$G$405,MATCH(63,②発注数を決める!$Z$10:$Z$409,0)),"")) | H73: =IF($B73="","",IFERROR(INDEX(②発注数を決める!$J$10:$J$409,MATCH(63,②発注数を決める!$Z$10:$Z$409,0)),"")) | I73: =IF($B73="","",IFERROR(INDEX(発注計算!$H$6:$H$405,MATCH(63,②発注数を決める!$Z$10:$Z$409,0)),"")) | J73: =IF($B73="","",N($H73)*N($I73))
B74: =IF(64<=MAX(②発注数を決める!$Z$10:$Z$409),64,"") | C74: =IF($B74="","",IFERROR(INDEX(発注計算!$F$6:$F$405,MATCH(64,②発注数を決める!$Z$10:$Z$409,0)),"")) | D74: =IF($B74="","",IFERROR(INDEX(発注計算!$C$6:$C$405,MATCH(64,②発注数を決める!$Z$10:$Z$409,0))&"","")) | E74: =IF($B74="","",IFERROR(INDEX(②発注数を決める!$C$10:$C$409,MATCH(64,②発注数を決める!$Z$10:$Z$409,0))&"","")) | F74: =IF($B74="","",IFERROR(INDEX(商品マスタ!$J$6:$J$1005,MATCH($D74,商品マスタ!$B$6:$B$1005,0)),"ケース")) | G74: =IF($B74="","",IFERROR(INDEX(発注計算!$G$6:$G$405,MATCH(64,②発注数を決める!$Z$10:$Z$409,0)),"")) | H74: =IF($B74="","",IFERROR(INDEX(②発注数を決める!$J$10:$J$409,MATCH(64,②発注数を決める!$Z$10:$Z$409,0)),"")) | I74: =IF($B74="","",IFERROR(INDEX(発注計算!$H$6:$H$405,MATCH(64,②発注数を決める!$Z$10:$Z$409,0)),"")) | J74: =IF($B74="","",N($H74)*N($I74))
B75: =IF(65<=MAX(②発注数を決める!$Z$10:$Z$409),65,"") | C75: =IF($B75="","",IFERROR(INDEX(発注計算!$F$6:$F$405,MATCH(65,②発注数を決める!$Z$10:$Z$409,0)),"")) | D75: =IF($B75="","",IFERROR(INDEX(発注計算!$C$6:$C$405,MATCH(65,②発注数を決める!$Z$10:$Z$409,0))&"","")) | E75: =IF($B75="","",IFERROR(INDEX(②発注数を決める!$C$10:$C$409,MATCH(65,②発注数を決める!$Z$10:$Z$409,0))&"","")) | F75: =IF($B75="","",IFERROR(INDEX(商品マスタ!$J$6:$J$1005,MATCH($D75,商品マスタ!$B$6:$B$1005,0)),"ケース")) | G75: =IF($B75="","",IFERROR(INDEX(発注計算!$G$6:$G$405,MATCH(65,②発注数を決める!$Z$10:$Z$409,0)),"")) | H75: =IF($B75="","",IFERROR(INDEX(②発注数を決める!$J$10:$J$409,MATCH(65,②発注数を決める!$Z$10:$Z$409,0)),"")) | I75: =IF($B75="","",IFERROR(INDEX(発注計算!$H$6:$H$405,MATCH(65,②発注数を決める!$Z$10:$Z$409,0)),"")) | J75: =IF($B75="","",N($H75)*N($I75))
B76: =IF(66<=MAX(②発注数を決める!$Z$10:$Z$409),66,"") | C76: =IF($B76="","",IFERROR(INDEX(発注計算!$F$6:$F$405,MATCH(66,②発注数を決める!$Z$10:$Z$409,0)),"")) | D76: =IF($B76="","",IFERROR(INDEX(発注計算!$C$6:$C$405,MATCH(66,②発注数を決める!$Z$10:$Z$409,0))&"","")) | E76: =IF($B76="","",IFERROR(INDEX(②発注数を決める!$C$10:$C$409,MATCH(66,②発注数を決める!$Z$10:$Z$409,0))&"","")) | F76: =IF($B76="","",IFERROR(INDEX(商品マスタ!$J$6:$J$1005,MATCH($D76,商品マスタ!$B$6:$B$1005,0)),"ケース")) | G76: =IF($B76="","",IFERROR(INDEX(発注計算!$G$6:$G$405,MATCH(66,②発注数を決める!$Z$10:$Z$409,0)),"")) | H76: =IF($B76="","",IFERROR(INDEX(②発注数を決める!$J$10:$J$409,MATCH(66,②発注数を決める!$Z$10:$Z$409,0)),"")) | I76: =IF($B76="","",IFERROR(INDEX(発注計算!$H$6:$H$405,MATCH(66,②発注数を決める!$Z$10:$Z$409,0)),"")) | J76: =IF($B76="","",N($H76)*N($I76))
B77: =IF(67<=MAX(②発注数を決める!$Z$10:$Z$409),67,"") | C77: =IF($B77="","",IFERROR(INDEX(発注計算!$F$6:$F$405,MATCH(67,②発注数を決める!$Z$10:$Z$409,0)),"")) | D77: =IF($B77="","",IFERROR(INDEX(発注計算!$C$6:$C$405,MATCH(67,②発注数を決める!$Z$10:$Z$409,0))&"","")) | E77: =IF($B77="","",IFERROR(INDEX(②発注数を決める!$C$10:$C$409,MATCH(67,②発注数を決める!$Z$10:$Z$409,0))&"","")) | F77: =IF($B77="","",IFERROR(INDEX(商品マスタ!$J$6:$J$1005,MATCH($D77,商品マスタ!$B$6:$B$1005,0)),"ケース")) | G77: =IF($B77="","",IFERROR(INDEX(発注計算!$G$6:$G$405,MATCH(67,②発注数を決める!$Z$10:$Z$409,0)),"")) | H77: =IF($B77="","",IFERROR(INDEX(②発注数を決める!$J$10:$J$409,MATCH(67,②発注数を決める!$Z$10:$Z$409,0)),"")) | I77: =IF($B77="","",IFERROR(INDEX(発注計算!$H$6:$H$405,MATCH(67,②発注数を決める!$Z$10:$Z$409,0)),"")) | J77: =IF($B77="","",N($H77)*N($I77))
B78: =IF(68<=MAX(②発注数を決める!$Z$10:$Z$409),68,"") | C78: =IF($B78="","",IFERROR(INDEX(発注計算!$F$6:$F$405,MATCH(68,②発注数を決める!$Z$10:$Z$409,0)),"")) | D78: =IF($B78="","",IFERROR(INDEX(発注計算!$C$6:$C$405,MATCH(68,②発注数を決める!$Z$10:$Z$409,0))&"","")) | E78: =IF($B78="","",IFERROR(INDEX(②発注数を決める!$C$10:$C$409,MATCH(68,②発注数を決める!$Z$10:$Z$409,0))&"","")) | F78: =IF($B78="","",IFERROR(INDEX(商品マスタ!$J$6:$J$1005,MATCH($D78,商品マスタ!$B$6:$B$1005,0)),"ケース")) | G78: =IF($B78="","",IFERROR(INDEX(発注計算!$G$6:$G$405,MATCH(68,②発注数を決める!$Z$10:$Z$409,0)),"")) | H78: =IF($B78="","",IFERROR(INDEX(②発注数を決める!$J$10:$J$409,MATCH(68,②発注数を決める!$Z$10:$Z$409,0)),"")) | I78: =IF($B78="","",IFERROR(INDEX(発注計算!$H$6:$H$405,MATCH(68,②発注数を決める!$Z$10:$Z$409,0)),"")) | J78: =IF($B78="","",N($H78)*N($I78))
B79: =IF(69<=MAX(②発注数を決める!$Z$10:$Z$409),69,"") | C79: =IF($B79="","",IFERROR(INDEX(発注計算!$F$6:$F$405,MATCH(69,②発注数を決める!$Z$10:$Z$409,0)),"")) | D79: =IF($B79="","",IFERROR(INDEX(発注計算!$C$6:$C$405,MATCH(69,②発注数を決める!$Z$10:$Z$409,0))&"","")) | E79: =IF($B79="","",IFERROR(INDEX(②発注数を決める!$C$10:$C$409,MATCH(69,②発注数を決める!$Z$10:$Z$409,0))&"","")) | F79: =IF($B79="","",IFERROR(INDEX(商品マスタ!$J$6:$J$1005,MATCH($D79,商品マスタ!$B$6:$B$1005,0)),"ケース")) | G79: =IF($B79="","",IFERROR(INDEX(発注計算!$G$6:$G$405,MATCH(69,②発注数を決める!$Z$10:$Z$409,0)),"")) | H79: =IF($B79="","",IFERROR(INDEX(②発注数を決める!$J$10:$J$409,MATCH(69,②発注数を決める!$Z$10:$Z$409,0)),"")) | I79: =IF($B79="","",IFERROR(INDEX(発注計算!$H$6:$H$405,MATCH(69,②発注数を決める!$Z$10:$Z$409,0)),"")) | J79: =IF($B79="","",N($H79)*N($I79))
B80: =IF(70<=MAX(②発注数を決める!$Z$10:$Z$409),70,"") | C80: =IF($B80="","",IFERROR(INDEX(発注計算!$F$6:$F$405,MATCH(70,②発注数を決める!$Z$10:$Z$409,0)),"")) | D80: =IF($B80="","",IFERROR(INDEX(発注計算!$C$6:$C$405,MATCH(70,②発注数を決める!$Z$10:$Z$409,0))&"","")) | E80: =IF($B80="","",IFERROR(INDEX(②発注数を決める!$C$10:$C$409,MATCH(70,②発注数を決める!$Z$10:$Z$409,0))&"","")) | F80: =IF($B80="","",IFERROR(INDEX(商品マスタ!$J$6:$J$1005,MATCH($D80,商品マスタ!$B$6:$B$1005,0)),"ケース")) | G80: =IF($B80="","",IFERROR(INDEX(発注計算!$G$6:$G$405,MATCH(70,②発注数を決める!$Z$10:$Z$409,0)),"")) | H80: =IF($B80="","",IFERROR(INDEX(②発注数を決める!$J$10:$J$409,MATCH(70,②発注数を決める!$Z$10:$Z$409,0)),"")) | I80: =IF($B80="","",IFERROR(INDEX(発注計算!$H$6:$H$405,MATCH(70,②発注数を決める!$Z$10:$Z$409,0)),"")) | J80: =IF($B80="","",N($H80)*N($I80))
B81: =IF(71<=MAX(②発注数を決める!$Z$10:$Z$409),71,"") | C81: =IF($B81="","",IFERROR(INDEX(発注計算!$F$6:$F$405,MATCH(71,②発注数を決める!$Z$10:$Z$409,0)),"")) | D81: =IF($B81="","",IFERROR(INDEX(発注計算!$C$6:$C$405,MATCH(71,②発注数を決める!$Z$10:$Z$409,0))&"","")) | E81: =IF($B81="","",IFERROR(INDEX(②発注数を決める!$C$10:$C$409,MATCH(71,②発注数を決める!$Z$10:$Z$409,0))&"","")) | F81: =IF($B81="","",IFERROR(INDEX(商品マスタ!$J$6:$J$1005,MATCH($D81,商品マスタ!$B$6:$B$1005,0)),"ケース")) | G81: =IF($B81="","",IFERROR(INDEX(発注計算!$G$6:$G$405,MATCH(71,②発注数を決める!$Z$10:$Z$409,0)),"")) | H81: =IF($B81="","",IFERROR(INDEX(②発注数を決める!$J$10:$J$409,MATCH(71,②発注数を決める!$Z$10:$Z$409,0)),"")) | I81: =IF($B81="","",IFERROR(INDEX(発注計算!$H$6:$H$405,MATCH(71,②発注数を決める!$Z$10:$Z$409,0)),"")) | J81: =IF($B81="","",N($H81)*N($I81))
B82: =IF(72<=MAX(②発注数を決める!$Z$10:$Z$409),72,"") | C82: =IF($B82="","",IFERROR(INDEX(発注計算!$F$6:$F$405,MATCH(72,②発注数を決める!$Z$10:$Z$409,0)),"")) | D82: =IF($B82="","",IFERROR(INDEX(発注計算!$C$6:$C$405,MATCH(72,②発注数を決める!$Z$10:$Z$409,0))&"","")) | E82: =IF($B82="","",IFERROR(INDEX(②発注数を決める!$C$10:$C$409,MATCH(72,②発注数を決める!$Z$10:$Z$409,0))&"","")) | F82: =IF($B82="","",IFERROR(INDEX(商品マスタ!$J$6:$J$1005,MATCH($D82,商品マスタ!$B$6:$B$1005,0)),"ケース")) | G82: =IF($B82="","",IFERROR(INDEX(発注計算!$G$6:$G$405,MATCH(72,②発注数を決める!$Z$10:$Z$409,0)),"")) | H82: =IF($B82="","",IFERROR(INDEX(②発注数を決める!$J$10:$J$409,MATCH(72,②発注数を決める!$Z$10:$Z$409,0)),"")) | I82: =IF($B82="","",IFERROR(INDEX(発注計算!$H$6:$H$405,MATCH(72,②発注数を決める!$Z$10:$Z$409,0)),"")) | J82: =IF($B82="","",N($H82)*N($I82))
B83: =IF(73<=MAX(②発注数を決める!$Z$10:$Z$409),73,"") | C83: =IF($B83="","",IFERROR(INDEX(発注計算!$F$6:$F$405,MATCH(73,②発注数を決める!$Z$10:$Z$409,0)),"")) | D83: =IF($B83="","",IFERROR(INDEX(発注計算!$C$6:$C$405,MATCH(73,②発注数を決める!$Z$10:$Z$409,0))&"","")) | E83: =IF($B83="","",IFERROR(INDEX(②発注数を決める!$C$10:$C$409,MATCH(73,②発注数を決める!$Z$10:$Z$409,0))&"","")) | F83: =IF($B83="","",IFERROR(INDEX(商品マスタ!$J$6:$J$1005,MATCH($D83,商品マスタ!$B$6:$B$1005,0)),"ケース")) | G83: =IF($B83="","",IFERROR(INDEX(発注計算!$G$6:$G$405,MATCH(73,②発注数を決める!$Z$10:$Z$409,0)),"")) | H83: =IF($B83="","",IFERROR(INDEX(②発注数を決める!$J$10:$J$409,MATCH(73,②発注数を決める!$Z$10:$Z$409,0)),"")) | I83: =IF($B83="","",IFERROR(INDEX(発注計算!$H$6:$H$405,MATCH(73,②発注数を決める!$Z$10:$Z$409,0)),"")) | J83: =IF($B83="","",N($H83)*N($I83))
B84: =IF(74<=MAX(②発注数を決める!$Z$10:$Z$409),74,"") | C84: =IF($B84="","",IFERROR(INDEX(発注計算!$F$6:$F$405,MATCH(74,②発注数を決める!$Z$10:$Z$409,0)),"")) | D84: =IF($B84="","",IFERROR(INDEX(発注計算!$C$6:$C$405,MATCH(74,②発注数を決める!$Z$10:$Z$409,0))&"","")) | E84: =IF($B84="","",IFERROR(INDEX(②発注数を決める!$C$10:$C$409,MATCH(74,②発注数を決める!$Z$10:$Z$409,0))&"","")) | F84: =IF($B84="","",IFERROR(INDEX(商品マスタ!$J$6:$J$1005,MATCH($D84,商品マスタ!$B$6:$B$1005,0)),"ケース")) | G84: =IF($B84="","",IFERROR(INDEX(発注計算!$G$6:$G$405,MATCH(74,②発注数を決める!$Z$10:$Z$409,0)),"")) | H84: =IF($B84="","",IFERROR(INDEX(②発注数を決める!$J$10:$J$409,MATCH(74,②発注数を決める!$Z$10:$Z$409,0)),"")) | I84: =IF($B84="","",IFERROR(INDEX(発注計算!$H$6:$H$405,MATCH(74,②発注数を決める!$Z$10:$Z$409,0)),"")) | J84: =IF($B84="","",N($H84)*N($I84))
B85: =IF(75<=MAX(②発注数を決める!$Z$10:$Z$409),75,"") | C85: =IF($B85="","",IFERROR(INDEX(発注計算!$F$6:$F$405,MATCH(75,②発注数を決める!$Z$10:$Z$409,0)),"")) | D85: =IF($B85="","",IFERROR(INDEX(発注計算!$C$6:$C$405,MATCH(75,②発注数を決める!$Z$10:$Z$409,0))&"","")) | E85: =IF($B85="","",IFERROR(INDEX(②発注数を決める!$C$10:$C$409,MATCH(75,②発注数を決める!$Z$10:$Z$409,0))&"","")) | F85: =IF($B85="","",IFERROR(INDEX(商品マスタ!$J$6:$J$1005,MATCH($D85,商品マスタ!$B$6:$B$1005,0)),"ケース")) | G85: =IF($B85="","",IFERROR(INDEX(発注計算!$G$6:$G$405,MATCH(75,②発注数を決める!$Z$10:$Z$409,0)),"")) | H85: =IF($B85="","",IFERROR(INDEX(②発注数を決める!$J$10:$J$409,MATCH(75,②発注数を決める!$Z$10:$Z$409,0)),"")) | I85: =IF($B85="","",IFERROR(INDEX(発注計算!$H$6:$H$405,MATCH(75,②発注数を決める!$Z$10:$Z$409,0)),"")) | J85: =IF($B85="","",N($H85)*N($I85))
B86: =IF(76<=MAX(②発注数を決める!$Z$10:$Z$409),76,"") | C86: =IF($B86="","",IFERROR(INDEX(発注計算!$F$6:$F$405,MATCH(76,②発注数を決める!$Z$10:$Z$409,0)),"")) | D86: =IF($B86="","",IFERROR(INDEX(発注計算!$C$6:$C$405,MATCH(76,②発注数を決める!$Z$10:$Z$409,0))&"","")) | E86: =IF($B86="","",IFERROR(INDEX(②発注数を決める!$C$10:$C$409,MATCH(76,②発注数を決める!$Z$10:$Z$409,0))&"","")) | F86: =IF($B86="","",IFERROR(INDEX(商品マスタ!$J$6:$J$1005,MATCH($D86,商品マスタ!$B$6:$B$1005,0)),"ケース")) | G86: =IF($B86="","",IFERROR(INDEX(発注計算!$G$6:$G$405,MATCH(76,②発注数を決める!$Z$10:$Z$409,0)),"")) | H86: =IF($B86="","",IFERROR(INDEX(②発注数を決める!$J$10:$J$409,MATCH(76,②発注数を決める!$Z$10:$Z$409,0)),"")) | I86: =IF($B86="","",IFERROR(INDEX(発注計算!$H$6:$H$405,MATCH(76,②発注数を決める!$Z$10:$Z$409,0)),"")) | J86: =IF($B86="","",N($H86)*N($I86))
B87: =IF(77<=MAX(②発注数を決める!$Z$10:$Z$409),77,"") | C87: =IF($B87="","",IFERROR(INDEX(発注計算!$F$6:$F$405,MATCH(77,②発注数を決める!$Z$10:$Z$409,0)),"")) | D87: =IF($B87="","",IFERROR(INDEX(発注計算!$C$6:$C$405,MATCH(77,②発注数を決める!$Z$10:$Z$409,0))&"","")) | E87: =IF($B87="","",IFERROR(INDEX(②発注数を決める!$C$10:$C$409,MATCH(77,②発注数を決める!$Z$10:$Z$409,0))&"","")) | F87: =IF($B87="","",IFERROR(INDEX(商品マスタ!$J$6:$J$1005,MATCH($D87,商品マスタ!$B$6:$B$1005,0)),"ケース")) | G87: =IF($B87="","",IFERROR(INDEX(発注計算!$G$6:$G$405,MATCH(77,②発注数を決める!$Z$10:$Z$409,0)),"")) | H87: =IF($B87="","",IFERROR(INDEX(②発注数を決める!$J$10:$J$409,MATCH(77,②発注数を決める!$Z$10:$Z$409,0)),"")) | I87: =IF($B87="","",IFERROR(INDEX(発注計算!$H$6:$H$405,MATCH(77,②発注数を決める!$Z$10:$Z$409,0)),"")) | J87: =IF($B87="","",N($H87)*N($I87))
B88: =IF(78<=MAX(②発注数を決める!$Z$10:$Z$409),78,"") | C88: =IF($B88="","",IFERROR(INDEX(発注計算!$F$6:$F$405,MATCH(78,②発注数を決める!$Z$10:$Z$409,0)),"")) | D88: =IF($B88="","",IFERROR(INDEX(発注計算!$C$6:$C$405,MATCH(78,②発注数を決める!$Z$10:$Z$409,0))&"","")) | E88: =IF($B88="","",IFERROR(INDEX(②発注数を決める!$C$10:$C$409,MATCH(78,②発注数を決める!$Z$10:$Z$409,0))&"","")) | F88: =IF($B88="","",IFERROR(INDEX(商品マスタ!$J$6:$J$1005,MATCH($D88,商品マスタ!$B$6:$B$1005,0)),"ケース")) | G88: =IF($B88="","",IFERROR(INDEX(発注計算!$G$6:$G$405,MATCH(78,②発注数を決める!$Z$10:$Z$409,0)),"")) | H88: =IF($B88="","",IFERROR(INDEX(②発注数を決める!$J$10:$J$409,MATCH(78,②発注数を決める!$Z$10:$Z$409,0)),"")) | I88: =IF($B88="","",IFERROR(INDEX(発注計算!$H$6:$H$405,MATCH(78,②発注数を決める!$Z$10:$Z$409,0)),"")) | J88: =IF($B88="","",N($H88)*N($I88))
B89: =IF(79<=MAX(②発注数を決める!$Z$10:$Z$409),79,"") | C89: =IF($B89="","",IFERROR(INDEX(発注計算!$F$6:$F$405,MATCH(79,②発注数を決める!$Z$10:$Z$409,0)),"")) | D89: =IF($B89="","",IFERROR(INDEX(発注計算!$C$6:$C$405,MATCH(79,②発注数を決める!$Z$10:$Z$409,0))&"","")) | E89: =IF($B89="","",IFERROR(INDEX(②発注数を決める!$C$10:$C$409,MATCH(79,②発注数を決める!$Z$10:$Z$409,0))&"","")) | F89: =IF($B89="","",IFERROR(INDEX(商品マスタ!$J$6:$J$1005,MATCH($D89,商品マスタ!$B$6:$B$1005,0)),"ケース")) | G89: =IF($B89="","",IFERROR(INDEX(発注計算!$G$6:$G$405,MATCH(79,②発注数を決める!$Z$10:$Z$409,0)),"")) | H89: =IF($B89="","",IFERROR(INDEX(②発注数を決める!$J$10:$J$409,MATCH(79,②発注数を決める!$Z$10:$Z$409,0)),"")) | I89: =IF($B89="","",IFERROR(INDEX(発注計算!$H$6:$H$405,MATCH(79,②発注数を決める!$Z$10:$Z$409,0)),"")) | J89: =IF($B89="","",N($H89)*N($I89))
B90: =IF(80<=MAX(②発注数を決める!$Z$10:$Z$409),80,"") | C90: =IF($B90="","",IFERROR(INDEX(発注計算!$F$6:$F$405,MATCH(80,②発注数を決める!$Z$10:$Z$409,0)),"")) | D90: =IF($B90="","",IFERROR(INDEX(発注計算!$C$6:$C$405,MATCH(80,②発注数を決める!$Z$10:$Z$409,0))&"","")) | E90: =IF($B90="","",IFERROR(INDEX(②発注数を決める!$C$10:$C$409,MATCH(80,②発注数を決める!$Z$10:$Z$409,0))&"","")) | F90: =IF($B90="","",IFERROR(INDEX(商品マスタ!$J$6:$J$1005,MATCH($D90,商品マスタ!$B$6:$B$1005,0)),"ケース")) | G90: =IF($B90="","",IFERROR(INDEX(発注計算!$G$6:$G$405,MATCH(80,②発注数を決める!$Z$10:$Z$409,0)),"")) | H90: =IF($B90="","",IFERROR(INDEX(②発注数を決める!$J$10:$J$409,MATCH(80,②発注数を決める!$Z$10:$Z$409,0)),"")) | I90: =IF($B90="","",IFERROR(INDEX(発注計算!$H$6:$H$405,MATCH(80,②発注数を決める!$Z$10:$Z$409,0)),"")) | J90: =IF($B90="","",N($H90)*N($I90))
B91: =IF(81<=MAX(②発注数を決める!$Z$10:$Z$409),81,"") | C91: =IF($B91="","",IFERROR(INDEX(発注計算!$F$6:$F$405,MATCH(81,②発注数を決める!$Z$10:$Z$409,0)),"")) | D91: =IF($B91="","",IFERROR(INDEX(発注計算!$C$6:$C$405,MATCH(81,②発注数を決める!$Z$10:$Z$409,0))&"","")) | E91: =IF($B91="","",IFERROR(INDEX(②発注数を決める!$C$10:$C$409,MATCH(81,②発注数を決める!$Z$10:$Z$409,0))&"","")) | F91: =IF($B91="","",IFERROR(INDEX(商品マスタ!$J$6:$J$1005,MATCH($D91,商品マスタ!$B$6:$B$1005,0)),"ケース")) | G91: =IF($B91="","",IFERROR(INDEX(発注計算!$G$6:$G$405,MATCH(81,②発注数を決める!$Z$10:$Z$409,0)),"")) | H91: =IF($B91="","",IFERROR(INDEX(②発注数を決める!$J$10:$J$409,MATCH(81,②発注数を決める!$Z$10:$Z$409,0)),"")) | I91: =IF($B91="","",IFERROR(INDEX(発注計算!$H$6:$H$405,MATCH(81,②発注数を決める!$Z$10:$Z$409,0)),"")) | J91: =IF($B91="","",N($H91)*N($I91))
B92: =IF(82<=MAX(②発注数を決める!$Z$10:$Z$409),82,"") | C92: =IF($B92="","",IFERROR(INDEX(発注計算!$F$6:$F$405,MATCH(82,②発注数を決める!$Z$10:$Z$409,0)),"")) | D92: =IF($B92="","",IFERROR(INDEX(発注計算!$C$6:$C$405,MATCH(82,②発注数を決める!$Z$10:$Z$409,0))&"","")) | E92: =IF($B92="","",IFERROR(INDEX(②発注数を決める!$C$10:$C$409,MATCH(82,②発注数を決める!$Z$10:$Z$409,0))&"","")) | F92: =IF($B92="","",IFERROR(INDEX(商品マスタ!$J$6:$J$1005,MATCH($D92,商品マスタ!$B$6:$B$1005,0)),"ケース")) | G92: =IF($B92="","",IFERROR(INDEX(発注計算!$G$6:$G$405,MATCH(82,②発注数を決める!$Z$10:$Z$409,0)),"")) | H92: =IF($B92="","",IFERROR(INDEX(②発注数を決める!$J$10:$J$409,MATCH(82,②発注数を決める!$Z$10:$Z$409,0)),"")) | I92: =IF($B92="","",IFERROR(INDEX(発注計算!$H$6:$H$405,MATCH(82,②発注数を決める!$Z$10:$Z$409,0)),"")) | J92: =IF($B92="","",N($H92)*N($I92))
B93: =IF(83<=MAX(②発注数を決める!$Z$10:$Z$409),83,"") | C93: =IF($B93="","",IFERROR(INDEX(発注計算!$F$6:$F$405,MATCH(83,②発注数を決める!$Z$10:$Z$409,0)),"")) | D93: =IF($B93="","",IFERROR(INDEX(発注計算!$C$6:$C$405,MATCH(83,②発注数を決める!$Z$10:$Z$409,0))&"","")) | E93: =IF($B93="","",IFERROR(INDEX(②発注数を決める!$C$10:$C$409,MATCH(83,②発注数を決める!$Z$10:$Z$409,0))&"","")) | F93: =IF($B93="","",IFERROR(INDEX(商品マスタ!$J$6:$J$1005,MATCH($D93,商品マスタ!$B$6:$B$1005,0)),"ケース")) | G93: =IF($B93="","",IFERROR(INDEX(発注計算!$G$6:$G$405,MATCH(83,②発注数を決める!$Z$10:$Z$409,0)),"")) | H93: =IF($B93="","",IFERROR(INDEX(②発注数を決める!$J$10:$J$409,MATCH(83,②発注数を決める!$Z$10:$Z$409,0)),"")) | I93: =IF($B93="","",IFERROR(INDEX(発注計算!$H$6:$H$405,MATCH(83,②発注数を決める!$Z$10:$Z$409,0)),"")) | J93: =IF($B93="","",N($H93)*N($I93))
B94: =IF(84<=MAX(②発注数を決める!$Z$10:$Z$409),84,"") | C94: =IF($B94="","",IFERROR(INDEX(発注計算!$F$6:$F$405,MATCH(84,②発注数を決める!$Z$10:$Z$409,0)),"")) | D94: =IF($B94="","",IFERROR(INDEX(発注計算!$C$6:$C$405,MATCH(84,②発注数を決める!$Z$10:$Z$409,0))&"","")) | E94: =IF($B94="","",IFERROR(INDEX(②発注数を決める!$C$10:$C$409,MATCH(84,②発注数を決める!$Z$10:$Z$409,0))&"","")) | F94: =IF($B94="","",IFERROR(INDEX(商品マスタ!$J$6:$J$1005,MATCH($D94,商品マスタ!$B$6:$B$1005,0)),"ケース")) | G94: =IF($B94="","",IFERROR(INDEX(発注計算!$G$6:$G$405,MATCH(84,②発注数を決める!$Z$10:$Z$409,0)),"")) | H94: =IF($B94="","",IFERROR(INDEX(②発注数を決める!$J$10:$J$409,MATCH(84,②発注数を決める!$Z$10:$Z$409,0)),"")) | I94: =IF($B94="","",IFERROR(INDEX(発注計算!$H$6:$H$405,MATCH(84,②発注数を決める!$Z$10:$Z$409,0)),"")) | J94: =IF($B94="","",N($H94)*N($I94))
B95: =IF(85<=MAX(②発注数を決める!$Z$10:$Z$409),85,"") | C95: =IF($B95="","",IFERROR(INDEX(発注計算!$F$6:$F$405,MATCH(85,②発注数を決める!$Z$10:$Z$409,0)),"")) | D95: =IF($B95="","",IFERROR(INDEX(発注計算!$C$6:$C$405,MATCH(85,②発注数を決める!$Z$10:$Z$409,0))&"","")) | E95: =IF($B95="","",IFERROR(INDEX(②発注数を決める!$C$10:$C$409,MATCH(85,②発注数を決める!$Z$10:$Z$409,0))&"","")) | F95: =IF($B95="","",IFERROR(INDEX(商品マスタ!$J$6:$J$1005,MATCH($D95,商品マスタ!$B$6:$B$1005,0)),"ケース")) | G95: =IF($B95="","",IFERROR(INDEX(発注計算!$G$6:$G$405,MATCH(85,②発注数を決める!$Z$10:$Z$409,0)),"")) | H95: =IF($B95="","",IFERROR(INDEX(②発注数を決める!$J$10:$J$409,MATCH(85,②発注数を決める!$Z$10:$Z$409,0)),"")) | I95: =IF($B95="","",IFERROR(INDEX(発注計算!$H$6:$H$405,MATCH(85,②発注数を決める!$Z$10:$Z$409,0)),"")) | J95: =IF($B95="","",N($H95)*N($I95))
B96: =IF(86<=MAX(②発注数を決める!$Z$10:$Z$409),86,"") | C96: =IF($B96="","",IFERROR(INDEX(発注計算!$F$6:$F$405,MATCH(86,②発注数を決める!$Z$10:$Z$409,0)),"")) | D96: =IF($B96="","",IFERROR(INDEX(発注計算!$C$6:$C$405,MATCH(86,②発注数を決める!$Z$10:$Z$409,0))&"","")) | E96: =IF($B96="","",IFERROR(INDEX(②発注数を決める!$C$10:$C$409,MATCH(86,②発注数を決める!$Z$10:$Z$409,0))&"","")) | F96: =IF($B96="","",IFERROR(INDEX(商品マスタ!$J$6:$J$1005,MATCH($D96,商品マスタ!$B$6:$B$1005,0)),"ケース")) | G96: =IF($B96="","",IFERROR(INDEX(発注計算!$G$6:$G$405,MATCH(86,②発注数を決める!$Z$10:$Z$409,0)),"")) | H96: =IF($B96="","",IFERROR(INDEX(②発注数を決める!$J$10:$J$409,MATCH(86,②発注数を決める!$Z$10:$Z$409,0)),"")) | I96: =IF($B96="","",IFERROR(INDEX(発注計算!$H$6:$H$405,MATCH(86,②発注数を決める!$Z$10:$Z$409,0)),"")) | J96: =IF($B96="","",N($H96)*N($I96))
B97: =IF(87<=MAX(②発注数を決める!$Z$10:$Z$409),87,"") | C97: =IF($B97="","",IFERROR(INDEX(発注計算!$F$6:$F$405,MATCH(87,②発注数を決める!$Z$10:$Z$409,0)),"")) | D97: =IF($B97="","",IFERROR(INDEX(発注計算!$C$6:$C$405,MATCH(87,②発注数を決める!$Z$10:$Z$409,0))&"","")) | E97: =IF($B97="","",IFERROR(INDEX(②発注数を決める!$C$10:$C$409,MATCH(87,②発注数を決める!$Z$10:$Z$409,0))&"","")) | F97: =IF($B97="","",IFERROR(INDEX(商品マスタ!$J$6:$J$1005,MATCH($D97,商品マスタ!$B$6:$B$1005,0)),"ケース")) | G97: =IF($B97="","",IFERROR(INDEX(発注計算!$G$6:$G$405,MATCH(87,②発注数を決める!$Z$10:$Z$409,0)),"")) | H97: =IF($B97="","",IFERROR(INDEX(②発注数を決める!$J$10:$J$409,MATCH(87,②発注数を決める!$Z$10:$Z$409,0)),"")) | I97: =IF($B97="","",IFERROR(INDEX(発注計算!$H$6:$H$405,MATCH(87,②発注数を決める!$Z$10:$Z$409,0)),"")) | J97: =IF($B97="","",N($H97)*N($I97))
B98: =IF(88<=MAX(②発注数を決める!$Z$10:$Z$409),88,"") | C98: =IF($B98="","",IFERROR(INDEX(発注計算!$F$6:$F$405,MATCH(88,②発注数を決める!$Z$10:$Z$409,0)),"")) | D98: =IF($B98="","",IFERROR(INDEX(発注計算!$C$6:$C$405,MATCH(88,②発注数を決める!$Z$10:$Z$409,0))&"","")) | E98: =IF($B98="","",IFERROR(INDEX(②発注数を決める!$C$10:$C$409,MATCH(88,②発注数を決める!$Z$10:$Z$409,0))&"","")) | F98: =IF($B98="","",IFERROR(INDEX(商品マスタ!$J$6:$J$1005,MATCH($D98,商品マスタ!$B$6:$B$1005,0)),"ケース")) | G98: =IF($B98="","",IFERROR(INDEX(発注計算!$G$6:$G$405,MATCH(88,②発注数を決める!$Z$10:$Z$409,0)),"")) | H98: =IF($B98="","",IFERROR(INDEX(②発注数を決める!$J$10:$J$409,MATCH(88,②発注数を決める!$Z$10:$Z$409,0)),"")) | I98: =IF($B98="","",IFERROR(INDEX(発注計算!$H$6:$H$405,MATCH(88,②発注数を決める!$Z$10:$Z$409,0)),"")) | J98: =IF($B98="","",N($H98)*N($I98))
B99: =IF(89<=MAX(②発注数を決める!$Z$10:$Z$409),89,"") | C99: =IF($B99="","",IFERROR(INDEX(発注計算!$F$6:$F$405,MATCH(89,②発注数を決める!$Z$10:$Z$409,0)),"")) | D99: =IF($B99="","",IFERROR(INDEX(発注計算!$C$6:$C$405,MATCH(89,②発注数を決める!$Z$10:$Z$409,0))&"","")) | E99: =IF($B99="","",IFERROR(INDEX(②発注数を決める!$C$10:$C$409,MATCH(89,②発注数を決める!$Z$10:$Z$409,0))&"","")) | F99: =IF($B99="","",IFERROR(INDEX(商品マスタ!$J$6:$J$1005,MATCH($D99,商品マスタ!$B$6:$B$1005,0)),"ケース")) | G99: =IF($B99="","",IFERROR(INDEX(発注計算!$G$6:$G$405,MATCH(89,②発注数を決める!$Z$10:$Z$409,0)),"")) | H99: =IF($B99="","",IFERROR(INDEX(②発注数を決める!$J$10:$J$409,MATCH(89,②発注数を決める!$Z$10:$Z$409,0)),"")) | I99: =IF($B99="","",IFERROR(INDEX(発注計算!$H$6:$H$405,MATCH(89,②発注数を決める!$Z$10:$Z$409,0)),"")) | J99: =IF($B99="","",N($H99)*N($I99))
B100: =IF(90<=MAX(②発注数を決める!$Z$10:$Z$409),90,"") | C100: =IF($B100="","",IFERROR(INDEX(発注計算!$F$6:$F$405,MATCH(90,②発注数を決める!$Z$10:$Z$409,0)),"")) | D100: =IF($B100="","",IFERROR(INDEX(発注計算!$C$6:$C$405,MATCH(90,②発注数を決める!$Z$10:$Z$409,0))&"","")) | E100: =IF($B100="","",IFERROR(INDEX(②発注数を決める!$C$10:$C$409,MATCH(90,②発注数を決める!$Z$10:$Z$409,0))&"","")) | F100: =IF($B100="","",IFERROR(INDEX(商品マスタ!$J$6:$J$1005,MATCH($D100,商品マスタ!$B$6:$B$1005,0)),"ケース")) | G100: =IF($B100="","",IFERROR(INDEX(発注計算!$G$6:$G$405,MATCH(90,②発注数を決める!$Z$10:$Z$409,0)),"")) | H100: =IF($B100="","",IFERROR(INDEX(②発注数を決める!$J$10:$J$409,MATCH(90,②発注数を決める!$Z$10:$Z$409,0)),"")) | I100: =IF($B100="","",IFERROR(INDEX(発注計算!$H$6:$H$405,MATCH(90,②発注数を決める!$Z$10:$Z$409,0)),"")) | J100: =IF($B100="","",N($H100)*N($I100))
B101: =IF(91<=MAX(②発注数を決める!$Z$10:$Z$409),91,"") | C101: =IF($B101="","",IFERROR(INDEX(発注計算!$F$6:$F$405,MATCH(91,②発注数を決める!$Z$10:$Z$409,0)),"")) | D101: =IF($B101="","",IFERROR(INDEX(発注計算!$C$6:$C$405,MATCH(91,②発注数を決める!$Z$10:$Z$409,0))&"","")) | E101: =IF($B101="","",IFERROR(INDEX(②発注数を決める!$C$10:$C$409,MATCH(91,②発注数を決める!$Z$10:$Z$409,0))&"","")) | F101: =IF($B101="","",IFERROR(INDEX(商品マスタ!$J$6:$J$1005,MATCH($D101,商品マスタ!$B$6:$B$1005,0)),"ケース")) | G101: =IF($B101="","",IFERROR(INDEX(発注計算!$G$6:$G$405,MATCH(91,②発注数を決める!$Z$10:$Z$409,0)),"")) | H101: =IF($B101="","",IFERROR(INDEX(②発注数を決める!$J$10:$J$409,MATCH(91,②発注数を決める!$Z$10:$Z$409,0)),"")) | I101: =IF($B101="","",IFERROR(INDEX(発注計算!$H$6:$H$405,MATCH(91,②発注数を決める!$Z$10:$Z$409,0)),"")) | J101: =IF($B101="","",N($H101)*N($I101))
...

Sheet 月1回_前回の在庫を貼る
B2: 前回の在庫を貼る（月1回） | H2: =IF(COUNTIF($B$6:$B$10005,'設定（最初に1回）'!$C$4)=0,"✖ まだ貼れていません","✔ "&COUNTIF($B$6:$B$10005,'設定（最初に1回）'!$C$4)&"行 読み込めました") -> ✔ 134行 読み込めました
B3: 当月を含まない直近2ヶ月前の1日時点の在庫一覧です。今日の在庫と突き合わせて、期間の消費量と商品の入れ替わりを見ます。 | H3: =IF(COUNTIF($B$6:$B$10005,'設定（最初に1回）'!$C$4)=0,"CSVの見出し行を除いたデータを A6 セルに貼り付けてください。貼ったのに0のままなら、劇場コードが数値になっています。","対象劇場：" & '設定（最初に1回）'!$C$4 & " " & '設定（最初に1回）'!$C$5) -> 対象劇場：0761 新宿
B4: 月に1回、A6 セルに貼り替えてください。
A5: 対象日付 | B5: 劇場コード | C5: 劇場名 | D5: 支払先コード | E5: 支払先名 | F5: 大分類コード | G5: 小分類コード | H5: 商品分類名 | I5: 商品コード | J5: 商品名 | K5: 入数 | L5: 在庫数ケース | M5: 在庫数バラ | N5: 総数 | O5: 規定数 | P5: 資産廃棄 | Q5: 税抜単価 | R5: 仕入税区分 | S5: 仕入税率 | U5: 連番(自動)
A6: 20260301 | B6: 0761 | C6: 新宿 | D6: 10400001 | E6: 株式会社 カクヤス | F6: 01 | G6: 04 | H6: アルコール | I6: 1812000008585 | J6: プレミアムモルツ ２０Ｌ | K6: 1 | L6: 108 | M6: 0 | N6: 108 | P6: 0 | Q6: 11300 | R6: 外税 | S6: 0.1 | U6: =IF($B6<>'設定（最初に1回）'!$C$4,N(U5),IF(COUNTIFS(①今日の在庫を貼る!$B$6:$B$10005,$B6,①今日の在庫を貼る!$I$6:$I$10005,$I6)>0,N(U5),N(U5)+1)) -> 0
A7: 20260301 | B7: 0761 | C7: 新宿 | D7: 10400001 | E7: 株式会社 カクヤス | F7: 01 | G7: 04 | H7: アルコール | I7: 1812000010991 | J7: ミオネット ベビーボトル２００ｍ | K7: 24 | L7: 0 | M7: 2 | N7: 2 | P7: 0 | Q7: 587 | R7: 外税 | S7: 0.1 | U7: =IF($B7<>'設定（最初に1回）'!$C$4,N(U6),IF(COUNTIFS(①今日の在庫を貼る!$B$6:$B$10005,$B7,①今日の在庫を貼る!$I$6:$I$10005,$I7)>0,N(U6),N(U6)+1)) -> 0
A8: 20260301 | B8: 0761 | C8: 新宿 | D8: 10400001 | E8: 株式会社 カクヤス | F8: 01 | G8: 04 | H8: アルコール | I8: 1812000011745 | J8: フォルタン リトラル 赤 | K8: 48 | L8: 1 | M8: 6 | N8: 54 | P8: 0 | Q8: 357 | R8: 外税 | S8: 0.1 | U8: =IF($B8<>'設定（最初に1回）'!$C$4,N(U7),IF(COUNTIFS(①今日の在庫を貼る!$B$6:$B$10005,$B8,①今日の在庫を貼る!$I$6:$I$10005,$I8)>0,N(U7),N(U7)+1)) -> 0
A9: 20260301 | B9: 0761 | C9: 新宿 | D9: 10400001 | E9: 株式会社 カクヤス | F9: 01 | G9: 04 | H9: アルコール | I9: 1812000011752 | J9: フォルタン リトラル 白 | K9: 48 | L9: 1 | M9: 33 | N9: 81 | P9: 0 | Q9: 357 | R9: 外税 | S9: 0.1 | U9: =IF($B9<>'設定（最初に1回）'!$C$4,N(U8),IF(COUNTIFS(①今日の在庫を貼る!$B$6:$B$10005,$B9,①今日の在庫を貼る!$I$6:$I$10005,$I9)>0,N(U8),N(U8)+1)) -> 0
A10: 20260301 | B10: 0761 | C10: 新宿 | D10: 10400001 | E10: 株式会社 カクヤス | F10: 01 | G10: 04 | H10: アルコール | I10: 1812000013343 | J10: フレシネコルドンネグロ２００ｍｌ | K10: 24 | L10: 11 | M10: 5 | N10: 269 | P10: 0 | Q10: 585 | R10: 外税 | S10: 0.1 | U10: =IF($B10<>'設定（最初に1回）'!$C$4,N(U9),IF(COUNTIFS(①今日の在庫を貼る!$B$6:$B$10005,$B10,①今日の在庫を貼る!$I$6:$I$10005,$I10)>0,N(U9),N(U9)+1)) -> 0
A11: 20260301 | B11: 0761 | C11: 新宿 | D11: 10400001 | E11: 株式会社 カクヤス | F11: 01 | G11: 04 | H11: アルコール | I11: 1813000187270 | J11: サントリー角ハイボール | K11: 30 | L11: 40 | M11: 25 | N11: 1225 | P11: 0 | Q11: 118 | R11: 外税 | S11: 0.1 | U11: =IF($B11<>'設定（最初に1回）'!$C$4,N(U10),IF(COUNTIFS(①今日の在庫を貼る!$B$6:$B$10005,$B11,①今日の在庫を貼る!$I$6:$I$10005,$I11)>0,N(U10),N(U10)+1)) -> 0
A12: 20260301 | B12: 0761 | C12: 新宿 | D12: 19903001 | E12: オザックス株式会社 | F12: 01 | G12: 01 | H12: コールド | I12: 1812000000237 | J12: アイスティシロップ | K12: 1 | L12: 98 | M12: 0 | N12: 98 | P12: 0 | Q12: 3756 | R12: 外税 | S12: 0.08 | U12: =IF($B12<>'設定（最初に1回）'!$C$4,N(U11),IF(COUNTIFS(①今日の在庫を貼る!$B$6:$B$10005,$B12,①今日の在庫を貼る!$I$6:$I$10005,$I12)>0,N(U11),N(U11)+1)) -> 0
A13: 20260301 | B13: 0761 | C13: 新宿 | D13: 19903001 | E13: オザックス株式会社 | F13: 01 | G13: 01 | H13: コールド | I13: 1812000000251 | J13: 烏龍茶１０倍シロップ | K13: 1 | L13: 70 | M13: 0 | N13: 70 | P13: 0 | Q13: 4382 | R13: 外税 | S13: 0.08 | U13: =IF($B13<>'設定（最初に1回）'!$C$4,N(U12),IF(COUNTIFS(①今日の在庫を貼る!$B$6:$B$10005,$B13,①今日の在庫を貼る!$I$6:$I$10005,$I13)>0,N(U12),N(U12)+1)) -> 0
A14: 20260301 | B14: 0761 | C14: 新宿 | D14: 19903001 | E14: オザックス株式会社 | F14: 01 | G14: 01 | H14: コールド | I14: 1812000007441 | J14: ミニッツメイドオレンジＦＫＡ | K14: 1 | L14: 2 | M14: 0 | N14: 2 | P14: 0 | Q14: 2890 | R14: 外税 | S14: 0.08 | U14: =IF($B14<>'設定（最初に1回）'!$C$4,N(U13),IF(COUNTIFS(①今日の在庫を貼る!$B$6:$B$10005,$B14,①今日の在庫を貼る!$I$6:$I$10005,$I14)>0,N(U13),N(U13)+1)) -> 0
A15: 20260301 | B15: 0761 | C15: 新宿 | D15: 19903001 | E15: オザックス株式会社 | F15: 01 | G15: 01 | H15: コールド | I15: 1812000013169 | J15: ミニッツメイドアップル | K15: 1 | L15: 4 | M15: 0 | N15: 4 | P15: 0 | Q15: 3636 | R15: 外税 | S15: 0.08 | U15: =IF($B15<>'設定（最初に1回）'!$C$4,N(U14),IF(COUNTIFS(①今日の在庫を貼る!$B$6:$B$10005,$B15,①今日の在庫を貼る!$I$6:$I$10005,$I15)>0,N(U14),N(U14)+1)) -> 0
A16: 20260301 | B16: 0761 | C16: 新宿 | D16: 19903001 | E16: オザックス株式会社 | F16: 01 | G16: 01 | H16: コールド | I16: 4902102081283 | J16: ＰＸＴ爽健美茶１Ｇ | K16: 1 | L16: 178 | M16: 0 | N16: 178 | P16: 0 | Q16: 3756 | R16: 外税 | S16: 0.08 | U16: =IF($B16<>'設定（最初に1回）'!$C$4,N(U15),IF(COUNTIFS(①今日の在庫を貼る!$B$6:$B$10005,$B16,①今日の在庫を貼る!$I$6:$I$10005,$I16)>0,N(U15),N(U15)+1)) -> 0
A17: 20260301 | B17: 0761 | C17: 新宿 | D17: 19903001 | E17: オザックス株式会社 | F17: 01 | G17: 01 | H17: コールド | I17: 4902102112901 | J17: フラットＢＩＢメロンＳ２．５Ｇ | K17: 1 | L17: 125 | M17: 0 | N17: 125 | P17: 0 | Q17: 7510 | R17: 外税 | S17: 0.08 | U17: =IF($B17<>'設定（最初に1回）'!$C$4,N(U16),IF(COUNTIFS(①今日の在庫を貼る!$B$6:$B$10005,$B17,①今日の在庫を貼る!$I$6:$I$10005,$I17)>0,N(U16),N(U16)+1)) -> 0
... A310: 20260301 | B310: 0902 | C310: 郊外シネマ | D310: 10400001 | E310: 株式会社 カクヤス | F310: 01 | G310: 04 | H310: アルコール | I310: 9909020000002 | J310: （終売）旧パッケージカップ | K310: 1 | L310: 90 | M310: 0 | N310: 90 | P310: 0 | Q310: 357 | R310: 外税 | S310: 0.1 | U310: =IF($B310<>'設定（最初に1回）'!$C$4,N(U309),IF(COUNTIFS(①今日の在庫を貼る!$B$6:$B$10005,$B310,①今日の在庫を貼る!$I$6:$I$10005,$I310)>0,N(U309),N(U309)+1)) -> 2
U311: =IF($B311<>'設定（最初に1回）'!$C$4,N(U310),IF(COUNTIFS(①今日の在庫を貼る!$B$6:$B$10005,$B311,①今日の在庫を貼る!$I$6:$I$10005,$I311)>0,N(U310),N(U310)+1)) -> 2
U312: =IF($B312<>'設定（最初に1回）'!$C$4,N(U311),IF(COUNTIFS(①今日の在庫を貼る!$B$6:$B$10005,$B312,①今日の在庫を貼る!$I$6:$I$10005,$I312)>0,N(U311),N(U311)+1)) -> 2
U313: =IF($B313<>'設定（最初に1回）'!$C$4,N(U312),IF(COUNTIFS(①今日の在庫を貼る!$B$6:$B$10005,$B313,①今日の在庫を貼る!$I$6:$I$10005,$I313)>0,N(U312),N(U312)+1)) -> 2
U314: =IF($B314<>'設定（最初に1回）'!$C$4,N(U313),IF(COUNTIFS(①今日の在庫を貼る!$B$6:$B$10005,$B314,①今日の在庫を貼る!$I$6:$I$10005,$I314)>0,N(U313),N(U313)+1)) -> 2
U315: =IF($B315<>'設定（最初に1回）'!$C$4,N(U314),IF(COUNTIFS(①今日の在庫を貼る!$B$6:$B$10005,$B315,①今日の在庫を貼る!$I$6:$I$10005,$I315)>0,N(U314),N(U314)+1)) -> 2
U316: =IF($B316<>'設定（最初に1回）'!$C$4,N(U315),IF(COUNTIFS(①今日の在庫を貼る!$B$6:$B$10005,$B316,①今日の在庫を貼る!$I$6:$I$10005,$I316)>0,N(U315),N(U315)+1)) -> 2
U317: =IF($B317<>'設定（最初に1回）'!$C$4,N(U316),IF(COUNTIFS(①今日の在庫を貼る!$B$6:$B$10005,$B317,①今日の在庫を貼る!$I$6:$I$10005,$I317)>0,N(U316),N(U316)+1)) -> 2
U318: =IF($B318<>'設定（最初に1回）'!$C$4,N(U317),IF(COUNTIFS(①今日の在庫を貼る!$B$6:$B$10005,$B318,①今日の在庫を貼る!$I$6:$I$10005,$I318)>0,N(U317),N(U317)+1)) -> 2
U319: =IF($B319<>'設定（最初に1回）'!$C$4,N(U318),IF(COUNTIFS(①今日の在庫を貼る!$B$6:$B$10005,$B319,①今日の在庫を貼る!$I$6:$I$10005,$I319)>0,N(U318),N(U318)+1)) -> 2
U320: =IF($B320<>'設定（最初に1回）'!$C$4,N(U319),IF(COUNTIFS(①今日の在庫を貼る!$B$6:$B$10005,$B320,①今日の在庫を貼る!$I$6:$I$10005,$I320)>0,N(U319),N(U319)+1)) -> 2
U321: =IF($B321<>'設定（最初に1回）'!$C$4,N(U320),IF(COUNTIFS(①今日の在庫を貼る!$B$6:$B$10005,$B321,①今日の在庫を貼る!$I$6:$I$10005,$I321)>0,N(U320),N(U320)+1)) -> 2
U322: =IF($B322<>'設定（最初に1回）'!$C$4,N(U321),IF(COUNTIFS(①今日の在庫を貼る!$B$6:$B$10005,$B322,①今日の在庫を貼る!$I$6:$I$10005,$I322)>0,N(U321),N(U321)+1)) -> 2
... U10005: =IF($B10005<>'設定（最初に1回）'!$C$4,N(U10004),IF(COUNTIFS(①今日の在庫を貼る!$B$6:$B$10005,$B10005,①今日の在庫を貼る!$I$6:$I$10005,$I10005)>0,N(U10004),N(U10004)+1)) -> 2

Sheet 随時_動員を入れる
B2: 動員計画
B3: 来場者予測を入れる唯一の場所です。空欄の日は劇場の標準来場者数が使われます。
B4: 入力のしかた
B5: ・「予測来場者数」に読みを入れます。空欄なら標準来場者数（設定シートの値）を使います。
B6: 自動 | C6: 自動 | D6: 入力 | E6: 入力 | F6: 自動 | G6: 自動
B7: 日付 | C7: 曜日 | D7: 予測来場者数 | E7: 主な作品・備考 | F7: 季節係数 | G7: 採用来場者数 | I7: グラフ目盛り用
B8: =IF('設定（最初に1回）'!$C$6="","",'設定（最初に1回）'!$C$6+0) -> 46143 | C8: =IF($B8="","",CHOOSE(WEEKDAY($B8),"日","月","火","水","木","金","土")) -> 金 | D8: 2871 | E8: GW初日 | F8: =IF($B8="","",IF(SUMPRODUCT(MAX((定数マスタ!$X$6:$X$25<=$B8)*(定数マスタ!$Y$6:$Y$25>=$B8)*定数マスタ!$Z$6:$Z$25))=0,IFERROR(INDEX(定数マスタ!$U$6:$U$17,MONTH($B8)),1),SUMPRODUCT(MAX((定数マスタ!$X$6:$X$25<=$B8)*(定数マスタ!$Y$6:$Y$25>=$B8)*定数マスタ!$Z$6:$Z$25)))) -> 1.45 | G8: =IF($B8="","",ROUND(IF(ISNUMBER($D8),$D8,N('設定（最初に1回）'!$C$14))*N($F8),0)) -> 4163 | I8: =IF($B8="","",TEXT($B8,"m/d")&"("&$C8&")") -> 5/1(金)
B9: =IF('設定（最初に1回）'!$C$6="","",'設定（最初に1回）'!$C$6+1) -> 46144 | C9: =IF($B9="","",CHOOSE(WEEKDAY($B9),"日","月","火","水","木","金","土")) -> 土 | D9: 3417 | E9: GW | F9: =IF($B9="","",IF(SUMPRODUCT(MAX((定数マスタ!$X$6:$X$25<=$B9)*(定数マスタ!$Y$6:$Y$25>=$B9)*定数マスタ!$Z$6:$Z$25))=0,IFERROR(INDEX(定数マスタ!$U$6:$U$17,MONTH($B9)),1),SUMPRODUCT(MAX((定数マスタ!$X$6:$X$25<=$B9)*(定数マスタ!$Y$6:$Y$25>=$B9)*定数マスタ!$Z$6:$Z$25)))) -> 1.45 | G9: =IF($B9="","",ROUND(IF(ISNUMBER($D9),$D9,N('設定（最初に1回）'!$C$14))*N($F9),0)) -> 4955 | I9: =IF($B9="","",TEXT($B9,"m/d")&"("&$C9&")") -> 5/2(土)
B10: =IF('設定（最初に1回）'!$C$6="","",'設定（最初に1回）'!$C$6+2) -> 46145 | C10: =IF($B10="","",CHOOSE(WEEKDAY($B10),"日","月","火","水","木","金","土")) -> 日 | D10: 5467 | E10: GW | F10: =IF($B10="","",IF(SUMPRODUCT(MAX((定数マスタ!$X$6:$X$25<=$B10)*(定数マスタ!$Y$6:$Y$25>=$B10)*定数マスタ!$Z$6:$Z$25))=0,IFERROR(INDEX(定数マスタ!$U$6:$U$17,MONTH($B10)),1),SUMPRODUCT(MAX((定数マスタ!$X$6:$X$25<=$B10)*(定数マスタ!$Y$6:$Y$25>=$B10)*定数マスタ!$Z$6:$Z$25)))) -> 1.45 | G10: =IF($B10="","",ROUND(IF(ISNUMBER($D10),$D10,N('設定（最初に1回）'!$C$14))*N($F10),0)) -> 7927 | I10: =IF($B10="","",TEXT($B10,"m/d")&"("&$C10&")") -> 5/3(日)
B11: =IF('設定（最初に1回）'!$C$6="","",'設定（最初に1回）'!$C$6+3) -> 46146 | C11: =IF($B11="","",CHOOSE(WEEKDAY($B11),"日","月","火","水","木","金","土")) -> 月 | D11: 5837 | E11: GW | F11: =IF($B11="","",IF(SUMPRODUCT(MAX((定数マスタ!$X$6:$X$25<=$B11)*(定数マスタ!$Y$6:$Y$25>=$B11)*定数マスタ!$Z$6:$Z$25))=0,IFERROR(INDEX(定数マスタ!$U$6:$U$17,MONTH($B11)),1),SUMPRODUCT(MAX((定数マスタ!$X$6:$X$25<=$B11)*(定数マスタ!$Y$6:$Y$25>=$B11)*定数マスタ!$Z$6:$Z$25)))) -> 1.45 | G11: =IF($B11="","",ROUND(IF(ISNUMBER($D11),$D11,N('設定（最初に1回）'!$C$14))*N($F11),0)) -> 8464 | I11: =IF($B11="","",TEXT($B11,"m/d")&"("&$C11&")") -> 5/4(月)
B12: =IF('設定（最初に1回）'!$C$6="","",'設定（最初に1回）'!$C$6+4) -> 46147 | C12: =IF($B12="","",CHOOSE(WEEKDAY($B12),"日","月","火","水","木","金","土")) -> 火 | D12: 1751 | E12: GWこどもの日／ファミリー作品 | F12: =IF($B12="","",IF(SUMPRODUCT(MAX((定数マスタ!$X$6:$X$25<=$B12)*(定数マスタ!$Y$6:$Y$25>=$B12)*定数マスタ!$Z$6:$Z$25))=0,IFERROR(INDEX(定数マスタ!$U$6:$U$17,MONTH($B12)),1),SUMPRODUCT(MAX((定数マスタ!$X$6:$X$25<=$B12)*(定数マスタ!$Y$6:$Y$25>=$B12)*定数マスタ!$Z$6:$Z$25)))) -> 1.45 | G12: =IF($B12="","",ROUND(IF(ISNUMBER($D12),$D12,N('設定（最初に1回）'!$C$14))*N($F12),0)) -> 2539 | I12: =IF($B12="","",TEXT($B12,"m/d")&"("&$C12&")") -> 5/5(火)
B13: =IF('設定（最初に1回）'!$C$6="","",'設定（最初に1回）'!$C$6+5) -> 46148 | C13: =IF($B13="","",CHOOSE(WEEKDAY($B13),"日","月","火","水","木","金","土")) -> 水 | D13: 924 | F13: =IF($B13="","",IF(SUMPRODUCT(MAX((定数マスタ!$X$6:$X$25<=$B13)*(定数マスタ!$Y$6:$Y$25>=$B13)*定数マスタ!$Z$6:$Z$25))=0,IFERROR(INDEX(定数マスタ!$U$6:$U$17,MONTH($B13)),1),SUMPRODUCT(MAX((定数マスタ!$X$6:$X$25<=$B13)*(定数マスタ!$Y$6:$Y$25>=$B13)*定数マスタ!$Z$6:$Z$25)))) -> 1.45 | G13: =IF($B13="","",ROUND(IF(ISNUMBER($D13),$D13,N('設定（最初に1回）'!$C$14))*N($F13),0)) -> 1340 | I13: =IF($B13="","",TEXT($B13,"m/d")&"("&$C13&")") -> 5/6(水)
B14: =IF('設定（最初に1回）'!$C$6="","",'設定（最初に1回）'!$C$6+6) -> 46149 | C14: =IF($B14="","",CHOOSE(WEEKDAY($B14),"日","月","火","水","木","金","土")) -> 木 | D14: 1271 | F14: =IF($B14="","",IF(SUMPRODUCT(MAX((定数マスタ!$X$6:$X$25<=$B14)*(定数マスタ!$Y$6:$Y$25>=$B14)*定数マスタ!$Z$6:$Z$25))=0,IFERROR(INDEX(定数マスタ!$U$6:$U$17,MONTH($B14)),1),SUMPRODUCT(MAX((定数マスタ!$X$6:$X$25<=$B14)*(定数マスタ!$Y$6:$Y$25>=$B14)*定数マスタ!$Z$6:$Z$25)))) -> 1.2 | G14: =IF($B14="","",ROUND(IF(ISNUMBER($D14),$D14,N('設定（最初に1回）'!$C$14))*N($F14),0)) -> 1525 | I14: =IF($B14="","",TEXT($B14,"m/d")&"("&$C14&")") -> 5/7(木)
B15: =IF('設定（最初に1回）'!$C$6="","",'設定（最初に1回）'!$C$6+7) -> 46150 | C15: =IF($B15="","",CHOOSE(WEEKDAY($B15),"日","月","火","水","木","金","土")) -> 金 | D15: 1277 | F15: =IF($B15="","",IF(SUMPRODUCT(MAX((定数マスタ!$X$6:$X$25<=$B15)*(定数マスタ!$Y$6:$Y$25>=$B15)*定数マスタ!$Z$6:$Z$25))=0,IFERROR(INDEX(定数マスタ!$U$6:$U$17,MONTH($B15)),1),SUMPRODUCT(MAX((定数マスタ!$X$6:$X$25<=$B15)*(定数マスタ!$Y$6:$Y$25>=$B15)*定数マスタ!$Z$6:$Z$25)))) -> 1.2 | G15: =IF($B15="","",ROUND(IF(ISNUMBER($D15),$D15,N('設定（最初に1回）'!$C$14))*N($F15),0)) -> 1532 | I15: =IF($B15="","",TEXT($B15,"m/d")&"("&$C15&")") -> 5/8(金)
B16: =IF('設定（最初に1回）'!$C$6="","",'設定（最初に1回）'!$C$6+8) -> 46151 | C16: =IF($B16="","",CHOOSE(WEEKDAY($B16),"日","月","火","水","木","金","土")) -> 土 | D16: 1772 | F16: =IF($B16="","",IF(SUMPRODUCT(MAX((定数マスタ!$X$6:$X$25<=$B16)*(定数マスタ!$Y$6:$Y$25>=$B16)*定数マスタ!$Z$6:$Z$25))=0,IFERROR(INDEX(定数マスタ!$U$6:$U$17,MONTH($B16)),1),SUMPRODUCT(MAX((定数マスタ!$X$6:$X$25<=$B16)*(定数マスタ!$Y$6:$Y$25>=$B16)*定数マスタ!$Z$6:$Z$25)))) -> 1.2 | G16: =IF($B16="","",ROUND(IF(ISNUMBER($D16),$D16,N('設定（最初に1回）'!$C$14))*N($F16),0)) -> 2126 | I16: =IF($B16="","",TEXT($B16,"m/d")&"("&$C16&")") -> 5/9(土)
B17: =IF('設定（最初に1回）'!$C$6="","",'設定（最初に1回）'!$C$6+9) -> 46152 | C17: =IF($B17="","",CHOOSE(WEEKDAY($B17),"日","月","火","水","木","金","土")) -> 日 | D17: 2909 | F17: =IF($B17="","",IF(SUMPRODUCT(MAX((定数マスタ!$X$6:$X$25<=$B17)*(定数マスタ!$Y$6:$Y$25>=$B17)*定数マスタ!$Z$6:$Z$25))=0,IFERROR(INDEX(定数マスタ!$U$6:$U$17,MONTH($B17)),1),SUMPRODUCT(MAX((定数マスタ!$X$6:$X$25<=$B17)*(定数マスタ!$Y$6:$Y$25>=$B17)*定数マスタ!$Z$6:$Z$25)))) -> 1.2 | G17: =IF($B17="","",ROUND(IF(ISNUMBER($D17),$D17,N('設定（最初に1回）'!$C$14))*N($F17),0)) -> 3491 | I17: =IF($B17="","",TEXT($B17,"m/d")&"("&$C17&")") -> 5/10(日)
B18: =IF('設定（最初に1回）'!$C$6="","",'設定（最初に1回）'!$C$6+10) -> 46153 | C18: =IF($B18="","",CHOOSE(WEEKDAY($B18),"日","月","火","水","木","金","土")) -> 月 | D18: 2570 | F18: =IF($B18="","",IF(SUMPRODUCT(MAX((定数マスタ!$X$6:$X$25<=$B18)*(定数マスタ!$Y$6:$Y$25>=$B18)*定数マスタ!$Z$6:$Z$25))=0,IFERROR(INDEX(定数マスタ!$U$6:$U$17,MONTH($B18)),1),SUMPRODUCT(MAX((定数マスタ!$X$6:$X$25<=$B18)*(定数マスタ!$Y$6:$Y$25>=$B18)*定数マスタ!$Z$6:$Z$25)))) -> 1.2 | G18: =IF($B18="","",ROUND(IF(ISNUMBER($D18),$D18,N('設定（最初に1回）'!$C$14))*N($F18),0)) -> 3084 | I18: =IF($B18="","",TEXT($B18,"m/d")&"("&$C18&")") -> 5/11(月)
B19: =IF('設定（最初に1回）'!$C$6="","",'設定（最初に1回）'!$C$6+11) -> 46154 | C19: =IF($B19="","",CHOOSE(WEEKDAY($B19),"日","月","火","水","木","金","土")) -> 火 | D19: 1104 | F19: =IF($B19="","",IF(SUMPRODUCT(MAX((定数マスタ!$X$6:$X$25<=$B19)*(定数マスタ!$Y$6:$Y$25>=$B19)*定数マスタ!$Z$6:$Z$25))=0,IFERROR(INDEX(定数マスタ!$U$6:$U$17,MONTH($B19)),1),SUMPRODUCT(MAX((定数マスタ!$X$6:$X$25<=$B19)*(定数マスタ!$Y$6:$Y$25>=$B19)*定数マスタ!$Z$6:$Z$25)))) -> 1.2 | G19: =IF($B19="","",ROUND(IF(ISNUMBER($D19),$D19,N('設定（最初に1回）'!$C$14))*N($F19),0)) -> 1325 | I19: =IF($B19="","",TEXT($B19,"m/d")&"("&$C19&")") -> 5/12(火)
B20: =IF('設定（最初に1回）'!$C$6="","",'設定（最初に1回）'!$C$6+12) -> 46155 | C20: =IF($B20="","",CHOOSE(WEEKDAY($B20),"日","月","火","水","木","金","土")) -> 水 | D20: 1014 | F20: =IF($B20="","",IF(SUMPRODUCT(MAX((定数マスタ!$X$6:$X$25<=$B20)*(定数マスタ!$Y$6:$Y$25>=$B20)*定数マスタ!$Z$6:$Z$25))=0,IFERROR(INDEX(定数マスタ!$U$6:$U$17,MONTH($B20)),1),SUMPRODUCT(MAX((定数マスタ!$X$6:$X$25<=$B20)*(定数マスタ!$Y$6:$Y$25>=$B20)*定数マスタ!$Z$6:$Z$25)))) -> 1.2 | G20: =IF($B20="","",ROUND(IF(ISNUMBER($D20),$D20,N('設定（最初に1回）'!$C$14))*N($F20),0)) -> 1217 | I20: =IF($B20="","",TEXT($B20,"m/d")&"("&$C20&")") -> 5/13(水)
B21: =IF('設定（最初に1回）'!$C$6="","",'設定（最初に1回）'!$C$6+13) -> 46156 | C21: =IF($B21="","",CHOOSE(WEEKDAY($B21),"日","月","火","水","木","金","土")) -> 木 | D21: 1172 | F21: =IF($B21="","",IF(SUMPRODUCT(MAX((定数マスタ!$X$6:$X$25<=$B21)*(定数マスタ!$Y$6:$Y$25>=$B21)*定数マスタ!$Z$6:$Z$25))=0,IFERROR(INDEX(定数マスタ!$U$6:$U$17,MONTH($B21)),1),SUMPRODUCT(MAX((定数マスタ!$X$6:$X$25<=$B21)*(定数マスタ!$Y$6:$Y$25>=$B21)*定数マスタ!$Z$6:$Z$25)))) -> 1.2 | G21: =IF($B21="","",ROUND(IF(ISNUMBER($D21),$D21,N('設定（最初に1回）'!$C$14))*N($F21),0)) -> 1406 | I21: =IF($B21="","",TEXT($B21,"m/d")&"("&$C21&")") -> 5/14(木)
B22: =IF('設定（最初に1回）'!$C$6="","",'設定（最初に1回）'!$C$6+14) -> 46157 | C22: =IF($B22="","",CHOOSE(WEEKDAY($B22),"日","月","火","水","木","金","土")) -> 金 | D22: 2802 | E22: 大型アニメ作品 公開初日 | F22: =IF($B22="","",IF(SUMPRODUCT(MAX((定数マスタ!$X$6:$X$25<=$B22)*(定数マスタ!$Y$6:$Y$25>=$B22)*定数マスタ!$Z$6:$Z$25))=0,IFERROR(INDEX(定数マスタ!$U$6:$U$17,MONTH($B22)),1),SUMPRODUCT(MAX((定数マスタ!$X$6:$X$25<=$B22)*(定数マスタ!$Y$6:$Y$25>=$B22)*定数マスタ!$Z$6:$Z$25)))) -> 1.6 | G22: =IF($B22="","",ROUND(IF(ISNUMBER($D22),$D22,N('設定（最初に1回）'!$C$14))*N($F22),0)) -> 4483 | I22: =IF($B22="","",TEXT($B22,"m/d")&"("&$C22&")") -> 5/15(金)
B23: =IF('設定（最初に1回）'!$C$6="","",'設定（最初に1回）'!$C$6+15) -> 46158 | C23: =IF($B23="","",CHOOSE(WEEKDAY($B23),"日","月","火","水","木","金","土")) -> 土 | D23: 3465 | E23: 大型アニメ作品 公開2日目 | F23: =IF($B23="","",IF(SUMPRODUCT(MAX((定数マスタ!$X$6:$X$25<=$B23)*(定数マスタ!$Y$6:$Y$25>=$B23)*定数マスタ!$Z$6:$Z$25))=0,IFERROR(INDEX(定数マスタ!$U$6:$U$17,MONTH($B23)),1),SUMPRODUCT(MAX((定数マスタ!$X$6:$X$25<=$B23)*(定数マスタ!$Y$6:$Y$25>=$B23)*定数マスタ!$Z$6:$Z$25)))) -> 1.6 | G23: =IF($B23="","",ROUND(IF(ISNUMBER($D23),$D23,N('設定（最初に1回）'!$C$14))*N($F23),0)) -> 5544 | I23: =IF($B23="","",TEXT($B23,"m/d")&"("&$C23&")") -> 5/16(土)
B24: =IF('設定（最初に1回）'!$C$6="","",'設定（最初に1回）'!$C$6+16) -> 46159 | C24: =IF($B24="","",CHOOSE(WEEKDAY($B24),"日","月","火","水","木","金","土")) -> 日 | D24: 5409 | E24: 大型アニメ作品 公開3日目 | F24: =IF($B24="","",IF(SUMPRODUCT(MAX((定数マスタ!$X$6:$X$25<=$B24)*(定数マスタ!$Y$6:$Y$25>=$B24)*定数マスタ!$Z$6:$Z$25))=0,IFERROR(INDEX(定数マスタ!$U$6:$U$17,MONTH($B24)),1),SUMPRODUCT(MAX((定数マスタ!$X$6:$X$25<=$B24)*(定数マスタ!$Y$6:$Y$25>=$B24)*定数マスタ!$Z$6:$Z$25)))) -> 1.6 | G24: =IF($B24="","",ROUND(IF(ISNUMBER($D24),$D24,N('設定（最初に1回）'!$C$14))*N($F24),0)) -> 8654 | I24: =IF($B24="","",TEXT($B24,"m/d")&"("&$C24&")") -> 5/17(日)
B25: =IF('設定（最初に1回）'!$C$6="","",'設定（最初に1回）'!$C$6+17) -> 46160 | C25: =IF($B25="","",CHOOSE(WEEKDAY($B25),"日","月","火","水","木","金","土")) -> 月 | D25: 2815 | F25: =IF($B25="","",IF(SUMPRODUCT(MAX((定数マスタ!$X$6:$X$25<=$B25)*(定数マスタ!$Y$6:$Y$25>=$B25)*定数マスタ!$Z$6:$Z$25))=0,IFERROR(INDEX(定数マスタ!$U$6:$U$17,MONTH($B25)),1),SUMPRODUCT(MAX((定数マスタ!$X$6:$X$25<=$B25)*(定数マスタ!$Y$6:$Y$25>=$B25)*定数マスタ!$Z$6:$Z$25)))) -> 1.6 | G25: =IF($B25="","",ROUND(IF(ISNUMBER($D25),$D25,N('設定（最初に1回）'!$C$14))*N($F25),0)) -> 4504 | I25: =IF($B25="","",TEXT($B25,"m/d")&"("&$C25&")") -> 5/18(月)
B26: =IF('設定（最初に1回）'!$C$6="","",'設定（最初に1回）'!$C$6+18) -> 46161 | C26: =IF($B26="","",CHOOSE(WEEKDAY($B26),"日","月","火","水","木","金","土")) -> 火 | D26: 953 | F26: =IF($B26="","",IF(SUMPRODUCT(MAX((定数マスタ!$X$6:$X$25<=$B26)*(定数マスタ!$Y$6:$Y$25>=$B26)*定数マスタ!$Z$6:$Z$25))=0,IFERROR(INDEX(定数マスタ!$U$6:$U$17,MONTH($B26)),1),SUMPRODUCT(MAX((定数マスタ!$X$6:$X$25<=$B26)*(定数マスタ!$Y$6:$Y$25>=$B26)*定数マスタ!$Z$6:$Z$25)))) -> 1.6 | G26: =IF($B26="","",ROUND(IF(ISNUMBER($D26),$D26,N('設定（最初に1回）'!$C$14))*N($F26),0)) -> 1525 | I26: =IF($B26="","",TEXT($B26,"m/d")&"("&$C26&")") -> 5/19(火)
B27: =IF('設定（最初に1回）'!$C$6="","",'設定（最初に1回）'!$C$6+19) -> 46162 | C27: =IF($B27="","",CHOOSE(WEEKDAY($B27),"日","月","火","水","木","金","土")) -> 水 | D27: 994 | F27: =IF($B27="","",IF(SUMPRODUCT(MAX((定数マスタ!$X$6:$X$25<=$B27)*(定数マスタ!$Y$6:$Y$25>=$B27)*定数マスタ!$Z$6:$Z$25))=0,IFERROR(INDEX(定数マスタ!$U$6:$U$17,MONTH($B27)),1),SUMPRODUCT(MAX((定数マスタ!$X$6:$X$25<=$B27)*(定数マスタ!$Y$6:$Y$25>=$B27)*定数マスタ!$Z$6:$Z$25)))) -> 1.6 | G27: =IF($B27="","",ROUND(IF(ISNUMBER($D27),$D27,N('設定（最初に1回）'!$C$14))*N($F27),0)) -> 1590 | I27: =IF($B27="","",TEXT($B27,"m/d")&"("&$C27&")") -> 5/20(水)
B28: =IF('設定（最初に1回）'!$C$6="","",'設定（最初に1回）'!$C$6+20) -> 46163 | C28: =IF($B28="","",CHOOSE(WEEKDAY($B28),"日","月","火","水","木","金","土")) -> 木 | D28: 1044 | F28: =IF($B28="","",IF(SUMPRODUCT(MAX((定数マスタ!$X$6:$X$25<=$B28)*(定数マスタ!$Y$6:$Y$25>=$B28)*定数マスタ!$Z$6:$Z$25))=0,IFERROR(INDEX(定数マスタ!$U$6:$U$17,MONTH($B28)),1),SUMPRODUCT(MAX((定数マスタ!$X$6:$X$25<=$B28)*(定数マスタ!$Y$6:$Y$25>=$B28)*定数マスタ!$Z$6:$Z$25)))) -> 1.6 | G28: =IF($B28="","",ROUND(IF(ISNUMBER($D28),$D28,N('設定（最初に1回）'!$C$14))*N($F28),0)) -> 1670 | I28: =IF($B28="","",TEXT($B28,"m/d")&"("&$C28&")") -> 5/21(木)
B29: =IF('設定（最初に1回）'!$C$6="","",'設定（最初に1回）'!$C$6+21) -> 46164 | C29: =IF($B29="","",CHOOSE(WEEKDAY($B29),"日","月","火","水","木","金","土")) -> 金 | D29: 2733 | E29: 洋画大作 公開 | F29: =IF($B29="","",IF(SUMPRODUCT(MAX((定数マスタ!$X$6:$X$25<=$B29)*(定数マスタ!$Y$6:$Y$25>=$B29)*定数マスタ!$Z$6:$Z$25))=0,IFERROR(INDEX(定数マスタ!$U$6:$U$17,MONTH($B29)),1),SUMPRODUCT(MAX((定数マスタ!$X$6:$X$25<=$B29)*(定数マスタ!$Y$6:$Y$25>=$B29)*定数マスタ!$Z$6:$Z$25)))) -> 1.2 | G29: =IF($B29="","",ROUND(IF(ISNUMBER($D29),$D29,N('設定（最初に1回）'!$C$14))*N($F29),0)) -> 3280 | I29: =IF($B29="","",TEXT($B29,"m/d")&"("&$C29&")") -> 5/22(金)
B30: =IF('設定（最初に1回）'!$C$6="","",'設定（最初に1回）'!$C$6+22) -> 46165 | C30: =IF($B30="","",CHOOSE(WEEKDAY($B30),"日","月","火","水","木","金","土")) -> 土 | F30: =IF($B30="","",IF(SUMPRODUCT(MAX((定数マスタ!$X$6:$X$25<=$B30)*(定数マスタ!$Y$6:$Y$25>=$B30)*定数マスタ!$Z$6:$Z$25))=0,IFERROR(INDEX(定数マスタ!$U$6:$U$17,MONTH($B30)),1),SUMPRODUCT(MAX((定数マスタ!$X$6:$X$25<=$B30)*(定数マスタ!$Y$6:$Y$25>=$B30)*定数マスタ!$Z$6:$Z$25)))) -> 1.2 | G30: =IF($B30="","",ROUND(IF(ISNUMBER($D30),$D30,N('設定（最初に1回）'!$C$14))*N($F30),0)) -> 3600 | I30: =IF($B30="","",TEXT($B30,"m/d")&"("&$C30&")") -> 5/23(土)
B31: =IF('設定（最初に1回）'!$C$6="","",'設定（最初に1回）'!$C$6+23) -> 46166 | C31: =IF($B31="","",CHOOSE(WEEKDAY($B31),"日","月","火","水","木","金","土")) -> 日 | F31: =IF($B31="","",IF(SUMPRODUCT(MAX((定数マスタ!$X$6:$X$25<=$B31)*(定数マスタ!$Y$6:$Y$25>=$B31)*定数マスタ!$Z$6:$Z$25))=0,IFERROR(INDEX(定数マスタ!$U$6:$U$17,MONTH($B31)),1),SUMPRODUCT(MAX((定数マスタ!$X$6:$X$25<=$B31)*(定数マスタ!$Y$6:$Y$25>=$B31)*定数マスタ!$Z$6:$Z$25)))) -> 1.2 | G31: =IF($B31="","",ROUND(IF(ISNUMBER($D31),$D31,N('設定（最初に1回）'!$C$14))*N($F31),0)) -> 3600 | I31: =IF($B31="","",TEXT($B31,"m/d")&"("&$C31&")") -> 5/24(日)
B32: =IF('設定（最初に1回）'!$C$6="","",'設定（最初に1回）'!$C$6+24) -> 46167 | C32: =IF($B32="","",CHOOSE(WEEKDAY($B32),"日","月","火","水","木","金","土")) -> 月 | F32: =IF($B32="","",IF(SUMPRODUCT(MAX((定数マスタ!$X$6:$X$25<=$B32)*(定数マスタ!$Y$6:$Y$25>=$B32)*定数マスタ!$Z$6:$Z$25))=0,IFERROR(INDEX(定数マスタ!$U$6:$U$17,MONTH($B32)),1),SUMPRODUCT(MAX((定数マスタ!$X$6:$X$25<=$B32)*(定数マスタ!$Y$6:$Y$25>=$B32)*定数マスタ!$Z$6:$Z$25)))) -> 1.2 | G32: =IF($B32="","",ROUND(IF(ISNUMBER($D32),$D32,N('設定（最初に1回）'!$C$14))*N($F32),0)) -> 3600 | I32: =IF($B32="","",TEXT($B32,"m/d")&"("&$C32&")") -> 5/25(月)
B33: =IF('設定（最初に1回）'!$C$6="","",'設定（最初に1回）'!$C$6+25) -> 46168 | C33: =IF($B33="","",CHOOSE(WEEKDAY($B33),"日","月","火","水","木","金","土")) -> 火 | F33: =IF($B33="","",IF(SUMPRODUCT(MAX((定数マスタ!$X$6:$X$25<=$B33)*(定数マスタ!$Y$6:$Y$25>=$B33)*定数マスタ!$Z$6:$Z$25))=0,IFERROR(INDEX(定数マスタ!$U$6:$U$17,MONTH($B33)),1),SUMPRODUCT(MAX((定数マスタ!$X$6:$X$25<=$B33)*(定数マスタ!$Y$6:$Y$25>=$B33)*定数マスタ!$Z$6:$Z$25)))) -> 1.2 | G33: =IF($B33="","",ROUND(IF(ISNUMBER($D33),$D33,N('設定（最初に1回）'!$C$14))*N($F33),0)) -> 3600 | I33: =IF($B33="","",TEXT($B33,"m/d")&"("&$C33&")") -> 5/26(火)
B34: =IF('設定（最初に1回）'!$C$6="","",'設定（最初に1回）'!$C$6+26) -> 46169 | C34: =IF($B34="","",CHOOSE(WEEKDAY($B34),"日","月","火","水","木","金","土")) -> 水 | F34: =IF($B34="","",IF(SUMPRODUCT(MAX((定数マスタ!$X$6:$X$25<=$B34)*(定数マスタ!$Y$6:$Y$25>=$B34)*定数マスタ!$Z$6:$Z$25))=0,IFERROR(INDEX(定数マスタ!$U$6:$U$17,MONTH($B34)),1),SUMPRODUCT(MAX((定数マスタ!$X$6:$X$25<=$B34)*(定数マスタ!$Y$6:$Y$25>=$B34)*定数マスタ!$Z$6:$Z$25)))) -> 1.2 | G34: =IF($B34="","",ROUND(IF(ISNUMBER($D34),$D34,N('設定（最初に1回）'!$C$14))*N($F34),0)) -> 3600 | I34: =IF($B34="","",TEXT($B34,"m/d")&"("&$C34&")") -> 5/27(水)
B35: =IF('設定（最初に1回）'!$C$6="","",'設定（最初に1回）'!$C$6+27) -> 46170 | C35: =IF($B35="","",CHOOSE(WEEKDAY($B35),"日","月","火","水","木","金","土")) -> 木 | F35: =IF($B35="","",IF(SUMPRODUCT(MAX((定数マスタ!$X$6:$X$25<=$B35)*(定数マスタ!$Y$6:$Y$25>=$B35)*定数マスタ!$Z$6:$Z$25))=0,IFERROR(INDEX(定数マスタ!$U$6:$U$17,MONTH($B35)),1),SUMPRODUCT(MAX((定数マスタ!$X$6:$X$25<=$B35)*(定数マスタ!$Y$6:$Y$25>=$B35)*定数マスタ!$Z$6:$Z$25)))) -> 1.2 | G35: =IF($B35="","",ROUND(IF(ISNUMBER($D35),$D35,N('設定（最初に1回）'!$C$14))*N($F35),0)) -> 3600 | I35: =IF($B35="","",TEXT($B35,"m/d")&"("&$C35&")") -> 5/28(木)
B36: =IF('設定（最初に1回）'!$C$6="","",'設定（最初に1回）'!$C$6+28) -> 46171 | C36: =IF($B36="","",CHOOSE(WEEKDAY($B36),"日","月","火","水","木","金","土")) -> 金 | F36: =IF($B36="","",IF(SUMPRODUCT(MAX((定数マスタ!$X$6:$X$25<=$B36)*(定数マスタ!$Y$6:$Y$25>=$B36)*定数マスタ!$Z$6:$Z$25))=0,IFERROR(INDEX(定数マスタ!$U$6:$U$17,MONTH($B36)),1),SUMPRODUCT(MAX((定数マスタ!$X$6:$X$25<=$B36)*(定数マスタ!$Y$6:$Y$25>=$B36)*定数マスタ!$Z$6:$Z$25)))) -> 1.2 | G36: =IF($B36="","",ROUND(IF(ISNUMBER($D36),$D36,N('設定（最初に1回）'!$C$14))*N($F36),0)) -> 3600 | I36: =IF($B36="","",TEXT($B36,"m/d")&"("&$C36&")") -> 5/29(金)
B37: =IF('設定（最初に1回）'!$C$6="","",'設定（最初に1回）'!$C$6+29) -> 46172 | C37: =IF($B37="","",CHOOSE(WEEKDAY($B37),"日","月","火","水","木","金","土")) -> 土 | F37: =IF($B37="","",IF(SUMPRODUCT(MAX((定数マスタ!$X$6:$X$25<=$B37)*(定数マスタ!$Y$6:$Y$25>=$B37)*定数マスタ!$Z$6:$Z$25))=0,IFERROR(INDEX(定数マスタ!$U$6:$U$17,MONTH($B37)),1),SUMPRODUCT(MAX((定数マスタ!$X$6:$X$25<=$B37)*(定数マスタ!$Y$6:$Y$25>=$B37)*定数マスタ!$Z$6:$Z$25)))) -> 1.2 | G37: =IF($B37="","",ROUND(IF(ISNUMBER($D37),$D37,N('設定（最初に1回）'!$C$14))*N($F37),0)) -> 3600 | I37: =IF($B37="","",TEXT($B37,"m/d")&"("&$C37&")") -> 5/30(土)
B38: =IF('設定（最初に1回）'!$C$6="","",'設定（最初に1回）'!$C$6+30) -> 46173 | C38: =IF($B38="","",CHOOSE(WEEKDAY($B38),"日","月","火","水","木","金","土")) -> 日 | F38: =IF($B38="","",IF(SUMPRODUCT(MAX((定数マスタ!$X$6:$X$25<=$B38)*(定数マスタ!$Y$6:$Y$25>=$B38)*定数マスタ!$Z$6:$Z$25))=0,IFERROR(INDEX(定数マスタ!$U$6:$U$17,MONTH($B38)),1),SUMPRODUCT(MAX((定数マスタ!$X$6:$X$25<=$B38)*(定数マスタ!$Y$6:$Y$25>=$B38)*定数マスタ!$Z$6:$Z$25)))) -> 1.2 | G38: =IF($B38="","",ROUND(IF(ISNUMBER($D38),$D38,N('設定（最初に1回）'!$C$14))*N($F38),0)) -> 3600 | I38: =IF($B38="","",TEXT($B38,"m/d")&"("&$C38&")") -> 5/31(日)
B39: =IF('設定（最初に1回）'!$C$6="","",'設定（最初に1回）'!$C$6+31) -> 46174 | C39: =IF($B39="","",CHOOSE(WEEKDAY($B39),"日","月","火","水","木","金","土")) -> 月 | F39: =IF($B39="","",IF(SUMPRODUCT(MAX((定数マスタ!$X$6:$X$25<=$B39)*(定数マスタ!$Y$6:$Y$25>=$B39)*定数マスタ!$Z$6:$Z$25))=0,IFERROR(INDEX(定数マスタ!$U$6:$U$17,MONTH($B39)),1),SUMPRODUCT(MAX((定数マスタ!$X$6:$X$25<=$B39)*(定数マスタ!$Y$6:$Y$25>=$B39)*定数マスタ!$Z$6:$Z$25)))) -> 0.85 | G39: =IF($B39="","",ROUND(IF(ISNUMBER($D39),$D39,N('設定（最初に1回）'!$C$14))*N($F39),0)) -> 2550 | I39: =IF($B39="","",TEXT($B39,"m/d")&"("&$C39&")") -> 6/1(月)
B40: =IF('設定（最初に1回）'!$C$6="","",'設定（最初に1回）'!$C$6+32) -> 46175 | C40: =IF($B40="","",CHOOSE(WEEKDAY($B40),"日","月","火","水","木","金","土")) -> 火 | F40: =IF($B40="","",IF(SUMPRODUCT(MAX((定数マスタ!$X$6:$X$25<=$B40)*(定数マスタ!$Y$6:$Y$25>=$B40)*定数マスタ!$Z$6:$Z$25))=0,IFERROR(INDEX(定数マスタ!$U$6:$U$17,MONTH($B40)),1),SUMPRODUCT(MAX((定数マスタ!$X$6:$X$25<=$B40)*(定数マスタ!$Y$6:$Y$25>=$B40)*定数マスタ!$Z$6:$Z$25)))) -> 0.85 | G40: =IF($B40="","",ROUND(IF(ISNUMBER($D40),$D40,N('設定（最初に1回）'!$C$14))*N($F40),0)) -> 2550 | I40: =IF($B40="","",TEXT($B40,"m/d")&"("&$C40&")") -> 6/2(火)
B41: =IF('設定（最初に1回）'!$C$6="","",'設定（最初に1回）'!$C$6+33) -> 46176 | C41: =IF($B41="","",CHOOSE(WEEKDAY($B41),"日","月","火","水","木","金","土")) -> 水 | D41: 1835 | E41: 映画の日 | F41: =IF($B41="","",IF(SUMPRODUCT(MAX((定数マスタ!$X$6:$X$25<=$B41)*(定数マスタ!$Y$6:$Y$25>=$B41)*定数マスタ!$Z$6:$Z$25))=0,IFERROR(INDEX(定数マスタ!$U$6:$U$17,MONTH($B41)),1),SUMPRODUCT(MAX((定数マスタ!$X$6:$X$25<=$B41)*(定数マスタ!$Y$6:$Y$25>=$B41)*定数マスタ!$Z$6:$Z$25)))) -> 0.85 | G41: =IF($B41="","",ROUND(IF(ISNUMBER($D41),$D41,N('設定（最初に1回）'!$C$14))*N($F41),0)) -> 1560 | I41: =IF($B41="","",TEXT($B41,"m/d")&"("&$C41&")") -> 6/3(水)
B42: =IF('設定（最初に1回）'!$C$6="","",'設定（最初に1回）'!$C$6+34) -> 46177 | C42: =IF($B42="","",CHOOSE(WEEKDAY($B42),"日","月","火","水","木","金","土")) -> 木 | F42: =IF($B42="","",IF(SUMPRODUCT(MAX((定数マスタ!$X$6:$X$25<=$B42)*(定数マスタ!$Y$6:$Y$25>=$B42)*定数マスタ!$Z$6:$Z$25))=0,IFERROR(INDEX(定数マスタ!$U$6:$U$17,MONTH($B42)),1),SUMPRODUCT(MAX((定数マスタ!$X$6:$X$25<=$B42)*(定数マスタ!$Y$6:$Y$25>=$B42)*定数マスタ!$Z$6:$Z$25)))) -> 0.85 | G42: =IF($B42="","",ROUND(IF(ISNUMBER($D42),$D42,N('設定（最初に1回）'!$C$14))*N($F42),0)) -> 2550 | I42: =IF($B42="","",TEXT($B42,"m/d")&"("&$C42&")") -> 6/4(木)
B43: =IF('設定（最初に1回）'!$C$6="","",'設定（最初に1回）'!$C$6+35) -> 46178 | C43: =IF($B43="","",CHOOSE(WEEKDAY($B43),"日","月","火","水","木","金","土")) -> 金 | F43: =IF($B43="","",IF(SUMPRODUCT(MAX((定数マスタ!$X$6:$X$25<=$B43)*(定数マスタ!$Y$6:$Y$25>=$B43)*定数マスタ!$Z$6:$Z$25))=0,IFERROR(INDEX(定数マスタ!$U$6:$U$17,MONTH($B43)),1),SUMPRODUCT(MAX((定数マスタ!$X$6:$X$25<=$B43)*(定数マスタ!$Y$6:$Y$25>=$B43)*定数マスタ!$Z$6:$Z$25)))) -> 0.85 | G43: =IF($B43="","",ROUND(IF(ISNUMBER($D43),$D43,N('設定（最初に1回）'!$C$14))*N($F43),0)) -> 2550 | I43: =IF($B43="","",TEXT($B43,"m/d")&"("&$C43&")") -> 6/5(金)
B44: =IF('設定（最初に1回）'!$C$6="","",'設定（最初に1回）'!$C$6+36) -> 46179 | C44: =IF($B44="","",CHOOSE(WEEKDAY($B44),"日","月","火","水","木","金","土")) -> 土 | F44: =IF($B44="","",IF(SUMPRODUCT(MAX((定数マスタ!$X$6:$X$25<=$B44)*(定数マスタ!$Y$6:$Y$25>=$B44)*定数マスタ!$Z$6:$Z$25))=0,IFERROR(INDEX(定数マスタ!$U$6:$U$17,MONTH($B44)),1),SUMPRODUCT(MAX((定数マスタ!$X$6:$X$25<=$B44)*(定数マスタ!$Y$6:$Y$25>=$B44)*定数マスタ!$Z$6:$Z$25)))) -> 0.85 | G44: =IF($B44="","",ROUND(IF(ISNUMBER($D44),$D44,N('設定（最初に1回）'!$C$14))*N($F44),0)) -> 2550 | I44: =IF($B44="","",TEXT($B44,"m/d")&"("&$C44&")") -> 6/6(土)
B45: =IF('設定（最初に1回）'!$C$6="","",'設定（最初に1回）'!$C$6+37) -> 46180 | C45: =IF($B45="","",CHOOSE(WEEKDAY($B45),"日","月","火","水","木","金","土")) -> 日 | F45: =IF($B45="","",IF(SUMPRODUCT(MAX((定数マスタ!$X$6:$X$25<=$B45)*(定数マスタ!$Y$6:$Y$25>=$B45)*定数マスタ!$Z$6:$Z$25))=0,IFERROR(INDEX(定数マスタ!$U$6:$U$17,MONTH($B45)),1),SUMPRODUCT(MAX((定数マスタ!$X$6:$X$25<=$B45)*(定数マスタ!$Y$6:$Y$25>=$B45)*定数マスタ!$Z$6:$Z$25)))) -> 0.85 | G45: =IF($B45="","",ROUND(IF(ISNUMBER($D45),$D45,N('設定（最初に1回）'!$C$14))*N($F45),0)) -> 2550 | I45: =IF($B45="","",TEXT($B45,"m/d")&"("&$C45&")") -> 6/7(日)
B46: =IF('設定（最初に1回）'!$C$6="","",'設定（最初に1回）'!$C$6+38) -> 46181 | C46: =IF($B46="","",CHOOSE(WEEKDAY($B46),"日","月","火","水","木","金","土")) -> 月 | F46: =IF($B46="","",IF(SUMPRODUCT(MAX((定数マスタ!$X$6:$X$25<=$B46)*(定数マスタ!$Y$6:$Y$25>=$B46)*定数マスタ!$Z$6:$Z$25))=0,IFERROR(INDEX(定数マスタ!$U$6:$U$17,MONTH($B46)),1),SUMPRODUCT(MAX((定数マスタ!$X$6:$X$25<=$B46)*(定数マスタ!$Y$6:$Y$25>=$B46)*定数マスタ!$Z$6:$Z$25)))) -> 0.8 | G46: =IF($B46="","",ROUND(IF(ISNUMBER($D46),$D46,N('設定（最初に1回）'!$C$14))*N($F46),0)) -> 2400 | I46: =IF($B46="","",TEXT($B46,"m/d")&"("&$C46&")") -> 6/8(月)
B47: =IF('設定（最初に1回）'!$C$6="","",'設定（最初に1回）'!$C$6+39) -> 46182 | C47: =IF($B47="","",CHOOSE(WEEKDAY($B47),"日","月","火","水","木","金","土")) -> 火 | F47: =IF($B47="","",IF(SUMPRODUCT(MAX((定数マスタ!$X$6:$X$25<=$B47)*(定数マスタ!$Y$6:$Y$25>=$B47)*定数マスタ!$Z$6:$Z$25))=0,IFERROR(INDEX(定数マスタ!$U$6:$U$17,MONTH($B47)),1),SUMPRODUCT(MAX((定数マスタ!$X$6:$X$25<=$B47)*(定数マスタ!$Y$6:$Y$25>=$B47)*定数マスタ!$Z$6:$Z$25)))) -> 0.8 | G47: =IF($B47="","",ROUND(IF(ISNUMBER($D47),$D47,N('設定（最初に1回）'!$C$14))*N($F47),0)) -> 2400 | I47: =IF($B47="","",TEXT($B47,"m/d")&"("&$C47&")") -> 6/9(火)
B48: =IF('設定（最初に1回）'!$C$6="","",'設定（最初に1回）'!$C$6+40) -> 46183 | C48: =IF($B48="","",CHOOSE(WEEKDAY($B48),"日","月","火","水","木","金","土")) -> 水 | F48: =IF($B48="","",IF(SUMPRODUCT(MAX((定数マスタ!$X$6:$X$25<=$B48)*(定数マスタ!$Y$6:$Y$25>=$B48)*定数マスタ!$Z$6:$Z$25))=0,IFERROR(INDEX(定数マスタ!$U$6:$U$17,MONTH($B48)),1),SUMPRODUCT(MAX((定数マスタ!$X$6:$X$25<=$B48)*(定数マスタ!$Y$6:$Y$25>=$B48)*定数マスタ!$Z$6:$Z$25)))) -> 0.8 | G48: =IF($B48="","",ROUND(IF(ISNUMBER($D48),$D48,N('設定（最初に1回）'!$C$14))*N($F48),0)) -> 2400 | I48: =IF($B48="","",TEXT($B48,"m/d")&"("&$C48&")") -> 6/10(水)
B49: =IF('設定（最初に1回）'!$C$6="","",'設定（最初に1回）'!$C$6+41) -> 46184 | C49: =IF($B49="","",CHOOSE(WEEKDAY($B49),"日","月","火","水","木","金","土")) -> 木 | F49: =IF($B49="","",IF(SUMPRODUCT(MAX((定数マスタ!$X$6:$X$25<=$B49)*(定数マスタ!$Y$6:$Y$25>=$B49)*定数マスタ!$Z$6:$Z$25))=0,IFERROR(INDEX(定数マスタ!$U$6:$U$17,MONTH($B49)),1),SUMPRODUCT(MAX((定数マスタ!$X$6:$X$25<=$B49)*(定数マスタ!$Y$6:$Y$25>=$B49)*定数マスタ!$Z$6:$Z$25)))) -> 0.8 | G49: =IF($B49="","",ROUND(IF(ISNUMBER($D49),$D49,N('設定（最初に1回）'!$C$14))*N($F49),0)) -> 2400 | I49: =IF($B49="","",TEXT($B49,"m/d")&"("&$C49&")") -> 6/11(木)
B50: =IF('設定（最初に1回）'!$C$6="","",'設定（最初に1回）'!$C$6+42) -> 46185 | C50: =IF($B50="","",CHOOSE(WEEKDAY($B50),"日","月","火","水","木","金","土")) -> 金 | F50: =IF($B50="","",IF(SUMPRODUCT(MAX((定数マスタ!$X$6:$X$25<=$B50)*(定数マスタ!$Y$6:$Y$25>=$B50)*定数マスタ!$Z$6:$Z$25))=0,IFERROR(INDEX(定数マスタ!$U$6:$U$17,MONTH($B50)),1),SUMPRODUCT(MAX((定数マスタ!$X$6:$X$25<=$B50)*(定数マスタ!$Y$6:$Y$25>=$B50)*定数マスタ!$Z$6:$Z$25)))) -> 0.8 | G50: =IF($B50="","",ROUND(IF(ISNUMBER($D50),$D50,N('設定（最初に1回）'!$C$14))*N($F50),0)) -> 2400 | I50: =IF($B50="","",TEXT($B50,"m/d")&"("&$C50&")") -> 6/12(金)
B51: =IF('設定（最初に1回）'!$C$6="","",'設定（最初に1回）'!$C$6+43) -> 46186 | C51: =IF($B51="","",CHOOSE(WEEKDAY($B51),"日","月","火","水","木","金","土")) -> 土 | F51: =IF($B51="","",IF(SUMPRODUCT(MAX((定数マスタ!$X$6:$X$25<=$B51)*(定数マスタ!$Y$6:$Y$25>=$B51)*定数マスタ!$Z$6:$Z$25))=0,IFERROR(INDEX(定数マスタ!$U$6:$U$17,MONTH($B51)),1),SUMPRODUCT(MAX((定数マスタ!$X$6:$X$25<=$B51)*(定数マスタ!$Y$6:$Y$25>=$B51)*定数マスタ!$Z$6:$Z$25)))) -> 0.8 | G51: =IF($B51="","",ROUND(IF(ISNUMBER($D51),$D51,N('設定（最初に1回）'!$C$14))*N($F51),0)) -> 2400 | I51: =IF($B51="","",TEXT($B51,"m/d")&"("&$C51&")") -> 6/13(土)
B52: =IF('設定（最初に1回）'!$C$6="","",'設定（最初に1回）'!$C$6+44) -> 46187 | C52: =IF($B52="","",CHOOSE(WEEKDAY($B52),"日","月","火","水","木","金","土")) -> 日 | F52: =IF($B52="","",IF(SUMPRODUCT(MAX((定数マスタ!$X$6:$X$25<=$B52)*(定数マスタ!$Y$6:$Y$25>=$B52)*定数マスタ!$Z$6:$Z$25))=0,IFERROR(INDEX(定数マスタ!$U$6:$U$17,MONTH($B52)),1),SUMPRODUCT(MAX((定数マスタ!$X$6:$X$25<=$B52)*(定数マスタ!$Y$6:$Y$25>=$B52)*定数マスタ!$Z$6:$Z$25)))) -> 0.8 | G52: =IF($B52="","",ROUND(IF(ISNUMBER($D52),$D52,N('設定（最初に1回）'!$C$14))*N($F52),0)) -> 2400 | I52: =IF($B52="","",TEXT($B52,"m/d")&"("&$C52&")") -> 6/14(日)
B53: =IF('設定（最初に1回）'!$C$6="","",'設定（最初に1回）'!$C$6+45) -> 46188 | C53: =IF($B53="","",CHOOSE(WEEKDAY($B53),"日","月","火","水","木","金","土")) -> 月 | F53: =IF($B53="","",IF(SUMPRODUCT(MAX((定数マスタ!$X$6:$X$25<=$B53)*(定数マスタ!$Y$6:$Y$25>=$B53)*定数マスタ!$Z$6:$Z$25))=0,IFERROR(INDEX(定数マスタ!$U$6:$U$17,MONTH($B53)),1),SUMPRODUCT(MAX((定数マスタ!$X$6:$X$25<=$B53)*(定数マスタ!$Y$6:$Y$25>=$B53)*定数マスタ!$Z$6:$Z$25)))) -> 0.8 | G53: =IF($B53="","",ROUND(IF(ISNUMBER($D53),$D53,N('設定（最初に1回）'!$C$14))*N($F53),0)) -> 2400 | I53: =IF($B53="","",TEXT($B53,"m/d")&"("&$C53&")") -> 6/15(月)
B54: =IF('設定（最初に1回）'!$C$6="","",'設定（最初に1回）'!$C$6+46) -> 46189 | C54: =IF($B54="","",CHOOSE(WEEKDAY($B54),"日","月","火","水","木","金","土")) -> 火 | F54: =IF($B54="","",IF(SUMPRODUCT(MAX((定数マスタ!$X$6:$X$25<=$B54)*(定数マスタ!$Y$6:$Y$25>=$B54)*定数マスタ!$Z$6:$Z$25))=0,IFERROR(INDEX(定数マスタ!$U$6:$U$17,MONTH($B54)),1),SUMPRODUCT(MAX((定数マスタ!$X$6:$X$25<=$B54)*(定数マスタ!$Y$6:$Y$25>=$B54)*定数マスタ!$Z$6:$Z$25)))) -> 0.8 | G54: =IF($B54="","",ROUND(IF(ISNUMBER($D54),$D54,N('設定（最初に1回）'!$C$14))*N($F54),0)) -> 2400 | I54: =IF($B54="","",TEXT($B54,"m/d")&"("&$C54&")") -> 6/16(火)
B55: =IF('設定（最初に1回）'!$C$6="","",'設定（最初に1回）'!$C$6+47) -> 46190 | C55: =IF($B55="","",CHOOSE(WEEKDAY($B55),"日","月","火","水","木","金","土")) -> 水 | F55: =IF($B55="","",IF(SUMPRODUCT(MAX((定数マスタ!$X$6:$X$25<=$B55)*(定数マスタ!$Y$6:$Y$25>=$B55)*定数マスタ!$Z$6:$Z$25))=0,IFERROR(INDEX(定数マスタ!$U$6:$U$17,MONTH($B55)),1),SUMPRODUCT(MAX((定数マスタ!$X$6:$X$25<=$B55)*(定数マスタ!$Y$6:$Y$25>=$B55)*定数マスタ!$Z$6:$Z$25)))) -> 0.8 | G55: =IF($B55="","",ROUND(IF(ISNUMBER($D55),$D55,N('設定（最初に1回）'!$C$14))*N($F55),0)) -> 2400 | I55: =IF($B55="","",TEXT($B55,"m/d")&"("&$C55&")") -> 6/17(水)
B56: =IF('設定（最初に1回）'!$C$6="","",'設定（最初に1回）'!$C$6+48) -> 46191 | C56: =IF($B56="","",CHOOSE(WEEKDAY($B56),"日","月","火","水","木","金","土")) -> 木 | F56: =IF($B56="","",IF(SUMPRODUCT(MAX((定数マスタ!$X$6:$X$25<=$B56)*(定数マスタ!$Y$6:$Y$25>=$B56)*定数マスタ!$Z$6:$Z$25))=0,IFERROR(INDEX(定数マスタ!$U$6:$U$17,MONTH($B56)),1),SUMPRODUCT(MAX((定数マスタ!$X$6:$X$25<=$B56)*(定数マスタ!$Y$6:$Y$25>=$B56)*定数マスタ!$Z$6:$Z$25)))) -> 0.8 | G56: =IF($B56="","",ROUND(IF(ISNUMBER($D56),$D56,N('設定（最初に1回）'!$C$14))*N($F56),0)) -> 2400 | I56: =IF($B56="","",TEXT($B56,"m/d")&"("&$C56&")") -> 6/18(木)
B57: =IF('設定（最初に1回）'!$C$6="","",'設定（最初に1回）'!$C$6+49) -> 46192 | C57: =IF($B57="","",CHOOSE(WEEKDAY($B57),"日","月","火","水","木","金","土")) -> 金 | F57: =IF($B57="","",IF(SUMPRODUCT(MAX((定数マスタ!$X$6:$X$25<=$B57)*(定数マスタ!$Y$6:$Y$25>=$B57)*定数マスタ!$Z$6:$Z$25))=0,IFERROR(INDEX(定数マスタ!$U$6:$U$17,MONTH($B57)),1),SUMPRODUCT(MAX((定数マスタ!$X$6:$X$25<=$B57)*(定数マスタ!$Y$6:$Y$25>=$B57)*定数マスタ!$Z$6:$Z$25)))) -> 0.8 | G57: =IF($B57="","",ROUND(IF(ISNUMBER($D57),$D57,N('設定（最初に1回）'!$C$14))*N($F57),0)) -> 2400 | I57: =IF($B57="","",TEXT($B57,"m/d")&"("&$C57&")") -> 6/19(金)
B58: =IF('設定（最初に1回）'!$C$6="","",'設定（最初に1回）'!$C$6+50) -> 46193 | C58: =IF($B58="","",CHOOSE(WEEKDAY($B58),"日","月","火","水","木","金","土")) -> 土 | F58: =IF($B58="","",IF(SUMPRODUCT(MAX((定数マスタ!$X$6:$X$25<=$B58)*(定数マスタ!$Y$6:$Y$25>=$B58)*定数マスタ!$Z$6:$Z$25))=0,IFERROR(INDEX(定数マスタ!$U$6:$U$17,MONTH($B58)),1),SUMPRODUCT(MAX((定数マスタ!$X$6:$X$25<=$B58)*(定数マスタ!$Y$6:$Y$25>=$B58)*定数マスタ!$Z$6:$Z$25)))) -> 0.85 | G58: =IF($B58="","",ROUND(IF(ISNUMBER($D58),$D58,N('設定（最初に1回）'!$C$14))*N($F58),0)) -> 2550 | I58: =IF($B58="","",TEXT($B58,"m/d")&"("&$C58&")") -> 6/20(土)
B59: =IF('設定（最初に1回）'!$C$6="","",'設定（最初に1回）'!$C$6+51) -> 46194 | C59: =IF($B59="","",CHOOSE(WEEKDAY($B59),"日","月","火","水","木","金","土")) -> 日 | F59: =IF($B59="","",IF(SUMPRODUCT(MAX((定数マスタ!$X$6:$X$25<=$B59)*(定数マスタ!$Y$6:$Y$25>=$B59)*定数マスタ!$Z$6:$Z$25))=0,IFERROR(INDEX(定数マスタ!$U$6:$U$17,MONTH($B59)),1),SUMPRODUCT(MAX((定数マスタ!$X$6:$X$25<=$B59)*(定数マスタ!$Y$6:$Y$25>=$B59)*定数マスタ!$Z$6:$Z$25)))) -> 0.85 | G59: =IF($B59="","",ROUND(IF(ISNUMBER($D59),$D59,N('設定（最初に1回）'!$C$14))*N($F59),0)) -> 2550 | I59: =IF($B59="","",TEXT($B59,"m/d")&"("&$C59&")") -> 6/21(日)
B60: =IF('設定（最初に1回）'!$C$6="","",'設定（最初に1回）'!$C$6+52) -> 46195 | C60: =IF($B60="","",CHOOSE(WEEKDAY($B60),"日","月","火","水","木","金","土")) -> 月 | F60: =IF($B60="","",IF(SUMPRODUCT(MAX((定数マスタ!$X$6:$X$25<=$B60)*(定数マスタ!$Y$6:$Y$25>=$B60)*定数マスタ!$Z$6:$Z$25))=0,IFERROR(INDEX(定数マスタ!$U$6:$U$17,MONTH($B60)),1),SUMPRODUCT(MAX((定数マスタ!$X$6:$X$25<=$B60)*(定数マスタ!$Y$6:$Y$25>=$B60)*定数マスタ!$Z$6:$Z$25)))) -> 0.85 | G60: =IF($B60="","",ROUND(IF(ISNUMBER($D60),$D60,N('設定（最初に1回）'!$C$14))*N($F60),0)) -> 2550 | I60: =IF($B60="","",TEXT($B60,"m/d")&"("&$C60&")") -> 6/22(月)
B61: =IF('設定（最初に1回）'!$C$6="","",'設定（最初に1回）'!$C$6+53) -> 46196 | C61: =IF($B61="","",CHOOSE(WEEKDAY($B61),"日","月","火","水","木","金","土")) -> 火 | F61: =IF($B61="","",IF(SUMPRODUCT(MAX((定数マスタ!$X$6:$X$25<=$B61)*(定数マスタ!$Y$6:$Y$25>=$B61)*定数マスタ!$Z$6:$Z$25))=0,IFERROR(INDEX(定数マスタ!$U$6:$U$17,MONTH($B61)),1),SUMPRODUCT(MAX((定数マスタ!$X$6:$X$25<=$B61)*(定数マスタ!$Y$6:$Y$25>=$B61)*定数マスタ!$Z$6:$Z$25)))) -> 0.85 | G61: =IF($B61="","",ROUND(IF(ISNUMBER($D61),$D61,N('設定（最初に1回）'!$C$14))*N($F61),0)) -> 2550 | I61: =IF($B61="","",TEXT($B61,"m/d")&"("&$C61&")") -> 6/23(火)
B62: =IF('設定（最初に1回）'!$C$6="","",'設定（最初に1回）'!$C$6+54) -> 46197 | C62: =IF($B62="","",CHOOSE(WEEKDAY($B62),"日","月","火","水","木","金","土")) -> 水 | F62: =IF($B62="","",IF(SUMPRODUCT(MAX((定数マスタ!$X$6:$X$25<=$B62)*(定数マスタ!$Y$6:$Y$25>=$B62)*定数マスタ!$Z$6:$Z$25))=0,IFERROR(INDEX(定数マスタ!$U$6:$U$17,MONTH($B62)),1),SUMPRODUCT(MAX((定数マスタ!$X$6:$X$25<=$B62)*(定数マスタ!$Y$6:$Y$25>=$B62)*定数マスタ!$Z$6:$Z$25)))) -> 0.85 | G62: =IF($B62="","",ROUND(IF(ISNUMBER($D62),$D62,N('設定（最初に1回）'!$C$14))*N($F62),0)) -> 2550 | I62: =IF($B62="","",TEXT($B62,"m/d")&"("&$C62&")") -> 6/24(水)
B63: =IF('設定（最初に1回）'!$C$6="","",'設定（最初に1回）'!$C$6+55) -> 46198 | C63: =IF($B63="","",CHOOSE(WEEKDAY($B63),"日","月","火","水","木","金","土")) -> 木 | F63: =IF($B63="","",IF(SUMPRODUCT(MAX((定数マスタ!$X$6:$X$25<=$B63)*(定数マスタ!$Y$6:$Y$25>=$B63)*定数マスタ!$Z$6:$Z$25))=0,IFERROR(INDEX(定数マスタ!$U$6:$U$17,MONTH($B63)),1),SUMPRODUCT(MAX((定数マスタ!$X$6:$X$25<=$B63)*(定数マスタ!$Y$6:$Y$25>=$B63)*定数マスタ!$Z$6:$Z$25)))) -> 0.85 | G63: =IF($B63="","",ROUND(IF(ISNUMBER($D63),$D63,N('設定（最初に1回）'!$C$14))*N($F63),0)) -> 2550 | I63: =IF($B63="","",TEXT($B63,"m/d")&"("&$C63&")") -> 6/25(木)
B64: =IF('設定（最初に1回）'!$C$6="","",'設定（最初に1回）'!$C$6+56) -> 46199 | C64: =IF($B64="","",CHOOSE(WEEKDAY($B64),"日","月","火","水","木","金","土")) -> 金 | F64: =IF($B64="","",IF(SUMPRODUCT(MAX((定数マスタ!$X$6:$X$25<=$B64)*(定数マスタ!$Y$6:$Y$25>=$B64)*定数マスタ!$Z$6:$Z$25))=0,IFERROR(INDEX(定数マスタ!$U$6:$U$17,MONTH($B64)),1),SUMPRODUCT(MAX((定数マスタ!$X$6:$X$25<=$B64)*(定数マスタ!$Y$6:$Y$25>=$B64)*定数マスタ!$Z$6:$Z$25)))) -> 0.85 | G64: =IF($B64="","",ROUND(IF(ISNUMBER($D64),$D64,N('設定（最初に1回）'!$C$14))*N($F64),0)) -> 2550 | I64: =IF($B64="","",TEXT($B64,"m/d")&"("&$C64&")") -> 6/26(金)
B65: =IF('設定（最初に1回）'!$C$6="","",'設定（最初に1回）'!$C$6+57) -> 46200 | C65: =IF($B65="","",CHOOSE(WEEKDAY($B65),"日","月","火","水","木","金","土")) -> 土 | F65: =IF($B65="","",IF(SUMPRODUCT(MAX((定数マスタ!$X$6:$X$25<=$B65)*(定数マスタ!$Y$6:$Y$25>=$B65)*定数マスタ!$Z$6:$Z$25))=0,IFERROR(INDEX(定数マスタ!$U$6:$U$17,MONTH($B65)),1),SUMPRODUCT(MAX((定数マスタ!$X$6:$X$25<=$B65)*(定数マスタ!$Y$6:$Y$25>=$B65)*定数マスタ!$Z$6:$Z$25)))) -> 0.85 | G65: =IF($B65="","",ROUND(IF(ISNUMBER($D65),$D65,N('設定（最初に1回）'!$C$14))*N($F65),0)) -> 2550 | I65: =IF($B65="","",TEXT($B65,"m/d")&"("&$C65&")") -> 6/27(土)
B66: =IF('設定（最初に1回）'!$C$6="","",'設定（最初に1回）'!$C$6+58) -> 46201 | C66: =IF($B66="","",CHOOSE(WEEKDAY($B66),"日","月","火","水","木","金","土")) -> 日 | F66: =IF($B66="","",IF(SUMPRODUCT(MAX((定数マスタ!$X$6:$X$25<=$B66)*(定数マスタ!$Y$6:$Y$25>=$B66)*定数マスタ!$Z$6:$Z$25))=0,IFERROR(INDEX(定数マスタ!$U$6:$U$17,MONTH($B66)),1),SUMPRODUCT(MAX((定数マスタ!$X$6:$X$25<=$B66)*(定数マスタ!$Y$6:$Y$25>=$B66)*定数マスタ!$Z$6:$Z$25)))) -> 0.85 | G66: =IF($B66="","",ROUND(IF(ISNUMBER($D66),$D66,N('設定（最初に1回）'!$C$14))*N($F66),0)) -> 2550 | I66: =IF($B66="","",TEXT($B66,"m/d")&"("&$C66&")") -> 6/28(日)
B67: =IF('設定（最初に1回）'!$C$6="","",'設定（最初に1回）'!$C$6+59) -> 46202 | C67: =IF($B67="","",CHOOSE(WEEKDAY($B67),"日","月","火","水","木","金","土")) -> 月 | F67: =IF($B67="","",IF(SUMPRODUCT(MAX((定数マスタ!$X$6:$X$25<=$B67)*(定数マスタ!$Y$6:$Y$25>=$B67)*定数マスタ!$Z$6:$Z$25))=0,IFERROR(INDEX(定数マスタ!$U$6:$U$17,MONTH($B67)),1),SUMPRODUCT(MAX((定数マスタ!$X$6:$X$25<=$B67)*(定数マスタ!$Y$6:$Y$25>=$B67)*定数マスタ!$Z$6:$Z$25)))) -> 0.85 | G67: =IF($B67="","",ROUND(IF(ISNUMBER($D67),$D67,N('設定（最初に1回）'!$C$14))*N($F67),0)) -> 2550 | I67: =IF($B67="","",TEXT($B67,"m/d")&"("&$C67&")") -> 6/29(月)
B68: =IF('設定（最初に1回）'!$C$6="","",'設定（最初に1回）'!$C$6+60) -> 46203 | C68: =IF($B68="","",CHOOSE(WEEKDAY($B68),"日","月","火","水","木","金","土")) -> 火 | F68: =IF($B68="","",IF(SUMPRODUCT(MAX((定数マスタ!$X$6:$X$25<=$B68)*(定数マスタ!$Y$6:$Y$25>=$B68)*定数マスタ!$Z$6:$Z$25))=0,IFERROR(INDEX(定数マスタ!$U$6:$U$17,MONTH($B68)),1),SUMPRODUCT(MAX((定数マスタ!$X$6:$X$25<=$B68)*(定数マスタ!$Y$6:$Y$25>=$B68)*定数マスタ!$Z$6:$Z$25)))) -> 0.85 | G68: =IF($B68="","",ROUND(IF(ISNUMBER($D68),$D68,N('設定（最初に1回）'!$C$14))*N($F68),0)) -> 2550 | I68: =IF($B68="","",TEXT($B68,"m/d")&"("&$C68&")") -> 6/30(火)
B69: =IF('設定（最初に1回）'!$C$6="","",'設定（最初に1回）'!$C$6+61) -> 46204 | C69: =IF($B69="","",CHOOSE(WEEKDAY($B69),"日","月","火","水","木","金","土")) -> 水 | F69: =IF($B69="","",IF(SUMPRODUCT(MAX((定数マスタ!$X$6:$X$25<=$B69)*(定数マスタ!$Y$6:$Y$25>=$B69)*定数マスタ!$Z$6:$Z$25))=0,IFERROR(INDEX(定数マスタ!$U$6:$U$17,MONTH($B69)),1),SUMPRODUCT(MAX((定数マスタ!$X$6:$X$25<=$B69)*(定数マスタ!$Y$6:$Y$25>=$B69)*定数マスタ!$Z$6:$Z$25)))) -> 1.25 | G69: =IF($B69="","",ROUND(IF(ISNUMBER($D69),$D69,N('設定（最初に1回）'!$C$14))*N($F69),0)) -> 3750 | I69: =IF($B69="","",TEXT($B69,"m/d")&"("&$C69&")") -> 7/1(水)
B70: =IF('設定（最初に1回）'!$C$6="","",'設定（最初に1回）'!$C$6+62) -> 46205 | C70: =IF($B70="","",CHOOSE(WEEKDAY($B70),"日","月","火","水","木","金","土")) -> 木 | F70: =IF($B70="","",IF(SUMPRODUCT(MAX((定数マスタ!$X$6:$X$25<=$B70)*(定数マスタ!$Y$6:$Y$25>=$B70)*定数マスタ!$Z$6:$Z$25))=0,IFERROR(INDEX(定数マスタ!$U$6:$U$17,MONTH($B70)),1),SUMPRODUCT(MAX((定数マスタ!$X$6:$X$25<=$B70)*(定数マスタ!$Y$6:$Y$25>=$B70)*定数マスタ!$Z$6:$Z$25)))) -> 1.25 | G70: =IF($B70="","",ROUND(IF(ISNUMBER($D70),$D70,N('設定（最初に1回）'!$C$14))*N($F70),0)) -> 3750 | I70: =IF($B70="","",TEXT($B70,"m/d")&"("&$C70&")") -> 7/2(木)
B71: =IF('設定（最初に1回）'!$C$6="","",'設定（最初に1回）'!$C$6+63) -> 46206 | C71: =IF($B71="","",CHOOSE(WEEKDAY($B71),"日","月","火","水","木","金","土")) -> 金 | F71: =IF($B71="","",IF(SUMPRODUCT(MAX((定数マスタ!$X$6:$X$25<=$B71)*(定数マスタ!$Y$6:$Y$25>=$B71)*定数マスタ!$Z$6:$Z$25))=0,IFERROR(INDEX(定数マスタ!$U$6:$U$17,MONTH($B71)),1),SUMPRODUCT(MAX((定数マスタ!$X$6:$X$25<=$B71)*(定数マスタ!$Y$6:$Y$25>=$B71)*定数マスタ!$Z$6:$Z$25)))) -> 1.25 | G71: =IF($B71="","",ROUND(IF(ISNUMBER($D71),$D71,N('設定（最初に1回）'!$C$14))*N($F71),0)) -> 3750 | I71: =IF($B71="","",TEXT($B71,"m/d")&"("&$C71&")") -> 7/3(金)
B72: =IF('設定（最初に1回）'!$C$6="","",'設定（最初に1回）'!$C$6+64) -> 46207 | C72: =IF($B72="","",CHOOSE(WEEKDAY($B72),"日","月","火","水","木","金","土")) -> 土 | F72: =IF($B72="","",IF(SUMPRODUCT(MAX((定数マスタ!$X$6:$X$25<=$B72)*(定数マスタ!$Y$6:$Y$25>=$B72)*定数マスタ!$Z$6:$Z$25))=0,IFERROR(INDEX(定数マスタ!$U$6:$U$17,MONTH($B72)),1),SUMPRODUCT(MAX((定数マスタ!$X$6:$X$25<=$B72)*(定数マスタ!$Y$6:$Y$25>=$B72)*定数マスタ!$Z$6:$Z$25)))) -> 1.25 | G72: =IF($B72="","",ROUND(IF(ISNUMBER($D72),$D72,N('設定（最初に1回）'!$C$14))*N($F72),0)) -> 3750 | I72: =IF($B72="","",TEXT($B72,"m/d")&"("&$C72&")") -> 7/4(土)
B73: =IF('設定（最初に1回）'!$C$6="","",'設定（最初に1回）'!$C$6+65) -> 46208 | C73: =IF($B73="","",CHOOSE(WEEKDAY($B73),"日","月","火","水","木","金","土")) -> 日 | F73: =IF($B73="","",IF(SUMPRODUCT(MAX((定数マスタ!$X$6:$X$25<=$B73)*(定数マスタ!$Y$6:$Y$25>=$B73)*定数マスタ!$Z$6:$Z$25))=0,IFERROR(INDEX(定数マスタ!$U$6:$U$17,MONTH($B73)),1),SUMPRODUCT(MAX((定数マスタ!$X$6:$X$25<=$B73)*(定数マスタ!$Y$6:$Y$25>=$B73)*定数マスタ!$Z$6:$Z$25)))) -> 1.25 | G73: =IF($B73="","",ROUND(IF(ISNUMBER($D73),$D73,N('設定（最初に1回）'!$C$14))*N($F73),0)) -> 3750 | I73: =IF($B73="","",TEXT($B73,"m/d")&"("&$C73&")") -> 7/5(日)
B74: =IF('設定（最初に1回）'!$C$6="","",'設定（最初に1回）'!$C$6+66) -> 46209 | C74: =IF($B74="","",CHOOSE(WEEKDAY($B74),"日","月","火","水","木","金","土")) -> 月 | F74: =IF($B74="","",IF(SUMPRODUCT(MAX((定数マスタ!$X$6:$X$25<=$B74)*(定数マスタ!$Y$6:$Y$25>=$B74)*定数マスタ!$Z$6:$Z$25))=0,IFERROR(INDEX(定数マスタ!$U$6:$U$17,MONTH($B74)),1),SUMPRODUCT(MAX((定数マスタ!$X$6:$X$25<=$B74)*(定数マスタ!$Y$6:$Y$25>=$B74)*定数マスタ!$Z$6:$Z$25)))) -> 1.25 | G74: =IF($B74="","",ROUND(IF(ISNUMBER($D74),$D74,N('設定（最初に1回）'!$C$14))*N($F74),0)) -> 3750 | I74: =IF($B74="","",TEXT($B74,"m/d")&"("&$C74&")") -> 7/6(月)
B75: =IF('設定（最初に1回）'!$C$6="","",'設定（最初に1回）'!$C$6+67) -> 46210 | C75: =IF($B75="","",CHOOSE(WEEKDAY($B75),"日","月","火","水","木","金","土")) -> 火 | F75: =IF($B75="","",IF(SUMPRODUCT(MAX((定数マスタ!$X$6:$X$25<=$B75)*(定数マスタ!$Y$6:$Y$25>=$B75)*定数マスタ!$Z$6:$Z$25))=0,IFERROR(INDEX(定数マスタ!$U$6:$U$17,MONTH($B75)),1),SUMPRODUCT(MAX((定数マスタ!$X$6:$X$25<=$B75)*(定数マスタ!$Y$6:$Y$25>=$B75)*定数マスタ!$Z$6:$Z$25)))) -> 1.25 | G75: =IF($B75="","",ROUND(IF(ISNUMBER($D75),$D75,N('設定（最初に1回）'!$C$14))*N($F75),0)) -> 3750 | I75: =IF($B75="","",TEXT($B75,"m/d")&"("&$C75&")") -> 7/7(火)
B76: =IF('設定（最初に1回）'!$C$6="","",'設定（最初に1回）'!$C$6+68) -> 46211 | C76: =IF($B76="","",CHOOSE(WEEKDAY($B76),"日","月","火","水","木","金","土")) -> 水 | F76: =IF($B76="","",IF(SUMPRODUCT(MAX((定数マスタ!$X$6:$X$25<=$B76)*(定数マスタ!$Y$6:$Y$25>=$B76)*定数マスタ!$Z$6:$Z$25))=0,IFERROR(INDEX(定数マスタ!$U$6:$U$17,MONTH($B76)),1),SUMPRODUCT(MAX((定数マスタ!$X$6:$X$25<=$B76)*(定数マスタ!$Y$6:$Y$25>=$B76)*定数マスタ!$Z$6:$Z$25)))) -> 1.25 | G76: =IF($B76="","",ROUND(IF(ISNUMBER($D76),$D76,N('設定（最初に1回）'!$C$14))*N($F76),0)) -> 3750 | I76: =IF($B76="","",TEXT($B76,"m/d")&"("&$C76&")") -> 7/8(水)
B77: =IF('設定（最初に1回）'!$C$6="","",'設定（最初に1回）'!$C$6+69) -> 46212 | C77: =IF($B77="","",CHOOSE(WEEKDAY($B77),"日","月","火","水","木","金","土")) -> 木 | F77: =IF($B77="","",IF(SUMPRODUCT(MAX((定数マスタ!$X$6:$X$25<=$B77)*(定数マスタ!$Y$6:$Y$25>=$B77)*定数マスタ!$Z$6:$Z$25))=0,IFERROR(INDEX(定数マスタ!$U$6:$U$17,MONTH($B77)),1),SUMPRODUCT(MAX((定数マスタ!$X$6:$X$25<=$B77)*(定数マスタ!$Y$6:$Y$25>=$B77)*定数マスタ!$Z$6:$Z$25)))) -> 1.25 | G77: =IF($B77="","",ROUND(IF(ISNUMBER($D77),$D77,N('設定（最初に1回）'!$C$14))*N($F77),0)) -> 3750 | I77: =IF($B77="","",TEXT($B77,"m/d")&"("&$C77&")") -> 7/9(木)
B78: =IF('設定（最初に1回）'!$C$6="","",'設定（最初に1回）'!$C$6+70) -> 46213 | C78: =IF($B78="","",CHOOSE(WEEKDAY($B78),"日","月","火","水","木","金","土")) -> 金 | F78: =IF($B78="","",IF(SUMPRODUCT(MAX((定数マスタ!$X$6:$X$25<=$B78)*(定数マスタ!$Y$6:$Y$25>=$B78)*定数マスタ!$Z$6:$Z$25))=0,IFERROR(INDEX(定数マスタ!$U$6:$U$17,MONTH($B78)),1),SUMPRODUCT(MAX((定数マスタ!$X$6:$X$25<=$B78)*(定数マスタ!$Y$6:$Y$25>=$B78)*定数マスタ!$Z$6:$Z$25)))) -> 1.25 | G78: =IF($B78="","",ROUND(IF(ISNUMBER($D78),$D78,N('設定（最初に1回）'!$C$14))*N($F78),0)) -> 3750 | I78: =IF($B78="","",TEXT($B78,"m/d")&"("&$C78&")") -> 7/10(金)
B79: =IF('設定（最初に1回）'!$C$6="","",'設定（最初に1回）'!$C$6+71) -> 46214 | C79: =IF($B79="","",CHOOSE(WEEKDAY($B79),"日","月","火","水","木","金","土")) -> 土 | F79: =IF($B79="","",IF(SUMPRODUCT(MAX((定数マスタ!$X$6:$X$25<=$B79)*(定数マスタ!$Y$6:$Y$25>=$B79)*定数マスタ!$Z$6:$Z$25))=0,IFERROR(INDEX(定数マスタ!$U$6:$U$17,MONTH($B79)),1),SUMPRODUCT(MAX((定数マスタ!$X$6:$X$25<=$B79)*(定数マスタ!$Y$6:$Y$25>=$B79)*定数マスタ!$Z$6:$Z$25)))) -> 1.25 | G79: =IF($B79="","",ROUND(IF(ISNUMBER($D79),$D79,N('設定（最初に1回）'!$C$14))*N($F79),0)) -> 3750 | I79: =IF($B79="","",TEXT($B79,"m/d")&"("&$C79&")") -> 7/11(土)
B80: =IF('設定（最初に1回）'!$C$6="","",'設定（最初に1回）'!$C$6+72) -> 46215 | C80: =IF($B80="","",CHOOSE(WEEKDAY($B80),"日","月","火","水","木","金","土")) -> 日 | F80: =IF($B80="","",IF(SUMPRODUCT(MAX((定数マスタ!$X$6:$X$25<=$B80)*(定数マスタ!$Y$6:$Y$25>=$B80)*定数マスタ!$Z$6:$Z$25))=0,IFERROR(INDEX(定数マスタ!$U$6:$U$17,MONTH($B80)),1),SUMPRODUCT(MAX((定数マスタ!$X$6:$X$25<=$B80)*(定数マスタ!$Y$6:$Y$25>=$B80)*定数マスタ!$Z$6:$Z$25)))) -> 1.25 | G80: =IF($B80="","",ROUND(IF(ISNUMBER($D80),$D80,N('設定（最初に1回）'!$C$14))*N($F80),0)) -> 3750 | I80: =IF($B80="","",TEXT($B80,"m/d")&"("&$C80&")") -> 7/12(日)
B81: =IF('設定（最初に1回）'!$C$6="","",'設定（最初に1回）'!$C$6+73) -> 46216 | C81: =IF($B81="","",CHOOSE(WEEKDAY($B81),"日","月","火","水","木","金","土")) -> 月 | F81: =IF($B81="","",IF(SUMPRODUCT(MAX((定数マスタ!$X$6:$X$25<=$B81)*(定数マスタ!$Y$6:$Y$25>=$B81)*定数マスタ!$Z$6:$Z$25))=0,IFERROR(INDEX(定数マスタ!$U$6:$U$17,MONTH($B81)),1),SUMPRODUCT(MAX((定数マスタ!$X$6:$X$25<=$B81)*(定数マスタ!$Y$6:$Y$25>=$B81)*定数マスタ!$Z$6:$Z$25)))) -> 1.25 | G81: =IF($B81="","",ROUND(IF(ISNUMBER($D81),$D81,N('設定（最初に1回）'!$C$14))*N($F81),0)) -> 3750 | I81: =IF($B81="","",TEXT($B81,"m/d")&"("&$C81&")") -> 7/13(月)
B82: =IF('設定（最初に1回）'!$C$6="","",'設定（最初に1回）'!$C$6+74) -> 46217 | C82: =IF($B82="","",CHOOSE(WEEKDAY($B82),"日","月","火","水","木","金","土")) -> 火 | F82: =IF($B82="","",IF(SUMPRODUCT(MAX((定数マスタ!$X$6:$X$25<=$B82)*(定数マスタ!$Y$6:$Y$25>=$B82)*定数マスタ!$Z$6:$Z$25))=0,IFERROR(INDEX(定数マスタ!$U$6:$U$17,MONTH($B82)),1),SUMPRODUCT(MAX((定数マスタ!$X$6:$X$25<=$B82)*(定数マスタ!$Y$6:$Y$25>=$B82)*定数マスタ!$Z$6:$Z$25)))) -> 1.25 | G82: =IF($B82="","",ROUND(IF(ISNUMBER($D82),$D82,N('設定（最初に1回）'!$C$14))*N($F82),0)) -> 3750 | I82: =IF($B82="","",TEXT($B82,"m/d")&"("&$C82&")") -> 7/14(火)
B83: =IF('設定（最初に1回）'!$C$6="","",'設定（最初に1回）'!$C$6+75) -> 46218 | C83: =IF($B83="","",CHOOSE(WEEKDAY($B83),"日","月","火","水","木","金","土")) -> 水 | F83: =IF($B83="","",IF(SUMPRODUCT(MAX((定数マスタ!$X$6:$X$25<=$B83)*(定数マスタ!$Y$6:$Y$25>=$B83)*定数マスタ!$Z$6:$Z$25))=0,IFERROR(INDEX(定数マスタ!$U$6:$U$17,MONTH($B83)),1),SUMPRODUCT(MAX((定数マスタ!$X$6:$X$25<=$B83)*(定数マスタ!$Y$6:$Y$25>=$B83)*定数マスタ!$Z$6:$Z$25)))) -> 1.25 | G83: =IF($B83="","",ROUND(IF(ISNUMBER($D83),$D83,N('設定（最初に1回）'!$C$14))*N($F83),0)) -> 3750 | I83: =IF($B83="","",TEXT($B83,"m/d")&"("&$C83&")") -> 7/15(水)
B84: =IF('設定（最初に1回）'!$C$6="","",'設定（最初に1回）'!$C$6+76) -> 46219 | C84: =IF($B84="","",CHOOSE(WEEKDAY($B84),"日","月","火","水","木","金","土")) -> 木 | F84: =IF($B84="","",IF(SUMPRODUCT(MAX((定数マスタ!$X$6:$X$25<=$B84)*(定数マスタ!$Y$6:$Y$25>=$B84)*定数マスタ!$Z$6:$Z$25))=0,IFERROR(INDEX(定数マスタ!$U$6:$U$17,MONTH($B84)),1),SUMPRODUCT(MAX((定数マスタ!$X$6:$X$25<=$B84)*(定数マスタ!$Y$6:$Y$25>=$B84)*定数マスタ!$Z$6:$Z$25)))) -> 1.25 | G84: =IF($B84="","",ROUND(IF(ISNUMBER($D84),$D84,N('設定（最初に1回）'!$C$14))*N($F84),0)) -> 3750 | I84: =IF($B84="","",TEXT($B84,"m/d")&"("&$C84&")") -> 7/16(木)
B85: =IF('設定（最初に1回）'!$C$6="","",'設定（最初に1回）'!$C$6+77) -> 46220 | C85: =IF($B85="","",CHOOSE(WEEKDAY($B85),"日","月","火","水","木","金","土")) -> 金 | F85: =IF($B85="","",IF(SUMPRODUCT(MAX((定数マスタ!$X$6:$X$25<=$B85)*(定数マスタ!$Y$6:$Y$25>=$B85)*定数マスタ!$Z$6:$Z$25))=0,IFERROR(INDEX(定数マスタ!$U$6:$U$17,MONTH($B85)),1),SUMPRODUCT(MAX((定数マスタ!$X$6:$X$25<=$B85)*(定数マスタ!$Y$6:$Y$25>=$B85)*定数マスタ!$Z$6:$Z$25)))) -> 1.25 | G85: =IF($B85="","",ROUND(IF(ISNUMBER($D85),$D85,N('設定（最初に1回）'!$C$14))*N($F85),0)) -> 3750 | I85: =IF($B85="","",TEXT($B85,"m/d")&"("&$C85&")") -> 7/17(金)
B86: =IF('設定（最初に1回）'!$C$6="","",'設定（最初に1回）'!$C$6+78) -> 46221 | C86: =IF($B86="","",CHOOSE(WEEKDAY($B86),"日","月","火","水","木","金","土")) -> 土 | F86: =IF($B86="","",IF(SUMPRODUCT(MAX((定数マスタ!$X$6:$X$25<=$B86)*(定数マスタ!$Y$6:$Y$25>=$B86)*定数マスタ!$Z$6:$Z$25))=0,IFERROR(INDEX(定数マスタ!$U$6:$U$17,MONTH($B86)),1),SUMPRODUCT(MAX((定数マスタ!$X$6:$X$25<=$B86)*(定数マスタ!$Y$6:$Y$25>=$B86)*定数マスタ!$Z$6:$Z$25)))) -> 1.25 | G86: =IF($B86="","",ROUND(IF(ISNUMBER($D86),$D86,N('設定（最初に1回）'!$C$14))*N($F86),0)) -> 3750 | I86: =IF($B86="","",TEXT($B86,"m/d")&"("&$C86&")") -> 7/18(土)
B87: =IF('設定（最初に1回）'!$C$6="","",'設定（最初に1回）'!$C$6+79) -> 46222 | C87: =IF($B87="","",CHOOSE(WEEKDAY($B87),"日","月","火","水","木","金","土")) -> 日 | F87: =IF($B87="","",IF(SUMPRODUCT(MAX((定数マスタ!$X$6:$X$25<=$B87)*(定数マスタ!$Y$6:$Y$25>=$B87)*定数マスタ!$Z$6:$Z$25))=0,IFERROR(INDEX(定数マスタ!$U$6:$U$17,MONTH($B87)),1),SUMPRODUCT(MAX((定数マスタ!$X$6:$X$25<=$B87)*(定数マスタ!$Y$6:$Y$25>=$B87)*定数マスタ!$Z$6:$Z$25)))) -> 1.25 | G87: =IF($B87="","",ROUND(IF(ISNUMBER($D87),$D87,N('設定（最初に1回）'!$C$14))*N($F87),0)) -> 3750 | I87: =IF($B87="","",TEXT($B87,"m/d")&"("&$C87&")") -> 7/19(日)
B88: =IF('設定（最初に1回）'!$C$6="","",'設定（最初に1回）'!$C$6+80) -> 46223 | C88: =IF($B88="","",CHOOSE(WEEKDAY($B88),"日","月","火","水","木","金","土")) -> 月 | F88: =IF($B88="","",IF(SUMPRODUCT(MAX((定数マスタ!$X$6:$X$25<=$B88)*(定数マスタ!$Y$6:$Y$25>=$B88)*定数マスタ!$Z$6:$Z$25))=0,IFERROR(INDEX(定数マスタ!$U$6:$U$17,MONTH($B88)),1),SUMPRODUCT(MAX((定数マスタ!$X$6:$X$25<=$B88)*(定数マスタ!$Y$6:$Y$25>=$B88)*定数マスタ!$Z$6:$Z$25)))) -> 1.25 | G88: =IF($B88="","",ROUND(IF(ISNUMBER($D88),$D88,N('設定（最初に1回）'!$C$14))*N($F88),0)) -> 3750 | I88: =IF($B88="","",TEXT($B88,"m/d")&"("&$C88&")") -> 7/20(月)
B89: =IF('設定（最初に1回）'!$C$6="","",'設定（最初に1回）'!$C$6+81) -> 46224 | C89: =IF($B89="","",CHOOSE(WEEKDAY($B89),"日","月","火","水","木","金","土")) -> 火 | F89: =IF($B89="","",IF(SUMPRODUCT(MAX((定数マスタ!$X$6:$X$25<=$B89)*(定数マスタ!$Y$6:$Y$25>=$B89)*定数マスタ!$Z$6:$Z$25))=0,IFERROR(INDEX(定数マスタ!$U$6:$U$17,MONTH($B89)),1),SUMPRODUCT(MAX((定数マスタ!$X$6:$X$25<=$B89)*(定数マスタ!$Y$6:$Y$25>=$B89)*定数マスタ!$Z$6:$Z$25)))) -> 1.25 | G89: =IF($B89="","",ROUND(IF(ISNUMBER($D89),$D89,N('設定（最初に1回）'!$C$14))*N($F89),0)) -> 3750 | I89: =IF($B89="","",TEXT($B89,"m/d")&"("&$C89&")") -> 7/21(火)
B90: =IF('設定（最初に1回）'!$C$6="","",'設定（最初に1回）'!$C$6+82) -> 46225 | C90: =IF($B90="","",CHOOSE(WEEKDAY($B90),"日","月","火","水","木","金","土")) -> 水 | F90: =IF($B90="","",IF(SUMPRODUCT(MAX((定数マスタ!$X$6:$X$25<=$B90)*(定数マスタ!$Y$6:$Y$25>=$B90)*定数マスタ!$Z$6:$Z$25))=0,IFERROR(INDEX(定数マスタ!$U$6:$U$17,MONTH($B90)),1),SUMPRODUCT(MAX((定数マスタ!$X$6:$X$25<=$B90)*(定数マスタ!$Y$6:$Y$25>=$B90)*定数マスタ!$Z$6:$Z$25)))) -> 1.25 | G90: =IF($B90="","",ROUND(IF(ISNUMBER($D90),$D90,N('設定（最初に1回）'!$C$14))*N($F90),0)) -> 3750 | I90: =IF($B90="","",TEXT($B90,"m/d")&"("&$C90&")") -> 7/22(水)
B91: =IF('設定（最初に1回）'!$C$6="","",'設定（最初に1回）'!$C$6+83) -> 46226 | C91: =IF($B91="","",CHOOSE(WEEKDAY($B91),"日","月","火","水","木","金","土")) -> 木 | F91: =IF($B91="","",IF(SUMPRODUCT(MAX((定数マスタ!$X$6:$X$25<=$B91)*(定数マスタ!$Y$6:$Y$25>=$B91)*定数マスタ!$Z$6:$Z$25))=0,IFERROR(INDEX(定数マスタ!$U$6:$U$17,MONTH($B91)),1),SUMPRODUCT(MAX((定数マスタ!$X$6:$X$25<=$B91)*(定数マスタ!$Y$6:$Y$25>=$B91)*定数マスタ!$Z$6:$Z$25)))) -> 1.25 | G91: =IF($B91="","",ROUND(IF(ISNUMBER($D91),$D91,N('設定（最初に1回）'!$C$14))*N($F91),0)) -> 3750 | I91: =IF($B91="","",TEXT($B91,"m/d")&"("&$C91&")") -> 7/23(木)
B92: =IF('設定（最初に1回）'!$C$6="","",'設定（最初に1回）'!$C$6+84) -> 46227 | C92: =IF($B92="","",CHOOSE(WEEKDAY($B92),"日","月","火","水","木","金","土")) -> 金 | F92: =IF($B92="","",IF(SUMPRODUCT(MAX((定数マスタ!$X$6:$X$25<=$B92)*(定数マスタ!$Y$6:$Y$25>=$B92)*定数マスタ!$Z$6:$Z$25))=0,IFERROR(INDEX(定数マスタ!$U$6:$U$17,MONTH($B92)),1),SUMPRODUCT(MAX((定数マスタ!$X$6:$X$25<=$B92)*(定数マスタ!$Y$6:$Y$25>=$B92)*定数マスタ!$Z$6:$Z$25)))) -> 1.25 | G92: =IF($B92="","",ROUND(IF(ISNUMBER($D92),$D92,N('設定（最初に1回）'!$C$14))*N($F92),0)) -> 3750 | I92: =IF($B92="","",TEXT($B92,"m/d")&"("&$C92&")") -> 7/24(金)
B93: =IF('設定（最初に1回）'!$C$6="","",'設定（最初に1回）'!$C$6+85) -> 46228 | C93: =IF($B93="","",CHOOSE(WEEKDAY($B93),"日","月","火","水","木","金","土")) -> 土 | F93: =IF($B93="","",IF(SUMPRODUCT(MAX((定数マスタ!$X$6:$X$25<=$B93)*(定数マスタ!$Y$6:$Y$25>=$B93)*定数マスタ!$Z$6:$Z$25))=0,IFERROR(INDEX(定数マスタ!$U$6:$U$17,MONTH($B93)),1),SUMPRODUCT(MAX((定数マスタ!$X$6:$X$25<=$B93)*(定数マスタ!$Y$6:$Y$25>=$B93)*定数マスタ!$Z$6:$Z$25)))) -> 1.25 | G93: =IF($B93="","",ROUND(IF(ISNUMBER($D93),$D93,N('設定（最初に1回）'!$C$14))*N($F93),0)) -> 3750 | I93: =IF($B93="","",TEXT($B93,"m/d")&"("&$C93&")") -> 7/25(土)
B94: =IF('設定（最初に1回）'!$C$6="","",'設定（最初に1回）'!$C$6+86) -> 46229 | C94: =IF($B94="","",CHOOSE(WEEKDAY($B94),"日","月","火","水","木","金","土")) -> 日 | F94: =IF($B94="","",IF(SUMPRODUCT(MAX((定数マスタ!$X$6:$X$25<=$B94)*(定数マスタ!$Y$6:$Y$25>=$B94)*定数マスタ!$Z$6:$Z$25))=0,IFERROR(INDEX(定数マスタ!$U$6:$U$17,MONTH($B94)),1),SUMPRODUCT(MAX((定数マスタ!$X$6:$X$25<=$B94)*(定数マスタ!$Y$6:$Y$25>=$B94)*定数マスタ!$Z$6:$Z$25)))) -> 1.25 | G94: =IF($B94="","",ROUND(IF(ISNUMBER($D94),$D94,N('設定（最初に1回）'!$C$14))*N($F94),0)) -> 3750 | I94: =IF($B94="","",TEXT($B94,"m/d")&"("&$C94&")") -> 7/26(日)
B95: =IF('設定（最初に1回）'!$C$6="","",'設定（最初に1回）'!$C$6+87) -> 46230 | C95: =IF($B95="","",CHOOSE(WEEKDAY($B95),"日","月","火","水","木","金","土")) -> 月 | F95: =IF($B95="","",IF(SUMPRODUCT(MAX((定数マスタ!$X$6:$X$25<=$B95)*(定数マスタ!$Y$6:$Y$25>=$B95)*定数マスタ!$Z$6:$Z$25))=0,IFERROR(INDEX(定数マスタ!$U$6:$U$17,MONTH($B95)),1),SUMPRODUCT(MAX((定数マスタ!$X$6:$X$25<=$B95)*(定数マスタ!$Y$6:$Y$25>=$B95)*定数マスタ!$Z$6:$Z$25)))) -> 1.25 | G95: =IF($B95="","",ROUND(IF(ISNUMBER($D95),$D95,N('設定（最初に1回）'!$C$14))*N($F95),0)) -> 3750 | I95: =IF($B95="","",TEXT($B95,"m/d")&"("&$C95&")") -> 7/27(月)
B96: =IF('設定（最初に1回）'!$C$6="","",'設定（最初に1回）'!$C$6+88) -> 46231 | C96: =IF($B96="","",CHOOSE(WEEKDAY($B96),"日","月","火","水","木","金","土")) -> 火 | F96: =IF($B96="","",IF(SUMPRODUCT(MAX((定数マスタ!$X$6:$X$25<=$B96)*(定数マスタ!$Y$6:$Y$25>=$B96)*定数マスタ!$Z$6:$Z$25))=0,IFERROR(INDEX(定数マスタ!$U$6:$U$17,MONTH($B96)),1),SUMPRODUCT(MAX((定数マスタ!$X$6:$X$25<=$B96)*(定数マスタ!$Y$6:$Y$25>=$B96)*定数マスタ!$Z$6:$Z$25)))) -> 1.25 | G96: =IF($B96="","",ROUND(IF(ISNUMBER($D96),$D96,N('設定（最初に1回）'!$C$14))*N($F96),0)) -> 3750 | I96: =IF($B96="","",TEXT($B96,"m/d")&"("&$C96&")") -> 7/28(火)
B97: =IF('設定（最初に1回）'!$C$6="","",'設定（最初に1回）'!$C$6+89) -> 46232 | C97: =IF($B97="","",CHOOSE(WEEKDAY($B97),"日","月","火","水","木","金","土")) -> 水 | F97: =IF($B97="","",IF(SUMPRODUCT(MAX((定数マスタ!$X$6:$X$25<=$B97)*(定数マスタ!$Y$6:$Y$25>=$B97)*定数マスタ!$Z$6:$Z$25))=0,IFERROR(INDEX(定数マスタ!$U$6:$U$17,MONTH($B97)),1),SUMPRODUCT(MAX((定数マスタ!$X$6:$X$25<=$B97)*(定数マスタ!$Y$6:$Y$25>=$B97)*定数マスタ!$Z$6:$Z$25)))) -> 1.25 | G97: =IF($B97="","",ROUND(IF(ISNUMBER($D97),$D97,N('設定（最初に1回）'!$C$14))*N($F97),0)) -> 3750 | I97: =IF($B97="","",TEXT($B97,"m/d")&"("&$C97&")") -> 7/29(水)

Sheet ダッシュボード
B2: ダッシュボード
B3: =IF('設定（最初に1回）'!$C$4="","設定シートで対象劇場を選んでください。",'設定（最初に1回）'!$C$4&" "&'設定（最初に1回）'!$C$5&" ／ 基準日 "&TEXT('設定（最初に1回）'!$C$6,"yyyy/m/d")&" ／ 算出基準 "&'設定（最初に1回）'!$C$9) -> 0761 新宿 ／ 基準日 2026/5/1 ／ 算出基準 実績消費
B5: 欠品リスク | I5: 要発注 | P5: 在庫に余裕 | W5: 推奨発注額（税抜）
B6: =COUNTIF(②発注数を決める!$G$10:$G$409,"今日が期限") -> 36 | I6: =COUNTIF(②発注数を決める!$G$10:$G$409,"要発注") -> 9 | P6: =COUNTIF(②発注数を決める!$G$10:$G$409,"余裕") -> 88 | W6: =SUM(発注計算!$AC$6:$AC$405) -> 1493771.8
B9: 今日発注しないと間に合わない | I9: 発注サイクル内に切れる | P9: しばらく発注不要 | W9: ="在庫金額 "&TEXT(SUM(発注計算!$AA$6:$AA$405),"¥#,##0") -> 在庫金額 ¥12,601,415
B11: 在庫状況の内訳 | M11: 在庫日数の分布
B12: 1マス＝全体の1%。100マスで取扱商品全体を表しています。
AE13: 欠品リスク% | AF13: =IFERROR(COUNTIF(②発注数を決める!$G$10:$G$409,"今日が期限")/$AF$18*100,0) -> 26.470588
B14: 1 | C14: 2 | D14: 3 | E14: 4 | F14: 5 | G14: 6 | H14: 7 | I14: 8 | J14: 9 | K14: 10 | AE14: ＋要発注% | AF14: =$AF$13+IFERROR(COUNTIF(②発注数を決める!$G$10:$G$409,"要発注")/$AF$18*100,0) -> 33.088235
B15: 11 | C15: 12 | D15: 13 | E15: 14 | F15: 15 | G15: 16 | H15: 17 | I15: 18 | J15: 19 | K15: 20 | AE15: ＋余裕% | AF15: =$AF$14+IFERROR(COUNTIF(②発注数を決める!$G$10:$G$409,"余裕")/$AF$18*100,0) -> 97.794118
B16: 21 | C16: 22 | D16: 23 | E16: 24 | F16: 25 | G16: 26 | H16: 27 | I16: 28 | J16: 29 | K16: 30
B17: 31 | C17: 32 | D17: 33 | E17: 34 | F17: 35 | G17: 36 | H17: 37 | I17: 38 | J17: 39 | K17: 40
B18: 41 | C18: 42 | D18: 43 | E18: 44 | F18: 45 | G18: 46 | H18: 47 | I18: 48 | J18: 49 | K18: 50 | AE18: 取扱商品数 | AF18: =COUNTIF(②発注数を決める!$G$10:$G$409,"?*") -> 136
B19: 51 | C19: 52 | D19: 53 | E19: 54 | F19: 55 | G19: 56 | H19: 57 | I19: 58 | J19: 59 | K19: 60
B20: 61 | C20: 62 | D20: 63 | E20: 64 | F20: 65 | G20: 66 | H20: 67 | I20: 68 | J20: 69 | K20: 70
B21: 71 | C21: 72 | D21: 73 | E21: 74 | F21: 75 | G21: 76 | H21: 77 | I21: 78 | J21: 79 | K21: 80 | AE21: 在庫日数 | AF21: 品目数
B22: 81 | C22: 82 | D22: 83 | E22: 84 | F22: 85 | G22: 86 | H22: 87 | I22: 88 | J22: 89 | K22: 90 | AE22: 14日以上 | AF22: =COUNTIFS(②発注数を決める!$E$10:$E$409,">14") -> 80
B23: 91 | C23: 92 | D23: 93 | E23: 94 | F23: 95 | G23: 96 | H23: 97 | I23: 98 | J23: 99 | K23: 100 | AE23: 7〜14日 | AF23: =COUNTIFS(②発注数を決める!$E$10:$E$409,">7",②発注数を決める!$E$10:$E$409,"<=14") -> 13
AE24: 3〜7日 | AF24: =COUNTIFS(②発注数を決める!$E$10:$E$409,">3",②発注数を決める!$E$10:$E$409,"<=7") -> 6
C25: 欠品リスク | F25: 要発注 | I25: 余裕 | L25: データなし | AE25: 1〜3日 | AF25: =COUNTIFS(②発注数を決める!$E$10:$E$409,">1",②発注数を決める!$E$10:$E$409,"<=3") -> 12
AE26: 0〜1日 | AF26: =COUNTIFS(②発注数を決める!$E$10:$E$409,">0",②発注数を決める!$E$10:$E$409,"<=1") -> 1
B27: 商品分類 × 状態 | S27: 仕入先別 推奨発注額 | AE27: 切れている | AF27: =COUNTIFS(②発注数を決める!$E$10:$E$409,"<=0") -> 21
B28: 商品分類 | H28: 今日が期限 | J28: 要発注 | L28: 余裕 | N28: 在庫金額
B29: アルコール | H29: =COUNTIFS(②発注数を決める!$D$10:$D$409,$B29,②発注数を決める!$G$10:$G$409,"今日が期限") -> 5 | J29: =COUNTIFS(②発注数を決める!$D$10:$D$409,$B29,②発注数を決める!$G$10:$G$409,"要発注") -> 1 | L29: =COUNTIFS(②発注数を決める!$D$10:$D$409,$B29,②発注数を決める!$G$10:$G$409,"余裕") -> 3 | N29: =SUMIF(発注計算!$E$6:$E$405,$B29,発注計算!$AA$6:$AA$405) -> 122902
B30: コールド | H30: =COUNTIFS(②発注数を決める!$D$10:$D$409,$B30,②発注数を決める!$G$10:$G$409,"今日が期限") -> 5 | J30: =COUNTIFS(②発注数を決める!$D$10:$D$409,$B30,②発注数を決める!$G$10:$G$409,"要発注") -> 0 | L30: =COUNTIFS(②発注数を決める!$D$10:$D$409,$B30,②発注数を決める!$G$10:$G$409,"余裕") -> 6 | N30: =SUMIF(発注計算!$E$6:$E$405,$B30,発注計算!$AA$6:$AA$405) -> 2980478
B31: コーヒー | H31: =COUNTIFS(②発注数を決める!$D$10:$D$409,$B31,②発注数を決める!$G$10:$G$409,"今日が期限") -> 0 | J31: =COUNTIFS(②発注数を決める!$D$10:$D$409,$B31,②発注数を決める!$G$10:$G$409,"要発注") -> 1 | L31: =COUNTIFS(②発注数を決める!$D$10:$D$409,$B31,②発注数を決める!$G$10:$G$409,"余裕") -> 1 | N31: =SUMIF(発注計算!$E$6:$E$405,$B31,発注計算!$AA$6:$AA$405) -> 570800.8 | AE31: 仕入先 | AF31: 推奨発注額
B32: ホット | H32: =COUNTIFS(②発注数を決める!$D$10:$D$409,$B32,②発注数を決める!$G$10:$G$409,"今日が期限") -> 0 | J32: =COUNTIFS(②発注数を決める!$D$10:$D$409,$B32,②発注数を決める!$G$10:$G$409,"要発注") -> 0 | L32: =COUNTIFS(②発注数を決める!$D$10:$D$409,$B32,②発注数を決める!$G$10:$G$409,"余裕") -> 3 | N32: =SUMIF(発注計算!$E$6:$E$405,$B32,発注計算!$AA$6:$AA$405) -> 300371 | AE32: オザックス株式会社 | AF32: =SUMIF(発注計算!$F$6:$F$405,$AE$32,発注計算!$AC$6:$AC$405) -> 1239046.6
B33: その他ドリンク | H33: =COUNTIFS(②発注数を決める!$D$10:$D$409,$B33,②発注数を決める!$G$10:$G$409,"今日が期限") -> 2 | J33: =COUNTIFS(②発注数を決める!$D$10:$D$409,$B33,②発注数を決める!$G$10:$G$409,"要発注") -> 0 | L33: =COUNTIFS(②発注数を決める!$D$10:$D$409,$B33,②発注数を決める!$G$10:$G$409,"余裕") -> 8 | N33: =SUMIF(発注計算!$E$6:$E$405,$B33,発注計算!$AA$6:$AA$405) -> 713710 | AE33: 株式会社 カクヤス | AF33: =SUMIF(発注計算!$F$6:$F$405,$AE$33,発注計算!$AC$6:$AC$405) -> 233016
B34: ポップコーン | H34: =COUNTIFS(②発注数を決める!$D$10:$D$409,$B34,②発注数を決める!$G$10:$G$409,"今日が期限") -> 3 | J34: =COUNTIFS(②発注数を決める!$D$10:$D$409,$B34,②発注数を決める!$G$10:$G$409,"要発注") -> 1 | L34: =COUNTIFS(②発注数を決める!$D$10:$D$409,$B34,②発注数を決める!$G$10:$G$409,"余裕") -> 9 | N34: =SUMIF(発注計算!$E$6:$E$405,$B34,発注計算!$AA$6:$AA$405) -> 3969554 | AE34: エパックス（株） | AF34: =SUMIF(発注計算!$F$6:$F$405,$AE$34,発注計算!$AC$6:$AC$405) -> 7950
B35: ホットドッグ | H35: =COUNTIFS(②発注数を決める!$D$10:$D$409,$B35,②発注数を決める!$G$10:$G$409,"今日が期限") -> 1 | J35: =COUNTIFS(②発注数を決める!$D$10:$D$409,$B35,②発注数を決める!$G$10:$G$409,"要発注") -> 0 | L35: =COUNTIFS(②発注数を決める!$D$10:$D$409,$B35,②発注数を決める!$G$10:$G$409,"余裕") -> 3 | N35: =SUMIF(発注計算!$E$6:$E$405,$B35,発注計算!$AA$6:$AA$405) -> 327082 | AE35: 松竹株式会社（コンセ） | AF35: =SUMIF(発注計算!$F$6:$F$405,$AE$35,発注計算!$AC$6:$AC$405) -> 1182
B36: 軽食系フード | H36: =COUNTIFS(②発注数を決める!$D$10:$D$409,$B36,②発注数を決める!$G$10:$G$409,"今日が期限") -> 0 | J36: =COUNTIFS(②発注数を決める!$D$10:$D$409,$B36,②発注数を決める!$G$10:$G$409,"要発注") -> 0 | L36: =COUNTIFS(②発注数を決める!$D$10:$D$409,$B36,②発注数を決める!$G$10:$G$409,"余裕") -> 3 | N36: =SUMIF(発注計算!$E$6:$E$405,$B36,発注計算!$AA$6:$AA$405) -> 210032.75 | AE36: 株式会社ムービック【コンセ】 | AF36: =SUMIF(発注計算!$F$6:$F$405,$AE$36,発注計算!$AC$6:$AC$405) -> 3750
B37: 調理系スイーツ | H37: =COUNTIFS(②発注数を決める!$D$10:$D$409,$B37,②発注数を決める!$G$10:$G$409,"今日が期限") -> 2 | J37: =COUNTIFS(②発注数を決める!$D$10:$D$409,$B37,②発注数を決める!$G$10:$G$409,"要発注") -> 0 | L37: =COUNTIFS(②発注数を決める!$D$10:$D$409,$B37,②発注数を決める!$G$10:$G$409,"余裕") -> 10 | N37: =SUMIF(発注計算!$E$6:$E$405,$B37,発注計算!$AA$6:$AA$405) -> 376908 | AE37: 東映ジョイ（コンセ） | AF37: =SUMIF(発注計算!$F$6:$F$405,$AE$37,発注計算!$AC$6:$AC$405) -> 5250
B38: その他フード | H38: =COUNTIFS(②発注数を決める!$D$10:$D$409,$B38,②発注数を決める!$G$10:$G$409,"今日が期限") -> 1 | J38: =COUNTIFS(②発注数を決める!$D$10:$D$409,$B38,②発注数を決める!$G$10:$G$409,"要発注") -> 0 | L38: =COUNTIFS(②発注数を決める!$D$10:$D$409,$B38,②発注数を決める!$G$10:$G$409,"余裕") -> 1 | N38: =SUMIF(発注計算!$E$6:$E$405,$B38,発注計算!$AA$6:$AA$405) -> 98664 | AE38: ㈱トップス | AF38: =SUMIF(発注計算!$F$6:$F$405,$AE$38,発注計算!$AC$6:$AC$405) -> 1800
B39: フード調味料 | H39: =COUNTIFS(②発注数を決める!$D$10:$D$409,$B39,②発注数を決める!$G$10:$G$409,"今日が期限") -> 0 | J39: =COUNTIFS(②発注数を決める!$D$10:$D$409,$B39,②発注数を決める!$G$10:$G$409,"要発注") -> 0 | L39: =COUNTIFS(②発注数を決める!$D$10:$D$409,$B39,②発注数を決める!$G$10:$G$409,"余裕") -> 4 | N39: =SUMIF(発注計算!$E$6:$E$405,$B39,発注計算!$AA$6:$AA$405) -> 72959 | AE39: ㈱そごう・西武 | AF39: =SUMIF(発注計算!$F$6:$F$405,$AE$39,発注計算!$AC$6:$AC$405) -> 680
B40: ＳＥＴ作品コンボ | H40: =COUNTIFS(②発注数を決める!$D$10:$D$409,$B40,②発注数を決める!$G$10:$G$409,"今日が期限") -> 5 | J40: =COUNTIFS(②発注数を決める!$D$10:$D$409,$B40,②発注数を決める!$G$10:$G$409,"要発注") -> 2 | L40: =COUNTIFS(②発注数を決める!$D$10:$D$409,$B40,②発注数を決める!$G$10:$G$409,"余裕") -> 5 | N40: =SUMIF(発注計算!$E$6:$E$405,$B40,発注計算!$AA$6:$AA$405) -> 440919 | AE40: 本社 番組編成部 マーケティング室 | AF40: =SUMIF(発注計算!$F$6:$F$405,$AE$40,発注計算!$AC$6:$AC$405) -> 1097.2
B41: コンセ包材 | H41: =COUNTIFS(②発注数を決める!$D$10:$D$409,$B41,②発注数を決める!$G$10:$G$409,"今日が期限") -> 12 | J41: =COUNTIFS(②発注数を決める!$D$10:$D$409,$B41,②発注数を決める!$G$10:$G$409,"要発注") -> 4 | L41: =COUNTIFS(②発注数を決める!$D$10:$D$409,$B41,②発注数を決める!$G$10:$G$409,"余裕") -> 32 | N41: =SUMIF(発注計算!$E$6:$E$405,$B41,発注計算!$AA$6:$AA$405) -> 2417034.1
B44: 今後14日の入荷予定（発注済で未入荷のもの）
B45: 納品予定日ごとの金額です。色が濃い日ほど入荷が集中しています。
B46: =IF('設定（最初に1回）'!$C$6="","",'設定（最初に1回）'!$C$6+0) -> 46143 | D46: =IF('設定（最初に1回）'!$C$6="","",'設定（最初に1回）'!$C$6+1) -> 46144 | F46: =IF('設定（最初に1回）'!$C$6="","",'設定（最初に1回）'!$C$6+2) -> 46145 | H46: =IF('設定（最初に1回）'!$C$6="","",'設定（最初に1回）'!$C$6+3) -> 46146 | J46: =IF('設定（最初に1回）'!$C$6="","",'設定（最初に1回）'!$C$6+4) -> 46147 | L46: =IF('設定（最初に1回）'!$C$6="","",'設定（最初に1回）'!$C$6+5) -> 46148 | N46: =IF('設定（最初に1回）'!$C$6="","",'設定（最初に1回）'!$C$6+6) -> 46149 | P46: =IF('設定（最初に1回）'!$C$6="","",'設定（最初に1回）'!$C$6+7) -> 46150 | R46: =IF('設定（最初に1回）'!$C$6="","",'設定（最初に1回）'!$C$6+8) -> 46151 | T46: =IF('設定（最初に1回）'!$C$6="","",'設定（最初に1回）'!$C$6+9) -> 46152 | V46: =IF('設定（最初に1回）'!$C$6="","",'設定（最初に1回）'!$C$6+10) -> 46153 | X46: =IF('設定（最初に1回）'!$C$6="","",'設定（最初に1回）'!$C$6+11) -> 46154 | Z46: =IF('設定（最初に1回）'!$C$6="","",'設定（最初に1回）'!$C$6+12) -> 46155 | AB46: =IF('設定（最初に1回）'!$C$6="","",'設定（最初に1回）'!$C$6+13) -> 46156
B47: =IF('設定（最初に1回）'!$C$6="",0,SUMIFS(発注管理!$N$6:$N$1005,発注管理!$C$6:$C$1005,'設定（最初に1回）'!$C$4,発注管理!$P$6:$P$1005,'設定（最初に1回）'!$C$6+0,発注管理!$Q$6:$Q$1005,"発注済")) -> 0 | D47: =IF('設定（最初に1回）'!$C$6="",0,SUMIFS(発注管理!$N$6:$N$1005,発注管理!$C$6:$C$1005,'設定（最初に1回）'!$C$4,発注管理!$P$6:$P$1005,'設定（最初に1回）'!$C$6+1,発注管理!$Q$6:$Q$1005,"発注済")) -> 0 | F47: =IF('設定（最初に1回）'!$C$6="",0,SUMIFS(発注管理!$N$6:$N$1005,発注管理!$C$6:$C$1005,'設定（最初に1回）'!$C$4,発注管理!$P$6:$P$1005,'設定（最初に1回）'!$C$6+2,発注管理!$Q$6:$Q$1005,"発注済")) -> 0 | H47: =IF('設定（最初に1回）'!$C$6="",0,SUMIFS(発注管理!$N$6:$N$1005,発注管理!$C$6:$C$1005,'設定（最初に1回）'!$C$4,発注管理!$P$6:$P$1005,'設定（最初に1回）'!$C$6+3,発注管理!$Q$6:$Q$1005,"発注済")) -> 13084 | J47: =IF('設定（最初に1回）'!$C$6="",0,SUMIFS(発注管理!$N$6:$N$1005,発注管理!$C$6:$C$1005,'設定（最初に1回）'!$C$4,発注管理!$P$6:$P$1005,'設定（最初に1回）'!$C$6+4,発注管理!$Q$6:$Q$1005,"発注済")) -> 0 | L47: =IF('設定（最初に1回）'!$C$6="",0,SUMIFS(発注管理!$N$6:$N$1005,発注管理!$C$6:$C$1005,'設定（最初に1回）'!$C$4,発注管理!$P$6:$P$1005,'設定（最初に1回）'!$C$6+5,発注管理!$Q$6:$Q$1005,"発注済")) -> 0 | N47: =IF('設定（最初に1回）'!$C$6="",0,SUMIFS(発注管理!$N$6:$N$1005,発注管理!$C$6:$C$1005,'設定（最初に1回）'!$C$4,発注管理!$P$6:$P$1005,'設定（最初に1回）'!$C$6+6,発注管理!$Q$6:$Q$1005,"発注済")) -> 0 | P47: =IF('設定（最初に1回）'!$C$6="",0,SUMIFS(発注管理!$N$6:$N$1005,発注管理!$C$6:$C$1005,'設定（最初に1回）'!$C$4,発注管理!$P$6:$P$1005,'設定（最初に1回）'!$C$6+7,発注管理!$Q$6:$Q$1005,"発注済")) -> 0 | R47: =IF('設定（最初に1回）'!$C$6="",0,SUMIFS(発注管理!$N$6:$N$1005,発注管理!$C$6:$C$1005,'設定（最初に1回）'!$C$4,発注管理!$P$6:$P$1005,'設定（最初に1回）'!$C$6+8,発注管理!$Q$6:$Q$1005,"発注済")) -> 0 | T47: =IF('設定（最初に1回）'!$C$6="",0,SUMIFS(発注管理!$N$6:$N$1005,発注管理!$C$6:$C$1005,'設定（最初に1回）'!$C$4,発注管理!$P$6:$P$1005,'設定（最初に1回）'!$C$6+9,発注管理!$Q$6:$Q$1005,"発注済")) -> 0 | V47: =IF('設定（最初に1回）'!$C$6="",0,SUMIFS(発注管理!$N$6:$N$1005,発注管理!$C$6:$C$1005,'設定（最初に1回）'!$C$4,発注管理!$P$6:$P$1005,'設定（最初に1回）'!$C$6+10,発注管理!$Q$6:$Q$1005,"発注済")) -> 0 | X47: =IF('設定（最初に1回）'!$C$6="",0,SUMIFS(発注管理!$N$6:$N$1005,発注管理!$C$6:$C$1005,'設定（最初に1回）'!$C$4,発注管理!$P$6:$P$1005,'設定（最初に1回）'!$C$6+11,発注管理!$Q$6:$Q$1005,"発注済")) -> 0 | Z47: =IF('設定（最初に1回）'!$C$6="",0,SUMIFS(発注管理!$N$6:$N$1005,発注管理!$C$6:$C$1005,'設定（最初に1回）'!$C$4,発注管理!$P$6:$P$1005,'設定（最初に1回）'!$C$6+12,発注管理!$Q$6:$Q$1005,"発注済")) -> 0 | AB47: =IF('設定（最初に1回）'!$C$6="",0,SUMIFS(発注管理!$N$6:$N$1005,発注管理!$C$6:$C$1005,'設定（最初に1回）'!$C$4,発注管理!$P$6:$P$1005,'設定（最初に1回）'!$C$6+13,発注管理!$Q$6:$Q$1005,"発注済")) -> 0
B50: 今後14日の動員予測 | T50: 商品の入れ替わり
B51: 動員計画シートの数字です。山の来る日に在庫が持つかを見てください。 | T51: 2つの在庫CSVを突き合わせた結果です。発注漏れの目印になります。
T52: 新商品 | Y52: =COUNTIF(発注計算!$AB$6:$AB$405,"*新商品*") -> 2
T53: 当日CSVにあり、2ヶ月前CSVに無い
T54: 終売候補 | Y54: =COUNTIF(発注計算!$AB$6:$AB$405,"*終売候補*") -> 2
T55: 2ヶ月前CSVにあり、当日CSVに無い
T56: マスタ未登録 | Y56: =COUNTIF(発注計算!$AB$6:$AB$405,"*マスタ未登録*") -> 4
T57: L/T・ロット・PI値が既定値のまま
T58: 在庫マイナス | Y58: =COUNTIF(発注計算!$AB$6:$AB$405,"*在庫マイナス*") -> 7
T59: 納品の未計上などデータ側のずれ
T60: PI値未設定 | Y60: =COUNTIF(発注計算!$AB$6:$AB$405,"*PI値未設定*") -> 0
T61: PI値予測を使うなら商品マスタに登録が要る
B62: ※ 数字は「発注計算」シートの推奨発注数にもとづく金額です（税抜）。
B63: ※ グラフの元データは AE 列以降（非表示）にあります。商品分類や仕入先が増えたらそこに追記してください。

Sheet 発注管理
B2: 発注管理
B3: 発注と入荷を記録します。入荷済みの数量は期間納品数として、未入荷分は発注残として使われます。
B4: 自動 | C4: 入力 | D4: 自動 | E4: 入力 | F4: 入力 | G4: 自動 | H4: 自動 | I4: 自動 | J4: 自動 | K4: 入力 | L4: 自動 | M4: 自動 | N4: 自動 | O4: 自動 | P4: 自動 | Q4: 選択 | R4: 入力 | S4: 自動 | T4: 入力 | U4: 入力
B5: 発注No | C5: 劇場コード | D5: 劇場名 | E5: 発注日 | F5: 商品コード | G5: 商品名 | H5: 支払先名 | I5: 入数 | J5: 推奨発注数(ケース) | K5: 実発注数(ケース) | L5: 発注数量(バラ) | M5: 税抜単価 | N5: 発注金額 | O5: L/T日数 | P5: 納品予定日 | Q5: 発注状況 | R5: 入荷日 | S5: 入荷数量(バラ) | T5: 担当者 | U5: 備考
B6: =IF(OR($E6="",$F6=""),"","PO-"&TEXT($E6,"yyyymmdd")&"-"&TEXT(COUNTIFS($E$6:$E6,$E6,$C$6:$C6,$C6),"000")) -> PO-20260412-001 | C6: 0761 | D6: =IFERROR(INDEX(定数マスタ!$C$6:$C$105,MATCH($C6,定数マスタ!$B$6:$B$105,0)),"") -> 新宿 | E6: 46124 | F6: 1812000012957 | G6: =IFERROR(INDEX(商品マスタ!$C$6:$C$1005,MATCH($F6,商品マスタ!$B$6:$B$1005,0)),"") -> 新 シネマイク蓋 | H6: =IFERROR(INDEX(商品マスタ!$E$6:$E$1005,MATCH($F6,商品マスタ!$B$6:$B$1005,0)),"") -> オザックス株式会社 | I6: =IFERROR(INDEX(商品マスタ!$F$6:$F$1005,MATCH($F6,商品マスタ!$B$6:$B$1005,0)),"") -> 1200 | J6: =IF(OR($F6="",$C6<>'設定（最初に1回）'!$C$4),"",IFERROR(INDEX(発注計算!$Y$6:$Y$405,MATCH($F6,発注計算!$C$6:$C$405,0)),"")) -> 0 | K6: 8 | L6: =IF($K6="","",N($K6)*N($I6)) -> 9600 | M6: =IFERROR(INDEX(商品マスタ!$G$6:$G$1005,MATCH($F6,商品マスタ!$B$6:$B$1005,0)),"") -> 5.63 | N6: =IF($K6="","",N($K6)*N($M6)) -> 45.04 | O6: =IFERROR(INDEX(商品マスタ!$H$6:$H$1005,MATCH($F6,商品マスタ!$B$6:$B$1005,0)),"") -> 5 | P6: =IF(OR($E6="",$O6=""),"",WORKDAY($E6,$O6)) -> 46129 | Q6: 入荷済み | R6: 46127 | S6: =IF($Q6="入荷済み",N($L6),0) -> 9600 | T6: 田中 | U6: 公開週の追加発注
B7: =IF(OR($E7="",$F7=""),"","PO-"&TEXT($E7,"yyyymmdd")&"-"&TEXT(COUNTIFS($E$6:$E7,$E7,$C$6:$C7,$C7),"000")) -> PO-20260323-001 | C7: 0301 | D7: =IFERROR(INDEX(定数マスタ!$C$6:$C$105,MATCH($C7,定数マスタ!$B$6:$B$105,0)),"") -> 中央シネマ | E7: 46104 | F7: 1812000011271 | G7: =IFERROR(INDEX(商品マスタ!$C$6:$C$1005,MATCH($F7,商品マスタ!$B$6:$B$1005,0)),"") -> サッポロポテトバーベＱシーズニン | H7: =IFERROR(INDEX(商品マスタ!$E$6:$E$1005,MATCH($F7,商品マスタ!$B$6:$B$1005,0)),"") -> オザックス株式会社 | I7: =IFERROR(INDEX(商品マスタ!$F$6:$F$1005,MATCH($F7,商品マスタ!$B$6:$B$1005,0)),"") -> 1 | J7: =IF(OR($F7="",$C7<>'設定（最初に1回）'!$C$4),"",IFERROR(INDEX(発注計算!$Y$6:$Y$405,MATCH($F7,発注計算!$C$6:$C$405,0)),"")) | K7: 3 | L7: =IF($K7="","",N($K7)*N($I7)) -> 3 | M7: =IFERROR(INDEX(商品マスタ!$G$6:$G$1005,MATCH($F7,商品マスタ!$B$6:$B$1005,0)),"") -> 1396 | N7: =IF($K7="","",N($K7)*N($M7)) -> 4188 | O7: =IFERROR(INDEX(商品マスタ!$H$6:$H$1005,MATCH($F7,商品マスタ!$B$6:$B$1005,0)),"") -> 2 | P7: =IF(OR($E7="",$O7=""),"",WORKDAY($E7,$O7)) -> 46106 | Q7: 入荷済み | R7: 46107 | S7: =IF($Q7="入荷済み",N($L7),0) -> 3 | T7: 笹川 | U7: 定期発注
B8: =IF(OR($E8="",$F8=""),"","PO-"&TEXT($E8,"yyyymmdd")&"-"&TEXT(COUNTIFS($E$6:$E8,$E8,$C$6:$C8,$C8),"000")) -> PO-20260423-001 | C8: 0902 | D8: =IFERROR(INDEX(定数マスタ!$C$6:$C$105,MATCH($C8,定数マスタ!$B$6:$B$105,0)),"") -> 郊外シネマ | E8: 46135 | F8: 1812000009865 | G8: =IFERROR(INDEX(商品マスタ!$C$6:$C$1005,MATCH($F8,商品マスタ!$B$6:$B$1005,0)),"") -> カラーシュガー グリーン | H8: =IFERROR(INDEX(商品マスタ!$E$6:$E$1005,MATCH($F8,商品マスタ!$B$6:$B$1005,0)),"") -> オザックス株式会社 | I8: =IFERROR(INDEX(商品マスタ!$F$6:$F$1005,MATCH($F8,商品マスタ!$B$6:$B$1005,0)),"") -> 1 | J8: =IF(OR($F8="",$C8<>'設定（最初に1回）'!$C$4),"",IFERROR(INDEX(発注計算!$Y$6:$Y$405,MATCH($F8,発注計算!$C$6:$C$405,0)),"")) | K8: 3 | L8: =IF($K8="","",N($K8)*N($I8)) -> 3 | M8: =IFERROR(INDEX(商品マスタ!$G$6:$G$1005,MATCH($F8,商品マスタ!$B$6:$B$1005,0)),"") -> 1181 | N8: =IF($K8="","",N($K8)*N($M8)) -> 3543 | O8: =IFERROR(INDEX(商品マスタ!$H$6:$H$1005,MATCH($F8,商品マスタ!$B$6:$B$1005,0)),"") -> 7 | P8: =IF(OR($E8="",$O8=""),"",WORKDAY($E8,$O8)) -> 46146 | Q8: 入荷済み | R8: 46138 | S8: =IF($Q8="入荷済み",N($L8),0) -> 3 | T8: 笹川 | U8: 定期発注
B9: =IF(OR($E9="",$F9=""),"","PO-"&TEXT($E9,"yyyymmdd")&"-"&TEXT(COUNTIFS($E$6:$E9,$E9,$C$6:$C9,$C9),"000")) -> PO-20260407-001 | C9: 0761 | D9: =IFERROR(INDEX(定数マスタ!$C$6:$C$105,MATCH($C9,定数マスタ!$B$6:$B$105,0)),"") -> 新宿 | E9: 46119 | F9: 1812000009292 | G9: =IFERROR(INDEX(商品マスタ!$C$6:$C$1005,MATCH($F9,商品マスタ!$B$6:$B$1005,0)),"") -> ＪＳＵバターフレーバーオイル | H9: =IFERROR(INDEX(商品マスタ!$E$6:$E$1005,MATCH($F9,商品マスタ!$B$6:$B$1005,0)),"") -> オザックス株式会社 | I9: =IFERROR(INDEX(商品マスタ!$F$6:$F$1005,MATCH($F9,商品マスタ!$B$6:$B$1005,0)),"") -> 6 | J9: =IF(OR($F9="",$C9<>'設定（最初に1回）'!$C$4),"",IFERROR(INDEX(発注計算!$Y$6:$Y$405,MATCH($F9,発注計算!$C$6:$C$405,0)),"")) -> 0 | K9: 2 | L9: =IF($K9="","",N($K9)*N($I9)) -> 12 | M9: =IFERROR(INDEX(商品マスタ!$G$6:$G$1005,MATCH($F9,商品マスタ!$B$6:$B$1005,0)),"") -> 786 | N9: =IF($K9="","",N($K9)*N($M9)) -> 1572 | O9: =IFERROR(INDEX(商品マスタ!$H$6:$H$1005,MATCH($F9,商品マスタ!$B$6:$B$1005,0)),"") -> 7 | P9: =IF(OR($E9="",$O9=""),"",WORKDAY($E9,$O9)) -> 46128 | Q9: 入荷済み | R9: 46122 | S9: =IF($Q9="入荷済み",N($L9),0) -> 12 | T9: 笹川 | U9: 公開週の追加発注
B10: =IF(OR($E10="",$F10=""),"","PO-"&TEXT($E10,"yyyymmdd")&"-"&TEXT(COUNTIFS($E$6:$E10,$E10,$C$6:$C10,$C10),"000")) -> PO-20260420-001 | C10: 0301 | D10: =IFERROR(INDEX(定数マスタ!$C$6:$C$105,MATCH($C10,定数マスタ!$B$6:$B$105,0)),"") -> 中央シネマ | E10: 46132 | F10: 1812000011868 | G10: =IFERROR(INDEX(商品マスタ!$C$6:$C$1005,MATCH($F10,商品マスタ!$B$6:$B$1005,0)),"") -> ＴＨ スパイシーハラペー オリ | H10: =IFERROR(INDEX(商品マスタ!$E$6:$E$1005,MATCH($F10,商品マスタ!$B$6:$B$1005,0)),"") -> オザックス株式会社 | I10: =IFERROR(INDEX(商品マスタ!$F$6:$F$1005,MATCH($F10,商品マスタ!$B$6:$B$1005,0)),"") -> 96 | J10: =IF(OR($F10="",$C10<>'設定（最初に1回）'!$C$4),"",IFERROR(INDEX(発注計算!$Y$6:$Y$405,MATCH($F10,発注計算!$C$6:$C$405,0)),"")) | K10: 3 | L10: =IF($K10="","",N($K10)*N($I10)) -> 288 | M10: =IFERROR(INDEX(商品マスタ!$G$6:$G$1005,MATCH($F10,商品マスタ!$B$6:$B$1005,0)),"") -> 239 | N10: =IF($K10="","",N($K10)*N($M10)) -> 717 | O10: =IFERROR(INDEX(商品マスタ!$H$6:$H$1005,MATCH($F10,商品マスタ!$B$6:$B$1005,0)),"") -> 3 | P10: =IF(OR($E10="",$O10=""),"",WORKDAY($E10,$O10)) -> 46135 | Q10: 入荷済み | R10: 46135 | S10: =IF($Q10="入荷済み",N($L10),0) -> 288 | T10: 笹川 | U10: 定期発注
B11: =IF(OR($E11="",$F11=""),"","PO-"&TEXT($E11,"yyyymmdd")&"-"&TEXT(COUNTIFS($E$6:$E11,$E11,$C$6:$C11,$C11),"000")) -> PO-20260419-001 | C11: 0902 | D11: =IFERROR(INDEX(定数マスタ!$C$6:$C$105,MATCH($C11,定数マスタ!$B$6:$B$105,0)),"") -> 郊外シネマ | E11: 46131 | F11: 1812000013503 | G11: =IFERROR(INDEX(商品マスタ!$C$6:$C$1005,MATCH($F11,商品マスタ!$B$6:$B$1005,0)),"") -> カラーシュガーレッドストロベリー | H11: =IFERROR(INDEX(商品マスタ!$E$6:$E$1005,MATCH($F11,商品マスタ!$B$6:$B$1005,0)),"") -> オザックス株式会社 | I11: =IFERROR(INDEX(商品マスタ!$F$6:$F$1005,MATCH($F11,商品マスタ!$B$6:$B$1005,0)),"") -> 1 | J11: =IF(OR($F11="",$C11<>'設定（最初に1回）'!$C$4),"",IFERROR(INDEX(発注計算!$Y$6:$Y$405,MATCH($F11,発注計算!$C$6:$C$405,0)),"")) | K11: 5 | L11: =IF($K11="","",N($K11)*N($I11)) -> 5 | M11: =IFERROR(INDEX(商品マスタ!$G$6:$G$1005,MATCH($F11,商品マスタ!$B$6:$B$1005,0)),"") -> 1181 | N11: =IF($K11="","",N($K11)*N($M11)) -> 5905 | O11: =IFERROR(INDEX(商品マスタ!$H$6:$H$1005,MATCH($F11,商品マスタ!$B$6:$B$1005,0)),"") -> 3 | P11: =IF(OR($E11="",$O11=""),"",WORKDAY($E11,$O11)) -> 46134 | Q11: 入荷済み | R11: 46134 | S11: =IF($Q11="入荷済み",N($L11),0) -> 5 | T11: 田中 | U11: 定期発注
B12: =IF(OR($E12="",$F12=""),"","PO-"&TEXT($E12,"yyyymmdd")&"-"&TEXT(COUNTIFS($E$6:$E12,$E12,$C$6:$C12,$C12),"000")) -> PO-20260423-001 | C12: 0761 | D12: =IFERROR(INDEX(定数マスタ!$C$6:$C$105,MATCH($C12,定数マスタ!$B$6:$B$105,0)),"") -> 新宿 | E12: 46135 | F12: 1814000006394 | G12: =IFERROR(INDEX(商品マスタ!$C$6:$C$1005,MATCH($F12,商品マスタ!$B$6:$B$1005,0)),"") -> ＴＨ（ＦＣ）スナックじゃが容器 | H12: =IFERROR(INDEX(商品マスタ!$E$6:$E$1005,MATCH($F12,商品マスタ!$B$6:$B$1005,0)),"") -> オザックス株式会社 | I12: =IFERROR(INDEX(商品マスタ!$F$6:$F$1005,MATCH($F12,商品マスタ!$B$6:$B$1005,0)),"") -> 450 | J12: =IF(OR($F12="",$C12<>'設定（最初に1回）'!$C$4),"",IFERROR(INDEX(発注計算!$Y$6:$Y$405,MATCH($F12,発注計算!$C$6:$C$405,0)),"")) -> 7 | K12: 3 | L12: =IF($K12="","",N($K12)*N($I12)) -> 1350 | M12: =IFERROR(INDEX(商品マスタ!$G$6:$G$1005,MATCH($F12,商品マスタ!$B$6:$B$1005,0)),"") -> 15.46 | N12: =IF($K12="","",N($K12)*N($M12)) -> 46.38 | O12: =IFERROR(INDEX(商品マスタ!$H$6:$H$1005,MATCH($F12,商品マスタ!$B$6:$B$1005,0)),"") -> 3 | P12: =IF(OR($E12="",$O12=""),"",WORKDAY($E12,$O12)) -> 46140 | Q12: 入荷済み | R12: 46138 | S12: =IF($Q12="入荷済み",N($L12),0) -> 1350 | T12: 田中 | U12: 公開週の追加発注
B13: =IF(OR($E13="",$F13=""),"","PO-"&TEXT($E13,"yyyymmdd")&"-"&TEXT(COUNTIFS($E$6:$E13,$E13,$C$6:$C13,$C13),"000")) -> PO-20260331-001 | C13: 0301 | D13: =IFERROR(INDEX(定数マスタ!$C$6:$C$105,MATCH($C13,定数マスタ!$B$6:$B$105,0)),"") -> 中央シネマ | E13: 46112 | F13: 1812000013190 | G13: =IFERROR(INDEX(商品マスタ!$C$6:$C$1005,MATCH($F13,商品マスタ!$B$6:$B$1005,0)),"") -> 銀魂 ショッパー 仕入 | H13: =IFERROR(INDEX(商品マスタ!$E$6:$E$1005,MATCH($F13,商品マスタ!$B$6:$B$1005,0)),"") -> 松竹株式会社（コンセ） | I13: =IFERROR(INDEX(商品マスタ!$F$6:$F$1005,MATCH($F13,商品マスタ!$B$6:$B$1005,0)),"") -> 20 | J13: =IF(OR($F13="",$C13<>'設定（最初に1回）'!$C$4),"",IFERROR(INDEX(発注計算!$Y$6:$Y$405,MATCH($F13,発注計算!$C$6:$C$405,0)),"")) | K13: 8 | L13: =IF($K13="","",N($K13)*N($I13)) -> 160 | M13: =IFERROR(INDEX(商品マスタ!$G$6:$G$1005,MATCH($F13,商品マスタ!$B$6:$B$1005,0)),"") -> 591 | N13: =IF($K13="","",N($K13)*N($M13)) -> 4728 | O13: =IFERROR(INDEX(商品マスタ!$H$6:$H$1005,MATCH($F13,商品マスタ!$B$6:$B$1005,0)),"") -> 5 | P13: =IF(OR($E13="",$O13=""),"",WORKDAY($E13,$O13)) -> 46119 | Q13: 入荷済み | R13: 46115 | S13: =IF($Q13="入荷済み",N($L13),0) -> 160 | T13: 田中 | U13: 定期発注
B14: =IF(OR($E14="",$F14=""),"","PO-"&TEXT($E14,"yyyymmdd")&"-"&TEXT(COUNTIFS($E$6:$E14,$E14,$C$6:$C14,$C14),"000")) -> PO-20260429-001 | C14: 0902 | D14: =IFERROR(INDEX(定数マスタ!$C$6:$C$105,MATCH($C14,定数マスタ!$B$6:$B$105,0)),"") -> 郊外シネマ | E14: 46141 | F14: 1814000006424 | G14: =IFERROR(INDEX(商品マスタ!$C$6:$C$1005,MATCH($F14,商品マスタ!$B$6:$B$1005,0)),"") -> ＴＨ（ＦＳ）Ｐポップコーン袋 | H14: =IFERROR(INDEX(商品マスタ!$E$6:$E$1005,MATCH($F14,商品マスタ!$B$6:$B$1005,0)),"") -> オザックス株式会社 | I14: =IFERROR(INDEX(商品マスタ!$F$6:$F$1005,MATCH($F14,商品マスタ!$B$6:$B$1005,0)),"") -> 500 | J14: =IF(OR($F14="",$C14<>'設定（最初に1回）'!$C$4),"",IFERROR(INDEX(発注計算!$Y$6:$Y$405,MATCH($F14,発注計算!$C$6:$C$405,0)),"")) | K14: 6 | L14: =IF($K14="","",N($K14)*N($I14)) -> 3000 | M14: =IFERROR(INDEX(商品マスタ!$G$6:$G$1005,MATCH($F14,商品マスタ!$B$6:$B$1005,0)),"") -> 15.6 | N14: =IF($K14="","",N($K14)*N($M14)) -> 93.6 | O14: =IFERROR(INDEX(商品マスタ!$H$6:$H$1005,MATCH($F14,商品マスタ!$B$6:$B$1005,0)),"") -> 3 | P14: =IF(OR($E14="",$O14=""),"",WORKDAY($E14,$O14)) -> 46146 | Q14: 発注済 | S14: =IF($Q14="入荷済み",N($L14),0) -> 0 | T14: 笹川 | U14: 定期発注
B15: =IF(OR($E15="",$F15=""),"","PO-"&TEXT($E15,"yyyymmdd")&"-"&TEXT(COUNTIFS($E$6:$E15,$E15,$C$6:$C15,$C15),"000")) -> PO-20260427-001 | C15: 0761 | D15: =IFERROR(INDEX(定数マスタ!$C$6:$C$105,MATCH($C15,定数マスタ!$B$6:$B$105,0)),"") -> 新宿 | E15: 46139 | F15: 1812000012391 | G15: =IFERROR(INDEX(商品マスタ!$C$6:$C$1005,MATCH($F15,商品マスタ!$B$6:$B$1005,0)),"") -> シネマイク ブラックＰ味シーズニ | H15: =IFERROR(INDEX(商品マスタ!$E$6:$E$1005,MATCH($F15,商品マスタ!$B$6:$B$1005,0)),"") -> オザックス株式会社 | I15: =IFERROR(INDEX(商品マスタ!$F$6:$F$1005,MATCH($F15,商品マスタ!$B$6:$B$1005,0)),"") -> 1 | J15: =IF(OR($F15="",$C15<>'設定（最初に1回）'!$C$4),"",IFERROR(INDEX(発注計算!$Y$6:$Y$405,MATCH($F15,発注計算!$C$6:$C$405,0)),"")) -> 0 | K15: 12 | L15: =IF($K15="","",N($K15)*N($I15)) -> 12 | M15: =IFERROR(INDEX(商品マスタ!$G$6:$G$1005,MATCH($F15,商品マスタ!$B$6:$B$1005,0)),"") -> 955 | N15: =IF($K15="","",N($K15)*N($M15)) -> 11460 | O15: =IFERROR(INDEX(商品マスタ!$H$6:$H$1005,MATCH($F15,商品マスタ!$B$6:$B$1005,0)),"") -> 5 | P15: =IF(OR($E15="",$O15=""),"",WORKDAY($E15,$O15)) -> 46146 | Q15: 発注済 | S15: =IF($Q15="入荷済み",N($L15),0) -> 0 | T15: 田中 | U15: 公開週の追加発注
B16: =IF(OR($E16="",$F16=""),"","PO-"&TEXT($E16,"yyyymmdd")&"-"&TEXT(COUNTIFS($E$6:$E16,$E16,$C$6:$C16,$C16),"000")) -> PO-20260429-001 | C16: 0301 | D16: =IFERROR(INDEX(定数マスタ!$C$6:$C$105,MATCH($C16,定数マスタ!$B$6:$B$105,0)),"") -> 中央シネマ | E16: 46141 | F16: 1812000011936 | G16: =IFERROR(INDEX(商品マスタ!$C$6:$C$1005,MATCH($F16,商品マスタ!$B$6:$B$1005,0)),"") -> 新パーティーポップ袋 | H16: =IFERROR(INDEX(商品マスタ!$E$6:$E$1005,MATCH($F16,商品マスタ!$B$6:$B$1005,0)),"") -> オザックス株式会社 | I16: =IFERROR(INDEX(商品マスタ!$F$6:$F$1005,MATCH($F16,商品マスタ!$B$6:$B$1005,0)),"") -> 400 | J16: =IF(OR($F16="",$C16<>'設定（最初に1回）'!$C$4),"",IFERROR(INDEX(発注計算!$Y$6:$Y$405,MATCH($F16,発注計算!$C$6:$C$405,0)),"")) | K16: 4 | L16: =IF($K16="","",N($K16)*N($I16)) -> 1600 | M16: =IFERROR(INDEX(商品マスタ!$G$6:$G$1005,MATCH($F16,商品マスタ!$B$6:$B$1005,0)),"") -> 52.02 | N16: =IF($K16="","",N($K16)*N($M16)) -> 208.08 | O16: =IFERROR(INDEX(商品マスタ!$H$6:$H$1005,MATCH($F16,商品マスタ!$B$6:$B$1005,0)),"") -> 3 | P16: =IF(OR($E16="",$O16=""),"",WORKDAY($E16,$O16)) -> 46146 | Q16: 発注済 | S16: =IF($Q16="入荷済み",N($L16),0) -> 0 | T16: 田中 | U16: 定期発注
B17: =IF(OR($E17="",$F17=""),"","PO-"&TEXT($E17,"yyyymmdd")&"-"&TEXT(COUNTIFS($E$6:$E17,$E17,$C$6:$C17,$C17),"000")) -> PO-20260427-001 | C17: 0902 | D17: =IFERROR(INDEX(定数マスタ!$C$6:$C$105,MATCH($C17,定数マスタ!$B$6:$B$105,0)),"") -> 郊外シネマ | E17: 46139 | F17: 1814000004581 | G17: =IFERROR(INDEX(商品マスタ!$C$6:$C$1005,MATCH($F17,商品マスタ!$B$6:$B$1005,0)),"") -> 新ＦドリンクカップＢＩＰ５１２Ｄ | H17: =IFERROR(INDEX(商品マスタ!$E$6:$E$1005,MATCH($F17,商品マスタ!$B$6:$B$1005,0)),"") -> オザックス株式会社 | I17: =IFERROR(INDEX(商品マスタ!$F$6:$F$1005,MATCH($F17,商品マスタ!$B$6:$B$1005,0)),"") -> 1000 | J17: =IF(OR($F17="",$C17<>'設定（最初に1回）'!$C$4),"",IFERROR(INDEX(発注計算!$Y$6:$Y$405,MATCH($F17,発注計算!$C$6:$C$405,0)),"")) | K17: 8 | L17: =IF($K17="","",N($K17)*N($I17)) -> 8000 | M17: =IFERROR(INDEX(商品マスタ!$G$6:$G$1005,MATCH($F17,商品マスタ!$B$6:$B$1005,0)),"") -> 8.73 | N17: =IF($K17="","",N($K17)*N($M17)) -> 69.84 | O17: =IFERROR(INDEX(商品マスタ!$H$6:$H$1005,MATCH($F17,商品マスタ!$B$6:$B$1005,0)),"") -> 2 | P17: =IF(OR($E17="",$O17=""),"",WORKDAY($E17,$O17)) -> 46141 | Q17: 発注済 | S17: =IF($Q17="入荷済み",N($L17),0) -> 0 | T17: 田中 | U17: 定期発注
B18: =IF(OR($E18="",$F18=""),"","PO-"&TEXT($E18,"yyyymmdd")&"-"&TEXT(COUNTIFS($E$6:$E18,$E18,$C$6:$C18,$C18),"000")) -> PO-20260430-001 | C18: 0761 | D18: =IFERROR(INDEX(定数マスタ!$C$6:$C$105,MATCH($C18,定数マスタ!$B$6:$B$105,0)),"") -> 新宿 | E18: 46142 | F18: 1812000011684 | G18: =IFERROR(INDEX(商品マスタ!$C$6:$C$1005,MATCH($F18,商品マスタ!$B$6:$B$1005,0)),"") -> 超マンゴー＆パッションフローズン | H18: =IFERROR(INDEX(商品マスタ!$E$6:$E$1005,MATCH($F18,商品マスタ!$B$6:$B$1005,0)),"") -> オザックス株式会社 | I18: =IFERROR(INDEX(商品マスタ!$F$6:$F$1005,MATCH($F18,商品マスタ!$B$6:$B$1005,0)),"") -> 80 | J18: =IF(OR($F18="",$C18<>'設定（最初に1回）'!$C$4),"",IFERROR(INDEX(発注計算!$Y$6:$Y$405,MATCH($F18,発注計算!$C$6:$C$405,0)),"")) -> 0 | K18: 8 | L18: =IF($K18="","",N($K18)*N($I18)) -> 640 | M18: =IFERROR(INDEX(商品マスタ!$G$6:$G$1005,MATCH($F18,商品マスタ!$B$6:$B$1005,0)),"") -> 203 | N18: =IF($K18="","",N($K18)*N($M18)) -> 1624 | O18: =IFERROR(INDEX(商品マスタ!$H$6:$H$1005,MATCH($F18,商品マスタ!$B$6:$B$1005,0)),"") -> 2 | P18: =IF(OR($E18="",$O18=""),"",WORKDAY($E18,$O18)) -> 46146 | Q18: 発注済 | S18: =IF($Q18="入荷済み",N($L18),0) -> 0 | T18: 佐藤 | U18: 公開週の追加発注
B19: =IF(OR($E19="",$F19=""),"","PO-"&TEXT($E19,"yyyymmdd")&"-"&TEXT(COUNTIFS($E$6:$E19,$E19,$C$6:$C19,$C19),"000")) -> PO-20260430-001 | C19: 0301 | D19: =IFERROR(INDEX(定数マスタ!$C$6:$C$105,MATCH($C19,定数マスタ!$B$6:$B$105,0)),"") -> 中央シネマ | E19: 46142 | F19: 1812000013329 | G19: =IFERROR(INDEX(商品マスタ!$C$6:$C$1005,MATCH($F19,商品マスタ!$B$6:$B$1005,0)),"") -> ビーバー トッパー 仕入 | H19: =IFERROR(INDEX(商品マスタ!$E$6:$E$1005,MATCH($F19,商品マスタ!$B$6:$B$1005,0)),"") -> オザックス株式会社 | I19: =IFERROR(INDEX(商品マスタ!$F$6:$F$1005,MATCH($F19,商品マスタ!$B$6:$B$1005,0)),"") -> 50 | J19: =IF(OR($F19="",$C19<>'設定（最初に1回）'!$C$4),"",IFERROR(INDEX(発注計算!$Y$6:$Y$405,MATCH($F19,発注計算!$C$6:$C$405,0)),"")) | K19: 8 | L19: =IF($K19="","",N($K19)*N($I19)) -> 400 | M19: =IFERROR(INDEX(商品マスタ!$G$6:$G$1005,MATCH($F19,商品マスタ!$B$6:$B$1005,0)),"") -> 393 | N19: =IF($K19="","",N($K19)*N($M19)) -> 3144 | O19: =IFERROR(INDEX(商品マスタ!$H$6:$H$1005,MATCH($F19,商品マスタ!$B$6:$B$1005,0)),"") -> 3 | P19: =IF(OR($E19="",$O19=""),"",WORKDAY($E19,$O19)) -> 46147 | Q19: 発注済 | S19: =IF($Q19="入荷済み",N($L19),0) -> 0 | T19: 笹川 | U19: 定期発注
B20: =IF(OR($E20="",$F20=""),"","PO-"&TEXT($E20,"yyyymmdd")&"-"&TEXT(COUNTIFS($E$6:$E20,$E20,$C$6:$C20,$C20),"000")) | D20: =IFERROR(INDEX(定数マスタ!$C$6:$C$105,MATCH($C20,定数マスタ!$B$6:$B$105,0)),"") | G20: =IFERROR(INDEX(商品マスタ!$C$6:$C$1005,MATCH($F20,商品マスタ!$B$6:$B$1005,0)),"") | H20: =IFERROR(INDEX(商品マスタ!$E$6:$E$1005,MATCH($F20,商品マスタ!$B$6:$B$1005,0)),"") | I20: =IFERROR(INDEX(商品マスタ!$F$6:$F$1005,MATCH($F20,商品マスタ!$B$6:$B$1005,0)),"") | J20: =IF(OR($F20="",$C20<>'設定（最初に1回）'!$C$4),"",IFERROR(INDEX(発注計算!$Y$6:$Y$405,MATCH($F20,発注計算!$C$6:$C$405,0)),"")) | L20: =IF($K20="","",N($K20)*N($I20)) | M20: =IFERROR(INDEX(商品マスタ!$G$6:$G$1005,MATCH($F20,商品マスタ!$B$6:$B$1005,0)),"") | N20: =IF($K20="","",N($K20)*N($M20)) | O20: =IFERROR(INDEX(商品マスタ!$H$6:$H$1005,MATCH($F20,商品マスタ!$B$6:$B$1005,0)),"") | P20: =IF(OR($E20="",$O20=""),"",WORKDAY($E20,$O20)) | S20: =IF($Q20="入荷済み",N($L20),0) -> 0
B21: =IF(OR($E21="",$F21=""),"","PO-"&TEXT($E21,"yyyymmdd")&"-"&TEXT(COUNTIFS($E$6:$E21,$E21,$C$6:$C21,$C21),"000")) | D21: =IFERROR(INDEX(定数マスタ!$C$6:$C$105,MATCH($C21,定数マスタ!$B$6:$B$105,0)),"") | G21: =IFERROR(INDEX(商品マスタ!$C$6:$C$1005,MATCH($F21,商品マスタ!$B$6:$B$1005,0)),"") | H21: =IFERROR(INDEX(商品マスタ!$E$6:$E$1005,MATCH($F21,商品マスタ!$B$6:$B$1005,0)),"") | I21: =IFERROR(INDEX(商品マスタ!$F$6:$F$1005,MATCH($F21,商品マスタ!$B$6:$B$1005,0)),"") | J21: =IF(OR($F21="",$C21<>'設定（最初に1回）'!$C$4),"",IFERROR(INDEX(発注計算!$Y$6:$Y$405,MATCH($F21,発注計算!$C$6:$C$405,0)),"")) | L21: =IF($K21="","",N($K21)*N($I21)) | M21: =IFERROR(INDEX(商品マスタ!$G$6:$G$1005,MATCH($F21,商品マスタ!$B$6:$B$1005,0)),"") | N21: =IF($K21="","",N($K21)*N($M21)) | O21: =IFERROR(INDEX(商品マスタ!$H$6:$H$1005,MATCH($F21,商品マスタ!$B$6:$B$1005,0)),"") | P21: =IF(OR($E21="",$O21=""),"",WORKDAY($E21,$O21)) | S21: =IF($Q21="入荷済み",N($L21),0) -> 0
B22: =IF(OR($E22="",$F22=""),"","PO-"&TEXT($E22,"yyyymmdd")&"-"&TEXT(COUNTIFS($E$6:$E22,$E22,$C$6:$C22,$C22),"000")) | D22: =IFERROR(INDEX(定数マスタ!$C$6:$C$105,MATCH($C22,定数マスタ!$B$6:$B$105,0)),"") | G22: =IFERROR(INDEX(商品マスタ!$C$6:$C$1005,MATCH($F22,商品マスタ!$B$6:$B$1005,0)),"") | H22: =IFERROR(INDEX(商品マスタ!$E$6:$E$1005,MATCH($F22,商品マスタ!$B$6:$B$1005,0)),"") | I22: =IFERROR(INDEX(商品マスタ!$F$6:$F$1005,MATCH($F22,商品マスタ!$B$6:$B$1005,0)),"") | J22: =IF(OR($F22="",$C22<>'設定（最初に1回）'!$C$4),"",IFERROR(INDEX(発注計算!$Y$6:$Y$405,MATCH($F22,発注計算!$C$6:$C$405,0)),"")) | L22: =IF($K22="","",N($K22)*N($I22)) | M22: =IFERROR(INDEX(商品マスタ!$G$6:$G$1005,MATCH($F22,商品マスタ!$B$6:$B$1005,0)),"") | N22: =IF($K22="","",N($K22)*N($M22)) | O22: =IFERROR(INDEX(商品マスタ!$H$6:$H$1005,MATCH($F22,商品マスタ!$B$6:$B$1005,0)),"") | P22: =IF(OR($E22="",$O22=""),"",WORKDAY($E22,$O22)) | S22: =IF($Q22="入荷済み",N($L22),0) -> 0
B23: =IF(OR($E23="",$F23=""),"","PO-"&TEXT($E23,"yyyymmdd")&"-"&TEXT(COUNTIFS($E$6:$E23,$E23,$C$6:$C23,$C23),"000")) | D23: =IFERROR(INDEX(定数マスタ!$C$6:$C$105,MATCH($C23,定数マスタ!$B$6:$B$105,0)),"") | G23: =IFERROR(INDEX(商品マスタ!$C$6:$C$1005,MATCH($F23,商品マスタ!$B$6:$B$1005,0)),"") | H23: =IFERROR(INDEX(商品マスタ!$E$6:$E$1005,MATCH($F23,商品マスタ!$B$6:$B$1005,0)),"") | I23: =IFERROR(INDEX(商品マスタ!$F$6:$F$1005,MATCH($F23,商品マスタ!$B$6:$B$1005,0)),"") | J23: =IF(OR($F23="",$C23<>'設定（最初に1回）'!$C$4),"",IFERROR(INDEX(発注計算!$Y$6:$Y$405,MATCH($F23,発注計算!$C$6:$C$405,0)),"")) | L23: =IF($K23="","",N($K23)*N($I23)) | M23: =IFERROR(INDEX(商品マスタ!$G$6:$G$1005,MATCH($F23,商品マスタ!$B$6:$B$1005,0)),"") | N23: =IF($K23="","",N($K23)*N($M23)) | O23: =IFERROR(INDEX(商品マスタ!$H$6:$H$1005,MATCH($F23,商品マスタ!$B$6:$B$1005,0)),"") | P23: =IF(OR($E23="",$O23=""),"",WORKDAY($E23,$O23)) | S23: =IF($Q23="入荷済み",N($L23),0) -> 0
B24: =IF(OR($E24="",$F24=""),"","PO-"&TEXT($E24,"yyyymmdd")&"-"&TEXT(COUNTIFS($E$6:$E24,$E24,$C$6:$C24,$C24),"000")) | D24: =IFERROR(INDEX(定数マスタ!$C$6:$C$105,MATCH($C24,定数マスタ!$B$6:$B$105,0)),"") | G24: =IFERROR(INDEX(商品マスタ!$C$6:$C$1005,MATCH($F24,商品マスタ!$B$6:$B$1005,0)),"") | H24: =IFERROR(INDEX(商品マスタ!$E$6:$E$1005,MATCH($F24,商品マスタ!$B$6:$B$1005,0)),"") | I24: =IFERROR(INDEX(商品マスタ!$F$6:$F$1005,MATCH($F24,商品マスタ!$B$6:$B$1005,0)),"") | J24: =IF(OR($F24="",$C24<>'設定（最初に1回）'!$C$4),"",IFERROR(INDEX(発注計算!$Y$6:$Y$405,MATCH($F24,発注計算!$C$6:$C$405,0)),"")) | L24: =IF($K24="","",N($K24)*N($I24)) | M24: =IFERROR(INDEX(商品マスタ!$G$6:$G$1005,MATCH($F24,商品マスタ!$B$6:$B$1005,0)),"") | N24: =IF($K24="","",N($K24)*N($M24)) | O24: =IFERROR(INDEX(商品マスタ!$H$6:$H$1005,MATCH($F24,商品マスタ!$B$6:$B$1005,0)),"") | P24: =IF(OR($E24="",$O24=""),"",WORKDAY($E24,$O24)) | S24: =IF($Q24="入荷済み",N($L24),0) -> 0
B25: =IF(OR($E25="",$F25=""),"","PO-"&TEXT($E25,"yyyymmdd")&"-"&TEXT(COUNTIFS($E$6:$E25,$E25,$C$6:$C25,$C25),"000")) | D25: =IFERROR(INDEX(定数マスタ!$C$6:$C$105,MATCH($C25,定数マスタ!$B$6:$B$105,0)),"") | G25: =IFERROR(INDEX(商品マスタ!$C$6:$C$1005,MATCH($F25,商品マスタ!$B$6:$B$1005,0)),"") | H25: =IFERROR(INDEX(商品マスタ!$E$6:$E$1005,MATCH($F25,商品マスタ!$B$6:$B$1005,0)),"") | I25: =IFERROR(INDEX(商品マスタ!$F$6:$F$1005,MATCH($F25,商品マスタ!$B$6:$B$1005,0)),"") | J25: =IF(OR($F25="",$C25<>'設定（最初に1回）'!$C$4),"",IFERROR(INDEX(発注計算!$Y$6:$Y$405,MATCH($F25,発注計算!$C$6:$C$405,0)),"")) | L25: =IF($K25="","",N($K25)*N($I25)) | M25: =IFERROR(INDEX(商品マスタ!$G$6:$G$1005,MATCH($F25,商品マスタ!$B$6:$B$1005,0)),"") | N25: =IF($K25="","",N($K25)*N($M25)) | O25: =IFERROR(INDEX(商品マスタ!$H$6:$H$1005,MATCH($F25,商品マスタ!$B$6:$B$1005,0)),"") | P25: =IF(OR($E25="",$O25=""),"",WORKDAY($E25,$O25)) | S25: =IF($Q25="入荷済み",N($L25),0) -> 0
B26: =IF(OR($E26="",$F26=""),"","PO-"&TEXT($E26,"yyyymmdd")&"-"&TEXT(COUNTIFS($E$6:$E26,$E26,$C$6:$C26,$C26),"000")) | D26: =IFERROR(INDEX(定数マスタ!$C$6:$C$105,MATCH($C26,定数マスタ!$B$6:$B$105,0)),"") | G26: =IFERROR(INDEX(商品マスタ!$C$6:$C$1005,MATCH($F26,商品マスタ!$B$6:$B$1005,0)),"") | H26: =IFERROR(INDEX(商品マスタ!$E$6:$E$1005,MATCH($F26,商品マスタ!$B$6:$B$1005,0)),"") | I26: =IFERROR(INDEX(商品マスタ!$F$6:$F$1005,MATCH($F26,商品マスタ!$B$6:$B$1005,0)),"") | J26: =IF(OR($F26="",$C26<>'設定（最初に1回）'!$C$4),"",IFERROR(INDEX(発注計算!$Y$6:$Y$405,MATCH($F26,発注計算!$C$6:$C$405,0)),"")) | L26: =IF($K26="","",N($K26)*N($I26)) | M26: =IFERROR(INDEX(商品マスタ!$G$6:$G$1005,MATCH($F26,商品マスタ!$B$6:$B$1005,0)),"") | N26: =IF($K26="","",N($K26)*N($M26)) | O26: =IFERROR(INDEX(商品マスタ!$H$6:$H$1005,MATCH($F26,商品マスタ!$B$6:$B$1005,0)),"") | P26: =IF(OR($E26="",$O26=""),"",WORKDAY($E26,$O26)) | S26: =IF($Q26="入荷済み",N($L26),0) -> 0
B27: =IF(OR($E27="",$F27=""),"","PO-"&TEXT($E27,"yyyymmdd")&"-"&TEXT(COUNTIFS($E$6:$E27,$E27,$C$6:$C27,$C27),"000")) | D27: =IFERROR(INDEX(定数マスタ!$C$6:$C$105,MATCH($C27,定数マスタ!$B$6:$B$105,0)),"") | G27: =IFERROR(INDEX(商品マスタ!$C$6:$C$1005,MATCH($F27,商品マスタ!$B$6:$B$1005,0)),"") | H27: =IFERROR(INDEX(商品マスタ!$E$6:$E$1005,MATCH($F27,商品マスタ!$B$6:$B$1005,0)),"") | I27: =IFERROR(INDEX(商品マスタ!$F$6:$F$1005,MATCH($F27,商品マスタ!$B$6:$B$1005,0)),"") | J27: =IF(OR($F27="",$C27<>'設定（最初に1回）'!$C$4),"",IFERROR(INDEX(発注計算!$Y$6:$Y$405,MATCH($F27,発注計算!$C$6:$C$405,0)),"")) | L27: =IF($K27="","",N($K27)*N($I27)) | M27: =IFERROR(INDEX(商品マスタ!$G$6:$G$1005,MATCH($F27,商品マスタ!$B$6:$B$1005,0)),"") | N27: =IF($K27="","",N($K27)*N($M27)) | O27: =IFERROR(INDEX(商品マスタ!$H$6:$H$1005,MATCH($F27,商品マスタ!$B$6:$B$1005,0)),"") | P27: =IF(OR($E27="",$O27=""),"",WORKDAY($E27,$O27)) | S27: =IF($Q27="入荷済み",N($L27),0) -> 0
B28: =IF(OR($E28="",$F28=""),"","PO-"&TEXT($E28,"yyyymmdd")&"-"&TEXT(COUNTIFS($E$6:$E28,$E28,$C$6:$C28,$C28),"000")) | D28: =IFERROR(INDEX(定数マスタ!$C$6:$C$105,MATCH($C28,定数マスタ!$B$6:$B$105,0)),"") | G28: =IFERROR(INDEX(商品マスタ!$C$6:$C$1005,MATCH($F28,商品マスタ!$B$6:$B$1005,0)),"") | H28: =IFERROR(INDEX(商品マスタ!$E$6:$E$1005,MATCH($F28,商品マスタ!$B$6:$B$1005,0)),"") | I28: =IFERROR(INDEX(商品マスタ!$F$6:$F$1005,MATCH($F28,商品マスタ!$B$6:$B$1005,0)),"") | J28: =IF(OR($F28="",$C28<>'設定（最初に1回）'!$C$4),"",IFERROR(INDEX(発注計算!$Y$6:$Y$405,MATCH($F28,発注計算!$C$6:$C$405,0)),"")) | L28: =IF($K28="","",N($K28)*N($I28)) | M28: =IFERROR(INDEX(商品マスタ!$G$6:$G$1005,MATCH($F28,商品マスタ!$B$6:$B$1005,0)),"") | N28: =IF($K28="","",N($K28)*N($M28)) | O28: =IFERROR(INDEX(商品マスタ!$H$6:$H$1005,MATCH($F28,商品マスタ!$B$6:$B$1005,0)),"") | P28: =IF(OR($E28="",$O28=""),"",WORKDAY($E28,$O28)) | S28: =IF($Q28="入荷済み",N($L28),0) -> 0
B29: =IF(OR($E29="",$F29=""),"","PO-"&TEXT($E29,"yyyymmdd")&"-"&TEXT(COUNTIFS($E$6:$E29,$E29,$C$6:$C29,$C29),"000")) | D29: =IFERROR(INDEX(定数マスタ!$C$6:$C$105,MATCH($C29,定数マスタ!$B$6:$B$105,0)),"") | G29: =IFERROR(INDEX(商品マスタ!$C$6:$C$1005,MATCH($F29,商品マスタ!$B$6:$B$1005,0)),"") | H29: =IFERROR(INDEX(商品マスタ!$E$6:$E$1005,MATCH($F29,商品マスタ!$B$6:$B$1005,0)),"") | I29: =IFERROR(INDEX(商品マスタ!$F$6:$F$1005,MATCH($F29,商品マスタ!$B$6:$B$1005,0)),"") | J29: =IF(OR($F29="",$C29<>'設定（最初に1回）'!$C$4),"",IFERROR(INDEX(発注計算!$Y$6:$Y$405,MATCH($F29,発注計算!$C$6:$C$405,0)),"")) | L29: =IF($K29="","",N($K29)*N($I29)) | M29: =IFERROR(INDEX(商品マスタ!$G$6:$G$1005,MATCH($F29,商品マスタ!$B$6:$B$1005,0)),"") | N29: =IF($K29="","",N($K29)*N($M29)) | O29: =IFERROR(INDEX(商品マスタ!$H$6:$H$1005,MATCH($F29,商品マスタ!$B$6:$B$1005,0)),"") | P29: =IF(OR($E29="",$O29=""),"",WORKDAY($E29,$O29)) | S29: =IF($Q29="入荷済み",N($L29),0) -> 0
B30: =IF(OR($E30="",$F30=""),"","PO-"&TEXT($E30,"yyyymmdd")&"-"&TEXT(COUNTIFS($E$6:$E30,$E30,$C$6:$C30,$C30),"000")) | D30: =IFERROR(INDEX(定数マスタ!$C$6:$C$105,MATCH($C30,定数マスタ!$B$6:$B$105,0)),"") | G30: =IFERROR(INDEX(商品マスタ!$C$6:$C$1005,MATCH($F30,商品マスタ!$B$6:$B$1005,0)),"") | H30: =IFERROR(INDEX(商品マスタ!$E$6:$E$1005,MATCH($F30,商品マスタ!$B$6:$B$1005,0)),"") | I30: =IFERROR(INDEX(商品マスタ!$F$6:$F$1005,MATCH($F30,商品マスタ!$B$6:$B$1005,0)),"") | J30: =IF(OR($F30="",$C30<>'設定（最初に1回）'!$C$4),"",IFERROR(INDEX(発注計算!$Y$6:$Y$405,MATCH($F30,発注計算!$C$6:$C$405,0)),"")) | L30: =IF($K30="","",N($K30)*N($I30)) | M30: =IFERROR(INDEX(商品マスタ!$G$6:$G$1005,MATCH($F30,商品マスタ!$B$6:$B$1005,0)),"") | N30: =IF($K30="","",N($K30)*N($M30)) | O30: =IFERROR(INDEX(商品マスタ!$H$6:$H$1005,MATCH($F30,商品マスタ!$B$6:$B$1005,0)),"") | P30: =IF(OR($E30="",$O30=""),"",WORKDAY($E30,$O30)) | S30: =IF($Q30="入荷済み",N($L30),0) -> 0
B31: =IF(OR($E31="",$F31=""),"","PO-"&TEXT($E31,"yyyymmdd")&"-"&TEXT(COUNTIFS($E$6:$E31,$E31,$C$6:$C31,$C31),"000")) | D31: =IFERROR(INDEX(定数マスタ!$C$6:$C$105,MATCH($C31,定数マスタ!$B$6:$B$105,0)),"") | G31: =IFERROR(INDEX(商品マスタ!$C$6:$C$1005,MATCH($F31,商品マスタ!$B$6:$B$1005,0)),"") | H31: =IFERROR(INDEX(商品マスタ!$E$6:$E$1005,MATCH($F31,商品マスタ!$B$6:$B$1005,0)),"") | I31: =IFERROR(INDEX(商品マスタ!$F$6:$F$1005,MATCH($F31,商品マスタ!$B$6:$B$1005,0)),"") | J31: =IF(OR($F31="",$C31<>'設定（最初に1回）'!$C$4),"",IFERROR(INDEX(発注計算!$Y$6:$Y$405,MATCH($F31,発注計算!$C$6:$C$405,0)),"")) | L31: =IF($K31="","",N($K31)*N($I31)) | M31: =IFERROR(INDEX(商品マスタ!$G$6:$G$1005,MATCH($F31,商品マスタ!$B$6:$B$1005,0)),"") | N31: =IF($K31="","",N($K31)*N($M31)) | O31: =IFERROR(INDEX(商品マスタ!$H$6:$H$1005,MATCH($F31,商品マスタ!$B$6:$B$1005,0)),"") | P31: =IF(OR($E31="",$O31=""),"",WORKDAY($E31,$O31)) | S31: =IF($Q31="入荷済み",N($L31),0) -> 0
... B1005: =IF(OR($E1005="",$F1005=""),"","PO-"&TEXT($E1005,"yyyymmdd")&"-"&TEXT(COUNTIFS($E$6:$E1005,$E1005,$C$6:$C1005,$C1005),"000")) | D1005: =IFERROR(INDEX(定数マスタ!$C$6:$C$105,MATCH($C1005,定数マスタ!$B$6:$B$105,0)),"") | G1005: =IFERROR(INDEX(商品マスタ!$C$6:$C$1005,MATCH($F1005,商品マスタ!$B$6:$B$1005,0)),"") | H1005: =IFERROR(INDEX(商品マスタ!$E$6:$E$1005,MATCH($F1005,商品マスタ!$B$6:$B$1005,0)),"") | I1005: =IFERROR(INDEX(商品マスタ!$F$6:$F$1005,MATCH($F1005,商品マスタ!$B$6:$B$1005,0)),"") | J1005: =IF(OR($F1005="",$C1005<>'設定（最初に1回）'!$C$4),"",IFERROR(INDEX(発注計算!$Y$6:$Y$405,MATCH($F1005,発注計算!$C$6:$C$405,0)),"")) | L1005: =IF($K1005="","",N($K1005)*N($I1005)) | M1005: =IFERROR(INDEX(商品マスタ!$G$6:$G$1005,MATCH($F1005,商品マスタ!$B$6:$B$1005,0)),"") | N1005: =IF($K1005="","",N($K1005)*N($M1005)) | O1005: =IFERROR(INDEX(商品マスタ!$H$6:$H$1005,MATCH($F1005,商品マスタ!$B$6:$B$1005,0)),"") | P1005: =IF(OR($E1005="",$O1005=""),"",WORKDAY($E1005,$O1005)) | S1005: =IF($Q1005="入荷済み",N($L1005),0) -> 0

Sheet 商品マスタ
B2: 商品マスタ
B3: PI値は来場者100人あたりの消費数です。取り扱いのないプロファイルは空欄のままで構いません。
B4: 入力 | C4: 入力 | D4: 入力 | E4: 入力 | F4: 入力 | G4: 入力 | H4: 入力 | I4: 入力 | J4: 入力 | K4: 入力 | L4: 入力 | M4: 入力 | N4: 入力 | O4: 入力
B5: 商品コード | C5: 商品名 | D5: 商品分類名 | E5: 支払先名 | F5: 入数 | G5: 税抜単価 | H5: L/T日数 | I5: 最低ロット | J5: 発注単位 | K5: 保管区分 | L5: 発注グループ | M5: PI値 1杯売り | N5: PI値 ドリンクバー | O5: 備考
B6: 1812000008585 | C6: プレミアムモルツ ２０Ｌ | D6: アルコール | E6: 株式会社 カクヤス | F6: 1 | G6: 11300 | H6: 2 | I6: 1 | J6: ケース | K6: 冷蔵 | L6: その他常温 | M6: 1.1 | N6: 0
